Workbook
Name IQ_CH: 110000
Name IQ_CQ: 5000
Name IQ_CY: 10000
Name IQ_DAILY: 500000
Name IQ_FH: 100000
Name IQ_FQ: 500
Name IQ_FY: 1000
Name IQ_LTM: 2000
Name IQ_MONTH: 15000
Name IQ_NTM: 6000
Name IQ_WEEK: 50000
Name IQ_YTD: 3000

Sheet 3Q26 Quick Look
A2: AT&T Inc. (T) — Q3 2026 Earnings First Look
A3: $M (except for as noted) | B3: 3Q25A | C3: 2Q26A | D3: 3Q26 Consensus | E3: 3Q26A | F3: YoY Growth (3Q26 vs 3Q25) | G3: Beat/(Miss) %
A4: Total Revenue | B4: =Segment!D30 -> 30709 | C4: =Segment!H30 -> 31558 | D4: =Segment!I30 -> 31667.9 | F4: =IF(E4="","",(E4-B4)/B4) | G4: =IF(E4="","",(E4-D4)/D4)
A5: Advanced Connectivity | B5: =Segment!D25 -> 27503 | C5: =Segment!H25 -> 28615 | D5: =Segment!I25 -> 28914.47 | F5: =IF(E5="","",(E5-B5)/B5) | G5: =IF(E5="","",(E5-D5)/D5)
A6: Consumer | B6: =Segment!D23 -> 21274 | C6: =Segment!H23 -> 22329 | D6: =Segment!I23 -> 22529.96 | F6: =IF(E6="","",(E6-B6)/B6) | G6: =IF(E6="","",(E6-D6)/D6)
A7: Business | B7: =Segment!D24 -> 6229 | C7: =Segment!H24 -> 6286 | D7: =Segment!I24 -> 6351.39 | F7: =IF(E7="","",(E7-B7)/B7) | G7: =IF(E7="","",(E7-D7)/D7)
A8: Legacy | B8: =Segment!D26 -> 2013 | C8: =Segment!H26 -> 1632 | D8: =Segment!I26 -> 1504.54 | F8: =IF(E8="","",(E8-B8)/B8) | G8: =IF(E8="","",(E8-D8)/D8)
A9: Latin America Segment - Mexico | B9: =Segment!D28 -> 1095 | C9: =Segment!H28 -> 1224 | D9: =Segment!I28 -> 1149.49 | F9: =IF(E9="","",(E9-B9)/B9) | G9: =IF(E9="","",(E9-D9)/D9)
A10: Corporate | B10: =Segment!D29 -> 98 | C10: =Segment!H29 -> 87 | D10: =Segment!I29 -> 91.86 | F10: =IF(E10="","",(E10-B10)/B10) | G10: =IF(E10="","",(E10-D10)/D10)
A11: Total EBITDA | B11: ='Income Statement'!D35 -> 11861 | C11: ='Income Statement'!H35 -> 12338 | D11: ='Income Statement'!I35 -> 12325.8 | F11: =IF(E11="","",(E11-B11)/B11) | G11: =IF(E11="","",(E11-D11)/D11)
A12: Advanced Connectivity | B12: =Segment!D43 -> 11493 | C12: =Segment!H43 -> 12032 | D12: =Segment!I43 -> 12240.49 | F12: =IF(E12="","",(E12-B12)/B12) | G12: =IF(E12="","",(E12-D12)/D12)
A13: Legacy | B13: =Segment!D44 -> 679 | C13: =Segment!H44 -> 523 | D13: =Segment!I44 -> 414.73 | F13: =IF(E13="","",(E13-B13)/B13) | G13: =IF(E13="","",(E13-D13)/D13)
A14: Latin America Segment - Mexico | B14: =Segment!D46 -> 199 | C14: =Segment!H46 -> 227 | D14: =Segment!I46 -> 205.57 | F14: =IF(E14="","",(E14-B14)/B14) | G14: =IF(E14="","",(E14-D14)/D14)
A15: Corporate | B15: =B11-B12-B13-B14 -> -510 | C15: =C11-C12-C13-C14 -> -444 | D15: =D11-D12-D13-D14 -> -534.99 | E15: =IF(OR(E11="",E12="",E13="",E14=""),"",E11-E12-E13-E14) | F15: =IF(E15="","",(E15-B15)/B15) | G15: =IF(E15="","",(E15-D15)/D15)
A16: Total EBITDA Margin | B16: =B11/B4 -> 0.38623856 | C16: =C11/C4 -> 0.39096267 | D16: =D11/D4 -> 0.38922063 | E16: =IF(OR(E11="",E4=""),"",E11/E4) | F16: =IF(E16="","",E16-B16) | G16: =IF(E16="","",E16-D16)
A17: Advanced Connectivity Margin | B17: =B12/B5 -> 0.41788169 | C17: =C12/C5 -> 0.42047877 | D17: =D12/D5 -> 0.42333441 | E17: =IF(OR(E12="",E5=""),"",E12/E5) | F17: =IF(E17="","",E17-B17) | G17: =IF(E17="","",E17-D17)
A18: Legacy Margin | B18: =B13/B8 -> 0.3373075 | C18: =C13/C8 -> 0.32046569 | D18: =D13/D8 -> 0.27565236 | E18: =IF(OR(E13="",E8=""),"",E13/E8) | F18: =IF(E18="","",E18-B18) | G18: =IF(E18="","",E18-D18)
A19: Latin America Segment - Mexico Margin | B19: =B14/B9 -> 0.18173516 | C19: =C14/C9 -> 0.18545752 | D19: =D14/D9 -> 0.17883583 | E19: =IF(OR(E14="",E9=""),"",E14/E9) | F19: =IF(E19="","",E19-B19) | G19: =IF(E19="","",E19-D19)
A20: Cash From Operating Activities | B20: ='Cash Flow'!D31 -> 10152 | C20: ='Cash Flow'!H31 -> 10801 | D20: ='Cash Flow'!I31 -> 10667.33 | F20: =IF(E20="","",(E20-B20)/B20) | G20: =IF(E20="","",(E20-D20)/D20)
A21: Capital Investment & Distributions | B21: ='Cash Flow'!D65 -> 5287 | C21: ='Cash Flow'!H65 -> 6131 | D21: ='Cash Flow'!I65 -> 5839.69 | F21: =IF(E21="","",(E21-B21)/B21) | G21: =IF(E21="","",(E21-D21)/D21)
A22: Free Cashflow | B22: ='Free Cash Flow'!D23 -> 4865 | C22: ='Free Cash Flow'!H23 -> 4670 | D22: ='Free Cash Flow'!I23 -> 4900.42 | F22: =IF(E22="","",(E22-B22)/B22) | G22: =IF(E22="","",(E22-D22)/D22)
A23: Adjusted EPS | B23: ='Income Statement'!D62 -> 0.54 | C23: ='Income Statement'!H62 -> 0.65 | D23: ='Income Statement'!I62 -> 0.6 | F23: =IF(E23="","",(E23-B23)/B23) | G23: =IF(E23="","",(E23-D23)/D23)
A25: Operational metrics
A26: Postpaid Phone Net Adds (in 000') | B26: ='AC Wireless'!D38 -> 405 | C26: ='AC Wireless'!H38 -> 432 | D26: ='AC Wireless'!I38 -> 382.61 | F26: =IF(E26="","",(E26-B26)/B26) | G26: =IF(E26="","",(E26-D26)/D26)
A27: Prepaid Phone Net Adds (in 000') | B27: ='AC Wireless'!D60 -> -83 | C27: ='AC Wireless'!H60 -> 4 | D27: ='AC Wireless'!I60 -> -67.97 | F27: =IF(E27="","",(E27-B27)/B27) | G27: =IF(E27="","",(E27-D27)/D27)
A28: Postpaid Phone-Only Churn (in %) | B28: ='AC Wireless'!D36 -> 0.0092 | C28: ='AC Wireless'!H36 -> 0.0086 | D28: ='AC Wireless'!I36 -> 0.0091 | F28: =IF(E28="","",E28-B28) | G28: =IF(E28="","",E28-D28)
A29: Postpaid Phone ARPU (in $) | B29: ='AC Wireless'!D43 -> 56.64 | C29: ='AC Wireless'!H43 -> 58.01 | D29: ='AC Wireless'!I43 -> 57.57 | F29: =IF(E29="","",(E29-B29)/B29) | G29: =IF(E29="","",(E29-D29)/D29)
A30: Cons. Fiber Net Adds (in 000') | B30: ='AC Internet'!D17 -> 288 | C30: ='AC Internet'!H17 -> 344 | D30: ='AC Internet'!I17 -> 364.28 | F30: =IF(E30="","",(E30-B30)/B30) | G30: =IF(E30="","",(E30-D30)/D30)
A31: Fiber ARPU (in $) | B31: ='AC Internet'!D20 -> 73.48 | C31: ='AC Internet'!H20 -> 72.29 | D31: ='AC Internet'!I20 -> 73.05 | F31: =IF(E31="","",(E31-B31)/B31) | G31: =IF(E31="","",(E31-D31)/D31)
A32: Consumer Locations Passed w/ Fiber (in millions) | B32: ='AC Internet'!D77/1000 -> 25.4 | C32: ='AC Internet'!H77/1000 -> 32.1 | D32: ='AC Internet'!I77/1000 -> 33.02435 | F32: =IF(E32="","",(E32-B32)/B32) | G32: =IF(E32="","",(E32-D32)/D32)
A33: Cons. FWA Net Adds (in 000') | B33: ='AC Internet'!D23 -> 270 | C33: ='AC Internet'!H23 -> 215 | D33: ='AC Internet'!I23 -> 245.41 | F33: =IF(E33="","",(E33-B33)/B33) | G33: =IF(E33="","",(E33-D33)/D33)

Sheet CapIQ cons on Oct 20, 2026 ->

Sheet Revenue
A2: AT&T Inc. | Revenue
A3: NYSE:T (MI KEY: 4024242; SPCIQ KEY: 100231)
A5: Visible Alpha
A7: Period Type : Fiscal Quarter, Fiscal Halves, Fiscal Year
A8: Period Start : 2025
A9: Period End : 2030
A10: Currency : Reported
A11: Consensus View : Mean
A12: As Of: 10/20/2026
A14: All numbers in $M unless otherwise indicated | B14: FQ1 2025A | C14: FQ2 2025A | D14: FQ3 2025A | E14: FQ4 2025A | F14: FY2025A | G14: FQ1 2026A | H14: FQ2 2026A | I14: FQ3 2026E | J14: FQ4 2026E | K14: FY2026E | L14: FQ1 2027E | M14: FQ2 2027E | N14: FQ3 2027E | O14: FQ4 2027E | P14: FY2027E | Q14: FQ1 2028E | R14: FQ2 2028E | S14: FQ3 2028E | T14: FQ4 2028E | U14: FY2028E | V14: FQ1 2029E | W14: FQ2 2029E | X14: FQ3 2029E | Y14: FQ4 2029E | Z14: FY2029E | AA14: FQ1 2030E | AB14: FQ2 2030E | AC14: FQ3 2030E | AD14: FQ4 2030E | AE14: FY2030E
A15: Number of Contributors Available | B15: 19 | C15: 19 | D15: 19 | E15: 19 | F15: 20 | G15: 19 | H15: 19 | I15: 20 of 20 | J15: 20 of 20 | K15: 20 of 20 | L15: 14 of 20 | M15: 14 of 20 | N15: 13 of 20 | O15: 13 of 20 | P15: 20 of 20 | Q15: 7 of 20 | R15: 7 of 20 | S15: 7 of 20 | T15: 7 of 20 | U15: 17 of 20 | V15: 5 of 20 | W15: 5 of 20 | X15: 5 of 20 | Y15: 5 of 20 | Z15: 14 of 20 | AA15: 5 of 20 | AB15: 5 of 20 | AC15: 5 of 20 | AD15: 5 of 20 | AE15: 14 of 20
A16: Revenue - Postpaid Phones | B16: 12367.98 | C16: 12529.32 | D16: 12506.88 | E16: 12559.81 | F16: 49963.99 | G16: 12606 | H16: 13002.13 | I16: 12974.19 | J16: 13029.43 | K16: 51619.5 | L16: 13055.68 | M16: 13282.62 | N16: 13309.32 | O16: 13348.75 | P16: 52964.38 | Q16: 13348.78 | R16: 13588.7 | S16: 13554.23 | T16: 13641.23 | U16: 54139.56 | V16: 13602.74 | W16: 13900.58 | X16: 13850.67 | Y16: 13853.6 | Z16: 55176.6 | AA16: 13842.67 | AB16: 14136.45 | AC16: 14092.59 | AD16: 14089.93 | AE16: 56133.23
A17: Revenue - Prepaid Phones | B17: 1885.86 | C17: 1895.5 | D17: 1877.86 | E17: 1838.22 | F17: 7497.44 | G17: 1816.33 | H17: 1826.07 | I17: 1822.32 | J17: 1799.38 | K17: 7261.47 | L17: 1783.48 | M17: 1790.76 | N17: 1791.92 | O17: 1772.23 | P17: 7123.76 | Q17: 1751.46 | R17: 1758.84 | S17: 1761.91 | T17: 1740.3 | U17: 7021.62 | V17: 1710.93 | W17: 1719.23 | X17: 1728.6 | Y17: 1698.59 | Z17: 6908.7 | AA17: 1675.84 | AB17: 1683.56 | AC17: 1696.63 | AD17: 1667.34 | AE17: 6810.33
A18: Revenue - Phone | B18: 14253.84 | C18: 14424.82 | D18: 14384.74 | E18: 14398.03 | F18: 57461.43 | G18: 14422.32 | H18: 14828.2 | I18: 14784.47 | J18: 14818.18 | K18: 58851.72 | L18: 14839.17 | M18: 15073.38 | N18: 15101.24 | O18: 15120.97 | P18: 60063.77 | Q18: 15100.24 | R18: 15347.53 | S18: 15316.14 | T18: 15381.53 | U18: 61106.63 | V18: 15313.67 | W18: 15619.81 | X18: 15579.28 | Y18: 15552.2 | Z18: 61984.93 | AA18: 15518.51 | AB18: 15820.01 | AC18: 15789.22 | AD18: 15757.28 | AE18: 62805.57
A19: Revenue - Other subscribers | B19: 2397.16 | C19: 2428.18 | D19: 2541.26 | E19: 2555.97 | F19: 9922.57 | G19: 2518.68 | H19: 2584.8 | I19: 2737.75 | J19: 2745.11 | K19: 10586.89 | L19: 2664.31 | M19: 2765.9 | N19: 2870.49 | O19: 2865.51 | P19: 11137.22 | Q19: 2789.04 | R19: 2866.47 | S19: 3006.11 | T19: 2992.07 | U19: 11603.55 | V19: 2738.58 | W19: 2832.07 | X19: 2948.97 | Y19: 2955.26 | Z19: 11720.51 | AA19: 2800.05 | AB19: 2878.78 | AC19: 3021.87 | AD19: 3002.58 | AE19: 12024.8
A20: Service revenues - wireless | B20: 16651 | C20: 16853 | D20: 16926 | E20: 16954 | F20: 67384 | G20: 16941 | H20: 17413 | I20: 17526.97 | J20: 17565.72 | K20: 69453.75 | L20: 17503.72 | M20: 17839.36 | N20: 17971.16 | O20: 17985.62 | P20: 71247.05 | Q20: 17888.28 | R20: 18213.15 | S20: 18321.82 | T20: 18373.47 | U20: 72800.94 | V20: 18052.25 | W20: 18451.87 | X20: 18528.25 | Y20: 18507.46 | Z20: 73883.32 | AA20: 18318.56 | AB20: 18698.79 | AC20: 18811.09 | AD20: 18759.85 | AE20: 75056.66
A21: Fiber revenue | B21: 2066 | C21: 2136 | D21: 2198 | E21: 2245 | F21: 8645 | G21: 2505 | H21: 2593 | I21: 2667.53 | J21: 2733.45 | K21: 10498.26 | L21: 2872.55 | M21: 2926.28 | N21: 3016.16 | O21: 3087.23 | P21: 11955.67 | Q21: 3260.63 | R21: 3322.67 | S21: 3429.64 | T21: 3501.33 | U21: 13493.42 | V21: 3745.84 | W21: 3815.16 | X21: 3936.65 | Y21: 4032.36 | Z21: 15207.68 | AA21: 4224.6 | AB21: 4292.53 | AC21: 4417.96 | AD21: 4514.36 | AE21: 16897.84
A22: AT&T Internet Air revenue | B22: 132 | C22: 163 | D22: 213 | E22: 257 | F22: 765 | G22: 294 | H22: 333 | I22: 383.24 | J22: 426.95 | K22: 1437.27 | L22: 464.32 | M22: 499.52 | N22: 553.99 | O22: 596.25 | P22: 2109.42 | Q22: 618.99 | R22: 644.6 | S22: 700.88 | T22: 736.82 | U22: 2717.44 | V22: 754.5 | W22: 774.89 | X22: 835.48 | Y22: 867.05 | Z22: 3255.19 | AA22: 886.28 | AB22: 902.73 | AC22: 965.38 | AD22: 994.24 | AE22: 3734.21
A23: Advanced home internet services revenue - Advanced connectivity | B23: 2198 | C23: 2299 | D23: 2411 | E23: 2502 | F23: 9410 | G23: 2799 | H23: 2926 | I23: 3065.8 | J23: 3181.73 | K23: 11993.31 | L23: 3349.99 | M23: 3432.08 | N23: 3580.82 | O23: 3701.07 | P23: 14128.13 | Q23: 3902.26 | R23: 3977 | S23: 4148.02 | T23: 4268.25 | U23: 16264.78 | V23: 4500.34 | W23: 4590.05 | X23: 4772.13 | Y23: 4899.41 | Z23: 18469.22 | AA23: 5110.89 | AB23: 5195.26 | AC23: 5383.34 | AD23: 5508.6 | AE23: 20618.1
A24: Business fiber and advanced connectivity services revenue - Advanced connectivity | B24: 1755 | C24: 1769 | D24: 1832 | E24: 1887 | F24: 7243 | G24: 1882 | H24: 1946 | I24: 1992 | J24: 2046.85 | K24: 7866.85 | L24: 2037 | M24: 2106.48 | N24: 2146.61 | O24: 2196.75 | P24: 8495 | Q24: 2177.4 | R24: 2237.25 | S24: 2261.04 | T24: 2304.39 | U24: 9092.5 | V24: 2376.18 | W24: 2438.72 | X24: 2476.61 | Y24: 2524.98 | Z24: 9847.16 | AA24: 2545.26 | AB24: 2606.66 | AC24: 2642.05 | AD24: 2689.49 | AE24: 10498.97
A25: Business transitional and other service revenue - Advanced connectivity | B25: 1294 | C25: 1249 | D25: 1198 | E25: 1170 | F25: 4911 | G25: 1083 | H25: 1042 | I25: 1021.53 | J25: 998.08 | K25: 4144.61 | L25: 932.87 | M25: 898.49 | N25: 881.42 | O25: 861.16 | P25: 3570.63 | Q25: 825.83 | R25: 794.57 | S25: 781.55 | T25: 764.06 | U25: 3148.6 | V25: 751.58 | W25: 723.62 | X25: 717.62 | Y25: 702.74 | Z25: 2813.96 | AA25: 677.3 | AB25: 652.18 | AC25: 647.12 | AD25: 633.78 | AE25: 2502.93
A26: Other services revenue - Advanced connectivity | B26: 162 | C26: 164 | D26: 162 | E26: 162 | F26: 650 | G26: 158 | H26: 151 | I26: 156.01 | J26: 156.22 | K26: 621.23 | L26: 152.8 | M26: 145.26 | N26: 150.43 | O26: 151.27 | P26: 597.96 | Q26: 146.75 | R26: 139.75 | S26: 144.31 | T26: 144.33 | U26: 577.04 | V26: 139.03 | W26: 132.63 | X26: 135.72 | Y26: 135.78 | Z26: 553.59 | AA26: 133.37 | AB26: 127.21 | AC26: 130.19 | AD26: 130.25 | AE26: 534.11
A27: Total service revenue - Advanced connectivity | B27: 22060 | C27: 22334 | D27: 22529 | E27: 22675 | F27: 89598 | G27: 22863 | H27: 23478 | I27: 23773.75 | J27: 23938.35 | K27: 94053.1 | L27: 23956.91 | M27: 24425.9 | N27: 24752.97 | O27: 24872.93 | P27: 97976.67 | Q27: 24940.53 | R27: 25361.72 | S27: 25656.74 | T27: 25854.49 | U27: 101853.62 | V27: 25819.37 | W27: 26336.89 | X27: 26630.33 | Y27: 26770.37 | Z27: 105551.96 | AA27: 26785.38 | AB27: 27280.1 | AC27: 27613.79 | AD27: 27721.97 | AE27: 109247.44
... A39: Operating revenues | B39: 30626 | C39: 30847 | D39: 30709 | E39: 33466 | F39: 125648 | G39: 31506 | H39: 31558 | I39: 31667.9 | J39: 34499.33 | K39: 129215.33 | L39: 32202.3 | M39: 32251.94 | N39: 32421.74 | O39: 35255.95 | P39: 132052.75 | Q39: 32816.09 | R39: 32690.07 | S39: 32932.11 | T39: 36065 | U39: 134712.76 | V39: 33509.2 | W39: 33519.5 | X39: 33751.99 | Y39: 36931.43 | Z39: 138007.48 | AA39: 34358.45 | AB39: 34370.16 | AC39: 34660.88 | AD39: 37859.21 | AE39: 141694.19

Sheet Segment
A2: AT&T Inc. | Segment
A3: NYSE:T (MI KEY: 4024242; SPCIQ KEY: 100231)
A5: Visible Alpha
A7: Period Type : Fiscal Quarter, Fiscal Halves, Fiscal Year
A8: Period Start : 2025
A9: Period End : 2030
A10: Currency : Reported
A11: Consensus View : Mean
A12: As Of: 10/20/2026
A14: All numbers in $M unless otherwise indicated | B14: FQ1 2025A | C14: FQ2 2025A | D14: FQ3 2025A | E14: FQ4 2025A | F14: FY2025A | G14: FQ1 2026A | H14: FQ2 2026A | I14: FQ3 2026E | J14: FQ4 2026E | K14: FY2026E | L14: FQ1 2027E | M14: FQ2 2027E | N14: FQ3 2027E | O14: FQ4 2027E | P14: FY2027E | Q14: FQ1 2028E | R14: FQ2 2028E | S14: FQ3 2028E | T14: FQ4 2028E | U14: FY2028E | V14: FQ1 2029E | W14: FQ2 2029E | X14: FQ3 2029E | Y14: FQ4 2029E | Z14: FY2029E | AA14: FQ1 2030E | AB14: FQ2 2030E | AC14: FQ3 2030E | AD14: FQ4 2030E | AE14: FY2030E
A15: Number of Contributors Available | B15: 19 | C15: 19 | D15: 19 | E15: 19 | F15: 20 | G15: 19 | H15: 19 | I15: 20 of 20 | J15: 20 of 20 | K15: 20 of 20 | L15: 14 of 20 | M15: 14 of 20 | N15: 13 of 20 | O15: 13 of 20 | P15: 20 of 20 | Q15: 7 of 20 | R15: 7 of 20 | S15: 7 of 20 | T15: 7 of 20 | U15: 17 of 20 | V15: 5 of 20 | W15: 5 of 20 | X15: 5 of 20 | Y15: 5 of 20 | Z15: 14 of 20 | AA15: 5 of 20 | AB15: 5 of 20 | AC15: 5 of 20 | AD15: 5 of 20 | AE15: 14 of 20
A16: Service revenue
A17: Total service revenue - Advanced connectivity | B17: 22060 | C17: 22334 | D17: 22529 | E17: 22675 | F17: 89598 | G17: 22863 | H17: 23478 | I17: 23773.75 | J17: 23938.35 | K17: 94053.1 | L17: 23956.91 | M17: 24425.9 | N17: 24752.97 | O17: 24872.93 | P17: 97976.67 | Q17: 24940.53 | R17: 25361.72 | S17: 25656.74 | T17: 25854.49 | U17: 101853.62 | V17: 25819.37 | W17: 26336.89 | X17: 26630.33 | Y17: 26770.37 | Z17: 105551.96 | AA17: 26785.38 | AB17: 27280.1 | AC17: 27613.79 | AD17: 27721.97 | AE17: 109247.44
A18: Revenue - Legacy | B18: 2368 | C18: 2202 | D18: 2013 | E18: 1889 | F18: 8472 | G18: 1768 | H18: 1632 | I18: 1504.54 | J18: 1400.95 | K18: 6305.49 | L18: 1259.37 | M18: 1143.27 | N18: 1040.74 | O18: 947.12 | P18: 4358.11 | Q18: 724.43 | R18: 642.29 | S18: 563.6 | T18: 501.43 | U18: 2651.29 | V18: 457.63 | W18: 399.61 | X18: 351.66 | Y18: 311.9 | Z18: 1654.41 | AA18: 346.97 | AB18: 422.12 | AC18: 391.25 | AD18: 358.64 | AE18: 1423.71
A19: Mexico wireless service revenue | B19: 615 | C19: 662 | D19: 696 | E19: 742 | F19: 2715 | G19: 753 | H19: 780 | I19: 713.78 | J19: 732.21 | K19: 2968.51 | L19: 732.73 | M19: 747.95 | N19: 703.81 | O19: 725.43 | P19: 2930.77 | Q19: 730.95 | R19: 759.87 | S19: 687.77 | T19: 716.48 | U19: 2982.09 | V19: 746.61 | W19: 777.66 | X19: 702.78 | Y19: 732.7 | Z19: 3056.4 | AA19: 761.41 | AB19: 792.13 | AC19: 711.2 | AD19: 741.48 | AE19: 3089.88
A20: Total revenue- Services | B20: 25043 | C20: 25198 | D20: 25238 | E20: 25306 | F20: 100785 | G20: 25384 | H20: 25890 | I20: 25981.49 | J20: 26080.84 | K20: 103336.33 | L20: 25962.47 | M20: 26311.25 | N20: 26466.93 | O20: 26555.69 | P20: 105241.21 | Q20: 26395.9 | R20: 26763.88 | S20: 26908.1 | T20: 27072.4 | U20: 107452.64 | V20: 27023.61 | W20: 27514.16 | X20: 27684.76 | Y20: 27814.97 | Z20: 110255.08 | AA20: 27824.37 | AB20: 28320.9 | AC20: 28550.11 | AD20: 28673.04 | AE20: 113402.32
A22: Revenue
A23: Advanced connectivity revenue - Consumer | B23: 20976 | C23: 21295 | D23: 21274 | E23: 23714 | F23: 87259 | G23: 22152 | H23: 22329 | I23: 22529.96 | J23: 25029.95 | K23: 92040.91 | L23: 23462.97 | M23: 23392.31 | N23: 23565.52 | O23: 26179.82 | P23: 96421.23 | Q23: 24714.22 | R23: 24491.93 | S23: 24932.98 | T23: 27733.77 | U23: 100613.03 | V23: 24779.24 | W23: 24718.62 | X23: 24902.3 | Y23: 27397.07 | Z23: 103600.7 | AA23: 25594.82 | AB23: 25389.47 | AC23: 25797.44 | AD23: 28174.46 | AE23: 107201.91
A24: Advanced connectivity revenue - Business | B24: 6216 | C24: 6202 | D24: 6229 | E24: 6518 | F24: 25165 | G24: 6319 | H24: 6286 | I24: 6351.39 | J24: 6646.63 | K24: 25603.02 | L24: 6355.07 | M24: 6318.73 | N24: 6323.6 | O24: 6684.2 | P24: 25891.13 | Q24: 6213.54 | R24: 6127.74 | S24: 6073.02 | T24: 6458.46 | U24: 26338.13 | V24: 6751.83 | W24: 6761.24 | X24: 6830.18 | Y24: 7364.61 | Z24: 27685.84 | AA24: 6911.7 | AB24: 6959.73 | AC24: 6998.7 | AD24: 7571.13 | AE24: 28524.77
A25: Advanced connectivity revenue | B25: 27192 | C25: 27497 | D25: 27503 | E25: 30232 | F25: 112424 | G25: 28471 | H25: 28615 | I25: 28914.47 | J25: 31785.77 | K25: 117786.24 | L25: 29666.41 | M25: 29801.33 | N25: 30135.6 | O25: 32964.52 | P25: 122554.94 | Q25: 30819.32 | R25: 30756.72 | S25: 31139.59 | T25: 34200.76 | U25: 126842.92 | V25: 31761.37 | W25: 31784.6 | X25: 32176.01 | Y25: 35256.45 | Z25: 131064.38 | AA25: 32770.35 | AB25: 32765.27 | AC25: 33199.27 | AD25: 36273.42 | AE25: 135287.83
A26: Revenue - Legacy | B26: 2368 | C26: 2202 | D26: 2013 | E26: 1889 | F26: 8472 | G26: 1768 | H26: 1632 | I26: 1504.54 | J26: 1400.95 | K26: 6305.49 | L26: 1259.37 | M26: 1143.27 | N26: 1040.74 | O26: 947.12 | P26: 4358.11 | Q26: 724.43 | R26: 642.29 | S26: 563.6 | T26: 501.43 | U26: 2651.29 | V26: 457.63 | W26: 399.61 | X26: 351.66 | Y26: 311.9 | Z26: 1654.41 | AA26: 346.97 | AB26: 422.12 | AC26: 391.25 | AD26: 358.64 | AE26: 1423.71
A27: Total Communications Revenue | B27: 29560 | C27: 29699 | D27: 29516 | E27: 32121 | F27: 120896 | G27: 30239 | H27: 30247 | I27: 30400.09 | J27: 33156.3 | K27: 124037.87 | L27: 30930.93 | M27: 30937.15 | N27: 31150.69 | O27: 33884.32 | P27: 126817.07 | Q27: 31543.74 | R27: 31399.01 | S27: 31703.19 | T27: 34702.19 | U27: 129463.7 | V27: 32219 | W27: 32184.21 | X27: 32527.67 | Y27: 35568.35 | Z27: 132680.51 | AA27: 33047.92 | AB27: 33013.94 | AC27: 33424.39 | AD27: 36483.01 | AE27: 136284.21
A28: Latin America revenue | B28: 971 | C28: 1054 | D28: 1095 | E28: 1259 | F28: 4379 | G28: 1173 | H28: 1224 | I28: 1149.49 | J28: 1247.25 | K28: 4784.74 | L28: 1185.98 | M28: 1221.23 | N28: 1155.52 | O28: 1261.88 | P28: 4833.03 | Q28: 1180.21 | R28: 1202.82 | S28: 1138.85 | T28: 1275.94 | U28: 4891.37 | V28: 1198.29 | W28: 1248.73 | X28: 1135.25 | Y28: 1278.41 | Z28: 4975.67 | AA28: 1219.63 | AB28: 1270.61 | AC28: 1148.41 | AD28: 1292.46 | AE28: 5043.04
A29: Revenue - Corporate, Video and other | B29: 95 | C29: 94 | D29: 98 | E29: 86 | F29: 373 | G29: 94 | H29: 87 | I29: 91.86 | J29: 85.73 | K29: 357.8 | L29: 90.65 | M29: 87.67 | N29: 89.24 | O29: 82.57 | P29: 348.55 | Q29: 90.89 | R29: 89.37 | S29: 88.26 | T29: 86.48 | U29: 346.94 | V29: 88.76 | W29: 86.68 | X29: 85.12 | Y29: 82.64 | Z29: 338.27 | AA29: 85.24 | AB29: 83.2 | AC29: 81.65 | AD29: 79.17 | AE29: 330.57
A30: Operating revenues | B30: 30626 | C30: 30847 | D30: 30709 | E30: 33466 | F30: 125648 | G30: 31506 | H30: 31558 | I30: 31667.9 | J30: 34499.33 | K30: 129215.33 | L30: 32202.3 | M30: 32251.94 | N30: 32421.74 | O30: 35255.95 | P30: 132052.75 | Q30: 32816.09 | R30: 32690.07 | S30: 32932.11 | T30: 36065 | U30: 134712.76 | V30: 33509.2 | W30: 33519.5 | X30: 33751.99 | Y30: 36931.43 | Z30: 138007.48 | AA30: 34358.45 | AB30: 34370.16 | AC30: 34660.88 | AD30: 37859.21 | AE30: 141694.19
A32: Operations and support
A33: Operations and support - Advanced connectivity | B33: 16247 | C33: 16356 | D33: 16010 | E33: 19264 | F33: 67877 | G33: 16913 | H33: 16583 | I33: 16676.2 | J33: 20026.37 | K33: 70198.57 | L33: 17398.56 | M33: 16986.46 | N33: 17017.35 | O33: 20522.4 | P33: 71910.54 | Q33: 17636.4 | R33: 17172.41 | S33: 17338.98 | T33: 20944.83 | U33: 73205.38 | V33: 17991.32 | W33: 17540.6 | X33: 17751.89 | Y33: 21431.53 | Z33: 74994.98 | AA33: 18376.86 | AB33: 17916.25 | AC33: 18158.54 | AD33: 21868.9 | AE33: 76752.61
A34: Operations and support - Legacy | B34: 1349 | C34: 1243 | D34: 1334 | E34: 1207 | F34: 5133 | G34: 1156 | H34: 1109 | I34: 1088.62 | J34: 1013.43 | K34: 4367.05 | L34: 954.26 | M34: 918.11 | N34: 904.81 | O34: 849.62 | P34: 3590.8 | Q34: 723.81 | R34: 685.82 | S34: 664.65 | T34: 619.99 | U34: 2722.26 | V34: 562.19 | W34: 519.21 | X34: 486.12 | Y34: 444.68 | Z34: 1903.29 | AA34: 455.7 | AB34: 430.04 | AC34: 412.99 | AD34: 383.05 | AE34: 1541.27
A35: Operations and Support - Communications | B35: 17596 | C35: 17599 | D35: 17344 | E35: 20471 | F35: 73010 | G35: 18069 | H35: 17692 | I35: 17758.46 | J35: 20976.91 | K35: 74508 | L35: 18301.1 | M35: 17953.1 | N35: 18017.66 | O35: 21267.26 | P35: 75477.07 | Q35: 18360.21 | R35: 17858.23 | S35: 18003.64 | T35: 21564.81 | U35: 75931.89 | V35: 18553.51 | W35: 18059.81 | X35: 18238.01 | Y35: 21876.2 | Z35: 76955.08 | AA35: 18741.42 | AB35: 18260.28 | AC35: 18488.93 | AD35: 22175.34 | AE35: 78122.71
A36: Operations and support - Latin America | B36: 778 | C36: 853 | D36: 896 | E36: 1036 | F36: 3563 | G36: 953 | H36: 997 | I36: 940.16 | J36: 1022.58 | K36: 3904.51 | L36: 961.39 | M36: 987.02 | N36: 937.2 | O36: 1027.98 | P36: 3911.34 | Q36: 956.9 | R36: 973.35 | S36: 931.92 | T36: 1042.68 | U36: 3957.45 | V36: 973.78 | W36: 1011.7 | X36: 924.04 | Y36: 1047.28 | Z36: 4010.34 | AA36: 989.46 | AB36: 1027.67 | AC36: 933.24 | AD36: 1057.07 | AE36: 4055.68
A37: Operations and Support - Corporate, Video and other | B37: 719 | C37: 643 | D37: 1033 | E37: 1043 | F37: 4027 | G37: 860 | H37: 865 | I37: 629.37 | J37: 860.51 | K37: 2986.31 | L37: 708.14 | M37: 581.56 | N37: 603.66 | O37: 845.88 | P37: 2639.66 | Q37: 675.39 | R37: 594.5 | S37: 590.87 | T37: 638.17 | U37: 2385.31 | V37: 774.05 | W37: 605.16 | X37: 613.89 | Y37: 679.09 | Z37: 2405.85 | AA37: 753.27 | AB37: 604.02 | AC37: 612.53 | AD37: 691.33 | AE37: 2394.09
A38: Operations and support | B38: 19178 | C38: 19095 | D38: 19273 | E38: 22550 | F38: 80600 | G38: 19882 | H38: 19554 | I38: 19301.39 | J38: 22825.63 | K38: 81467.69 | L38: 19949.35 | M38: 19564.71 | N38: 19653.94 | O38: 23126.5 | P38: 81986.96 | Q38: 19950.66 | R38: 19511.28 | S38: 19678.8 | T38: 23367.68 | U38: 82218.03 | V38: 20278.15 | W38: 19912.19 | X38: 20153.69 | Y38: 23994.39 | Z38: 84002.91 | AA38: 20487.78 | AB38: 20149.55 | AC38: 20421.3 | AD38: 24314.61 | AE38: 85196.02
A40: EBITDA
A41: EBITDA - Consumer - Advanced Connectivity | B41: 9175 | C41: 9429 | D41: 9701 | E41: 9286 | F41: 37591 | G41: 9563 | H41: 10095 | I41: 10259.68 | J41: 9843.87 | K41: 39761.55 | L41: 10288.58 | M41: 10559.43 | N41: 10906.72 | O41: 10370.65 | P41: 41999.89 | Q41: 10874.34 | R41: 11256.16 | S41: 11581.44 | T41: 11085.07 | U41: 44231.89 | V41: 11534.17 | W41: 11987.14 | X41: 12351.48 | Y41: 11762.15 | Z41: 46114.68 | AA41: 12100.96 | AB41: 12489.91 | AC41: 12992.3 | AD41: 12296.11 | AE41: 47966.94
A42: EBITDA - Business - Advanced Connectivity | B42: 1770 | C42: 1712 | D42: 1792 | E42: 1682 | F42: 6956 | G42: 1995 | H42: 1937 | I42: 1889.96 | J42: 1760.05 | K42: 7582.01 | L42: 2114.74 | M42: 2030.57 | N42: 1915.84 | O42: 1853.12 | P42: 8043.82 | Q42: 2278.64 | R42: 2167.74 | S42: 2041.93 | T42: 2044.29 | U42: 8483.89 | V42: 2331.14 | W42: 2283.3 | X42: 2178.08 | Y42: 2161.05 | Z42: 8887.01 | AA42: 2430.99 | AB42: 2400.71 | AC42: 2274.52 | AD42: 2275.18 | AE42: 9326.17
A43: EBITDA - Advanced connectivity | B43: 10945 | C43: 11141 | D43: 11493 | E43: 10968 | F43: 44547 | G43: 11558 | H43: 12032 | I43: 12240.49 | J43: 11713.56 | K43: 47544.04 | L43: 12315.75 | M43: 12759.45 | N43: 13038.25 | O43: 12399.7 | P43: 50510.31 | Q43: 13182.92 | R43: 13584.31 | S43: 13800.61 | T43: 13255.94 | U43: 53603.28 | V43: 13770.05 | W43: 14244 | X43: 14424.12 | Y43: 13824.92 | Z43: 56048.28 | AA43: 14393.48 | AB43: 14849.02 | AC43: 15040.72 | AD43: 14404.53 | AE43: 58480.23
A44: EBITDA - Legacy | B44: 1019 | C44: 959 | D44: 679 | E44: 682 | F44: 3339 | G44: 612 | H44: 523 | I44: 414.73 | J44: 387.29 | K44: 1937.02 | L44: 313.24 | M44: 238.89 | N44: 130.75 | O44: 90.76 | P44: 800.51 | Q44: 0.62 | R44: -43.53 | S44: -101.05 | T44: -118.56 | U44: -64.59 | V44: -104.55 | W44: -119.6 | X44: -134.46 | Y44: -132.77 | Z44: -279.23 | AA44: -48.87 | AB44: -54.61 | AC44: -131.58 | AD44: -121.07 | AE44: -203.86
A45: EBITDA - Communications | B45: 11964 | C45: 12100 | D45: 12172 | E45: 11650 | F45: 47886 | G45: 12170 | H45: 12555 | I45: 12656.3 | J45: 12107.95 | K45: 49465.67 | L45: 12628.99 | M45: 12998.33 | N45: 13169.01 | O45: 12490.46 | P45: 51281.25 | Q45: 13183.53 | R45: 13540.78 | S45: 13699.55 | T45: 13137.38 | U45: 53490.84 | V45: 13665.49 | W45: 14124.4 | X45: 14289.66 | Y45: 13692.15 | Z45: 55697.42 | AA45: 14306.5 | AB45: 14753.66 | AC45: 14935.46 | AD45: 14307.67 | AE45: 58139.93
A46: EBITDA - Latin America | B46: 193 | C46: 201 | D46: 199 | E46: 223 | F46: 816 | G46: 220 | H46: 227 | I46: 205.57 | J46: 224.38 | K46: 875.67 | L46: 220.07 | M46: 229.04 | N46: 209.24 | O46: 233.14 | P46: 907.83 | Q46: 223.31 | R46: 229.47 | S46: 206.93 | T46: 233.26 | U46: 933.92 | V46: 224.51 | W46: 237.03 | X46: 211.22 | Y46: 231.13 | Z46: 965.33 | AA46: 230.18 | AB46: 242.93 | AC46: 215.16 | AD46: 235.39 | AE46: 987.36
A47: EBITDA - Corporate & Other | B47: -624 | C47: -570 | D47: -510 | E47: -957 | F47: -2341 | G47: -766 | H47: -778 | I47: -537.6 | J47: -648.51 | K47: -2407.14 | L47: -591.39 | M47: -495.56 | N47: -509.14 | O47: -695.71 | P47: -2179.03 | Q47: -545.55 | R47: -545.67 | S47: -557.05 | T47: -621.21 | U47: -2008.13 | V47: -499.51 | W47: -500.59 | X47: -524.66 | Y47: -885.27 | Z47: -2070.74 | AA47: -484.94 | AB47: -495.24 | AC47: -518.46 | AD47: -606.26 | AE47: -1947.65
A48: EBITDA | B48: 10944 | C48: 11752 | D48: 11436 | E48: 10916 | F48: 45048 | G48: 11624 | H48: 12004 | I48: 12306.16 | J48: 11668.56 | K48: 47751.02 | L48: 12242.29 | M48: 12716.43 | N48: 12852.44 | O48: 12011.22 | P48: 49908.58 | Q48: 12861.29 | R48: 13224.58 | S48: 13349.44 | T48: 12749.42 | U48: 52313.74 | V48: 13390.49 | W48: 13860.84 | X48: 13976.21 | Y48: 13038.01 | Z48: 54455.61 | AA48: 14051.74 | AB48: 14501.35 | AC48: 14632.17 | AD48: 13936.81 | AE48: 56996.15
A50: Operating income/(loss)
A51: Operating income/(loss) - Advanced connectivity | B51: 5972 | C51: 6106 | D51: 6417 | E51: 6093 | F51: 24588 | G51: 6853 | H51: 7345 | I51: 7368.96 | J51: 6760.85 | K51: 28327.81 | L51: 7607.22 | M51: 7951.6 | N51: 8102.7 | O51: 7474.14 | P51: 31136.32 | Q51: 8388.04 | R51: 8740.54 | S51: 8833.32 | T51: 8242.19 | U51: 33951.24 | V51: 8863.52 | W51: 9280.63 | X51: 9319.4 | Y51: 8809.81 | Z51: 36024.18 | AA51: 9342.41 | AB51: 9746.19 | AC51: 9809.35 | AD51: 9267.49 | AE51: 38150.61
A52: Operating income/(loss) - Legacy | B52: 1019 | C52: 959 | D52: 679 | E52: 682 | F52: 3339 | G52: 612 | H52: 523 | I52: 403.65 | J52: 379.99 | K52: 1918.64 | L52: 294.89 | M52: 219.6 | N52: 118.79 | O52: 85.52 | P52: 743.06 | Q52: -0.61 | R52: -43.45 | S52: -102.96 | T52: -115.9 | U52: -105.31 | V52: -87.66 | W52: -97.92 | X52: -108.8 | Y52: -101.13 | Z52: -234.29 | AA52: -48.87 | AB52: -54.61 | AC52: -62.7 | AD52: -47.67 | AE52: -202.93
A53: Operating Income/(loss) - Communications | B53: 6991 | C53: 7065 | D53: 7096 | E53: 6775 | F53: 27927 | G53: 7465 | H53: 7868 | I53: 7776.16 | J53: 7135.88 | K53: 30245.04 | L53: 7864.35 | M53: 8187.44 | N53: 8207.41 | O53: 7537.5 | P53: 31831.18 | Q53: 8302.81 | R53: 8719.31 | S53: 8680.47 | T53: 8044.92 | U53: 33770.17 | V53: 8608.29 | W53: 9197.97 | X53: 9103.87 | Y53: 8531.81 | Z53: 35640.44 | AA53: 9105.45 | AB53: 9729.39 | AC53: 9634.69 | AD53: 9040.21 | AE53: 37791.63
A54: Operating income/(loss) - Latin America | B54: 43 | C54: 46 | D54: 22 | E54: 34 | F54: 145 | G54: 20 | H54: 38 | I54: 17.23 | J54: 32.01 | K54: 109.32 | L54: 31.47 | M54: 44.41 | N54: 22.63 | O54: 41.4 | P54: 154.17 | Q54: 28.91 | R54: 46.07 | S54: 18.68 | T54: 41.88 | U54: 177.49 | V54: 22.33 | W54: 41.02 | X54: 21.56 | Y54: 35.06 | Z54: 189.53 | AA54: 22 | AB54: 41.02 | AC54: 21.56 | AD54: 35.28 | AE54: 195.91
A55: Operating income - Corporate & Other | B55: -1280 | C55: -610 | D55: -999 | E55: -1021 | F55: -3910 | G55: -827 | H55: -868 | I55: -619.35 | J55: -688.47 | K55: -2863.94 | L55: -688.53 | M55: -594.66 | N55: -603.52 | O55: -667.34 | P55: -2432.09 | Q55: -679.49 | R55: -607.97 | S55: -598.9 | T55: -639.67 | U55: -2401.84 | V55: -703.86 | W55: -586.57 | X55: -585.49 | Y55: -638.51 | Z55: -2356.96 | AA55: -680.95 | AB55: -578.56 | AC55: -576.13 | AD55: -641.61 | AE55: -2338.9
A56: Operating income/(loss) - WarnerMedia | B56: - | C56: - | D56: - | E56: - | F56: - | G56: - | H56: - | I56: - | J56: - | K56: - | L56: - | M56: - | N56: - | O56: - | P56: - | Q56: - | R56: - | S56: - | T56: - | U56: - | V56: - | W56: - | X56: - | Y56: - | Z56: - | AA56: - | AB56: - | AC56: - | AD56: - | AE56: -
A57: Operating income/(loss) | B57: 5754 | C57: 6501 | D57: 6119 | E57: 5788 | F57: 24162 | G57: 6658 | H57: 7038 | I57: 7188.82 | J57: 6489.34 | K57: 27412.86 | L57: 7168.23 | M57: 7642.17 | N57: 7726.89 | O57: 6886.41 | P57: 29443.98 | Q57: 7798.12 | R57: 8173.02 | S57: 8181.89 | T57: 7589.91 | U57: 31708.81 | V57: 8243.38 | W57: 8724.88 | X57: 8703.01 | Y57: 7793.84 | Z57: 33522.51 | AA57: 8827.9 | AB57: 9294.79 | AC57: 9281.87 | AD57: 8629.32 | AE57: 35856.34

Sheet Income Statement
A2: AT&T Inc. | Income statement
A3: NYSE:T (MI KEY: 4024242; SPCIQ KEY: 100231)
A5: Visible Alpha
A7: Period Type : Fiscal Quarter, Fiscal Halves, Fiscal Year
A8: Period Start : 2025
A9: Period End : 2030
A10: Currency : Reported
A11: Consensus View : Mean
A12: As Of: 10/20/2026
A14: All numbers in $M unless otherwise indicated | B14: FQ1 2025A | C14: FQ2 2025A | D14: FQ3 2025A | E14: FQ4 2025A | F14: FY2025A | G14: FQ1 2026A | H14: FQ2 2026A | I14: FQ3 2026E | J14: FQ4 2026E | K14: FY2026E | L14: FQ1 2027E | M14: FQ2 2027E | N14: FQ3 2027E | O14: FQ4 2027E | P14: FY2027E | Q14: FQ1 2028E | R14: FQ2 2028E | S14: FQ3 2028E | T14: FQ4 2028E | U14: FY2028E | V14: FQ1 2029E | W14: FQ2 2029E | X14: FQ3 2029E | Y14: FQ4 2029E | Z14: FY2029E | AA14: FQ1 2030E | AB14: FQ2 2030E | AC14: FQ3 2030E | AD14: FQ4 2030E | AE14: FY2030E
A15: Number of Contributors Available | B15: 19 | C15: 19 | D15: 19 | E15: 19 | F15: 20 | G15: 19 | H15: 19 | I15: 20 of 20 | J15: 20 of 20 | K15: 20 of 20 | L15: 14 of 20 | M15: 14 of 20 | N15: 13 of 20 | O15: 13 of 20 | P15: 20 of 20 | Q15: 7 of 20 | R15: 7 of 20 | S15: 7 of 20 | T15: 7 of 20 | U15: 17 of 20 | V15: 5 of 20 | W15: 5 of 20 | X15: 5 of 20 | Y15: 5 of 20 | Z15: 14 of 20 | AA15: 5 of 20 | AB15: 5 of 20 | AC15: 5 of 20 | AD15: 5 of 20 | AE15: 14 of 20
A16: Service revenue | B16: 25138 | C16: 25292 | D16: 25336 | E16: 25392 | F16: 101158 | G16: 25478 | H16: 25977 | I16: 26084.69 | J16: 26176.83 | K16: 103631.83 | L16: 25994.06 | M16: 26322.71 | N16: 26558.6 | O16: 26629.08 | P16: 105457.07 | Q16: 26502.43 | R16: 26837.57 | S16: 27081.09 | T16: 27245.72 | U16: 107631.46 | V16: 27105.05 | W16: 27545.49 | X16: 27809.42 | Y16: 27934.14 | Z16: 110294.63 | AA16: 27930.57 | AB16: 28368.56 | AC16: 28700.02 | AD16: 28811.82 | AE16: 113527.44
A17: Equipment revenue | B17: 5488 | C17: 5555 | D17: 5373 | E17: 8074 | F17: 24490 | G17: 6028 | H17: 5581 | I17: 5537.36 | J17: 8360.35 | K17: 25604.28 | L17: 6209.08 | M17: 5766.98 | N17: 5671.96 | O17: 8683.29 | P17: 26373.77 | Q17: 6324.85 | R17: 5807.87 | S17: 5801.47 | T17: 8861.17 | U17: 26911.66 | V17: 6334.48 | W17: 5876.7 | X17: 5791.98 | Y17: 8879.75 | Z17: 27349.31 | AA17: 6382.16 | AB17: 5919.4 | AC17: 5830.49 | AD17: 8939.82 | AE17: 27761.39
A18: Operating revenues | B18: 30626 | C18: 30847 | D18: 30709 | E18: 33466 | F18: 125648 | G18: 31506 | H18: 31558 | I18: 31667.9 | J18: 34499.33 | K18: 129215.33 | L18: 32202.3 | M18: 32251.94 | N18: 32421.74 | O18: 35255.95 | P18: 132052.75 | Q18: 32816.09 | R18: 32690.07 | S18: 32932.11 | T18: 36065 | U18: 134712.76 | V18: 33509.2 | W18: 33519.5 | X18: 33751.99 | Y18: 36931.43 | Z18: 138007.48 | AA18: 34358.45 | AB18: 34370.16 | AC18: 34660.88 | AD18: 37859.21 | AE18: 141694.19
A19: Equipment cost | B19: 5694 | C19: 5738 | D19: 5468 | E19: 8496 | F19: 25396 | G19: 6305 | H19: 5741 | I19: 5712.31 | J19: 8108.68 | K19: 25866.99 | L19: 6207.03 | M19: 5773.46 | N19: 5746.54 | O19: 8038.6 | P19: 26019.31 | Q19: 6593.8 | R19: 5847.03 | S19: 5956.86 | T19: 9337.31 | U19: 26434.14 | V19: 6373.75 | W19: 5784.9 | X19: 5766.78 | Y19: 9139.15 | Z19: 26366.55 | AA19: 6352.23 | AB19: 5757.39 | AC19: 5745.86 | AD19: 9106.94 | AE19: 26648.9
A20: Broadcast, programming and operations | B20: - | C20: - | D20: - | E20: - | F20: - | G20: - | H20: - | I20: - | J20: - | K20: - | L20: - | M20: - | N20: - | O20: - | P20: - | Q20: - | R20: - | S20: - | T20: - | U20: - | V20: - | W20: - | X20: - | Y20: - | Z20: - | AA20: - | AB20: - | AC20: - | AD20: - | AE20: -
A21: Other cost of services and sales (ex of D&A) | B21: 6339 | C21: 6412 | D21: 6351 | E21: 6322 | F21: 25424 | G21: 6261 | H21: 6306 | I21: 6273.22 | J21: 6783.43 | K21: 25623.65 | L21: 6541.89 | M21: 6444.22 | N21: 6446.34 | O21: 7138.51 | P21: 25880.2 | Q21: 6665.37 | R21: 6672.95 | S21: 6817.33 | T21: 6819.51 | U21: 25736.19 | V21: 6551.01 | W21: 6565.39 | X21: 6833.35 | Y21: 6822.39 | Z21: 25681.39 | AA21: 6727.24 | AB21: 6741.99 | AC21: 7018.16 | AD21: 7000.74 | AE21: 26202.07
A22: Cost of sales - as reported | B22: 12033 | C22: 12150 | D22: 11819 | E22: 14818 | F22: 50820 | G22: 12566 | H22: 12047 | I22: 12452.47 | J22: 15089 | K22: 52154.47 | L22: 13105.93 | M22: 12802.74 | N22: 13023.69 | O22: 15364.61 | P22: 53619.25 | Q22: 13259.17 | R22: 12519.99 | S22: 12774.19 | T22: 16156.82 | U22: 52093.5 | V22: 12924.76 | W22: 12350.29 | X22: 12600.14 | Y22: 15961.54 | Z22: 52047.94 | AA22: 13079.47 | AB22: 12499.38 | AC22: 12764.02 | AD22: 16107.68 | AE22: 52850.97
A23: Selling, general and administrative | B23: 7145 | C23: 6945 | D23: 7454 | E23: 7398 | F23: 28942 | G23: 7316 | H23: 7221 | I23: 6765.75 | J23: 7653.54 | K23: 28956.3 | L23: 6707.95 | M23: 6679.13 | N23: 6570.44 | O23: 7579.45 | P23: 27841.23 | Q23: 6723.6 | R23: 6827.15 | S23: 6715.83 | T23: 7021.88 | U23: 29362.9 | V23: 7145.06 | W23: 7261.51 | X23: 7036.28 | Y23: 7381.94 | Z23: 30838.56 | AA23: 7092.18 | AB23: 7186.51 | AC23: 6945.25 | AD23: 7325.31 | AE23: 31119.14
A24: Asset abandonments and Impairment Charges | B24: 504 | C24: - | D24: - | E24: 334 | F24: 838 | G24: - | H24: 286 | I24: - | J24: - | K24: 286 | L24: - | M24: - | N24: - | O24: - | P24: - | Q24: - | R24: - | S24: - | T24: - | U24: - | V24: - | W24: - | X24: - | Y24: - | Z24: - | AA24: - | AB24: - | AC24: - | AD24: - | AE24: -
A25: Operations and support | B25: 19178 | C25: 19095 | D25: 19273 | E25: 22550 | F25: 80600 | G25: 19882 | H25: 19554 | I25: 19301.39 | J25: 22825.63 | K25: 81467.69 | L25: 19949.35 | M25: 19564.71 | N25: 19653.94 | O25: 23126.5 | P25: 81986.96 | Q25: 19950.66 | R25: 19511.28 | S25: 19678.8 | T25: 23367.68 | U25: 82218.03 | V25: 20278.15 | W25: 19912.19 | X25: 20153.69 | Y25: 23994.39 | Z25: 84002.91 | AA25: 20487.78 | AB25: 20149.55 | AC25: 20421.3 | AD25: 24314.61 | AE25: 85196.02
A26: Integration cost & other adjustments | B26: 589 | C26: -21 | D26: 425 | E26: 320 | F26: 1313 | G26: 171 | H26: 334 | I26: -86.36 | J26: -95.4 | K26: 379.25 | L26: -97.33 | M26: -118.58 | N26: 84.14 | O26: -19.34 | P26: -505.31 | Q26: 50 | R26: 50 | S26: 50 | T26: 50 | U26: -563.33 | V26: 50 | W26: 50 | X26: 50 | Y26: 50 | Z26: 450 | AA26: 50 | AB26: 50 | AC26: 50 | AD26: 50 | AE26: 450
A27: Operations and support - Operating | B27: 19093 | C27: 19116 | D27: 18848 | E27: 22230 | F27: 79287 | G27: 19711 | H27: 19220 | I27: 19342.03 | J27: 22767.03 | K27: 81058.45 | L27: 19953.36 | M27: 19518.24 | N27: 19550.8 | O27: 23056.69 | P27: 82009.43 | Q27: 19904.8 | R27: 19415.49 | S27: 19532.67 | T27: 23265.57 | U27: 82325.42 | V27: 20088.71 | W27: 19628.66 | X27: 19745.78 | Y27: 23583.42 | Z27: 83339.49 | AA27: 20276.71 | AB27: 19838.8 | AC27: 19998.71 | AD27: 23892.4 | AE27: 84538.59
A28: Depreciation and amortization expense | B28: 5190 | C28: 5251 | D28: 5317 | E28: 5128 | F28: 20886 | G28: 4966 | H28: 4966 | I28: 5101.72 | J28: 5171 | K28: 20214.92 | L28: 5052.15 | M28: 5070.41 | N28: 5116.95 | O28: 5201.93 | P28: 20425.33 | Q28: 5063.17 | R28: 5051.56 | S28: 5167.55 | T28: 5159.51 | U28: 20525.3 | V28: 5147.11 | W28: 5135.96 | X28: 5273.2 | Y28: 5244.16 | Z28: 20868.25 | AA28: 5223.84 | AB28: 5206.56 | AC28: 5350.3 | AD28: 5307.49 | AE28: 21098.74
A29: Amortization of intangible assets - Adjustment | B29: 9 | C29: 9 | D29: 10 | E29: 10 | F29: 38 | G29: 57 | H29: 84 | I29: 26.08 | J29: 24.92 | K29: 117 | L29: 43.22 | M29: 49.89 | N29: 29.11 | O29: 28.6 | P29: 4214.88 | Q29: 20.74 | R29: 29.38 | S29: 5.06 | T29: 5.06 | U29: 5270.1 | V29: 29.18 | W29: 43.01 | X29: 4.1 | Y29: 4.1 | Z29: 164.48 | AA29: 23.35 | AB29: 34.41 | AC29: 3.28 | AD29: 3.28 | AE29: 144.01
A30: Total Depreciation and Amortization - Operating | B30: 5190 | C30: 5251 | D30: 5307 | E30: 5118 | F30: 20848 | G30: 4909 | H30: 4966 | I30: 5067.91 | J30: 5121.46 | K30: 20111.33 | L30: 4995.19 | M30: 4982.79 | N30: 5088.67 | O30: 5144.54 | P30: 20348.35 | Q30: 4954.22 | R30: 4933.48 | S30: 5109.92 | T30: 5004.36 | U30: 20504.16 | V30: 5037.87 | W30: 5011.4 | X30: 5219.34 | Y30: 5057.41 | Z30: 21077.42 | AA30: 5100.97 | AB30: 5071.3 | AC30: 5278.67 | AD30: 5103.9 | AE30: 21390.02
A31: Total cost and expenses | B31: 24872 | C31: 24346 | D31: 24590 | E31: 27678 | F31: 101486 | G31: 24848 | H31: 24520 | I31: 24493.92 | J31: 28097.34 | K31: 101893.34 | L31: 25076.26 | M31: 24718.22 | N31: 24775.16 | O31: 28340.65 | P31: 102711.85 | Q31: 24989.25 | R31: 24546.2 | S31: 24818.17 | T31: 28454.67 | U31: 103053.39 | V31: 25387.03 | W31: 25017.05 | X31: 25397.13 | Y31: 29142.56 | Z31: 104968.45 | AA31: 25666.69 | AB31: 25320.32 | AC31: 25731.95 | AD31: 29520.6 | AE31: 106468.69
A32: Total cost and expenses - Operating | B32: 24283 | C32: 24367 | D32: 24165 | E32: 27348 | F32: 100135 | G32: 24620 | H32: 24102 | I32: 24422.04 | J32: 27859.74 | K32: 101132.3 | L32: 25071.87 | M32: 24581.09 | N32: 24683.68 | O32: 28368.8 | P32: 100257.72 | Q32: 25051.29 | R32: 24421.89 | S32: 24898.66 | T32: 28415.77 | U32: 101086.2 | V32: 25722.93 | W32: 24820.27 | X32: 25567.69 | Y32: 29211.87 | Z32: 105689.93 | AA32: 26027.53 | AB32: 25068.17 | AC32: 25880.46 | AD32: 29573.12 | AE32: 107349.61
A33: EBITDA | B33: 10944 | C33: 11752 | D33: 11436 | E33: 10916 | F33: 45048 | G33: 11624 | H33: 12004 | I33: 12306.16 | J33: 11668.56 | K33: 47751.02 | L33: 12242.29 | M33: 12716.43 | N33: 12852.44 | O33: 12011.22 | P33: 49908.58 | Q33: 12861.29 | R33: 13224.58 | S33: 13349.44 | T33: 12749.42 | U33: 52313.74 | V33: 13390.49 | W33: 13860.84 | X33: 13976.21 | Y33: 13038.01 | Z33: 54455.61 | AA33: 14051.74 | AB33: 14501.35 | AC33: 14632.17 | AD33: 13936.81 | AE33: 56996.15
A34: EBITDA - Corporate and other or Eliminations adjustments | B34: 589 | C34: -21 | D34: 425 | E34: 320 | F34: 1313 | G34: 171 | H34: 334 | I34: 69.19 | J34: 208.81 | K34: 583.61 | L34: 65.65 | M34: 91.49 | N34: 61.99 | O34: 332.49 | P34: 464.18 | Q34: 118.41 | R34: 118.43 | S34: 118.27 | T34: 117.9 | U34: 429.2 | V34: 75 | W34: 75 | X34: 75 | Y34: 775 | Z34: 681.75 | AA34: 75 | AB34: 75 | AC34: 75 | AD34: 75 | AE34: 331.75
A35: EBITDA - Operating | B35: 11533 | C35: 11731 | D35: 11861 | E35: 11236 | F35: 46361 | G35: 11795 | H35: 12338 | I35: 12325.8 | J35: 11732.12 | K35: 48163.77 | L35: 12249.29 | M35: 12734.22 | N35: 12871.66 | O35: 12199.23 | P35: 50045.84 | Q35: 12912.04 | R35: 13275.33 | S35: 13400.12 | T35: 12799.95 | U35: 52390.05 | V35: 13420.49 | W35: 13890.84 | X35: 14006.21 | Y35: 13348.01 | Z35: 54669.92 | AA35: 14081.74 | AB35: 14531.35 | AC35: 14662.17 | AD35: 13966.81 | AE35: 57157.53
A36: Operating income/(loss) | B36: 5754 | C36: 6501 | D36: 6119 | E36: 5788 | F36: 24162 | G36: 6658 | H36: 7038 | I36: 7188.82 | J36: 6489.34 | K36: 27412.86 | L36: 7168.23 | M36: 7642.17 | N36: 7726.89 | O36: 6886.41 | P36: 29443.98 | Q36: 7798.12 | R36: 8173.02 | S36: 8181.89 | T36: 7589.91 | U36: 31708.81 | V36: 8243.38 | W36: 8724.88 | X36: 8703.01 | Y36: 7793.84 | Z36: 33522.51 | AA36: 8827.9 | AB36: 9294.79 | AC36: 9281.87 | AD36: 8629.32 | AE36: 35856.34
... A50: Income From Continuing Operations | B50: 4692 | C50: 4861 | D50: 9677 | E50: 4156 | F50: 23386 | G50: 4219 | H50: 5038 | I50: 4499.28 | J50: 3899.12 | K50: 17607.56 | L50: 4408.64 | M50: 4862.28 | N50: 4850.2 | O50: 4138.34 | P50: 18289.87 | Q50: 4874.44 | R50: 5236.46 | S50: 5195.93 | T50: 4748.65 | U50: 19854.49 | V50: 5321.4 | W50: 5686.98 | X50: 5696.59 | Y50: 4996.1 | Z50: 21234.82 | AA50: 5838.08 | AB50: 6194.94 | AC50: 6205.71 | AD50: 5719.98 | AE50: 23237.76
A51: Income/(loss) from discontinued ops | B51: 90 | C51: - | D51: - | E51: 1 | F51: 45.5 | G51: -38 | H51: -28 | I51: -29 | J51: -29 | K51: -72 | L51: -28 | M51: -28 | N51: -28 | O51: -28 | P51: -112 | Q51: - | R51: - | S51: - | T51: - | U51: -112 | V51: - | W51: - | X51: - | Y51: - | Z51: -112 | AA51: - | AB51: - | AC51: - | AD51: - | AE51: -112
A52: Net income attributable to noncontrolling interest | B52: 341 | C52: 361 | D52: 363 | E52: 368 | F52: 1433 | G52: 352 | H52: 383 | I52: 362.95 | J52: 367.65 | K52: 1466.83 | L52: 349.99 | M52: 361.82 | N52: 358.21 | O52: 357.53 | P52: 1436.39 | Q52: 347.04 | R52: 354.57 | S52: 351.26 | T52: 350.43 | U52: 1448.79 | V52: 345.96 | W52: 356.83 | X52: 352.9 | Y52: 351.54 | Z52: 1460.62 | AA52: 353.69 | AB52: 365.13 | AC52: 361.32 | AD52: 360.48 | AE52: 1482.26
A53: Net income attributable to AT&T | B53: 4351 | C53: 4500 | D53: 9314 | E53: 3788 | F53: 21953 | G53: 3829 | H53: 4627 | I53: 4136.72 | J53: 3526.48 | K53: 16095.93 | L53: 4060.92 | M53: 4520.66 | N53: 4489.66 | O53: 3778.47 | P53: 16877.4 | Q53: 4527.41 | R53: 4881.89 | S53: 4844.67 | T53: 4398.22 | U53: 18429.1 | V53: 4975.44 | W53: 5330.16 | X53: 5343.68 | Y53: 4644.56 | Z53: 19766.9 | AA53: 5484.39 | AB53: 5829.81 | AC53: 5844.39 | AD53: 5359.51 | AE53: 21746.4
A54: Preferred dividend | B54: -44 | C54: 36 | D54: 36 | E54: 36 | F54: 64 | G54: 36 | H54: 36 | I54: 36.85 | J54: 36.85 | K54: 139.47 | L54: 37.52 | M54: 37.52 | N54: 39.86 | O54: 39.86 | P54: 150.67 | Q54: 40.54 | R54: 40.54 | S54: 40.54 | T54: 40.54 | U54: 154.84 | V54: 41.56 | W54: 41.56 | X54: 41.56 | Y54: 41.56 | Z54: 155.28 | AA54: 41.56 | AB54: 41.56 | AC54: 41.56 | AD54: 41.56 | AE54: 155.28
A55: Net income attributable to common shareholder | B55: 4395 | C55: 4464 | D55: 9278 | E55: 3752 | F55: 21889 | G55: 3793 | H55: 4591 | I55: 4086.81 | J55: 3495.38 | K55: 15952.55 | L55: 4030.84 | M55: 4476.47 | N55: 4458.04 | O55: 3754.45 | P55: 16651.56 | Q55: 4486.87 | R55: 4841.35 | S55: 4804.13 | T55: 4357.68 | U55: 18153.07 | V55: 4933.88 | W55: 5288.6 | X55: 5302.13 | Y55: 4603 | Z55: 19535.2 | AA55: 5442.84 | AB55: 5788.25 | AC55: 5802.83 | AD55: 5317.95 | AE55: 21502.72
A56: Net income/(loss) - Adjustments | B56: -686 | C56: -536 | D56: -5387 | E56: -59 | F56: -6668 | G56: 197 | H56: -117 | I56: 7.15 | J56: 14.04 | K56: 77.63 | L56: 29.06 | M56: 36.03 | N56: 28.45 | O56: 37.87 | P56: 118.15 | Q56: 24.51 | R56: 35.98 | S56: 3.7 | T56: 3.7 | U56: -6.67 | V56: 15.43 | W56: 26 | X56: -3.75 | Y56: -3.75 | Z56: -27.72 | AA56: 10.06 | AB56: 14.93 | AC56: -7.81 | AD56: -7.81 | AE56: -35.23
A57: Preferred stock redemption gain | B57: -90 | C57: - | D57: - | E57: - | F57: -90 | G57: - | H57: - | I57: - | J57: - | K57: - | L57: - | M57: - | N57: - | O57: - | P57: - | Q57: - | R57: - | S57: - | T57: - | U57: - | V57: - | W57: - | X57: - | Y57: - | Z57: - | AA57: - | AB57: - | AC57: - | AD57: - | AE57: -
A58: Net income/(loss) - Operating | B58: 3709 | C58: 3928 | D58: 3891 | E58: 3693 | F58: 15221 | G58: 3990 | H58: 4474 | I58: 4135.17 | J58: 3596.42 | K58: 16161.81 | L58: 4056.76 | M58: 4549.93 | N58: 4469.41 | O58: 3938.85 | P58: 16915.79 | Q58: 4524.43 | R58: 4944.55 | S58: 4856.46 | T58: 4420.04 | U58: 18360.41 | V58: 5012.65 | W58: 5380.88 | X58: 5327.57 | Y58: 4864.02 | Z58: 19834.15 | AA58: 5550.66 | AB58: 5916.78 | AC58: 5871.83 | AD58: 5406.11 | AE58: 21833.97
A59: Basic EPS($) | B59: 0.61 | C59: 0.62 | D59: 1.3 | E59: 0.53 | F59: 3.05 | G59: 0.54 | H59: 0.66 | I59: 0.59 | J59: 0.52 | K59: 2.31 | L59: 0.61 | M59: 0.67 | N59: 0.67 | O59: 0.58 | P59: 2.52 | Q59: 0.71 | R59: 0.76 | S59: 0.77 | T59: 0.71 | U59: 2.86 | V59: 0.83 | W59: 0.87 | X59: 0.9 | Y59: 0.79 | Z59: 3.18 | AA59: 0.96 | AB59: 0.99 | AC59: 1.03 | AD59: 0.97 | AE59: 3.64
A60: Basic EPS - operating($) | B60: 0.51 | C60: 0.54 | D60: 0.54 | E60: 0.52 | F60: 2.12 | G60: 0.57 | H60: 0.65 | I60: 0.6 | J60: 0.54 | K60: 2.34 | L60: 0.61 | M60: 0.68 | N60: 0.68 | O60: 0.61 | P60: 2.56 | Q60: 0.73 | R60: 0.78 | S60: 0.78 | T60: 0.73 | U60: 2.91 | V60: 0.86 | W60: 0.89 | X60: 0.91 | Y60: 0.85 | Z60: 3.24 | AA60: 1 | AB60: 1.02 | AC60: 1.06 | AD60: 1 | AE60: 3.72
A61: Diluted EPS($) | B61: 0.61 | C61: 0.62 | D61: 1.29 | E61: 0.53 | F61: 3.05 | G61: 0.54 | H61: 0.66 | I61: 0.6 | J61: 0.53 | K61: 2.33 | L61: 0.61 | M61: 0.68 | N61: 0.69 | O61: 0.59 | P61: 2.55 | Q61: 0.7 | R61: 0.77 | S61: 0.77 | T61: 0.71 | U61: 2.91 | V61: 0.81 | W61: 0.88 | X61: 0.89 | Y61: 0.78 | Z61: 3.25 | AA61: 0.93 | AB61: 1 | AC61: 1.02 | AD61: 0.94 | AE61: 3.72
A62: Diluted EPS - Operating($) | B62: 0.51 | C62: 0.54 | D62: 0.54 | E62: 0.52 | F62: 2.12 | G62: 0.57 | H62: 0.65 | I62: 0.6 | J62: 0.53 | K62: 2.35 | L62: 0.61 | M62: 0.68 | N62: 0.69 | O62: 0.61 | P62: 2.57 | Q62: 0.71 | R62: 0.78 | S62: 0.78 | T62: 0.71 | U62: 2.91 | V62: 0.82 | W62: 0.89 | X62: 0.89 | Y62: 0.84 | Z62: 3.28 | AA62: 0.94 | AB62: 1.01 | AC62: 1.02 | AD62: 0.94 | AE62: 3.75
A63: Basic shares(M#) | B63: 7213 | C63: 7209 | D63: 7156 | E63: 7098 | F63: 7169 | G63: 7017 | H63: 6938 | I63: 6841.93 | J63: 6741.83 | K63: 6883.3 | L63: 6658.86 | M63: 6586.67 | N63: 6515.65 | O63: 6444.79 | P63: 6566.05 | Q63: 6393.51 | R63: 6331.72 | S63: 6270.77 | T63: 6210.64 | U63: 6322.19 | V63: 6135.58 | W63: 6069.1 | X63: 6003.92 | Y63: 5940.02 | Z63: 6098.36 | AA63: 5877.38 | AB63: 5815.97 | AC63: 5755.78 | AD63: 5696.77 | AE63: 5866.78
A64: Diluted shares(M#) | B64: 7223 | C64: 7219 | D64: 7169 | E64: 7108 | F64: 7179.75 | G64: 7027 | H64: 6946 | I64: 6846.15 | J64: 6747.38 | K64: 6881.37 | L64: 6662.66 | M64: 6589.06 | N64: 6516.89 | O64: 6444.83 | P64: 6569.89 | Q64: 6358.91 | R64: 6295.24 | S64: 6232.56 | T64: 6170.85 | U64: 6303.07 | V64: 6079.38 | W64: 6015.86 | X64: 5953.7 | Y64: 5889.58 | Z64: 6039.08 | AA64: 5823.75 | AB64: 5759.2 | AC64: 5698.92 | AD64: 5639.87 | AE64: 5777.97
A65: Dividends per share($) | B65: 0.28 | C65: 0.28 | D65: 0.28 | E65: 0.28 | F65: 1.11 | G65: 0.28 | H65: 0.28 | I65: 0.28 | J65: 0.28 | K65: 1.11 | L65: 0.28 | M65: 0.28 | N65: 0.28 | O65: 0.28 | P65: 1.11 | Q65: 0.28 | R65: 0.28 | S65: 0.28 | T65: 0.28 | U65: 1.12 | V65: 0.28 | W65: 0.28 | X65: 0.28 | Y65: 0.28 | Z65: 1.13 | AA65: 0.28 | AB65: 0.28 | AC65: 0.28 | AD65: 0.29 | AE65: 1.14
A67: Supplemental
A68: Diluted EPS under ASU 2020-06($) | B68: 0.61 | C68: 0.62 | D68: 1.29 | E68: 0.53 | F68: 3.05 | G68: 0.54 | H68: 0.66 | I68: 0.59 | J68: 0.51 | K68: 2.3 | L68: 0.61 | M68: 0.67 | N68: 0.67 | O68: 0.59 | P68: 2.51 | Q68: 0.73 | R68: 0.78 | S68: 0.79 | T68: 0.71 | U68: 2.85 | V68: 0.85 | W68: 0.92 | X68: 0.92 | Y68: 0.83 | Z68: 3.21 | AA68: 0.98 | AB68: 1.06 | AC68: 1.05 | AD68: 0.95 | AE68: 3.66
A69: Diluted EPS under ASU 2020-06 - Operating($) | B69: 0.51 | C69: 0.54 | D69: 0.59 | E69: 0.52 | F69: 2.12 | G69: 0.57 | H69: 0.64 | I69: 0.61 | J69: 0.53 | K69: 2.35 | L69: 0.61 | M69: 0.71 | N69: 0.7 | O69: 0.62 | P69: 2.55 | Q69: 0.74 | R69: 0.81 | S69: 0.81 | T69: 0.72 | U69: 2.92 | V69: 0.85 | W69: 0.92 | X69: 0.92 | Y69: 0.83 | Z69: 3.33 | AA69: 0.98 | AB69: 1.06 | AC69: 1.05 | AD69: 0.95 | AE69: 3.84
A70: Diluted EPS under historical - Operating($) | B70: 0.51 | C70: 0.54 | D70: 0.54 | E70: 0.52 | F70: 2.12 | G70: 0.57 | H70: 0.65 | I70: 0.59 | J70: 0.48 | K70: 2.29 | L70: 0.65 | M70: 0.66 | N70: 0.68 | O70: 0.56 | P70: 2.55 | Q70: - | R70: - | S70: - | T70: - | U70: 2.83 | V70: - | W70: - | X70: - | Y70: - | Z70: 3.05 | AA70: - | AB70: - | AC70: - | AD70: - | AE70: 3.32
A71: Diluted shares under ASU 2020-06(M#) | B71: 7223 | C71: 7219 | D71: 7169 | E71: 7108 | F71: 7179.75 | G71: 7027 | H71: 6946 | I71: 6846.16 | J71: 6738.87 | K71: 6889.51 | L71: 6642.55 | M71: 6559.25 | N71: 6477.56 | O71: 6397.31 | P71: 6562.53 | Q71: 6261.88 | R71: 6192.2 | S71: 6123.68 | T71: 6056.29 | U71: 6296.26 | V71: 5894.42 | W71: 5832.61 | X71: 5772.29 | Y71: 5705.21 | Z71: 6049.43 | AA71: 5632.06 | AB71: 5560.33 | AC71: 5497.51 | AD71: 5436.03 | AE71: 5820.57

Sheet Cash Flow
A2: AT&T Inc. | Cash flow
A3: NYSE:T (MI KEY: 4024242; SPCIQ KEY: 100231)
A5: Visible Alpha
A7: Period Type : Fiscal Quarter, Fiscal Halves, Fiscal Year
A8: Period Start : 2025
A9: Period End : 2030
A10: Currency : Reported
A11: Consensus View : Mean
A12: As Of: 10/20/2026
A14: All numbers in $M unless otherwise indicated | B14: FQ1 2025A | C14: FQ2 2025A | D14: FQ3 2025A | E14: FQ4 2025A | F14: FY2025A | G14: FQ1 2026A | H14: FQ2 2026A | I14: FQ3 2026E | J14: FQ4 2026E | K14: FY2026E | L14: FQ1 2027E | M14: FQ2 2027E | N14: FQ3 2027E | O14: FQ4 2027E | P14: FY2027E | Q14: FQ1 2028E | R14: FQ2 2028E | S14: FQ3 2028E | T14: FQ4 2028E | U14: FY2028E | V14: FQ1 2029E | W14: FQ2 2029E | X14: FQ3 2029E | Y14: FQ4 2029E | Z14: FY2029E | AA14: FQ1 2030E | AB14: FQ2 2030E | AC14: FQ3 2030E | AD14: FQ4 2030E | AE14: FY2030E
A15: Number of Contributors Available | B15: 19 | C15: 19 | D15: 19 | E15: 19 | F15: 20 | G15: 19 | H15: 19 | I15: 20 of 20 | J15: 20 of 20 | K15: 20 of 20 | L15: 14 of 20 | M15: 14 of 20 | N15: 13 of 20 | O15: 13 of 20 | P15: 20 of 20 | Q15: 7 of 20 | R15: 7 of 20 | S15: 7 of 20 | T15: 7 of 20 | U15: 17 of 20 | V15: 5 of 20 | W15: 5 of 20 | X15: 5 of 20 | Y15: 5 of 20 | Z15: 14 of 20 | AA15: 5 of 20 | AB15: 5 of 20 | AC15: 5 of 20 | AD15: 5 of 20 | AE15: 14 of 20
A16: Net income | B16: 4692 | C16: 4861 | D16: 9677 | E16: 4156 | F16: 23386 | G16: 4219 | H16: 5038 | I16: 4406.37 | J16: 3785.31 | K16: 17406.65 | L16: 4384.82 | M16: 4841.97 | N16: 4814.61 | O16: 4070.42 | P16: 18033.47 | Q16: 4874.44 | R16: 5236.46 | S16: 5195.93 | T16: 4748.65 | U16: 19725.56 | V16: 5321.4 | W16: 5686.98 | X16: 5696.59 | Y16: 4996.1 | Z16: 21184.5 | AA16: 5838.08 | AB16: 6194.94 | AC16: 6205.71 | AD16: 5719.98 | AE16: 23228.88
A17: Depreciation and amortization | B17: 5190 | C17: 5251 | D17: 5317 | E17: 5128 | F17: 20886 | G17: 4966 | H17: 4966 | I17: 5063.36 | J17: 5131.84 | K17: 20192.49 | L17: 5044.06 | M17: 5042.7 | N17: 5125.05 | O17: 5176.29 | P17: 20342.64 | Q17: 5063.17 | R17: 5051.56 | S17: 5167.55 | T17: 5159.51 | U17: 20473.75 | V17: 5147.11 | W17: 5135.96 | X17: 5273.2 | Y17: 5244.16 | Z17: 20809.45 | AA17: 5223.84 | AB17: 5206.56 | AC17: 5350.3 | AD17: 5307.49 | AE17: 21044.54
A18: Undistributed earnings from investments in equity affiliates | B18: 81 | C18: -112 | D18: -5691 | E18: -167 | F18: -5889 | G18: 28 | H18: -198 | I18: - | J18: - | K18: -170 | L18: - | M18: - | N18: - | O18: - | P18: -170 | Q18: - | R18: - | S18: - | T18: - | U18: -170 | V18: - | W18: - | X18: - | Y18: - | Z18: -170 | AA18: - | AB18: - | AC18: - | AD18: - | AE18: -170
A19: Provision or uncollectible accounts | B19: 516 | C19: 521 | D19: 555 | E19: 679 | F19: 2271 | G19: 560 | H19: 589 | I19: 588.97 | J19: 632.38 | K19: 2283.82 | L19: 566.03 | M19: 572.02 | N19: 566.88 | O19: 600.16 | P19: 2298.11 | Q19: 569.28 | R19: 577.11 | S19: 570.45 | T19: 607.49 | U19: 2323.65 | V19: 586.91 | W19: 598.87 | X19: 589.26 | Y19: 640.45 | Z19: 2384.18 | AA19: 596.4 | AB19: 608.41 | AC19: 599.53 | AD19: 650.67 | AE19: 2423.44
A20: Deferred income tax expense | B20: 1285 | C20: 378 | D20: 946 | E20: -383 | F20: 2226 | G20: 1147 | H20: 682 | I20: 821.86 | J20: 638.38 | K20: 3036.69 | L20: 908.21 | M20: 771.71 | N20: 1102.31 | O20: 593.05 | P20: 3244.01 | Q20: 859.73 | R20: 624.06 | S20: 1155.07 | T20: 663.05 | U20: 3397.52 | V20: 748.92 | W20: 357.6 | X20: 795.37 | Y20: 491.19 | Z20: 2971.9 | AA20: 730.62 | AB20: 168.11 | AC20: 769.92 | AD20: 456.75 | AE20: 2594.89
A21: Amortization of intangibles | B21: - | C21: - | D21: - | E21: - | F21: - | G21: - | H21: - | I21: - | J21: - | K21: - | L21: - | M21: - | N21: - | O21: - | P21: - | Q21: - | R21: - | S21: - | T21: - | U21: - | V21: - | W21: - | X21: - | Y21: - | Z21: - | AA21: - | AB21: - | AC21: - | AD21: - | AE21: -
A22: Gain on sale of investments | B22: 81 | C22: -112 | D22: -5691 | E22: -167 | F22: -5889 | G22: 28 | H22: -198 | I22: -198 | J22: -198 | K22: -219.5 | L22: -198 | M22: -198 | N22: -198 | O22: -198 | P22: -792 | Q22: -198 | R22: -198 | S22: -198 | T22: -198 | U22: -792 | V22: - | W22: - | X22: - | Y22: - | Z22: - | AA22: - | AB22: - | AC22: - | AD22: - | AE22: -
A23: Change in accounts receivable | B23: 15 | C23: -262 | D23: -366 | E23: -913 | F23: -1526 | G23: -119 | H23: -299 | I23: -343.27 | J23: -533.63 | K23: -1250.55 | L23: 160.78 | M23: -307.21 | N23: -130.02 | O23: -779.61 | P23: -1118.99 | Q23: 276.39 | R23: -233.58 | S23: -21.08 | T23: -693.48 | U23: -1130.79 | V23: 931.29 | W23: -291.9 | X23: 0.79 | Y23: -907.6 | Z23: -995.56 | AA23: 937.71 | AB23: -287.31 | AC23: 15.41 | AD23: -919.19 | AE23: -1130.65
A24: Change in total other current assets | B24: 404 | C24: 95 | D24: -2127 | E24: 284 | F24: -1344 | G24: -245 | H24: -75 | I24: -291.08 | J24: 1333.87 | K24: 546.57 | L24: -1970.39 | M24: 503.32 | N24: -459.23 | O24: 1155.76 | P24: -323.59 | Q24: -2021.13 | R24: 535.82 | S24: -580.51 | T24: 1559.92 | U24: -185.72 | V24: -3167.56 | W24: 643.32 | X24: -794.45 | Y24: 2073.41 | Z24: -763.66 | AA24: -3557.72 | AB24: 716.88 | AC24: -1094.16 | AD24: 2160.23 | AE24: -1102.54
A25: Change in accounts payable and accrued liabilities | B25: -3297 | C25: -1143 | D25: 2411 | E25: 2913 | F25: 884 | G25: -2770 | H25: 205 | I25: 274.77 | J25: 1737.44 | K25: -720.89 | L25: -1394.11 | M25: -46.09 | N25: 287.53 | O25: 2074.94 | P25: 769.69 | Q25: -1498.47 | R25: -196.27 | S25: 548.24 | T25: 1583.93 | U25: 264.88 | V25: -732.8 | W25: -113.72 | X25: 738.15 | Y25: 1338.66 | Z25: 1069.69 | AA25: -543.56 | AB25: -153.34 | AC25: 934.79 | AD25: 1410.01 | AE25: 1334.42
A26: Change in income taxes | B26: 1285 | C26: 378 | D26: 946 | E26: -383 | F26: 2226 | G26: 1147 | H26: 682 | I26: 905.87 | J26: 745.88 | K26: 3480.75 | L26: - | M26: - | N26: - | O26: - | P26: 3956.48 | Q26: - | R26: - | S26: - | T26: - | U26: 4203.28 | V26: - | W26: - | X26: - | Y26: - | Z26: 3510.42 | AA26: - | AB26: - | AC26: - | AD26: - | AE26: 2277
A27: Change in operating assets/liabilities | B27: -2878 | C27: -1310 | D27: -82 | E27: 2284 | F27: -1986 | G27: -3134 | H27: -169 | I27: -270.49 | J27: 2951.44 | K27: -548 | L27: -2994.38 | M27: -47.18 | N27: -0.45 | O27: 2587.65 | P27: -176.71 | Q27: -2795.91 | R27: 70.05 | S27: -27.04 | T27: 2242.83 | U27: -316.86 | V27: -2803.81 | W27: 241.71 | X27: -11.82 | Y27: 2472.79 | Z27: -155.95 | AA27: -2957.8 | AB27: 272.3 | AC27: -83.98 | AD27: 2589.66 | AE27: -440.07
A28: Total other operating activities | B28: 244 | C28: 62 | D28: -570 | E28: -377 | F28: -610 | G28: -191 | H28: -107 | I28: 102.79 | J28: -35.58 | K28: -329.67 | L28: 157.01 | M28: -77.43 | N28: -103.04 | O28: -326.6 | P28: -455.19 | Q28: 356.19 | R28: 38.94 | S28: -197.11 | T28: -107.5 | U28: -155.01 | V28: 327.34 | W28: -70.28 | X28: -494.9 | Y28: -542.52 | Z28: -712.63 | AA28: 463.37 | AB28: -119.24 | AC28: -553.49 | AD28: -631.77 | AE28: -745.52
A29: Net Cash Flows Provided By/(Used In) Operating Activities-Continuing operations | B29: 9049 | C29: 9763 | D29: 10152 | E29: 11320 | F29: 40284 | G29: 7595 | H29: 10801 | I29: 10662.24 | J29: 12668.74 | K29: 41628.53 | L29: 7862.27 | M29: 10911.63 | N29: 11384.3 | O29: 12519.95 | P29: 42765.01 | Q29: 8775.81 | R29: 11480.74 | S29: 11836.56 | T29: 13191.02 | U29: 44987.26 | V29: 9327.88 | W29: 11950.84 | X29: 11847.71 | Y29: 13302.18 | Z29: 46205.87 | AA29: 9894.52 | AB29: 12331.08 | AC29: 12287.98 | AD29: 14092.8 | AE29: 47685.86
A30: Net cash flows provided by/(used in) operating activities-Discontinued operations | B30: - | C30: - | D30: - | E30: - | F30: - | G30: -38 | H30: 69 | I30: -60 | J30: -25 | K30: 9.75 | L30: - | M30: - | N30: - | O30: - | P30: - | Q30: - | R30: - | S30: - | T30: - | U30: - | V30: - | W30: - | X30: - | Y30: - | Z30: - | AA30: - | AB30: - | AC30: - | AD30: - | AE30: -
A31: Net cash provided by (used in) operating activities | B31: 9049 | C31: 9763 | D31: 10152 | E31: 11320 | F31: 40284 | G31: 7595 | H31: 10801 | I31: 10667.33 | J31: 12543.94 | K31: 41598.36 | L31: 7731.49 | M31: 10932.44 | N31: 11411.38 | O31: 12578.61 | P31: 42772.68 | Q31: 8618.07 | R31: 11507.73 | S31: 11847.29 | T31: 13275.84 | U31: 44926.04 | V31: 9134.76 | W31: 12109.35 | X31: 12005.64 | Y31: 13603.38 | Z31: 45983.73 | AA31: 9733.67 | AB31: 12636.67 | AC31: 12440.36 | AD31: 14474.62 | AE31: 47492.33
A32: Purchase of property and equipment | B32: 4240 | C32: 4857 | D32: 4843 | E32: 6737 | F32: 20677 | G32: 4835 | H32: 5651 | I32: 5341.41 | J32: 6256.3 | K32: 22095.08 | L32: 5085.77 | M32: 5531.11 | N32: 5372.17 | O32: 5955.78 | P32: 21855.14 | Q32: 4875.48 | R32: 5468.8 | S32: 5208.01 | T32: 5879.41 | U32: 21552.69 | V32: 4968.91 | W32: 5508.8 | X32: 5352.51 | Y32: 5816.78 | Z32: 21674.27 | AA32: 5001.52 | AB32: 5543.34 | AC32: 5386.76 | AD32: 5860.02 | AE32: 21329.22
A33: Interest during construction | B33: 37 | C33: 40 | D33: 44 | E33: 44 | F33: 165 | G33: 42 | H33: 49 | I33: 40.81 | J33: 41.58 | K33: 173.39 | L33: 38.04 | M33: 40.5 | N33: 39.94 | O33: 40.82 | P33: 157.98 | Q33: 42.13 | R33: 45.63 | S33: 44.95 | T33: 46.25 | U33: 156.8 | V33: 43 | W33: 45.34 | X33: 44.97 | Y33: 46.71 | Z33: 153.01 | AA33: 43.14 | AB33: 45.5 | AC33: 45.12 | AD33: 46.89 | AE33: 153.39
A34: Total capital expenditures | B34: 4277 | C34: 4897 | D34: 4887 | E34: 6781 | F34: 20842 | G34: 4877 | H34: 5700 | I34: 5553.66 | J34: 6262.03 | K34: 22460.63 | L34: 4997.7 | M34: 5546.95 | N34: 5616.37 | O34: 6217.85 | P34: 22488.81 | Q34: 4840.45 | R34: 5488.73 | S34: 5606.05 | T34: 6124.59 | U34: 22309.68 | V34: 4958.76 | W34: 5618.59 | X34: 5604.87 | Y34: 5868.84 | Z34: 22208.62 | AA34: 4932.12 | AB34: 5598.78 | AC34: 5589.8 | AD34: 5848.85 | AE34: 21871.34
A35: Acquisitions, net of cash acquired | B35: -20 | C35: -28 | D35: 1 | E35: -332 | F35: -379 | G35: -2674 | H35: -51 | I35: -21180.58 | J35: -32.5 | K35: -23140.54 | L35: -173.75 | M35: -173.75 | N35: -3449.17 | O35: 550.83 | P35: -1967.69 | Q35: -147.88 | R35: -147.88 | S35: -147.88 | T35: -147.88 | U35: -8706.36 | V35: -117.69 | W35: -117.69 | X35: -1411.79 | Y35: -117.69 | Z35: -5047.66 | AA35: -92.5 | AB35: -92.5 | AC35: -92.5 | AD35: -1892.5 | AE35: -2065.6
A36: Dispositions | B36: 11 | C36: 29 | D36: 399 | E36: 2779 | F36: 3218 | G36: 628 | H36: 119 | I36: - | J36: 3000 | K36: 977.77 | L36: 100 | M36: 100 | N36: 100 | O36: 100 | P36: 250 | Q36: 100 | R36: 100 | S36: 100 | T36: 300 | U36: 450 | V36: 125 | W36: 125 | X36: 125 | Y36: 125 | Z36: 516.67 | AA36: - | AB36: - | AC36: - | AD36: - | AE36: 500
A37: Proceeds from short-term investments | B37: 45 | C37: -1129 | D37: 1109 | E37: 156 | F37: 181 | G37: -14 | H37: -10 | I37: -23000 | J37: - | K37: -3325 | L37: - | M37: - | N37: - | O37: - | P37: - | Q37: - | R37: - | S37: - | T37: - | U37: - | V37: - | W37: - | X37: - | Y37: - | Z37: - | AA37: - | AB37: - | AC37: - | AD37: - | AE37: -
A38: Other investing (excl. acquisition, disposition, purchase and all other) | B38: -672 | C38: -1190 | D38: -11 | E38: -166 | F38: -774 | G38: -547 | H38: -107 | I38: -242.75 | J38: 233.33 | K38: -635 | L38: 7.5 | M38: 7.5 | N38: 7.5 | O38: 7.5 | P38: 30 | Q38: 7.5 | R38: 7.5 | S38: 7.5 | T38: 7.5 | U38: -2125 | V38: 70 | W38: 70 | X38: 70 | Y38: 70 | Z38: -1075 | AA38: 70 | AB38: 70 | AC38: 70 | AD38: 70 | AE38: -2791.67
A39: Net Cash Flows Provided By/(Used In) Investing Activities-Continuing operations | B39: -4958 | C39: -6086 | D39: -3389 | E39: -4344 | F39: -18777 | G39: -7484 | H39: -5749 | I39: -25883.95 | J39: -6052.35 | K39: -46834.91 | L39: -5009.74 | M39: -5568.09 | N39: -6546.6 | O39: -6057.16 | P39: -23064.67 | Q39: -4866.27 | R39: -5514.55 | S39: -5631.87 | T39: -6078.98 | U39: -25415.75 | V39: -4952.83 | W39: -5612.66 | X39: -6398.95 | Y39: -5862.91 | Z39: -23980.55 | AA39: -4941.12 | AB39: -5607.78 | AC39: -5598.8 | AD39: -6577.85 | AE39: -23104.63
A40: Net cash flows provided by/(used in) investing activities-Discontinued operations | B40: - | C40: - | D40: - | E40: - | F40: - | G40: -4171 | H40: -192 | I40: -300 | J40: -100 | K40: -4496.33 | L40: - | M40: - | N40: - | O40: - | P40: - | Q40: - | R40: - | S40: - | T40: - | U40: - | V40: - | W40: - | X40: - | Y40: - | Z40: - | AA40: - | AB40: - | AC40: - | AD40: - | AE40: -
A41: Net cash provided by (used in) investing activities | B41: -4958 | C41: -6086 | D41: -3389 | E41: -4344 | F41: -18777 | G41: -7484 | H41: -5749 | I41: -26915.94 | J41: -6037.56 | K41: -49225.22 | L41: -4984.32 | M41: -5561.99 | N41: -6624.36 | O41: -6042.98 | P41: -23086.51 | Q41: -4866.27 | R41: -5514.55 | S41: -5631.87 | T41: -6078.98 | U41: -25757.58 | V41: -4952.83 | W41: -5612.66 | X41: -6398.95 | Y41: -5862.91 | Z41: -24203.6 | AA41: -4941.12 | AB41: -5607.78 | AC41: -5598.8 | AD41: -6577.85 | AE41: -23141.27
A42: Issuance of long-term debt | B42: 2956 | C42: 3473 | D42: 7598 | E42: - | F42: 14027 | G42: 8098 | H42: 5939 | I42: 9642.86 | J42: - | K42: 21238.41 | L42: 4000 | M42: 3000 | N42: - | O42: - | P42: 5500 | Q42: 4000 | R42: 2000 | S42: - | T42: - | U42: 14267.57 | V42: - | W42: - | X42: - | Y42: - | Z42: 7160.99 | AA42: 1000 | AB42: 1000 | AC42: - | AD42: - | AE42: 3946.38
A43: Repayment of long-term debt | B43: 1526 | C43: 94 | D43: 229 | E43: 3679 | F43: 5528 | G43: 5247 | H43: 151 | I43: 2191.95 | J43: 1880.5 | K43: 6124.74 | L43: 3054 | M43: 1833.33 | N43: 1812.33 | O43: 1348.67 | P43: 6715.5 | Q43: 4232 | R43: 2318 | S43: 2133 | T43: 2264.5 | U43: 7141.6 | V43: 3108 | W43: 180 | X43: 2742 | Y43: 1970 | Z43: 8104.27 | AA43: 4842 | AB43: 2087 | AC43: 2000 | AD43: 2594.5 | AE43: 8977.58
A44: Net change in long term debt | B44: 1430 | C44: 3379 | D44: 7369 | E44: -3679 | F44: 8499 | G44: 2851 | H44: 5788 | I44: 7627.84 | J44: -33.24 | K44: 13966.87 | L44: 680.31 | M44: -1125 | N44: -1445.6 | O44: -1868.01 | P44: -4113.05 | Q44: -488 | R44: -859.67 | S44: -1809.4 | T44: -1742.5 | U44: -1973.17 | V44: -2554 | W44: -1090 | X44: -2494.67 | Y44: -1485 | Z44: -5937.28 | AA44: -1947.33 | AB44: -1724.67 | AC44: -1500 | AD44: -1797.25 | AE44: -5960.91
A45: Net change in short term borrowings | B45: - | C45: - | D45: - | E45: - | F45: - | G45: - | H45: - | I45: 2105.69 | J45: -752.13 | K45: 12275.34 | L45: -349.45 | M45: -3161.76 | N45: -46.84 | O45: 5115.05 | P45: 4971.42 | Q45: - | R45: - | S45: - | T45: - | U45: 4978.48 | V45: - | W45: - | X45: - | Y45: - | Z45: 6490.19 | AA45: - | AB45: - | AC45: - | AD45: - | AE45: 375.77
A46: Change in total debt | B46: 1430 | C46: 3379 | D46: 7369 | E46: -3679 | F46: 8499 | G46: 2851 | H46: 5788 | I46: 7803.31 | J46: -153.05 | K46: 15720.49 | L46: 610.42 | M46: -1532.35 | N46: -1212.47 | O46: -1218.6 | P46: -3118.77 | Q46: -488 | R46: -859.67 | S46: -1809.4 | T46: -1742.5 | U46: -977.47 | V46: -2554 | W46: -1090 | X46: -2494.67 | Y46: -1485 | Z46: -4495.01 | AA46: -1947.33 | AB46: -1724.67 | AC46: -1500 | AD46: -1797.25 | AE46: -5919.16
A47: Proceeds from Issuance of equity | B47: 163 | C47: -419.83 | D47: 2 | E47: -63 | F47: 102 | G47: 1 | H47: -1105.2 | I47: -1257.15 | J47: -1319.51 | K47: -1982.44 | L47: -830.36 | M47: -833.38 | N47: -835.46 | O47: -837.18 | P47: -3124.92 | Q47: -1065.01 | R47: -1069.33 | S47: -1073.85 | T47: -1078.15 | U47: -3599.97 | V47: -1456.3 | W47: -1460.84 | X47: -1466.42 | Y47: -1470.59 | Z47: -4182.86 | AA47: -1474.33 | AB47: -1477.99 | AC47: -1483.25 | AD47: -1487.65 | AE47: -4238.96
A48: Purchase of treasury stock | B48: 218 | C48: 961 | D48: 1490 | E48: 1831 | F48: 4500 | G48: 2475 | H48: 2194 | I48: 2566.39 | J48: 2552.35 | K48: 9415.91 | L48: 2009 | M48: 1960.83 | N48: 2023.93 | O48: 2031.62 | P48: 7940.65 | Q48: 1760.34 | R48: 1771.65 | S48: 1783.21 | T48: 1795.02 | U48: 6973.95 | V48: 1875 | W48: 1562.5 | X48: 1875 | Y48: 1875 | Z48: 8351.17 | AA48: 2187.5 | AB48: 1875 | AC48: 1875 | AD48: 1875 | AE48: 8553.19
A49: Net change in shares and other | B49: -55 | C49: -961 | D49: -1488 | E49: -1894 | F49: -4398 | G49: -2474 | H49: -2194 | I49: -2621.89 | J49: -2682.82 | K49: -10477.91 | L49: -2157.34 | M49: -2112.04 | N49: -2167.69 | O49: -2192.53 | P49: -8502.6 | Q49: -1866.45 | R49: -1875.47 | S49: -1884.74 | T49: -1894.14 | U49: -7780.92 | V49: -2082.52 | W49: -1834.34 | X49: -2086.57 | Y49: -2088.24 | Z49: -8384.07 | AA49: -2339.73 | AB49: -2091.2 | AC49: -2093.3 | AD49: -2095.06 | AE49: -8455.47
A50: Dividends paid | B50: 2091 | C50: 2044 | D50: 2033 | E50: 2012 | F50: 8180 | G50: 1997 | H50: 1976 | I50: 1915.33 | J50: 1887.14 | K50: 7760.26 | L50: 1866.35 | M50: 1842.21 | N50: 1821.14 | O50: 1800.44 | P50: 7351.62 | Q50: 1787.33 | R50: 1768.88 | S50: 1750.41 | T50: 1741.88 | U50: 7110.7 | V50: 1744.64 | W50: 1723.76 | X50: 1706.2 | Y50: 1699.78 | Z50: 6919.41 | AA50: 1696.42 | AB50: 1675.47 | AC50: 1657.01 | AD50: 1651.26 | AE50: 6727.34
A51: Other financing activities | B51: 163 | C51: -419 | D51: -859 | E51: -1192 | F51: -2307 | G51: -477 | H51: -938 | I51: 419.11 | J51: -335.67 | K51: -830.13 | L51: -441.14 | M51: -488.21 | N51: -474.65 | O51: -471.61 | P51: -1319.83 | Q51: -586.73 | R51: -611.67 | S51: -595.36 | T51: -592.02 | U51: -1375.23 | V51: -497.42 | W51: -522.84 | X51: -505.45 | Y51: -502.06 | Z51: -649.44 | AA51: -494.97 | AB51: -517.88 | AC51: -502.22 | AD51: -499.18 | AE51: -1018.39
A52: Net Cash Flows Provided By/(Used In) Financing Activities-Continuing operations | B52: -553 | C52: -45 | D52: 2989 | E52: -8777 | F52: -6386 | G52: -2097 | H52: 680 | I52: 3309.21 | J52: -4642.85 | K52: -2156.74 | L52: -3875.28 | M52: -4956.96 | N52: -4943.53 | O52: -5045.72 | P52: -18663.6 | Q52: -4337.54 | R52: -4567.4 | S52: -5622.26 | T52: -5267.73 | U52: -16717.11 | V52: -5633.25 | W52: -4911.51 | X52: -6195.9 | Y52: -5478.08 | Z52: -19797.01 | AA52: -5699.52 | AB52: -5319.35 | AC52: -5452.53 | AD52: -5683.3 | AE52: -20970.77
A53: Net cash flows provided by/(used in) financing activities-Discontinued operations | B53: - | C53: - | D53: - | E53: - | F53: - | G53: - | H53: - | I53: - | J53: - | K53: -4171 | L53: - | M53: - | N53: - | O53: - | P53: - | Q53: - | R53: - | S53: - | T53: - | U53: - | V53: - | W53: - | X53: - | Y53: - | Z53: - | AA53: - | AB53: - | AC53: - | AD53: - | AE53: -
A54: Net cash provided by (used in) financing activities | B54: -553 | C54: -45 | D54: 2989 | E54: -8777 | F54: -6386 | G54: -2097 | H54: 680 | I54: 2069.14 | J54: -4777.46 | K54: -3759.74 | L54: -3837.95 | M54: -4983.97 | N54: -4983.46 | O54: -4839.41 | P54: -18714.27 | Q54: -4112.35 | R54: -4293.5 | S54: -5365.29 | T54: -5024.63 | U54: -16598.6 | V54: -5203.34 | W54: -4680 | X54: -5762.82 | Y54: -5374.89 | Z54: -19900.38 | AA54: -5651.26 | AB54: -5151.64 | AC54: -5341.61 | AD54: -5637.72 | AE54: -21182.59
A55: Cash provided from discontinued operations | B55: 49 | C55: -18 | D55: 21 | E55: -237 | F55: -185 | G55: -4209 | H55: -123 | I55: -360 | J55: -125 | K55: -4385 | L55: - | M55: - | N55: - | O55: - | P55: - | Q55: - | R55: - | S55: - | T55: - | U55: - | V55: - | W55: - | X55: - | Y55: - | Z55: - | AA55: - | AB55: - | AC55: - | AD55: - | AE55: -
A56: Net change in cash and cash equivalents | B56: 3538 | C56: 3632 | D56: 9752 | E56: -1801 | F56: 15121 | G56: -6195 | H56: 5609 | I56: -14735.38 | J56: 1841.98 | K56: -11478.61 | L56: -877.82 | M56: 468.23 | N56: -269.38 | O56: 2068.98 | P56: 1639.77 | Q56: -348.37 | R56: 1706.24 | S56: 1063.52 | T56: 2447.63 | U56: 3900.13 | V56: -854.35 | W56: 1737.69 | X56: 38.99 | Y56: 2598.19 | Z56: 3441.38 | AA56: -628.98 | AB56: 1751.14 | AC56: 1621.13 | AD56: 2463.78 | AE56: 4625.63
A57: Cash and cash equivalents beginning of year | B57: 3406 | C57: 6944 | D57: 10576 | E57: 20328 | F57: 3406 | G57: 18527 | H57: 12332 | I57: 18045.29 | J57: 4331.29 | K57: 18391.57 | L57: 6422.04 | M57: 5374.67 | N57: 6070.73 | O57: 7260.26 | P57: 6728.25 | Q57: 11393.87 | R57: 11005.26 | S57: 13063.43 | T57: 11625.41 | U57: 9574.1 | V57: 9831.7 | W57: 12082.51 | X57: 14332.62 | Y57: 14283.1 | Z57: 10512.81 | AA57: 17457.85 | AB57: 17561.23 | AC57: 19889.87 | AD57: 21303.36 | AE57: 15211.02
A58: Cash and cash equivalents end of period | B58: 6944 | C58: 10576 | D58: 20328 | E58: 18527 | F58: 18527 | G58: 12332 | H58: 17941 | I58: 4331.29 | J58: 6237.56 | K58: 7032.52 | L58: 5374.67 | M58: 6070.73 | N58: 7260.26 | O58: 8979.14 | P58: 9206.87 | Q58: 11005.26 | R58: 13063.43 | S58: 13923.13 | T58: 12148.06 | U58: 10719.72 | V58: 11989.36 | W58: 14237.2 | X58: 14184.89 | Y58: 17357.56 | Z58: 14332.83 | AA58: 17459.07 | AB58: 19785.87 | AC58: 21196.73 | AD58: 24532.06 | AE58: 19669.56
A60: Cash Paid for Capital Investment
A61: Purchase of property and equipment | B61: 4240 | C61: 4857 | D61: 4843 | E61: 6737 | F61: 20677 | G61: 4835 | H61: 5651 | I61: 5341.41 | J61: 6256.3 | K61: 22095.08 | L61: 5085.77 | M61: 5531.11 | N61: 5372.17 | O61: 5955.78 | P61: 21855.14 | Q61: 4875.48 | R61: 5468.8 | S61: 5208.01 | T61: 5879.41 | U61: 21552.69 | V61: 4968.91 | W61: 5508.8 | X61: 5352.51 | Y61: 5816.78 | Z61: 21674.27 | AA61: 5001.52 | AB61: 5543.34 | AC61: 5386.76 | AD61: 5860.02 | AE61: 21329.22
A62: Interest during construction | B62: 37 | C62: 40 | D62: 44 | E62: 44 | F62: 165 | G62: 42 | H62: 49 | I62: 40.81 | J62: 41.58 | K62: 173.39 | L62: 38.04 | M62: 40.5 | N62: 39.94 | O62: 40.82 | P62: 157.98 | Q62: 42.13 | R62: 45.63 | S62: 44.95 | T62: 46.25 | U62: 156.8 | V62: 43 | W62: 45.34 | X62: 44.97 | Y62: 46.71 | Z62: 153.01 | AA62: 43.14 | AB62: 45.5 | AC62: 45.12 | AD62: 46.89 | AE62: 153.39
A63: Total capital expenditures | B63: 4277 | C63: 4897 | D63: 4887 | E63: 6781 | F63: 20842 | G63: 4877 | H63: 5700 | I63: 5553.66 | J63: 6262.03 | K63: 22460.63 | L63: 4997.7 | M63: 5546.95 | N63: 5616.37 | O63: 6217.85 | P63: 22488.81 | Q63: 4840.45 | R63: 5488.73 | S63: 5606.05 | T63: 6124.59 | U63: 22309.68 | V63: 4958.76 | W63: 5618.59 | X63: 5604.87 | Y63: 5868.84 | Z63: 22208.62 | AA63: 4932.12 | AB63: 5598.78 | AC63: 5589.8 | AD63: 5848.85 | AE63: 21871.34
A64: Cash paid for vendor financing | B64: 203 | C64: 220 | D64: 400 | E64: 358 | F64: 1181 | G64: 212 | H64: 431 | I64: 295.02 | J64: 286.51 | K64: 1201.74 | L64: 292.56 | M64: 315.08 | N64: 303 | O64: 300.65 | P64: 1091.06 | Q64: 305.95 | R64: 325.98 | S64: 312.17 | T64: 309.48 | U64: 1117.57 | V64: 284.42 | W64: 309.65 | X64: 292.26 | Y64: 288.87 | Z64: 1145.48 | AA64: 281.98 | AB64: 304.69 | AC64: 289.03 | AD64: 285.98 | AE64: 1141.35
A65: Cash paid for capital investment | B65: 4480 | C65: 5117 | D65: 5287 | E65: 7139 | F65: 22023 | G65: 5089 | H65: 6131 | I65: 5839.69 | J65: 6550.91 | K65: 23660.41 | L65: 5221.48 | M65: 5852.89 | N65: 5922.42 | O65: 6529.64 | P65: 23544.72 | Q65: 5146.41 | R65: 5814.71 | S65: 5918.22 | T65: 6434.07 | U65: 23301.87 | V65: 5243.18 | W65: 5928.24 | X65: 5897.13 | Y65: 6157.71 | Z65: 23073.21 | AA65: 5214.1 | AB65: 5903.47 | AC65: 5878.83 | AD65: 6134.83 | AE65: 22717.65
A66: FirstNet reimbursement | B66: - | C66: - | D66: - | E66: - | F66: - | G66: - | H66: - | I66: - | J66: - | K66: - | L66: - | M66: - | N66: - | O66: - | P66: - | Q66: - | R66: - | S66: - | T66: - | U66: - | V66: - | W66: - | X66: - | Y66: - | Z66: - | AA66: - | AB66: - | AC66: - | AD66: - | AE66: -
A67: Gross capital investment | B67: 4480 | C67: 5117 | D67: 5287 | E67: 7139 | F67: 22023 | G67: 5089 | H67: 6131 | I67: 5839.69 | J67: 6550.91 | K67: 23660.41 | L67: 5221.48 | M67: 5852.89 | N67: 5922.42 | O67: 6529.64 | P67: 23544.72 | Q67: 5146.41 | R67: 5814.71 | S67: 5918.22 | T67: 6434.07 | U67: 23301.87 | V67: 5243.18 | W67: 5928.24 | X67: 5897.13 | Y67: 6157.71 | Z67: 23073.21 | AA67: 5214.1 | AB67: 5903.47 | AC67: 5878.83 | AD67: 6134.83 | AE67: 22717.65

Sheet Free Cash Flow
A2: AT&T Inc. | Free cash flow
A3: NYSE:T (MI KEY: 4024242; SPCIQ KEY: 100231)
A5: Visible Alpha
A7: Period Type : Fiscal Quarter, Fiscal Halves, Fiscal Year
A8: Period Start : 2025
A9: Period End : 2030
A10: Currency : Reported
A11: Consensus View : Mean
A12: As Of: 10/20/2026
A14: All numbers in $M unless otherwise indicated | B14: FQ1 2025A | C14: FQ2 2025A | D14: FQ3 2025A | E14: FQ4 2025A | F14: FY2025A | G14: FQ1 2026A | H14: FQ2 2026A | I14: FQ3 2026E | J14: FQ4 2026E | K14: FY2026E | L14: FQ1 2027E | M14: FQ2 2027E | N14: FQ3 2027E | O14: FQ4 2027E | P14: FY2027E | Q14: FQ1 2028E | R14: FQ2 2028E | S14: FQ3 2028E | T14: FQ4 2028E | U14: FY2028E | V14: FQ1 2029E | W14: FQ2 2029E | X14: FQ3 2029E | Y14: FQ4 2029E | Z14: FY2029E | AA14: FQ1 2030E | AB14: FQ2 2030E | AC14: FQ3 2030E | AD14: FQ4 2030E | AE14: FY2030E
A15: Number of Contributors Available | B15: 19 | C15: 19 | D15: 19 | E15: 19 | F15: 20 | G15: 19 | H15: 19 | I15: 20 of 20 | J15: 20 of 20 | K15: 20 of 20 | L15: 14 of 20 | M15: 14 of 20 | N15: 13 of 20 | O15: 13 of 20 | P15: 20 of 20 | Q15: 7 of 20 | R15: 7 of 20 | S15: 7 of 20 | T15: 7 of 20 | U15: 17 of 20 | V15: 5 of 20 | W15: 5 of 20 | X15: 5 of 20 | Y15: 5 of 20 | Z15: 14 of 20 | AA15: 5 of 20 | AB15: 5 of 20 | AC15: 5 of 20 | AD15: 5 of 20 | AE15: 14 of 20
A16: Free Cash Flow
A17: Net cash provided by (used in) operating activities | B17: 9049 | C17: 9763 | D17: 10152 | E17: 11320 | F17: 40284 | G17: 7595 | H17: 10801 | I17: 10667.33 | J17: 12543.94 | K17: 41598.36 | L17: 7731.49 | M17: 10932.44 | N17: 11411.38 | O17: 12578.61 | P17: 42772.68 | Q17: 8618.07 | R17: 11507.73 | S17: 11847.29 | T17: 13275.84 | U17: 44926.04 | V17: 9134.76 | W17: 12109.35 | X17: 12005.64 | Y17: 13603.38 | Z17: 45983.73 | AA17: 9733.67 | AB17: 12636.67 | AC17: 12440.36 | AD17: 14474.62 | AE17: 47492.33
A18: DTV distribution classified as op activities | B18: 1423 | C18: 503 | D18: 251 | E18: 251 | F18: 1926 | G18: - | H18: - | I18: - | J18: - | K18: - | L18: - | M18: - | N18: - | O18: - | P18: - | Q18: - | R18: - | S18: - | T18: - | U18: - | V18: - | W18: - | X18: - | Y18: - | Z18: - | AA18: - | AB18: - | AC18: - | AD18: - | AE18: -
A19: Cash taxes paid on DTV | B19: - | C19: 251 | D19: - | E19: - | F19: 251 | G19: - | H19: - | I19: - | J19: - | K19: - | L19: - | M19: - | N19: - | O19: - | P19: - | Q19: - | R19: - | S19: - | T19: - | U19: - | V19: - | W19: - | X19: - | Y19: - | Z19: - | AA19: - | AB19: - | AC19: - | AD19: - | AE19: -
A20: Total capital expenditures | B20: 4277 | C20: 4897 | D20: 4887 | E20: 6781 | F20: 20842 | G20: 4877 | H20: 5700 | I20: 5553.66 | J20: 6262.03 | K20: 22460.63 | L20: 4997.7 | M20: 5546.95 | N20: 5616.37 | O20: 6217.85 | P20: 22488.81 | Q20: 4840.45 | R20: 5488.73 | S20: 5606.05 | T20: 6124.59 | U20: 22309.68 | V20: 4958.76 | W20: 5618.59 | X20: 5604.87 | Y20: 5868.84 | Z20: 22208.62 | AA20: 4932.12 | AB20: 5598.78 | AC20: 5589.8 | AD20: 5848.85 | AE20: 21871.34
A21: Cash paid for vendor financing | B21: 203 | C21: 220 | D21: 400 | E21: 358 | F21: 1181 | G21: 212 | H21: 431 | I21: 295.02 | J21: 286.51 | K21: 1201.74 | L21: 292.56 | M21: 315.08 | N21: 303 | O21: 300.65 | P21: 1091.06 | Q21: 305.95 | R21: 325.98 | S21: 312.17 | T21: 309.48 | U21: 1117.57 | V21: 284.42 | W21: 309.65 | X21: 292.26 | Y21: 288.87 | Z21: 1145.48 | AA21: 281.98 | AB21: 304.69 | AC21: 289.03 | AD21: 285.98 | AE21: 1141.35
A22: Cash paid for capital investment | B22: 4480 | C22: 5117 | D22: 5287 | E22: 7139 | F22: 22023 | G22: 5089 | H22: 6131 | I22: 5839.69 | J22: 6550.91 | K22: 23660.41 | L22: 5221.48 | M22: 5852.89 | N22: 5922.42 | O22: 6529.64 | P22: 23544.72 | Q22: 5146.41 | R22: 5814.71 | S22: 5918.22 | T22: 6434.07 | U22: 23301.87 | V22: 5243.18 | W22: 5928.24 | X22: 5897.13 | Y22: 6157.71 | Z22: 23073.21 | AA22: 5214.1 | AB22: 5903.47 | AC22: 5878.83 | AD22: 6134.83 | AE22: 22717.65
A23: Free cash flow | B23: 3146 | C23: 4394 | D23: 4865 | E23: 4181 | F23: 16586 | G23: 2506 | H23: 4670 | I23: 4900.42 | J23: 6008.83 | K23: 18149.5 | L23: 2636.28 | M23: 5090.38 | N23: 5719.31 | O23: 6044.74 | P23: 19460.12 | Q23: 3812.01 | R23: 5333.52 | S23: 6220.82 | T23: 6400.28 | U23: 21535.08 | V23: 4045.77 | W23: 5312.16 | X23: 6235.71 | Y23: 6786.78 | Z23: 22439.87 | AA23: 4476.96 | AB23: 5507.61 | AC23: 6626.08 | AD23: 7777.78 | AE23: 24136.3
A24: Dividends paid | B24: 2091 | C24: 2044 | D24: 2033 | E24: 2012 | F24: 8180 | G24: 1997 | H24: 1976 | I24: 1915.33 | J24: 1887.14 | K24: 7760.26 | L24: 1866.35 | M24: 1842.21 | N24: 1821.14 | O24: 1800.44 | P24: 7351.62 | Q24: 1787.33 | R24: 1768.88 | S24: 1750.41 | T24: 1741.88 | U24: 7110.7 | V24: 1744.64 | W24: 1723.76 | X24: 1706.2 | Y24: 1699.78 | Z24: 6919.41 | AA24: 1696.42 | AB24: 1675.47 | AC24: 1657.01 | AD24: 1651.26 | AE24: 6727.34
A25: Free cash flow after dividends | B25: 1055 | C25: 2350 | D25: 2832 | E25: 2169 | F25: 8406 | G25: 509 | H25: 2694 | I25: 2985.35 | J25: 4109.59 | K25: 10389.46 | L25: 770.12 | M25: 3248.36 | N25: 3898.13 | O25: 4244.06 | P25: 12104.59 | Q25: 2022.78 | R25: 3562.21 | S25: 4467.51 | T25: 4653.46 | U25: 14414.41 | V25: 2287.93 | W25: 3575.42 | X25: 4516.03 | Y25: 5070.34 | Z25: 15488.08 | AA25: 2760.02 | AB25: 3812.24 | AC25: 4949.29 | AD25: 6103.75 | AE25: 17355.68
A27: Free Cash Flow from Adjusted EBITDA
A28: EBITDA - Operating | B28: 11533 | C28: 11731 | D28: 11861 | E28: 11236 | F28: 46361 | G28: 11795 | H28: 12338 | I28: 12325.8 | J28: 11732.12 | K28: 48163.77 | L28: 12249.29 | M28: 12734.22 | N28: 12871.66 | O28: 12199.23 | P28: 50045.84 | Q28: 12912.04 | R28: 13275.33 | S28: 13400.12 | T28: 12799.95 | U28: 52390.05 | V28: 13420.49 | W28: 13890.84 | X28: 14006.21 | Y28: 13348.01 | Z28: 54669.92 | AA28: 14081.74 | AB28: 14531.35 | AC28: 14662.17 | AD28: 13966.81 | AE28: 57157.53
A29: Bad debt expense - FCF | B29: 516 | C29: 521 | D29: 555 | E29: 679 | F29: 2271 | G29: 560 | H29: 589 | I29: 565.89 | J29: 608.45 | K29: 2323.34 | L29: 566.61 | M29: 574.32 | N29: 567.71 | O29: 606.92 | P29: 2303.82 | Q29: 579.2 | R29: 590.16 | S29: 580.84 | T29: 632.69 | U29: 2355.7 | V29: 586.39 | W29: 601.34 | X29: 589.33 | Y29: 653.31 | Z29: 2402.29 | AA29: 598.25 | AB29: 613.26 | AC29: 602.16 | AD29: 666.09 | AE29: 2456.82
A30: Gross capital investment | B30: 4480 | C30: 5117 | D30: 5287 | E30: 7139 | F30: 22023 | G30: 5089 | H30: 6131 | I30: 5839.69 | J30: 6550.91 | K30: 23660.41 | L30: 5221.48 | M30: 5852.89 | N30: 5922.42 | O30: 6529.64 | P30: 23544.72 | Q30: 5146.41 | R30: 5814.71 | S30: 5918.22 | T30: 6434.07 | U30: 23301.87 | V30: 5243.18 | W30: 5928.24 | X30: 5897.13 | Y30: 6157.71 | Z30: 23073.21 | AA30: 5214.1 | AB30: 5903.47 | AC30: 5878.83 | AD30: 6134.83 | AE30: 22717.65
A31: Cash paid for interest | B31: 1804 | C31: 1512 | D31: 1855 | E31: 1454 | F31: 6625 | G31: 1936 | H31: 1798 | I31: 2022.68 | J31: 1961.93 | K31: 7754.06 | L31: 2060.54 | M31: 1937.56 | N31: 2020.33 | O31: 1837.8 | P31: 7900.35 | Q31: 1952.55 | R31: 1873.38 | S31: 1936.49 | T31: 1789.32 | U31: 7705.03 | V31: 1800.24 | W31: 1681.42 | X31: 1775.98 | Y31: 1535.77 | Z31: 7330.74 | AA31: 1724.99 | AB31: 1601.09 | AC31: 1695.53 | AD31: 1420.5 | AE31: 7114.63
A32: Interest during construction - FCF | B32: 56 | C32: 55 | D32: 56 | E32: 54 | F32: 221 | G32: 42 | H32: 49 | I32: 74.44 | J32: 99.35 | K32: 265.34 | L32: 119.27 | M32: 111.29 | N32: 104.27 | O32: 95.66 | P32: 360.37 | Q32: 45.78 | R32: 49.41 | S32: 52.85 | T32: 51.84 | U32: 303.58 | V32: 42 | W32: 49 | X32: 56 | Y32: 54 | Z32: 284.06 | AA32: 42 | AB32: 49 | AC32: 56 | AD32: 54 | AE32: 244.74
A33: Cash paid for interest - FCF | B33: 1748 | C33: 1457 | D33: 1799 | E33: 1400 | F33: 6404 | G33: 1894 | H33: 1749 | I33: 1948.8 | J33: 1765.57 | K33: 7385.37 | L33: 1993.63 | M33: 1838.86 | N33: 1972.66 | O33: 1686.78 | P33: 7545.26 | Q33: 1943.53 | R33: 1795.76 | S33: 1932.07 | T33: 1624.36 | U33: 7383.53 | V33: 1855.25 | W33: 1669.31 | X33: 1835.08 | Y33: 1445.27 | Z33: 7065.81 | AA33: 1785.48 | AB33: 1594.17 | AC33: 1754.03 | AD33: 1352.63 | AE33: 6786.36
A34: Cash paid for taxes - FCF | B34: 11 | C34: 869 | D34: 17 | E34: 456 | F34: 1353 | G34: 1 | H34: 90 | I34: 286.43 | J34: 677.17 | K34: 1058.33 | L34: 124.8 | M34: 385.8 | N34: 224.32 | O34: 574.86 | P34: 1269.65 | Q34: 50.77 | R34: 435.44 | S34: 129.01 | T34: 677.35 | U34: 1370.32 | V34: 255.95 | W34: 1200.31 | X34: 284.63 | Y34: 1013.55 | Z34: 2528.95 | AA34: 468.21 | AB34: 1695.64 | AC34: 519.09 | AD34: 1366.36 | AE34: 3617.46
A35: Working capital - FCF | B35: -2878 | C35: -1310 | D35: -82 | E35: 2284 | F35: -1986 | G35: -3134 | H35: -169 | I35: -290.73 | J35: 3375.99 | K35: -183.66 | L35: -3153.63 | M35: 84.5 | N35: -59.32 | O35: 2216.72 | P35: -781.35 | Q35: -2944.46 | R35: 361.29 | S35: -249.29 | T35: 2169.93 | U35: -917.88 | V35: -2989.35 | W35: 530.16 | X35: -260.19 | Y35: 2405.95 | Z35: -730.13 | AA35: -3015.81 | AB35: 673.82 | AC35: -419.35 | AD35: 2497.51 | AE35: -851.46
A36: Cash received from DIRECTV - FCF | B36: 1423 | C36: 503 | D36: - | E36: - | F36: 1926 | G36: - | H36: - | I36: - | J36: - | K36: - | L36: - | M36: - | N36: - | O36: - | P36: - | Q36: - | R36: - | S36: - | T36: - | U36: - | V36: - | W36: - | X36: - | Y36: - | Z36: - | AA36: - | AB36: - | AC36: - | AD36: - | AE36: -
A37: Other- FCF | B37: 214 | C37: 644 | D37: -366 | E37: -1023 | F37: -531 | G37: 269 | H37: -118 | I37: 399.49 | J37: -552.99 | K37: 45.07 | L37: 126.22 | M37: 143.51 | N37: 314.44 | O37: 49.24 | P37: 505.1 | Q37: -280 | R37: -75.35 | S37: 161.32 | T37: 478.63 | U37: 482.1 | V37: -340.04 | W37: -236.53 | X37: -205.51 | Y37: -551.37 | Z37: -212.53 | AA37: -334.65 | AB37: -564.01 | AC37: -213.51 | AD37: 144.86 | AE37: -4.58
A38: Free cash flow including DIRECTV | B38: 3146 | C38: 4645 | D38: 4865 | E38: 4181 | F38: 18261 | G38: 2506 | H38: 4670 | I38: 4819.65 | J38: 6158.61 | K38: 18201.92 | L38: 2556.72 | M38: 5141.97 | N38: 5566.81 | O38: 6218.89 | P38: 19468.18 | Q38: 3451.46 | R38: 5661.35 | S38: 5937.31 | T38: 6957.99 | U38: 21710.66 | V38: 3842.4 | W38: 6015.77 | X38: 5983.32 | Y38: 7432.17 | Z38: 23217.36 | AA38: 4441.02 | AB38: 6421.46 | AC38: 6443.41 | AD38: 8242.96 | AE38: 25054.2
A39: Cash taxes paid on DTV | B39: - | C39: 251 | D39: - | E39: - | F39: 251 | G39: - | H39: - | I39: - | J39: - | K39: - | L39: - | M39: - | N39: - | O39: - | P39: - | Q39: - | R39: - | S39: - | T39: - | U39: - | V39: - | W39: - | X39: - | Y39: - | Z39: - | AA39: - | AB39: - | AC39: - | AD39: - | AE39: -
A40: Free cash flow | B40: 3146 | C40: 4394 | D40: 4865 | E40: 4181 | F40: 16586 | G40: 2506 | H40: 4670 | I40: 4900.42 | J40: 6008.83 | K40: 18149.5 | L40: 2636.28 | M40: 5090.38 | N40: 5719.31 | O40: 6044.74 | P40: 19460.12 | Q40: 3812.01 | R40: 5333.52 | S40: 6220.82 | T40: 6400.28 | U40: 21535.08 | V40: 4045.77 | W40: 5312.16 | X40: 6235.71 | Y40: 6786.78 | Z40: 22439.87 | AA40: 4476.96 | AB40: 5507.61 | AC40: 6626.08 | AD40: 7777.78 | AE40: 24136.3
A42: Free cash flow per share($) | B42: 0.44 | C42: 0.61 | D42: 0.68 | E42: 0.59 | F42: 2.31 | G42: 0.36 | H42: 0.67 | I42: 0.71 | J42: 0.91 | K42: 2.64 | L42: 0.36 | M42: 0.79 | N42: 0.87 | O42: 0.97 | P42: 2.98 | Q42: 0.57 | R42: 0.85 | S42: 0.95 | T42: 1.02 | U42: 3.38 | V42: 0.65 | W42: 0.93 | X42: 0.97 | Y42: 1.19 | Z42: 3.78 | AA42: 0.74 | AB42: 1.03 | AC42: 1.07 | AD42: 1.38 | AE42: 4.23
A44: Free cash flow per share including DIRECTV($) | B44: 0.63 | C44: 0.64 | D44: 0.68 | E44: 0.59 | F44: 2.54 | G44: 0.36 | H44: 0.67 | I44: 0.7 | J44: 0.94 | K44: 2.66 | L44: 0.39 | M44: 0.78 | N44: 0.8 | O44: 1.03 | P44: 2.99 | Q44: 0.53 | R44: 0.95 | S44: 0.89 | T44: 1.13 | U44: 3.47 | V44: 0.63 | W44: 1.13 | X44: 0.89 | Y44: 1.27 | Z44: 3.91 | AA44: 0.78 | AB44: 1.27 | AC44: 1.02 | AD44: 1.38 | AE44: 4.42

Sheet Legacy
A2: AT&T Inc. | Legacy
A3: NYSE:T (MI KEY: 4024242; SPCIQ KEY: 100231)
A5: Visible Alpha
A7: Period Type : Fiscal Quarter, Fiscal Halves, Fiscal Year
A8: Period Start : 2025
A9: Period End : 2030
A10: Currency : Reported
A11: Consensus View : Mean
A12: As Of: 10/20/2026
A14: All numbers in $M unless otherwise indicated | B14: FQ1 2025A | C14: FQ2 2025A | D14: FQ3 2025A | E14: FQ4 2025A | F14: FY2025A | G14: FQ1 2026A | H14: FQ2 2026A | I14: FQ3 2026E | J14: FQ4 2026E | K14: FY2026E | L14: FQ1 2027E | M14: FQ2 2027E | N14: FQ3 2027E | O14: FQ4 2027E | P14: FY2027E | Q14: FQ1 2028E | R14: FQ2 2028E | S14: FQ3 2028E | T14: FQ4 2028E | U14: FY2028E | V14: FQ1 2029E | W14: FQ2 2029E | X14: FQ3 2029E | Y14: FQ4 2029E | Z14: FY2029E | AA14: FQ1 2030E | AB14: FQ2 2030E | AC14: FQ3 2030E | AD14: FQ4 2030E | AE14: FY2030E
A15: Number of Contributors Available | B15: 19 | C15: 19 | D15: 19 | E15: 19 | F15: 20 | G15: 19 | H15: 19 | I15: 20 of 20 | J15: 20 of 20 | K15: 20 of 20 | L15: 14 of 20 | M15: 14 of 20 | N15: 13 of 20 | O15: 13 of 20 | P15: 20 of 20 | Q15: 7 of 20 | R15: 7 of 20 | S15: 7 of 20 | T15: 7 of 20 | U15: 17 of 20 | V15: 5 of 20 | W15: 5 of 20 | X15: 5 of 20 | Y15: 5 of 20 | Z15: 14 of 20 | AA15: 5 of 20 | AB15: 5 of 20 | AC15: 5 of 20 | AD15: 5 of 20 | AE15: 14 of 20
A16: Financials
A17: Legacy - Business service | B17: 1206 | C17: 1124 | D17: 1031 | E17: 988 | F17: 4349 | G17: 918 | H17: 856 | I17: 798.56 | J17: 760.91 | K17: 3333.46 | L17: 677.13 | M17: 629.5 | N17: 584.4 | O17: 547.85 | P17: 2427.11 | Q17: 400.69 | R17: 364.3 | S17: 320.58 | T17: 293.34 | U17: 1547.73 | V17: 254.44 | W17: 223.48 | X17: 244.3 | Y17: 225.9 | Z17: 1034.91 | AA17: 195.18 | AB17: 176.43 | AC17: 157.34 | AD17: 147.07 | AE17: 841.66
A18: Legacy - Consumer - Broadband | B18: 786.38 | C18: 727.77 | D18: 658.39 | E18: 601.05 | F18: 2773.59 | G18: 568 | H18: 519.69 | I18: 456.28 | J18: 399.89 | K18: 1943.86 | L18: 346.48 | M18: 289.78 | N18: 230.82 | O18: 177.92 | P18: 1083.07 | Q18: - | R18: 23.87 | S18: 3.6 | T18: 3.62 | U18: 462.81 | V18: - | W18: - | X18: - | Y18: - | Z18: 119.44 | AA18: - | AB18: - | AC18: - | AD18: - | AE18: 87.45
A19: Legacy voice and data services | B19: 286 | C19: 265 | D19: 243 | E19: 219 | F19: 1013 | G19: 222.04 | H19: 205.52 | I19: 191.87 | J19: 176.56 | K19: 799.34 | L19: 167.71 | M19: 157 | N19: 146.01 | O19: 134.99 | P19: 619.32 | Q19: 95.6 | R19: 81.99 | S19: 68.42 | T19: 55.53 | U19: 402.85 | V19: 58.82 | W19: 53.28 | X19: 47.41 | Y19: 41.46 | Z19: 304.37 | AA19: 36.76 | AB19: 33.03 | AC19: 29.16 | AD19: 25.29 | AE19: 256.21
A20: Legacy - Consumer - Other services | B20: 90 | C20: 84 | D20: 80 | E20: 79 | F20: 333 | G20: 68.92 | H20: 65.1 | I20: 60 | J20: 59.25 | K20: 253.27 | L20: 56.33 | M20: 53.52 | N20: 48.4 | O20: 47.8 | P20: 191.48 | Q20: 34.26 | R20: 32.47 | S20: 31.2 | T20: 30.81 | U20: 149.25 | V20: - | W20: - | X20: - | Y20: - | Z20: 117.12 | AA20: - | AB20: - | AC20: - | AD20: - | AE20: 154.25
A21: Legacy - Consumer service | B21: 1162 | C21: 1078 | D21: 982 | E21: 901 | F21: 4123 | G21: 850 | H21: 776 | I21: 704 | J21: 633.6 | K21: 2963.53 | L21: 576.23 | M21: 512.13 | N21: 448.27 | O21: 386.53 | P21: 1907.56 | Q21: 323.74 | R21: 278 | S21: 243.02 | T21: 208.08 | U21: 1092.31 | V21: 203.19 | W21: 176.13 | X21: 156.22 | Y21: 167.59 | Z21: 649.12 | AA21: 214.81 | AB21: 196.33 | AC21: 186.38 | AD21: 164.83 | AE21: 667.13
A22: Revenue - Legacy | B22: 2368 | C22: 2202 | D22: 2013 | E22: 1889 | F22: 8472 | G22: 1768 | H22: 1632 | I22: 1504.54 | J22: 1400.95 | K22: 6305.49 | L22: 1259.37 | M22: 1143.27 | N22: 1040.74 | O22: 947.12 | P22: 4358.11 | Q22: 724.43 | R22: 642.29 | S22: 563.6 | T22: 501.43 | U22: 2651.29 | V22: 457.63 | W22: 399.61 | X22: 351.66 | Y22: 311.9 | Z22: 1654.41 | AA22: 346.97 | AB22: 422.12 | AC22: 391.25 | AD22: 358.64 | AE22: 1423.71
A24: Operations and support - Legacy - Business | B24: 611 | C24: 581 | D24: 648 | E24: 594 | F24: 2434 | G24: 585 | H24: 554 | I24: 569.02 | J24: 538.71 | K24: 2246.73 | L24: 505.16 | M24: 479.14 | N24: 493.99 | O24: 465.27 | P24: 1948.82 | Q24: 343.82 | R24: 322.31 | S24: 331.13 | T24: 307.54 | U24: 1495.58 | V24: 212.99 | W24: 185.73 | X24: 178.85 | Y24: 155.98 | Z24: 1051.96 | AA24: 113.96 | AB24: 101.93 | AC24: 104.4 | AD24: 91.38 | AE24: 872.13
A25: Operations and support - Legacy - Consumer | B25: 738 | C25: 662 | D25: 686 | E25: 613 | F25: 2699 | G25: 571 | H25: 555 | I25: 517.18 | J25: 466.63 | K25: 2109.8 | L25: 438.33 | M25: 424.51 | N25: 398.11 | O25: 361.63 | P25: 1570.05 | Q25: 270.76 | R25: 259.17 | S25: 239.02 | T25: 215.27 | U25: 1029.34 | V25: 163.66 | W25: 147.77 | X25: 123.23 | Y25: 102.41 | Z25: 629.03 | AA25: 82.57 | AB25: 76.02 | AC25: 62.85 | AD25: 54.58 | AE25: 537.56
A26: Operations and support - Legacy | B26: 1349 | C26: 1243 | D26: 1334 | E26: 1207 | F26: 5133 | G26: 1156 | H26: 1109 | I26: 1088.62 | J26: 1013.43 | K26: 4367.05 | L26: 954.26 | M26: 918.11 | N26: 904.81 | O26: 849.62 | P26: 3590.8 | Q26: 723.81 | R26: 685.82 | S26: 664.65 | T26: 619.99 | U26: 2722.26 | V26: 562.19 | W26: 519.21 | X26: 486.12 | Y26: 444.68 | Z26: 1903.29 | AA26: 455.7 | AB26: 430.04 | AC26: 412.99 | AD26: 383.05 | AE26: 1541.27
A28: EBITDA - Legacy - Business | B28: 595 | C28: 543 | D28: 383 | E28: 394 | F28: 1915 | G28: 333 | H28: 302 | I28: 215.72 | J28: 212.65 | K28: 1063.37 | L28: 157.98 | M28: 120.89 | N28: 26.91 | O28: 12.77 | P28: 340.37 | Q28: -0.73 | R28: -25.06 | S28: -94.97 | T28: -113.04 | U28: -222.22 | V28: -48.72 | W28: -65.04 | X28: -93.51 | Y28: -86.78 | Z28: -308.78 | AA28: -21.5 | AB28: -22.44 | AC28: -49.4 | AD28: -40.14 | AE28: -373.25
A29: EBITDA - Legacy - Consumer | B29: 424 | C29: 416 | D29: 296 | E29: 288 | F29: 1424 | G29: 279 | H29: 221 | I29: 179.24 | J29: 163.68 | K29: 842.76 | L29: 116.54 | M29: 59.63 | N29: 12.52 | O29: -11.55 | P29: 278.19 | Q29: 0.81 | R29: -24.68 | S29: -28.57 | T29: -41.59 | U29: -95.03 | V29: -27.18 | W29: -40.02 | X29: -37.59 | Y29: -41 | Z29: -188.51 | AA29: 1.73 | AB29: -5.36 | AC29: 2.69 | AD29: -0.71 | AE29: -198.74
A30: EBITDA - Legacy | B30: 1019 | C30: 959 | D30: 679 | E30: 682 | F30: 3339 | G30: 612 | H30: 523 | I30: 414.73 | J30: 387.29 | K30: 1937.02 | L30: 313.24 | M30: 238.89 | N30: 130.75 | O30: 90.76 | P30: 800.51 | Q30: 0.62 | R30: -43.53 | S30: -101.05 | T30: -118.56 | U30: -64.59 | V30: -104.55 | W30: -119.6 | X30: -134.46 | Y30: -132.77 | Z30: -279.23 | AA30: -48.87 | AB30: -54.61 | AC30: -131.58 | AD30: -121.07 | AE30: -203.86
A32: Operating income/(loss) - Legacy | B32: 1019 | C32: 959 | D32: 679 | E32: 682 | F32: 3339 | G32: 612 | H32: 523 | I32: 403.65 | J32: 379.99 | K32: 1918.64 | L32: 294.89 | M32: 219.6 | N32: 118.79 | O32: 85.52 | P32: 743.06 | Q32: -0.61 | R32: -43.45 | S32: -102.96 | T32: -115.9 | U32: -105.31 | V32: -87.66 | W32: -97.92 | X32: -108.8 | Y32: -101.13 | Z32: -234.29 | AA32: -48.87 | AB32: -54.61 | AC32: -62.7 | AD32: -47.67 | AE32: -202.93
A34: Metrics
A35: Consumer internet connections - net adds(K#) | B35: -310 | C35: -303 | D35: -327 | E35: -298 | F35: -1238 | G35: -270 | H35: -254 | I35: -280.58 | J35: -267.9 | K35: -1072.48 | L35: -265.39 | M35: -251.58 | N35: -267.06 | O35: -251.71 | P35: -1006.33 | Q35: -207.5 | R35: -170.5 | S35: -135 | T35: -125 | U35: -569.78 | V35: -82.5 | W35: -72.5 | X35: -60 | Y35: -55 | Z35: -206.02 | AA35: -40 | AB35: -30 | AC35: -30 | AD35: 176 | AE35: -47.64
A36: Consumer internet connections(K#) | B36: 3776 | C36: 3473 | D36: 3146 | E36: 2848 | F36: 2848 | G36: 2578 | H36: 2324 | I36: 2043.42 | J36: 1775.52 | K36: 1775.52 | L36: 1504.13 | M36: 1252.55 | N36: 985.48 | O36: 733.78 | P36: 769.19 | Q36: 539 | R36: 486 | S36: 354 | T36: 229 | U36: 274.34 | V36: 146.5 | W36: 74 | X36: 29 | Y36: - | Z36: 189.76 | AA36: - | AB36: - | AC36: - | AD36: - | AE36: 100.9
A38: Customer location switched access lines - net adds(K#) | B38: -164 | C38: -199 | D38: -151 | E38: -156 | F38: -670 | G38: -157 | H38: -162 | I38: -142.94 | J38: -141.75 | K38: -605.69 | L38: -154.97 | M38: -167.68 | N38: -148.61 | O38: -147.47 | P38: -573.33 | Q38: -156.67 | R38: -165 | S38: -150 | T38: -140 | U38: -424.19 | V38: -122.5 | W38: -50 | X38: -50 | Y38: -51 | Z38: -304.79 | AA38: - | AB38: - | AC38: - | AD38: - | AE38: -138.23
A39: Customer location switched access lines(K#) | B39: 2572 | C39: 2373 | D39: 2222 | E39: 2066 | F39: 2066 | G39: 1909 | H39: 1747 | I39: 1602.06 | J39: 1460.31 | K39: 1460.31 | L39: 1288.23 | M39: 1120.55 | N39: 971.94 | O39: 824.47 | P39: 886.98 | Q39: 572 | R39: 407 | S39: 257 | T39: 162 | U39: 486.95 | V39: 39.5 | W39: - | X39: - | Y39: - | Z39: 456.58 | AA39: - | AB39: - | AC39: - | AD39: - | AE39: 354.7

Sheet AC Financials
A2: AT&T Inc. | Advanced Connectivity - Financials
A3: NYSE:T (MI KEY: 4024242; SPCIQ KEY: 100231)
A5: Visible Alpha
A7: Period Type : Fiscal Quarter, Fiscal Halves, Fiscal Year
A8: Period Start : 2025
A9: Period End : 2030
A10: Currency : Reported
A11: Consensus View : Mean
A12: As Of: 10/20/2026
A14: All numbers in $M unless otherwise indicated | B14: FQ1 2025A | C14: FQ2 2025A | D14: FQ3 2025A | E14: FQ4 2025A | F14: FY2025A | G14: FQ1 2026A | H14: FQ2 2026A | I14: FQ3 2026E | J14: FQ4 2026E | K14: FY2026E | L14: FQ1 2027E | M14: FQ2 2027E | N14: FQ3 2027E | O14: FQ4 2027E | P14: FY2027E | Q14: FQ1 2028E | R14: FQ2 2028E | S14: FQ3 2028E | T14: FQ4 2028E | U14: FY2028E | V14: FQ1 2029E | W14: FQ2 2029E | X14: FQ3 2029E | Y14: FQ4 2029E | Z14: FY2029E | AA14: FQ1 2030E | AB14: FQ2 2030E | AC14: FQ3 2030E | AD14: FQ4 2030E | AE14: FY2030E
A15: Number of Contributors Available | B15: 19 | C15: 19 | D15: 19 | E15: 19 | F15: 20 | G15: 19 | H15: 19 | I15: 20 of 20 | J15: 20 of 20 | K15: 20 of 20 | L15: 14 of 20 | M15: 14 of 20 | N15: 13 of 20 | O15: 13 of 20 | P15: 20 of 20 | Q15: 7 of 20 | R15: 7 of 20 | S15: 7 of 20 | T15: 7 of 20 | U15: 17 of 20 | V15: 5 of 20 | W15: 5 of 20 | X15: 5 of 20 | Y15: 5 of 20 | Z15: 14 of 20 | AA15: 5 of 20 | AB15: 5 of 20 | AC15: 5 of 20 | AD15: 5 of 20 | AE15: 14 of 20
A16: Consumer
A17: Wireless service revenue - Consumer - Advanced connectivity | B17: 14370 | C17: 14559 | D17: 14594 | E17: 14605 | F17: 58128 | G17: 14584 | H17: 14992 | I17: 15103.68 | J17: 15144.6 | K17: 59824.28 | L17: 15121.7 | M17: 15362.88 | N17: 15560.49 | O17: 15549.25 | P17: 61437.89 | Q17: 15594.39 | R17: 15847.87 | S17: 16096.11 | T17: 16174.3 | U17: 62875.6 | V17: 15465.29 | W17: 15807.91 | X17: 15943.35 | Y17: 15877.47 | Z17: 63165.52 | AA17: 15696.69 | AB17: 15990.46 | AC17: 16224.92 | AD17: 16094.88 | AE17: 64032.64
A18: Advanced home internet services revenue - Advanced connectivity | B18: 2198 | C18: 2299 | D18: 2411 | E18: 2502 | F18: 9410 | G18: 2799 | H18: 2926 | I18: 3065.8 | J18: 3181.73 | K18: 11993.31 | L18: 3349.99 | M18: 3432.08 | N18: 3580.82 | O18: 3701.07 | P18: 14128.13 | Q18: 3902.26 | R18: 3977 | S18: 4148.02 | T18: 4268.25 | U18: 16264.78 | V18: 4500.34 | W18: 4590.05 | X18: 4772.13 | Y18: 4899.41 | Z18: 18469.22 | AA18: 5110.89 | AB18: 5195.26 | AC18: 5383.34 | AD18: 5508.6 | AE18: 20618.1
A19: Other services revenue - Advanced connectivity | B19: 162 | C19: 164 | D19: 162 | E19: 162 | F19: 650 | G19: 158 | H19: 151 | I19: 156.01 | J19: 156.22 | K19: 621.23 | L19: 152.8 | M19: 145.26 | N19: 150.43 | O19: 151.27 | P19: 597.96 | Q19: 146.75 | R19: 139.75 | S19: 144.31 | T19: 144.33 | U19: 577.04 | V19: 139.03 | W19: 132.63 | X19: 135.72 | Y19: 135.78 | Z19: 553.59 | AA19: 133.37 | AB19: 127.21 | AC19: 130.19 | AD19: 130.25 | AE19: 534.11
A20: Total service revenue - Consumer - Advanced connectivity | B20: 16730 | C20: 17022 | D20: 17167 | E20: 17269 | F20: 68188 | G20: 17541 | H20: 18069 | I20: 18314.63 | J20: 18469.87 | K20: 72394.5 | L20: 18612.48 | M20: 18934.72 | N20: 19290.82 | O20: 19401.23 | P20: 76096.43 | Q20: 19603.76 | R20: 19943.31 | S20: 20365.58 | T20: 20567.33 | U20: 79699.06 | V20: 20119.97 | W20: 20580.58 | X20: 20918.88 | Y20: 20993.29 | Z20: 82337.11 | AA20: 20994.1 | AB20: 21405.52 | AC20: 21850.72 | AD20: 21861.06 | AE20: 85458.87
A21: Equipment revenue - Consumer - Advanced connectivity | B21: 4246 | C21: 4273 | D21: 4107 | E21: 6445 | F21: 19071 | G21: 4611 | H21: 4260 | I21: 4193.58 | J21: 6548.97 | K21: 19613.55 | L21: 4784.42 | M21: 4457.82 | N21: 4251.05 | O21: 6728.38 | P21: 20188.43 | Q21: 4949.51 | R21: 4525.15 | S21: 4479.8 | T21: 6987.15 | U21: 20702.29 | V21: 4810.97 | W21: 4457.8 | X21: 4276.12 | Y21: 6640.57 | Z21: 20869.13 | AA21: 4891.45 | AB21: 4503.96 | AC21: 4348.28 | AD21: 6721.89 | AE21: 21199.68
A22: Advanced connectivity revenue - Consumer | B22: 20976 | C22: 21295 | D22: 21274 | E22: 23714 | F22: 87259 | G22: 22152 | H22: 22329 | I22: 22529.96 | J22: 25029.95 | K22: 92040.91 | L22: 23462.97 | M22: 23392.31 | N22: 23565.52 | O22: 26179.82 | P22: 96421.23 | Q22: 24714.22 | R22: 24491.93 | S22: 24932.98 | T22: 27733.77 | U22: 100613.03 | V22: 24779.24 | W22: 24718.62 | X22: 24902.3 | Y22: 27397.07 | Z22: 103600.7 | AA22: 25594.82 | AB22: 25389.47 | AC22: 25797.44 | AD22: 28174.46 | AE22: 107201.91
A23: Business
A24: Wireless service revenue - Business - Advanced connectivity | B24: 2281 | C24: 2294 | D24: 2332 | E24: 2349 | F24: 9256 | G24: 2357 | H24: 2421 | I24: 2462.89 | J24: 2463.44 | K24: 9704.33 | L24: 2420.19 | M24: 2442.53 | N24: 2497.41 | O24: 2504.07 | P24: 9884.22 | Q24: 2431.97 | R24: 2428.6 | S24: 2420.01 | T24: 2431.3 | U24: 10107.21 | V24: 2589.27 | W24: 2628.46 | X24: 2646.78 | Y24: 2659.52 | Z24: 10682.29 | AA24: 2646.56 | AB24: 2687.04 | AC24: 2705.91 | AD24: 2719.01 | AE24: 11054.49
A25: Business fiber and advanced connectivity services revenue - Advanced connectivity | B25: 1755 | C25: 1769 | D25: 1832 | E25: 1887 | F25: 7243 | G25: 1882 | H25: 1946 | I25: 1992 | J25: 2046.85 | K25: 7866.85 | L25: 2037 | M25: 2106.48 | N25: 2146.61 | O25: 2196.75 | P25: 8495 | Q25: 2177.4 | R25: 2237.25 | S25: 2261.04 | T25: 2304.39 | U25: 9092.5 | V25: 2376.18 | W25: 2438.72 | X25: 2476.61 | Y25: 2524.98 | Z25: 9847.16 | AA25: 2545.26 | AB25: 2606.66 | AC25: 2642.05 | AD25: 2689.49 | AE25: 10498.97
A26: Business transitional and other service revenue - Advanced connectivity | B26: 1294 | C26: 1249 | D26: 1198 | E26: 1170 | F26: 4911 | G26: 1083 | H26: 1042 | I26: 1021.53 | J26: 998.08 | K26: 4144.61 | L26: 932.87 | M26: 898.49 | N26: 881.42 | O26: 861.16 | P26: 3570.63 | Q26: 825.83 | R26: 794.57 | S26: 781.55 | T26: 764.06 | U26: 3148.6 | V26: 751.58 | W26: 723.62 | X26: 717.62 | Y26: 702.74 | Z26: 2813.96 | AA26: 677.3 | AB26: 652.18 | AC26: 647.12 | AD26: 633.78 | AE26: 2502.93
A27: Total service revenue - Business - Advanced connectivity | B27: 5330 | C27: 5312 | D27: 5362 | E27: 5406 | F27: 21410 | G27: 5322 | H27: 5409 | I27: 5455.85 | J27: 5487.35 | K27: 21674.2 | L27: 5367 | M27: 5424.42 | N27: 5467.96 | O27: 5506.53 | P27: 21841.08 | Q27: 5336.54 | R27: 5373.13 | S27: 5362.27 | T27: 5396.77 | U27: 22155.73 | V27: 5683.18 | W27: 5772.11 | X27: 5834.91 | Y27: 5892.97 | Z27: 23215.42 | AA27: 5834.2 | AB27: 5932.58 | AC27: 6001.05 | AD27: 6065.5 | AE27: 23895.2
A28: Equipment revenue - Business - Advanced connectivity | B28: 886 | C28: 890 | D28: 867 | E28: 1112 | F28: 3755 | G28: 997 | H28: 877 | I28: 893.2 | J28: 1163.97 | K28: 3931.17 | L28: 1001.72 | M28: 903.11 | N28: 863.5 | O28: 1187.95 | P28: 3989.51 | Q28: 963.18 | R28: 846.1 | S28: 829.84 | T28: 1191.31 | U28: 4033.83 | V28: 1021.37 | W28: 908.66 | X28: 901.02 | Y28: 1381.95 | Z28: 4240.59 | AA28: 1025.73 | AB28: 941.59 | AC28: 897.52 | AD28: 1411.1 | AE28: 4329.61
A29: Advanced connectivity revenue - Business | B29: 6216 | C29: 6202 | D29: 6229 | E29: 6518 | F29: 25165 | G29: 6319 | H29: 6286 | I29: 6351.39 | J29: 6646.63 | K29: 25603.02 | L29: 6355.07 | M29: 6318.73 | N29: 6323.6 | O29: 6684.2 | P29: 25891.13 | Q29: 6213.54 | R29: 6127.74 | S29: 6073.02 | T29: 6458.46 | U29: 26338.13 | V29: 6751.83 | W29: 6761.24 | X29: 6830.18 | Y29: 7364.61 | Z29: 27685.84 | AA29: 6911.7 | AB29: 6959.73 | AC29: 6998.7 | AD29: 7571.13 | AE29: 28524.77
A31: Service revenues - wireless | B31: 16651 | C31: 16853 | D31: 16926 | E31: 16954 | F31: 67384 | G31: 16941 | H31: 17413 | I31: 17526.97 | J31: 17565.72 | K31: 69453.75 | L31: 17503.72 | M31: 17839.36 | N31: 17971.16 | O31: 17985.62 | P31: 71247.05 | Q31: 17888.28 | R31: 18213.15 | S31: 18321.82 | T31: 18373.47 | U31: 72800.94 | V31: 18052.25 | W31: 18451.87 | X31: 18528.25 | Y31: 18507.46 | Z31: 73883.32 | AA31: 18318.56 | AB31: 18698.79 | AC31: 18811.09 | AD31: 18759.85 | AE31: 75056.66
A32: Advanced home internet services revenue - Advanced connectivity | B32: 2198 | C32: 2299 | D32: 2411 | E32: 2502 | F32: 9410 | G32: 2799 | H32: 2926 | I32: 3065.8 | J32: 3181.73 | K32: 11993.31 | L32: 3349.99 | M32: 3432.08 | N32: 3580.82 | O32: 3701.07 | P32: 14128.13 | Q32: 3902.26 | R32: 3977 | S32: 4148.02 | T32: 4268.25 | U32: 16264.78 | V32: 4500.34 | W32: 4590.05 | X32: 4772.13 | Y32: 4899.41 | Z32: 18469.22 | AA32: 5110.89 | AB32: 5195.26 | AC32: 5383.34 | AD32: 5508.6 | AE32: 20618.1
A33: Business fiber and advanced connectivity services revenue - Advanced connectivity | B33: 1755 | C33: 1769 | D33: 1832 | E33: 1887 | F33: 7243 | G33: 1882 | H33: 1946 | I33: 1992 | J33: 2046.85 | K33: 7866.85 | L33: 2037 | M33: 2106.48 | N33: 2146.61 | O33: 2196.75 | P33: 8495 | Q33: 2177.4 | R33: 2237.25 | S33: 2261.04 | T33: 2304.39 | U33: 9092.5 | V33: 2376.18 | W33: 2438.72 | X33: 2476.61 | Y33: 2524.98 | Z33: 9847.16 | AA33: 2545.26 | AB33: 2606.66 | AC33: 2642.05 | AD33: 2689.49 | AE33: 10498.97
A34: Business transitional and other service revenue - Advanced connectivity | B34: 1294 | C34: 1249 | D34: 1198 | E34: 1170 | F34: 4911 | G34: 1083 | H34: 1042 | I34: 1021.53 | J34: 998.08 | K34: 4144.61 | L34: 932.87 | M34: 898.49 | N34: 881.42 | O34: 861.16 | P34: 3570.63 | Q34: 825.83 | R34: 794.57 | S34: 781.55 | T34: 764.06 | U34: 3148.6 | V34: 751.58 | W34: 723.62 | X34: 717.62 | Y34: 702.74 | Z34: 2813.96 | AA34: 677.3 | AB34: 652.18 | AC34: 647.12 | AD34: 633.78 | AE34: 2502.93
A35: Other services revenue - Advanced connectivity | B35: 162 | C35: 164 | D35: 162 | E35: 162 | F35: 650 | G35: 158 | H35: 151 | I35: 156.01 | J35: 156.22 | K35: 621.23 | L35: 152.8 | M35: 145.26 | N35: 150.43 | O35: 151.27 | P35: 597.96 | Q35: 146.75 | R35: 139.75 | S35: 144.31 | T35: 144.33 | U35: 577.04 | V35: 139.03 | W35: 132.63 | X35: 135.72 | Y35: 135.78 | Z35: 553.59 | AA35: 133.37 | AB35: 127.21 | AC35: 130.19 | AD35: 130.25 | AE35: 534.11
A36: Total service revenue - Advanced connectivity | B36: 22060 | C36: 22334 | D36: 22529 | E36: 22675 | F36: 89598 | G36: 22863 | H36: 23478 | I36: 23773.75 | J36: 23938.35 | K36: 94053.1 | L36: 23956.91 | M36: 24425.9 | N36: 24752.97 | O36: 24872.93 | P36: 97976.67 | Q36: 24940.53 | R36: 25361.72 | S36: 25656.74 | T36: 25854.49 | U36: 101853.62 | V36: 25819.37 | W36: 26336.89 | X36: 26630.33 | Y36: 26770.37 | Z36: 105551.96 | AA36: 26785.38 | AB36: 27280.1 | AC36: 27613.79 | AD36: 27721.97 | AE36: 109247.44
... A43: Operating income/(loss) - Advanced connectivity | B43: 5972 | C43: 6106 | D43: 6417 | E43: 6093 | F43: 24588 | G43: 6853 | H43: 7345 | I43: 7368.96 | J43: 6760.85 | K43: 28327.81 | L43: 7607.22 | M43: 7951.6 | N43: 8102.7 | O43: 7474.14 | P43: 31136.32 | Q43: 8388.04 | R43: 8740.54 | S43: 8833.32 | T43: 8242.19 | U43: 33951.24 | V43: 8863.52 | W43: 9280.63 | X43: 9319.4 | Y43: 8809.81 | Z43: 36024.18 | AA43: 9342.41 | AB43: 9746.19 | AC43: 9809.35 | AD43: 9267.49 | AE43: 38150.61

Sheet Latin America
A2: AT&T Inc. | Latin America
A3: NYSE:T (MI KEY: 4024242; SPCIQ KEY: 100231)
A5: Visible Alpha
A7: Period Type : Fiscal Quarter, Fiscal Halves, Fiscal Year
A8: Period Start : 2025
A9: Period End : 2030
A10: Currency : Reported
A11: Consensus View : Mean
A12: As Of: 10/20/2026
A14: All numbers in $M unless otherwise indicated | B14: FQ1 2025A | C14: FQ2 2025A | D14: FQ3 2025A | E14: FQ4 2025A | F14: FY2025A | G14: FQ1 2026A | H14: FQ2 2026A | I14: FQ3 2026E | J14: FQ4 2026E | K14: FY2026E | L14: FQ1 2027E | M14: FQ2 2027E | N14: FQ3 2027E | O14: FQ4 2027E | P14: FY2027E | Q14: FQ1 2028E | R14: FQ2 2028E | S14: FQ3 2028E | T14: FQ4 2028E | U14: FY2028E | V14: FQ1 2029E | W14: FQ2 2029E | X14: FQ3 2029E | Y14: FQ4 2029E | Z14: FY2029E | AA14: FQ1 2030E | AB14: FQ2 2030E | AC14: FQ3 2030E | AD14: FQ4 2030E | AE14: FY2030E
A15: Number of Contributors Available | B15: 19 | C15: 19 | D15: 19 | E15: 19 | F15: 20 | G15: 19 | H15: 19 | I15: 20 of 20 | J15: 20 of 20 | K15: 20 of 20 | L15: 14 of 20 | M15: 14 of 20 | N15: 13 of 20 | O15: 13 of 20 | P15: 20 of 20 | Q15: 7 of 20 | R15: 7 of 20 | S15: 7 of 20 | T15: 7 of 20 | U15: 17 of 20 | V15: 5 of 20 | W15: 5 of 20 | X15: 5 of 20 | Y15: 5 of 20 | Z15: 14 of 20 | AA15: 5 of 20 | AB15: 5 of 20 | AC15: 5 of 20 | AD15: 5 of 20 | AE15: 14 of 20
A16: Vrio (Video entertainment) - International | B16: - | C16: - | D16: - | E16: - | F16: - | G16: - | H16: - | I16: - | J16: - | K16: - | L16: - | M16: - | N16: - | O16: - | P16: - | Q16: - | R16: - | S16: - | T16: - | U16: - | V16: - | W16: - | X16: - | Y16: - | Z16: - | AA16: - | AB16: - | AC16: - | AD16: - | AE16: -
A17: Mexico wireless service revenue | B17: 615 | C17: 662 | D17: 696 | E17: 742 | F17: 2715 | G17: 753 | H17: 780 | I17: 713.78 | J17: 732.21 | K17: 2968.51 | L17: 732.73 | M17: 747.95 | N17: 703.81 | O17: 725.43 | P17: 2930.77 | Q17: 730.95 | R17: 759.87 | S17: 687.77 | T17: 716.48 | U17: 2982.09 | V17: 746.61 | W17: 777.66 | X17: 702.78 | Y17: 732.7 | Z17: 3056.4 | AA17: 761.41 | AB17: 792.13 | AC17: 711.2 | AD17: 741.48 | AE17: 3089.88
A18: Mexico wireless equipment revenue | B18: 356 | C18: 392 | D18: 399 | E18: 517 | F18: 1664 | G18: 420 | H18: 444 | I18: 428.21 | J18: 506.49 | K18: 1797.77 | L18: 449.42 | M18: 464.62 | N18: 442.62 | O18: 535.68 | P18: 1864.14 | Q18: 449.27 | R18: 442.96 | S18: 451.08 | T18: 559.46 | U18: 1859.21 | V18: 451.68 | W18: 471.07 | X18: 432.47 | Y18: 545.71 | Z18: 1861.54 | AA18: 458.22 | AB18: 478.48 | AC18: 437.21 | AD18: 550.98 | AE18: 1877.42
A19: Total Mexico Wireless revenue | B19: 971 | C19: 1054 | D19: 1095 | E19: 1259 | F19: 4379 | G19: 1173 | H19: 1224 | I19: 1141.99 | J19: 1238.71 | K19: 4766.29 | L19: 1182.14 | M19: 1212.57 | N19: 1146.43 | O19: 1261.11 | P19: 4794.91 | Q19: 1180.21 | R19: 1202.82 | S19: 1138.85 | T19: 1275.94 | U19: 4841.3 | V19: 1198.29 | W19: 1248.73 | X19: 1135.25 | Y19: 1278.41 | Z19: 4917.94 | AA19: 1219.63 | AB19: 1270.61 | AC19: 1148.41 | AD19: 1292.46 | AE19: 4967.3
A20: Latin America revenue | B20: 971 | C20: 1054 | D20: 1095 | E20: 1259 | F20: 4379 | G20: 1173 | H20: 1224 | I20: 1149.49 | J20: 1247.25 | K20: 4784.74 | L20: 1185.98 | M20: 1221.23 | N20: 1155.52 | O20: 1261.88 | P20: 4833.03 | Q20: 1180.21 | R20: 1202.82 | S20: 1138.85 | T20: 1275.94 | U20: 4891.37 | V20: 1198.29 | W20: 1248.73 | X20: 1135.25 | Y20: 1278.41 | Z20: 4975.67 | AA20: 1219.63 | AB20: 1270.61 | AC20: 1148.41 | AD20: 1292.46 | AE20: 5043.04
A22: Operations and Support - Mexico international | B22: 778 | C22: 853 | D22: 896 | E22: 1036 | F22: 3563 | G22: 953 | H22: 997 | I22: 944.1 | J22: 990.14 | K22: 3884.25 | L22: 978.83 | M22: 1027.5 | N22: 971.72 | O22: 1036.25 | P22: 3945.59 | Q22: 933.28 | R22: 1006.5 | S22: 898.29 | T22: 1005.7 | U22: 3993.7 | V22: 944.04 | W22: 1018.63 | X22: 909.73 | Y22: 1019.57 | Z22: 4045.76 | AA22: 956.5 | AB22: 1032.13 | AC22: 922.1 | AD22: 1034.08 | AE22: 4108.31
A23: Operations and Support - International | B23: - | C23: - | D23: - | E23: - | F23: - | G23: - | H23: - | I23: - | J23: - | K23: - | L23: - | M23: - | N23: - | O23: - | P23: - | Q23: - | R23: - | S23: - | T23: - | U23: - | V23: - | W23: - | X23: - | Y23: - | Z23: - | AA23: - | AB23: - | AC23: - | AD23: - | AE23: -
A24: Operations and support - Latin America | B24: 778 | C24: 853 | D24: 896 | E24: 1036 | F24: 3563 | G24: 953 | H24: 997 | I24: 940.16 | J24: 1022.58 | K24: 3904.51 | L24: 961.39 | M24: 987.02 | N24: 937.2 | O24: 1027.98 | P24: 3911.34 | Q24: 956.9 | R24: 973.35 | S24: 931.92 | T24: 1042.68 | U24: 3957.45 | V24: 973.78 | W24: 1011.7 | X24: 924.04 | Y24: 1047.28 | Z24: 4010.34 | AA24: 989.46 | AB24: 1027.67 | AC24: 933.24 | AD24: 1057.07 | AE24: 4055.68
A25: EBITDA - Mexico International | B25: 193 | C25: 201 | D25: 199 | E25: 223 | F25: 816 | G25: 220 | H25: 227 | I25: 215.23 | J25: 224.57 | K25: 879.66 | L25: 233.4 | M25: 240.32 | N25: 225.14 | O25: 237.75 | P25: 934.81 | Q25: 256.11 | R25: 261.89 | S25: 232.78 | T25: 258.9 | U25: 994.45 | V25: 278 | W25: 282.51 | X25: 246.43 | Y25: 274.06 | Z25: 1043.4 | AA25: 302.01 | AB25: 304.92 | AC25: 260.87 | AD25: 290.06 | AE25: 1078.92
A26: EBITDA - International | B26: - | C26: - | D26: - | E26: - | F26: - | G26: - | H26: - | I26: - | J26: - | K26: - | L26: - | M26: - | N26: - | O26: - | P26: - | Q26: - | R26: - | S26: - | T26: - | U26: - | V26: - | W26: - | X26: - | Y26: - | Z26: - | AA26: - | AB26: - | AC26: - | AD26: - | AE26: -
A27: EBITDA - Latin America | B27: 193 | C27: 201 | D27: 199 | E27: 223 | F27: 816 | G27: 220 | H27: 227 | I27: 205.57 | J27: 224.38 | K27: 875.67 | L27: 220.07 | M27: 229.04 | N27: 209.24 | O27: 233.14 | P27: 907.83 | Q27: 223.31 | R27: 229.47 | S27: 206.93 | T27: 233.26 | U27: 933.92 | V27: 224.51 | W27: 237.03 | X27: 211.22 | Y27: 231.13 | Z27: 965.33 | AA27: 230.18 | AB27: 242.93 | AC27: 215.16 | AD27: 235.39 | AE27: 987.36
A28: Depreciation and amortization - Latin America | B28: 150 | C28: 155 | D28: 177 | E28: 189 | F28: 671 | G28: 200 | H28: 189 | I28: 186.84 | J28: 192.26 | K28: 763.64 | L28: 187.78 | M28: 185.79 | N28: 183.07 | O28: 189.19 | P28: 740.38 | Q28: 189.16 | R28: 185.47 | S28: 182.88 | T28: 186.7 | U28: 738.15 | V28: 188.81 | W28: 184.64 | X28: 180.85 | Y28: 185.35 | Z28: 734.52 | AA28: 190.22 | AB28: 186.42 | AC28: 182.18 | AD28: 186.45 | AE28: 735.84
A29: Total operating expenses - International | B29: 928 | C29: 1008 | D29: 1073 | E29: 1225 | F29: 4234 | G29: 1153 | H29: 1186 | I29: 1128.92 | J29: 1209.87 | K29: 4661.45 | L29: 1147.25 | M29: 1179.81 | N29: 1119.41 | O29: 1213.77 | P29: 4637.33 | Q29: 1132.98 | R29: 1168.59 | S29: 1107.17 | T29: 1210.58 | U29: 4653.16 | V29: 1132.42 | W29: 1167.56 | X29: 1088.29 | Y29: 1210.92 | Z29: 4682.15 | AA29: 1138.76 | AB29: 1176.22 | AC29: 1094.62 | AD29: 1217.04 | AE29: 4707.55
A30: Operating income/(loss) - Latin America | B30: 43 | C30: 46 | D30: 22 | E30: 34 | F30: 145 | G30: 20 | H30: 38 | I30: 17.23 | J30: 32.01 | K30: 109.32 | L30: 31.47 | M30: 44.41 | N30: 22.63 | O30: 41.4 | P30: 154.17 | Q30: 28.91 | R30: 46.07 | S30: 18.68 | T30: 41.88 | U30: 177.49 | V30: 22.33 | W30: 41.02 | X30: 21.56 | Y30: 35.06 | Z30: 189.53 | AA30: 22 | AB30: 41.02 | AC30: 21.56 | AD30: 35.28 | AE30: 195.91
A31: Equity in Net Income (Loss) of Affiliates - International | B31: - | C31: - | D31: - | E31: - | F31: - | G31: - | H31: - | I31: - | J31: - | K31: - | L31: - | M31: - | N31: - | O31: - | P31: - | Q31: - | R31: - | S31: - | T31: - | U31: - | V31: - | W31: - | X31: - | Y31: - | Z31: - | AA31: - | AB31: - | AC31: - | AD31: - | AE31: -
A32: Segment Income (Loss)- International | B32: 43 | C32: 46 | D32: 22 | E32: 34 | F32: 145 | G32: 20 | H32: 38 | I32: 31.23 | J32: 32.97 | K32: 122.2 | L32: 40.3 | M32: 45.29 | N32: 43.85 | O32: 51.32 | P32: 168.93 | Q32: - | R32: - | S32: - | T32: - | U32: 168.14 | V32: - | W32: - | X32: - | Y32: - | Z32: 168.52 | AA32: - | AB32: - | AC32: - | AD32: - | AE32: 169.86
A34: Mexico - Wireless
A35: Net Adds - Postpaid - Mexico international(K#) | B35: 160 | C35: 183 | D35: 243 | E35: 328 | F35: 914 | G35: 337 | H35: 369 | I35: 225 | J35: 350 | K35: 1281 | L35: 220.19 | M35: 248.84 | N35: 213.75 | O35: 339.25 | P35: 1022.03 | Q35: - | R35: - | S35: - | T35: - | U35: 1336.41 | V35: - | W35: - | X35: - | Y35: - | Z35: 1265.48 | AA35: - | AB35: - | AC35: - | AD35: - | AE35: 1192.96
A36: Subscribers - Postpaid - Mexico international(K#) | B36: 5997 | C36: 6180 | D36: 6423 | E36: 6751 | F36: 6751 | G36: 7088 | H36: 7457 | I36: 7682 | J36: 8032 | K36: 8032 | L36: 8252.18 | M36: 8501.03 | N36: 8714.78 | O36: 9054.03 | P36: 9054.03 | Q36: - | R36: - | S36: - | T36: - | U36: 9705.96 | V36: - | W36: - | X36: - | Y36: - | Z36: 10257.69 | AA36: - | AB36: - | AC36: - | AD36: - | AE36: 10726.82
A37: Net Adds - Prepaid - Mexico international(K#) | B37: -110 | C37: 64 | D37: 68 | E37: 222 | F37: 244 | G37: -895 | H37: -1006 | I37: -355 | J37: -300 | K37: -2556 | L37: -478 | M37: -375.37 | N37: 428.41 | O37: 731.36 | P37: 306.4 | Q37: - | R37: - | S37: - | T37: - | U37: 540.5 | V37: - | W37: - | X37: - | Y37: - | Z37: 544.2 | AA37: - | AB37: - | AC37: - | AD37: - | AE37: 538.18
A38: Subscribers - Prepaid - Mexico international(K#) | B38: 17376 | C38: 17440 | D38: 17508 | E38: 17730 | F38: 17730 | G38: 16835 | H38: 15829 | I38: 15474 | J38: 15174 | K38: 15174 | L38: 14696 | M38: 14320.63 | N38: 14749.04 | O38: 15480.4 | P38: 15480.4 | Q38: - | R38: - | S38: - | T38: - | U38: 15795.75 | V38: - | W38: - | X38: - | Y38: - | Z38: 16105.16 | AA38: - | AB38: - | AC38: - | AD38: - | AE38: 16405.24
A39: Net Adds - Reseller - Mexico international(K#) | B39: -18 | C39: -12 | D39: -5 | E39: -19 | F39: -54 | G39: -19 | H39: -31 | I39: -17.67 | J39: -4.73 | K39: -60.4 | L39: -14.57 | M39: -15.89 | N39: -4.85 | O39: -9.36 | P39: -44.67 | Q39: -1.16 | R39: 0.92 | S39: -0.88 | T39: 0.49 | U39: -61.91 | V39: - | W39: - | X39: - | Y39: - | Z39: -96.08 | AA39: - | AB39: - | AC39: - | AD39: - | AE39: -97.3
A40: Subscribers - Reseller - Mexico international(K#) | B40: 235 | C40: 223 | D40: 218 | E40: 199 | F40: 199 | G40: 180 | H40: 149 | I40: 143.33 | J40: 138.6 | K40: 138.6 | L40: 124.03 | M40: 108.14 | N40: 103.29 | O40: 93.93 | P40: 93.93 | Q40: 155.19 | R40: 156.11 | S40: 155.23 | T40: 155.72 | U40: 87.54 | V40: - | W40: - | X40: - | Y40: - | Z40: 44.2 | AA40: - | AB40: - | AC40: - | AD40: - | AE40: 34.97
A42: Beginning Subscribers - Mexico international(K#) | B42: 23576 | C42: 23608 | D42: 23843 | E42: 24149 | F42: 23576 | G42: 24680 | H42: 24103 | I42: 23428.28 | J42: 23444.94 | K42: 24554.2 | L42: 23465.05 | M42: 23191.78 | N42: 22747.55 | O42: 22881.32 | P42: 23675.49 | Q42: 22764.15 | R42: 22575.24 | S42: 22037.82 | T42: 22091.4 | U42: 23385.67 | V42: 22910.32 | W42: 22823.75 | X42: 22499.82 | Y42: 22578.37 | Z42: 23714.13 | AA42: 22899.27 | AB42: 22854.97 | AC42: 22568.43 | AD42: 22649.37 | AE42: 23874.79
A43: Gross Additions - Mexico international(K#) | B43: 4023.77 | C43: 4277.83 | D43: 4402.12 | E43: 4779.12 | F43: 17482.83 | G43: 3528.09 | H43: 3004.31 | I43: 3878.27 | J43: 4189.35 | K43: 14557.31 | L43: 3539.62 | M43: 3074.37 | N43: 3894.11 | O43: 4232.05 | P43: 14946.86 | Q43: 3572.6 | R43: 2883.56 | S43: 3717.36 | T43: 4016.62 | U43: 14851.07 | V43: 3779.25 | W43: 3189.04 | X43: 3870.17 | Y43: 4234.71 | Z43: 15266.77 | AA43: 3824.46 | AB43: 3231.15 | AC43: 3895.2 | AD43: 4258.82 | AE43: 15242.38
A44: Disconnects - Mexico international(K#) | B44: 3991.77 | C44: 4042.83 | D44: 4096.12 | E44: 4248.12 | F44: 16378.83 | G44: 4105.09 | H44: 3672.31 | I44: 3944.12 | J44: 4021.6 | K44: 15662.52 | L44: 3869.71 | M44: 3564.72 | N44: 3804.91 | O44: 3910.52 | P44: 15394.38 | Q44: 3766.42 | R44: 3405.25 | S44: 3722.46 | T44: 3814.27 | U44: 15058.24 | V44: 3798.87 | W44: 3491.4 | X44: 3811.92 | Y44: 3902.89 | Z44: 15140.34 | AA44: 3804.53 | AB44: 3502.15 | AC44: 3827.96 | AD44: 3920.53 | AE44: 15095.79
A45: Monthly churn - Mexico international(%) | B45: 0.0564 | C45: 0.0568 | D45: 0.0569 | E45: 0.058 | F45: 0.057 | G45: 0.0561 | H45: 0.0515 | I45: 0.0572 | J45: 0.058 | K45: 0.055 | L45: 0.0565 | M45: 0.0534 | N45: 0.057 | O45: 0.0579 | P45: 0.0556 | Q45: 0.0559 | R45: 0.0513 | S45: 0.0567 | T45: 0.0578 | U45: 0.0544 | V45: 0.0557 | W45: 0.0511 | X45: 0.0565 | Y45: 0.0576 | Z45: 0.0539 | AA45: 0.0555 | AB45: 0.051 | AC45: 0.0564 | AD45: 0.0575 | AE45: 0.0534
A46: Net Additions - Mexico international(K#) | B46: 32 | C46: 235 | D46: 306 | E46: 531 | F46: 1104 | G46: -577 | H46: -668 | I46: 47.06 | J46: 264.48 | K46: -807.3 | L46: -303.72 | M46: -440.57 | N46: 161.8 | O46: 395.53 | P46: -151.41 | Q46: -267.97 | R46: -574.92 | S46: 66.32 | T46: 306.61 | U46: -65.55 | V46: -86.57 | W46: -323.93 | X46: 78.55 | Y46: 320.9 | Z46: 160.67 | AA46: -44.29 | AB46: -286.54 | AC46: 80.94 | AD46: 317.76 | AE46: -113.15
A47: Adjustments/Other - Mexico international(K#) | B47: - | C47: - | D47: - | E47: - | F47: - | G47: - | H47: 20 | I47: - | J47: - | K47: 20 | L47: - | M47: - | N47: - | O47: - | P47: - | Q47: - | R47: - | S47: - | T47: - | U47: - | V47: - | W47: - | X47: - | Y47: - | Z47: - | AA47: - | AB47: - | AC47: - | AD47: - | AE47: -
A48: Ending Subscribers - Mexico international(K#) | B48: 23608 | C48: 23843 | D48: 24149 | E48: 24680 | F48: 24680 | G48: 24103 | H48: 23435 | I48: 23444.94 | J48: 23675.49 | K48: 23675.49 | L48: 23191.78 | M48: 22747.55 | N48: 22881.32 | O48: 23234.32 | P48: 23486.69 | Q48: 22575.24 | R48: 22037.82 | S48: 22091.4 | T48: 22356.17 | U48: 23322.22 | V48: 22823.75 | W48: 22499.82 | X48: 22578.37 | Y48: 22899.27 | Z48: 23874.79 | AA48: 22854.97 | AB48: 22568.43 | AC48: 22649.37 | AD48: 22967.13 | AE48: 23761.64
A49: Average Subscribers - Mexico international(K#) | B49: 23592 | C49: 23725.5 | D49: 23996 | E49: 24414.5 | F49: 24128 | G49: 24391.5 | H49: 23769 | I49: 23436.61 | J49: 23560.22 | K49: 23985.6 | L49: 23328.42 | M49: 22969.67 | N49: 22814.44 | O49: 23057.82 | P49: 23510.62 | Q49: 22669.7 | R49: 22306.53 | S49: 22064.61 | T49: 22223.79 | U49: 23289.14 | V49: 22867.04 | W49: 22661.79 | X49: 22539.09 | Y49: 22738.82 | Z49: 23725.29 | AA49: 22877.12 | AB49: 22711.7 | AC49: 22608.9 | AD49: 22808.25 | AE49: 23753.61
A50: Service ARPU - Mexico international($) | B50: 8.69 | C50: 9.3 | D50: 9.67 | E50: 10.13 | F50: 9.38 | G50: 10.29 | H50: 10.94 | I50: 10.16 | J50: 10.37 | K50: 10.33 | L50: 10.49 | M50: 10.86 | N50: 10.3 | O50: 10.52 | P50: 10.41 | Q50: 10.77 | R50: 11.34 | S50: 10.39 | T50: 10.77 | U50: 10.69 | V50: 10.9 | W50: 11.41 | X50: 10.4 | Y50: 10.77 | Z50: 10.76 | AA50: 11.1 | AB50: 11.59 | AC50: 10.49 | AD50: 10.86 | AE50: 10.86
A51: Mexico wireless service revenue | B51: 615 | C51: 662 | D51: 696 | E51: 742 | F51: 2715 | G51: 753 | H51: 780 | I51: 713.78 | J51: 732.21 | K51: 2968.51 | L51: 732.73 | M51: 747.95 | N51: 703.81 | O51: 725.43 | P51: 2930.77 | Q51: 730.95 | R51: 759.87 | S51: 687.77 | T51: 716.48 | U51: 2982.09 | V51: 746.61 | W51: 777.66 | X51: 702.78 | Y51: 732.7 | Z51: 3056.4 | AA51: 761.41 | AB51: 792.13 | AC51: 711.2 | AD51: 741.48 | AE51: 3089.88
A53: Gross Additions - Mexico international(K#) | B53: 4023.77 | C53: 4277.83 | D53: 4402.12 | E53: 4779.12 | F53: 17482.83 | G53: 3528.09 | H53: 3004.31 | I53: 3878.27 | J53: 4189.35 | K53: 14557.31 | L53: 3539.62 | M53: 3074.37 | N53: 3894.11 | O53: 4232.05 | P53: 14946.86 | Q53: 3572.6 | R53: 2883.56 | S53: 3717.36 | T53: 4016.62 | U53: 14851.07 | V53: 3779.25 | W53: 3189.04 | X53: 3870.17 | Y53: 4234.71 | Z53: 15266.77 | AA53: 3824.46 | AB53: 3231.15 | AC53: 3895.2 | AD53: 4258.82 | AE53: 15242.38
A54: Equipment Revenue / Gross Additions - International($) | B54: 88.47 | C54: 91.64 | D54: 90.64 | E54: 108.18 | F54: 95.18 | G54: 119.04 | H54: 147.79 | I54: 110.63 | J54: 122.42 | K54: 123.58 | L54: 125.53 | M54: 147.48 | N54: 113.45 | O54: 126.97 | P54: 124.25 | Q54: 130.76 | R54: 158.46 | S54: 125.19 | T54: 142.84 | U54: 127.06 | V54: 124.69 | W54: 151.15 | X54: 115.09 | Y54: 131.79 | Z54: 122.37 | AA54: 125.74 | AB54: 152.37 | AC54: 115.99 | AD54: 132.82 | AE54: 124.16
A55: Mexico wireless equipment revenue | B55: 356 | C55: 392 | D55: 399 | E55: 517 | F55: 1664 | G55: 420 | H55: 444 | I55: 428.21 | J55: 506.49 | K55: 1797.77 | L55: 449.42 | M55: 464.62 | N55: 442.62 | O55: 535.68 | P55: 1864.14 | Q55: 449.27 | R55: 442.96 | S55: 451.08 | T55: 559.46 | U55: 1859.21 | V55: 451.68 | W55: 471.07 | X55: 432.47 | Y55: 545.71 | Z55: 1861.54 | AA55: 458.22 | AB55: 478.48 | AC55: 437.21 | AD55: 550.98 | AE55: 1877.42
A56: Vrio
A57: Vrio (Video entertainment) subscribers - international(K#) | B57: - | C57: - | D57: - | E57: - | F57: - | G57: - | H57: - | I57: - | J57: - | K57: - | L57: - | M57: - | N57: - | O57: - | P57: - | Q57: - | R57: - | S57: - | T57: - | U57: - | V57: - | W57: - | X57: - | Y57: - | Z57: - | AA57: - | AB57: - | AC57: - | AD57: - | AE57: -
A58: Vrio (Video entertainment) net adds - international(K#) | B58: - | C58: - | D58: - | E58: - | F58: - | G58: - | H58: - | I58: - | J58: - | K58: - | L58: - | M58: - | N58: - | O58: - | P58: - | Q58: - | R58: - | S58: - | T58: - | U58: - | V58: - | W58: - | X58: - | Y58: - | Z58: - | AA58: - | AB58: - | AC58: - | AD58: - | AE58: -
A59: Vrio (Video entertainment) average subscribers - international(K#) | B59: - | C59: - | D59: - | E59: - | F59: - | G59: - | H59: - | I59: - | J59: - | K59: - | L59: - | M59: - | N59: - | O59: - | P59: - | Q59: - | R59: - | S59: - | T59: - | U59: - | V59: - | W59: - | X59: - | Y59: - | Z59: - | AA59: - | AB59: - | AC59: - | AD59: - | AE59: -
A60: Vrio (Video entertainment) ARPU - International($) | B60: - | C60: - | D60: - | E60: - | F60: - | G60: - | H60: - | I60: - | J60: - | K60: - | L60: - | M60: - | N60: - | O60: - | P60: - | Q60: - | R60: - | S60: - | T60: - | U60: - | V60: - | W60: - | X60: - | Y60: - | Z60: - | AA60: - | AB60: - | AC60: - | AD60: - | AE60: -
A61: Vrio (Video entertainment) - International | B61: - | C61: - | D61: - | E61: - | F61: - | G61: - | H61: - | I61: - | J61: - | K61: - | L61: - | M61: - | N61: - | O61: - | P61: - | Q61: - | R61: - | S61: - | T61: - | U61: - | V61: - | W61: - | X61: - | Y61: - | Z61: - | AA61: - | AB61: - | AC61: - | AD61: - | AE61: -

Sheet AC Internet
A2: AT&T Inc. | Advanced Connectivity - Internet
A3: NYSE:T (MI KEY: 4024242; SPCIQ KEY: 100231)
A5: Visible Alpha
A7: Period Type : Fiscal Quarter, Fiscal Halves, Fiscal Year
A8: Period Start : 2025
A9: Period End : 2030
A10: Currency : Reported
A11: Consensus View : Mean
A12: As Of: 10/20/2026
A14: All numbers in $M unless otherwise indicated | B14: FQ1 2025A | C14: FQ2 2025A | D14: FQ3 2025A | E14: FQ4 2025A | F14: FY2025A | G14: FQ1 2026A | H14: FQ2 2026A | I14: FQ3 2026E | J14: FQ4 2026E | K14: FY2026E | L14: FQ1 2027E | M14: FQ2 2027E | N14: FQ3 2027E | O14: FQ4 2027E | P14: FY2027E | Q14: FQ1 2028E | R14: FQ2 2028E | S14: FQ3 2028E | T14: FQ4 2028E | U14: FY2028E | V14: FQ1 2029E | W14: FQ2 2029E | X14: FQ3 2029E | Y14: FQ4 2029E | Z14: FY2029E | AA14: FQ1 2030E | AB14: FQ2 2030E | AC14: FQ3 2030E | AD14: FQ4 2030E | AE14: FY2030E
A15: Number of Contributors Available | B15: 19 | C15: 19 | D15: 19 | E15: 19 | F15: 20 | G15: 19 | H15: 19 | I15: 20 of 20 | J15: 20 of 20 | K15: 20 of 20 | L15: 14 of 20 | M15: 14 of 20 | N15: 13 of 20 | O15: 13 of 20 | P15: 20 of 20 | Q15: 7 of 20 | R15: 7 of 20 | S15: 7 of 20 | T15: 7 of 20 | U15: 17 of 20 | V15: 5 of 20 | W15: 5 of 20 | X15: 5 of 20 | Y15: 5 of 20 | Z15: 14 of 20 | AA15: 5 of 20 | AB15: 5 of 20 | AC15: 5 of 20 | AD15: 5 of 20 | AE15: 14 of 20
A16: Advanced Home Internet
A17: AT&T Fiber - Net adds(K#) | B17: 261 | C17: 243 | D17: 288 | E17: 283 | F17: 1075 | G17: 1394 | H17: 344 | I17: 364.28 | J17: 351.84 | K17: 2313.99 | L17: 326.27 | M17: 361.43 | N17: 388.7 | O17: 374.43 | P17: 1426.52 | Q17: 370.76 | R17: 398.71 | S17: 416.39 | T17: 404.08 | U17: 1514.26 | V17: 393.01 | W17: 415.15 | X17: 438.05 | Y17: 433.08 | Z17: 1515.4 | AA17: 394.1 | AB17: 415.84 | AC17: 439.81 | AD17: 434.06 | AE17: 1479.98
A18: AT&T Fiber connections(K#) | B18: 9592 | C18: 9835 | D18: 10123 | E18: 10406 | F18: 10406 | G18: 11800 | H18: 12144 | I18: 12508.28 | J18: 12860.12 | K18: 12860.12 | L18: 13193.69 | M18: 13555.12 | N18: 13943.81 | O18: 14318.24 | P18: 14292.38 | Q18: 14697.09 | R18: 15095.8 | S18: 15512.19 | T18: 15916.27 | U18: 15813.32 | V18: 16394.44 | W18: 16809.59 | X18: 17247.64 | Y18: 17680.72 | Z18: 17347.04 | AA18: 18074.82 | AB18: 18490.66 | AC18: 18930.47 | AD18: 19364.53 | AE18: 18827.02
A19: Average AT&T Fiber connections(K#) | B19: 9461.5 | C19: 9713.5 | D19: 9979 | E19: 10264.5 | F19: 9868.5 | G19: 11103 | H19: 11972 | I19: 12326.14 | J19: 12684.2 | K19: 11729.66 | L19: 13030.55 | M19: 13374.4 | N19: 13749.46 | O19: 14131.02 | P19: 13574.85 | Q19: 14511.71 | R19: 14896.45 | S19: 15304 | T19: 15714.23 | U19: 15051.34 | V19: 16197.94 | W19: 16602.02 | X19: 17028.61 | Y19: 17464.18 | Z19: 16583.6 | AA19: 17877.77 | AB19: 18282.74 | AC19: 18710.56 | AD19: 19147.5 | AE19: 18081.25
A20: Fiber ARPU($) | B20: 72.85 | C20: 73.26 | D20: 73.48 | E20: 72.87 | F20: 73.12 | G20: 74.09 | H20: 72.29 | I20: 73.05 | J20: 72.76 | K20: 73.82 | L20: 74.19 | M20: 73.66 | N20: 73.87 | O20: 73.57 | P20: 74.06 | Q20: 76.26 | R20: 75.75 | S20: 76.13 | T20: 75.68 | U20: 75.54 | V20: 77.16 | W20: 76.69 | X20: 77.17 | Y20: 77.1 | Z20: 76.36 | AA20: 78.89 | AB20: 78.4 | AC20: 78.87 | AD20: 78.77 | AE20: 77.79
A21: Fiber revenue | B21: 2066 | C21: 2136 | D21: 2198 | E21: 2245 | F21: 8645 | G21: 2505 | H21: 2593 | I21: 2667.53 | J21: 2733.45 | K21: 10498.26 | L21: 2872.55 | M21: 2926.28 | N21: 3016.16 | O21: 3087.23 | P21: 11955.67 | Q21: 3260.63 | R21: 3322.67 | S21: 3429.64 | T21: 3501.33 | U21: 13493.42 | V21: 3745.84 | W21: 3815.16 | X21: 3936.65 | Y21: 4032.36 | Z21: 15207.68 | AA21: 4224.6 | AB21: 4292.53 | AC21: 4417.96 | AD21: 4514.36 | AE21: 16897.84
A23: AT&T Internet Air - Net adds(K#) | B23: 169 | C23: 203 | D23: 270 | E23: 221 | F23: 875 | G23: 239 | H23: 215 | I23: 245.41 | J23: 227.44 | K23: 926.84 | L23: 226.09 | M23: 211.19 | N23: 243.83 | O23: 214.23 | P23: 886.13 | Q23: 190.31 | R23: 173.72 | S23: 201.89 | T23: 175.57 | U23: 766.14 | V23: 159.58 | W23: 145.87 | X23: 162.15 | Y23: 145.58 | Z23: 625.77 | AA23: 145.43 | AB23: 131.92 | AC23: 148 | AD23: 131.55 | AE23: 552.17
A24: AT&T Internet Air connections(K#) | B24: 803 | C24: 1006 | D24: 1276 | E24: 1497 | F24: 1497 | G24: 1736 | H24: 1951 | I24: 2196.41 | J24: 2423.84 | K24: 2423.84 | L24: 2646.4 | M24: 2857.59 | N24: 3101.42 | O24: 3315.65 | P24: 3306.16 | Q24: 3432.67 | R24: 3606.4 | S24: 3808.28 | T24: 3983.86 | U24: 4044.74 | V24: 4012.27 | W24: 4158.14 | X24: 4320.29 | Y24: 4465.88 | Z24: 4626.01 | AA24: 4611.31 | AB24: 4743.23 | AC24: 4891.23 | AD24: 5022.78 | AE24: 5178.17
A25: AT&T Internet Air average connections(K#) | B25: 718.5 | C25: 904.5 | D25: 1141 | E25: 1386.5 | F25: 1065.5 | G25: 1616.5 | H25: 1843.5 | I25: 2073.7 | J25: 2310.12 | K25: 1961.18 | L25: 2533.35 | M25: 2751.99 | N25: 2979.5 | O25: 3208.53 | P25: 2863.66 | Q25: 3337.51 | R25: 3519.53 | S25: 3707.34 | T25: 3896.07 | U25: 3662.27 | V25: 3932.48 | W25: 4085.21 | X25: 4239.22 | Y25: 4393.08 | Z25: 4313.81 | AA25: 4538.59 | AB25: 4677.27 | AC25: 4817.23 | AD25: 4957 | AE25: 4902.78
A26: AT&T Internet Air ARPU($) | B26: 61.74 | C26: 60.57 | D26: 62.28 | E26: 61.8 | F26: 61.65 | G26: 61.01 | H26: 60.09 | I26: 61.61 | J26: 61.62 | K26: 61.1 | L26: 61.11 | M26: 60.52 | N26: 62.04 | O26: 62.03 | P26: 61.43 | Q26: 61.94 | R26: 61.19 | S26: 63.26 | T26: 63.36 | U26: 61.92 | V26: 64.13 | W26: 63.41 | X26: 65.95 | Y26: 66.15 | Z26: 63.02 | AA26: 65.39 | AB26: 64.63 | AC26: 67.22 | AD26: 67.41 | AE26: 63.7
A27: AT&T Internet Air revenue | B27: 132 | C27: 163 | D27: 213 | E27: 257 | F27: 765 | G27: 294 | H27: 333 | I27: 383.24 | J27: 426.95 | K27: 1437.27 | L27: 464.32 | M27: 499.52 | N27: 553.99 | O27: 596.25 | P27: 2109.42 | Q27: 618.99 | R27: 644.6 | S27: 700.88 | T27: 736.82 | U27: 2717.44 | V27: 754.5 | W27: 774.89 | X27: 835.48 | Y27: 867.05 | Z27: 3255.19 | AA27: 886.28 | AB27: 902.73 | AC27: 965.38 | AD27: 994.24 | AE27: 3734.21
A29: Internal/Organic net adds - Advanced home internet connections(K#) | B29: 442 | C29: 446 | D29: 558 | E29: 504 | F29: 1950 | G29: 512 | H29: 559 | I29: 613.68 | J29: 584.39 | K29: 2269.07 | L29: 553.72 | M29: 568.76 | N29: 648.15 | O29: 585.2 | P29: 2377.87 | Q29: 558.5 | R29: 557 | S29: 610 | T29: 552.5 | U29: 2374.04 | V29: 542 | W29: 559 | X29: 600 | Y29: 560 | Z29: 2252.26 | AA29: 502 | AB29: 519 | AC29: 560 | AD29: 520 | AE29: 2122.99
A30: Net adds acquired - Advanced home internet connections(K#) | B30: -12 | C30: - | D30: - | E30: - | F30: -12 | G30: 1121 | H30: - | I30: - | J30: - | K30: 1121 | L30: - | M30: - | N30: - | O30: - | P30: - | Q30: - | R30: - | S30: - | T30: - | U30: - | V30: - | W30: - | X30: - | Y30: - | Z30: - | AA30: - | AB30: - | AC30: - | AD30: - | AE30: -
A31: Advanced home internet connections - Net adds(K#) | B31: 430 | C31: 446 | D31: 558 | E31: 504 | F31: 1938 | G31: 1633 | H31: 559 | I31: 609.69 | J31: 579.27 | K31: 3380.96 | L31: 552.35 | M31: 572.62 | N31: 632.53 | O31: 588.66 | P31: 2312.65 | Q31: 561.07 | R31: 572.43 | S31: 618.28 | T31: 579.65 | U31: 2280.41 | V31: 552.59 | W31: 561.01 | X31: 600.2 | Y31: 578.66 | Z31: 2141.17 | AA31: 539.53 | AB31: 547.76 | AC31: 587.81 | AD31: 565.61 | AE31: 2032.15
A32: Advanced home internet connections(K#) | B32: 10395 | C32: 10841 | D32: 11399 | E32: 11903 | F32: 11903 | G32: 13536 | H32: 14095 | I32: 14704.69 | J32: 15283.96 | K32: 15283.96 | L32: 15840.09 | M32: 16412.7 | N32: 17045.23 | O32: 17633.89 | P32: 17598.54 | Q32: 18129.76 | R32: 18702.19 | S32: 19320.47 | T32: 19900.12 | U32: 19858.06 | V32: 20406.72 | W32: 20967.73 | X32: 21567.93 | Y32: 22146.59 | Z32: 21973.05 | AA32: 22686.13 | AB32: 23233.89 | AC32: 23821.7 | AD32: 24387.31 | AE32: 24005.19
A33: Advanced home internet average connections(K#) | B33: 10180 | C33: 10618 | D33: 11120 | E33: 11651 | F33: 10934 | G33: 12719.5 | H33: 13815.5 | I33: 14399.84 | J33: 14994.32 | K33: 13616.96 | L33: 15563.91 | M33: 16126.39 | N33: 16728.97 | O33: 17339.56 | P33: 16442.22 | Q33: 17849.23 | R33: 18415.98 | S33: 19011.33 | T33: 19610.3 | U33: 18717.85 | V33: 20130.42 | W33: 20687.22 | X33: 21267.83 | Y33: 21857.26 | Z33: 20902.46 | AA33: 22416.36 | AB33: 22960.01 | AC33: 23527.79 | AD33: 24104.5 | AE33: 22989.12
A34: Advanced home ARPU($) | B34: 72.07 | C34: 72.19 | D34: 72.33 | E34: 71.56 | F34: 72.03 | G34: 72.46 | H34: 70.66 | I34: 70.87 | J34: 70.64 | K34: 72.43 | L34: 71.64 | M34: 70.84 | N34: 71.25 | O34: 71.06 | P34: 71.57 | Q34: 72.9 | R34: 72.03 | S34: 72.79 | T34: 72.63 | U34: 72.48 | V34: 74.61 | W34: 74.07 | X34: 74.92 | Y34: 74.88 | Z34: 73.77 | AA34: 76.16 | AB34: 75.6 | AC34: 76.46 | AD34: 76.4 | AE34: 74.94
A35: Advanced home internet services revenue - Advanced connectivity | B35: 2198 | C35: 2299 | D35: 2411 | E35: 2502 | F35: 9410 | G35: 2799 | H35: 2926 | I35: 3065.8 | J35: 3181.73 | K35: 11993.31 | L35: 3349.99 | M35: 3432.08 | N35: 3580.82 | O35: 3701.07 | P35: 14128.13 | Q35: 3902.26 | R35: 3977 | S35: 4148.02 | T35: 4268.25 | U35: 16264.78 | V35: 4500.34 | W35: 4590.05 | X35: 4772.13 | Y35: 4899.41 | Z35: 18469.22 | AA35: 5110.89 | AB35: 5195.26 | AC35: 5383.34 | AD35: 5508.6 | AE35: 20618.1
A37: Advanced Connectivity Internet
A38: AT&T Fiber - Net adds(K#) | B38: 261 | C38: 243 | D38: 288 | E38: 283 | F38: 1075 | G38: 1394 | H38: 344 | I38: 364.28 | J38: 351.84 | K38: 2313.99 | L38: 326.27 | M38: 361.43 | N38: 388.7 | O38: 374.43 | P38: 1426.52 | Q38: 370.76 | R38: 398.71 | S38: 416.39 | T38: 404.08 | U38: 1514.26 | V38: 393.01 | W38: 415.15 | X38: 438.05 | Y38: 433.08 | Z38: 1515.4 | AA38: 394.1 | AB38: 415.84 | AC38: 439.81 | AD38: 434.06 | AE38: 1479.98
A39: AT&T Business Fiber - Net adds(K#) | B39: 22 | C39: 26 | D39: 21 | E39: 16 | F39: 85 | G39: 19 | H39: 23 | I39: 20.7 | J39: 18.2 | K39: 80.9 | L39: 22.29 | M39: 26.54 | N39: 23.83 | O39: 21.48 | P39: 91.06 | Q39: 24.27 | R39: 29.16 | S39: 26.88 | T39: 23.96 | U39: 93.09 | V39: 27.2 | W39: 32.45 | X39: 31.02 | Y39: 25.64 | Z39: 97.17 | AA39: 28.16 | AB39: 33.88 | AC39: 32.65 | AD39: 26.69 | AE39: 100.19
A40: Internal/Organic net adds - Fiber(K#) | B40: 283 | C40: 269 | D40: 309 | E40: 299 | F40: 1160 | G40: 292 | H40: 367 | I40: 391.46 | J40: 366.83 | K40: 1417.29 | L40: 329.61 | M40: 383.7 | N40: 405.99 | O40: 383.61 | P40: 1502.9 | Q40: 381 | R40: 419.33 | S40: 431.33 | T40: 416.33 | U40: 1623.59 | V40: 406.5 | W40: 461.5 | X40: 472 | Y40: 462 | Z40: 1606.88 | AA40: 416.5 | AB40: 471.5 | AC40: 482 | AD40: 472 | AE40: 1599.51
A41: Net adds acquired - Fiber(K#) | B41: - | C41: - | D41: - | E41: - | F41: - | G41: 1121 | H41: - | I41: - | J41: - | K41: 1121 | L41: - | M41: - | N41: - | O41: - | P41: - | Q41: - | R41: - | S41: - | T41: - | U41: - | V41: - | W41: - | X41: - | Y41: - | Z41: - | AA41: - | AB41: - | AC41: - | AD41: - | AE41: -
A42: Fiber - Net adds(K#) | B42: 283 | C42: 269 | D42: 309 | E42: 299 | F42: 1160 | G42: 1413 | H42: 367 | I42: 385.16 | J42: 371.03 | K42: 2363.73 | L42: 349.86 | M42: 384.9 | N42: 406.63 | O42: 391.43 | P42: 1502.42 | Q42: 411.62 | R42: 438.81 | S42: 462.11 | T42: 448.76 | U42: 1591.79 | V42: 436.31 | W42: 469.07 | X42: 496.09 | Y42: 484.32 | Z42: 1591.84 | AA42: 437.94 | AB42: 470.65 | AC42: 499.22 | AD42: 485.89 | AE42: 1567.35
A43: AT&T Internet Air - Net adds(K#) | B43: 169 | C43: 203 | D43: 270 | E43: 221 | F43: 875 | G43: 239 | H43: 215 | I43: 245.41 | J43: 227.44 | K43: 926.84 | L43: 226.09 | M43: 211.19 | N43: 243.83 | O43: 214.23 | P43: 886.13 | Q43: 190.31 | R43: 173.72 | S43: 201.89 | T43: 175.57 | U43: 766.14 | V43: 159.58 | W43: 145.87 | X43: 162.15 | Y43: 145.58 | Z43: 625.77 | AA43: 145.43 | AB43: 131.92 | AC43: 148 | AD43: 131.55 | AE43: 552.17
A44: Business FWA subs - net adds(K#) | B44: 52 | C44: 37 | D44: 34 | E44: 43 | F44: 166 | G44: 53 | H44: 64 | I44: 55.39 | J44: 53.88 | K44: 226.27 | L44: 58.56 | M44: 60.67 | N44: 53.11 | O44: 57 | P44: 225.79 | Q44: 55.4 | R44: 61 | S44: 49.4 | T44: 52.6 | U44: 209.83 | V44: 50.17 | W44: 57.17 | X44: 42.67 | Y44: 46.67 | Z44: 186.25 | AA44: 45.01 | AB44: 52.01 | AC44: 37.51 | AD44: 41.51 | AE44: 173.44
A45: Fixed wireless - Net adds(K#) | B45: 221 | C45: 240 | D45: 304 | E45: 264 | F45: 1029 | G45: 292 | H45: 279 | I45: 296.77 | J45: 284.07 | K45: 1151.84 | L45: 287.68 | M45: 275.5 | N45: 298.56 | O45: 277.19 | P45: 1120.31 | Q45: 249.14 | R45: 236.81 | S45: 250.72 | T45: 228.21 | U45: 974.64 | V45: 230.9 | W45: 220.76 | X45: 226.62 | Y45: 209.9 | Z45: 830.22 | AA45: 208.05 | AB45: 198.16 | AC45: 203.75 | AD45: 187.2 | AE45: 736.79
A46: Internal/Organic net adds - Advanced Connectivity Internet(K#) | B46: 516 | C46: 509 | D46: 613 | E46: 563 | F46: 2201 | G46: 584 | H46: 646 | I46: 688.02 | J46: 653.61 | K46: 2571.63 | L46: 636.45 | M46: 656.48 | N46: 711.05 | O46: 663.72 | P46: 2705.87 | Q46: 664.16 | R46: 680.92 | S46: 726.54 | T46: 683.97 | U46: 2770.7 | V46: 678.71 | W46: 705.97 | X46: 748.38 | Y46: 714 | Z46: 2686.96 | AA46: 663.06 | AB46: 690.04 | AC46: 733.86 | AD46: 698.33 | AE46: 2606.08
A47: Net adds acquired - Advanced Connectivity Internet(K#) | B47: -12 | C47: - | D47: - | E47: - | F47: -12 | G47: 1121 | H47: - | I47: - | J47: - | K47: 1121 | L47: - | M47: - | N47: - | O47: - | P47: - | Q47: - | R47: - | S47: - | T47: - | U47: - | V47: - | W47: - | X47: - | Y47: - | Z47: - | AA47: - | AB47: - | AC47: - | AD47: - | AE47: -
A48: Advanced Connectivity Internet - Net adds(K#) | B48: 504 | C48: 509 | D48: 613 | E48: 563 | F48: 2189 | G48: 1705 | H48: 646 | I48: 686.26 | J48: 656.36 | K48: 3693.62 | L48: 637.54 | M48: 660.4 | N48: 705.19 | O48: 668.63 | P48: 2622.72 | Q48: 660.76 | R48: 675.61 | S48: 712.83 | T48: 676.97 | U48: 2566.43 | V48: 667.22 | W48: 689.82 | X48: 722.71 | Y48: 694.22 | Z48: 2422.06 | AA48: 645.99 | AB48: 668.82 | AC48: 702.97 | AD48: 673.09 | AE48: 2304.14
A50: AT&T Fiber connections(K#) | B50: 9592 | C50: 9835 | D50: 10123 | E50: 10406 | F50: 10406 | G50: 11800 | H50: 12144 | I50: 12508.28 | J50: 12860.12 | K50: 12860.12 | L50: 13193.69 | M50: 13555.12 | N50: 13943.81 | O50: 14318.24 | P50: 14292.38 | Q50: 14697.09 | R50: 15095.8 | S50: 15512.19 | T50: 15916.27 | U50: 15813.32 | V50: 16394.44 | W50: 16809.59 | X50: 17247.64 | Y50: 17680.72 | Z50: 17347.04 | AA50: 18074.82 | AB50: 18490.66 | AC50: 18930.47 | AD50: 19364.53 | AE50: 18827.02
A51: AT&T Business Fiber connections(K#) | B51: 619 | C51: 645 | D51: 666 | E51: 682 | F51: 682 | G51: 701 | H51: 724 | I51: 744.76 | J51: 762.81 | K51: 762.81 | L51: 788.29 | M51: 814.83 | N51: 838.66 | O51: 860.14 | P51: 853.87 | Q51: 885.6 | R51: 914.76 | S51: 941.64 | T51: 965.6 | U51: 945.94 | V51: 997.45 | W51: 1029.9 | X51: 1060.93 | Y51: 1086.57 | Z51: 1043.01 | AA51: 1114.72 | AB51: 1148.6 | AC51: 1181.25 | AD51: 1207.94 | AE51: 1143.2
A52: Fiber connections(K#) | B52: 10211 | C52: 10480 | D52: 10789 | E52: 11088 | F52: 11088 | G52: 12501 | H52: 12868 | I52: 13257.75 | J52: 13631.37 | K52: 13631.37 | L52: 13987.4 | M52: 14372.31 | N52: 14778.94 | O52: 15170.37 | P52: 15133.79 | Q52: 15671.5 | R52: 16110.3 | S52: 16572.42 | T52: 17021.18 | U52: 16731.92 | V52: 17556.78 | W52: 18025.85 | X52: 18521.94 | Y52: 19006.26 | Z52: 18334.55 | AA52: 19444.2 | AB52: 19914.85 | AC52: 20414.07 | AD52: 20899.97 | AE52: 19901.9
A53: AT&T Internet Air connections(K#) | B53: 803 | C53: 1006 | D53: 1276 | E53: 1497 | F53: 1497 | G53: 1736 | H53: 1951 | I53: 2196.41 | J53: 2423.84 | K53: 2423.84 | L53: 2646.4 | M53: 2857.59 | N53: 3101.42 | O53: 3315.65 | P53: 3306.16 | Q53: 3432.67 | R53: 3606.4 | S53: 3808.28 | T53: 3983.86 | U53: 4044.74 | V53: 4012.27 | W53: 4158.14 | X53: 4320.29 | Y53: 4465.88 | Z53: 4626.01 | AA53: 4611.31 | AB53: 4743.23 | AC53: 4891.23 | AD53: 5022.78 | AE53: 5178.17
A54: Business fixed wireless(K#) | B54: 429 | C54: 466 | D54: 500 | E54: 543 | F54: 543 | G54: 596 | H54: 660 | I54: 715.39 | J54: 769.27 | K54: 769.27 | L54: 829.22 | M54: 889.89 | N54: 943 | O54: 1000 | P54: 995.06 | Q54: 1060.2 | R54: 1121.2 | S54: 1170.6 | T54: 1223.2 | U54: 1202.62 | V54: 1270.42 | W54: 1327.6 | X54: 1370.28 | Y54: 1416.95 | Z54: 1385.64 | AA54: 1461.96 | AB54: 1513.96 | AC54: 1551.47 | AD54: 1592.98 | AE54: 1559.08
A55: Fixed wireless connections(K#) | B55: 1232 | C55: 1472 | D55: 1776 | E55: 2040 | F55: 2040 | G55: 2332 | H55: 2611 | I55: 2907.5 | J55: 3190.25 | K55: 3190.25 | L55: 3480.01 | M55: 3755.51 | N55: 4054.07 | O55: 4331.26 | P55: 4310.56 | Q55: 4502.15 | R55: 4738.96 | S55: 4989.68 | T55: 5217.89 | U55: 5248.7 | V55: 5419.27 | W55: 5640.02 | X55: 5866.64 | Y55: 6076.54 | Z55: 6070.19 | AA55: 6284.59 | AB55: 6482.76 | AC55: 6686.51 | AD55: 6873.71 | AE55: 6806.99
A56: Advanced Connectivity Internet Connections(K#) | B56: 11443 | C56: 11952 | D56: 12565 | E56: 13128 | F56: 13128 | G56: 14833 | H56: 15479 | I56: 16165.26 | J56: 16821.62 | K56: 16821.62 | L56: 17467.41 | M56: 18127.82 | N56: 18833.01 | O56: 19501.63 | P56: 19444.34 | Q56: 20173.65 | R56: 20849.26 | S56: 21562.09 | T56: 22239.07 | U56: 21980.62 | V56: 22976.05 | W56: 23665.87 | X56: 24388.58 | Y56: 25082.8 | Z56: 24404.74 | AA56: 25728.79 | AB56: 26397.61 | AC56: 27100.58 | AD56: 27773.67 | AE56: 26708.88
A58: AT&T Business Fiber connections(K#) | B58: 619 | C58: 645 | D58: 666 | E58: 682 | F58: 682 | G58: 701 | H58: 724 | I58: 744.76 | J58: 762.81 | K58: 762.81 | L58: 788.29 | M58: 814.83 | N58: 838.66 | O58: 860.14 | P58: 853.87 | Q58: 885.6 | R58: 914.76 | S58: 941.64 | T58: 965.6 | U58: 945.94 | V58: 997.45 | W58: 1029.9 | X58: 1060.93 | Y58: 1086.57 | Z58: 1043.01 | AA58: 1114.72 | AB58: 1148.6 | AC58: 1181.25 | AD58: 1207.94 | AE58: 1143.2
A59: Business fixed wireless(K#) | B59: 429 | C59: 466 | D59: 500 | E59: 543 | F59: 543 | G59: 596 | H59: 660 | I59: 715.39 | J59: 769.27 | K59: 769.27 | L59: 829.22 | M59: 889.89 | N59: 943 | O59: 1000 | P59: 995.06 | Q59: 1060.2 | R59: 1121.2 | S59: 1170.6 | T59: 1223.2 | U59: 1202.62 | V59: 1270.42 | W59: 1327.6 | X59: 1370.28 | Y59: 1416.95 | Z59: 1385.64 | AA59: 1461.96 | AB59: 1513.96 | AC59: 1551.47 | AD59: 1592.98 | AE59: 1559.08
A60: Advanced business connections(K#) | B60: 1048 | C60: 1111 | D60: 1166 | E60: 1225 | F60: 1225 | G60: 1297 | H60: 1384 | I60: 1460.15 | J60: 1532.08 | K60: 1532.08 | L60: 1617.51 | M60: 1704.72 | N60: 1781.66 | O60: 1860.14 | P60: 1848.93 | Q60: 1945.8 | R60: 2035.96 | S60: 2112.24 | T60: 2188.8 | U60: 2148.57 | V60: 2267.88 | W60: 2357.5 | X60: 2431.2 | Y60: 2503.52 | Z60: 2428.64 | AA60: 2576.68 | AB60: 2662.57 | AC60: 2732.73 | AD60: 2800.92 | AE60: 2702.28
A61: Advanced business ARPU($) | B61: 578.64 | C61: 546.24 | D61: 536.38 | E61: 526.14 | F61: 548.96 | G61: 497.49 | H61: 483.9 | I61: 467.61 | J61: 457.32 | K61: 475.63 | L61: 431.57 | M61: 424.39 | N61: 413.16 | O61: 405.3 | P61: 419.25 | Q61: 388.99 | R61: 382.35 | S61: 372.73 | T61: 367.23 | U61: 379.71 | V61: 356.89 | W61: 353.31 | X61: 346.28 | Y61: 342.81 | Z61: 353.44 | AA61: 336.87 | AB61: 334.78 | AC61: 329.34 | AD61: 327.13 | AE61: 336.1
A62: Business fiber and advanced connectivity services revenue - Advanced connectivity | B62: 1755 | C62: 1769 | D62: 1832 | E62: 1887 | F62: 7243 | G62: 1882 | H62: 1946 | I62: 1992 | J62: 2046.85 | K62: 7866.85 | L62: 2037 | M62: 2106.48 | N62: 2146.61 | O62: 2196.75 | P62: 8495 | Q62: 2177.4 | R62: 2237.25 | S62: 2261.04 | T62: 2304.39 | U62: 9092.5 | V62: 2376.18 | W62: 2438.72 | X62: 2476.61 | Y62: 2524.98 | Z62: 9847.16 | AA62: 2545.26 | AB62: 2606.66 | AC62: 2642.05 | AD62: 2689.49 | AE62: 10498.97
A64: Converged Customers
A65: AT&T Fiber connections with AT&T Wireless - Converged customers(K#) | B65: 3859 | C65: 4022 | D65: 4205 | E65: 4374 | F65: 4374 | G65: 4742 | H65: 4920 | I65: 5097.37 | J65: 5354.2 | K65: 5354.2 | L65: 5523.23 | M65: 5721.05 | N65: 5953.53 | O65: 6174.14 | P65: 6146.11 | Q65: 6310.9 | R65: 6504.01 | S65: 6707.68 | T65: 6900.05 | U65: 7174.9 | V65: - | W65: - | X65: - | Y65: - | Z65: 8118.09 | AA65: - | AB65: - | AC65: - | AD65: - | AE65: 8940.04
A66: FWA Home Internet connections with AT&T Wireless - Converged customers(K#) | B66: 396 | C66: 512 | D66: 658 | E66: 790 | F66: 790 | G66: 942 | H66: 1066 | I66: 1208.08 | J66: 1335.2 | K66: 1335.2 | L66: 1490.54 | M66: 1620.32 | N66: 1778.62 | O66: 1904.63 | P66: 1885.09 | Q66: 2044.15 | R66: 2167.28 | S66: 2318.83 | T66: 2445.78 | U66: 2408.17 | V66: - | W66: - | X66: - | Y66: - | Z66: 2884.47 | AA66: - | AB66: - | AC66: - | AD66: - | AE66: 3359.41
A67: Advanced Home Internet connections with AT&T Wireless - Converged customers(K#) | B67: 4255 | C67: 4534 | D67: 4863 | E67: 5164 | F67: 5164 | G67: 5684 | H67: 5986 | I67: 6250.27 | J67: 6668.75 | K67: 6668.75 | L67: 6997.42 | M67: 7337.54 | N67: 7747.15 | O67: 8117.74 | P67: 8047.83 | Q67: 8355.05 | R67: 8671.3 | S67: 9026.51 | T67: 9345.83 | U67: 9698.02 | V67: - | W67: - | X67: - | Y67: - | Z67: 11294.98 | AA67: - | AB67: - | AC67: - | AD67: - | AE67: 12647.37
A69: AT&T Fiber connections with AT&T Wireless - Converged(%) | B69: 0.402 | C69: 0.409 | D69: 0.415 | E69: 0.42 | F69: 0.42 | G69: 0.402 | H69: 0.405 | I69: 0.4081 | J69: 0.4128 | K69: 0.4286 | L69: 0.4163 | M69: 0.4201 | N69: 0.4246 | O69: 0.4291 | P69: 0.4415 | Q69: 0.4326 | R69: 0.4351 | S69: 0.4376 | T69: 0.4401 | U69: 0.4492 | V69: - | W69: - | X69: - | Y69: - | Z69: 0.4568 | AA69: - | AB69: - | AC69: - | AD69: - | AE69: 0.4591
A70: FWA Home Internet connections with AT&T Wireless - Converged(%) | B70: 0.4932 | C70: 0.5089 | D70: 0.5157 | E70: 0.5277 | F70: 0.5277 | G70: 0.5426 | H70: 0.5464 | I70: 0.5505 | J70: 0.5545 | K70: 0.5545 | L70: 0.5601 | M70: 0.5639 | N70: 0.5676 | O70: 0.5714 | P70: 0.569 | Q70: 0.5814 | R70: 0.5864 | S70: 0.5914 | T70: 0.5964 | U70: 0.5791 | V70: - | W70: - | X70: - | Y70: - | Z70: 0.5742 | AA70: - | AB70: - | AC70: - | AD70: - | AE70: 0.5772
A71: Advanced Home Internet connections with AT&T Wireless - Converged(%) | B71: 0.409 | C71: 0.418 | D71: 0.427 | E71: 0.434 | F71: 0.434 | G71: 0.42 | H71: 0.425 | I71: 0.4289 | J71: 0.4351 | K71: 0.4351 | L71: 0.4404 | M71: 0.4451 | N71: 0.4507 | O71: 0.4557 | P71: 0.4512 | Q71: 0.4615 | R71: 0.4651 | S71: 0.469 | T71: 0.4725 | U71: 0.4758 | V71: - | W71: - | X71: - | Y71: - | Z71: 0.4822 | AA71: - | AB71: - | AC71: - | AD71: - | AE71: 0.4857
A73: Fiber location metrics
A74: Internal/Organic net adds - Fiber broadband customer locations - Consumer(K#) | B74: 700 | C74: 600 | D74: 740 | E74: 716.67 | F74: 2660 | G74: -725 | H74: -1700 | I74: -419.27 | J74: -425.52 | K74: 453.96 | L74: -870.16 | M74: -911.83 | N74: -953.5 | O74: -995.16 | P74: 1861.01 | Q74: -1036.83 | R74: -1078.5 | S74: -1120.16 | T74: -1161.83 | U74: 1727.68 | V74: -2330.25 | W74: -2392.75 | X74: -2455.25 | Y74: -2517.75 | Z74: 241.52 | AA74: -2580.25 | AB74: -2642.75 | AC74: -2705.25 | AD74: -2767.75 | AE74: -8.48
A75: Net adds acquired - Fiber broadband customer locations - Consumer(K#) | B75: - | C75: - | D75: - | E75: - | F75: - | G75: 4725 | H75: 3300 | I75: 2593 | J75: 2632.5 | K75: 6550 | L75: 2748.88 | M75: 2811.38 | N75: 2873.88 | O75: 2936.38 | P75: 5775 | Q75: 2991.54 | R75: 3054.04 | S75: 3116.54 | T75: 3179.04 | U75: 6275 | V75: 3235.31 | W75: 3297.81 | X75: 3360.31 | Y75: 3422.81 | Z75: 6775 | AA75: 3480.02 | AB75: 3542.52 | AC75: 3605.02 | AD75: 3667.52 | AE75: 7275
A76: Net adds - Fiber broadband customer locations - Consumer(K#) | B76: 500 | C76: 600 | D76: 700 | E76: 700 | F76: 2800 | G76: 5200 | H76: 800 | I76: 924.35 | J76: 931.1 | K76: 7634.03 | L76: 867.39 | M76: 982.03 | N76: 977.66 | O76: 1135.99 | P76: 4067.81 | Q76: 1000.27 | R76: 1000.27 | S76: 1000.27 | T76: 1166.93 | U76: 4174.34 | V76: 987.83 | W76: 987.83 | X76: 987.83 | Y76: 1187.83 | Z76: 4190.16 | AA76: 985.71 | AB76: 985.71 | AC76: 985.71 | AD76: 1185.71 | AE76: 4031.64
A77: IP-Fiber broadband home passed(K#) | B77: 24000 | C77: 24600 | D77: 25400 | E77: 26100 | F77: 26100 | G77: 31300 | H77: 32100 | I77: 33024.35 | J77: 33955.45 | K77: 33955.45 | L77: 34851.94 | M77: 35833.98 | N77: 36811.63 | O77: 37947.62 | P77: 38023.26 | Q77: 39051.83 | R77: 40052.1 | S77: 41052.36 | T77: 42219.29 | U77: 42306.31 | V77: 43150.98 | W77: 44138.81 | X77: 45126.63 | Y77: 46314.46 | Z77: 46480.33 | AA77: 47300.17 | AB77: 48285.87 | AC77: 49271.58 | AD77: 50457.29 | AE77: 50511.97
A79: Net adds - Fiber broadband customer locations - Commercial(K#) | B79: 100 | C79: 200 | D79: 200 | E79: 100 | F79: 300 | G79: 300 | H79: 300 | I79: 320.72 | J79: 198.37 | K79: 894.26 | L79: 359.75 | M79: 227.09 | N79: 229.97 | O79: 202.87 | P79: 891.08 | Q79: 226.3 | R79: 226.3 | S79: 186.3 | T79: 186.3 | U79: 834.99 | V79: 232.87 | W79: 232.87 | X79: 182.87 | Y79: 182.87 | Z79: 803.6 | AA79: 232.87 | AB79: 232.87 | AC79: 182.87 | AD79: 182.87 | AE79: 826.69
A80: Fiber broadband customer locations - Commercial(K#) | B80: 5700 | C80: 5900 | D80: 6100 | E80: 5900 | F80: 5900 | G80: 6200 | H80: 6500 | I80: 6771.1 | J80: 6936.41 | K80: 6936.41 | L80: 7159.57 | M80: 7361.43 | N80: 7565.85 | O80: 7746.18 | P80: 7753.23 | Q80: 7648.18 | R80: 7836.77 | S80: 7992.02 | T80: 8147.26 | U80: 8536.43 | V80: 8263.02 | W80: 8449.31 | X80: 8595.61 | Y80: 8741.91 | Z80: 9263.31 | AA80: 8928.21 | AB80: 9114.51 | AC80: 9260.81 | AD80: 9407.1 | AE80: 10007.33
A82: Internal/Organic net adds - Fiber broadband customer locations(K#) | B82: 564.16 | C82: 701.98 | D82: 785.77 | E82: 720.13 | F82: 2772.05 | G82: 728.28 | H82: -969.38 | I82: 990.73 | J82: 1048.1 | K82: 2545.25 | L82: 1250 | M82: 1250 | N82: 1250 | O82: 1250 | P82: 4552.53 | Q82: 1275 | R82: 1275 | S82: 1275 | T82: 1275 | U82: 4580.62 | V82: 1300 | W82: 1300 | X82: 1300 | Y82: 1300 | Z82: 4587.19 | AA82: 1300 | AB82: 1300 | AC82: 1300 | AD82: 1300 | AE82: 4809.84
A83: Net adds acquired - Fiber broadband customer locations(K#) | B83: 353.75 | C83: 547.03 | D83: 621.34 | E83: 519.81 | F83: 983.86 | G83: 4159.76 | H83: 2836.72 | I83: 757.66 | J83: 771.61 | K83: 5291 | L83: 1250 | M83: 1250 | N83: 1250 | O83: 1250 | P83: 1877.88 | Q83: 1250 | R83: 1250 | S83: 1250 | T83: 1250 | U83: 1458.13 | V83: 1250 | W83: 1250 | X83: 1250 | Y83: 1250 | Z83: 1025.62 | AA83: 1250 | AB83: 1250 | AC83: 1250 | AD83: 1250 | AE83: 580.33
A84: Net adds - Fiber broadband customer locations(K#) | B84: 600 | C84: 800 | D84: 900 | E84: 800 | F84: 3100 | G84: 5500 | H84: 1100 | I84: 1063.35 | J84: 1080.35 | K84: 8401.08 | L84: 1144.47 | M84: 1164.47 | N84: 1161.97 | O84: 1314.47 | P84: 4834.92 | Q84: 1188.85 | R84: 1188.85 | S84: 1155.51 | T84: 1322.18 | U84: 4935.03 | V84: 1174.12 | W84: 1174.12 | X84: 1134.12 | Y84: 1334.12 | Z84: 4920.05 | AA84: 1172.01 | AB84: 1172.01 | AC84: 1132.01 | AD84: 1332.01 | AE84: 4902.56
A85: Total fiber broadband customer locations(K#) | B85: 29500 | C85: 30300 | D85: 31200 | E85: 32000 | F85: 32000 | G85: 37500 | H85: 38600 | I85: 39666.88 | J85: 40747.23 | K85: 40747.23 | L85: 41793.38 | M85: 42957.85 | N85: 44119.82 | O85: 45434.3 | P85: 45582.15 | Q85: 46700.01 | R85: 47888.86 | S85: 49044.38 | T85: 50366.56 | U85: 50640.86 | V85: 51413.99 | W85: 52588.12 | X85: 53722.24 | Y85: 55056.37 | Z85: 55528.26 | AA85: 56228.38 | AB85: 57400.38 | AC85: 58532.39 | AD85: 59864.39 | AE85: 60430.82

Sheet AC Wireless
A2: AT&T Inc. | Advanced Connectivity - Wireless
A3: NYSE:T (MI KEY: 4024242; SPCIQ KEY: 100231)
A5: Visible Alpha
A7: Period Type : Fiscal Quarter, Fiscal Halves, Fiscal Year
A8: Period Start : 2025
A9: Period End : 2030
A10: Currency : Reported
A11: Consensus View : Mean
A12: As Of: 10/20/2026
A14: All numbers in $M unless otherwise indicated | B14: FQ1 2025A | C14: FQ2 2025A | D14: FQ3 2025A | E14: FQ4 2025A | F14: FY2025A | G14: FQ1 2026A | H14: FQ2 2026A | I14: FQ3 2026E | J14: FQ4 2026E | K14: FY2026E | L14: FQ1 2027E | M14: FQ2 2027E | N14: FQ3 2027E | O14: FQ4 2027E | P14: FY2027E | Q14: FQ1 2028E | R14: FQ2 2028E | S14: FQ3 2028E | T14: FQ4 2028E | U14: FY2028E | V14: FQ1 2029E | W14: FQ2 2029E | X14: FQ3 2029E | Y14: FQ4 2029E | Z14: FY2029E | AA14: FQ1 2030E | AB14: FQ2 2030E | AC14: FQ3 2030E | AD14: FQ4 2030E | AE14: FY2030E
A15: Number of Contributors Available | B15: 19 | C15: 19 | D15: 19 | E15: 19 | F15: 20 | G15: 19 | H15: 19 | I15: 20 of 20 | J15: 20 of 20 | K15: 20 of 20 | L15: 14 of 20 | M15: 14 of 20 | N15: 13 of 20 | O15: 13 of 20 | P15: 20 of 20 | Q15: 7 of 20 | R15: 7 of 20 | S15: 7 of 20 | T15: 7 of 20 | U15: 17 of 20 | V15: 5 of 20 | W15: 5 of 20 | X15: 5 of 20 | Y15: 5 of 20 | Z15: 14 of 20 | AA15: 5 of 20 | AB15: 5 of 20 | AC15: 5 of 20 | AD15: 5 of 20 | AE15: 14 of 20
A16: Consumer Postpaid Accounts
A17: Consumer postpaid wireless accounts(K#) | B17: 25415 | C17: 25481 | D17: 25570 | E17: 25655 | F17: 25655 | G17: 25739 | H17: 25886 | I17: 25982.08 | J17: 26090.86 | K17: 26090.86 | L17: 26129.7 | M17: 26235.87 | N17: 26313.41 | O17: 26411.71 | P17: 26391 | Q17: 26353.95 | R17: 26474.32 | S17: 26523.63 | T17: 26611.53 | U17: 26693.32 | V17: 26491.74 | W17: 26596.1 | X17: 26618.76 | Y17: 26681.88 | Z17: 26881.95 | AA17: 26674.12 | AB17: 26765.54 | AC17: 26775.59 | AD17: 26826.11 | AE17: 27072.57
A18: Consumer postpaid wireless accounts - Average(K#) | B18: 25407 | C18: 25448 | D18: 25525.5 | E18: 25612.5 | F18: 25527 | G18: 25697 | H18: 25812.5 | I18: 25934.04 | J18: 26036.47 | K18: 25877.9 | L18: 26113.49 | M18: 26182.79 | N18: 26274.64 | O18: 26362.56 | P18: 26240.93 | Q18: 26340.16 | R18: 26414.14 | S18: 26498.98 | T18: 26567.58 | U18: 26542.16 | V18: 26493.69 | W18: 26543.92 | X18: 26607.43 | Y18: 26650.32 | Z18: 26768.64 | AA18: 26678 | AB18: 26719.83 | AC18: 26770.57 | AD18: 26800.85 | AE18: 26977.26
A19: Consumer postpaid wireless ARPA($) | B19: 154.82 | C19: 156.77 | D19: 155.51 | E19: 156.07 | F19: 155.89 | G19: 156.23 | H19: 160.18 | I19: 159.01 | J19: 159.53 | K19: 158.32 | L19: 159.52 | M19: 161.75 | N19: 160.8 | O19: 160.94 | P19: 160.27 | Q19: 160.79 | R19: 162.95 | S19: 161.9 | T19: 163.21 | U19: 161.44 | V19: 160.97 | W19: 163.69 | X19: 162.23 | Y19: 162.47 | Z19: 162.49 | AA19: 162.03 | AB19: 165.02 | AC19: 163.46 | AD19: 163.71 | AE19: 163.49
A20: Total revenue - Consumer postpaid wireless | B20: 11800.54 | C20: 11968.45 | D20: 11908.41 | E20: 11992.03 | F20: 47669.42 | G20: 12043.93 | H20: 12403.94 | I20: 12371.39 | J20: 12460.41 | K20: 49274.26 | L20: 12497.19 | M20: 12705.63 | N20: 12674.92 | O20: 12728.9 | P20: 50631.33 | Q20: 12707 | R20: 12913.33 | S20: 12872.85 | T20: 13009.68 | U20: 51635.5 | V20: 12794.24 | W20: 13036.59 | X20: 12952.03 | Y20: 12991.79 | Z20: 52251.02 | AA20: 12969.23 | AB20: 13230.71 | AC20: 13132.52 | AD20: 13166.52 | AE20: 52978.36
A22: Consumer Postpaid Wireless
A23: Net adds - Consumer postpaid wireless(K#) | B23: 174 | C23: 338 | D23: 178 | E23: 490 | F23: 1180 | G23: 102 | H23: 346 | I23: 298.5 | J23: 443.33 | K23: 1189.83 | L23: 124 | M23: 305.66 | N23: 238.74 | O23: 393.02 | P23: 1117.27 | Q23: 101.19 | R23: 294.76 | S23: 188.46 | T23: 416.33 | U23: 1057.38 | V23: 89.32 | W23: 343.17 | X23: 210.02 | Y23: 331.3 | Z23: 969.17 | AA23: 77.91 | AB23: 306.47 | AC23: 172.78 | AD23: 294.38 | AE23: 864.34
A24: Subscribers - Consumer postpaid wireless(K#) | B24: 73775 | C24: 74113 | D24: 74291 | E24: 74781 | F24: 74781 | G24: 74883 | H24: 75229 | I24: 75527.5 | J24: 75970.83 | K24: 75970.83 | L24: 76068.3 | M24: 76373.96 | N24: 76612.71 | O24: 77005.72 | P24: 77088.09 | Q24: 77054.75 | R24: 77349.51 | S24: 77537.97 | T24: 77954.3 | U24: 78145.47 | V24: 78203.14 | W24: 78546.31 | X24: 78756.33 | Y24: 79087.62 | Z24: 79210.32 | AA24: 79165.53 | AB24: 79472 | AC24: 79644.78 | AD24: 79939.16 | AE24: 80074.66
A26: Consumer Prepaid Wireless
A27: Net adds - Consumer prepaid wireless(K#) | B27: -48 | C27: -65 | D27: -136 | E27: -315 | F27: -564 | G27: -102 | H27: -23 | I27: -90.42 | J27: -220.95 | K27: -301.04 | L27: -84.94 | M27: -20.14 | N27: 51.31 | O27: -242.49 | P27: -278.55 | Q27: -112.81 | R27: -22.86 | S27: -135.82 | T27: -288.84 | U27: -293.81 | V27: -106.47 | W27: -33.48 | X27: -129.47 | Y27: -304.85 | Z27: -252.61 | AA27: -116.22 | AB27: -44.05 | AC27: -139.64 | AD27: -314.24 | AE27: -273.66
A28: Subscribers - Consumer prepaid wireless(K#) | B28: 17159 | C28: 17094 | D28: 16958 | E28: 16643 | F28: 16643 | G28: 16541 | H28: 16518 | I28: 16562.91 | J28: 16341.96 | K28: 16341.96 | L28: 16262.47 | M28: 16242.32 | N28: 16293.63 | O28: 16051.14 | P28: 16063.4 | Q28: 15486.75 | R28: 15463.89 | S28: 15328.08 | T28: 15039.24 | U28: 15769.6 | V28: 14978.3 | W28: 14944.82 | X28: 14815.35 | Y28: 14510.51 | Z28: 15681.27 | AA28: 14394.29 | AB28: 14350.24 | AC28: 14210.6 | AD28: 13896.37 | AE28: 15407.61
A29: Subscribers - Consumer prepaid wireless - Average(K#) | B29: 17183 | C29: 17126.5 | D29: 17026 | E29: 16800.5 | F29: 16925 | G29: 16592 | H29: 16529.5 | I29: 16545.04 | J29: 16452.43 | K29: 16513.31 | L29: 16304.94 | M29: 16252.39 | N29: 16267.98 | O29: 16172.39 | P29: 16220.43 | Q29: 15543.16 | R29: 15475.32 | S29: 15395.99 | T29: 15183.66 | U29: 15934.25 | V29: 15031.53 | W29: 14961.56 | X29: 14880.09 | Y29: 14662.93 | Z29: 15828.88 | AA29: 14452.4 | AB29: 14372.27 | AC29: 14280.42 | AD29: 14053.49 | AE29: 15565.74
A30: ARPU - Consumer prepaid wireless($) | B30: 36.29 | C30: 36.45 | D30: 36.38 | E30: 36.15 | F30: 36.32 | G30: 36.19 | H30: 36.53 | I30: 36.54 | J30: 36.41 | K30: 36.52 | L30: 36.46 | M30: 36.58 | N30: 36.77 | O30: 36.68 | P30: 36.67 | Q30: 36.61 | R30: 36.83 | S30: 37.09 | T30: 37.14 | U30: 36.78 | V30: 36.49 | W30: 36.57 | X30: 37.28 | Y30: 37.07 | Z30: 36.76 | AA30: 36.44 | AB30: 36.66 | AC30: 37.33 | AD30: 37.31 | AE30: 36.83
A31: Total revenue - Consumer prepaid wireless | B31: 1870.71 | C31: 1872.78 | D31: 1858.22 | E31: 1822.01 | F31: 7423.73 | G31: 1801.39 | H31: 1811.47 | I31: 1813.55 | J31: 1797.25 | K31: 7221.9 | L31: 1783.2 | M31: 1783.44 | N31: 1794.49 | O31: 1779.38 | P31: 7125.44 | Q31: 1706.99 | R31: 1709.67 | S31: 1713.39 | T31: 1691.51 | U31: 7022.12 | V31: 1644.4 | W31: 1640.96 | X31: 1664.79 | Y31: 1631.17 | Z31: 6972.38 | AA31: 1578.37 | AB31: 1579.19 | AC31: 1600.37 | AD31: 1573.51 | AE31: 6869.12
A33: Postpaid phones
A34: Beginning subs. - Postpaid Phones(K#) | B34: 72749 | C34: 73031 | D34: 73408 | E34: 73801 | F34: 72749 | G34: 74214 | H34: 74503 | I34: 74931.5 | J34: 75312.71 | K34: 74214 | L34: 75713.2 | M34: 75981.13 | N34: 76357.91 | O34: 76695.82 | P34: 75721.28 | Q34: 77060.03 | R34: 77277.86 | S34: 77600.17 | T34: 77861.7 | U34: 77047.86 | V34: 78290.65 | W34: 78456.12 | X34: 78756.28 | Y34: 78986.43 | Z34: 78251.35 | AA34: 79241.58 | AB34: 79359.53 | AC34: 79613.42 | AD34: 79796.66 | AE34: 79260.46
A35: Gross adds. - Postpaid Phones(K#) | B35: 2135.45 | C35: 2307.11 | D35: 2431.06 | E35: 2596.82 | F35: 9484.29 | G35: 2279.37 | H35: 2359.57 | I35: 2427.64 | J35: 2592.72 | K35: 9654.98 | L35: 2253.97 | M35: 2330.47 | N35: 2408.25 | O35: 2574.64 | P35: 9522.78 | Q35: 2264.84 | R35: 2336 | S35: 2420.57 | T35: 2581.03 | U35: 9547.54 | V35: 2269.48 | W35: 2334.3 | X35: 2418.33 | Y35: 2582.58 | Z35: 9539.07 | AA35: 2265.83 | AB35: 2329.82 | AC35: 2413.67 | AD35: 2577.62 | AE35: 9543.36
A36: Churn - Postpaid Phones(%) | B36: 0.0083 | C36: 0.0087 | D36: 0.0092 | E36: 0.0098 | F36: 0.009 | G36: 0.0089 | H36: 0.0086 | I36: 0.0091 | J36: 0.0097 | K36: 0.0091 | L36: 0.0087 | M36: 0.0086 | N36: 0.009 | O36: 0.0095 | P36: 0.009 | Q36: 0.0088 | R36: 0.0087 | S36: 0.0092 | T36: 0.0096 | U36: 0.009 | V36: 0.0089 | W36: 0.0086 | X36: 0.0092 | Y36: 0.0098 | Z36: 0.0091 | AA36: 0.009 | AB36: 0.0087 | AC36: 0.0093 | AD36: 0.0099 | AE36: 0.0091
A37: Disconnects - Postpaid Phones(K#) | B37: 1814.96 | C37: 1911.03 | D37: 2031.48 | E37: 2175.82 | F37: 7933.29 | G37: 1985.37 | H37: 1927.57 | I37: 2048.81 | J37: 2182.48 | K37: 8140.76 | L37: 1984.5 | M37: 1961.67 | N37: 2067.61 | O37: 2197.72 | P37: 8202.9 | Q37: 2046.01 | R37: 2012.79 | S37: 2153.89 | T37: 2252.33 | U37: 8398.83 | V37: 2096 | W37: 2026.14 | X37: 2180.17 | Y37: 2319.44 | Z37: 8542.61 | AA37: 2139.89 | AB37: 2067.93 | AC37: 2222.43 | AD37: 2361.66 | AE37: 8694.51
A38: Internal net adds - Postpaid Phones(K#) | B38: 324 | C38: 401 | D38: 405 | E38: 421 | F38: 1551 | G38: 294 | H38: 432 | I38: 382.61 | J38: 412.19 | K38: 1529.8 | L38: 269.77 | M38: 369.13 | N38: 341 | O38: 377.31 | P38: 1339.28 | Q38: 219.27 | R38: 323.74 | S38: 267.24 | T38: 329.31 | U38: 1171.56 | V38: 173.47 | W38: 308.16 | X38: 238.16 | Y38: 263.14 | Z38: 1027.57 | AA38: 125.95 | AB38: 261.9 | AC38: 191.24 | AD38: 215.96 | AE38: 885.88
A39: Acquired net adds - Postpaid Phones(K#) | B39: -42 | C39: -24 | D39: -12 | E39: -8 | F39: -86 | G39: -5 | H39: -14 | I39: -3.33 | J39: -3.33 | K39: -22.2 | L39: -1.43 | M39: -1.43 | N39: -1.43 | O39: -1.43 | P39: -12 | Q39: -2.5 | R39: -2.5 | S39: -10 | T39: -10 | U39: -18 | V39: -10 | W39: -10 | X39: -10 | Y39: -10 | Z39: -26.67 | AA39: -10 | AB39: -10 | AC39: -10 | AD39: -10 | AE39: -26.67
A40: Total net adds - Postpaid Phones(K#) | B40: 282 | C40: 377 | D40: 393 | E40: 413 | F40: 1465 | G40: 289 | H40: 418 | I40: 381.21 | J40: 408.58 | K40: 1507.28 | L40: 267.93 | M40: 376.78 | N40: 337.91 | O40: 367.07 | P40: 1327.23 | Q40: 217.84 | R40: 322.31 | S40: 261.53 | T40: 323.6 | U40: 1159.56 | V40: 165.47 | W40: 300.16 | X40: 230.16 | Y40: 255.14 | Z40: 1009.11 | AA40: 117.95 | AB40: 253.9 | AC40: 183.24 | AD40: 207.96 | AE40: 867.42
A41: Subscribers - Postpaid Phones(K#) | B41: 73031 | C41: 73408 | D41: 73801 | E41: 74214 | F41: 74214 | G41: 74503 | H41: 74921 | I41: 75312.71 | J41: 75721.28 | K41: 75721.28 | L41: 75981.13 | M41: 76357.91 | N41: 76695.82 | O41: 77062.89 | P41: 77047.86 | Q41: 77277.86 | R41: 77600.17 | S41: 77861.7 | T41: 78185.3 | U41: 78207.43 | V41: 78456.12 | W41: 78756.28 | X41: 78986.43 | Y41: 79241.58 | Z41: 79260.46 | AA41: 79359.53 | AB41: 79613.42 | AC41: 79796.66 | AD41: 80004.62 | AE41: 80127.88
A42: Average Subs. - Postpaid Phones(K#) | B42: 72890 | C42: 73219.5 | D42: 73604.5 | E42: 74007.5 | F42: 73481.5 | G42: 74358.5 | H42: 74712 | I42: 75122.1 | J42: 75516.99 | K42: 74950.77 | L42: 75847.16 | M42: 76169.52 | N42: 76526.87 | O42: 76879.35 | P42: 76371.33 | Q42: 77168.95 | R42: 77439.02 | S42: 77730.94 | T42: 78023.5 | U42: 77612.59 | V42: 78373.38 | W42: 78606.2 | X42: 78871.36 | Y42: 79114.01 | Z42: 78745.66 | AA42: 79300.55 | AB42: 79486.47 | AC42: 79705.04 | AD42: 79900.64 | AE42: 79683.89
A43: ARPU - Postpaid Phones($) | B43: 56.56 | C43: 57.04 | D43: 56.64 | E43: 56.57 | F43: 56.7 | G43: 56.51 | H43: 58.01 | I43: 57.57 | J43: 57.51 | K43: 57.4 | L43: 57.38 | M43: 58.13 | N43: 57.98 | O43: 57.88 | P43: 57.8 | Q43: 57.66 | R43: 58.49 | S43: 58.12 | T43: 58.28 | U43: 58.13 | V43: 57.86 | W43: 58.95 | X43: 58.54 | Y43: 58.37 | Z43: 58.39 | AA43: 58.19 | AB43: 59.28 | AC43: 58.94 | AD43: 58.78 | AE43: 58.7
A44: Revenue - Postpaid Phones | B44: 12367.98 | C44: 12529.32 | D44: 12506.88 | E44: 12559.81 | F44: 49963.99 | G44: 12606 | H44: 13002.13 | I44: 12974.19 | J44: 13029.43 | K44: 51619.5 | L44: 13055.68 | M44: 13282.62 | N44: 13309.32 | O44: 13348.75 | P44: 52964.38 | Q44: 13348.78 | R44: 13588.7 | S44: 13554.23 | T44: 13641.23 | U44: 54139.56 | V44: 13602.74 | W44: 13900.58 | X44: 13850.67 | Y44: 13853.6 | Z44: 55176.6 | AA44: 13842.67 | AB44: 14136.45 | AC44: 14092.59 | AD44: 14089.93 | AE44: 56133.23
A46: Total Postpaid phones
A47: Net additions - Smart phones(K#) | B47: 321.11 | C47: 410.13 | D47: 422.13 | E47: 440.81 | F47: 1619.74 | G47: 315.76 | H47: 447.81 | I47: 385.19 | J47: 395.53 | K47: 1309.82 | L47: 416.62 | M47: 527.58 | N47: 358.09 | O47: 356.64 | P47: 1034.86 | Q47: 286.34 | R47: 400.85 | S47: 204.58 | T47: 197.64 | U47: 845.02 | V47: 204.99 | W47: 322.7 | X47: 156.54 | Y47: 149.37 | Z47: 691.26 | AA47: 182.93 | AB47: 302.25 | AC47: 135.41 | AD47: 127.58 | AE47: 604.56
A48: Net additions - Feature phones(K#) | B48: -58.66 | C48: -49.7 | D48: -43.7 | E48: -41.71 | F48: -232.12 | G48: -40.15 | H48: -44.72 | I48: 183.33 | J48: 221.62 | K48: 281.44 | L48: -29.97 | M48: -27.74 | N48: -27.82 | O48: -26.56 | P48: 586.45 | Q48: -25.82 | R48: -23.87 | S48: -24 | T48: -22.89 | U48: 492.15 | V48: -21.75 | W48: -20.08 | X48: -19.99 | Y48: -19.05 | Z48: 413.24 | AA48: -17.97 | AB48: -16.6 | AC48: -16.51 | AD48: -15.73 | AE48: 346.53
A49: Total net adds - Postpaid Phones(K#) | B49: 282 | C49: 377 | D49: 393 | E49: 413 | F49: 1465 | G49: 289 | H49: 418 | I49: 381.21 | J49: 408.58 | K49: 1507.28 | L49: 267.93 | M49: 376.78 | N49: 337.91 | O49: 367.07 | P49: 1327.23 | Q49: 217.84 | R49: 322.31 | S49: 261.53 | T49: 323.6 | U49: 1159.56 | V49: 165.47 | W49: 300.16 | X49: 230.16 | Y49: 255.14 | Z49: 1009.11 | AA49: 117.95 | AB49: 253.9 | AC49: 183.24 | AD49: 207.96 | AE49: 867.42
A51: Subscribers - Smart phones(K#) | B51: 72978.63 | C51: 73388.77 | D51: 73810.9 | E51: 74251.71 | F51: 74301.8 | G51: 74567.48 | H51: 75015.29 | I51: 75272.08 | J51: 75535.76 | K51: 75611.62 | L51: 75355.05 | M51: 75882.62 | N51: 76240.71 | O51: 76597.35 | P51: 76646.48 | Q51: 76883.69 | R51: 77284.54 | S51: 77489.12 | T51: 77686.76 | U51: 77491.5 | V51: 77891.76 | W51: 78214.45 | X51: 78370.99 | Y51: 78520.37 | Z51: 78182.77 | AA51: 78703.29 | AB51: 79005.54 | AC51: 79140.95 | AD51: 79268.52 | AE51: 78787.33
A52: Subscribers - Feature phones(K#) | B52: 1104 | C52: 1029 | D52: 954 | E52: 879 | F52: 879 | G52: 804 | H52: 729 | I52: 695.67 | J52: 663.91 | K52: 663.91 | L52: 633.94 | M52: 606.2 | N52: 578.38 | O52: 551.82 | P52: 551.82 | Q52: 526 | R52: 502.13 | S52: 478.13 | T52: 455.24 | U52: 455.24 | V52: 433.5 | W52: 413.41 | X52: 393.42 | Y52: 374.37 | Z52: 374.37 | AA52: 356.4 | AB52: 339.8 | AC52: 323.29 | AD52: 307.56 | AE52: 307.56
A53: Subscribers - Postpaid Phones(K#) | B53: 73031 | C53: 73408 | D53: 73801 | E53: 74214 | F53: 74214 | G53: 74503 | H53: 74921 | I53: 75312.71 | J53: 75721.28 | K53: 75721.28 | L53: 75981.13 | M53: 76357.91 | N53: 76695.82 | O53: 77062.89 | P53: 77047.86 | Q53: 77277.86 | R53: 77600.17 | S53: 77861.7 | T53: 78185.3 | U53: 78207.43 | V53: 78456.12 | W53: 78756.28 | X53: 78986.43 | Y53: 79241.58 | Z53: 79260.46 | AA53: 79359.53 | AB53: 79613.42 | AC53: 79796.66 | AD53: 80004.62 | AE53: 80127.88
A55: Prepaid phones
A56: Beginnings subs - Prepaid Phones(K#) | B56: 17217 | C56: 17162 | D56: 17093 | E56: 16954 | F56: 17217 | G56: 16630 | H56: 16554 | I56: 16518 | J56: 16444.82 | K56: 16630 | L56: 16240.7 | M56: 16192.17 | N56: 16190.1 | O56: 16124.81 | P56: 16244.1 | Q56: 15809.77 | R56: 15746.54 | S56: 15736.03 | T56: 15647.54 | U56: 15924.62 | V56: 15418.58 | W56: 15352.31 | X56: 15346.15 | Y56: 15260.72 | Z56: 15661.86 | AA56: 15030.14 | AB56: 14961.03 | AC56: 14950.82 | AD56: 14862.51 | AE56: 15398.67
A57: Gross adds - Prepaid Phones(K#) | B57: 1295 | C57: 1214.59 | D57: 1260.15 | E57: 1130.34 | F57: 4900.09 | G57: 1232.13 | H57: 1144.98 | I57: 1218.81 | J57: 1122.17 | K57: 4717.07 | L57: 1204.85 | M57: 1119.89 | N57: 1182.6 | O57: 1084.64 | P57: 4648.04 | Q57: 1167.54 | R57: 1085.15 | S57: 1141.77 | T57: 1033.26 | U57: 4542.28 | V57: 1153.26 | W57: 1072.92 | X57: 1129.76 | Y57: 1022.36 | Z57: 4510.14 | AA57: 1122.99 | AB57: 1044.76 | AC57: 1098.84 | AD57: 991.26 | AE57: 4435.57
A58: Churn - Prepaid Phones(%) | B58: 0.0255 | C58: 0.0243 | D58: 0.0263 | E58: 0.0275 | F58: 0.0259 | G58: 0.0262 | H58: 0.023 | I58: 0.0261 | J58: 0.0269 | K58: 0.0256 | L58: 0.0257 | M58: 0.0231 | N58: 0.0258 | O58: 0.0266 | P58: 0.0254 | Q58: 0.0259 | R58: 0.0231 | S58: 0.026 | T58: 0.027 | U58: 0.0252 | V58: 0.0263 | W58: 0.0233 | X58: 0.0263 | Y58: 0.0274 | Z58: 0.0252 | AA58: 0.0263 | AB58: 0.0234 | AC58: 0.0264 | AD58: 0.0275 | AE58: 0.0252
A59: Disconnects - Prepaid Phones(K#) | B59: 1315 | C59: 1248.59 | D59: 1343.15 | E59: 1385.34 | F59: 5292.09 | G59: 1304.13 | H59: 1140.98 | I59: 1287.33 | J59: 1319.33 | K59: 5050.49 | L59: 1250.99 | M59: 1117.43 | N59: 1245.04 | O59: 1274.72 | P59: 4932.39 | Q59: 1227.19 | R59: 1092.09 | S59: 1226.69 | T59: 1261.19 | U59: 4817.58 | V59: 1214.53 | W59: 1074.08 | X59: 1210.19 | Y59: 1247.95 | Z59: 4742.55 | AA59: 1187.1 | AB59: 1049.97 | AC59: 1182.15 | AD59: 1218.44 | AE59: 4651.99
A60: Internal/Organic net adds - Prepaid Phones(K#) | B60: -20 | C60: -34 | D60: -83 | E60: -255 | F60: -392 | G60: -72 | H60: 4 | I60: -67.97 | J60: -199.7 | K60: -335.68 | L60: -46.26 | M60: 0.2 | N60: -63.02 | O60: -194.5 | P60: -289.32 | Q60: -59.65 | R60: -6.94 | S60: -84.92 | T60: -227.93 | U60: -283.09 | V60: -61.27 | W60: -1.16 | X60: -80.42 | Y60: -225.59 | Z60: -241.37 | AA60: -64.11 | AB60: -5.21 | AC60: -83.31 | AD60: -227.18 | AE60: -227.54
A61: Acquired net adds - Prepaid Phones(K#) | B61: -35 | C61: -35 | D61: -56 | E61: -69 | F61: -195 | G61: -4 | H61: -40 | I61: -5.79 | J61: -4.64 | K61: -54.43 | L61: -2.27 | M61: -2.27 | N61: -2.27 | O61: -2.27 | P61: -17.14 | Q61: -3.57 | R61: -3.57 | S61: -3.57 | T61: -3.57 | U61: -18.46 | V61: -5 | W61: -5 | X61: -5 | Y61: -5 | Z61: -21.82 | AA61: -5 | AB61: -5 | AC61: -5 | AD61: -5 | AE61: -21.82
A62: Net adds - Prepaid Phones(K#) | B62: -55 | C62: -69 | D62: -139 | E62: -324 | F62: -587 | G62: -76 | H62: -36 | I62: -73.18 | J62: -200.72 | K62: -385.9 | L62: -48.53 | M62: -2.07 | N62: -65.29 | O62: -196.77 | P62: -306.46 | Q62: -63.23 | R62: -10.51 | S62: -88.49 | T62: -231.5 | U62: -301.55 | V62: -66.27 | W62: -6.16 | X62: -85.42 | Y62: -230.59 | Z62: -263.19 | AA62: -69.11 | AB62: -10.21 | AC62: -88.31 | AD62: -232.18 | AE62: -249.36
A63: Subscribers - Prepaid Phones(K#) | B63: 17162 | C63: 17093 | D63: 16954 | E63: 16630 | F63: 16630 | G63: 16554 | H63: 16518 | I63: 16444.82 | J63: 16244.1 | K63: 16244.1 | L63: 16192.17 | M63: 16190.1 | N63: 16124.81 | O63: 15928.03 | P63: 15933.43 | Q63: 15746.54 | R63: 15736.03 | S63: 15647.54 | T63: 15416.04 | U63: 15623.07 | V63: 15352.31 | W63: 15346.15 | X63: 15260.72 | Y63: 15030.14 | Z63: 15398.67 | AA63: 14961.03 | AB63: 14950.82 | AC63: 14862.51 | AD63: 14630.33 | AE63: 15149.32
A64: Average subs - Prepaid phones(K#) | B64: 17189.5 | C64: 17127.5 | D64: 17023.5 | E64: 16792 | F64: 16923.5 | G64: 16592 | H64: 16536 | I64: 16481.41 | J64: 16344.46 | K64: 16451.68 | L64: 16216.44 | M64: 16191.14 | N64: 16157.45 | O64: 16026.42 | P64: 16103.19 | Q64: 15778.16 | R64: 15741.29 | S64: 15691.79 | T64: 15531.79 | U64: 15791.37 | V64: 15385.45 | W64: 15349.23 | X64: 15303.44 | Y64: 15145.43 | Z64: 15550.67 | AA64: 14995.58 | AB64: 14955.93 | AC64: 14906.67 | AD64: 14746.42 | AE64: 15294.1
A65: ARPU - Prepaid Phones($) | B65: 36.57 | C65: 36.89 | D65: 36.77 | E65: 36.49 | F65: 36.68 | G65: 36.49 | H65: 36.81 | I65: 36.88 | J65: 36.73 | K65: 36.78 | L65: 36.69 | M65: 36.9 | N65: 37.02 | O65: 36.92 | P65: 36.89 | Q65: 37.01 | R65: 37.25 | S65: 37.44 | T65: 37.36 | U65: 37.12 | V65: 37.08 | W65: 37.35 | X65: 37.66 | Y65: 37.39 | Z65: 37.11 | AA65: 37.27 | AB65: 37.54 | AC65: 37.95 | AD65: 37.69 | AE65: 37.22
A66: Revenue - Prepaid Phones | B66: 1885.86 | C66: 1895.5 | D66: 1877.86 | E66: 1838.22 | F66: 7497.44 | G66: 1816.33 | H66: 1826.07 | I66: 1822.32 | J66: 1799.38 | K66: 7261.47 | L66: 1783.48 | M66: 1790.76 | N66: 1791.92 | O66: 1772.23 | P66: 7123.76 | Q66: 1751.46 | R66: 1758.84 | S66: 1761.91 | T66: 1740.3 | U66: 7021.62 | V66: 1710.93 | W66: 1719.23 | X66: 1728.6 | Y66: 1698.59 | Z66: 6908.7 | AA66: 1675.84 | AB66: 1683.56 | AC66: 1696.63 | AD66: 1667.34 | AE66: 6810.33
A68: Total phones
A69: Beginning subs - Phone(K#) | B69: 89966 | C69: 90193 | D69: 90501 | E69: 90755 | F69: 89966 | G69: 90844 | H69: 91057 | I69: 91439 | J69: 91741.61 | K69: 90844 | L69: 91953.9 | M69: 92175.11 | N69: 92540.62 | O69: 92813.69 | P69: 91949.2 | Q69: 92869.79 | R69: 93024.41 | S69: 93336.21 | T69: 93509.25 | U69: 92928.32 | V69: 93709.22 | W69: 93808.43 | X69: 94102.42 | Y69: 94247.16 | Z69: 93821.67 | AA69: 94271.71 | AB69: 94320.56 | AC69: 94564.25 | AD69: 94659.17 | AE69: 94518.27
A70: Gross adds - Phone(K#) | B70: 3436.65 | C70: 3534.45 | D70: 3692.33 | E70: 3732.63 | F70: 14396.06 | G70: 3497.49 | H70: 3500.23 | I70: 3453.83 | J70: 3531.21 | K70: 13982.76 | L70: 3212.51 | M70: 3226.56 | N70: 3374.14 | O70: 3443 | P70: 13517.44 | Q70: 3064.72 | R70: 3095.49 | S70: 3250.83 | T70: 3336.94 | U70: 13502.71 | V70: 2924.56 | W70: 2963.83 | X70: 3118.84 | Y70: 3236.48 | Z70: 13445.35 | AA70: 2915.24 | AB70: 2954.63 | AC70: 3106.63 | AD70: 3222.09 | AE70: 13428.12
A71: Churn - Phone(%) | B71: 0.0116 | C71: 0.0117 | D71: 0.0124 | E71: 0.0131 | F71: 0.0122 | G71: 0.012 | H71: 0.0112 | I71: 0.0121 | J71: 0.0127 | K71: 0.012 | L71: 0.0117 | M71: 0.011 | N71: 0.0118 | O71: 0.0124 | P71: 0.0118 | Q71: 0.0117 | R71: 0.0111 | S71: 0.012 | T71: 0.0125 | U71: 0.0117 | V71: 0.012 | W71: 0.0112 | X71: 0.0123 | Y71: 0.0129 | Z71: 0.0118 | AA71: 0.0121 | AB71: 0.0113 | AC71: 0.0124 | AD71: 0.0129 | AE71: 0.0118
A72: Disconnects - Phone(K#) | B72: 3132.65 | C72: 3167.45 | D72: 3370.33 | E72: 3566.63 | F72: 13237.06 | G72: 3275.49 | H72: 3064.23 | I72: 3306.6 | J72: 3470.36 | K72: 13116.67 | L72: 3219.17 | M72: 3053.36 | N72: 3286.61 | O72: 3450.68 | P72: 13118.64 | Q72: 3259.11 | R72: 3107.15 | S72: 3372.32 | T72: 3539.78 | U72: 13200.06 | V72: 3394.03 | W72: 3176.2 | X72: 3497.94 | Y72: 3662.03 | Z72: 13432.28 | AA72: 3441.81 | AB72: 3224.12 | AC72: 3543.2 | AD72: 3705.19 | AE72: 13568.12
A73: Internal/Organic net adds - Phone(K#) | B73: 304 | C73: 367 | D73: 322 | E73: 166 | F73: 1159 | G73: 222 | H73: 436 | I73: 352.34 | J73: 251.77 | K73: 1262.11 | L73: 237.89 | M73: 400.15 | N73: 335.62 | O73: 216.5 | P73: 1185.28 | Q73: 209.12 | R73: 362.8 | S73: 287.86 | T73: 167.07 | U73: 1081.27 | V73: 129.75 | W73: 343.72 | X73: 228.79 | Y73: 123.77 | Z73: 938.08 | AA73: 66.65 | AB73: 281.04 | AC73: 165.24 | AD73: 60.72 | AE73: 775.76
A74: Acquired net adds - Phone(K#) | B74: -77 | C74: -59 | D74: -68 | E74: -77 | F74: -281 | G74: -9 | H74: -54 | I74: 0 | J74: 0 | K74: -63 | L74: 0 | M74: 0 | N74: 0 | O74: 0 | P74: 0 | Q74: 0 | R74: 0 | S74: 0 | T74: 0 | U74: 0 | V74: 0 | W74: 0 | X74: 0 | Y74: 0 | Z74: 0 | AA74: 0 | AB74: 0 | AC74: 0 | AD74: 0 | AE74: 0
A75: Net adds - Phone(K#) | B75: 227 | C75: 308 | D75: 254 | E75: 89 | F75: 878 | G75: 213 | H75: 382 | I75: 302.61 | J75: 207.59 | K75: 1105.2 | L75: 221.21 | M75: 365.51 | N75: 273.07 | O75: 179.97 | P75: 1003.44 | Q75: 154.61 | R75: 311.8 | S75: 173.04 | T75: 92.1 | U75: 817.96 | V75: 99.21 | W75: 293.99 | X75: 144.73 | Y75: 24.56 | Z75: 696.6 | AA75: 48.84 | AB75: 243.69 | AC75: 94.93 | AD75: -24.22 | AE75: 565.2
A76: Subscribers - Phone(K#) | B76: 90193 | C76: 90501 | D76: 90755 | E76: 90844 | F76: 90844 | G76: 91057 | H76: 91439 | I76: 91741.61 | J76: 91949.2 | K76: 91949.2 | L76: 92175.11 | M76: 92540.62 | N76: 92813.69 | O76: 92993.67 | P76: 92946.58 | Q76: 93024.41 | R76: 93336.21 | S76: 93509.25 | T76: 93601.34 | U76: 93746.28 | V76: 93808.43 | W76: 94102.42 | X76: 94247.16 | Y76: 94271.71 | Z76: 94518.27 | AA76: 94320.56 | AB76: 94564.25 | AC76: 94659.17 | AD76: 94634.95 | AE76: 95083.47
A77: Average subscribers - Phone(K#) | B77: 90079.5 | C77: 90347 | D77: 90628 | E77: 90799.5 | F77: 90405 | G77: 90950.5 | H77: 91248 | I77: 91590.3 | J77: 91845.41 | K77: 91393.52 | L77: 92064.5 | M77: 92357.86 | N77: 92677.16 | O77: 92903.68 | P77: 92447.31 | Q77: 92947.1 | R77: 93180.31 | S77: 93422.73 | T77: 93555.29 | U77: 93339.83 | V77: 93758.83 | W77: 93955.43 | X77: 94174.79 | Y77: 94259.43 | Z77: 94172.99 | AA77: 94296.13 | AB77: 94442.4 | AC77: 94611.71 | AD77: 94647.06 | AE77: 94803.9
A78: ARPU - Phone($) | B78: 52.75 | C78: 53.22 | D78: 52.91 | E78: 52.86 | F78: 52.97 | G78: 52.86 | H78: 54.17 | I78: 53.81 | J78: 53.79 | K78: 53.66 | L78: 53.75 | M78: 59.33 | N78: 54.35 | O78: 54.29 | P78: 54.15 | Q78: 54.15 | R78: 54.9 | S78: 54.65 | T78: 54.81 | U78: 54.57 | V78: 54.45 | W78: 55.42 | X78: 55.14 | Y78: 55 | Z78: 54.85 | AA78: 54.86 | AB78: 55.84 | AC78: 55.63 | AD78: 55.5 | AE78: 55.2
A79: Revenue - Phone | B79: 14253.84 | C79: 14424.82 | D79: 14384.74 | E79: 14398.03 | F79: 57461.43 | G79: 14422.32 | H79: 14828.2 | I79: 14784.47 | J79: 14818.18 | K79: 58851.72 | L79: 14839.17 | M79: 15073.38 | N79: 15101.24 | O79: 15120.97 | P79: 60063.77 | Q79: 15100.24 | R79: 15347.53 | S79: 15316.14 | T79: 15381.53 | U79: 61106.63 | V79: 15313.67 | W79: 15619.81 | X79: 15579.28 | Y79: 15552.2 | Z79: 61984.93 | AA79: 15518.51 | AB79: 15820.01 | AC79: 15789.22 | AD79: 15757.28 | AE79: 62805.57
A81: Other subscribers
A82: Beginning subscribers - Other subscribers(K#) | B82: 18257 | C82: 18225 | D82: 18195 | E82: 18044 | F82: 18257 | G82: 18329 | H82: 18235 | I82: 18361 | J82: 18370.43 | K82: 18329 | L82: 18698.06 | M82: 18727.89 | N82: 18878.94 | O82: 18909.45 | P82: 18670.29 | Q82: 19531.26 | R82: 19606.83 | S82: 19828.5 | T82: 19911.24 | U82: 19205.02 | V82: 18603.34 | W82: 18542.5 | X82: 18594.12 | Y82: 18494.09 | Z82: 18941.19 | AA82: 18678.41 | AB82: 18619.85 | AC82: 18668.4 | AD82: 18568.02 | AE82: 19138.23
A83: Gross adds - Other subscribers(K#) | B83: 852.59 | C83: 872.9 | D83: 755.96 | E83: 1144.94 | F83: 3626.39 | G83: 772.87 | H83: 977.1 | I83: 1093.2 | J83: 1445.33 | K83: 4288.5 | L83: 556.26 | M83: 811 | N83: 592.08 | O83: 1206.7 | P83: 4888.21 | Q83: 638.01 | R83: 918.27 | S83: 662.56 | T83: 1335.98 | U83: 5065.67 | V83: - | W83: - | X83: - | Y83: - | Z83: 5925.09 | AA83: - | AB83: - | AC83: - | AD83: - | AE83: 5983.89
A84: Churn - Other subscribers(%) | B84: 0.0163 | C84: 0.0166 | D84: 0.0167 | E84: 0.0158 | F84: 0.0085 | G84: 0.0156 | H84: 0.0156 | I84: 0.02 | J84: 0.0201 | K84: 0.013 | L84: 0.01 | M84: 0.01 | N84: 0.01 | O84: 0.01 | P84: 0.019 | Q84: 0.01 | R84: 0.01 | S84: 0.01 | T84: 0.01 | U84: 0.0188 | V84: - | W84: - | X84: - | Y84: - | Z84: 0.023 | AA84: - | AB84: - | AC84: - | AD84: - | AE84: 0.0227
A85: Disconnects - Other subscribers(K#) | B85: 625.17 | C85: 405.1 | D85: 644.69 | E85: 678.76 | F85: 2353.72 | G85: 620.84 | H85: 675.56 | I85: 395.32 | J85: 394.56 | K85: 2086.28 | L85: 605.33 | M85: 625.84 | N85: 646.88 | O85: 673.86 | P85: 1669.68 | Q85: 701.54 | R85: 724.88 | S85: 748.59 | T85: 778.57 | U85: 1821.23 | V85: - | W85: - | X85: - | Y85: - | Z85: 1293.26 | AA85: - | AB85: - | AC85: - | AD85: - | AE85: 1339.77
A86: Internal/Organic net adds - Other subscribers(K#) | B86: -48 | C86: -40 | D86: -161 | E86: 292 | F86: 43 | G86: -64 | H86: 113 | I86: -45.82 | J86: 236.9 | K86: 240.08 | L86: -38.83 | M86: 47.33 | N86: -60.25 | O86: 244.54 | P86: 249.39 | Q86: -61.33 | R86: 29.33 | S86: -87 | T86: 268.5 | U86: 219.46 | V86: -57 | W86: 31.5 | X86: -155.5 | Y86: 292 | Z86: 218.73 | AA86: -57 | AB86: 31.5 | AC86: -155.5 | AD86: 292 | AE86: 212.79
A87: Acquired net adds - Other subscribers(K#) | B87: 16 | C87: 10 | D87: 10 | E87: -7 | F87: 29 | G87: -30 | H87: 13 | I87: - | J87: - | K87: -347.33 | L87: - | M87: - | N87: - | O87: - | P87: - | Q87: - | R87: - | S87: - | T87: - | U87: - | V87: - | W87: - | X87: - | Y87: - | Z87: - | AA87: - | AB87: - | AC87: - | AD87: - | AE87: -
A88: Net adds - Other subscribers(K#) | B88: -32 | C88: -30 | D88: -151 | E88: 285 | F88: 72 | G88: -94 | H88: 126 | I88: -41.32 | J88: 236.64 | K88: 60.66 | L88: -45.83 | M88: 72.82 | N88: -50.35 | O88: 252.72 | P88: 579.66 | Q88: -64.73 | R88: 76.69 | S88: -66.98 | T88: 276.64 | U88: 670.09 | V88: -60.84 | W88: 51.62 | X88: -100.02 | Y88: 151.47 | Z88: 262.72 | AA88: -58.56 | AB88: 48.56 | AC88: -100.39 | AD88: 150.92 | AE88: 255.04
A89: Other subscribers(K#) | B89: 18225 | C89: 18195 | D89: 18044 | E89: 18329 | F89: 18329 | G89: 18235 | H89: 18361 | I89: 18370.43 | J89: 18659.93 | K89: 18670.29 | L89: 18727.89 | M89: 18878.94 | N89: 18909.45 | O89: 19246.06 | P89: 19205.02 | Q89: 19606.83 | R89: 19828.5 | S89: 19911.24 | T89: 20338.27 | U89: 19741.09 | V89: 18542.5 | W89: 18594.12 | X89: 18494.09 | Y89: 18678.41 | Z89: 19138.23 | AA89: 18619.85 | AB89: 18668.4 | AC89: 18568.02 | AD89: 18751.97 | AE89: 19329.51
A90: Average subsribers - Other subscribers(K#) | B90: 18241 | C90: 18210 | D90: 18119.5 | E90: 18186.5 | F90: 18293 | G90: 18282 | H90: 18298 | I90: 18365.72 | J90: 18515.18 | K90: 18460.21 | L90: 18712.97 | M90: 18803.42 | N90: 18894.2 | O90: 19077.76 | P90: 18924.24 | Q90: 19569.05 | R90: 19717.67 | S90: 19869.87 | T90: 20124.76 | U90: 19453.13 | V90: 18572.92 | W90: 18568.31 | X90: 18544.11 | Y90: 18586.25 | Z90: 19014.81 | AA90: 18649.13 | AB90: 18644.13 | AC90: 18618.21 | AD90: 18659.99 | AE90: 19208.96
A91: ARPU - Other subscribers($) | B91: 43.81 | C91: 44.45 | D91: 46.75 | E91: 46.85 | F91: 45.2 | G91: 45.92 | H91: 47.09 | I91: 49.35 | J91: 49.11 | K91: 47.63 | L91: 47.4 | M91: 48.16 | N91: 49.98 | O91: 49.5 | P91: 48.56 | Q91: 48.03 | R91: 48.88 | S91: 50.62 | T91: 49.95 | U91: 49.61 | V91: 48.94 | W91: 50.01 | X91: 52.2 | Y91: 51.76 | Z91: 50.91 | AA91: 49.55 | AB91: 50.63 | AC91: 52.86 | AD91: 52.42 | AE91: 51.74
A92: Revenue - Other subscribers | B92: 2397.16 | C92: 2428.18 | D92: 2541.26 | E92: 2555.97 | F92: 9922.57 | G92: 2518.68 | H92: 2584.8 | I92: 2737.75 | J92: 2745.11 | K92: 10586.89 | L92: 2664.31 | M92: 2765.9 | N92: 2870.49 | O92: 2865.51 | P92: 11137.22 | Q92: 2789.04 | R92: 2866.47 | S92: 3006.11 | T92: 2992.07 | U92: 11603.55 | V92: 2738.58 | W92: 2832.07 | X92: 2948.97 | Y92: 2955.26 | Z92: 11720.51 | AA92: 2800.05 | AB92: 2878.78 | AC92: 3021.87 | AD92: 3002.58 | AE92: 12024.8
A94: Wireless retail subscribers
A95: Churn - Wireless retail(%) | B95: 0.0124 | C95: 0.0132 | D95: 0.0132 | E95: 0.0145 | F95: 0.0137 | G95: 0.0131 | H95: 0.0127 | I95: 0.0134 | J95: 0.0138 | K95: 0.0132 | L95: 0.0129 | M95: 0.0126 | N95: 0.0132 | O95: 0.0136 | P95: 0.0129 | Q95: 0.0128 | R95: 0.0123 | S95: 0.0131 | T95: 0.0135 | U95: 0.0129 | V95: 0.013 | W95: 0.0121 | X95: 0.0131 | Y95: 0.0137 | Z95: 0.0129 | AA95: 0.0129 | AB95: 0.012 | AC95: 0.013 | AD95: 0.0136 | AE95: 0.0128
A96: Gross adds - Wireless retail(K#) | B96: 4565.19 | C96: 4705.48 | D96: 4771.02 | E96: 5246.12 | F96: 19373.29 | G96: 4523.52 | H96: 4673.59 | I96: 4702.71 | J96: 5134.17 | K96: 19074.67 | L96: 4561.73 | M96: 4716.45 | N96: 4697.67 | O96: 5154.93 | P96: 19111.32 | Q96: 4564.18 | R96: 4671.73 | S96: 4686.37 | T96: 5188.66 | U96: 19128.15 | V96: 4573.95 | W96: 4642 | X96: 4654.33 | Y96: 5152.86 | Z96: 19131.62 | AA96: 4553.72 | AB96: 4623.98 | AC96: 4634.31 | AD96: 5133.78 | AE96: 19109.09
A97: Internal/Organic net adds - Wireless retail(K#) | B97: 256 | C97: 327 | D97: 161 | E97: 458 | F97: 1202 | G97: 158 | H97: 549 | I97: 319.67 | J97: 503.34 | K97: 1524.16 | L97: 233.59 | M97: 516.4 | N97: 304.12 | O97: 496.61 | P97: 1594.08 | Q97: 192.45 | R97: 466.19 | S97: 243.28 | T97: 453.87 | U97: 1422.13 | V97: 161.73 | W97: 508.98 | X97: 158.89 | Y97: 454.22 | Z97: 1349.28 | AA97: 133.51 | AB97: 481.18 | AC97: 129.51 | AD97: 425.76 | AE97: 1238.96
A98: Net adds acquired - Wireless retail(K#) | B98: -61 | C98: -49 | D98: -58 | E98: -84 | F98: -252 | G98: -39 | H98: -41 | I98: -35 | J98: -35 | K98: -67.86 | L98: -35 | M98: -35 | N98: -35 | O98: -35 | P98: -140 | Q98: -35 | R98: -35 | S98: -65 | T98: -65 | U98: -200 | V98: -65 | W98: -65 | X98: -65 | Y98: -65 | Z98: -260 | AA98: -65 | AB98: -65 | AC98: -65 | AD98: -65 | AE98: -260
A99: Net adds - Wireless retail(K#) | B99: 195 | C99: 278 | D99: 103 | E99: 374 | F99: 950 | G99: 119 | H99: 508 | I99: 326.76 | J99: 509.47 | K99: 1489.37 | L99: 234.08 | M99: 453.35 | N99: 255.51 | O99: 517.7 | P99: 1553.42 | Q99: 219.87 | R99: 517.89 | S99: 239.38 | T99: 324.88 | U99: 1390.83 | V99: 60.8 | W99: 378.23 | X99: 76.04 | Y99: 263.67 | Z99: 1036.77 | AA99: 17.53 | AB99: 331.28 | AC99: 31.46 | AD99: 220.51 | AE99: 903.1
A100: Subscribers - Wireless retail(K#) | B100: 108418 | C100: 108696 | D100: 108799 | E100: 109173 | F100: 109173 | G100: 109292 | H100: 109800 | I100: 110145.29 | J100: 110654.77 | K100: 110662.37 | L100: 110890.23 | M100: 111404.59 | N100: 111704.75 | O100: 112222.45 | P100: 112222.1 | Q100: 112574.16 | R100: 113092.05 | S100: 113331.43 | T100: 113846.25 | U100: 113577.79 | V100: 112694.02 | W100: 113072.25 | X100: 113148.28 | Y100: 113411.96 | Z100: 114124.65 | AA100: 113429.48 | AB100: 113760.77 | AC100: 113792.23 | AD100: 114012.74 | AE100: 115027.75
A101: Average subscribers - Wireless retail(K#) | B101: 108320.5 | C101: 108557 | D101: 108747.5 | E101: 108986 | F101: 108698 | G101: 109232.5 | H101: 109546 | I101: 109876.97 | J101: 110299.75 | K101: 109797.13 | L101: 110773.19 | M101: 111147.41 | N101: 111554.67 | O101: 111963.6 | P101: 111351.74 | Q101: 112464.23 | R101: 112833.11 | S101: 113211.74 | T101: 113588.84 | U101: 112807.43 | V101: 112663.62 | W101: 112883.13 | X101: 113110.27 | Y101: 113280.12 | Z101: 113551.07 | AA101: 113420.72 | AB101: 113595.13 | AC101: 113776.5 | AD101: 113902.49 | AE101: 114552.02
A102: ARPU - Wireless retail($) | B102: 51.24 | C102: 51.75 | D102: 51.88 | E102: 51.85 | F102: 51.66 | G102: 51.7 | H102: 52.99 | I102: 53.12 | J102: 53.03 | K102: 52.68 | L102: 52.71 | M102: 53.44 | N102: 53.51 | O102: 53.41 | P102: 53.25 | Q102: 53.02 | R102: 53.91 | S102: 53.97 | T102: 53.8 | U102: 53.78 | V102: 53.4 | W102: 54.56 | X102: 54.61 | Y102: 54.43 | Z102: 54.25 | AA102: 53.85 | AB102: 55.02 | AC102: 55.08 | AD102: 54.9 | AE102: 54.65
A103: Service revenues - wireless | B103: 16651 | C103: 16853 | D103: 16926 | E103: 16954 | F103: 67384 | G103: 16941 | H103: 17413 | I103: 17526.97 | J103: 17565.72 | K103: 69453.75 | L103: 17503.72 | M103: 17839.36 | N103: 17971.16 | O103: 17985.62 | P103: 71247.05 | Q103: 17888.28 | R103: 18213.15 | S103: 18321.82 | T103: 18373.47 | U103: 72800.94 | V103: 18052.25 | W103: 18451.87 | X103: 18528.25 | Y103: 18507.46 | Z103: 73883.32 | AA103: 18318.56 | AB103: 18698.79 | AC103: 18811.09 | AD103: 18759.85 | AE103: 75056.66

Sheet Sheet3
