Workbook
Name IQ_CH: 110000
Name IQ_CQ: 5000
Name IQ_CY: 10000
Name IQ_DAILY: 500000
Name IQ_FH: 100000
Name IQ_FQ: 500
Name IQ_FY: 1000
Name IQ_LTM: 2000
Name IQ_MONTH: 15000
Name IQ_NTM: 6000
Name IQ_WEEK: 50000
Name IQ_YTD: 3000

Sheet 3Q26 Quick Look
A1: Comcast Corporation (CMCSA) — Q3 2026 Earnings First Look
A2: $M (except for as noted) | B2: Q3'25 | C2: Q2'26 | D2: Q3'26 (CON) | E2: Actual | F2: YoY Growth (3Q26 vs 3Q25) | G2: Delta (vs Con.)
A3: Total Revenue | B3: ='SPG Segments'!D22 -> 29151 | C3: ='SPG Segments'!H22 -> 29568 | D3: ='SPG Segments'!I22 -> 29229.46 | F3: =IF(E3="","",(E3-B3)/B3) | G3: =IF(E3="","",(E3-D3)/ABS(D3))
A4: C&P | B4: ='SPG Conn & Platforms'!D49 -> 20212 | C4: ='SPG Conn & Platforms'!H49 -> 19795 | D4: ='SPG Conn & Platforms'!I49 -> 19677.91 | F4: =IF(E4="","",(E4-B4)/B4) | G4: =IF(E4="","",(E4-D4)/ABS(D4))
A5: Residential | B5: ='SPG Conn & Platforms'!D64 -> 17636 | C5: ='SPG Conn & Platforms'!H64 -> 17124 | D5: ='SPG Conn & Platforms'!I64 -> 17027.39 | F5: =IF(E5="","",(E5-B5)/B5) | G5: =IF(E5="","",(E5-D5)/ABS(D5))
A6: Convergence Revenue | B6: =B7+B8 -> 7465 | C6: =C7+C8 -> 7287 | D6: =D7+D8 -> 7278.19 | E6: =IF(OR(E7="",E8=""),"",E7+E8) | F6: =IF(E6="","",(E6-B6)/B6) | G6: =IF(E6="","",(E6-D6)/ABS(D6))
A7: Broadband Revenue | B7: ='SPG Conn & Platforms'!D20 -> 6550 | C7: ='SPG Conn & Platforms'!H20 -> 6280 | D7: ='SPG Conn & Platforms'!I20 -> 6221.77 | F7: =IF(E7="","",(E7-B7)/B7) | G7: =IF(E7="","",(E7-D7)/ABS(D7))
A8: Mobile Revenue | B8: ='SPG Wireless'!D28 -> 915 | C8: ='SPG Wireless'!H28 -> 1007 | D8: ='SPG Wireless'!I28 -> 1056.42 | F8: =IF(E8="","",(E8-B8)/B8) | G8: =IF(E8="","",(E8-D8)/ABS(D8))
A9: Business Services | B9: ='SPG Conn & Platforms'!D71 -> 2576 | C9: ='SPG Conn & Platforms'!H71 -> 2671 | D9: ='SPG Conn & Platforms'!I71 -> 2650.53 | F9: =IF(E9="","",(E9-B9)/B9) | G9: =IF(E9="","",(E9-D9)/ABS(D9))
A10: C&E | B10: ='SPG Content & Experiences'!D23 -> 9897 | C10: ='SPG Content & Experiences'!H23 -> 10728 | D10: ='SPG Content & Experiences'!I23 -> 10519.29 | F10: =IF(E10="","",(E10-B10)/B10) | G10: =IF(E10="","",(E10-D10)/ABS(D10))
A11: Media | B11: ='SPG Content & Experiences'!D17 -> 4744 | C11: ='SPG Content & Experiences'!H17 -> 5691 | D11: ='SPG Content & Experiences'!I17 -> 5354.47 | F11: =IF(E11="","",(E11-B11)/B11) | G11: =IF(E11="","",(E11-D11)/ABS(D11))
A12: Studios | B12: ='SPG Content & Experiences'!D18 -> 3000 | C12: ='SPG Content & Experiences'!H18 -> 3040 | D12: ='SPG Content & Experiences'!I18 -> 3076.95 | F12: =IF(E12="","",(E12-B12)/B12) | G12: =IF(E12="","",(E12-D12)/ABS(D12))
A13: Park | B13: ='SPG Content & Experiences'!D19 -> 2717 | C13: ='SPG Content & Experiences'!H19 -> 2413 | D13: ='SPG Content & Experiences'!I19 -> 2668.31 | F13: =IF(E13="","",(E13-B13)/B13) | G13: =IF(E13="","",(E13-D13)/ABS(D13))
A15: Total EBITDA | B15: ='SPG Segments'!D38 -> 9038 | C15: ='SPG Segments'!H38 -> 8923 | D15: ='SPG Segments'!I38 -> 8867.61 | F15: =IF(E15="","",(E15-B15)/B15) | G15: =IF(E15="","",(E15-D15)/ABS(D15))
A16: C&P | B16: ='SPG Conn & Platforms'!D54 -> 7938 | C16: ='SPG Conn & Platforms'!H54 -> 7964 | D16: ='SPG Conn & Platforms'!I54 -> 7568.55 | F16: =IF(E16="","",(E16-B16)/B16) | G16: =IF(E16="","",(E16-D16)/ABS(D16))
A17: Residential | B17: ='SPG Conn & Platforms'!D52 -> 6484 | C17: ='SPG Conn & Platforms'!H52 -> 6448 | D17: ='SPG Conn & Platforms'!I52 -> 6095.11 | F17: =IF(E17="","",(E17-B17)/B17) | G17: =IF(E17="","",(E17-D17)/ABS(D17))
A18: Business Services | B18: ='SPG Conn & Platforms'!D53 -> 1454 | C18: ='SPG Conn & Platforms'!H53 -> 1516 | D18: ='SPG Conn & Platforms'!I53 -> 1491.75 | F18: =IF(E18="","",(E18-B18)/B18) | G18: =IF(E18="","",(E18-D18)/ABS(D18))
A19: EBITDA Margin | B19: =B16/B4 -> 0.39273699 | C19: =C16/C4 -> 0.40232382 | D19: =D16/D4 -> 0.38462164 | E19: =IF(OR(E16="",E4=""),"",E16/E4) | F19: =IF(E19="","",E19-B19) | G19: =IF(E19="","",E19-D19)
A20: C&E | B20: ='SPG Content & Experiences'!D32 -> 1392 | C20: ='SPG Content & Experiences'!H32 -> 1329 | D20: ='SPG Content & Experiences'!I32 -> 1609.76 | F20: =IF(E20="","",(E20-B20)/B20) | G20: =IF(E20="","",(E20-D20)/ABS(D20))
A21: Media | B21: ='SPG Content & Experiences'!D26 -> 247 | C21: ='SPG Content & Experiences'!H26 -> 708 | D21: ='SPG Content & Experiences'!I26 -> 595.67 | F21: =IF(E21="","",(E21-B21)/B21) | G21: =IF(E21="","",(E21-D21)/ABS(D21))
A22: Studios | B22: ='SPG Content & Experiences'!D27 -> 338 | C22: ='SPG Content & Experiences'!H27 -> 202 | D22: ='SPG Content & Experiences'!I27 -> 400.42 | F22: =IF(E22="","",(E22-B22)/B22) | G22: =IF(E22="","",(E22-D22)/ABS(D22))
A23: Park | B23: ='SPG Content & Experiences'!D28 -> 940.4 | C23: ='SPG Content & Experiences'!H28 -> 608 | D23: ='SPG Content & Experiences'!I28 -> 789.64 | F23: =IF(E23="","",(E23-B23)/B23) | G23: =IF(E23="","",(E23-D23)/ABS(D23))
A24: EBITDA Margin | B24: =B20/B10 -> 0.14064868 | C24: =C20/C10 -> 0.12388143 | D24: =D20/D10 -> 0.15302934 | E24: =IF(OR(E20="",E10=""),"",E20/E10) | F24: =IF(E24="","",E24-B24) | G24: =IF(E24="","",E24-D24)
A26: Adjusted EPS | B26: ='SPG Income Statement'!D40 -> 0.95 | C26: ='SPG Income Statement'!H40 -> 1.04 | D26: ='SPG Income Statement'!I40 -> 0.97 | F26: =IF(E26="","",(E26-B26)/B26) | G26: =IF(E26="","",(E26-D26)/ABS(D26))
A27: FCF | B27: ='SPG Free Cash Flow'!D20 -> 4945 | C27: ='SPG Free Cash Flow'!H20 -> 4604 | D27: ='SPG Free Cash Flow'!I20 -> 3425.71 | F27: =IF(E27="","",(E27-B27)/B27) | G27: =IF(E27="","",(E27-D27)/ABS(D27))
A29: Operational metrics
A30: Resi BB Net adds (in 000') | B30: ='SPG C&P Customer Metrics'!D36 -> -91 | C30: ='SPG C&P Customer Metrics'!H36 -> -167 | D30: ='SPG C&P Customer Metrics'!I36 -> -135.59 | F30: =IF(E30="","",(E30-B30)/B30) | G30: =IF(E30="","",(E30-D30)/ABS(D30))
A31: Resi BB ARPU (implied) | B31: ='SPG C&P Customer Metrics'!D46 -> 75.44 | C31: ='SPG C&P Customer Metrics'!H46 -> 73.27 | D31: ='SPG C&P Customer Metrics'!I46 -> 72.96 | F31: =IF(E31="","",(E31-B31)/B31) | G31: =IF(E31="","",(E31-D31)/ABS(D31))
A32: Video net adds (in 000') | B32: ='SPG C&P Customer Metrics'!D53 -> -256 | C32: ='SPG C&P Customer Metrics'!H53 -> -280 | D32: ='SPG C&P Customer Metrics'!I53 -> -246.9 | F32: =IF(E32="","",(E32-B32)/B32) | G32: =IF(E32="","",(E32-D32)/ABS(D32))
A33: Wireless net adds (in 000') | B33: ='SPG C&P Customer Metrics'!D50 -> 414 | C33: ='SPG C&P Customer Metrics'!H50 -> 448 | D33: ='SPG C&P Customer Metrics'!I50 -> 399.29 | F33: =IF(E33="","",(E33-B33)/B33) | G33: =IF(E33="","",(E33-D33)/ABS(D33))
A34: Peacock (EOP sub) | B34: ='SPG Peacock'!D28/1000 -> 41 | C34: ='SPG Peacock'!H28/1000 -> 48 | D34: ='SPG Peacock'!I28/1000 -> 48.22188 | F34: =IF(E34="","",(E34-B34)/B34) | G34: =IF(E34="","",(E34-D34)/ABS(D34))

Sheet CapIQ cons on Oct 20, 2026 ->

Sheet SPG Income Statement
A2: Comcast Corporation | Income statement
A3: NASDAQGS:CMCSA (MI KEY: 4057180; SPCIQ KEY: 173341)
A5: Visible Alpha
A7: Period Type : Fiscal Quarter, Fiscal Halves, Fiscal Year
A8: Period Start : 2025
A9: Period End : 2030
A10: Currency : Reported
A11: Consensus View : Mean
A12: As Of: 10/20/2026
A14: All numbers in $M unless otherwise indicated | B14: FQ1 2025A | C14: FQ2 2025A | D14: FQ3 2025A | E14: FQ4 2025A | F14: FY2025A | G14: FQ1 2026A | H14: FQ2 2026A | I14: FQ3 2026E | J14: FQ4 2026E | K14: FY2026E | L14: FQ1 2027E | M14: FQ2 2027E | N14: FQ3 2027E | O14: FQ4 2027E | P14: FY2027E | Q14: FQ1 2028E | R14: FQ2 2028E | S14: FQ3 2028E | T14: FQ4 2028E | U14: FY2028E | V14: FQ1 2029E | W14: FQ2 2029E | X14: FQ3 2029E | Y14: FQ4 2029E | Z14: FY2029E | AA14: FQ1 2030E | AB14: FQ2 2030E | AC14: FQ3 2030E | AD14: FQ4 2030E | AE14: FY2030E
A15: Number of Contributors Available | B15: 22 | C15: 21 | D15: 21 | E15: 20 | F15: 21 | G15: 21 | H15: 20 | I15: 20 of 20 | J15: 20 of 20 | K15: 20 of 20 | L15: 12 of 20 | M15: 12 of 20 | N15: 11 of 20 | O15: 11 of 20 | P15: 20 of 20 | Q15: 8 of 20 | R15: 8 of 20 | S15: 8 of 20 | T15: 8 of 20 | U15: 19 of 20 | V15: 7 of 20 | W15: 7 of 20 | X15: 7 of 20 | Y15: 7 of 20 | Z15: 16 of 20 | AA15: 7 of 20 | AB15: 7 of 20 | AC15: 7 of 20 | AD15: 7 of 20 | AE15: 16 of 20
A16: Revenue | B16: 27865 | C16: 28249 | D16: 29151 | E16: 30287 | F16: 115552 | G16: 30892 | H16: 29568 | I16: 29229.46 | J16: 30096.76 | K16: 119902.79 | L16: 29232.16 | M16: 29071.52 | N16: 28889.77 | O16: 30006.17 | P16: 117534.94 | Q16: 29428.42 | R16: 29256.84 | S16: 30939.39 | T16: 30410.85 | U16: 120340.38 | V16: 29699.41 | W16: 29443.43 | X16: 29425.33 | Y16: 30534.94 | Z16: 119319.01 | AA16: 31312.12 | AB16: 29925.52 | AC16: 29876.6 | AD16: 30986.23 | AE16: 122294.14
A17: Total cost and exp. excl. D&A | B17: 19170 | C17: 18826 | D17: 20113 | E17: 22989 | F17: 81098 | G17: 22925 | H17: 20645 | I17: 20349.17 | J17: 22678.22 | K17: 86776.23 | L17: 21231.38 | M17: 20184.31 | N17: 19962.22 | O17: 22332.76 | P17: 84173.96 | Q17: 21319.98 | R17: 20268.68 | S17: 21817.52 | T17: 22662.51 | U17: 86309.48 | V17: 21551.81 | W17: 20322.91 | X17: 20206.81 | Y17: 22686.03 | Z17: 85081.04 | AA17: 22962.76 | AB17: 20655.1 | AC17: 20498.39 | AD17: 22887.16 | AE17: 87294.06
A18: Adjusted EBITDA | B18: 8695 | C18: 9423 | D18: 9038 | E18: 7298 | F18: 34454 | G18: 7967 | H18: 8923 | I18: 8867.61 | J18: 7422.42 | K18: 33164.19 | L18: 8035.64 | M18: 8864.77 | N18: 8868.47 | O18: 7609 | P18: 33333.85 | Q18: 8122.09 | R18: 8914.82 | S18: 9026.42 | T18: 7659.09 | U18: 33967.78 | V18: 8158.34 | W18: 8989.6 | X18: 9054.84 | Y18: 7733.29 | Z18: 34127.15 | AA18: 8241.84 | AB18: 9099.61 | AC18: 9198.46 | AD18: 7956.13 | AE18: 34809.51
A19: Depreciation | B19: 2231 | C19: 2349 | D19: 2353 | E19: 2393 | F19: 9326 | G19: 2333 | H19: 2391 | I19: 2349.97 | J19: 2373.61 | K19: 9410.61 | L19: 2358.11 | M19: 2392.05 | N19: 2363.81 | O19: 2382.45 | P19: 9582.01 | Q19: 2348.53 | R19: 2391.8 | S19: 2412.19 | T19: 2444.36 | U19: 9744.82 | V19: 2430.9 | W19: 2465.94 | X19: 2423.56 | Y19: 2446.11 | Z19: 9933.48 | AA19: 2435.65 | AB19: 2472.84 | AC19: 2439.92 | AD19: 2463.54 | AE19: 10047.78
A20: Amortization | B20: 1618 | C20: 1805 | D20: 1666 | E20: 1794 | F20: 6883 | G20: 1533 | H20: 1297 | I20: 1396.77 | J20: 1393.85 | K20: 5609.59 | L20: 1323.38 | M20: 1251.75 | N20: 1323.6 | O20: 1343.82 | P20: 5212.58 | Q20: 1306.37 | R20: 1279.76 | S20: 1346.61 | T20: 1329.01 | U20: 5176.5 | V20: 1303.87 | W20: 1272.44 | X20: 1292.96 | Y20: 1313.96 | Z20: 4946.54 | AA20: 1344.75 | AB20: 1277.75 | AC20: 1296.86 | AD20: 1315.74 | AE20: 4953.76
A21: Depreciation and amortization | B21: 3849 | C21: 4154 | D21: 4020 | E21: 4187 | F21: 16210 | G21: 3866 | H21: 3688 | I21: 3785.68 | J21: 3814.22 | K21: 15125.74 | L21: 3758.04 | M21: 3716.72 | N21: 3793.71 | O21: 3842.65 | P21: 15065.61 | Q21: 3709.96 | R21: 3677.4 | S21: 3802.91 | T21: 3837.1 | U21: 15145.1 | V21: 3781.74 | W21: 3758.57 | X21: 3768.61 | Y21: 3810.11 | Z21: 15141.66 | AA21: 3825.86 | AB21: 3773.78 | AC21: 3791.01 | AD21: 3831.65 | AE21: 15263.18
A22: Total goodwill and other expenses | B22: 25 | C22: 137 | D22: 116 | E22: 225 | F22: 634 | G22: -72 | H22: 75 | I22: - | J22: - | K22: 112.12 | L22: - | M22: -1 | N22: - | O22: - | P22: 1 | Q22: - | R22: - | S22: - | T22: - | U22: 1 | V22: - | W22: - | X22: - | Y22: - | Z22: 1 | AA22: - | AB22: - | AC22: - | AD22: - | AE22: 1
A23: Total costs and expenses | B23: 23043 | C23: 22257 | D23: 24250 | E23: 27401 | F23: 103035 | G23: 27322 | H23: 24408 | I23: 24073.71 | J23: 26435.02 | K23: 101841.75 | L23: 24942.62 | M23: 23875.52 | N23: 23779.09 | O23: 26175.64 | P23: 99057.81 | Q23: 24992.55 | R23: 23950.59 | S23: 25641.58 | T23: 26495.32 | U23: 101305.24 | V23: 25289.23 | W23: 24114.85 | X23: 24053.52 | Y23: 26516.51 | Z23: 100136.37 | AA23: 26875.13 | AB23: 24469.14 | AC23: 24386.86 | AD23: 26779.18 | AE23: 102468.05
A24: Operating income/(loss) | B24: 5658 | C24: 5129 | D24: 4901 | E24: 3488 | F24: 20672 | G24: 4135 | H24: 5160 | I24: 5095.43 | J24: 3583.71 | K24: 17963.32 | L24: 4313.42 | M24: 5149.39 | N24: 5087.04 | O24: 3799.99 | P24: 18309.26 | Q24: 4477.94 | R24: 5237.51 | S24: 5276.56 | T24: 3878.54 | U24: 18887.33 | V24: 4457.46 | W24: 5247.35 | X24: 5337.06 | Y24: 3973.54 | Z24: 19022.08 | AA24: 4497.55 | AB24: 5374.89 | AC24: 5455.27 | AD24: 4160.79 | AE24: 19587.95
A25: Interest expense | B25: 1050 | C25: 1105 | D25: 1128 | E25: 1126 | F25: 4409 | G25: 1094 | H25: 1052 | I25: 1014.6 | J25: 1012.33 | K25: 4172.93 | L25: 1004.38 | M25: 1000.18 | N25: 1000.21 | O25: 1002.11 | P25: 3993.73 | Q25: 995.05 | R25: 990.43 | S25: 993.24 | T25: 994.02 | U25: 3908.06 | V25: 1007.43 | W25: 1002.77 | X25: 1005.59 | Y25: 1005.41 | Z25: 3866.16 | AA25: 1003.84 | AB25: 999.36 | AC25: 1002.3 | AD25: 1003.24 | AE25: 3822.26
A26: Realized and unrealized gains losses on equity securities | B26: -24 | C26: 136 | D26: -60 | E26: -72 | F26: -20 | G26: -5 | H26: -13 | I26: -21.9 | J26: -47.5 | K26: -19.71 | L26: -23.61 | M26: -15.96 | N26: -20.25 | O26: -0.91 | P26: 105.78 | Q26: - | R26: - | S26: - | T26: - | U26: 197.68 | V26: - | W26: - | X26: - | Y26: - | Z26: 221.58 | AA26: - | AB26: - | AC26: - | AD26: - | AE26: 263.17
A27: Other income (expense), net | B27: 102 | C27: 9652 | D27: 212 | E27: 148 | F27: 10114 | G27: 87 | H27: 232 | I27: 102.34 | J27: 93.51 | K27: 361.56 | L27: 112.33 | M27: 100.07 | N27: 111.18 | O27: 90.01 | P27: 361.38 | Q27: 88.73 | R27: 88.37 | S27: 91.64 | T27: 89.85 | U27: 356.46 | V27: 86.69 | W27: 86.24 | X27: 89.41 | Y27: 87.04 | Z27: 341.92 | AA27: 83.28 | AB27: 84.42 | AC27: 89.21 | AD27: 88.34 | AE27: 334.73
A28: Other Income/(loss) | B28: 78 | C28: 9788 | D28: 152 | E28: 76 | F28: 10094 | G28: 82 | H28: 219 | I28: 83.58 | J28: 65.2 | K28: 312.87 | L28: 79.1 | M28: 98.72 | N28: 100.16 | O28: 92.26 | P28: 388.63 | Q28: 63.04 | R28: 113.27 | S28: 106.31 | T28: 98.47 | U28: 426.83 | V28: 63.87 | W28: 116.59 | X28: 109.19 | Y28: 100.8 | Z28: 432.33 | AA28: 64.32 | AB28: 120.2 | AC28: 112.93 | AD28: 104.65 | AE28: 452
A29: Equity in net income (losses) of investees, net | B29: -194 | C29: -29 | D29: -90 | E29: -278 | F29: -591 | G29: -391 | H29: 285 | I29: -51.39 | J29: -107.99 | K29: -98.55 | L29: -200.45 | M29: 172 | N29: -65.65 | O29: -151.48 | P29: -155.11 | Q29: -320.62 | R29: 233.7 | S29: -68.04 | T29: -210.17 | U29: -188.45 | V29: -295.6 | W29: 215.46 | X29: -63.43 | Y29: -195.93 | Z29: -177.97 | AA29: -275.58 | AB29: 200.87 | AC29: -59.75 | AD29: -184.55 | AE29: -169.2
A30: Nonoperating income/(expense) | B30: -1166 | C30: 8654 | D30: -1066 | E30: -1328 | F30: 5094 | G30: -1403 | H30: -548 | I30: -995.08 | J30: -1031.72 | K30: -3979.9 | L30: -1034.13 | M30: -883.79 | N30: -969.46 | O30: -1006.87 | P30: -3840.86 | Q30: -1051.56 | R30: -889.53 | S30: -970.38 | T30: -1009.64 | U30: -3750.23 | V30: -1064.51 | W30: -891.25 | X30: -976.92 | Y30: -1018.19 | Z30: -3677.98 | AA30: -1055.01 | AB30: -890.45 | AC30: -970.98 | AD30: -1011.11 | AE30: -3615.95
A31: Income/(loss) before income taxes | B31: 4492 | C31: 13783 | D31: 3835 | E31: 2160 | F31: 25766 | G31: 2732 | H31: 4612 | I31: 4080.04 | J31: 2559.64 | K31: 13947.19 | L31: 3247.61 | M31: 4231.33 | N31: 4117.58 | O31: 2793.12 | P31: 14437.94 | Q31: 3426.38 | R31: 4347.98 | S31: 4306.18 | T31: 2868.91 | U31: 15084.83 | V31: 3392.95 | W31: 4356.11 | X31: 4360.15 | Y31: 2955.35 | Z31: 15381.58 | AA31: 3442.53 | AB31: 4484.43 | AC31: 4484.29 | AD31: 3149.68 | AE31: 16002.52
A32: Income tax expense/(benefit) | B32: 1196 | C32: 3603 | D32: 1218 | E32: 89 | F32: 6106 | G32: 706 | H32: 1194 | I32: 1043.19 | J32: 633.56 | K32: 3576.73 | L32: 816.86 | M32: 1059.07 | N32: 1030.94 | O32: 702.32 | P32: 3687.62 | Q32: 882.89 | R32: 1113.28 | S32: 1104.14 | T32: 739.86 | U32: 3881.62 | V32: 875.91 | W32: 1116.79 | X32: 1117.54 | Y32: 766.36 | Z32: 3962.45 | AA32: 888.27 | AB32: 1149.73 | AC32: 1149.48 | AD32: 814.46 | AE32: 4119.73
A33: Net income/(loss) before non-controlling interest | B33: 3296 | C33: 10180 | D33: 2617 | E33: 2071 | F33: 19660 | G33: 2026 | H33: 3419 | I33: 3045.58 | J33: 1935.77 | K33: 10412.46 | L33: 2457.02 | M33: 3190.84 | N33: 3086.64 | O33: 2090.8 | P33: 10788.92 | Q33: 2543.5 | R33: 3234.82 | S33: 3202.03 | T33: 2129.05 | U33: 11268.46 | V33: 2517.03 | W33: 3239.46 | X33: 3242.61 | Y33: 2188.99 | Z33: 11419.2 | AA33: 2554.26 | AB33: 3334.85 | AC33: 3334.81 | AD33: 2335.22 | AE33: 11882.86
A34: Noncontrolling interests, net | B34: -79 | C34: -79 | D34: -83 | E34: -97 | F34: -338 | G34: -147 | H34: -107 | I34: -83.82 | J34: -94.23 | K34: -420.84 | L34: -82.79 | M34: -93.66 | N34: -69.77 | O34: -88.63 | P34: -340.1 | Q34: -79.91 | R34: -89.02 | S34: -51.81 | T34: -76.21 | U34: -330.62 | V34: -69.92 | W34: -75.08 | X34: -29.34 | Y34: -58 | Z34: -303.4 | AA34: -71.01 | AB34: -64.36 | AC34: -12.59 | AD34: -40.46 | AE34: -290
A35: Net income/(loss) attributable to CMCSA | B35: 3375 | C35: 10259 | D35: 2700 | E35: 2168 | F35: 19998 | G35: 2174 | H35: 3526 | I35: 3120.67 | J35: 2020.31 | K35: 10789.06 | L35: 2513.54 | M35: 3266.01 | N35: 3156.41 | O35: 2179.43 | P35: 11090.47 | Q35: 2623.41 | R35: 3323.84 | S35: 3253.84 | T35: 2205.25 | U35: 11533.88 | V35: 2586.95 | W35: 3314.55 | X35: 3271.95 | Y35: 2246.99 | Z35: 11722.6 | AA35: 2625.27 | AB35: 3399.21 | AC35: 3347.39 | AD35: 2375.68 | AE35: 12172.86
A36: Net of tax adjustments | B36: 757 | C36: -6471 | D36: 793 | E36: 895 | F36: -4026 | G36: 690 | H36: 185 | I36: 382.75 | J36: 359.49 | K36: 1601.38 | L36: 392.53 | M36: 362.03 | N36: 393.08 | O36: 362.77 | P36: 1487.87 | Q36: 454.55 | R36: 354.08 | S36: 401.3 | T36: 391.95 | U36: 1448.02 | V36: 468.82 | W36: 359.61 | X36: 403.01 | Y36: 415.82 | Z36: 1477.71 | AA36: 457.16 | AB36: 347.99 | AC36: 389.73 | AD36: 402.45 | AE36: 1444.6
A37: Net income/(loss) attributable to CMCSA - operating | B37: 4132 | C37: 4653 | D37: 3493 | E37: 3062 | F37: 15972 | G37: 2863 | H37: 3710 | I37: 3463.72 | J37: 2355.12 | K37: 12384.21 | L37: 2882.53 | M37: 3631.29 | N37: 3571.25 | O37: 2582.3 | P37: 12526.77 | Q37: 3077.96 | R37: 3677.92 | S37: 3655.14 | T37: 2597.21 | U37: 12942.5 | V37: 3055.78 | W37: 3674.15 | X37: 3674.96 | Y37: 2662.81 | Z37: 13126.66 | AA37: 3082.43 | AB37: 3747.19 | AC37: 3737.13 | AD37: 2778.12 | AE37: 13586.02
A38: EPS - basic($) | B38: 0.9 | C38: 2.99 | D38: 0.91 | E38: 0.6 | F38: 5.41 | G38: 0.61 | H38: 0.99 | I38: 0.88 | J38: 0.55 | K38: 3.02 | L38: 0.7 | M38: 0.95 | N38: 0.91 | O38: 0.64 | P38: 3.19 | Q38: 0.74 | R38: 1.01 | S38: 0.96 | T38: 0.71 | U38: 3.48 | V38: 0.78 | W38: 1.06 | X38: 1.01 | Y38: 0.71 | Z38: 3.7 | AA38: 0.85 | AB38: 1.14 | AC38: 1.08 | AD38: 0.78 | AE38: 4.14
... A43: Dividend per share($) | B43: 0.33 | C43: 0.33 | D43: 0.33 | E43: 0.33 | F43: 1.32 | G43: 0.33 | H43: 0.33 | I43: 0.33 | J43: 0.33 | K43: 1.33 | L43: 0.34 | M43: 0.35 | N43: 0.35 | O43: 0.35 | P43: 1.39 | Q43: 0.36 | R43: 0.37 | S43: 0.37 | T43: 0.37 | U43: 1.46 | V43: 0.38 | W43: 0.39 | X43: 0.39 | Y43: 0.39 | Z43: 1.54 | AA43: 0.4 | AB43: 0.42 | AC43: 0.42 | AD43: 0.42 | AE43: 1.62

Sheet SPG Segments
A2: Comcast Corporation | Segments
A3: NASDAQGS:CMCSA (MI KEY: 4057180; SPCIQ KEY: 173341)
A5: Visible Alpha
A7: Period Type : Fiscal Quarter, Fiscal Halves, Fiscal Year
A8: Period Start : 2025
A9: Period End : 2030
A10: Currency : Reported
A11: Consensus View : Mean
A12: As Of: 10/20/2026
A14: All numbers in $M unless otherwise indicated | B14: FQ1 2025A | C14: FQ2 2025A | D14: FQ3 2025A | E14: FQ4 2025A | F14: FY2025A | G14: FQ1 2026A | H14: FQ2 2026A | I14: FQ3 2026E | J14: FQ4 2026E | K14: FY2026E | L14: FQ1 2027E | M14: FQ2 2027E | N14: FQ3 2027E | O14: FQ4 2027E | P14: FY2027E | Q14: FQ1 2028E | R14: FQ2 2028E | S14: FQ3 2028E | T14: FQ4 2028E | U14: FY2028E | V14: FQ1 2029E | W14: FQ2 2029E | X14: FQ3 2029E | Y14: FQ4 2029E | Z14: FY2029E | AA14: FQ1 2030E | AB14: FQ2 2030E | AC14: FQ3 2030E | AD14: FQ4 2030E | AE14: FY2030E
A15: Number of Contributors Available | B15: 22 | C15: 21 | D15: 21 | E15: 20 | F15: 21 | G15: 21 | H15: 20 | I15: 20 of 20 | J15: 20 of 20 | K15: 20 of 20 | L15: 12 of 20 | M15: 12 of 20 | N15: 11 of 20 | O15: 11 of 20 | P15: 20 of 20 | Q15: 8 of 20 | R15: 8 of 20 | S15: 8 of 20 | T15: 8 of 20 | U15: 19 of 20 | V15: 7 of 20 | W15: 7 of 20 | X15: 7 of 20 | Y15: 7 of 20 | Z15: 16 of 20 | AA15: 7 of 20 | AB15: 7 of 20 | AC15: 7 of 20 | AD15: 7 of 20 | AE15: 16 of 20
A16: Revenue
A17: Total connectivity and platforms revenue | B17: 20161 | C17: 20414 | D17: 20212 | E17: 20282 | F17: 81069 | G17: 19962 | H17: 19795 | I17: 19677.91 | J17: 19893.98 | K17: 79329.57 | L17: 19611.38 | M17: 19489.81 | N17: 19338 | O17: 19534.55 | P17: 78171.99 | Q17: 19508.57 | R17: 19392.88 | S17: 19311.31 | T17: 19564.47 | U17: 77831.83 | V17: 19474.87 | W17: 19370.9 | X17: 19255.8 | Y17: 19480.69 | Z17: 77326.17 | AA17: 19502.4 | AB17: 19416.88 | AC17: 19329.09 | AD17: 19604.16 | AE17: 77398.34
A18: Total content and experiences revenue | B18: 8546 | C18: 8728 | D18: 9897 | E18: 10941 | F18: 38114 | G18: 11941 | H18: 10728 | I18: 10519.29 | J18: 11188.49 | K18: 44372.14 | L18: 10500.26 | M18: 10471.82 | N18: 10540.21 | O18: 11446.38 | P18: 43316.08 | Q18: 10879.31 | R18: 10821.01 | S18: 12674.61 | T18: 11823.91 | U18: 46512.26 | V18: 11200.91 | W18: 11037.75 | X18: 11171.84 | Y18: 12042.92 | Z18: 46069.93 | AA18: 12826.75 | AB18: 11486.95 | AC18: 11564.81 | AD18: 12386.32 | AE18: 49005.92
A19: Corporate and other | B19: 390 | C19: 322 | D19: 315 | E19: 379 | F19: 1406 | G19: 424 | H19: 368 | I19: 331.91 | J19: 371.72 | K19: 1598.54 | L19: 404.79 | M19: 365.8 | N19: 331.89 | O19: 374.11 | P19: 1481.95 | Q19: 391.06 | R19: 349.95 | S19: 312.28 | T19: 359.35 | U19: 1480.75 | V19: 386.99 | W19: 347.44 | X19: 311.54 | Y19: 357.71 | Z19: 1481.27 | AA19: 387.97 | AB19: 347.68 | AC19: 311.09 | AD19: 358.33 | AE19: 1488.61
A20: Eliminations | B20: -1231 | C20: -1217 | D20: -1273 | E20: -1315 | F20: -5036 | G20: -1435 | H20: -1324 | I20: -1306.51 | J20: -1348.61 | K20: -5417.1 | L20: -1366.65 | M20: -1330.36 | N20: -1319.45 | O20: -1352.74 | P20: -5343.01 | Q20: -1343.16 | R20: -1307.14 | S20: -1365.85 | T20: -1342.81 | U20: -5447.51 | V20: -1357.6 | W20: -1314.19 | X20: -1314.71 | Y20: -1355.16 | Z20: -5469.96 | AA20: -1406.01 | AB20: -1329.72 | AC20: -1331.72 | AD20: -1373.95 | AE20: -5616.33
A21: Corporate, other and eliminations | B21: -841 | C21: -895 | D21: -958 | E21: -936 | F21: -3630 | G21: -1011 | H21: -956 | I21: -976.59 | J21: -974.37 | K21: -3828.49 | L21: -966.33 | M21: -963.79 | N21: -988.44 | O21: -974.75 | P21: -3885.57 | Q21: -959.47 | R21: -957.05 | S21: -1046.53 | T21: -977.53 | U21: -3990.43 | V21: -976.38 | W21: -965.22 | X21: -1002.32 | Y21: -988.67 | Z21: -3982.79 | AA21: -1017.03 | AB21: -978.32 | AC21: -1017.3 | AD21: -1004.25 | AE21: -4112.56
A22: Revenue | B22: 27865 | C22: 28249 | D22: 29151 | E22: 30287 | F22: 115552 | G22: 30892 | H22: 29568 | I22: 29229.46 | J22: 30096.76 | K22: 119902.79 | L22: 29232.16 | M22: 29071.52 | N22: 28889.77 | O22: 30006.17 | P22: 117534.94 | Q22: 29428.42 | R22: 29256.84 | S22: 30939.39 | T22: 30410.85 | U22: 120340.38 | V22: 29699.41 | W22: 29443.43 | X22: 29425.33 | Y22: 30534.94 | Z22: 119319.01 | AA22: 31312.12 | AB22: 29925.52 | AC22: 29876.6 | AD22: 30986.23 | AE22: 122294.14
A24: Costs and expenses excl. D&A
A25: Total connectivity and platforms - Costs and Exps excl. D&A | B25: 11896 | C25: 11964 | D25: 12274 | E25: 12846 | F25: 48980 | G25: 12053 | H25: 11830 | I25: 12098.09 | J25: 12651.19 | K25: 48632.23 | L25: 11864.01 | M25: 11626.76 | N25: 11819.52 | O25: 12310.38 | P25: 47811 | Q25: 11768.39 | R25: 11579.72 | S25: 11842.3 | T25: 12402.32 | U25: 47407.11 | V25: 11719.49 | W25: 11542.93 | X25: 11810.46 | Y25: 12387.55 | Z25: 47028.68 | AA25: 11739.86 | AB25: 11573.57 | AC25: 11857.3 | AD25: 12445.9 | AE25: 46862.37
A26: Total content and experiences - Costs and exps excl. D&A | B26: 7932 | C26: 7490 | D26: 8507 | E26: 10666 | F26: 34593 | G26: 11609 | H26: 9399 | I26: 8877.66 | J26: 10565.15 | K26: 40450.41 | L26: 9874.52 | M26: 9133.67 | N26: 8861.75 | O26: 10625.75 | P26: 38781.15 | Q26: 10069.33 | R26: 9362.23 | S26: 10765.86 | T26: 10830.34 | U26: 41330.47 | V26: 10331.74 | W26: 9490.14 | X26: 9144.92 | Y26: 10857.68 | Z26: 40533.77 | AA26: 11810.76 | AB26: 9775.61 | AC26: 9383.61 | AD26: 11028.08 | AE26: 42789.96
A27: Corporate and other - Costs and exps excl. D&A | B27: 585 | C27: 609 | D27: 587 | E27: 793 | F27: 2574 | G27: 669 | H27: 742 | I27: 632.23 | J27: 731.66 | K27: 2960.92 | L27: 666.15 | M27: 712.81 | N27: 612.89 | O27: 749.49 | P27: 2721.19 | Q27: 657.26 | R27: 744.3 | S27: 624.76 | T27: 763.27 | U27: 2778.89 | V27: 661.32 | W27: 757.32 | X27: 638.55 | Y27: 767.36 | Z27: 2812.79 | AA27: 666.79 | AB27: 767.45 | AC27: 641.99 | AD27: 775.31 | AE27: 2858.12
A28: Eliminations - Costs and exps excl. D&A | B28: -1244 | C28: -1237 | D28: -1254 | E28: -1315 | F28: -5050 | G28: -1404 | H28: -1327 | I28: -1303.22 | J28: -1361.05 | K28: -5399.48 | L28: -1390.5 | M28: -1352.2 | N28: -1331.17 | O28: -1377.56 | P28: -5401.57 | Q28: -1400.73 | R28: -1350.35 | S28: -1376.74 | T28: -1401.16 | U28: -5493.57 | V28: -1435.64 | W28: -1392.41 | X28: -1393.66 | Y28: -1461.18 | Z28: -5576.12 | AA28: -1511.44 | AB28: -1431.82 | AC28: -1434.23 | AD28: -1506.52 | AE28: -5750.7
A29: Corporate, other and eliminations excl. D&A | B29: -659 | C29: -628 | D29: -667 | E29: -522 | F29: -2476 | G29: -735 | H29: -585 | I29: -676.86 | J29: -633.74 | K29: -2462.76 | L29: -728.93 | M29: -647.71 | N29: -721.9 | O29: -635.31 | P29: -2698.7 | Q29: -746.97 | R29: -626.04 | S29: -751.03 | T29: -647.52 | U29: -2731.55 | V29: -770.99 | W29: -652.82 | X29: -753.15 | Y29: -691.86 | Z29: -2777.02 | AA29: -823.74 | AB29: -674.78 | AC29: -780.99 | AD29: -719.91 | AE29: -2893.35
A30: Total cost and exp. excl. D&A | B30: 19170 | C30: 18826 | D30: 20113 | E30: 22989 | F30: 81098 | G30: 22925 | H30: 20645 | I30: 20349.17 | J30: 22678.22 | K30: 86776.23 | L30: 21231.38 | M30: 20184.31 | N30: 19962.22 | O30: 22332.76 | P30: 84173.96 | Q30: 21319.98 | R30: 20268.68 | S30: 21817.52 | T30: 22662.51 | U30: 86309.48 | V30: 21551.81 | W30: 20322.91 | X30: 20206.81 | Y30: 22686.03 | Z30: 85081.04 | AA30: 22962.76 | AB30: 20655.1 | AC30: 20498.39 | AD30: 22887.16 | AE30: 87294.06
A32: Adjusted EBITDA
A33: Total connectivity and platforms - Adjusted EBITDA | B33: 8264 | C33: 8450 | D33: 7938 | E33: 7437 | F33: 32089 | G33: 7910 | H33: 7964 | I33: 7568.55 | J33: 7256.55 | K33: 30699.78 | L33: 7740.79 | M33: 7846.8 | N33: 7518.48 | O33: 7224.17 | P33: 30358.14 | Q33: 7740.18 | R33: 7813.16 | S33: 7469.01 | T33: 7162.15 | U33: 30414.22 | V33: 7755.39 | W33: 7827.97 | X33: 7445.35 | Y33: 7093.15 | Z33: 30297.5 | AA33: 7762.54 | AB33: 7843.31 | AC33: 7471.8 | AD33: 7158.26 | AE33: 30535.97
A34: Total Content and experiences - Adjusted EBITDA | B34: 614 | C34: 1241 | D34: 1392 | E34: 275 | F34: 3521 | G34: 331 | H34: 1329 | I34: 1609.76 | J34: 581.84 | K34: 3848.34 | L34: 566.37 | M34: 1339.86 | N34: 1661.17 | O34: 796 | P34: 4357.17 | Q34: 721.96 | R34: 1475.83 | S34: 1931.16 | T34: 946.86 | U34: 5038.68 | V34: 763.26 | W34: 1561.51 | X34: 1989.69 | Y34: 1089.93 | Z34: 5365.75 | AA34: 845.54 | AB34: 1697.39 | AC34: 2109.68 | AD34: 1241.02 | AE34: 5903.78
A35: Corporate and other - Adjusted EBITDA | B35: -195 | C35: -287 | D35: -272 | E35: -414 | F35: -1168 | G35: -244 | H35: -374 | I35: -296.47 | J35: -400.62 | K35: -1322.21 | L35: -255 | M35: -354.72 | N35: -278.48 | O35: -384.22 | P35: -1252.78 | Q35: -261.79 | R35: -374.53 | S35: -299.82 | T35: -392 | U35: -1300.59 | V35: -268.97 | W35: -382.52 | X35: -307.28 | Y35: -396.14 | Z35: -1341.9 | AA35: -272.6 | AB35: -389.66 | AC35: -311.45 | AD35: -402 | AE35: -1374.76
A36: Eliminations - Adjusted EBITDA | B36: 13 | C36: 21 | D36: -19 | E36: - | F36: 13 | G36: -31 | H36: 3 | I36: -16.89 | J36: -57.88 | K36: -58.93 | L36: -14.02 | M36: 3.53 | N36: -18.57 | O36: -7.2 | P36: -50.4 | Q36: -10.47 | R36: 5.05 | S36: -20.11 | T36: - | U36: -70.88 | V36: -6.37 | W36: 5.5 | X36: -20.35 | Y36: - | Z36: -74.9 | AA36: -6.84 | AB36: 5.54 | AC36: -20.66 | AD36: - | AE36: -76.85
A37: Corporate, other and eliminations - adjusted EBITDA | B37: -181 | C37: -267 | D37: -291 | E37: -414 | F37: -1154 | G37: -276 | H37: -371 | I37: -310.35 | J37: -409.08 | K37: -1371.9 | L37: -271.94 | M37: -350.1 | N37: -298.89 | O37: -377.52 | P37: -1302.61 | Q37: -274.23 | R37: -374.09 | S37: -320.7 | T37: -393.37 | U37: -1374.92 | V37: -279.45 | W37: -383.56 | X37: -329.36 | Y37: -399.43 | Z37: -1400.04 | AA37: -284.67 | AB37: -392.04 | AC37: -335.2 | AD37: -406.84 | AE37: -1440.51
A38: Adjusted EBITDA | B38: 8695 | C38: 9423 | D38: 9038 | E38: 7298 | F38: 34454 | G38: 7967 | H38: 8923 | I38: 8867.61 | J38: 7422.42 | K38: 33164.19 | L38: 8035.64 | M38: 8864.77 | N38: 8868.47 | O38: 7609 | P38: 33333.85 | Q38: 8122.09 | R38: 8914.82 | S38: 9026.42 | T38: 7659.09 | U38: 33967.78 | V38: 8158.34 | W38: 8989.6 | X38: 9054.84 | Y38: 7733.29 | Z38: 34127.15 | AA38: 8241.84 | AB38: 9099.61 | AC38: 9198.46 | AD38: 7956.13 | AE38: 34809.51
A40: Supplemental
A41: NBCUniversal Adjusted EBITDA | B41: 628.81 | C41: 911.72 | D41: 1012.32 | E41: 387.26 | F41: 3810.48 | G41: 713.01 | H41: 1192.39 | I41: 1307.33 | J41: 664.93 | K41: 4924.82 | L41: 1764.88 | M41: 1228.21 | N41: 1440.23 | O41: 1583.61 | P41: 4402.13 | Q41: - | R41: - | S41: - | T41: - | U41: 4527.56 | V41: - | W41: - | X41: - | Y41: - | Z41: 4862.52 | AA41: - | AB41: - | AC41: - | AD41: - | AE41: 5461.25
A42: Sky Adjusted EBITDA | B42: 256.19 | C42: 210.4 | D42: 112.97 | E42: -159.98 | F42: 983.23 | G42: 195.24 | H42: 274.7 | I42: 406.48 | J42: 57.14 | K42: 1359.29 | L42: 104.31 | M42: 104.14 | N42: 116.9 | O42: 131.76 | P42: 1339.25 | Q42: - | R42: - | S42: - | T42: - | U42: 1569.47 | V42: - | W42: - | X42: - | Y42: - | Z42: 1502.12 | AA42: - | AB42: - | AC42: - | AD42: - | AE42: 1755.56
A43: Cable communications Adjusted EBITDA | B43: 7631.05 | C43: 7818.21 | D43: 7688.96 | E43: 7461.49 | F43: 30908.62 | G43: 6729 | H43: 6816.81 | I43: 6552.51 | J43: 6467.82 | K43: 29305.19 | L43: 5315.61 | M43: 5335.73 | N43: 5320.02 | O43: 4866.38 | P43: 28056.35 | Q43: - | R43: - | S43: - | T43: - | U43: 32064.63 | V43: - | W43: - | X43: - | Y43: - | Z43: 31943.14 | AA43: - | AB43: - | AC43: - | AD43: - | AE43: 32307.11
A44: Corporate and eliminations Adjusted EBITDA | B44: 173.05 | C44: 644.31 | D44: -25.27 | E44: -231.6 | F44: 91.1 | G44: 618.83 | H44: 648.61 | I44: 508.85 | J44: 262.15 | K44: 1143.84 | L44: -492.71 | M44: 764.38 | N44: 1044.67 | O44: 2152.08 | P44: 642.61 | Q44: - | R44: - | S44: 800 | T44: - | U44: -423.41 | V44: 600 | W44: - | X44: -800 | Y44: - | Z44: -708.74 | AA44: 50 | AB44: - | AC44: - | AD44: - | AE44: -577.42

Sheet SPG Free Cash Flow
A2: Comcast Corporation | Free Cash Flow
A3: NASDAQGS:CMCSA (MI KEY: 4057180; SPCIQ KEY: 173341)
A5: Visible Alpha
A7: Period Type : Fiscal Quarter, Fiscal Halves, Fiscal Year
A8: Period Start : 2025
A9: Period End : 2030
A10: Currency : Reported
A11: Consensus View : Mean
A12: As Of: 10/20/2026
A14: All numbers in $M unless otherwise indicated | B14: FQ1 2025A | C14: FQ2 2025A | D14: FQ3 2025A | E14: FQ4 2025A | F14: FY2025A | G14: FQ1 2026A | H14: FQ2 2026A | I14: FQ3 2026E | J14: FQ4 2026E | K14: FY2026E | L14: FQ1 2027E | M14: FQ2 2027E | N14: FQ3 2027E | O14: FQ4 2027E | P14: FY2027E | Q14: FQ1 2028E | R14: FQ2 2028E | S14: FQ3 2028E | T14: FQ4 2028E | U14: FY2028E | V14: FQ1 2029E | W14: FQ2 2029E | X14: FQ3 2029E | Y14: FQ4 2029E | Z14: FY2029E | AA14: FQ1 2030E | AB14: FQ2 2030E | AC14: FQ3 2030E | AD14: FQ4 2030E | AE14: FY2030E
A15: Number of Contributors Available | B15: 22 | C15: 21 | D15: 21 | E15: 20 | F15: 21 | G15: 21 | H15: 20 | I15: 20 of 20 | J15: 20 of 20 | K15: 20 of 20 | L15: 12 of 20 | M15: 12 of 20 | N15: 11 of 20 | O15: 11 of 20 | P15: 20 of 20 | Q15: 8 of 20 | R15: 8 of 20 | S15: 8 of 20 | T15: 8 of 20 | U15: 19 of 20 | V15: 7 of 20 | W15: 7 of 20 | X15: 7 of 20 | Y15: 7 of 20 | Z15: 16 of 20 | AA15: 7 of 20 | AB15: 7 of 20 | AC15: 7 of 20 | AD15: 7 of 20 | AE15: 16 of 20
A16: Net cash provided by (used in) operating activities | B16: 8294 | C16: 7815 | D16: 8693 | E16: 8841 | F16: 33643 | G16: 6891 | H16: 8092 | I16: 7001.35 | J16: 6018.83 | K16: 27655.01 | L16: 6135.92 | M16: 6783.34 | N16: 7258.61 | O16: 6465.71 | P16: 26871.55 | Q16: 6319 | R16: 6848.69 | S16: 7316.64 | T16: 6670.71 | U16: 27855.68 | V16: 6303.2 | W16: 6892.89 | X16: 7248.68 | Y16: 6770.94 | Z16: 28332.21 | AA16: 6478.25 | AB16: 7006.89 | AC16: 7405.78 | AD16: 6946.68 | AE16: 28838.83
A17: Capital expenditures | B17: 2252 | C17: 2679 | D17: 3071 | E17: 3749 | F17: 11750 | G17: 2351 | H17: 2902 | I17: 3008.63 | J17: 3414.4 | K17: 11697.53 | L17: 2533.47 | M17: 2889.47 | N17: 2944.27 | O17: 3364.73 | P17: 11716.07 | Q17: 2495.59 | R17: 2889.56 | S17: 2991.8 | T17: 3449.46 | U17: 11828.09 | V17: 2618.33 | W17: 2994.08 | X17: 3032.18 | Y17: 3488.74 | Z17: 12097.24 | AA17: 2666.01 | AB17: 2998.68 | AC17: 3048.83 | AD17: 3510.75 | AE17: 12211.56
A18: Cash paid for capitalized software and other intangibles | B18: 622 | C18: 635 | D18: 677 | E18: 724 | F18: 2658 | G18: 639 | H18: 587 | I18: 657.95 | J18: 708.22 | K18: 2597.07 | L18: 623.25 | M18: 603.68 | N18: 650.4 | O18: 686.13 | P18: 2578.62 | Q18: 641.08 | R18: 624.04 | S18: 679.9 | T18: 700.06 | U18: 2642.91 | V18: 645.72 | W18: 632.75 | X18: 670.78 | Y18: 699.48 | Z18: 2644.42 | AA18: 656.95 | AB18: 637.21 | AC18: 675.29 | AD18: 704.55 | AE18: 2683.72
A19: Capex (incl. intangible invest) | B19: -2874 | C19: -3314 | D19: -3748 | E19: -4473 | F19: -14408 | G19: -2990 | H19: -3489 | I19: -3680.37 | J19: -4139.18 | K19: -14323.15 | L19: -3086.06 | M19: -3396.92 | N19: -3594.67 | O19: -4050.86 | P19: -14340.95 | Q19: -3136.67 | R19: -3513.61 | S19: -3671.7 | T19: -4149.52 | U19: -14536.36 | V19: -3264.05 | W19: -3626.83 | X19: -3702.95 | Y19: -4188.22 | Z19: -14811.29 | AA19: -3322.95 | AB19: -3635.9 | AC19: -3724.12 | AD19: -4215.3 | AE19: -14974.17
A20: Free cash flow incl. economic stimulus | B20: 4584 | C20: 4500 | D20: 4945 | E20: 4369 | F20: 19236 | G20: 3901 | H20: 4604 | I20: 3425.71 | J20: 1974.58 | K20: 13863.87 | L20: 3171.49 | M20: 3464.99 | N20: 3783.32 | O20: 2546.54 | P20: 12922.37 | Q20: 3191.22 | R20: 3270.93 | S20: 3612.08 | T20: 2503.3 | U20: 13259.15 | V20: 3041.8 | W20: 3196.54 | X20: 3505.63 | Y20: 2557.22 | Z20: 13382.58 | AA20: 3152.04 | AB20: 3304.09 | AC20: 3638.9 | AD20: 2700.97 | AE20: 13773.22
A22: FCF calculation
A23: Adjusted EBITDA - FCF | B23: 8695 | C23: 9423 | D23: 9038 | E23: 7298 | F23: 34454 | G23: 7966 | H23: 8923 | I23: 8805.09 | J23: 7302.03 | K23: 32768.07 | L23: 7992.17 | M23: 8831.62 | N23: 8888.92 | O23: 7739.29 | P23: 32929.89 | Q23: 8156.03 | R23: 8941.32 | S23: 9141.41 | T23: 7810.4 | U23: 33573.11 | V23: 8206.17 | W23: 8978.81 | X23: 9124.69 | Y23: 7722.94 | Z23: 33736.76 | AA23: 8225.65 | AB23: 9145.88 | AC23: 9262.04 | AD23: 7891.56 | AE23: 34446.25
A24: Capital expenditures | B24: 2252 | C24: 2679 | D24: 3071 | E24: 3749 | F24: 11750 | G24: 2351 | H24: 2902 | I24: 3008.63 | J24: 3414.4 | K24: 11697.53 | L24: 2533.47 | M24: 2889.47 | N24: 2944.27 | O24: 3364.73 | P24: 11716.07 | Q24: 2495.59 | R24: 2889.56 | S24: 2991.8 | T24: 3449.46 | U24: 11828.09 | V24: 2618.33 | W24: 2994.08 | X24: 3032.18 | Y24: 3488.74 | Z24: 12097.24 | AA24: 2666.01 | AB24: 2998.68 | AC24: 3048.83 | AD24: 3510.75 | AE24: 12211.56
A25: Cash paid for capitalized software and other intangibles | B25: 622 | C25: 635 | D25: 677 | E25: 724 | F25: 2658 | G25: 639 | H25: 587 | I25: 657.95 | J25: 708.22 | K25: 2597.07 | L25: 623.25 | M25: 603.68 | N25: 650.4 | O25: 686.13 | P25: 2578.62 | Q25: 641.08 | R25: 624.04 | S25: 679.9 | T25: 700.06 | U25: 2642.91 | V25: 645.72 | W25: 632.75 | X25: 670.78 | Y25: 699.48 | Z25: 2644.42 | AA25: 656.95 | AB25: 637.21 | AC25: 675.29 | AD25: 704.55 | AE25: 2683.72
A26: Capex (incl. intangible invest) | B26: -2874 | C26: -3314 | D26: -3748 | E26: -4473 | F26: -14408 | G26: -2990 | H26: -3489 | I26: -3680.37 | J26: -4139.18 | K26: -14323.15 | L26: -3086.06 | M26: -3396.92 | N26: -3594.67 | O26: -4050.86 | P26: -14340.95 | Q26: -3136.67 | R26: -3513.61 | S26: -3671.7 | T26: -4149.52 | U26: -14536.36 | V26: -3264.05 | W26: -3626.83 | X26: -3702.95 | Y26: -4188.22 | Z26: -14811.29 | AA26: -3322.95 | AB26: -3635.9 | AC26: -3724.12 | AD26: -4215.3 | AE26: -14974.17
A27: Cash interest expense - FCF | B27: 674 | C27: 1129 | D27: 879 | E27: 1189 | F27: 3871 | G27: 727 | H27: 1053.12 | I27: 831.23 | J27: 1006.94 | K27: 3702.01 | L27: 854.8 | M27: 947.23 | N27: 873.34 | O27: 980.33 | P27: 3565.15 | Q27: 734.51 | R27: 922.92 | S27: 769.83 | T27: 988.57 | U27: 3402.04 | V27: 731.77 | W27: 919.2 | X27: 763.98 | Y27: 976.66 | Z27: 3295.66 | AA27: 723.81 | AB27: 909.51 | AC27: 756.22 | AD27: 969.64 | AE27: 3213.7
A28: Cash taxes - FCF | B28: 400 | C28: 1685 | D28: 293 | E28: -1623 | F28: 755 | G28: 249 | H28: 515.67 | I28: 1039.49 | J28: 815 | K28: 2573.34 | L28: 646.66 | M28: 903.2 | N28: 1013.21 | O28: 745.16 | P28: 3101.97 | Q28: 601.2 | R28: 889 | S28: 1126.55 | T28: 730.64 | U28: 3226.81 | V28: 602.61 | W28: 888.08 | X28: 1132.4 | Y28: 677.66 | Z28: 3044.39 | AA28: 603.66 | AB28: 906.57 | AC28: 1146.79 | AD28: 602.36 | AE28: 3377.08
A29: Change in operating assets and liabilities - FCF | B29: 636 | C29: -22 | D29: 169 | E29: -232 | F29: 551 | G29: 555 | H29: -157 | I29: 498.39 | J29: 68.49 | K29: 574.48 | L29: 986.67 | M29: 697.17 | N29: -152.32 | O29: -281.01 | P29: 1151.22 | Q29: 1434.72 | R29: 962.82 | S29: -147.47 | T29: -630.57 | U29: 948.86 | V29: 1425.97 | W29: 930.91 | X29: 185.56 | Y29: -686.49 | Z29: 1148.66 | AA29: 1221.03 | AB29: 1019.9 | AC29: 134.08 | AD29: -591.09 | AE29: 1117.95
A30: Noncash share based compensation - FCF | B30: -382 | C30: -321 | D30: -311 | E30: -274 | F30: -1288 | G30: -427 | H30: -359 | I30: -328.47 | J30: -312.4 | K30: -1474.31 | L30: -381.69 | M30: -354.47 | N30: -339.22 | O30: -327.92 | P30: -1463.01 | Q30: -394.05 | R30: -343.17 | S30: -320.79 | T30: -293.19 | U30: -1491.64 | V30: -400.42 | W30: -348.26 | X30: -320.26 | Y30: -298.19 | Z30: -1497.29 | AA30: -411.53 | AB30: -354.64 | AC30: -326.33 | AD30: -303.55 | AE30: -1519.22
A31: Other adjustment - FCF | B31: -90 | C31: -3 | D31: -54 | E31: -2 | F31: -149 | G31: 55.22 | H31: -232.45 | I31: -25.26 | J31: -156.21 | K31: -309.62 | L31: -101.75 | M31: -97.73 | N31: -120.78 | O31: -101.12 | P31: -389.18 | Q31: - | R31: - | S31: - | T31: - | U31: -360.3 | V31: - | W31: - | X31: - | Y31: - | Z31: -411.25 | AA31: - | AB31: - | AC31: - | AD31: - | AE31: -412
A32: Adjustment - FCF | B32: -419.5 | C32: -859.5 | D32: -657.5 | E32: -402.33 | F32: -1693.33 | G32: 18.5 | H32: -319 | I32: - | J32: - | K32: -141 | L32: - | M32: - | N32: - | O32: - | P32: - | Q32: - | R32: - | S32: - | T32: - | U32: - | V32: - | W32: - | X32: - | Y32: - | Z32: - | AA32: - | AB32: - | AC32: - | AD32: - | AE32: -
A33: Free cash flow incl. economic stimulus | B33: 4584 | C33: 4500 | D33: 4945 | E33: 4369 | F33: 19236 | G33: 3901 | H33: 4604 | I33: 3425.71 | J33: 1974.58 | K33: 13863.87 | L33: 3171.49 | M33: 3464.99 | N33: 3783.32 | O33: 2546.54 | P33: 12922.37 | Q33: 3191.22 | R33: 3270.93 | S33: 3612.08 | T33: 2503.3 | U33: 13259.15 | V33: 3041.8 | W33: 3196.54 | X33: 3505.63 | Y33: 2557.22 | Z33: 13382.58 | AA33: 3152.04 | AB33: 3304.09 | AC33: 3638.9 | AD33: 2700.97 | AE33: 13773.22

Sheet SPG Conn & Platforms
A2: Comcast Corporation | Connectivity and Platforms
A3: NASDAQGS:CMCSA (MI KEY: 4057180; SPCIQ KEY: 173341)
A5: Visible Alpha
A7: Period Type : Fiscal Quarter, Fiscal Halves, Fiscal Year
A8: Period Start : 2025
A9: Period End : 2030
A10: Currency : Reported
A11: Consensus View : Mean
A12: As Of: 10/20/2026
A14: All numbers in $M unless otherwise indicated | B14: FQ1 2025A | C14: FQ2 2025A | D14: FQ3 2025A | E14: FQ4 2025A | F14: FY2025A | G14: FQ1 2026A | H14: FQ2 2026A | I14: FQ3 2026E | J14: FQ4 2026E | K14: FY2026E | L14: FQ1 2027E | M14: FQ2 2027E | N14: FQ3 2027E | O14: FQ4 2027E | P14: FY2027E | Q14: FQ1 2028E | R14: FQ2 2028E | S14: FQ3 2028E | T14: FQ4 2028E | U14: FY2028E | V14: FQ1 2029E | W14: FQ2 2029E | X14: FQ3 2029E | Y14: FQ4 2029E | Z14: FY2029E | AA14: FQ1 2030E | AB14: FQ2 2030E | AC14: FQ3 2030E | AD14: FQ4 2030E | AE14: FY2030E
A15: Number of Contributors Available | B15: 22 | C15: 21 | D15: 21 | E15: 20 | F15: 21 | G15: 21 | H15: 20 | I15: 20 of 20 | J15: 20 of 20 | K15: 20 of 20 | L15: 12 of 20 | M15: 12 of 20 | N15: 11 of 20 | O15: 11 of 20 | P15: 20 of 20 | Q15: 8 of 20 | R15: 8 of 20 | S15: 8 of 20 | T15: 8 of 20 | U15: 19 of 20 | V15: 7 of 20 | W15: 7 of 20 | X15: 7 of 20 | Y15: 7 of 20 | Z15: 16 of 20 | AA15: 7 of 20 | AB15: 7 of 20 | AC15: 7 of 20 | AD15: 7 of 20 | AE15: 16 of 20
A16: Domestic broadband residential customers
A17: Domestic broadband residential customers(K#) | B17: 29190 | C17: 28989 | D17: 28897 | E17: 28719 | F17: 28719 | G17: 28654 | H17: 28486 | I17: 28350.5 | J17: 28182.12 | K17: 28182.18 | L17: 28072.16 | M17: 27913.09 | N17: 27808.48 | O17: 27672.93 | P17: 27673.11 | Q17: 27617.89 | R17: 27466.44 | S17: 27384.01 | T17: 27259.07 | U17: 27169.88 | V17: 27288.94 | W17: 27166.39 | X17: 27116.23 | Y17: 27022.81 | Z17: 26785.05 | AA17: 26939.22 | AB17: 26818.32 | AC17: 26777.62 | AD17: 26689.54 | AE17: 26385.42
A18: Avg domestic broadband residential customers(K#) | B18: 29281.5 | C18: 29089.5 | D18: 28943 | E18: 28808 | F18: 29046 | G18: 28686.5 | H18: 28570 | I18: 28418.29 | J18: 28266.31 | K18: 28461.72 | L18: 28126.9 | M18: 27992.62 | N18: 27860.79 | O18: 27740.7 | P18: 27932.57 | Q18: 27663.14 | R18: 27542.16 | S18: 27425.22 | T18: 27321.54 | U18: 27424.53 | V18: 27327.8 | W18: 27227.66 | X18: 27141.31 | Y18: 27069.52 | Z18: 27006.17 | AA18: 26981.01 | AB18: 26878.77 | AC18: 26797.97 | AD18: 26733.58 | AE18: 26586.97
A19: Average monthly domestic broadband residential revenue per subscriber($) | B19: 76.03 | C19: 76.19 | D19: 75.44 | E19: 74.17 | F19: 75.42 | G19: 73.65 | H19: 73.27 | I19: 72.96 | J19: 72.79 | K19: 73.22 | L19: 73.38 | M19: 73.37 | N19: 73.24 | O19: 73.13 | P19: 73.14 | Q19: 74.02 | R19: 74.09 | S19: 73.93 | T19: 73.77 | U19: 73.47 | V19: 75.11 | W19: 75.26 | X19: 75.07 | Y19: 74.88 | Z19: 74.1 | AA19: 76.17 | AB19: 76.38 | AC19: 76.18 | AD19: 75.99 | AE19: 74.78
A20: Domestic broadband revenue | B20: 6679 | C20: 6649 | D20: 6550 | E20: 6410 | F20: 26288 | G20: 6338 | H20: 6280 | I20: 6221.77 | J20: 6167.32 | K20: 25007.2 | L20: 6197.42 | M20: 6164.08 | N20: 6120.45 | O20: 6084.53 | P20: 24560.83 | Q20: 6143.04 | R20: 6122.2 | S20: 6083.01 | T20: 6046.37 | U20: 24300.69 | V20: 6158.06 | W20: 6148.2 | X20: 6112.78 | Y20: 6081.47 | Z20: 24178.19 | AA20: 6166.36 | AB20: 6161.65 | AC20: 6126.33 | AD20: 6097.19 | AE20: 24076.69
A22: Domestic wireless customers
A23: Total domestic wireless lines(K#) | B23: 8148 | C23: 8527 | D23: 8941 | E23: 9305 | F23: 9305 | G23: 9739 | H23: 10187 | I23: 10586.4 | J23: 10972.44 | K23: 10972.49 | L23: 11352.17 | M23: 11741.5 | N23: 12118.03 | O23: 12480.89 | P23: 12490.77 | Q23: 12823.06 | R23: 13200.51 | S23: 13557.76 | T23: 13898.8 | U23: 13860.48 | V23: 14235.31 | W23: 14601.13 | X23: 14942.62 | Y23: 15274.73 | Z23: 15130.43 | AA23: 15593.72 | AB23: 15951.35 | AC23: 16288.43 | AD23: 16614.15 | AE23: 16324.41
A24: Avg total domestic wireless lines(K#) | B24: 7987 | C24: 8337.5 | D24: 8733.5 | E24: 9123 | F24: 8565.5 | G24: 9522 | H24: 9963 | I24: 10386.31 | J24: 10777.86 | K24: 10144.86 | L24: 11161.24 | M24: 11546.84 | N24: 11929.77 | O24: 12299.46 | P24: 11733.84 | Q24: 12646.02 | R24: 13011.78 | S24: 13379.13 | T24: 13728.28 | U24: 13171.84 | V24: 14070.04 | W24: 14418.22 | X24: 14771.88 | Y24: 15108.68 | Z24: 14497.69 | AA24: 15434.23 | AB24: 15772.54 | AC24: 16119.89 | AD24: 16451.29 | AE24: 15729.52
A25: Average monthly total domestic wireless revenue per subscriber($) | B25: 46.87 | C25: 47.78 | D25: 47.56 | E25: 51.26 | F25: 48.32 | G25: 48.83 | H25: 47.21 | I25: 46.51 | J25: 49.6 | K25: 48.12 | L25: 47.14 | M25: 46.42 | N25: 45.7 | O25: 48.47 | P25: 47.21 | Q25: 47.16 | R25: 46.49 | S25: 45.86 | T25: 48.49 | U25: 46.76 | V25: 47.06 | W25: 46.3 | X25: 45.96 | Y25: 48.51 | Z25: 46.71 | AA25: 47.38 | AB25: 46.53 | AC25: 46.22 | AD25: 48.65 | AE25: 46.87
A26: Domestic wireless revenue | B26: 1123 | C26: 1195 | D26: 1246 | E26: 1403 | F26: 4967 | G26: 1395 | H26: 1411 | I26: 1450.07 | J26: 1606.28 | K26: 5861.71 | L26: 1579.24 | M26: 1606.7 | N26: 1635.53 | O26: 1788.53 | P26: 6647.92 | Q26: 1789.19 | R26: 1814.69 | S26: 1840.72 | T26: 1997.6 | U26: 7387.21 | V26: 1987.02 | W26: 2003.07 | X26: 2037.68 | Y26: 2199.91 | Z26: 8130.32 | AA26: 2194.91 | AB26: 2202.83 | AC26: 2236.92 | AD26: 2403.21 | AE26: 8856.12
A28: International residential connectivity customer relationships
A29: International residential connectivity & platforms customer relationships(K#) | B29: 17674 | C29: 17573 | D29: 17477 | E29: 17499 | F29: 17499 | G29: 17603 | H29: 17539 | I29: 17485.47 | J29: 17507.69 | K29: 17505.89 | L29: 17553.54 | M29: 17506.92 | N29: 17467.62 | O29: 17485.98 | P29: 17483.63 | Q29: 17566.02 | R29: 17529.27 | S29: 17491.85 | T29: 17513.48 | U29: 17473.44 | V29: 17525.64 | W29: 17479.43 | X29: 17431.6 | Y29: 17452.07 | Z29: 17432.49 | AA29: 17504.57 | AB29: 17458.73 | AC29: 17411.72 | AD29: 17432.51 | AE29: 17417.99
A30: Avg international residential connectivity & platforms customer relationships(K#) | B30: 17680 | C30: 17623.5 | D30: 17525 | E30: 17488 | F30: 17592.5 | G30: 17551 | H30: 17571 | I30: 17512.23 | J30: 17496.58 | K30: 17515.48 | L30: 17535.94 | M30: 17530.23 | N30: 17487.27 | O30: 17476.8 | P30: 17497.94 | Q30: 17541 | R30: 17547.65 | S30: 17510.56 | T30: 17502.67 | U30: 17482.4 | V30: 17499.88 | W30: 17502.53 | X30: 17455.51 | Y30: 17441.83 | Z30: 17444.27 | AA30: 17478.32 | AB30: 17481.65 | AC30: 17435.22 | AD30: 17422.12 | AE30: 17427.92
A31: Average monthly international residential customer relationship revenue per customer($) | B31: 21.34 | C31: 23.06 | D31: 24.25 | E31: 25.48 | F31: 23.51 | G31: 23.55 | H31: 23.64 | I31: 24.82 | J31: 26.14 | K31: 24.53 | L31: 24.29 | M31: 24.69 | N31: 25.93 | O31: 27.37 | P31: 25.53 | Q31: 24.76 | R31: 25.12 | S31: 26.5 | T31: 27.9 | U31: 26.08 | V31: 25.39 | W31: 25.79 | X31: 27.15 | Y31: 28.57 | Z31: 26.78 | AA31: 26.06 | AB31: 26.47 | AC31: 27.87 | AD31: 29.33 | AE31: 27.51
A32: International connectivity revenue | B32: 1132 | C32: 1219 | D32: 1275 | E32: 1337 | F32: 4963 | G32: 1240 | H32: 1246 | I32: 1307.89 | J32: 1375.54 | K32: 5169.43 | L32: 1284.12 | M32: 1297.36 | N32: 1364.57 | O32: 1439.77 | P32: 5363.82 | Q32: 1313.69 | R32: 1323.98 | S32: 1398.05 | T32: 1471.61 | U32: 5479.77 | V32: 1345.21 | W32: 1355.86 | X32: 1428.83 | Y32: 1502.49 | Z32: 5619.41 | AA32: 1378.87 | AB32: 1390.26 | AC32: 1465.08 | AD32: 1540.67 | AE32: 5767.35
A34: Business services connectivity customer relationships
A35: Business services connectivity customer relationships(K#) | B35: 2613 | C35: 2713 | D35: 2702 | E35: 2702 | F35: 2702 | G35: 2685.26 | H35: 2687.57 | I35: 2680.75 | J35: 2669.38 | K35: 2669.38 | L35: 2681.99 | M35: 2680.71 | N35: 2672.66 | O35: 2669.36 | P35: 2661.24 | Q35: 2664.08 | R35: 2663.35 | S35: 2653.85 | T35: 2650.08 | U35: 2642.91 | V35: 2655.24 | W35: 2655.26 | X35: 2646.78 | Y35: 2643.75 | Z35: 2631.4 | AA35: 2649.32 | AB35: 2649.92 | AC35: 2642.32 | AD35: 2639.92 | AE35: 2621.06
A36: Avg business services connectivity customer relationships(K#) | B36: 2619.5 | C36: 2663 | D36: 2707.5 | E36: 2702 | F36: 2664 | G36: 2686.98 | H36: 2688.81 | I36: 2682.6 | J36: 2674.88 | K36: 2675.34 | L36: 2680.58 | M36: 2678.51 | N36: 2673.9 | O36: 2671.22 | P36: 2665.13 | Q36: 2662.34 | R36: 2660.62 | S36: 2655.51 | T36: 2652.78 | U36: 2649.38 | V36: 2653.7 | W36: 2652.6 | X36: 2648.33 | Y36: 2646.43 | Z36: 2637.16 | AA36: 2647.89 | AB36: 2647.26 | AC36: 2643.69 | AD36: 2642.51 | AE36: 2626.23
A37: Average monthly business services connectivity revenue per cust relationship($) | B37: 317.62 | C37: 322.32 | D37: 317.14 | E37: 319.52 | F37: 320.23 | G37: 327.49 | H37: 331.47 | I37: 330.19 | J37: 332.14 | K37: 330.94 | L37: 340.27 | M37: 344.59 | N37: 343.77 | O37: 343.9 | P37: 341.87 | Q37: 355.1 | R37: 359.61 | S37: 356.62 | T37: 355.29 | U37: 353.1 | V37: 370.03 | W37: 374.62 | X37: 370.36 | Y37: 368.52 | Z37: 364.97 | AA37: 385.13 | AB37: 389.81 | AC37: 384.25 | AD37: 381.88 | AE37: 376.99
A38: Business services connectivity revenue | B38: 2495.5 | C38: 2575 | D38: 2576 | E38: 2590 | F38: 10237 | G38: 2640 | H38: 2671 | I38: 2650.53 | J38: 2662.95 | K38: 10624.37 | L38: 2723.3 | M38: 2752.07 | N38: 2741.73 | O38: 2755.18 | P38: 10925.54 | Q38: 2815.68 | R38: 2849.16 | S38: 2821.24 | T38: 2830.95 | U38: 11242.7 | V38: 2908.96 | W38: 2943.46 | X38: 2909.77 | Y38: 2917.86 | Z38: 11586.78 | AA38: 3003.03 | AB38: 3038.57 | AC38: 3000.28 | AD38: 3007.2 | AE38: 11913.58
A40: Total domestic broadband customers
A41: Total domestic broadband customers(K#) | B41: 29190 | C41: 28989 | D41: 28897 | E41: 31255 | F41: 31255 | G41: 30472.76 | H41: 30479.01 | I41: 30345.96 | J41: 30189.27 | K41: 30189.1 | L41: 30120.74 | M41: 29978.71 | N41: 29903.28 | O41: 29818.95 | P41: 29705.03 | Q41: 30347.57 | R41: 30229.35 | S41: 30212.03 | T41: 30170.69 | U41: 29220.81 | V41: 30133.03 | W41: 30038.83 | X41: 30056.8 | Y41: 30039.84 | Z41: 28867.52 | AA41: 30014.78 | AB41: 29934.74 | AC41: 29984.98 | AD41: 29990.7 | AE41: 28564.14
A42: Avg total domestic broadband customers(K#) | B42: 31742.5 | C42: 29089.5 | D42: 28943 | E42: 31345 | F42: 31548.5 | G42: 30633.29 | H42: 30566.87 | I42: 30412.53 | J42: 30267.61 | K42: 30589.15 | L42: 30174.61 | M42: 30049.73 | N42: 29941 | O42: 29861.12 | P42: 29928.07 | Q42: 30374.14 | R42: 30288.46 | S42: 30220.69 | T42: 30191.36 | U42: 29421.88 | V42: 30151.86 | W42: 30085.93 | X42: 30047.82 | Y42: 30048.32 | Z42: 29044.16 | AA42: 30027.31 | AB42: 29974.76 | AC42: 29959.86 | AD42: 29987.84 | AE42: 28715.83
A43: Average monthly domestic broadband revenue per customer($) | B43: 70.14 | C43: 70.16 | D43: 69.34 | E43: 68.17 | F43: 69.44 | G43: 67.68 | H43: 68.62 | I43: 68.35 | J43: 68.21 | K43: 68.27 | L43: 68.92 | M43: 68.76 | N43: 68.62 | O43: 68.62 | P43: 68.79 | Q43: 67.9 | R43: 67.8 | S43: 67.61 | T43: 67.47 | U43: 69.61 | V43: 68.63 | W43: 68.68 | X43: 68.47 | Y43: 68.34 | Z43: 70.56 | AA43: 69.58 | AB43: 69.77 | AC43: 69.55 | AD43: 69.43 | AE43: 71.62
A44: Domestic broadband revenue | B44: 6679 | C44: 6649 | D44: 6550 | E44: 6410 | F44: 26288 | G44: 6338 | H44: 6280 | I44: 6221.77 | J44: 6167.32 | K44: 25007.2 | L44: 6197.42 | M44: 6164.08 | N44: 6120.45 | O44: 6084.53 | P44: 24560.83 | Q44: 6143.04 | R44: 6122.2 | S44: 6083.01 | T44: 6046.37 | U44: 24300.69 | V44: 6158.06 | W44: 6148.2 | X44: 6112.78 | Y44: 6081.47 | Z44: 24178.19 | AA44: 6166.36 | AB44: 6161.65 | AC44: 6126.33 | AD44: 6097.19 | AE44: 24076.69
A46: Connectivity & platforms revenue
A47: Residential connectivity and platforms revenue | B47: 17665 | C47: 17839 | D47: 17636 | E47: 17692 | F47: 70832 | G47: 17323 | H47: 17124 | I47: 17027.39 | J47: 17231.02 | K47: 68705.46 | L47: 16888.08 | M47: 16737.75 | N47: 16596.26 | O47: 16779.37 | P47: 67246.49 | Q47: 16692.89 | R47: 16543.72 | S47: 16490.07 | T47: 16733.52 | U47: 66589.14 | V47: 16565.92 | W47: 16427.44 | X47: 16346.04 | Y47: 16562.84 | Z47: 65739.39 | AA47: 16499.37 | AB47: 16378.31 | AC47: 16328.82 | AD47: 16596.95 | AE47: 65484.73
A48: Business services connectivity revenue | B48: 2495.5 | C48: 2575 | D48: 2576 | E48: 2590 | F48: 10237 | G48: 2640 | H48: 2671 | I48: 2650.53 | J48: 2662.95 | K48: 10624.37 | L48: 2723.3 | M48: 2752.07 | N48: 2741.73 | O48: 2755.18 | P48: 10925.54 | Q48: 2815.68 | R48: 2849.16 | S48: 2821.24 | T48: 2830.95 | U48: 11242.7 | V48: 2908.96 | W48: 2943.46 | X48: 2909.77 | Y48: 2917.86 | Z48: 11586.78 | AA48: 3003.03 | AB48: 3038.57 | AC48: 3000.28 | AD48: 3007.2 | AE48: 11913.58
A49: Total connectivity and platforms revenue | B49: 20161 | C49: 20414 | D49: 20212 | E49: 20282 | F49: 81069 | G49: 19962 | H49: 19795 | I49: 19677.91 | J49: 19893.98 | K49: 79329.57 | L49: 19611.38 | M49: 19489.81 | N49: 19338 | O49: 19534.55 | P49: 78171.99 | Q49: 19508.57 | R49: 19392.88 | S49: 19311.31 | T49: 19564.47 | U49: 77831.83 | V49: 19474.87 | W49: 19370.9 | X49: 19255.8 | Y49: 19480.69 | Z49: 77326.17 | AA49: 19502.4 | AB49: 19416.88 | AC49: 19329.09 | AD49: 19604.16 | AE49: 77398.34
A51: Connectivity & platforms adjusted EBITDA
A52: Residential connectivity platforms - Adjusted EBITDA | B52: 6842 | C52: 7006 | D52: 6484 | E52: 6032 | F52: 26364 | G52: 6434 | H52: 6448 | I52: 6095.11 | J52: 5827.21 | K52: 24804.52 | L52: 6248.12 | M52: 6284.49 | N52: 5977.69 | O52: 5717.95 | P52: 24217.39 | Q52: 6182.97 | R52: 6226.41 | S52: 5919.23 | T52: 5649.49 | U52: 24123.3 | V52: 6118.84 | W52: 6156.89 | X52: 5808.8 | Y52: 5494.59 | Z52: 23633.84 | AA52: 6072.62 | AB52: 6113.25 | AC52: 5778.71 | AD52: 5504.42 | AE52: 23597.83
A53: Business services connectivity - Adjusted EBITDA | B53: 1422 | C53: 1444 | D53: 1454 | E53: 1405 | F53: 5725 | G53: 1476 | H53: 1516 | I53: 1491.75 | J53: 1455.8 | K53: 5940.08 | L53: 1537.71 | M53: 1558.86 | N53: 1542.14 | O53: 1513.57 | P53: 6102.77 | Q53: 1581.83 | R53: 1616.28 | S53: 1584.09 | T53: 1547.16 | U53: 6273.6 | V53: 1636.55 | W53: 1671.08 | X53: 1636.55 | Y53: 1598.56 | Z53: 6461.22 | AA53: 1689.92 | AB53: 1730.07 | AC53: 1693.09 | AD53: 1653.83 | AE53: 6640.7
A54: Total connectivity and platforms - Adjusted EBITDA | B54: 8264 | C54: 8450 | D54: 7938 | E54: 7437 | F54: 32089 | G54: 7910 | H54: 7964 | I54: 7568.55 | J54: 7256.55 | K54: 30699.78 | L54: 7740.79 | M54: 7846.8 | N54: 7518.48 | O54: 7224.17 | P54: 30358.14 | Q54: 7740.18 | R54: 7813.16 | S54: 7469.01 | T54: 7162.15 | U54: 30414.22 | V54: 7755.39 | W54: 7827.97 | X54: 7445.35 | Y54: 7093.15 | Z54: 30297.5 | AA54: 7762.54 | AB54: 7843.31 | AC54: 7471.8 | AD54: 7158.26 | AE54: 30535.97
A56: Residential connectivity & platforms
A57: Domestic broadband revenue | B57: 6679 | C57: 6649 | D57: 6550 | E57: 6410 | F57: 26288 | G57: 6338 | H57: 6280 | I57: 6221.77 | J57: 6167.32 | K57: 25007.2 | L57: 6197.42 | M57: 6164.08 | N57: 6120.45 | O57: 6084.53 | P57: 24560.83 | Q57: 6143.04 | R57: 6122.2 | S57: 6083.01 | T57: 6046.37 | U57: 24300.69 | V57: 6158.06 | W57: 6148.2 | X57: 6112.78 | Y57: 6081.47 | Z57: 24178.19 | AA57: 6166.36 | AB57: 6161.65 | AC57: 6126.33 | AD57: 6097.19 | AE57: 24076.69
A58: Domestic wireless revenue | B58: 1123 | C58: 1195 | D58: 1246 | E58: 1403 | F58: 4967 | G58: 1395 | H58: 1411 | I58: 1450.07 | J58: 1606.28 | K58: 5861.71 | L58: 1579.24 | M58: 1606.7 | N58: 1635.53 | O58: 1788.53 | P58: 6647.92 | Q58: 1789.19 | R58: 1814.69 | S58: 1840.72 | T58: 1997.6 | U58: 7387.21 | V58: 1987.02 | W58: 2003.07 | X58: 2037.68 | Y58: 2199.91 | Z58: 8130.32 | AA58: 2194.91 | AB58: 2202.83 | AC58: 2236.92 | AD58: 2403.21 | AE58: 8856.12
A59: International connectivity revenue | B59: 1132 | C59: 1219 | D59: 1275 | E59: 1337 | F59: 4963 | G59: 1240 | H59: 1246 | I59: 1307.89 | J59: 1375.54 | K59: 5169.43 | L59: 1284.12 | M59: 1297.36 | N59: 1364.57 | O59: 1439.77 | P59: 5363.82 | Q59: 1313.69 | R59: 1323.98 | S59: 1398.05 | T59: 1471.61 | U59: 5479.77 | V59: 1345.21 | W59: 1355.86 | X59: 1428.83 | Y59: 1502.49 | Z59: 5619.41 | AA59: 1378.87 | AB59: 1390.26 | AC59: 1465.08 | AD59: 1540.67 | AE59: 5767.35
A60: Residential connectivity revenue | B60: 8933 | C60: 9063 | D60: 9071 | E60: 9150 | F60: 36218 | G60: 8973 | H60: 8937 | I60: 8979.77 | J60: 9149.3 | K60: 36039.18 | L60: 9060.8 | M60: 9068.13 | N60: 9120.56 | O60: 9312.8 | P60: 36572.55 | Q60: 9245.97 | R60: 9260.92 | S60: 9321.75 | T60: 9515.62 | U60: 37167.72 | V60: 9490.23 | W60: 9507.16 | X60: 9579.35 | Y60: 9783.84 | Z60: 37927.91 | AA60: 9740.09 | AB60: 9754.77 | AC60: 9828.29 | AD60: 10041.04 | AE60: 38700.12
A61: Video platform revenue | B61: 6600 | C61: 6605 | D61: 6475 | E61: 6266 | F61: 25946 | G61: 6256 | H61: 6092 | I61: 6007.86 | J61: 5830.44 | K61: 24186.3 | L61: 5836.1 | M61: 5692.16 | N61: 5575.47 | O61: 5416.93 | P61: 22687.7 | Q61: 5519.18 | R61: 5386.13 | S61: 5296.11 | T61: 5146.87 | U61: 21466.6 | V61: 5234.62 | W61: 5111.5 | X61: 5027.54 | Y61: 4891.98 | Z61: 20316.99 | AA61: 4965.02 | AB61: 4850.37 | AC61: 4774.14 | AD61: 4649.66 | AE61: 19283.31
A62: Advertising platform revenue | B62: 899 | C62: 951 | D62: 893 | E62: 1067 | F62: 3810 | G62: 951 | H62: 962 | I62: 925.7 | J62: 1129.32 | K62: 3967.96 | L62: 915.54 | M62: 912.9 | N62: 845.65 | O62: 998.17 | P62: 3717.69 | Q62: 906.11 | R62: 887.19 | S62: 861.31 | T62: 1065.1 | U62: 3886.37 | V62: 852.93 | W62: 832.89 | X62: 753.83 | Y62: 914.64 | Z62: 3587.87 | AA62: 847.37 | AB62: 838.84 | AC62: 777.85 | AD62: 974.26 | AE62: 3764.14
A63: Other platform revenue | B63: 1233 | C63: 1219 | D63: 1197 | E63: 1209 | F63: 4858 | G63: 1143 | H63: 1133 | I63: 1114.07 | J63: 1121.98 | K63: 4512.05 | L63: 1075.61 | M63: 1064.59 | N63: 1054.55 | O63: 1051.44 | P63: 4268.5 | Q63: 1021.69 | R63: 1009.43 | S63: 1010.88 | T63: 1005.88 | U63: 4068.42 | V63: 988.19 | W63: 975.84 | X63: 985.31 | Y63: 972.41 | Z63: 3906.63 | AA63: 946.85 | AB63: 934.36 | AC63: 948.57 | AD63: 931.94 | AE63: 3737.15
A64: Residential connectivity and platforms revenue | B64: 17665 | C64: 17839 | D64: 17636 | E64: 17692 | F64: 70832 | G64: 17323 | H64: 17124 | I64: 17027.39 | J64: 17231.02 | K64: 68705.46 | L64: 16888.08 | M64: 16737.75 | N64: 16596.26 | O64: 16779.37 | P64: 67246.49 | Q64: 16692.89 | R64: 16543.72 | S64: 16490.07 | T64: 16733.52 | U64: 66589.14 | V64: 16565.92 | W64: 16427.44 | X64: 16346.04 | Y64: 16562.84 | Z64: 65739.39 | AA64: 16499.37 | AB64: 16378.31 | AC64: 16328.82 | AD64: 16596.95 | AE64: 65484.73
A65: Programming - Connectivity and platforms | B65: 4107 | C65: 3998 | D65: 3952 | E65: 3950 | F65: 16007 | G65: 3787 | H65: 3698 | I65: 3677.81 | J65: 3672.35 | K65: 14835.16 | L65: 3573.79 | M65: 3488.3 | N65: 3446.02 | O65: 3444.02 | P65: 14026.87 | Q65: 3392.44 | R65: 3320.9 | S65: 3290.17 | T65: 3298.45 | U65: 13348.72 | V65: 3234.9 | W65: 3169.43 | X65: 3141.22 | Y65: 3157.94 | Z65: 12727.93 | AA65: 3085.84 | AB65: 3025.81 | AC65: 3002.23 | AD65: 3021.92 | AE65: 12145.61
A66: Non programming - Residential connectivity and platforms | B66: 6715 | C66: 6835 | D66: 7200 | E66: 7710 | F66: 28462 | G66: 7102 | H66: 6978 | I66: 7231.67 | J66: 7706.61 | K66: 29018.12 | L66: 7076.81 | M66: 6954 | N66: 7180.66 | O66: 7608.14 | P66: 28883.73 | Q66: 7150.12 | R66: 7029.11 | S66: 7314.42 | T66: 7818.93 | U66: 29118.84 | V66: 7212.18 | W66: 7101.12 | X66: 7396.02 | Y66: 7910.31 | Z66: 29330.97 | AA66: 7340.91 | AB66: 7239.26 | AC66: 7547.88 | AD66: 8070.61 | AE66: 29755.91
A67: Residential connectivity platforms - Costs and exps excl. D&A | B67: 10822 | C67: 10833 | D67: 11152 | E67: 11660 | F67: 44469 | G67: 10889 | H67: 10676 | I67: 10910.88 | J67: 11401.86 | K67: 43877.59 | L67: 10664.21 | M67: 10464.32 | N67: 10652.26 | O67: 11092.91 | P67: 43006.05 | Q67: 10549.16 | R67: 10357.64 | S67: 10610.68 | T67: 11129.87 | U67: 42558.16 | V67: 10447.08 | W67: 10270.55 | X67: 10537.23 | Y67: 11068.25 | Z67: 42166.77 | AA67: 10426.75 | AB67: 10265.06 | AC67: 10550.11 | AD67: 11092.53 | AE67: 41993.46
A68: Residential connectivity platforms - Adjusted EBITDA | B68: 6842 | C68: 7006 | D68: 6484 | E68: 6032 | F68: 26364 | G68: 6434 | H68: 6448 | I68: 6095.11 | J68: 5827.21 | K68: 24804.52 | L68: 6248.12 | M68: 6284.49 | N68: 5977.69 | O68: 5717.95 | P68: 24217.39 | Q68: 6182.97 | R68: 6226.41 | S68: 5919.23 | T68: 5649.49 | U68: 24123.3 | V68: 6118.84 | W68: 6156.89 | X68: 5808.8 | Y68: 5494.59 | Z68: 23633.84 | AA68: 6072.62 | AB68: 6113.25 | AC68: 5778.71 | AD68: 5504.42 | AE68: 23597.83
A70: Business services connectivity
A71: Business services connectivity revenue | B71: 2495.5 | C71: 2575 | D71: 2576 | E71: 2590 | F71: 10237 | G71: 2640 | H71: 2671 | I71: 2650.53 | J71: 2662.95 | K71: 10624.37 | L71: 2723.3 | M71: 2752.07 | N71: 2741.73 | O71: 2755.18 | P71: 10925.54 | Q71: 2815.68 | R71: 2849.16 | S71: 2821.24 | T71: 2830.95 | U71: 11242.7 | V71: 2908.96 | W71: 2943.46 | X71: 2909.77 | Y71: 2917.86 | Z71: 11586.78 | AA71: 3003.03 | AB71: 3038.57 | AC71: 3000.28 | AD71: 3007.2 | AE71: 11913.58
A72: Business services connectivity - Costs and Exps excl. D&A | B72: 1074 | C72: 1131 | D72: 1122 | E72: 1186 | F72: 4513 | G72: 1163 | H72: 1155 | I72: 1159.11 | J72: 1210.95 | K72: 4688.23 | L72: 1186.99 | M72: 1196.76 | N72: 1201.5 | O72: 1242.14 | P72: 4825 | Q72: 1235.97 | R72: 1235.09 | S72: 1238.06 | T72: 1283.9 | U72: 4982.4 | V72: 1272.41 | W72: 1272.38 | X72: 1273.22 | Y72: 1319.3 | Z72: 5119.74 | AA72: 1313.11 | AB72: 1308.51 | AC72: 1307.19 | AD72: 1353.37 | AE72: 5252.04
A73: Business services connectivity - Adjusted EBITDA | B73: 1422 | C73: 1444 | D73: 1454 | E73: 1405 | F73: 5725 | G73: 1476 | H73: 1516 | I73: 1491.75 | J73: 1455.8 | K73: 5940.08 | L73: 1537.71 | M73: 1558.86 | N73: 1542.14 | O73: 1513.57 | P73: 6102.77 | Q73: 1581.83 | R73: 1616.28 | S73: 1584.09 | T73: 1547.16 | U73: 6273.6 | V73: 1636.55 | W73: 1671.08 | X73: 1636.55 | Y73: 1598.56 | Z73: 6461.22 | AA73: 1689.92 | AB73: 1730.07 | AC73: 1693.09 | AD73: 1653.83 | AE73: 6640.7
A75: Supplemental
A76: Residential connectivity platforms - Costs and exps excl. D&A | B76: 10822 | C76: 10833 | D76: 11152 | E76: 11660 | F76: 44469 | G76: 10889 | H76: 10676 | I76: 10910.88 | J76: 11401.86 | K76: 43877.59 | L76: 10664.21 | M76: 10464.32 | N76: 10652.26 | O76: 11092.91 | P76: 43006.05 | Q76: 10549.16 | R76: 10357.64 | S76: 10610.68 | T76: 11129.87 | U76: 42558.16 | V76: 10447.08 | W76: 10270.55 | X76: 10537.23 | Y76: 11068.25 | Z76: 42166.77 | AA76: 10426.75 | AB76: 10265.06 | AC76: 10550.11 | AD76: 11092.53 | AE76: 41993.46
A77: Business services connectivity - Costs and Exps excl. D&A | B77: 1074 | C77: 1131 | D77: 1122 | E77: 1186 | F77: 4513 | G77: 1163 | H77: 1155 | I77: 1159.11 | J77: 1210.95 | K77: 4688.23 | L77: 1186.99 | M77: 1196.76 | N77: 1201.5 | O77: 1242.14 | P77: 4825 | Q77: 1235.97 | R77: 1235.09 | S77: 1238.06 | T77: 1283.9 | U77: 4982.4 | V77: 1272.41 | W77: 1272.38 | X77: 1273.22 | Y77: 1319.3 | Z77: 5119.74 | AA77: 1313.11 | AB77: 1308.51 | AC77: 1307.19 | AD77: 1353.37 | AE77: 5252.04
A78: Total connectivity and platforms - Costs and Exps excl. D&A | B78: 11896 | C78: 11964 | D78: 12274 | E78: 12846 | F78: 48980 | G78: 12053 | H78: 11830 | I78: 12098.09 | J78: 12651.19 | K78: 48632.23 | L78: 11864.01 | M78: 11626.76 | N78: 11819.52 | O78: 12310.38 | P78: 47811 | Q78: 11768.39 | R78: 11579.72 | S78: 11842.3 | T78: 12402.32 | U78: 47407.11 | V78: 11719.49 | W78: 11542.93 | X78: 11810.46 | Y78: 12387.55 | Z78: 47028.68 | AA78: 11739.86 | AB78: 11573.57 | AC78: 11857.3 | AD78: 12445.9 | AE78: 46862.37
A80: Programming - Connectivity and platforms | B80: 4107 | C80: 3998 | D80: 3952 | E80: 3950 | F80: 16007 | G80: 3787 | H80: 3698 | I80: 3677.81 | J80: 3672.35 | K80: 14835.16 | L80: 3573.79 | M80: 3488.3 | N80: 3446.02 | O80: 3444.02 | P80: 14026.87 | Q80: 3392.44 | R80: 3320.9 | S80: 3290.17 | T80: 3298.45 | U80: 13348.72 | V80: 3234.9 | W80: 3169.43 | X80: 3141.22 | Y80: 3157.94 | Z80: 12727.93 | AA80: 3085.84 | AB80: 3025.81 | AC80: 3002.23 | AD80: 3021.92 | AE80: 12145.61
A81: Marketing Promotion - Connectivity and Platforms | B81: 1242 | C81: 1249 | D81: 1332 | E81: 1323 | F81: 5146 | G81: 1337 | H81: 1311 | I81: 1361.8 | J81: 1335.11 | K81: 5344.91 | L81: 1330.32 | M81: 1301.72 | N81: 1354.21 | O81: 1320.31 | P81: 5337.86 | Q81: 1337.31 | R81: 1313.62 | S81: 1380.11 | T81: 1341.09 | U81: 5368.27 | V81: 1355.94 | W81: 1324.53 | X81: 1394.21 | Y81: 1357.54 | Z81: 5408.94 | AA81: 1384.17 | AB81: 1349.82 | AC81: 1416.94 | AD81: 1384.99 | AE81: 5492.43
A82: Direct Product Costs - Connectivity and Platforms | B82: 1625 | C82: 1829 | D82: 1911 | E82: 2210 | F82: 7575 | G82: 1962 | H82: 1992 | I82: 2032.47 | J82: 2322.74 | K82: 8309.22 | L82: 2044.48 | M82: 2056.72 | N82: 2085.01 | O82: 2357.93 | P82: 8602.57 | Q82: 2144.82 | R82: 2175.11 | S82: 2221.29 | T82: 2561.78 | U82: 8967.95 | V82: 2216.1 | W82: 2249.1 | X82: 2286.44 | Y82: 2637.36 | Z82: 9233.55 | AA82: 2319.02 | AB82: 2352.58 | AC82: 2392.27 | AD82: 2757.53 | AE82: 9588.14
A83: Technical Support - Connectivity and Platforms | B83: 1935 | C83: 1918 | D83: 2019 | E83: 1981 | F83: 7853 | G83: 1968 | H83: 1913 | I83: 1994.23 | J83: 1965.13 | K83: 7840.36 | L83: 1942.76 | M83: 1892.23 | N83: 1963.65 | O83: 1940.95 | P83: 7771.09 | Q83: 1942.26 | R83: 1888.53 | S83: 1989.52 | T83: 1966.72 | U83: 7744.41 | V83: 1963.09 | W83: 1910.18 | X83: 2031.97 | Y83: 2014.06 | Z83: 7759.65 | AA83: 1972.27 | AB83: 1920.58 | AC83: 2064.69 | AD83: 2050.77 | AE83: 7765.96
A84: Customer Service - Connectivity and Platforms | B84: 682 | C84: 677 | D84: 707 | E84: 699 | F84: 2765 | G84: 676 | H84: 671 | I84: 703.6 | J84: 687.84 | K84: 2738.45 | L84: 669.54 | M84: 664.8 | N84: 685.52 | O84: 673.25 | P84: 2708.48 | Q84: 668.8 | R84: 663.24 | S84: 686.15 | T84: 677.93 | U84: 2698.97 | V84: 679.14 | W84: 673.17 | X84: 692.59 | Y84: 684.05 | Z84: 2700.4 | AA84: 684.77 | AB84: 678.58 | AC84: 695.7 | AD84: 687.78 | AE84: 2697.72
A85: Other - Connectivity and Platforms | B85: 2305 | C85: 2293 | D85: 2353 | E85: 2683 | F85: 9634 | G85: 2323 | H85: 2245 | I85: 2326.38 | J85: 2659.24 | K85: 9553.62 | L85: 2303.08 | M85: 2222.96 | N85: 2285.14 | O85: 2573.94 | P85: 9336.26 | Q85: 2282.8 | R85: 2218.38 | S85: 2275.04 | T85: 2556.35 | U85: 9258.36 | V85: 2270.36 | W85: 2216.47 | X85: 2263.97 | Y85: 2536.64 | Z85: 9153.56 | AA85: 2293.73 | AB85: 2246.15 | AC85: 2285.48 | AD85: 2542.97 | AE85: 9140.29
A86: Total connectivity and platforms - Costs and Exps excl. D&A | B86: 11896 | C86: 11964 | D86: 12274 | E86: 12846 | F86: 48980 | G86: 12053 | H86: 11830 | I86: 12098.09 | J86: 12651.19 | K86: 48632.23 | L86: 11864.01 | M86: 11626.76 | N86: 11819.52 | O86: 12310.38 | P86: 47811 | Q86: 11768.39 | R86: 11579.72 | S86: 11842.3 | T86: 12402.32 | U86: 47407.11 | V86: 11719.49 | W86: 11542.93 | X86: 11810.46 | Y86: 12387.55 | Z86: 47028.68 | AA86: 11739.86 | AB86: 11573.57 | AC86: 11857.3 | AD86: 12445.9 | AE86: 46862.37

Sheet SPG C&P Customer Metrics
A2: Comcast Corporation | Connectivity and Platforms - Customer Metrics
A3: NASDAQGS:CMCSA (MI KEY: 4057180; SPCIQ KEY: 173341)
A5: Visible Alpha
A7: Period Type : Fiscal Quarter, Fiscal Halves, Fiscal Year
A8: Period Start : 2025
A9: Period End : 2030
A10: Currency : Reported
A11: Consensus View : Mean
A12: As Of: 10/20/2026
A14: All numbers in $M unless otherwise indicated | B14: FQ1 2025A | C14: FQ2 2025A | D14: FQ3 2025A | E14: FQ4 2025A | F14: FY2025A | G14: FQ1 2026A | H14: FQ2 2026A | I14: FQ3 2026E | J14: FQ4 2026E | K14: FY2026E | L14: FQ1 2027E | M14: FQ2 2027E | N14: FQ3 2027E | O14: FQ4 2027E | P14: FY2027E | Q14: FQ1 2028E | R14: FQ2 2028E | S14: FQ3 2028E | T14: FQ4 2028E | U14: FY2028E | V14: FQ1 2029E | W14: FQ2 2029E | X14: FQ3 2029E | Y14: FQ4 2029E | Z14: FY2029E | AA14: FQ1 2030E | AB14: FQ2 2030E | AC14: FQ3 2030E | AD14: FQ4 2030E | AE14: FY2030E
A15: Number of Contributors Available | B15: 22 | C15: 21 | D15: 21 | E15: 20 | F15: 21 | G15: 21 | H15: 20 | I15: 20 of 20 | J15: 20 of 20 | K15: 20 of 20 | L15: 12 of 20 | M15: 12 of 20 | N15: 11 of 20 | O15: 11 of 20 | P15: 20 of 20 | Q15: 8 of 20 | R15: 8 of 20 | S15: 8 of 20 | T15: 8 of 20 | U15: 19 of 20 | V15: 7 of 20 | W15: 7 of 20 | X15: 7 of 20 | Y15: 7 of 20 | Z15: 16 of 20 | AA15: 7 of 20 | AB15: 7 of 20 | AC15: 7 of 20 | AD15: 7 of 20 | AE15: 16 of 20
A16: Connectivity & platforms: Customer metrics
A18: Homes and businesses passed - net adds(K#) | B18: 236 | C18: 293 | D18: 285 | E18: 344 | F18: 1291 | G18: 229 | H18: 279 | I18: 307.37 | J18: 299.86 | K18: 1162.01 | L18: 286.6 | M18: 283.83 | N18: 286.14 | O18: 281 | P18: 1173.11 | Q18: 251.72 | R18: 299.65 | S18: 302.65 | T18: 311.41 | U18: 1151.37 | V18: 234.66 | W18: 299.19 | X18: 302.77 | Y18: 313.01 | Z18: 1116.99 | AA18: 227.39 | AB18: 301.41 | AC18: 305.06 | AD18: 315.43 | AE18: 1093.76
A19: Homes and businesses passed(K#) | B19: 58063 | C19: 58356 | D19: 58641 | E19: 64983 | F19: 64983 | G19: 59164 | H19: 59443 | I19: 63582.89 | J19: 63882.75 | K19: 64219.22 | L19: 63988.87 | M19: 64272.7 | N19: 64558.84 | O19: 64839.84 | P19: 65315.17 | Q19: 65311.96 | R19: 65611.61 | S19: 65914.26 | T19: 66225.67 | U19: 66344.52 | V19: 66108.15 | W19: 66407.34 | X19: 66710.11 | Y19: 67023.12 | Z19: 67281.01 | AA19: 67250.52 | AB19: 67551.93 | AC19: 67856.98 | AD19: 68172.41 | AE19: 68374.77
A21: Customer relationships
A22: Domestic residential connectivity & platforms customer relationships net additions (losses)(K#) | B22: -203 | C22: -223 | D22: -104 | E22: -203 | F22: -733 | G22: -94 | H22: -166 | I22: -128.61 | J22: -135.25 | K22: -523.86 | L22: -73.33 | M22: -99.92 | N22: -53.97 | O22: -86.34 | P22: -415.99 | Q22: -54.53 | R22: -81.71 | S22: -36.8 | T22: -73.28 | U22: -398.67 | V22: -37.08 | W22: -48.76 | X22: -8.98 | Y22: -41.03 | Z22: -337.34 | AA22: -31.55 | AB22: -38.63 | AC22: -1.61 | AD22: -32.01 | AE22: -288.38
A23: Domestic residential connectivity & platforms customer relationships(K#) | B23: 30969 | C23: 30746 | D23: 30642 | E23: 30439 | F23: 30439 | G23: 30345 | H23: 30179 | I23: 30050.39 | J23: 29915.14 | K23: 29915.14 | L23: 29884.05 | M23: 29784.12 | N23: 29730.16 | O23: 29643.81 | P23: 29502.44 | Q23: 29644.34 | R23: 29562.64 | S23: 29525.84 | T23: 29452.56 | U23: 29081.52 | V23: 29537.99 | W23: 29489.23 | X23: 29480.24 | Y23: 29439.21 | Z23: 28781.6 | AA23: 29407.66 | AB23: 29369.03 | AC23: 29367.43 | AD23: 29335.41 | AE23: 28493.22
A24: International residential connectivity & platforms customer relationships net additions (losses)(K#) | B24: -12 | C24: -101 | D24: -96 | E24: 22 | F24: -187 | G24: 104 | H24: -64 | I24: -60.67 | J24: 23.62 | K24: -7.88 | L24: 38.61 | M24: -51.28 | N24: -43.23 | O24: 20.19 | P24: -30.35 | Q24: 57.21 | R24: -42 | S24: -42.77 | T24: 24.71 | U24: -15.88 | V24: 60.11 | W24: -53.92 | X24: -55.8 | Y24: 23.89 | Z24: -23.44 | AA24: 61.24 | AB24: -53.48 | AC24: -54.84 | AD24: 24.26 | AE24: -18.45
A25: International residential connectivity & platforms customer relationships(K#) | B25: 17674 | C25: 17573 | D25: 17477 | E25: 17499 | F25: 17499 | G25: 17603 | H25: 17539 | I25: 17485.47 | J25: 17507.69 | K25: 17505.89 | L25: 17553.54 | M25: 17506.92 | N25: 17467.62 | O25: 17485.98 | P25: 17483.63 | Q25: 17566.02 | R25: 17529.27 | S25: 17491.85 | T25: 17513.48 | U25: 17473.44 | V25: 17525.64 | W25: 17479.43 | X25: 17431.6 | Y25: 17452.07 | Z25: 17432.49 | AA25: 17504.57 | AB25: 17458.73 | AC25: 17411.72 | AD25: 17432.51 | AE25: 17417.99
A26: Business services connectivity customer relationships net additions (losses)(K#) | B26: -13 | C26: 100 | D26: -11 | E26: 1 | F26: 76 | G26: -4.71 | H26: -18.61 | I26: -5.03 | J26: -19.1 | K26: -18.73 | L26: 2.22 | M26: -0.24 | N26: -7.08 | O26: -10 | P26: -8.88 | Q26: 3.94 | R26: 0.17 | S26: -6.22 | T26: -8.85 | U26: -12.94 | V26: 4.05 | W26: 0.6 | X26: -5.34 | Y26: -7.7 | Z26: -11.51 | AA26: 4.17 | AB26: 1.03 | AC26: -4.44 | AD26: -6.57 | AE26: -10.34
A27: Business services connectivity customer relationships(K#) | B27: 2613 | C27: 2713 | D27: 2702 | E27: 2702 | F27: 2702 | G27: 2685.26 | H27: 2687.57 | I27: 2680.75 | J27: 2669.38 | K27: 2669.38 | L27: 2681.99 | M27: 2680.71 | N27: 2672.66 | O27: 2669.36 | P27: 2661.24 | Q27: 2664.08 | R27: 2663.35 | S27: 2653.85 | T27: 2650.08 | U27: 2642.91 | V27: 2655.24 | W27: 2655.26 | X27: 2646.78 | Y27: 2643.75 | Z27: 2631.4 | AA27: 2649.32 | AB27: 2649.92 | AC27: 2642.32 | AD27: 2639.92 | AE27: 2621.06
A28: Total customer relationships net additions (losses) - Connectivity and platforms(K#) | B28: -228 | C28: -224 | D28: -211 | E28: -181 | F28: -844 | G28: 9 | H28: -230 | I28: -192.58 | J28: -130.35 | K28: -767.73 | L28: -22.04 | M28: -138.45 | N28: -85.46 | O28: -72.23 | P28: -422.13 | Q28: 12.52 | R28: -107.93 | S28: -62.2 | T28: -53.32 | U28: -401.54 | V28: 37.87 | W28: -77.91 | X28: -39.13 | Y28: -9.18 | Z28: -336.04 | AA28: 45.73 | AB28: -64.93 | AC28: -28.92 | AD28: 4.68 | AE28: -271.83
A29: Total customer relationships - Connectivity and platforms(K#) | B29: 51256 | C29: 51032 | D29: 50821 | E29: 50640 | F29: 50640 | G29: 50022.66 | H29: 47718 | I29: 49391.74 | J29: 49270.98 | K29: 49434.17 | L29: 48819.47 | M29: 48668.45 | N29: 48572.21 | O29: 48493.85 | P29: 48752.53 | Q29: 48605.95 | R29: 48486.78 | S29: 48414.52 | T29: 48353.44 | U29: 48206.46 | V29: 48798.8 | W29: 48714.53 | X29: 48669.06 | Y29: 48651.71 | Z29: 48023.33 | AA29: 48714.2 | AB29: 48646.65 | AC29: 48614.58 | AD29: 48612.23 | AE29: 47731.11
A30: Average Total Customer Relationships - Connectivity and Platforms(K#) | B30: 51370 | C30: 51144 | D30: 50926.5 | E30: 50730.5 | F30: 51062 | G30: 50064.87 | H30: 49713.02 | I30: 49362.7 | J30: 49204.56 | K30: 49570.19 | L30: 48854.85 | M30: 48596.17 | N30: 48482.07 | O30: 48404.55 | P30: 49038.41 | Q30: 48429.5 | R30: 48383.1 | S30: 48295.27 | T30: 48237.87 | U30: 48351.68 | V30: 48545.51 | W30: 48526.81 | X30: 48465.07 | Y30: 48437.66 | Z30: 48143.56 | AA30: 48463.28 | AB30: 48454.83 | AC30: 48404.68 | AD30: 48388.15 | AE30: 47839.91
A32: Average monthly total revenue per customer relationship - Connectivity and platforms($) | B32: 130.83 | C32: 133.04 | D32: 132.3 | E32: 133.27 | F32: 132.3 | G32: 133.24 | H32: 137.95 | I32: 132.81 | J32: 134.54 | K32: 133.33 | L32: 134.26 | M32: 133.83 | N32: 133.25 | O32: 134.78 | P32: 132.89 | Q32: 134.89 | R32: 134.23 | S32: 134.13 | T32: 136.01 | U32: 133.8 | V32: 134.99 | W32: 134.32 | X32: 133.9 | Y32: 135.43 | Z32: 133.7 | AA32: 135.8 | AB32: 135.25 | AC32: 134.97 | AD32: 136.82 | AE32: 134.8
A33: Average monthly total adjusted EBITDA per customer relationship - Connectivity and platforms($) | B33: 53.64 | C33: 55.07 | D33: 51.96 | E33: 49.18 | F33: 52.37 | G33: 52.92 | H33: 55.5 | I33: 51.49 | J33: 49.18 | K33: 51.84 | L33: 53.64 | M33: 54.36 | N33: 52.21 | O33: 50.18 | P33: 51.97 | Q33: 53.48 | R33: 54.04 | S33: 51.78 | T33: 49.6 | U33: 51.95 | V33: 53.82 | W33: 54.35 | X33: 51.78 | Y33: 49.18 | Z33: 51.96 | AA33: 54.23 | AB33: 54.83 | AC33: 52.32 | AD33: 49.99 | AE33: 52.68
A35: Domestic broadband
A36: Domestic broadband residential net additions (losses)(K#) | B36: -183 | C36: -201 | D36: -91 | E36: -178 | F36: -654 | G36: -65 | H36: -167 | I36: -135.59 | J36: -168.38 | K36: -536.51 | L36: -109.49 | M36: -159.07 | N36: -104.6 | O36: -135.56 | P36: -511.08 | Q36: -90.51 | R36: -151.45 | S36: -82.43 | T36: -124.94 | U36: -500.74 | V36: -77.72 | W36: -122.54 | X36: -58.53 | Y36: -93.42 | Z36: -435.89 | AA36: -83.59 | AB36: -120.9 | AC36: -40.7 | AD36: -88.08 | AE36: -399.63
A37: Domestic broadband residential customers(K#) | B37: 29190 | C37: 28989 | D37: 28897 | E37: 28719 | F37: 28719 | G37: 28654 | H37: 28486 | I37: 28350.5 | J37: 28182.12 | K37: 28182.18 | L37: 28072.16 | M37: 27913.09 | N37: 27808.48 | O37: 27672.93 | P37: 27673.11 | Q37: 27617.89 | R37: 27466.44 | S37: 27384.01 | T37: 27259.07 | U37: 27169.88 | V37: 27288.94 | W37: 27166.39 | X37: 27116.23 | Y37: 27022.81 | Z37: 26785.05 | AA37: 26939.22 | AB37: 26818.32 | AC37: 26777.62 | AD37: 26689.54 | AE37: 26385.42
A38: Domestic broadband business services net additions (losses)(K#) | B38: -17 | C38: -25 | D38: -13 | E38: -3 | F38: -58 | G38: -9.23 | H38: -9.5 | I38: -8.14 | J38: -4.08 | K38: -30.96 | L38: -6.25 | M38: -5.75 | N38: -2.25 | O38: 0.25 | P38: -23.63 | Q38: -5.62 | R38: -5.12 | S38: -1.43 | T38: 1.65 | U38: -22.48 | V38: -4.99 | W38: -4.49 | X38: -0.57 | Y38: 1.41 | Z38: -21.33 | AA38: -4.34 | AB38: -3.84 | AC38: 0.33 | AD38: 2 | AE38: -15.86
A39: Domestic broadband business services customers(K#) | B39: 2453 | C39: 2551 | D39: 2538 | E39: 2536 | F39: 2536 | G39: 2510.37 | H39: 2500.4 | I39: 2490.98 | J39: 2486.02 | K39: 2486.02 | L39: 2498.67 | M39: 2492.36 | N39: 2486.83 | O39: 2485.11 | P39: 2480.4 | Q39: 2483.62 | R39: 2479.01 | S39: 2475.24 | T39: 2475.01 | U39: 2460.4 | V39: 2474.96 | W39: 2471.73 | X39: 2469.42 | Y39: 2470.39 | Z39: 2443.2 | AA39: 2471.54 | AB39: 2468.75 | AC39: 2467.02 | AD39: 2468.39 | AE39: 2427.34
A40: Total domestic broadband net additions (losses)(K#) | B40: -199 | C40: -201 | D40: -104 | E40: -181 | F40: -710 | G40: -79.33 | H40: -175.23 | I40: -133.04 | J40: -156.7 | K40: -546.3 | L40: -107.74 | M40: -142.03 | N40: -75.43 | O40: -84.33 | P40: -446.08 | Q40: -53.14 | R40: -118.22 | S40: -17.32 | T40: -41.34 | U40: -402.14 | V40: -37.66 | W40: -94.2 | X40: 17.97 | Y40: -16.96 | Z40: -353.3 | AA40: -25.06 | AB40: -80.05 | AC40: 50.24 | AD40: 5.72 | AE40: -303.37
A41: Total domestic broadband customers(K#) | B41: 29190 | C41: 28989 | D41: 28897 | E41: 31255 | F41: 31255 | G41: 30472.76 | H41: 30479.01 | I41: 30345.96 | J41: 30189.27 | K41: 30189.1 | L41: 30120.74 | M41: 29978.71 | N41: 29903.28 | O41: 29818.95 | P41: 29705.03 | Q41: 30347.57 | R41: 30229.35 | S41: 30212.03 | T41: 30170.69 | U41: 29220.81 | V41: 30133.03 | W41: 30038.83 | X41: 30056.8 | Y41: 30039.84 | Z41: 28867.52 | AA41: 30014.78 | AB41: 29934.74 | AC41: 29984.98 | AD41: 29990.7 | AE41: 28564.14
A42: Total domestic broadband penetration of homes & businesses passed(%) | B42: 0.545 | C42: 0.5405 | D42: 0.5361 | E42: 0.481 | F42: 0.481 | G42: 0.4797 | H42: 0.4786 | I42: 0.4742 | J42: 0.4696 | K42: 0.4696 | L42: 0.4621 | M42: 0.458 | N42: 0.455 | O42: 0.4519 | P42: 0.4502 | Q42: 0.4493 | R42: 0.4456 | S42: 0.4433 | T42: 0.4407 | U42: 0.4363 | V42: 0.4389 | W42: 0.4357 | X42: 0.434 | Y42: 0.4318 | Z42: 0.424 | AA42: 0.4304 | AB42: 0.4274 | AC42: 0.4263 | AD42: 0.4244 | AE42: 0.4129
A44: Domestic broadband residential
A45: Domestic broadband residential customers(K#) | B45: 29190 | C45: 28989 | D45: 28897 | E45: 28719 | F45: 28719 | G45: 28654 | H45: 28486 | I45: 28350.5 | J45: 28182.12 | K45: 28182.18 | L45: 28072.16 | M45: 27913.09 | N45: 27808.48 | O45: 27672.93 | P45: 27673.11 | Q45: 27617.89 | R45: 27466.44 | S45: 27384.01 | T45: 27259.07 | U45: 27169.88 | V45: 27288.94 | W45: 27166.39 | X45: 27116.23 | Y45: 27022.81 | Z45: 26785.05 | AA45: 26939.22 | AB45: 26818.32 | AC45: 26777.62 | AD45: 26689.54 | AE45: 26385.42
A46: Average monthly domestic broadband residential revenue per subscriber($) | B46: 76.03 | C46: 76.19 | D46: 75.44 | E46: 74.17 | F46: 75.42 | G46: 73.65 | H46: 73.27 | I46: 72.96 | J46: 72.79 | K46: 73.22 | L46: 73.38 | M46: 73.37 | N46: 73.24 | O46: 73.13 | P46: 73.14 | Q46: 74.02 | R46: 74.09 | S46: 73.93 | T46: 73.77 | U46: 73.47 | V46: 75.11 | W46: 75.26 | X46: 75.07 | Y46: 74.88 | Z46: 74.1 | AA46: 76.17 | AB46: 76.38 | AC46: 76.18 | AD46: 75.99 | AE46: 74.78
A47: Domestic broadband revenue | B47: 6679 | C47: 6649 | D47: 6550 | E47: 6410 | F47: 26288 | G47: 6338 | H47: 6280 | I47: 6221.77 | J47: 6167.32 | K47: 25007.2 | L47: 6197.42 | M47: 6164.08 | N47: 6120.45 | O47: 6084.53 | P47: 24560.83 | Q47: 6143.04 | R47: 6122.2 | S47: 6083.01 | T47: 6046.37 | U47: 24300.69 | V47: 6158.06 | W47: 6148.2 | X47: 6112.78 | Y47: 6081.47 | Z47: 24178.19 | AA47: 6166.36 | AB47: 6161.65 | AC47: 6126.33 | AD47: 6097.19 | AE47: 24076.69
A49: Domestic wireless
A50: Total domestic wireless line net additions (losses)(K#) | B50: 322 | C50: 379 | D50: 414 | E50: 364 | F50: 1479 | G50: 434 | H50: 448 | I50: 399.29 | J50: 386.04 | K50: 1667.8 | L50: 381.87 | M50: 389.33 | N50: 376.53 | O50: 362.86 | P50: 1517.66 | Q50: 354.08 | R50: 377.45 | S50: 357.25 | T50: 341.04 | U50: 1381.28 | V50: 330.54 | W50: 365.82 | X50: 341.49 | Y50: 332.11 | Z50: 1269.72 | AA50: 319 | AB50: 357.62 | AC50: 337.08 | AD50: 325.72 | AE50: 1193.98
A51: Total domestic wireless lines(K#) | B51: 8148 | C51: 8527 | D51: 8941 | E51: 9305 | F51: 9305 | G51: 9739 | H51: 10187 | I51: 10586.4 | J51: 10972.44 | K51: 10972.49 | L51: 11352.17 | M51: 11741.5 | N51: 12118.03 | O51: 12480.89 | P51: 12490.77 | Q51: 12823.06 | R51: 13200.51 | S51: 13557.76 | T51: 13898.8 | U51: 13860.48 | V51: 14235.31 | W51: 14601.13 | X51: 14942.62 | Y51: 15274.73 | Z51: 15130.43 | AA51: 15593.72 | AB51: 15951.35 | AC51: 16288.43 | AD51: 16614.15 | AE51: 16324.41
A52: Domestic video
A53: Total domestic video net additions (losses)(K#) | B53: -427 | C53: -325 | D53: -256 | E53: -245 | F53: -1253 | G53: -322 | H53: -280 | I53: -246.9 | J53: -232.16 | K53: -1081.06 | L53: -291.27 | M53: -264.58 | N53: -215.18 | O53: -206.08 | P53: -964.98 | Q53: -254.04 | R53: -209.13 | S53: -174.68 | T53: -165.5 | U53: -818.64 | V53: -209.77 | W53: -184.36 | X53: -151.44 | Y53: -142.09 | Z53: -713.62 | AA53: -187.26 | AB53: -165.38 | AC53: -132.66 | AD53: -123.17 | AE53: -636.77
A54: Total domestic video customers(K#) | B54: 12096 | C54: 11771 | D54: 11515 | E54: 11270 | F54: 11270 | G54: 10948 | H54: 10668 | I54: 10421.1 | J54: 10188.94 | K54: 10188.94 | L54: 9897.24 | M54: 9632.66 | N54: 9417.48 | O54: 9211.4 | P54: 9222.35 | Q54: 9036.15 | R54: 8827.02 | S54: 8652.34 | T54: 8486.83 | U54: 8424.1 | V54: 8328.76 | W54: 8144.4 | X54: 7992.96 | Y54: 7850.87 | Z54: 7733.49 | AA54: 7663.61 | AB54: 7498.22 | AC54: 7365.56 | AD54: 7242.39 | AE54: 7096.72
A55: Domestic voice
A56: Total domestic voice net additions (losses)(K#) | B56: -325 | C56: -290 | D56: -244 | E56: -217 | F56: -1076 | G56: -255.93 | H56: -244.38 | I56: -221.85 | J56: -207.5 | K56: -939.86 | L56: -246.91 | M56: -230.99 | N56: -202.82 | O56: -188.86 | P56: -839.68 | Q56: -182.89 | R56: -155.51 | S56: -120.4 | T56: -106.51 | U56: -663.79 | V56: -159.14 | W56: -143.58 | X56: -125.35 | Y56: -129.4 | Z56: -591.66 | AA56: -139.44 | AB56: -133.14 | AC56: -98.46 | AD56: -83.08 | AE56: -515.05
A57: Total domestic voice customers(K#) | B57: 6401 | C57: 6111 | D57: 5867 | E57: 5650 | F57: 5650 | G57: 5319.38 | H57: 5074.43 | I57: 4868.81 | J57: 4676.51 | K57: 4676.51 | L57: 4513.88 | M57: 4282.89 | N57: 4080.07 | O57: 3891.21 | P57: 3856.4 | Q57: 3882.06 | R57: 3726.54 | S57: 3606.14 | T57: 3499.63 | U57: 3192.6 | V57: 3340.49 | W57: 3196.91 | X57: 3071.57 | Y57: 2942.16 | Z57: 2600.94 | AA57: 2802.72 | AB57: 2669.58 | AC57: 2571.11 | AD57: 2488.03 | AE57: 2085.9

Sheet SPG Content & Experiences
A2: Comcast Corporation | Content & Experiences
A3: NASDAQGS:CMCSA (MI KEY: 4057180; SPCIQ KEY: 173341)
A5: Visible Alpha
A7: Period Type : Fiscal Quarter, Fiscal Halves, Fiscal Year
A8: Period Start : 2025
A9: Period End : 2030
A10: Currency : Reported
A11: Consensus View : Mean
A12: As Of: 10/20/2026
A14: All numbers in $M unless otherwise indicated | B14: FQ1 2025A | C14: FQ2 2025A | D14: FQ3 2025A | E14: FQ4 2025A | F14: FY2025A | G14: FQ1 2026A | H14: FQ2 2026A | I14: FQ3 2026E | J14: FQ4 2026E | K14: FY2026E | L14: FQ1 2027E | M14: FQ2 2027E | N14: FQ3 2027E | O14: FQ4 2027E | P14: FY2027E | Q14: FQ1 2028E | R14: FQ2 2028E | S14: FQ3 2028E | T14: FQ4 2028E | U14: FY2028E | V14: FQ1 2029E | W14: FQ2 2029E | X14: FQ3 2029E | Y14: FQ4 2029E | Z14: FY2029E | AA14: FQ1 2030E | AB14: FQ2 2030E | AC14: FQ3 2030E | AD14: FQ4 2030E | AE14: FY2030E
A15: Number of Contributors Available | B15: 22 | C15: 21 | D15: 21 | E15: 20 | F15: 21 | G15: 21 | H15: 20 | I15: 20 of 20 | J15: 20 of 20 | K15: 20 of 20 | L15: 12 of 20 | M15: 12 of 20 | N15: 11 of 20 | O15: 11 of 20 | P15: 20 of 20 | Q15: 8 of 20 | R15: 8 of 20 | S15: 8 of 20 | T15: 8 of 20 | U15: 19 of 20 | V15: 7 of 20 | W15: 7 of 20 | X15: 7 of 20 | Y15: 7 of 20 | Z15: 16 of 20 | AA15: 7 of 20 | AB15: 7 of 20 | AC15: 7 of 20 | AD15: 7 of 20 | AE15: 16 of 20
A16: Content & experiences revenue
A17: Media revenue - C&E | B17: 4527 | C17: 4543 | D17: 4744 | E17: 5824 | F17: 19637 | G17: 7280 | H17: 5691 | I17: 5354.47 | J17: 6216.64 | K17: 24538.17 | L17: 5635.88 | M17: 5555.87 | N17: 5336.93 | O17: 6339.19 | P17: 22947.1 | Q17: 5919.24 | R17: 5793.92 | S17: 7333.92 | T17: 6597.59 | U17: 25598.38 | V17: 6174.86 | W17: 5911.73 | X17: 5715.53 | Y17: 6626.37 | Z17: 24645.34 | AA17: 7681.29 | AB17: 6219.54 | AC17: 5941.16 | AD17: 6787.1 | AE17: 26981.82
A18: Studios revenue- C&E | B18: 2826 | C18: 2432 | D18: 3000 | E18: 3027 | F18: 11285 | G18: 3426 | H18: 3040 | I18: 3076.95 | J18: 2850.41 | K18: 12393.31 | L18: 3315.37 | M18: 2890.23 | N18: 2955.27 | O18: 2891.25 | P18: 12275.58 | Q18: 3311.4 | R18: 2901.2 | S18: 3012.78 | T18: 2901.19 | U18: 12477.92 | V18: 3315.24 | W18: 2910.11 | X18: 2980.13 | Y18: 2959.95 | Z18: 12617.21 | AA18: 3365.89 | AB18: 2940.47 | AC18: 3023.62 | AD18: 3010.68 | AE18: 12835.6
A19: Theme parks revenue - C&E | B19: 1876 | C19: 2349 | D19: 2717 | E19: 2893 | F19: 9835 | G19: 2331 | H19: 2413 | I19: 2668.31 | J19: 2900.11 | K19: 10312.42 | L19: 2408.43 | M19: 2537.19 | N19: 2810.63 | O19: 3004.53 | P19: 10814.9 | Q19: 2527.02 | R19: 2640.61 | S19: 2944.93 | T19: 3183.8 | U19: 11258.87 | V19: 2632.84 | W19: 2751.09 | X19: 3068.64 | Y19: 3332.35 | Z19: 11666.42 | AA19: 2749.5 | AB19: 2872.95 | AC19: 3204.07 | AD19: 3479.01 | AE19: 12133.33
A20: Headquarters and others revenue - C&E | B20: 11 | C20: 9 | D20: 15 | E20: 11 | F20: 46 | G20: 15 | H20: 18 | I20: 15.03 | J20: 12.93 | K20: 61.05 | L20: 15.31 | M20: 17.45 | N20: 16.01 | O20: 13.35 | P20: 60.66 | Q20: 15.33 | R20: 17.05 | S20: 15.98 | T20: 13.8 | U20: 60.87 | V20: 15.41 | W20: 17.42 | X20: 16.18 | Y20: 13.62 | Z20: 61.43 | AA20: 15.43 | AB20: 17.46 | AC20: 16.22 | AD20: 13.65 | AE20: 62.21
A21: Eliminations revenue - C&E | B21: -694 | C21: -604 | D21: -579 | E21: -815 | F21: -2692 | G21: -1111 | H21: -435 | I21: -595.38 | J21: -785.13 | K21: -2926.47 | L21: -830.69 | M21: -502.93 | N21: -572.71 | O21: -789.19 | P21: -2737.3 | Q21: -858.79 | R21: -543.83 | S21: -621.84 | T21: -864.81 | U21: -2820.71 | V21: -899.27 | W21: -568.51 | X21: -599.4 | Y21: -880.51 | Z21: -2837.37 | AA21: -933.83 | AB21: -576.62 | AC21: -608.17 | AD21: -893.27 | AE21: -2908.28
A22: Headquarters, other and elimination revenue - C&E | B22: -683 | C22: -595 | D22: -564 | E22: -804 | F22: -2646 | G22: -1096 | H22: -417 | I22: -580.49 | J22: -778.73 | K22: -2872.12 | L22: -860.28 | M22: -473.29 | N22: -562.71 | O22: -788.68 | P22: -2721.83 | Q22: -878.47 | R22: -514.85 | S22: -617.14 | T22: -858.8 | U22: -2823.26 | V22: -922.17 | W22: -535.33 | X22: -592.6 | Y22: -875.9 | Z22: -2859.44 | AA22: -970.07 | AB22: -546.14 | AC22: -604.19 | AD22: -890.62 | AE22: -2945.22
A23: Total content and experiences revenue | B23: 8546 | C23: 8728 | D23: 9897 | E23: 10941 | F23: 38114 | G23: 11941 | H23: 10728 | I23: 10519.29 | J23: 11188.49 | K23: 44372.14 | L23: 10500.26 | M23: 10471.82 | N23: 10540.21 | O23: 11446.38 | P23: 43316.08 | Q23: 10879.31 | R23: 10821.01 | S23: 12674.61 | T23: 11823.91 | U23: 46512.26 | V23: 11200.91 | W23: 11037.75 | X23: 11171.84 | Y23: 12042.92 | Z23: 46069.93 | AA23: 12826.75 | AB23: 11486.95 | AC23: 11564.81 | AD23: 12386.32 | AE23: 49005.92
A25: Content & experiences Adjusted EBITDA
A26: Media - C&E - Adjusted EBITDA | B26: 108 | C26: 683 | D26: 247 | E26: -872 | F26: 165 | G26: -425 | H26: 708 | I26: 595.67 | J26: -425.98 | K26: 424.67 | L26: -166.25 | M26: 696.53 | N26: 630.98 | O26: -276.04 | P26: 804.42 | Q26: -71.93 | R26: 826.67 | S26: 824.31 | T26: -179.64 | U26: 1328.02 | V26: -30.34 | W26: 866.26 | X26: 873.83 | Y26: -109.42 | Z26: 1550.88 | AA26: 29.53 | AB26: 988.79 | AC26: 957.74 | AD26: -5.87 | AE26: 1976.5
A27: Studios - C&E - Adjusted EBITDA | B27: 274 | C27: 61 | D27: 338 | E27: 327 | F27: 1000 | G27: 555 | H27: 202 | I27: 400.42 | J27: 263.9 | K27: 1420.69 | L27: 406.25 | M27: 218.6 | N27: 345.25 | O27: 284.11 | P27: 1259.64 | Q27: 440.96 | R27: 201.79 | S27: 366.92 | T27: 266.15 | U27: 1269.58 | V27: 421.19 | W27: 212.72 | X27: 334.13 | Y27: 284.78 | Z27: 1267.36 | AA27: 419.02 | AB27: 114.14 | AC27: 325.35 | AD27: 284.48 | AE27: 1256.35
A28: Theme parks - C&E- Adjusted EBITDA | B28: 413 | C28: 641.4 | D28: 940.4 | E28: 1019 | F28: 3013 | G28: 551 | H28: 608 | I28: 789.64 | J28: 958.67 | K28: 2907.68 | L28: 585.03 | M28: 681.72 | N28: 869.65 | O28: 1017.77 | P28: 3175.06 | Q28: 618.06 | R28: 703.88 | S28: 918.91 | T28: 1081.47 | U28: 3326.18 | V28: 639.78 | W28: 733.72 | X28: 952.38 | Y28: 1124.27 | Z28: 3428.3 | AA28: 665.62 | AB28: 770.94 | AC28: 996.74 | AD28: 1172.68 | AE28: 3570.93
A29: Headquarters and Other - C&E - Adjusted EBITDA | B29: -195 | C29: -201 | D29: -204 | E29: -245 | F29: -845 | G29: -208 | H29: -214 | I29: -202.02 | J29: -226.81 | K29: -851.29 | L29: -208.92 | M29: -227.02 | N29: -200.24 | O29: -224.76 | P29: -848.34 | Q29: -199.67 | R29: -204.33 | S29: -195.94 | T29: -216.17 | U29: -833.67 | V29: -202.4 | W29: -202.6 | X29: -198.4 | Y29: -215.6 | Z29: -840.43 | AA29: -203.4 | AB29: -203.6 | AC29: -199.4 | AD29: -216.6 | AE29: -853.62
A30: Eliminations - C&E - Adjusted EBITDA | B30: 14 | C30: 56 | D30: 69 | E30: 47 | F30: 186 | G30: -140 | H30: 25 | I30: 33.76 | J30: 25.55 | K30: -64.33 | L30: -49.21 | M30: 22.05 | N30: 25.31 | O30: 11.09 | P30: 2.23 | Q30: -56.94 | R30: 22.66 | S30: 28.9 | T30: 17.4 | U30: 4.44 | V30: -53 | W30: 39.7 | X30: 47.03 | Y30: 39.69 | Z30: 51.38 | AA30: -51.07 | AB30: 43.6 | AC30: 50.45 | AD30: 42.38 | AE30: 61.32
A31: Headquarters, other and elimination - C&E - Adjusted EBITDA | B31: -181 | C31: -144 | D31: -135 | E31: -199 | F31: -659 | G31: -348 | H31: -190 | I31: -175.96 | J31: -214.79 | K31: -928.91 | L31: -250.24 | M31: -207.55 | N31: -183.91 | O31: -231.53 | P31: -878.02 | Q31: -252.21 | R31: -187.92 | S31: -176.79 | T31: -222.07 | U31: -880.57 | V31: -251.97 | W31: -174.39 | X31: -166.47 | Y31: -208.64 | Z31: -874.66 | AA31: -252.74 | AB31: -173.09 | AC31: -165.62 | AD31: -209.04 | AE31: -894.58
A32: Total Content and experiences - Adjusted EBITDA | B32: 614 | C32: 1241 | D32: 1392 | E32: 275 | F32: 3521 | G32: 331 | H32: 1329 | I32: 1609.76 | J32: 581.84 | K32: 3848.34 | L32: 566.37 | M32: 1339.86 | N32: 1661.17 | O32: 796 | P32: 4357.17 | Q32: 721.96 | R32: 1475.83 | S32: 1931.16 | T32: 946.86 | U32: 5038.68 | V32: 763.26 | W32: 1561.51 | X32: 1989.69 | Y32: 1089.93 | Z32: 5365.75 | AA32: 845.54 | AB32: 1697.39 | AC32: 2109.68 | AD32: 1241.02 | AE32: 5903.78
A34: Media
A35: Domestic advertising revenue | B35: 1468 | C35: 1395 | D35: 1556 | E35: 2294 | F35: 6713 | G35: 3453 | H35: 2163 | I35: 1784.56 | J35: 2384.63 | K35: 9642.91 | L35: 1749.68 | M35: 1762.49 | N35: 1612.38 | O35: 2350.69 | P35: 7702.54 | Q35: 1824.81 | R35: 1840.59 | S35: 3176.23 | T35: 2385.45 | U35: 9234.04 | V35: 1971.16 | W35: 1854.8 | X35: 1671.5 | Y35: 2331.53 | Z35: 8106.25 | AA35: 3274.16 | AB35: 2060.58 | AC35: 1790.59 | AD35: 2367.29 | AE35: 9663.15
A36: Domestic distribution revenue | B36: 1667 | C36: 1632 | D36: 1690 | E36: 1876 | F36: 6865 | G36: 2283 | H36: 1993 | I36: 1994.59 | J36: 2118.49 | K36: 8373.66 | L36: 2310.35 | M36: 2169.79 | N36: 2150.7 | O36: 2275.25 | P36: 8763.99 | Q36: 2467.12 | R36: 2298.06 | S36: 2499.81 | T36: 2420.51 | U36: 9566.71 | V36: 2561.19 | W36: 2383.17 | X36: 2366.59 | Y36: 2485.93 | Z36: 9748.04 | AA36: 2754.67 | AB36: 2473.39 | AC36: 2453.02 | AD36: 2576.99 | AE36: 10295.4
A37: International networks revenue | B37: 1148 | C37: 1254 | D37: 1239 | E37: 1283 | F37: 4924 | G37: 1291 | H37: 1330 | I37: 1301.98 | J37: 1328.74 | K37: 5251.74 | L37: 1302.48 | M37: 1370.1 | N37: 1324.6 | O37: 1355.68 | P37: 5337.15 | Q37: 1394.3 | R37: 1467.16 | S37: 1412.18 | T37: 1442.59 | U37: 5610.42 | V37: 1411.53 | W37: 1487.53 | X37: 1431.4 | Y37: 1459.79 | Z37: 5705.14 | AA37: 1424.22 | AB37: 1499.03 | AC37: 1443.17 | AD37: 1472.23 | AE37: 5790.31
A38: Other media revenue | B38: 244 | C38: 261 | D38: 259 | E38: 371 | F38: 1135 | G38: 253 | H38: 204 | I38: 259.39 | J38: 371.03 | K38: 1087.44 | L38: 257.81 | M38: 216.28 | N38: 268.37 | O38: 384.6 | P38: 1122.08 | Q38: 259.04 | R38: 209.12 | S38: 274.99 | T38: 390.59 | U38: 1134.8 | V38: 265.67 | W38: 214.2 | X38: 284.01 | Y38: 402.96 | Z38: 1157.37 | AA38: 264.57 | AB38: 216.25 | AC38: 295.4 | AD38: 430.41 | AE38: 1183.54
A39: Media revenue - C&E | B39: 4527 | C39: 4543 | D39: 4744 | E39: 5824 | F39: 19637 | G39: 7280 | H39: 5691 | I39: 5354.47 | J39: 6216.64 | K39: 24538.17 | L39: 5635.88 | M39: 5555.87 | N39: 5336.93 | O39: 6339.19 | P39: 22947.1 | Q39: 5919.24 | R39: 5793.92 | S39: 7333.92 | T39: 6597.59 | U39: 25598.38 | V39: 6174.86 | W39: 5911.73 | X39: 5715.53 | Y39: 6626.37 | Z39: 24645.34 | AA39: 7681.29 | AB39: 6219.54 | AC39: 5941.16 | AD39: 6787.1 | AE39: 26981.82
A40: Programming production - Media - Costs and exps excl. D&A | B40: 3283 | C40: 2759 | D40: 3359 | E40: 5280 | F40: 14681 | G40: 6304 | H40: 3699 | I40: 3509.51 | J40: 5224.4 | K40: 18736.83 | L40: 4392.09 | M40: 3483.55 | N40: 3407.58 | O40: 5234.67 | P40: 16778.64 | Q40: 4569.79 | R40: 3642.8 | S40: 5010.64 | T40: 5318.28 | U40: 18773.38 | V40: 4782.08 | W40: 3702.65 | X40: 3441.47 | Y40: 5300.63 | Z40: 17610.02 | AA40: 5908.28 | AB40: 3881.74 | AC40: 3558.19 | AD40: 5334.33 | AE40: 19166.88
A41: Marketing and promotion - Media - Costs and exps excl. D&A | B41: 306 | C41: 285 | D41: 287 | E41: 484 | F41: 1362 | G41: 404 | H41: 289 | I41: 292.51 | J41: 428.71 | K41: 1384.15 | L41: 342.3 | M41: 276.2 | N41: 290.47 | O41: 406.81 | P41: 1338.61 | Q41: 370.01 | R41: 296.7 | S41: 344.97 | T41: 430.35 | U41: 1453.22 | V41: 367.97 | W41: 300.13 | X41: 326.89 | Y41: 433.7 | Z41: 1454.15 | AA41: 391.26 | AB41: 305.35 | AC41: 331.93 | AD41: 439.88 | AE41: 1509.84
A42: Other - Media - Costs and exps excl. D&A | B42: 830 | C42: 816 | D42: 851 | E42: 932 | F42: 3429 | G42: 997 | H42: 994 | I42: 936.82 | J42: 963.25 | K42: 3891.07 | L42: 995.78 | M42: 992.06 | N42: 974.91 | O42: 995.8 | P42: 3943.27 | Q42: 1094.17 | R42: 1015.22 | S42: 1074.18 | T42: 1003.68 | U42: 4117.1 | V42: 1135.84 | W42: 1036.45 | X42: 1081.79 | Y42: 1007.66 | Z42: 4148.23 | AA42: 1178.2 | AB42: 1061.58 | AC42: 1154.84 | AD42: 1031.13 | AE42: 4325.9
A43: Media - Costs and exps excl. D&A | B43: 4419 | C43: 3860 | D43: 4497 | E43: 6696 | F43: 19472 | G43: 7705 | H43: 4982 | I43: 4750.97 | J43: 6610.39 | K43: 24042.3 | L43: 5793.45 | M43: 4839.25 | N43: 4705.95 | O43: 6615.22 | P43: 22071.5 | Q43: 5991.17 | R43: 4967.25 | S43: 6509.62 | T43: 6777.23 | U43: 24231.29 | V43: 6205.2 | W43: 5045.47 | X43: 4841.7 | Y43: 6735.79 | Z43: 23027.34 | AA43: 7651.75 | AB43: 5230.75 | AC43: 4983.41 | AD43: 6792.97 | AE43: 24855.51
A44: Media - C&E - Adjusted EBITDA | B44: 108 | C44: 683 | D44: 247 | E44: -872 | F44: 165 | G44: -425 | H44: 708 | I44: 595.67 | J44: -425.98 | K44: 424.67 | L44: -166.25 | M44: 696.53 | N44: 630.98 | O44: -276.04 | P44: 804.42 | Q44: -71.93 | R44: 826.67 | S44: 824.31 | T44: -179.64 | U44: 1328.02 | V44: -30.34 | W44: 866.26 | X44: 873.83 | Y44: -109.42 | Z44: 1550.88 | AA44: 29.53 | AB44: 988.79 | AC44: 957.74 | AD44: -5.87 | AE44: 1976.5
A46: Studios
A47: Content licensing revenue - Studios | B47: 2174 | C47: 1805 | D47: 2035 | E47: 2186 | F47: 8200 | G47: 2973 | H47: 1799 | I47: 1866.15 | J47: 2044.87 | K47: 8683.02 | L47: 2791.5 | M47: 1890.05 | N47: 1879.43 | O47: 2077.33 | P47: 8737.88 | Q47: 2782.63 | R47: 1941.57 | S47: 1895.61 | T47: 2111.87 | U47: 8904.49 | V47: 2779.07 | W47: 1984.41 | X47: 1940.44 | Y47: 2157.07 | Z47: 9075.75 | AA47: 2821.15 | AB47: 2018.16 | AC47: 1972.44 | AD47: 2193.99 | AE47: 9245.48
A48: Theatrical revenue - Studios | B48: 286 | C48: 284 | D48: 639 | E48: 411 | F48: 1620 | G48: 117 | H48: 972 | I48: 889.77 | J48: 351.09 | K48: 2329.86 | L48: 165.69 | M48: 735.52 | N48: 751.09 | O48: 373.67 | P48: 2166.57 | Q48: 186.48 | R48: 682.53 | S48: 800.49 | T48: 372.21 | U48: 2197.41 | V48: 193.19 | W48: 647.22 | X48: 724.51 | Y48: 388.53 | Z48: 2201.19 | AA48: 199.51 | AB48: 641.69 | AC48: 732.96 | AD48: 398.9 | AE48: 2246.13
A49: Other revenue - Studios | B49: 366 | C49: 343 | D49: 326 | E49: 430 | F49: 1465 | G49: 336 | H49: 269 | I49: 323.37 | J49: 423.88 | K49: 1352.25 | L49: 335.37 | M49: 274.23 | N49: 314.39 | O49: 410.73 | P49: 1343.5 | Q49: 342.29 | R49: 277.1 | S49: 316.69 | T49: 417.11 | U49: 1344.41 | V49: 342.98 | W49: 278.49 | X49: 315.18 | Y49: 414.35 | Z49: 1340.33 | AA49: 345.22 | AB49: 280.62 | AC49: 318.23 | AD49: 417.79 | AE49: 1344.06
A50: Studios revenue- C&E | B50: 2826 | C50: 2432 | D50: 3000 | E50: 3027 | F50: 11285 | G50: 3426 | H50: 3040 | I50: 3076.95 | J50: 2850.41 | K50: 12393.31 | L50: 3315.37 | M50: 2890.23 | N50: 2955.27 | O50: 2891.25 | P50: 12275.58 | Q50: 3311.4 | R50: 2901.2 | S50: 3012.78 | T50: 2901.19 | U50: 12477.92 | V50: 3315.24 | W50: 2910.11 | X50: 2980.13 | Y50: 2959.95 | Z50: 12617.21 | AA50: 3365.89 | AB50: 2940.47 | AC50: 3023.62 | AD50: 3010.68 | AE50: 12835.6
A51: Programming production - Studios - Costs and exps excl. D&A | B51: 1901 | C51: 1664 | D51: 1962 | E51: 1924 | F51: 7451 | G51: 2236 | H51: 2047 | I51: 1971.3 | J51: 1817.63 | K51: 8098.81 | L51: 2156.89 | M51: 1947.56 | N51: 1885.75 | O51: 1820.57 | P51: 7991.93 | Q51: 2144.04 | R51: 1957.73 | S51: 1927.67 | T51: 1848.5 | U51: 8160.22 | V51: 2148.18 | W51: 1952.56 | X51: 1916.52 | Y51: 1873.01 | Z51: 8290.55 | AA51: 2188.49 | AB51: 1991.3 | AC51: 1953.99 | AD51: 1908.3 | AE51: 8478.67
A52: Marketing and promotion - Studios - Costs and exps excl. D&A | B52: 392 | C52: 452 | D52: 436 | E52: 493 | F52: 1773 | G52: 373 | H52: 545 | I52: 436.22 | J52: 460.02 | K52: 1787.36 | L52: 434.28 | M52: 531.35 | N52: 442.31 | O52: 478.58 | P52: 1878.15 | Q52: 442.04 | R52: 552.7 | S52: 443.65 | T52: 495.83 | U52: 1905.38 | V52: 453.79 | W52: 555.31 | X52: 447.94 | Y52: 504.56 | Z52: 1931.15 | AA52: 461.26 | AB52: 566.28 | AC52: 456.84 | AD52: 514.08 | AE52: 1964.58
A53: Other - Studios - Costs and exps excl. D&A | B53: 259 | C53: 256 | D53: 264 | E53: 283 | F53: 1062 | G53: 262 | H53: 247 | I53: 266.63 | J53: 276.39 | K53: 1052.02 | L53: 277.99 | M53: 251.84 | N53: 267.06 | O53: 278.74 | P53: 1069.88 | Q53: 284.35 | R53: 256.9 | S53: 274.55 | T53: 290.71 | U53: 1088.13 | V53: 292.07 | W53: 263.35 | X53: 281.55 | Y53: 297.59 | Z53: 1110.96 | AA53: 297.12 | AB53: 268.75 | AC53: 287.44 | AD53: 303.83 | AE53: 1132.56
A54: Studios - Costs and exps excl. D&A | B54: 2552 | C54: 2372 | D54: 2662 | E54: 2700 | F54: 10286 | G54: 2871 | H54: 2839 | I54: 2670 | J54: 2575.71 | K54: 10955.66 | L54: 2895.15 | M54: 2718.15 | N54: 2610.02 | O54: 2607.14 | P54: 10993.9 | Q54: 2870.43 | R54: 2767.32 | S54: 2645.86 | T54: 2635.04 | U54: 11175.59 | V54: 2894.04 | W54: 2771.22 | X54: 2646 | Y54: 2675.17 | Z54: 11349.92 | AA54: 2946.86 | AB54: 2826.32 | AC54: 2698.28 | AD54: 2726.2 | AE54: 11579.32
A55: Studios - C&E - Adjusted EBITDA | B55: 274 | C55: 61 | D55: 338 | E55: 327 | F55: 1000 | G55: 555 | H55: 202 | I55: 400.42 | J55: 263.9 | K55: 1420.69 | L55: 406.25 | M55: 218.6 | N55: 345.25 | O55: 284.11 | P55: 1259.64 | Q55: 440.96 | R55: 201.79 | S55: 366.92 | T55: 266.15 | U55: 1269.58 | V55: 421.19 | W55: 212.72 | X55: 334.13 | Y55: 284.78 | Z55: 1267.36 | AA55: 419.02 | AB55: 114.14 | AC55: 325.35 | AD55: 284.48 | AE55: 1256.35
A57: Theme parks
A58: Theme parks revenue - C&E | B58: 1876 | C58: 2349 | D58: 2717 | E58: 2893 | F58: 9835 | G58: 2331 | H58: 2413 | I58: 2668.31 | J58: 2900.11 | K58: 10312.42 | L58: 2408.43 | M58: 2537.19 | N58: 2810.63 | O58: 3004.53 | P58: 10814.9 | Q58: 2527.02 | R58: 2640.61 | S58: 2944.93 | T58: 3183.8 | U58: 11258.87 | V58: 2632.84 | W58: 2751.09 | X58: 3068.64 | Y58: 3332.35 | Z58: 11666.42 | AA58: 2749.5 | AB58: 2872.95 | AC58: 3204.07 | AD58: 3479.01 | AE58: 12133.33
A59: Theme parks - C&E - Costs and exps excl. D&A | B59: 1463 | C59: 1708 | D59: 1777 | E59: 1874 | F59: 6822 | G59: 1780 | H59: 1805 | I59: 1880.17 | J59: 1939.1 | K59: 7404.21 | L59: 1822.28 | M59: 1858.31 | N59: 1940.99 | O59: 1986.77 | P59: 7634.38 | Q59: 1908.97 | R59: 1936.73 | S59: 2026.02 | T59: 2102.33 | U59: 7926 | V59: 1993.07 | W59: 2017.37 | X59: 2116.25 | Y59: 2208.08 | Z59: 8234.59 | AA59: 2083.88 | AB59: 2102 | AC59: 2207.33 | AD59: 2306.34 | AE59: 8556.63
A60: Theme parks - C&E- Adjusted EBITDA | B60: 413 | C60: 641.4 | D60: 940.4 | E60: 1019 | F60: 3013 | G60: 551 | H60: 608 | I60: 789.64 | J60: 958.67 | K60: 2907.68 | L60: 585.03 | M60: 681.72 | N60: 869.65 | O60: 1017.77 | P60: 3175.06 | Q60: 618.06 | R60: 703.88 | S60: 918.91 | T60: 1081.47 | U60: 3326.18 | V60: 639.78 | W60: 733.72 | X60: 952.38 | Y60: 1124.27 | Z60: 3428.3 | AA60: 665.62 | AB60: 770.94 | AC60: 996.74 | AD60: 1172.68 | AE60: 3570.93
A62: Theme parks - Prior to resegmentation
A63: Theme parks revenue - Prior to resegmentation | B63: 1876 | C63: 2349 | D63: 2717 | E63: 2893 | F63: 9116.53 | G63: 2331 | H63: 2413 | I63: 2635.49 | J63: 2835.14 | K63: 9534.36 | L63: 2307.69 | M63: 2413 | N63: 2819.97 | O63: 3005.25 | P63: 9649.3 | Q63: 2376.92 | R63: 2485.39 | S63: 2904.57 | T63: 3095.41 | U63: 9882.49 | V63: 2448.23 | W63: 2559.95 | X63: 2991.71 | Y63: 3250.18 | Z63: 10151.37 | AA63: 2521.68 | AB63: 2636.75 | AC63: 3081.46 | AD63: 3347.68 | AE63: 10395.12
A64: Theme parks - Costs and exp excl D&A - Prior to resegmentation | B64: 1463 | C64: 1708 | D64: 1777 | E64: 1874 | F64: 6082.15 | G64: 1780 | H64: 1804.5 | I64: 1802.68 | J64: 1896.45 | K64: 6345.52 | L64: 1770.68 | M64: 1804 | N64: 1901.93 | O64: 1931.74 | P64: 6605.14 | Q64: 1805.29 | R64: 1840.19 | S64: 1944.23 | T64: 1976.82 | U64: 6715 | V64: 1848.08 | W64: 1884.93 | X64: 1996.51 | Y64: 2069.69 | Z64: 6850.34 | AA64: 1892.14 | AB64: 1931.01 | AC64: 2050.36 | AD64: 2128.19 | AE64: 7001.36
A65: Theme parks - Adjusted EBITDA - Prior to resegmentation | B65: 413 | C65: 641 | D65: 940 | E65: 1019 | F65: 3214 | G65: 551 | H65: 609 | I65: 777.82 | J65: 922.8 | K65: 3323.72 | L65: 537.01 | M65: 609 | N65: 918.05 | O65: 1073.5 | P65: 3313.5 | Q65: 571.63 | R65: 645.2 | S65: 960.35 | T65: 1118.58 | U65: 3492.99 | V65: 600.15 | W65: 675.02 | X65: 995.2 | Y65: 1180.49 | Z65: 3676.71 | AA65: 629.53 | AB65: 705.74 | AC65: 1031.1 | AD65: 1219.49 | AE65: 3834.09
A67: Supplemental
A68: Headquarters and Other - C&E - Costs and exps excl. D&A | B68: 206 | C68: 210 | D68: 219 | E68: 257 | F68: 892 | G68: 223 | H68: 233 | I68: 219.1 | J68: 244.48 | K68: 919.58 | L68: 226.86 | M68: 259.1 | N68: 214.67 | O68: 235.76 | P68: 947.17 | Q68: 213 | R68: 219 | S68: 208.42 | T68: 227.75 | U68: 925.71 | V68: 217 | W68: 216 | X68: 211.67 | Y68: 225.67 | Z68: 948.28 | AA68: 218.67 | AB68: 217.67 | AC68: 213.33 | AD68: 227.33 | AE68: 965.1
A69: Eliminations - C&E - Costs and exps excl. D&A | B69: -708 | C69: -660 | D69: -648 | E69: -862 | F69: -2878 | G69: -970 | H69: -460 | I69: -659.27 | J69: -800.09 | K69: -2889.47 | L69: -730.9 | M69: -509.15 | N69: -650.65 | O69: -804.21 | P69: -2797.36 | Q69: -744.87 | R69: -525.5 | S69: -629.7 | T69: -847.17 | U69: -2880.01 | V69: -817.5 | W69: -605 | X69: -696.5 | Y69: -916.5 | Z69: -3003.32 | AA69: -830 | AB69: -617.5 | AC69: -709 | AD69: -929 | AE69: -3058.21

Sheet SPG Peacock
A2: Comcast Corporation | Peacock
A3: NASDAQGS:CMCSA (MI KEY: 4057180; SPCIQ KEY: 173341)
A5: Visible Alpha
A7: Period Type : Fiscal Quarter, Fiscal Halves, Fiscal Year
A8: Period Start : 2025
A9: Period End : 2030
A10: Currency : Reported
A11: Consensus View : Mean
A12: As Of: 10/20/2026
A14: All numbers in $M unless otherwise indicated | B14: FQ1 2025A | C14: FQ2 2025A | D14: FQ3 2025A | E14: FQ4 2025A | F14: FY2025A | G14: FQ1 2026A | H14: FQ2 2026A | I14: FQ3 2026E | J14: FQ4 2026E | K14: FY2026E | L14: FQ1 2027E | M14: FQ2 2027E | N14: FQ3 2027E | O14: FQ4 2027E | P14: FY2027E | Q14: FQ1 2028E | R14: FQ2 2028E | S14: FQ3 2028E | T14: FQ4 2028E | U14: FY2028E | V14: FQ1 2029E | W14: FQ2 2029E | X14: FQ3 2029E | Y14: FQ4 2029E | Z14: FY2029E | AA14: FQ1 2030E | AB14: FQ2 2030E | AC14: FQ3 2030E | AD14: FQ4 2030E | AE14: FY2030E
A15: Number of Contributors Available | B15: 22 | C15: 21 | D15: 21 | E15: 20 | F15: 21 | G15: 21 | H15: 20 | I15: 20 of 20 | J15: 20 of 20 | K15: 20 of 20 | L15: 12 of 20 | M15: 12 of 20 | N15: 11 of 20 | O15: 11 of 20 | P15: 20 of 20 | Q15: 8 of 20 | R15: 8 of 20 | S15: 8 of 20 | T15: 8 of 20 | U15: 19 of 20 | V15: 7 of 20 | W15: 7 of 20 | X15: 7 of 20 | Y15: 7 of 20 | Z15: 16 of 20 | AA15: 7 of 20 | AB15: 7 of 20 | AC15: 7 of 20 | AD15: 7 of 20 | AE15: 16 of 20
A16: Total sign-ups - Peacock(K#) | B16: 104485 | C16: 105785 | D16: 107085 | E16: 108385 | F16: 108385 | G16: 109685 | H16: 110985 | I16: 112285 | J16: 113585 | K16: 113585 | L16: 93270 | M16: 93370 | N16: 93470 | O16: 93570 | P16: 118785 | Q16: 93670 | R16: 93770 | S16: 93870 | T16: 93970 | U16: 123985 | V16: 94070 | W16: 94170 | X16: 94270 | Y16: 94370 | Z16: 94370 | AA16: 94470 | AB16: 94570 | AC16: 94670 | AD16: 94770 | AE16: 94770
A17: New sign-ups - Peacock(K#) | B17: 1300 | C17: 1300 | D17: 1300 | E17: 2500 | F17: 10000 | G17: 1300 | H17: 1300 | I17: 1300 | J17: 1300 | K17: 5200 | L17: 100 | M17: 100 | N17: 100 | O17: 100 | P17: 5200 | Q17: 100 | R17: 100 | S17: 100 | T17: 100 | U17: 5200 | V17: 100 | W17: 100 | X17: 100 | Y17: 100 | Z17: 400 | AA17: 100 | AB17: 100 | AC17: 100 | AD17: 100 | AE17: 400
A19: Ending subs - Premium peacock ad supported(K#) | B19: 32483.96 | C19: 32973.45 | D19: 32964.66 | E19: 35514.98 | F19: 35014.98 | G19: 37514.63 | H19: 39117.48 | I19: 39759.38 | J19: 41084.54 | K19: 40584.54 | L19: 36362.5 | M19: 36292.5 | N19: 36042.5 | O19: 35992.5 | P19: 43791.65 | Q19: 36192.5 | R19: 36342.5 | S19: 36392.5 | T19: 36542.5 | U19: 46428.42 | V19: 36792.5 | W19: 36942.5 | X19: 36992.5 | Y19: 37142.5 | Z19: 47978.34 | AA19: 37392.5 | AB19: 37542.5 | AC19: 37592.5 | AD19: 37742.5 | AE19: 50495.34
A20: Ending subs - Free Peacock(K#) | B20: 15900 | C20: 15950 | D20: 16000 | E20: 16050 | F20: 16050 | G20: 17050 | H20: 18050 | I20: 18100 | J20: 18150 | K20: 18150 | L20: 20150 | M20: 20250 | N20: 20350 | O20: 20450 | P20: 18350 | Q20: 20550 | R20: 20650 | S20: 20750 | T20: 20850 | U20: 18550 | V20: 20950 | W20: 21050 | X20: 21150 | Y20: 21250 | Z20: 21250 | AA20: 21350 | AB20: 21450 | AC20: 21550 | AD20: 21650 | AE20: 21650
A21: Ending MAUs - Ad supported - Peacock(K#) | B21: 42052.87 | C21: 42093.85 | D21: 42134.83 | E21: 44905.29 | F21: 44905.29 | G21: 47544.6 | H21: 49674.08 | I21: 50006.04 | J21: 50588.01 | K21: 50588.01 | L21: 43289.95 | M21: 43453.88 | N21: 43617.81 | O21: 43781.74 | P21: 52903.37 | Q21: 43945.67 | R21: 44109.6 | S21: 44273.53 | T21: 44437.46 | U21: 54721.86 | V21: 44601.39 | W21: 44765.32 | X21: 44929.25 | Y21: 45093.18 | Z21: 45093.18 | AA21: 45257.11 | AB21: 45421.04 | AC21: 45584.98 | AD21: 45748.91 | AE21: 45748.91
A22: Average MAU's Ad supported - Peacock(K#) | B22: 40212.72 | C22: 42073.36 | D22: 42114.34 | E22: 43520.06 | F22: 41638.94 | G22: 46224.95 | H22: 48609.34 | I22: 49840.06 | J22: 50297.03 | K22: 47746.65 | L22: 43207.98 | M22: 43371.91 | N22: 43535.84 | O22: 43699.77 | P22: 51745.69 | Q22: 43863.7 | R22: 44027.64 | S22: 44191.57 | T22: 44355.5 | U22: 53812.61 | V22: 44519.43 | W22: 44683.36 | X22: 44847.29 | Y22: 45011.22 | Z22: 44765.32 | AA22: 45175.15 | AB22: 45339.08 | AC22: 45503.01 | AD22: 45666.94 | AE22: 45421.04
A23: ARPU - MAU - Ad supported - Peacock($) | B23: 3.57 | C23: 3.5 | D23: 3.9 | E23: 4.46 | F23: 3.9 | G23: 6.67 | H23: 5.02 | I23: 4.65 | J23: 4.77 | K23: 5.38 | L23: 7.37 | M23: 5.4 | N23: 4.87 | O23: 5.85 | P23: 4.94 | Q23: 7.59 | R23: 5.62 | S23: 5.11 | T23: 6.14 | U23: 5.36 | V23: 7.82 | W23: 5.79 | X23: 5.11 | Y23: 6.14 | Z23: 6.21 | AA23: 8.13 | AB23: 6.02 | AC23: 5.32 | AD23: 6.45 | AE23: 6.48
A24: Peacock Advertising Revenue - Media | B24: 414 | C24: 427 | D24: 477 | E24: 564 | F24: 1882 | G24: 901 | H24: 717 | I24: 641.39 | J24: 673.39 | K24: 2932.79 | L24: 757.79 | M24: 697.3 | N24: 671.03 | O24: 720.11 | P24: 3037.48 | Q24: 826.6 | R24: 761.26 | S24: 928.93 | T24: 784.82 | U24: 3482.66 | V24: 878.47 | W24: 800.18 | X24: 785.76 | Y24: 832.89 | Z24: 3631.28 | AA24: 1065.15 | AB24: 882.87 | AC24: 852.22 | AD24: 887.66 | AE24: 3989.27
A26: Ending subs - Premium peacock ad supported(K#) | B26: 32483.96 | C26: 32973.45 | D26: 32964.66 | E26: 35514.98 | F26: 35014.98 | G26: 37514.63 | H26: 39117.48 | I26: 39759.38 | J26: 41084.54 | K26: 40584.54 | L26: 36362.5 | M26: 36292.5 | N26: 36042.5 | O26: 35992.5 | P26: 43791.65 | Q26: 36192.5 | R26: 36342.5 | S26: 36392.5 | T26: 36542.5 | U26: 46428.42 | V26: 36792.5 | W26: 36942.5 | X26: 36992.5 | Y26: 37142.5 | Z26: 47978.34 | AA26: 37392.5 | AB26: 37542.5 | AC26: 37592.5 | AD26: 37742.5 | AE26: 50495.34
A27: Ending subs - Premium plus Peacock Ad free(K#) | B27: 8516.04 | C27: 8039.05 | D27: 8047.84 | E27: 8516.27 | F27: 9016.27 | G27: 8541.62 | H27: 8913.77 | I27: 8878.14 | J27: 8966.67 | K27: 9660.42 | L27: 12962.5 | M27: 12757.5 | N27: 12732.5 | O27: 13007.5 | P27: 9279.27 | Q27: 13157.5 | R27: 13107.5 | S27: 13157.5 | T27: 13357.5 | U27: 9907.63 | V27: 13457.5 | W27: 13407.5 | X27: 13457.5 | Y27: 13657.5 | Z27: 9725.44 | AA27: 13757.5 | AB27: 13707.5 | AC27: 13757.5 | AD27: 13957.5 | AE27: 9907.01
A28: Ending paid subs - Peacock(K#) | B28: 41000 | C28: 41000 | D28: 41000 | E28: 44000 | F28: 44000 | G28: 46000 | H28: 48000 | I28: 48221.88 | J28: 49419.05 | K28: 49467.49 | L28: 50338.89 | M28: 50756.67 | N28: 50665.44 | O28: 51510.57 | P28: 53379.92 | Q28: 52623.2 | R28: 53127.13 | S28: 53124.42 | T28: 53903.22 | U28: 55831.38 | V28: 55299.03 | W28: 55683.13 | X28: 55833.67 | Y28: 56514.02 | Z28: 58173.93 | AA28: 57296.62 | AB28: 57502.44 | AC28: 57522.14 | AD28: 58152.04 | AE28: 60193.79
A29: Ending subs - Free Peacock(K#) | B29: 15900 | C29: 15950 | D29: 16000 | E29: 16050 | F29: 16050 | G29: 17050 | H29: 18050 | I29: 18100 | J29: 18150 | K29: 18150 | L29: 20150 | M29: 20250 | N29: 20350 | O29: 20450 | P29: 18350 | Q29: 20550 | R29: 20650 | S29: 20750 | T29: 20850 | U29: 18550 | V29: 20950 | W29: 21050 | X29: 21150 | Y29: 21250 | Z29: 21250 | AA29: 21350 | AB29: 21450 | AC29: 21550 | AD29: 21650 | AE29: 21650
A30: Ending subs - Peacock(K#) | B30: 47515.33 | C30: 47552.83 | D30: 47577.83 | E30: 49871.58 | F30: 48722.26 | G30: 51421.58 | H30: 52921.58 | I30: 53340.33 | J30: 53884.08 | K30: 52274.76 | L30: 51805.65 | M30: 52355.65 | N30: 52905.65 | O30: 53455.65 | P30: 58481.01 | Q30: 54505.65 | R30: 55055.65 | S30: 55605.65 | T30: 56155.65 | U30: 60819.05 | V30: 57205.65 | W30: 57755.65 | X30: 58305.65 | Y30: 58855.65 | Z30: 58881.45 | AA30: 59905.65 | AB30: 60455.65 | AC30: 61005.65 | AD30: 61555.65 | AE30: 60710.93
A32: Net adds - Paid subs - Peacock(K#) | B32: 5000 | C32: 50 | D32: - | E32: 3000 | F32: 8000 | G32: 2000 | H32: 2000 | I32: 285.42 | J32: 1368.19 | K32: 5334.68 | L32: 1107.14 | M32: 537.14 | N32: -117.29 | O32: 950.76 | P32: 4173.26 | Q32: 912.93 | R32: 671.91 | S32: -3.62 | T32: 778.81 | U32: 2614.88 | V32: 838.2 | W32: 537.74 | X32: 210.76 | Y32: 680.35 | Z32: 2376.09 | AA32: 782.6 | AB32: 240.13 | AC32: 22.98 | AD32: 568.22 | AE32: 2356.5
A33: Ending paid subs - Peacock(K#) | B33: 41000 | C33: 41000 | D33: 41000 | E33: 44000 | F33: 44000 | G33: 46000 | H33: 48000 | I33: 48221.88 | J33: 49419.05 | K33: 49467.49 | L33: 50338.89 | M33: 50756.67 | N33: 50665.44 | O33: 51510.57 | P33: 53379.92 | Q33: 52623.2 | R33: 53127.13 | S33: 53124.42 | T33: 53903.22 | U33: 55831.38 | V33: 55299.03 | W33: 55683.13 | X33: 55833.67 | Y33: 56514.02 | Z33: 58173.93 | AA33: 57296.62 | AB33: 57502.44 | AC33: 57522.14 | AD33: 58152.04 | AE33: 60193.79
A34: Average paid subs - Peacock(K#) | B34: 38500 | C34: 41000 | D34: 41000 | E34: 42500 | F34: 40000 | G34: 45000 | H34: 47000 | I34: 48114.85 | J34: 48820.47 | K34: 47025.49 | L34: 49908.33 | M34: 50547.78 | N34: 50711.06 | O34: 51088.01 | P34: 51520.16 | Q34: 52223.79 | R34: 52875.16 | S34: 53125.77 | T34: 53513.82 | U34: 54699.92 | V34: 54879.93 | W34: 55491.08 | X34: 55758.4 | Y34: 56173.85 | Z34: 57176.84 | AA34: 56905.32 | AB34: 57399.53 | AC34: 57512.29 | AD34: 57837.09 | AE34: 59288.88
A36: Net adds - Peacock(K#) | B36: 3775 | C36: 75 | D36: 100 | E36: 3025 | F36: 6500 | G36: 1550 | H36: 1500 | I36: 558.33 | J36: 725 | K36: 3552.5 | L36: 1050 | M36: 550 | N36: 550 | O36: 550 | P36: 6206.25 | Q36: 1050 | R36: 550 | S36: 550 | T36: 550 | U36: 2338.04 | V36: 1050 | W36: 550 | X36: 550 | Y36: 550 | Z36: 1859.2 | AA36: 1050 | AB36: 550 | AC36: 550 | AD36: 550 | AE36: 1829.48
A37: Ending subs - Peacock(K#) | B37: 47515.33 | C37: 47552.83 | D37: 47577.83 | E37: 49871.58 | F37: 48722.26 | G37: 51421.58 | H37: 52921.58 | I37: 53340.33 | J37: 53884.08 | K37: 52274.76 | L37: 51805.65 | M37: 52355.65 | N37: 52905.65 | O37: 53455.65 | P37: 58481.01 | Q37: 54505.65 | R37: 55055.65 | S37: 55605.65 | T37: 56155.65 | U37: 60819.05 | V37: 57205.65 | W37: 57755.65 | X37: 58305.65 | Y37: 58855.65 | Z37: 58881.45 | AA37: 59905.65 | AB37: 60455.65 | AC37: 61005.65 | AD37: 61555.65 | AE37: 60710.93
A38: Average subs - Peacock(K#) | B38: 45419.49 | C38: 47534.08 | D38: 47565.33 | E38: 48724.7 | F38: 46438.93 | G38: 50563.24 | H38: 52171.58 | I38: 53130.95 | J38: 53612.2 | K38: 50755.18 | L38: 51113.99 | M38: 52080.65 | N38: 52630.65 | O38: 53180.65 | P38: 55584.55 | Q38: 53813.99 | R38: 54780.65 | S38: 55330.65 | T38: 55880.65 | U38: 59856.7 | V38: 56513.99 | W38: 57480.65 | X38: 58030.65 | Y38: 58580.65 | Z38: 58210.19 | AA38: 59213.99 | AB38: 60180.65 | AC38: 60730.65 | AD38: 61280.65 | AE38: 60054.53
A39: Blended ARPU - Peacock($) | B39: 9.86 | C39: 9.45 | D39: 10.45 | E39: 12.14 | F39: 10.58 | G39: 15 | H39: 13.11 | I39: 12.79 | J39: 13.12 | K39: 13.74 | L39: 15.12 | M39: 14.61 | N39: 14.65 | O39: 15.31 | P39: 14.26 | Q39: 15.75 | R39: 15.25 | S39: 16.98 | T39: 16.05 | U39: 15.17 | V39: 16.9 | W39: 15.8 | X39: 15.79 | Y39: 16.49 | Z39: 16.5 | AA39: 18.59 | AB39: 16.73 | AC39: 16.6 | AD39: 17.18 | AE39: 17.46
A40: Streaming - Peacock revenue | B40: 1226 | C40: 1232 | D40: 1363 | E40: 1628 | F40: 5449 | G40: 2099 | H40: 1895 | I40: 1853.56 | J40: 2014.04 | K40: 7861.6 | L40: 2201.95 | M40: 2089.96 | N40: 2080.62 | O40: 2241.22 | P40: 8763.15 | Q40: 2430 | R40: 2299.73 | S40: 2486.67 | T40: 2465.75 | U40: 9879.97 | V40: 2601.55 | W40: 2441.77 | X40: 2447.87 | Y40: 2610.06 | Z40: 10567.42 | AA40: 2922.68 | AB40: 2647.11 | AC40: 2633.82 | AD40: 2789.32 | AE40: 11479.93
A42: Peacock Advertising Revenue - Media | B42: 414 | C42: 427 | D42: 477 | E42: 564 | F42: 1882 | G42: 901 | H42: 717 | I42: 641.39 | J42: 673.39 | K42: 2932.79 | L42: 757.79 | M42: 697.3 | N42: 671.03 | O42: 720.11 | P42: 3037.48 | Q42: 826.6 | R42: 761.26 | S42: 928.93 | T42: 784.82 | U42: 3482.66 | V42: 878.47 | W42: 800.18 | X42: 785.76 | Y42: 832.89 | Z42: 3631.28 | AA42: 1065.15 | AB42: 882.87 | AC42: 852.22 | AD42: 887.66 | AE42: 3989.27
A43: Peacock Distribution Revenue - Media | B43: 763 | C43: 759 | D43: 843 | E43: 1013 | F43: 3378 | G43: 1151 | H43: 1155 | I43: 1169.5 | J43: 1292.6 | K43: 4768.1 | L43: 1365.64 | M43: 1334.39 | N43: 1333.94 | O43: 1442.22 | P43: 5485.98 | Q43: 1517.48 | R43: 1476.71 | S43: 1475.14 | T43: 1594.67 | U43: 6153.49 | V43: 1629.55 | W43: 1574.01 | X43: 1571.74 | Y43: 1683.45 | Z43: 6672.01 | AA43: 1760.76 | AB43: 1694.76 | AC43: 1688.19 | AD43: 1804.7 | AE43: 7215.17
A44: Peacock Other Revenue - Media | B44: 49 | C44: 46 | D44: 43 | E44: 51 | F44: 189 | G44: 47 | H44: 23 | I44: 42.79 | J44: 48.02 | K44: 160.81 | L44: 78.53 | M44: 58.28 | N44: 75.65 | O44: 78.89 | P44: 243.98 | Q44: 85.91 | R44: 61.76 | S44: 82.6 | T44: 86.26 | U44: 247.23 | V44: 93.52 | W44: 67.58 | X44: 90.37 | Y44: 93.72 | Z44: 268.13 | AA44: 96.76 | AB44: 69.48 | AC44: 93.41 | AD44: 96.95 | AE44: 278.75
A45: Streaming - Peacock revenue | B45: 1226 | C45: 1232 | D45: 1363 | E45: 1628 | F45: 5449 | G45: 2099 | H45: 1895 | I45: 1853.56 | J45: 2014.04 | K45: 7861.6 | L45: 2201.95 | M45: 2089.96 | N45: 2080.62 | O45: 2241.22 | P45: 8763.15 | Q45: 2430 | R45: 2299.73 | S45: 2486.67 | T45: 2465.75 | U45: 9879.97 | V45: 2601.55 | W45: 2441.77 | X45: 2447.87 | Y45: 2610.06 | Z45: 10567.42 | AA45: 2922.68 | AB45: 2647.11 | AC45: 2633.82 | AD45: 2789.32 | AE45: 11479.93
A46: Programming and production - Peacock | B46: 976 | C46: 883 | D46: 1115 | E46: 1552 | F46: 4526 | G46: 1945 | H46: 1184 | I46: 1194.97 | J46: 1580.49 | K46: 5904.46 | L46: 1831.2 | M46: 1249.61 | N46: 1258.05 | O46: 1667.48 | P46: 6090.14 | Q46: 1951.11 | R46: 1320.33 | S46: 1589.26 | T46: 1767.05 | U46: 6636.7 | V46: 2082.55 | W46: 1391.2 | X46: 1394.13 | Y46: 1826.5 | Z46: 6796.51 | AA46: 2219.11 | AB46: 1457.92 | AC46: 1460.1 | AD46: 1913.77 | AE46: 7169.45
... A49: Streaming EBITDA - Peacock | B49: -214 | C49: -101 | D49: -217 | E49: -552 | F49: -1084 | G49: -432 | H49: 189 | I49: 181.39 | J49: -175.06 | K49: -232.35 | L49: -200.59 | M49: 327.8 | N49: 324.36 | O49: -40.36 | P49: 359.59 | Q49: -108.03 | R49: 451.28 | S49: 372.83 | T49: 72.17 | U49: 799.19 | V49: -67.97 | W49: 521.43 | X49: 534.41 | Y49: 160.99 | Z49: 1129.43 | AA49: 99.78 | AB49: 645.49 | AC49: 640.15 | AD49: 235.09 | AE49: 1450.59

Sheet SPG Wireless
A2: Comcast Corporation | Wireless
A3: NASDAQGS:CMCSA (MI KEY: 4057180; SPCIQ KEY: 173341)
A5: Visible Alpha
A7: Period Type : Fiscal Quarter, Fiscal Halves, Fiscal Year
A8: Period Start : 2025
A9: Period End : 2030
A10: Currency : Reported
A11: Consensus View : Mean
A12: As Of: 10/20/2026
A14: All numbers in $M unless otherwise indicated | B14: FQ1 2025A | C14: FQ2 2025A | D14: FQ3 2025A | E14: FQ4 2025A | F14: FY2025A | G14: FQ1 2026A | H14: FQ2 2026A | I14: FQ3 2026E | J14: FQ4 2026E | K14: FY2026E | L14: FQ1 2027E | M14: FQ2 2027E | N14: FQ3 2027E | O14: FQ4 2027E | P14: FY2027E | Q14: FQ1 2028E | R14: FQ2 2028E | S14: FQ3 2028E | T14: FQ4 2028E | U14: FY2028E | V14: FQ1 2029E | W14: FQ2 2029E | X14: FQ3 2029E | Y14: FQ4 2029E | Z14: FY2029E | AA14: FQ1 2030E | AB14: FQ2 2030E | AC14: FQ3 2030E | AD14: FQ4 2030E | AE14: FY2030E
A15: Number of Contributors Available | B15: 22 | C15: 21 | D15: 21 | E15: 20 | F15: 21 | G15: 21 | H15: 20 | I15: 20 of 20 | J15: 20 of 20 | K15: 20 of 20 | L15: 12 of 20 | M15: 12 of 20 | N15: 11 of 20 | O15: 11 of 20 | P15: 20 of 20 | Q15: 8 of 20 | R15: 8 of 20 | S15: 8 of 20 | T15: 8 of 20 | U15: 19 of 20 | V15: 7 of 20 | W15: 7 of 20 | X15: 7 of 20 | Y15: 7 of 20 | Z15: 16 of 20 | AA15: 7 of 20 | AB15: 7 of 20 | AC15: 7 of 20 | AD15: 7 of 20 | AE15: 16 of 20
A16: Beginning - Domestic wireless subscribers(K#) | B16: 7826 | C16: 8148 | D16: 8527 | E16: 8941 | F16: 7826 | G16: 9305 | H16: 9739 | I16: 10187.08 | J16: 10585.54 | K16: 9304.94 | L16: 10970.3 | M16: 11352.17 | N16: 11741.5 | O16: 12118.03 | P16: 10972.49 | Q16: 12468.98 | R16: 12823.06 | S16: 13200.51 | T16: 13557.76 | U16: 12479.19 | V16: 13904.77 | W16: 14235.31 | X16: 14601.13 | Y16: 14942.62 | Z16: 13860.71 | AA16: 15274.73 | AB16: 15593.72 | AC16: 15951.35 | AD16: 16288.43 | AE16: 15130.43
A17: Gross adds - Domestic wireless subscribers(K#) | B17: 625.89 | C17: 696.78 | D17: 695.87 | E17: 714.9 | F17: 2776.82 | G17: 791.53 | H17: 824.17 | I17: 795.99 | J17: 803.64 | K17: 3215.33 | L17: 775.71 | M17: 830.43 | N17: 815.09 | O17: 841.92 | P17: 3353.21 | Q17: 790.01 | R17: 867.91 | S17: 849.77 | T17: 877.87 | U17: 3181.33 | V17: 820.56 | W17: 904.37 | X17: 883.56 | Y17: 912.82 | Z17: 3641.85 | AA17: 864.85 | AB17: 955.04 | AC17: 932.2 | AD17: 963.27 | AE17: 3800.68
A18: Disconnects - Domestic wireless subscribers(K#) | B18: 303.28 | C18: 318.33 | D18: 281.87 | E18: 350.96 | F18: 1297.82 | G18: 356.92 | H18: 376.22 | I18: 394.77 | J18: 416.13 | K18: 1346.47 | L18: 410.01 | M18: 423.49 | N18: 438.36 | O18: 470.1 | P18: 1793.67 | Q18: 464.11 | R18: 476.07 | S18: 490.37 | T18: 523.23 | U18: 1726.08 | V18: 514.68 | W18: 525.89 | X18: 539.69 | Y18: 573.6 | Z18: 2271.29 | AA18: 562.68 | AB18: 573.8 | AC18: 587.71 | AD18: 623.36 | AE18: 2494.19
A19: Churn rate - Domestic wireless(%) | B19: 0.0133 | C19: 0.0133 | D19: 0.0111 | E19: 0.0134 | F19: 0.0129 | G19: 0.0131 | H19: 0.0131 | I19: 0.0132 | J19: 0.0134 | K19: 0.013 | L19: 0.0123 | M19: 0.0123 | N19: 0.0123 | O19: 0.0128 | P19: 0.0133 | Q19: 0.0122 | R19: 0.0122 | S19: 0.0122 | T19: 0.0127 | U19: 0.0107 | V19: 0.0122 | W19: 0.0122 | X19: 0.0122 | Y19: 0.0127 | Z19: 0.0135 | AA19: 0.0122 | AB19: 0.0122 | AC19: 0.0122 | AD19: 0.0126 | AE19: 0.0136
A20: Total domestic wireless line net additions (losses)(K#) | B20: 322 | C20: 379 | D20: 414 | E20: 364 | F20: 1479 | G20: 434 | H20: 448 | I20: 399.29 | J20: 386.04 | K20: 1667.8 | L20: 381.87 | M20: 389.33 | N20: 376.53 | O20: 362.86 | P20: 1517.66 | Q20: 354.08 | R20: 377.45 | S20: 357.25 | T20: 341.04 | U20: 1381.28 | V20: 330.54 | W20: 365.82 | X20: 341.49 | Y20: 332.11 | Z20: 1269.72 | AA20: 319 | AB20: 357.62 | AC20: 337.08 | AD20: 325.72 | AE20: 1193.98
A21: Total domestic wireless lines(K#) | B21: 8148 | C21: 8527 | D21: 8941 | E21: 9305 | F21: 9305 | G21: 9739 | H21: 10187 | I21: 10586.4 | J21: 10972.44 | K21: 10972.49 | L21: 11352.17 | M21: 11741.5 | N21: 12118.03 | O21: 12480.89 | P21: 12490.77 | Q21: 12823.06 | R21: 13200.51 | S21: 13557.76 | T21: 13898.8 | U21: 13860.48 | V21: 14235.31 | W21: 14601.13 | X21: 14942.62 | Y21: 15274.73 | Z21: 15130.43 | AA21: 15593.72 | AB21: 15951.35 | AC21: 16288.43 | AD21: 16614.15 | AE21: 16324.41
A22: Avg total domestic wireless lines(K#) | B22: 7987 | C22: 8337.5 | D22: 8733.5 | E22: 9123 | F22: 8565.5 | G22: 9522 | H22: 9963 | I22: 10386.31 | J22: 10777.86 | K22: 10144.86 | L22: 11161.24 | M22: 11546.84 | N22: 11929.77 | O22: 12299.46 | P22: 11733.84 | Q22: 12646.02 | R22: 13011.78 | S22: 13379.13 | T22: 13728.28 | U22: 13171.84 | V22: 14070.04 | W22: 14418.22 | X22: 14771.88 | Y22: 15108.68 | Z22: 14497.69 | AA22: 15434.23 | AB22: 15772.54 | AC22: 16119.89 | AD22: 16451.29 | AE22: 15729.52
A23: Average monthly total domestic wireless revenue per subscriber($) | B23: 46.87 | C23: 47.78 | D23: 47.56 | E23: 51.26 | F23: 48.32 | G23: 48.83 | H23: 47.21 | I23: 46.51 | J23: 49.6 | K23: 48.12 | L23: 47.14 | M23: 46.42 | N23: 45.7 | O23: 48.47 | P23: 47.21 | Q23: 47.16 | R23: 46.49 | S23: 45.86 | T23: 48.49 | U23: 46.76 | V23: 47.06 | W23: 46.3 | X23: 45.96 | Y23: 48.51 | Z23: 46.71 | AA23: 47.38 | AB23: 46.53 | AC23: 46.22 | AD23: 48.65 | AE23: 46.87
A24: Domestic wireless revenue | B24: 1123 | C24: 1195 | D24: 1246 | E24: 1403 | F24: 4967 | G24: 1395 | H24: 1411 | I24: 1450.07 | J24: 1606.28 | K24: 5861.71 | L24: 1579.24 | M24: 1606.7 | N24: 1635.53 | O24: 1788.53 | P24: 6647.92 | Q24: 1789.19 | R24: 1814.69 | S24: 1840.72 | T24: 1997.6 | U24: 7387.21 | V24: 1987.02 | W24: 2003.07 | X24: 2037.68 | Y24: 2199.91 | Z24: 8130.32 | AA24: 2194.91 | AB24: 2202.83 | AC24: 2236.92 | AD24: 2403.21 | AE24: 8856.12
A26: Avg total domestic wireless lines(K#) | B26: 7987 | C26: 8337.5 | D26: 8733.5 | E26: 9123 | F26: 8565.5 | G26: 9522 | H26: 9963 | I26: 10386.31 | J26: 10777.86 | K26: 10144.86 | L26: 11161.24 | M26: 11546.84 | N26: 11929.77 | O26: 12299.46 | P26: 11733.84 | Q26: 12646.02 | R26: 13011.78 | S26: 13379.13 | T26: 13728.28 | U26: 13171.84 | V26: 14070.04 | W26: 14418.22 | X26: 14771.88 | Y26: 15108.68 | Z26: 14497.69 | AA26: 15434.23 | AB26: 15772.54 | AC26: 16119.89 | AD26: 16451.29 | AE26: 15729.52
A27: Average monthly Wireless service revenue per subscriber($) | B27: 35.47 | C27: 35.26 | D27: 34.92 | E27: 35.26 | F27: 35.14 | G27: 34.2 | H27: 33.69 | I27: 33.92 | J27: 34.59 | K27: 34.15 | L27: 35.09 | M27: 34.84 | N27: 34.78 | O27: 35.11 | P27: 34.65 | Q27: 36 | R27: 35.66 | S27: 35.61 | T27: 36.11 | U27: 35.29 | V27: 36.85 | W27: 36.27 | X27: 36.34 | Y27: 36.94 | Z27: 35.91 | AA27: 37.56 | AB27: 36.97 | AC27: 37 | AD27: 37.62 | AE27: 36.51
A28: Domestic wireless service revenue | B28: 850 | C28: 882 | D28: 915 | E28: 965 | F28: 3612 | G28: 977 | H28: 1007 | I28: 1056.42 | J28: 1117.63 | K28: 4157.39 | L28: 1172.45 | M28: 1202.98 | N28: 1243.68 | O28: 1294 | P28: 4871.13 | Q28: 1363.23 | R28: 1388.65 | S28: 1425.28 | T28: 1482.4 | U28: 5556.66 | V28: 1549.26 | W28: 1561.71 | X28: 1602.69 | Y28: 1665.72 | Z28: 6233.71 | AA28: 1729.35 | AB28: 1738.67 | AC28: 1778 | AD28: 1844.58 | AE28: 6870.82
... A32: Domestic wireless equipment revenue | B32: 273 | C32: 313 | D32: 331 | E32: 438 | F32: 1355 | G32: 418 | H32: 404 | I32: 393.76 | J32: 487.74 | K32: 1703.5 | L32: 403.83 | M32: 402.81 | N32: 390.81 | O32: 489.35 | P32: 1772.84 | Q32: 420.41 | R32: 425.13 | S32: 414.62 | T32: 506.19 | U32: 1819.98 | V32: 429.48 | W32: 438.54 | X32: 434.65 | Y32: 521.78 | Z32: 1879.42 | AA32: 458.03 | AB32: 462.47 | AC32: 460.46 | AD32: 545.21 | AE32: 1963.28
A34: Financials
A35: Domestic wireless service revenue | B35: 850 | C35: 882 | D35: 915 | E35: 965 | F35: 3612 | G35: 977 | H35: 1007 | I35: 1056.42 | J35: 1117.63 | K35: 4157.39 | L35: 1172.45 | M35: 1202.98 | N35: 1243.68 | O35: 1294 | P35: 4871.13 | Q35: 1363.23 | R35: 1388.65 | S35: 1425.28 | T35: 1482.4 | U35: 5556.66 | V35: 1549.26 | W35: 1561.71 | X35: 1602.69 | Y35: 1665.72 | Z35: 6233.71 | AA35: 1729.35 | AB35: 1738.67 | AC35: 1778 | AD35: 1844.58 | AE35: 6870.82
A36: Domestic wireless equipment revenue | B36: 273 | C36: 313 | D36: 331 | E36: 438 | F36: 1355 | G36: 418 | H36: 404 | I36: 393.76 | J36: 487.74 | K36: 1703.5 | L36: 403.83 | M36: 402.81 | N36: 390.81 | O36: 489.35 | P36: 1772.84 | Q36: 420.41 | R36: 425.13 | S36: 414.62 | T36: 506.19 | U36: 1819.98 | V36: 429.48 | W36: 438.54 | X36: 434.65 | Y36: 521.78 | Z36: 1879.42 | AA36: 458.03 | AB36: 462.47 | AC36: 460.46 | AD36: 545.21 | AE36: 1963.28
A37: Domestic wireless revenue | B37: 1123 | C37: 1195 | D37: 1246 | E37: 1403 | F37: 4967 | G37: 1395 | H37: 1411 | I37: 1450.07 | J37: 1606.28 | K37: 5861.71 | L37: 1579.24 | M37: 1606.7 | N37: 1635.53 | O37: 1788.53 | P37: 6647.92 | Q37: 1789.19 | R37: 1814.69 | S37: 1840.72 | T37: 1997.6 | U37: 7387.21 | V37: 1987.02 | W37: 2003.07 | X37: 2037.68 | Y37: 2199.91 | Z37: 8130.32 | AA37: 2194.91 | AB37: 2202.83 | AC37: 2236.92 | AD37: 2403.21 | AE37: 8856.12
A38: Cost of Services - Domestic wireless | B38: 523.34 | C38: 541.77 | D38: 564.35 | E38: 587.99 | F38: 2054.27 | G38: 659.39 | H38: 678.31 | I38: 702.25 | J38: 730.95 | K38: 2440.69 | L38: 671.22 | M38: 695.22 | N38: 719.22 | O38: 743.22 | P38: 2536.7 | Q38: 767.22 | R38: 791.22 | S38: 815.22 | T38: 839.22 | U38: 2857.31 | V38: 863.22 | W38: 887.22 | X38: 911.22 | Y38: 935.22 | Z38: 3172.98 | AA38: 959.22 | AB38: 983.22 | AC38: 1007.22 | AD38: 1031.22 | AE38: 3469.14
A39: Cost of equipment - Domestic wireless | B39: 273 | C39: 313 | D39: 331 | E39: 459.37 | F39: 1479.17 | G39: 443.26 | H39: 438.54 | I39: 444.58 | J39: 520.11 | K39: 1855.35 | L39: 451.75 | M39: 464.47 | N39: 491.57 | O39: 504.77 | P39: 1884.47 | Q39: 502.63 | R39: 515.35 | S39: 544.37 | T39: 557.57 | U39: 2111.8 | V39: 553.51 | W39: 566.23 | X39: 597.17 | Y39: 610.37 | Z39: 2310.64 | AA39: 604.39 | AB39: 617.11 | AC39: 649.97 | AD39: 663.17 | AE39: 2489.21
A40: SG&A Expenses - Domestic wireless | B40: 182.9 | C40: 189.64 | D40: 222.68 | E40: 232.47 | F40: 844.31 | G40: 208 | H40: 211.73 | I40: 254.56 | J40: 259.9 | K40: 957.69 | L40: 206 | M40: 190.55 | N40: 190.96 | O40: 190.96 | P40: 1374.84 | Q40: 212.18 | R40: 196.27 | S40: 196.69 | T40: 196.69 | U40: 1524.9 | V40: 218.55 | W40: 202.15 | X40: 202.59 | Y40: 202.59 | Z40: 1668.48 | AA40: 225.1 | AB40: 208.22 | AC40: 208.67 | AD40: 208.67 | AE40: 1811.56
A41: Cash expenses - Domestic wireless | B41: 994.1 | C41: 1059.76 | D41: 1130.75 | E41: 1232.32 | F41: 4267.03 | G41: 1274.11 | H41: 1305 | I41: 1365.49 | J41: 1453.57 | K41: 5095.64 | L41: 1211.91 | M41: 1228.59 | N41: 1262.55 | O41: 1300.42 | P41: 5356.96 | Q41: 1314.51 | R41: 1333.8 | S41: 1371.3 | T41: 1407.05 | U41: 5936.89 | V41: 1417.2 | W41: 1438.78 | X41: 1487.83 | Y41: 1517.29 | Z41: 6492.96 | AA41: 1520.38 | AB41: 1543.67 | AC41: 1609.96 | AD41: 1631.7 | AE41: 7022.94
A42: EBITDA - Domestic wireless | B42: 128.9 | C42: 135.24 | D42: 115.25 | E42: 170.68 | F42: 699.97 | G42: 118.49 | H42: 106 | I42: 98.09 | J42: 106.67 | K42: 731.79 | L42: 377.04 | M42: 404.24 | N42: 419.07 | O42: 448.4 | P42: 1337.93 | Q42: 516.59 | R42: 540.28 | S42: 551.54 | T42: 584.74 | U42: 1681.4 | V42: 660.29 | W42: 659.04 | X42: 681.77 | Y42: 723.92 | Z42: 2033.34 | AA42: 810.38 | AB42: 804.88 | AC42: 814.17 | AD42: 867.42 | AE42: 2422.49
A44: Supplemental data
A45: Gross adds - Wireless(K#) | B45: 615.48 | C45: 684.55 | D45: 733.76 | E45: 699.29 | F45: 2733.07 | G45: 782.94 | H45: 813.21 | I45: 773.92 | J45: 782.27 | K45: 3152.34 | L45: 745 | M45: 749.97 | N45: 761.01 | O45: 775.78 | P45: 3031.76 | Q45: 764.04 | R45: 773.77 | S45: 791.34 | T45: 802.3 | U45: 3131.44 | V45: 784 | W45: 798.01 | X45: 837.11 | Y45: 836.44 | Z45: 3255.55 | AA45: 805.12 | AB45: 822.37 | AC45: 893.28 | AD45: 878.73 | AE45: 3399.5
A46: Disconnects - Wireless(K#) | B46: 293.48 | C46: 305.55 | D46: 319.76 | E46: 335.29 | F46: 1254.08 | G46: 348.94 | H46: 365.21 | I46: 382.01 | J46: 396.71 | K46: 1492.87 | L46: 411.17 | M46: 423.69 | N46: 435.92 | O46: 448.11 | P46: 1718.89 | Q46: 460.4 | R46: 471.79 | S46: 483.11 | T46: 494.67 | U46: 1909.97 | V46: 506.21 | W46: 516.62 | X46: 527.17 | Y46: 538.8 | Z46: 2088.8 | AA46: 549.96 | AB46: 559.53 | AC46: 569.38 | AD46: 581.53 | AE46: 2260.4
A47: Churn rate - Wireless(%) | B47: 0.0288 | C47: 0.0217 | D47: 0.0217 | E47: 0.025 | F47: 0.0367 | G47: 0.0212 | H47: 0.0212 | I47: 0.0188 | J47: 0.02 | K47: 0.03 | L47: 0.0155 | M47: 0.0225 | N47: 0.0225 | O47: 0.0175 | P47: 0.015 | Q47: 0.0158 | R47: 0.0212 | S47: 0.0212 | T47: 0.0175 | U47: 0.0133 | V47: 0.0158 | W47: 0.0212 | X47: 0.0212 | Y47: 0.0175 | Z47: 0.0133 | AA47: 0.0175 | AB47: 0.0238 | AC47: 0.0238 | AD47: 0.0175 | AE47: 0.0133
A48: Net adds - Wireless(K#) | B48: 322 | C48: 378.67 | D48: 414 | E48: 364 | F48: 1390.31 | G48: 434.33 | H48: 448 | I48: 383.46 | J48: 405.28 | K48: 1445.9 | L48: 333.83 | M48: 326.28 | N48: 325.09 | O48: 327.66 | P48: 1135.34 | Q48: 303.64 | R48: 301.98 | S48: 308.22 | T48: 307.63 | U48: 992.41 | V48: 277.79 | W48: 281.38 | X48: 309.93 | Y48: 297.64 | Z48: 882.25 | AA48: 255.16 | AB48: 262.84 | AC48: 323.9 | AD48: 297.2 | AE48: 797.71
A49: Ending wireless subs(K#) | B49: 8148 | C49: 8527 | D49: 8941 | E49: 9305 | F49: 9264.9 | G49: 9739 | H49: - | I49: - | J49: - | K49: 10465.42 | L49: - | M49: - | N49: - | O49: - | P49: 10671.94 | Q49: - | R49: - | S49: - | T49: - | U49: 11211.72 | V49: - | W49: - | X49: - | Y49: - | Z49: 11658.15 | AA49: - | AB49: - | AC49: - | AD49: - | AE49: 12033.64
A50: Avg. wireless subs(K#) | B50: 7987.25 | C50: 8337.5 | D50: 8733.75 | E50: 9123 | F50: 8599.14 | G50: 9522.25 | H50: 9963.5 | I50: 10386.97 | J50: 10787.57 | K50: 9855.14 | L50: 11142.72 | M50: 11506.15 | N50: 11892.08 | O50: 12242.89 | P50: 10340.64 | Q50: 12530.81 | R50: 12849.7 | S50: 13223.47 | T50: 13557.89 | U50: 10941.83 | V50: 13824.27 | W50: 14126.07 | X50: 14488.3 | Y50: 14807.14 | Z50: 11434.94 | AA50: 15074.68 | AB50: 15403.78 | AC50: 15798.78 | AD50: 16146.46 | AE50: 11845.9
A51: ARPU - Service($) | B51: 50 | C51: 50 | D51: 50 | E51: 50 | F51: 41.67 | G51: 50 | H51: - | I51: - | J51: - | K51: 34.23 | L51: - | M51: - | N51: - | O51: - | P51: 35.23 | Q51: - | R51: - | S51: - | T51: - | U51: 36.23 | V51: - | W51: - | X51: - | Y51: - | Z51: 37.23 | AA51: - | AB51: - | AC51: - | AD51: - | AE51: 38.23
A52: Retail service revenues | B52: 1198.05 | C52: 1250.62 | D52: 1310.1 | E52: 1368.45 | F52: 4303.73 | G52: 1428.3 | H52: - | I52: - | J52: - | K52: 3942.25 | L52: - | M52: - | N52: - | O52: - | P52: 4371.69 | Q52: - | R52: - | S52: - | T52: - | U52: 4757.16 | V52: - | W52: - | X52: - | Y52: - | Z52: 5108.76 | AA52: - | AB52: - | AC52: - | AD52: - | AE52: 5434.52

Sheet SPG Residential
A2: Comcast Corporation | Residential
A3: NASDAQGS:CMCSA (MI KEY: 4057180; SPCIQ KEY: 173341)
A5: Visible Alpha
A7: Period Type : Fiscal Quarter, Fiscal Halves, Fiscal Year
A8: Period Start : 2025
A9: Period End : 2030
A10: Currency : Reported
A11: Consensus View : Mean
A12: As Of: 10/20/2026
A14: All numbers in $M unless otherwise indicated | B14: FQ1 2025A | C14: FQ2 2025A | D14: FQ3 2025A | E14: FQ4 2025A | F14: FY2025A | G14: FQ1 2026A | H14: FQ2 2026A | I14: FQ3 2026E | J14: FQ4 2026E | K14: FY2026E | L14: FQ1 2027E | M14: FQ2 2027E | N14: FQ3 2027E | O14: FQ4 2027E | P14: FY2027E | Q14: FQ1 2028E | R14: FQ2 2028E | S14: FQ3 2028E | T14: FQ4 2028E | U14: FY2028E | V14: FQ1 2029E | W14: FQ2 2029E | X14: FQ3 2029E | Y14: FQ4 2029E | Z14: FY2029E | AA14: FQ1 2030E | AB14: FQ2 2030E | AC14: FQ3 2030E | AD14: FQ4 2030E | AE14: FY2030E
A15: Number of Contributors Available | B15: 22 | C15: 21 | D15: 21 | E15: 20 | F15: 21 | G15: 21 | H15: 20 | I15: 20 of 20 | J15: 20 of 20 | K15: 20 of 20 | L15: 12 of 20 | M15: 12 of 20 | N15: 11 of 20 | O15: 11 of 20 | P15: 20 of 20 | Q15: 8 of 20 | R15: 8 of 20 | S15: 8 of 20 | T15: 8 of 20 | U15: 19 of 20 | V15: 7 of 20 | W15: 7 of 20 | X15: 7 of 20 | Y15: 7 of 20 | Z15: 16 of 20 | AA15: 7 of 20 | AB15: 7 of 20 | AC15: 7 of 20 | AD15: 7 of 20 | AE15: 16 of 20
A16: Homes and businesses passed(K#) | B16: 58063 | C16: 58356 | D16: 58641 | E16: 64983 | F16: 64983 | G16: 59164 | H16: 59443 | I16: 63582.89 | J16: 63882.75 | K16: 64219.22 | L16: 63988.87 | M16: 64272.7 | N16: 64558.84 | O16: 64839.84 | P16: 65315.17 | Q16: 65311.96 | R16: 65611.61 | S16: 65914.26 | T16: 66225.67 | U16: 66344.52 | V16: 66108.15 | W16: 66407.34 | X16: 66710.11 | Y16: 67023.12 | Z16: 67281.01 | AA16: 67250.52 | AB16: 67551.93 | AC16: 67856.98 | AD16: 68172.41 | AE16: 68374.77
A18: Video residential penetration(%) | B18: 0.1891 | C18: 0.183 | D18: 0.1785 | E18: 0.1739 | F18: 0.1702 | G18: 0.1684 | H18: 0.1634 | I18: 0.1589 | J18: 0.1547 | K18: 0.1486 | L18: 0.1485 | M18: 0.1441 | N18: 0.1403 | O18: 0.1369 | P18: 0.1378 | Q18: 0.1334 | R18: 0.1301 | S18: 0.127 | T18: 0.1241 | U18: 0.1234 | V18: 0.1211 | W18: 0.1179 | X18: 0.1151 | Y18: 0.1125 | Z18: 0.1103 | AA18: 0.1097 | AB18: 0.1068 | AC18: 0.1042 | AD18: 0.1018 | AE18: 0.0982
A19: Video residential - net adds(K#) | B19: -427 | C19: -325 | D19: -256 | E19: -234.3 | F19: -1371.48 | G19: -315.25 | H19: -268.31 | I19: -235.97 | J19: -222.62 | K19: -1242.77 | L19: -232.7 | M19: -243 | N19: -198.4 | O19: -180.02 | P19: -919.14 | Q19: -173.89 | R19: -163.6 | S19: -149.88 | T19: -137.02 | U19: -796.16 | V19: -158.11 | W19: -160.17 | X19: -144.39 | Y19: -128.61 | Z19: -758.46 | AA19: -145.49 | AB19: -156.91 | AC19: -139.45 | AD19: -121.89 | AE19: -727.79
A20: Video residential subscribers(K#) | B20: 12096 | C20: 11771 | D20: 11515 | E20: 11078.3 | F20: 10859.24 | G20: 10766.7 | H20: 10501.05 | I20: 10266.87 | J20: 10043.37 | K20: 9650.3 | L20: 9845.55 | M20: 9602.55 | N20: 9404.15 | O20: 9224.12 | P20: 9093.22 | Q20: 9050.24 | R20: 8886.64 | S20: 8736.75 | T20: 8599.74 | U20: 8285.95 | V20: 8441.63 | W20: 8281.46 | X20: 8137.06 | Y20: 8008.45 | Z20: 7523.99 | AA20: 7862.96 | AB20: 7706.05 | AC20: 7566.6 | AD20: 7444.7 | AE20: 6800.17
A21: Avg. video residential subs.(K#) | B21: 12309.5 | C21: 11933.5 | D21: 11643 | E21: 11227.01 | F21: 11507.41 | G21: 10953.58 | H21: 10662.89 | I21: 10410.39 | J21: 10180.63 | K21: 10241.46 | L21: 9991.61 | M21: 9740.55 | N21: 9511.71 | O21: 9313.32 | P21: 9547.29 | Q21: 9116.31 | R21: 8918.72 | S21: 8738.94 | T21: 8576.63 | U21: 8684.4 | V21: 8405.51 | W21: 8221.3 | X21: 8050.57 | Y21: 7898.16 | Z21: 7900.62 | AA21: 7740 | AB21: 7567.64 | AC21: 7405.37 | AD21: 7261.83 | AE21: 7158.4
A22: Video revenue per residential subs.($) | B22: 125.47 | C22: 126.76 | D22: 125.81 | E22: 123.74 | F22: 125.66 | G22: 127.94 | H22: 128.19 | I22: 128.4 | J22: 126.28 | K22: 129.64 | L22: 135.2 | M22: 139.71 | N22: 140.76 | O22: 137.11 | P22: 129.37 | Q22: 138.92 | R22: 143.51 | S22: 144.55 | T22: 140.76 | U22: 132.01 | V22: 142.59 | W22: 147.28 | X22: 148.33 | Y22: 144.41 | Z22: 134.46 | AA22: 146.26 | AB22: 151.04 | AC22: 152.07 | AD22: 148.02 | AE22: 136.86
A23: Video revenue | B23: 4434.26 | C23: 4353.17 | D23: 4235.43 | E23: 4100.63 | F23: 17062.13 | G23: 4075.33 | H23: 3989.85 | I23: 3903.53 | J23: 3761.73 | K23: 15496.03 | L23: 3707.01 | M23: 3695.09 | N23: 3615.91 | O23: 3474.15 | P23: 14364.32 | Q23: 3658.61 | R23: 3697.83 | S23: 3642.25 | T23: 3466.57 | U23: 13407.99 | V23: 3430.32 | W23: 3459.26 | X23: 3399.18 | Y23: 3227.16 | Z23: 12254.09 | AA23: 3185.04 | AB23: 3203.04 | AC23: 3138.25 | AD23: 2970.27 | AE23: 11091.38
A25: HSI residential penetration(%) | B25: 0.5027 | C25: 0.4968 | D25: 0.4928 | E25: 0.4873 | F25: 0.4646 | G25: 0.4843 | H25: 0.4792 | I25: 0.4555 | J25: 0.4506 | K25: 0.4471 | L25: 0.4553 | M25: 0.4509 | N25: 0.4478 | O25: 0.4439 | P25: 0.4319 | Q25: 0.4411 | R25: 0.4371 | S25: 0.4344 | T25: 0.4308 | U25: 0.4181 | V25: 0.4282 | W25: 0.4244 | X25: 0.422 | Y25: 0.4187 | Z25: 0.4048 | AA25: 0.4162 | AB25: 0.4124 | AC25: 0.4101 | AD25: 0.4069 | AE25: 0.3921
A26: HSI residential - net adds(K#) | B26: -183 | C26: -201 | D26: -91.75 | E26: -178 | F26: -654 | G26: -65 | H26: -168 | I26: -139.82 | J26: -169.26 | K26: -542.08 | L26: -70.62 | M26: -114.3 | N26: -69.75 | O26: -80.85 | P26: -351.78 | Q26: -64.12 | R26: -100.86 | S26: -49.05 | T26: -64.83 | U26: -307.08 | V26: -84.25 | W26: -115.78 | X26: -43 | Y26: -71.14 | Z26: -327.32 | AA26: -118.5 | AB26: -146.56 | AC26: -46 | AD26: -87.28 | AE26: -359.98
A27: HSI residential subscribers(K#) | B27: 29190 | C27: 28989 | D27: 28897 | E27: 28719 | F27: 28719 | G27: 28654 | H27: 28486 | I27: 28347.15 | J27: 28175.74 | K27: 28175.74 | L27: 28122.97 | M27: 28008.67 | N27: 27938.92 | O27: 27858.08 | P27: 27784.31 | Q27: 27793.95 | R27: 27693.09 | S27: 27644.04 | T27: 27579.21 | U27: 27428.65 | V27: 27494.96 | W27: 27379.18 | X27: 27336.18 | Y27: 27265.04 | Z27: 27056.79 | AA27: 27146.54 | AB27: 26999.98 | AC27: 26953.98 | AD27: 26866.7 | AE27: 26664.31
A28: Avg. HSI residential subs.(K#) | B28: 29281.5 | C28: 29089.5 | D28: 28943 | E28: 28808 | F28: 29036.7 | G28: 28686.5 | H28: 28570 | I28: 28416.57 | J28: 28261.44 | K28: 28467.47 | L28: 28158.29 | M28: 28065.83 | N28: 27973.8 | O28: 27898.5 | P28: 27980.83 | Q28: 27826.01 | R28: 27743.52 | S28: 27668.56 | T28: 27611.62 | U28: 27605.5 | V28: 27537.08 | W28: 27437.07 | X28: 27357.68 | Y28: 27300.61 | Z28: 27238.61 | AA28: 27205.79 | AB28: 27073.26 | AC28: 26976.98 | AD28: 26910.34 | AE28: 26852.34
A29: HSI revenue per residential subs.($) | B29: 76.03 | C29: 76.19 | D29: 75.44 | E29: 74.17 | F29: 75.61 | G29: 73.65 | H29: 73.27 | I29: 72.95 | J29: 72.4 | K29: 74.48 | L29: 74.59 | M29: 74.58 | N29: 74.49 | O29: 73.62 | P29: 74.06 | Q29: 75.63 | R29: 76.08 | S29: 75.95 | T29: 75.09 | U29: 75.52 | V29: 76.64 | W29: 77.56 | X29: 77.37 | Y29: 76.53 | Z29: 76.99 | AA29: 77.6 | AB29: 79.01 | AC29: 78.77 | AD29: 77.93 | AE29: 78.48
... A45: Avg. residential customer relationship(K#) | B45: 31070.5 | C45: 30857.5 | D45: 30694 | E45: 30540.5 | F45: 30953.23 | G45: 30392 | H45: 30346.66 | I45: 30158.81 | J45: 29969.29 | K45: 30468.88 | L45: 29878.46 | M45: 29798.09 | N45: 29719.17 | O45: 29672.41 | P45: 30048.59 | Q45: 29638.17 | R45: 29580.07 | S45: 29517.61 | T45: 29488.8 | U45: 29740.14 | V45: 29466.47 | W45: 29419.34 | X45: 29370.53 | Y45: 29354.49 | Z45: 29445.68 | AA45: 29346.01 | AB45: 29311.49 | AC45: 29271.43 | AD45: 29262.58 | AE45: 29152.18
A46: Revenue per residential customer($) | B46: 126.13 | C46: 124.38 | D46: 122.45 | E46: 119.9 | F46: 122.65 | G46: 119.52 | H46: 116.54 | I46: 115.62 | J46: 114 | K46: 117.66 | L46: - | M46: - | N46: - | O46: - | P46: 114.25 | Q46: - | R46: - | S46: - | T46: - | U46: 110.74 | V46: - | W46: - | X46: - | Y46: - | Z46: 107.08 | AA46: - | AB46: - | AC46: - | AD46: - | AE46: 103.3
A47: Residential customer revenue | B47: 11756.46 | C47: 11514.54 | D47: 11275.28 | E47: 10985.04 | F47: 45890.63 | G47: 10897.51 | H47: 10579.87 | I47: 10442.1 | J47: 10236.34 | K47: 43508.54 | L47: - | M47: - | N47: - | O47: - | P47: 41735.32 | Q47: - | R47: - | S47: - | T47: - | U47: 39998.82 | V47: - | W47: - | X47: - | Y47: - | Z47: 38229.9 | AA47: - | AB47: - | AC47: - | AD47: - | AE47: 36441.88
A49: Single product subscribers(K#) | B49: 15914.12 | C49: 16230.43 | D49: 16470.62 | E49: 16638.62 | F49: 16638.62 | G49: 16443.03 | H49: 16655.45 | I49: 17372.61 | J49: 17461.3 | K49: 17461.3 | L49: 17269.37 | M49: 17435.63 | N49: 17576.35 | O49: 17645.74 | P49: 17645.74 | Q49: 17513.79 | R49: 17623.92 | S49: 17709.72 | T49: 17751.86 | U49: 17751.86 | V49: 17649.56 | W49: 17746.44 | X49: 17798.19 | Y49: 17821.75 | Z49: 17821.75 | AA49: 17742.69 | AB49: 17829.2 | AC49: 17844.98 | AD49: 17850.32 | AE49: 17850.32
A50: Double product subscribers(K#) | B50: 10134.35 | C50: 10049.87 | D50: 9994.76 | E50: 9980.54 | F50: 9980.54 | G50: 10450.62 | H50: 10393.89 | I50: 10229.36 | J50: 10221.85 | K50: 10221.85 | L50: 10683.13 | M50: 10638.72 | N50: 10606.44 | O50: 10600.56 | P50: 10600.56 | Q50: 10917.7 | R50: 10888.29 | S50: 10868.6 | T50: 10865.03 | U50: 10865.03 | V50: 11110.9 | W50: 11085.03 | X50: 11073.15 | Y50: 11071.16 | Z50: 11071.16 | AA50: 11261.17 | AB50: 11238.06 | AC50: 11234.44 | AD50: 11233.99 | AE50: 11233.99
A51: Triple product subscribers(K#) | B51: 4920.53 | C51: 4465.71 | D51: 4176.62 | E51: 3819.84 | F51: 3819.84 | G51: 3719.84 | H51: 3619.84 | I51: 2214.25 | J51: 2154.69 | K51: 2154.69 | L51: 1918.47 | M51: 1719.15 | N51: 1563.61 | O51: 1446.01 | P51: 1446.01 | Q51: 1278.48 | R51: 1138.3 | S51: 1029.68 | T51: 947.84 | U51: 947.84 | V51: 812.85 | W51: 679.82 | X51: 582.06 | Y51: 516.81 | Z51: 516.81 | AA51: 407.94 | AB51: 281.7 | AC51: 193.71 | AD51: 141.71 | AE51: 141.71
A52: Residential customer relationship(K#) | B52: 30969 | C52: 30746 | D52: 30642 | E52: 30439 | F52: 30706.27 | G52: 30434.5 | H52: 30371.71 | I52: 30018.62 | J52: 29932.19 | K52: 30294.19 | L52: 29870.97 | M52: 29793.5 | N52: 29746.4 | O52: 29692.31 | P52: 30040.96 | Q52: 29709.98 | R52: 29650.5 | S52: 29608 | T52: 29564.74 | U52: 29809.02 | V52: 29573.31 | W52: 29511.29 | X52: 29453.4 | Y52: 29409.72 | Z52: 29580.64 | AA52: 29411.8 | AB52: 29348.97 | AC52: 29273.14 | AD52: 29226.03 | AE52: 29342.89

Sheet SPG Business Services
A2: Comcast Corporation | Business services
A3: NASDAQGS:CMCSA (MI KEY: 4057180; SPCIQ KEY: 173341)
A5: Visible Alpha
A7: Period Type : Fiscal Quarter, Fiscal Halves, Fiscal Year
A8: Period Start : 2025
A9: Period End : 2030
A10: Currency : Reported
A11: Consensus View : Mean
A12: As Of: 10/20/2026
A14: All numbers in $M unless otherwise indicated | B14: FQ1 2025A | C14: FQ2 2025A | D14: FQ3 2025A | E14: FQ4 2025A | F14: FY2025A | G14: FQ1 2026A | H14: FQ2 2026A | I14: FQ3 2026E | J14: FQ4 2026E | K14: FY2026E | L14: FQ1 2027E | M14: FQ2 2027E | N14: FQ3 2027E | O14: FQ4 2027E | P14: FY2027E | Q14: FQ1 2028E | R14: FQ2 2028E | S14: FQ3 2028E | T14: FQ4 2028E | U14: FY2028E | V14: FQ1 2029E | W14: FQ2 2029E | X14: FQ3 2029E | Y14: FQ4 2029E | Z14: FY2029E | AA14: FQ1 2030E | AB14: FQ2 2030E | AC14: FQ3 2030E | AD14: FQ4 2030E | AE14: FY2030E
A15: Number of Contributors Available | B15: 22 | C15: 21 | D15: 21 | E15: 20 | F15: 21 | G15: 21 | H15: 20 | I15: 20 of 20 | J15: 20 of 20 | K15: 20 of 20 | L15: 12 of 20 | M15: 12 of 20 | N15: 11 of 20 | O15: 11 of 20 | P15: 20 of 20 | Q15: 8 of 20 | R15: 8 of 20 | S15: 8 of 20 | T15: 8 of 20 | U15: 19 of 20 | V15: 7 of 20 | W15: 7 of 20 | X15: 7 of 20 | Y15: 7 of 20 | Z15: 16 of 20 | AA15: 7 of 20 | AB15: 7 of 20 | AC15: 7 of 20 | AD15: 7 of 20 | AE15: 16 of 20
A16: Video business services customers - net adds(K#) | B16: -18.07 | C16: -17.43 | D16: -17.27 | E16: -22.6 | F16: -90.92 | G16: -14.25 | H16: -14.19 | I16: -14.75 | J16: -15.94 | K16: -69.07 | L16: -7.25 | M16: -7.25 | N16: -7.03 | O16: -7.03 | P16: -26.62 | Q16: -7.03 | R16: -7.03 | S16: -6.82 | T16: -6.82 | U16: -20.62 | V16: -6.82 | W16: -6.82 | X16: -6.64 | Y16: -6.64 | Z16: -16.43 | AA16: -6.64 | AB16: -6.64 | AC16: -6.48 | AD16: -6.48 | AE16: -20.74
A17: Video business services customers(K#) | B17: 421.21 | C17: 403.78 | D17: 386.51 | E17: 319.51 | F17: 313.17 | G17: 354.06 | H17: 339.87 | I17: 325.12 | J17: 309.18 | K17: 323.99 | L17: 332.6 | M17: 325.35 | N17: 318.33 | O17: 311.3 | P17: 297.37 | Q17: 304.28 | R17: 297.25 | S17: 290.43 | T17: 283.61 | U17: 276.74 | V17: 276.79 | W17: 269.96 | X17: 263.32 | Y17: 256.68 | Z17: 260.32 | AA17: 250.04 | AB17: 243.4 | AC17: 236.93 | AD17: 230.45 | AE17: 213.4
A18: Average Video business services customers(K#) | B18: 430.24 | C18: 412.49 | D18: 395.14 | E18: 330.81 | F18: 358.62 | G18: 310.84 | H18: 346.96 | I18: 332.49 | J18: 317.15 | K18: 312.12 | L18: 336.23 | M18: 328.98 | N18: 321.84 | O18: 314.82 | P18: 310.63 | Q18: 307.79 | R18: 300.77 | S18: 293.84 | T18: 287.02 | U18: 287.01 | V18: 280.2 | W18: 273.38 | X18: 266.64 | Y18: 260 | Z18: 268.49 | AA18: 253.36 | AB18: 246.72 | AC18: 240.16 | AD18: 233.69 | AE18: 223.73
A20: Broadband business services customers - net adds(K#) | B20: -16 | C20: 98 | D20: -13 | E20: -2 | F20: 63.99 | G20: -1.31 | H20: -0.45 | I20: -1.55 | J20: -28.15 | K20: 5.17 | L20: 2.5 | M20: 2.5 | N20: 6.5 | O20: 1.5 | P20: 23.66 | Q20: 2.75 | R20: 2.75 | S20: 7.15 | T20: 1.65 | U20: 15.68 | V20: 3.03 | W20: 3.03 | X20: 7.86 | Y20: 1.82 | Z20: 16.48 | AA20: 3.33 | AB20: 3.33 | AC20: 8.65 | AD20: 2 | AE20: 14.52
A21: Broadband business services customers(K#) | B21: 2453 | C21: 2551 | D21: 2538 | E21: 2536 | F21: 2525.72 | G21: 2534.69 | H21: 2534.24 | I21: 2532.69 | J21: 2504.53 | K21: 2530.89 | L21: 2521.5 | M21: 2524 | N21: 2530.5 | O21: 2532 | P21: 2607.5 | Q21: 2534.75 | R21: 2537.5 | S21: 2544.65 | T21: 2546.3 | U21: 2623.18 | V21: 2549.32 | W21: 2552.35 | X21: 2560.22 | Y21: 2562.03 | Z21: 2639.66 | AA21: 2565.36 | AB21: 2568.68 | AC21: 2577.34 | AD21: 2579.33 | AE21: 2654.18
A22: Average Broadband business services customers(K#) | B22: 2460.88 | C22: 2486.5 | D22: 2529.12 | E22: 2536.88 | F22: 2498.91 | G22: 2533.78 | H22: 2529.5 | I22: 2525.34 | J22: 2513.26 | K22: 2534.43 | L22: 2507.52 | M22: 2503.89 | N22: 2501.71 | O22: 2503.99 | P22: 2595.64 | Q22: 2505.85 | R22: 2504.22 | S22: 2503.99 | T22: 2508.06 | U22: 2615.31 | V22: 2511.5 | W22: 2511.39 | X22: 2512.69 | Y22: 2518.16 | Z22: 2631.38 | AA22: 2522.3 | AB22: 2522.33 | AC22: 2523.9 | AD22: 2529.63 | AE22: 2646.88
A24: Voice business services customers - net adds(K#) | B24: 11.58 | C24: 27.47 | D24: -5.26 | E24: -8.57 | F24: 18.33 | G24: 17.67 | H24: 1.15 | I24: -1.11 | J24: -13.51 | K24: 8.19 | L24: 6.33 | M24: -1.18 | N24: -5.31 | O24: -6.5 | P24: 14.22 | Q24: 5.69 | R24: -1.06 | S24: -4.78 | T24: -5.85 | U24: 11.29 | V24: 5.12 | W24: -0.96 | X24: -4.3 | Y24: -5.26 | Z24: 12.27 | AA24: 4.61 | AB24: -0.86 | AC24: -3.87 | AD24: -4.74 | AE24: 12.75
A25: Voice business services customers(K#) | B25: 1392.25 | C25: 1419.72 | D25: 1414.46 | E25: 1368.27 | F25: 1380.8 | G25: 1429.52 | H25: 1430.68 | I25: 1429.57 | J25: 1416.06 | K25: 1415.96 | L25: 1340.4 | M25: 1339.22 | N25: 1333.9 | O25: 1327.41 | P25: 1457.2 | Q25: 1333.1 | R25: 1332.04 | S25: 1327.25 | T25: 1321.41 | U25: 1468.5 | V25: 1326.53 | W25: 1325.58 | X25: 1321.27 | Y25: 1316.01 | Z25: 1480.77 | AA25: 1320.62 | AB25: 1319.76 | AC25: 1315.89 | AD25: 1311.15 | AE25: 1493.52
A26: Average Voice business services customers(K#) | B26: 1390.8 | C26: 1411.77 | D26: 1414.58 | E26: 1370.2 | F26: 1401.42 | G26: 1386.82 | H26: 1429.88 | I26: 1428.99 | J26: 1415.62 | K26: 1389.07 | L26: 1337.23 | M26: 1339.81 | N26: 1336.56 | O26: 1330.65 | P26: 1451.16 | Q26: 1330.25 | R26: 1332.57 | S26: 1329.65 | T26: 1324.33 | U26: 1463.81 | V26: 1323.97 | W26: 1326.05 | X26: 1323.42 | Y26: 1318.64 | Z26: 1475.5 | AA26: 1318.32 | AB26: 1320.19 | AC26: 1317.82 | AD26: 1313.52 | AE26: 1487.92
A28: Business services PSUs - net adds(K#) | B28: -13.19 | C28: 91.54 | D28: -24.56 | E28: -15.02 | F28: -67.06 | G28: -2.97 | H28: -11.31 | I28: -16.9 | J28: -12.22 | K28: -109.25 | L28: 4.33 | M28: -3.18 | N28: -2.86 | O28: -9.05 | P28: -10.76 | Q28: 4.39 | R28: -2.36 | S28: -1.28 | T28: -7.84 | U28: -7.09 | V28: 4.5 | W28: -1.58 | X28: 0.28 | Y28: -6.73 | Z28: -3.52 | AA28: 4.66 | AB28: -0.81 | AC28: 1.82 | AD28: -5.69 | AE28: -0.02
A29: Business services PSUs subscribers(K#) | B29: 4240.33 | C29: 4347.64 | D29: 4311.61 | E29: 4288.79 | F29: 4216.02 | G29: 4265.87 | H29: 4238.8 | I29: 4213.76 | J29: 4191.07 | K29: 4125.52 | L29: 4353.1 | M29: 4349.92 | N29: 4347.06 | O29: 4338.01 | P29: 4240.85 | Q29: 4342.41 | R29: 4340.04 | S29: 4338.77 | T29: 4330.93 | U29: 4195.79 | V29: 4335.43 | W29: 4333.85 | X29: 4334.13 | Y29: 4327.41 | Z29: 4145.44 | AA29: 4332.07 | AB29: 4331.25 | AC29: 4333.08 | AD29: 4327.39 | AE29: 4089.4
A30: Average Business services PSUs subs.(K#) | B30: 4256.64 | C30: 4293.98 | D30: 4329.62 | E30: 4300.2 | F30: 4233.2 | G30: 4277.33 | H30: 4252.33 | I30: 4226.28 | J30: 4202.41 | K30: 4171.81 | L30: 4350.94 | M30: 4351.51 | N30: 4348.49 | O30: 4342.54 | P30: 4264.74 | Q30: 4340.21 | R30: 4341.23 | S30: 4339.41 | T30: 4334.85 | U30: 4219.8 | V30: 4333.18 | W30: 4334.64 | X30: 4333.99 | Y30: 4330.77 | Z30: 4171.94 | AA30: 4329.74 | AB30: 4331.66 | AC30: 4332.16 | AD30: 4330.23 | AE30: 4118.61
A32: Business services customer relationships - net adds(K#) | B32: -25 | C32: 50.5 | D32: -11 | E32: - | F32: 48 | G32: -27.5 | H32: -10 | I32: -9.47 | J32: 3.6 | K32: -25.67 | L32: -4.66 | M32: -18.07 | N32: -4.18 | O32: 5.9 | P32: -2 | Q32: -2.53 | R32: -16.07 | S32: -2.47 | T32: 7.39 | U32: -4.56 | V32: -1.15 | W32: -14.77 | X32: -1.36 | Y32: 8.35 | Z32: -7.97 | AA32: -0.25 | AB32: -13.93 | AC32: -0.64 | AD32: 8.98 | AE32: -11.95
A33: Business services customer relationships(K#) | B33: 2613 | C33: 2713 | D33: 2702 | E33: 2702 | F33: 2685 | G33: 2702.26 | H33: 2686.67 | I33: 2677.2 | J33: 2679 | K33: 2659.33 | L33: 2664.94 | M33: 2646.87 | N33: 2642.69 | O33: 2648.59 | P33: 2657.33 | Q33: 2646.06 | R33: 2630 | S33: 2627.53 | T33: 2634.92 | U33: 2652.77 | V33: 2633.77 | W33: 2619 | X33: 2617.64 | Y33: 2625.99 | Z33: 2644.8 | AA33: 2625.74 | AB33: 2611.82 | AC33: 2611.18 | AD33: 2620.16 | AE33: 2632.85
A34: Average Business services customer relationships(K#) | B34: 2621.5 | C34: 2663 | D34: 2707.5 | E34: 2702 | F34: 2657.5 | G34: 2704.44 | H34: 2699.89 | I34: 2688.85 | J34: 2684.5 | K34: 2680.36 | L34: 2667.27 | M34: 2655.9 | N34: 2644.78 | O34: 2645.64 | P34: 2666.99 | Q34: 2647.33 | R34: 2638.03 | S34: 2628.76 | T34: 2631.22 | U34: 2663.69 | V34: 2634.34 | W34: 2626.39 | X34: 2618.32 | Y34: 2621.82 | Z34: 2658.13 | AA34: 2625.87 | AB34: 2618.78 | AC34: 2611.5 | AD34: 2615.67 | AE34: 2649.79
A35: Revenue per customer relationship - Business services($) | B35: 336.2 | C35: 339.8 | D35: 333.68 | E35: 334.82 | F35: 346.08 | G35: 338.55 | H35: 341.19 | I35: 338.59 | J35: 339.82 | K35: 353.14 | L35: - | M35: - | N35: - | O35: - | P35: 361.03 | Q35: - | R35: - | S35: - | T35: - | U35: 369.94 | V35: - | W35: - | X35: - | Y35: - | Z35: 379.42 | AA35: - | AB35: - | AC35: - | AD35: - | AE35: 389.29
A36: Business services revenue | B36: 2591.53 | C36: 2645.83 | D36: 2654.66 | E36: 2668.54 | F36: 10711.73 | G36: 2646.24 | H36: 2675.84 | I36: 2672.14 | J36: 2686.39 | K36: 10944.31 | L36: 2541 | M36: 2577 | N36: 2599 | O36: 2623 | P36: 11106.86 | Q36: - | R36: - | S36: - | T36: - | U36: 11724.99 | V36: - | W36: - | X36: - | Y36: - | Z36: 11939.06 | AA36: - | AB36: - | AC36: - | AD36: - | AE36: 12123

Sheet SPG Cash Flow
A2: Comcast Corporation | Cash flow
A3: NASDAQGS:CMCSA (MI KEY: 4057180; SPCIQ KEY: 173341)
A5: Visible Alpha
A7: Period Type : Fiscal Quarter, Fiscal Halves, Fiscal Year
A8: Period Start : 2025
A9: Period End : 2030
A10: Currency : Reported
A11: Consensus View : Mean
A12: As Of: 10/20/2026
A14: All numbers in $M unless otherwise indicated | B14: FQ1 2025A | C14: FQ2 2025A | D14: FQ3 2025A | E14: FQ4 2025A | F14: FY2025A | G14: FQ1 2026A | H14: FQ2 2026A | I14: FQ3 2026E | J14: FQ4 2026E | K14: FY2026E | L14: FQ1 2027E | M14: FQ2 2027E | N14: FQ3 2027E | O14: FQ4 2027E | P14: FY2027E | Q14: FQ1 2028E | R14: FQ2 2028E | S14: FQ3 2028E | T14: FQ4 2028E | U14: FY2028E | V14: FQ1 2029E | W14: FQ2 2029E | X14: FQ3 2029E | Y14: FQ4 2029E | Z14: FY2029E | AA14: FQ1 2030E | AB14: FQ2 2030E | AC14: FQ3 2030E | AD14: FQ4 2030E | AE14: FY2030E
A15: Number of Contributors Available | B15: 22 | C15: 21 | D15: 21 | E15: 20 | F15: 21 | G15: 21 | H15: 20 | I15: 20 of 20 | J15: 20 of 20 | K15: 20 of 20 | L15: 12 of 20 | M15: 12 of 20 | N15: 11 of 20 | O15: 11 of 20 | P15: 20 of 20 | Q15: 8 of 20 | R15: 8 of 20 | S15: 8 of 20 | T15: 8 of 20 | U15: 19 of 20 | V15: 7 of 20 | W15: 7 of 20 | X15: 7 of 20 | Y15: 7 of 20 | Z15: 16 of 20 | AA15: 7 of 20 | AB15: 7 of 20 | AC15: 7 of 20 | AD15: 7 of 20 | AE15: 16 of 20
A16: Net income (CF) | B16: 3296 | C16: 11044 | D16: 3250 | E16: 2070 | F16: 19660 | G16: 2027 | H16: 3418 | I16: 3039.87 | J16: 1938.89 | K16: 10386.51 | L16: 2462.2 | M16: 3174.79 | N16: 3114.03 | O16: 2133.61 | P16: 10791.07 | Q16: 2585.32 | R16: 3257.36 | S16: 3198.72 | T16: 2162.6 | U16: 11198.67 | V16: 2516.59 | W16: 3231.45 | X16: 3232.19 | Y16: 2196.72 | Z16: 11378.12 | AA16: 2581.17 | AB16: 3321.02 | AC16: 3312.37 | AD16: 2331.99 | AE16: 11832.93
A17: Depreciation and amortization (CF) | B17: 3849 | C17: 4154 | D17: 4020 | E17: 4187 | F17: 16210 | G17: 3865 | H17: 3688 | I17: 3806.53 | J17: 3838.22 | K17: 15115.46 | L17: 3752.26 | M17: 3702.42 | N17: 3785.15 | O17: 3835.94 | P17: 15037.88 | Q17: 3709.96 | R17: 3677.4 | S17: 3802.91 | T17: 3837.1 | U17: 15158.63 | V17: 3781.74 | W17: 3758.57 | X17: 3768.61 | Y17: 3810.11 | Z17: 15169.73 | AA17: 3825.86 | AB17: 3773.78 | AC17: 3791.01 | AD17: 3831.65 | AE17: 15301.06
A18: Share-based compensation | B18: 382 | C18: 321 | D18: 311 | E18: 274 | F18: 1288 | G18: 427 | H18: 359 | I18: 331.43 | J18: 326.81 | K18: 1464.39 | L18: 399.11 | M18: 350.47 | N18: 342.17 | O18: 352.16 | P18: 1465.23 | Q18: 416.94 | R18: 347.08 | S18: 346.14 | T18: 347.27 | U18: 1503.46 | V18: 433.69 | W18: 351.15 | X18: 337.98 | Y18: 348.83 | Z18: 1527.54 | AA18: 446.63 | AB18: 359.12 | AC18: 343.29 | AD18: 354.52 | AE18: 1562.55
A19: Deferred income taxes (CF) | B19: -43 | C19: 2599 | D19: 694 | E19: -576 | F19: 2674 | G19: 730 | H19: 697 | I19: 162.74 | J19: 58.83 | K19: 1665.71 | L19: 92.7 | M19: 124.58 | N19: 285.16 | O19: 279.42 | P19: 881.89 | Q19: -19.12 | R19: -69.88 | S19: 223.2 | T19: 249.59 | U19: 641.06 | V19: -15.06 | W19: -64.76 | X19: 207.42 | Y19: 249.54 | Z19: 825.14 | AA19: 11.93 | AB19: -65.01 | AC19: 203.32 | AD19: 246.6 | AE19: 650.54
A20: Total other operating activities | B20: 361 | C20: -9498 | D20: 214 | E20: 558 | F20: -8365 | G20: 397 | H20: -228 | I20: 204.39 | J20: 214.18 | K20: 501.11 | L20: 225.19 | M20: 139.82 | N20: 217.61 | O20: 287.15 | P20: 696.63 | Q20: 172.08 | R20: -82.56 | S20: 100.69 | T20: 235.56 | U20: 405.65 | V20: 156.24 | W20: -74.29 | X20: 96.53 | Y20: 225 | Z20: 402.22 | AA20: 145.14 | AB20: -67.7 | AC20: 93.43 | AD20: 216.39 | AE20: 408.46
A21: Change in current and noncurrent receivables, net | B21: 935 | C21: 88 | D21: -307 | E21: -851 | F21: -135 | G21: -1376 | H21: 38 | I21: -6.75 | J21: -165.5 | K21: -1252.24 | L21: 44.56 | M21: -211.57 | N21: 103.46 | O21: -130.42 | P21: -246.61 | Q21: -468.93 | R21: -320.29 | S21: -178.08 | T21: 571.84 | U21: -595.01 | V21: -663.87 | W21: -430.85 | X21: 462.3 | Y21: 533.01 | Z21: 0.08 | AA21: -1386.43 | AB21: 13.86 | AC21: 343.44 | AD21: 477.04 | AE21: -410.64
A22: Change in film and television costs | B22: -123 | C22: 311 | D22: -356 | E22: 506 | F22: 338 | G22: 375 | H22: 498 | I22: -299.56 | J22: 147.35 | K22: 785.68 | L22: -152.6 | M22: -82.85 | N22: -183.28 | O22: 33.05 | P22: -23.2 | Q22: -143.21 | R22: -77.94 | S22: -241.95 | T22: 60.5 | U22: -44.41 | V22: -201.04 | W22: -99.83 | X22: -266.77 | Y22: 50.87 | Z22: -271.79 | AA22: -208.85 | AB22: -99.98 | AC22: -266.68 | AD22: 25.43 | AE22: -323.49
A23: Change in accounts payable and accrued expenses related to trade creditors | B23: -35 | C23: 69 | D23: -169 | E23: 115 | F23: -20 | G23: 1119 | H23: -161 | I23: -232.84 | J23: -428.8 | K23: 548.74 | L23: 61.37 | M23: 66.68 | N23: -69.63 | O23: -445.5 | P23: -367.62 | Q23: 305.49 | R23: 195.47 | S23: 382.06 | T23: -831.51 | U23: 128.29 | V23: 428.54 | W23: 290 | X23: -290.01 | Y23: -756.59 | Z23: -295.09 | AA23: 1203.21 | AB23: -289.28 | AC23: -174.57 | AD23: -767.52 | AE23: 12.56
A24: Change in other operating assets and liabilities | B24: -327 | C24: -1275 | D24: 1036 | E24: 2560 | F24: 1994 | G24: -673 | H24: -218 | I24: -87.9 | J24: 252.01 | K24: -798.56 | L24: -445.43 | M24: -415.19 | N24: 66.13 | O24: 516.37 | P24: -197.71 | Q24: -622.84 | R24: -498.67 | S24: -16.98 | T24: 601.13 | U24: -89.61 | V24: -912.96 | W24: -717.47 | X24: -123.47 | Y24: 843.45 | Z24: -120.34 | AA24: -729.72 | AB24: -662.22 | AC24: 8.59 | AD24: 823.01 | AE24: 34.24
A25: Changes in working capital | B25: 450 | C25: -807 | D25: 204 | E25: 2330 | F25: 2177 | G25: -555 | H25: 157 | I25: -420.75 | J25: -50.94 | K25: -782.26 | L25: -506.09 | M25: -416.29 | N25: 5.96 | O25: 96.86 | P25: -730.36 | Q25: -538.61 | R25: -413.71 | S25: -117.8 | T25: 181.18 | U25: -689.01 | V25: -639.94 | W25: -463.23 | X25: -200.53 | Y25: 218.47 | Z25: -682.6 | AA25: -550.49 | AB25: -495.05 | AC25: -149.02 | AD25: 168.27 | AE25: -740.12
A26: Net cash provided by (used in) operating activities | B26: 8294 | C26: 7815 | D26: 8693 | E26: 8841 | F26: 33643 | G26: 6891 | H26: 8092 | I26: 7001.35 | J26: 6018.83 | K26: 27655.01 | L26: 6135.92 | M26: 6783.34 | N26: 7258.61 | O26: 6465.71 | P26: 26871.55 | Q26: 6319 | R26: 6848.69 | S26: 7316.64 | T26: 6670.71 | U26: 27855.68 | V26: 6303.2 | W26: 6892.89 | X26: 7248.68 | Y26: 6770.94 | Z26: 28332.21 | AA26: 6478.25 | AB26: 7006.89 | AC26: 7405.78 | AD26: 6946.68 | AE26: 28838.83
A27: Capital expenditures | B27: 2252 | C27: 2679 | D27: 3071 | E27: 3749 | F27: 11750 | G27: 2351 | H27: 2902 | I27: 3008.63 | J27: 3414.4 | K27: 11697.53 | L27: 2533.47 | M27: 2889.47 | N27: 2944.27 | O27: 3364.73 | P27: 11716.07 | Q27: 2495.59 | R27: 2889.56 | S27: 2991.8 | T27: 3449.46 | U27: 11828.09 | V27: 2618.33 | W27: 2994.08 | X27: 3032.18 | Y27: 3488.74 | Z27: 12097.24 | AA27: 2666.01 | AB27: 2998.68 | AC27: 3048.83 | AD27: 3510.75 | AE27: 12211.56
... A34: Dividends paid | B34: 1224 | C34: 1238 | D34: 1223 | E34: 1209 | F34: 4894 | G34: 1248 | H34: 1184 | I34: 1186.46 | J34: 1186.84 | K34: 4806.5 | L34: 1221.6 | M34: 1235.38 | N34: 1223.25 | O34: 1212.03 | P34: 4918.32 | Q34: 1246.56 | R34: 1253 | S34: 1237.59 | T34: 1223.34 | U34: 4944.26 | V34: 1254.52 | W34: 1265.43 | X34: 1251.24 | Y34: 1238.25 | Z34: 4983.89 | AA34: 1262.53 | AB34: 1273.84 | AC34: 1260.25 | AD34: 1247.61 | AE34: 4989.47
A35: Distributions to noncontrolling interests and dividends for redeemable subsidiary preferred stock | B35: - | C35: - | D35: - | E35: - | F35: - | G35: 750 | H35: - | I35: - | J35: - | K35: 750 | L35: - | M35: - | N35: - | O35: - | P35: 750 | Q35: - | R35: - | S35: - | T35: - | U35: 750 | V35: - | W35: - | X35: - | Y35: - | Z35: 750 | AA35: - | AB35: - | AC35: - | AD35: - | AE35: 750
A36: Payment of dividends | B36: 1224 | C36: 1238 | D36: 1223 | E36: 1209 | F36: 4894 | G36: 1248 | H36: 1184 | I36: 1189.71 | J36: 1190.49 | K36: 4893.48 | L36: 1235.31 | M36: 1246.94 | N36: 1233.85 | O36: 1221.82 | P36: 4996.44 | Q36: 1278.51 | R36: 1284.34 | S36: 1270.91 | T36: 1257.85 | U36: 5031.23 | V36: 1316.03 | W36: 1326.87 | X36: 1314.24 | Y36: 1302.11 | Z36: 5103.06 | AA36: 1342.65 | AB36: 1353.25 | AC36: 1340.65 | AD36: 1328.49 | AE36: 5111.31
A37: Other financing activities | B37: 24 | C37: -15 | D37: 42 | E37: -101 | F37: -50 | G37: -1066 | H37: 46 | I37: 30.43 | J37: 30.43 | K37: -846.24 | L37: -34.24 | M37: -34.24 | N37: -34.24 | O37: -34.24 | P37: 31.51 | Q37: -33.77 | R37: -33.77 | S37: -33.77 | T37: -33.77 | U37: 32.46 | V37: -33.28 | W37: -33.28 | X37: -33.28 | Y37: -33.28 | Z37: 33.43 | AA37: -32.78 | AB37: -32.78 | AC37: -32.78 | AD37: -32.78 | AE37: 34.44
A38: Net cash provided by (used in) financing activities | B38: -4076 | C38: -1805 | D38: -5243 | E38: -3221 | F38: -14345 | G38: -5008 | H38: -6305 | I38: -1402.46 | J38: -1484.73 | K38: -13790.02 | L38: -1444.59 | M38: -1548.09 | N38: -2288.12 | O38: -2113.7 | P38: -8653.24 | Q38: -2560.45 | R38: -2822.8 | S38: -2441.39 | T38: -2853.95 | U38: -12804.34 | V38: -2734.07 | W38: -2608.56 | X38: -2760.07 | Y38: -2788.96 | Z38: -12042.86 | AA38: -2714.31 | AB38: -2614.17 | AC38: -2674.59 | AD38: -2665.83 | AE38: -12399.91
A39: Impact of foreign currency on cash, cash equivalents and restricted cash | B39: 14 | C39: 32 | D39: -11 | E39: 7 | F39: 42 | G39: -6 | H39: 2 | I39: - | J39: - | K39: 50.29 | L39: - | M39: - | N39: - | O39: - | P39: - | Q39: - | R39: - | S39: - | T39: - | U39: - | V39: - | W39: - | X39: - | Y39: - | Z39: - | AA39: - | AB39: - | AC39: - | AD39: - | AE39: -
A40: Increase (decrease) in cash and cash equivalents | B40: 1274 | C40: 1096 | D40: -378 | E40: 1188 | F40: 3182 | G40: -1042 | H40: -1782 | I40: 1713.64 | J40: 261.8 | K40: -578.36 | L40: 1439.94 | M40: 1810.27 | N40: 1370.74 | O40: 371.28 | P40: 4234.24 | Q40: 533.97 | R40: 465.21 | S40: 1359.52 | T40: -189.78 | U40: 290.15 | V40: 101.26 | W40: 630.08 | X40: 877.64 | Y40: 5.42 | Z40: 1573.59 | AA40: 212.98 | AB40: 687.72 | AC40: 1094.66 | AD40: 273.46 | AE40: 1429.35
A41: Cash and cash equivalents, beginning of year | B41: 7377 | C41: 8652 | D41: 9748 | E41: 9371 | F41: 7377 | G41: 10559 | H41: 9517 | I41: 7896.55 | J41: 9710.54 | K41: 10204.99 | L41: 10045.75 | M41: 11705.57 | N41: 13539.34 | O41: 14964.93 | P41: 9902.85 | Q41: 15380.75 | R41: 15917.97 | S41: 16621.18 | T41: 17788.82 | U41: 14557.04 | V41: 19368.06 | W41: 19572.05 | X41: 20140.89 | Y41: 20869.38 | Z41: 15585.35 | AA41: 20623.1 | AB41: 20951.45 | AC41: 21609.42 | AD41: 22558.07 | AE41: 17118.74
A42: Cash and cash equivalents, end of year | B42: 8652 | C42: 9747 | D42: 9370 | E42: 10559 | F42: 10559 | G42: 9517 | H42: 7735 | I42: 9710.54 | J42: 10005.98 | K42: 9902.85 | L42: 11705.57 | M42: 13539.34 | N42: 14964.93 | O42: 15320.51 | P42: 14031.37 | Q42: 15917.97 | R42: 16621.18 | S42: 17788.82 | T42: 17424.65 | U42: 14451 | V42: 19572.05 | W42: 20140.89 | X42: 20869.38 | Y42: 20623.1 | Z42: 17118.74 | AA42: 20951.45 | AB42: 21609.42 | AC42: 22558.07 | AD42: 22559.66 | AE42: 18570.49
