Workbook
Name IQ_CH: 110000
Name IQ_CQ: 5000
Name IQ_CY: 10000
Name IQ_DAILY: 500000
Name IQ_FH: 100000
Name IQ_FQ: 500
Name IQ_FY: 1000
Name IQ_LTM: 2000
Name IQ_MONTH: 15000
Name IQ_NTM: 6000
Name IQ_WEEK: 50000
Name IQ_YTD: 3000

Sheet 3Q26 First look
A1: EXHIBIT 1: TMUS 3Q26 earnings first look
A3: T-Mobile US — Q3 2026 Earnings First Look
A4: $M (except for as noted) | B4: Q3'25 | C4: Q2'26 | D4: Consensus | E4: Actual 3Q26 | F4: YoY Growth | G4: Beat/Miss
A5: Total Revenue | B5: =Revenue!D38 -> 21957 | C5: =Revenue!H38 -> 22791 | D5: =Revenue!I38 -> 23184.12 | E5: 23584 | F5: =IF(E5="","",E5/B5-1) -> 0.074099376 | G5: =IF(E5="","",E5/D5-1) -> 0.017248013
A6: Service Revenue | B6: =Revenue!D31 -> 18241 | C6: =Revenue!H31 -> 18983 | D6: =Revenue!I31 -> 19311.99 | E6: 19375 | F6: =IF(E6="","",E6/B6-1) -> 0.062167644 | G6: =IF(E6="","",E6/D6-1) -> 0.0032627399
A7: Postpaid revenue | B7: =Revenue!D25 -> 14882 | C7: =Revenue!H25 -> 15853 | D7: =Revenue!I25 -> 16096.01 | E7: 16269 | F7: =IF(E7="","",E7/B7-1) -> 0.093199839 | G7: =IF(E7="","",E7/D7-1) -> 0.010747384
A8: Prepaid revenue | B8: =Revenue!D26 -> 2625 | C8: =Revenue!H26 -> 2473 | D8: =Revenue!I26 -> 2481.39 | E8: 2427 | F8: =IF(E8="","",E8/B8-1) -> -0.075428571 | G8: =IF(E8="","",E8/D8-1) -> -0.021919166
A9: Wholesale and other service revenues | B9: =Revenue!D30 -> 734 | C9: =Revenue!H30 -> 657 | D9: =Revenue!I30 -> 733.62 | E9: 679 | F9: =IF(E9="","",E9/B9-1) -> -0.07493188 | G9: =IF(E9="","",E9/D9-1) -> -0.074452714
A10: Equipment Revenues | B10: =Revenue!D34 -> 3465 | C10: =Revenue!H34 -> 3524 | D10: =Revenue!I34 -> 3607.84 | E10: 3929 | F10: =IF(E10="","",E10/B10-1) -> 0.13391053 | G10: =IF(E10="","",E10/D10-1) -> 0.089017251
A11: Cost of services | B11: ='Income statement'!D21 -> 2873 | C11: ='Income statement'!H21 -> 2978 | D11: ='Income statement'!I21 -> 3131.93 | E11: 3007 | F11: =IF(E11="","",E11/B11-1) -> 0.046641142 | G11: =IF(E11="","",E11/D11-1) -> -0.039889142
A12: Cost of equipment sales | B12: ='Income statement'!D24 -> 4853 | C12: ='Income statement'!H24 -> 5055 | D12: ='Income statement'!I24 -> 5045.7 | E12: 5444 | F12: =IF(E12="","",E12/B12-1) -> 0.12178034 | G12: =IF(E12="","",E12/D12-1) -> 0.078938502
A13: Adj. EBITDA | B13: =EBITDA!D22 -> 8684 | C13: =EBITDA!H22 -> 9537 | D13: =EBITDA!I22 -> 9413.94 | E13: 9620 | F13: =IF(E13="","",E13/B13-1) -> 0.10778443 | G13: =IF(E13="","",E13/D13-1) -> 0.021888816
A14: Adj. EBITDA Margin | B14: =B13/B6 -> 0.47607039 | C14: =C13/C6 -> 0.50239688 | D14: =D13/D6 -> 0.48746608 | E14: =IF(E13="","",E13/E6) -> 0.49651613 | F14: =IF(E14="","",E14-B14) -> 0.020445738 | G14: =IF(E14="","",E14-D14) -> 0.0090500523
A15: Core Adj. EBITDA | B15: =EBITDA!D26 -> 8680 | C15: =EBITDA!H26 -> 9537 | D15: =EBITDA!I26 -> 9409.55 | E15: 9620 | F15: =IF(E15="","",E15/B15-1) -> 0.10829493 | G15: =IF(E15="","",E15/D15-1) -> 0.022365575
A16: Core Adj. EBITDA Margin | B16: =B15/B6 -> 0.4758511 | C16: =C15/C6 -> 0.50239688 | D16: =D15/D6 -> 0.48723876 | E16: =IF(E15="","",E15/E6) -> 0.49651613 | F16: =IF(E16="","",E16-B16) -> 0.020665024 | G16: =IF(E16="","",E16-D16) -> 0.0092773722
A17: CapEx | B17: ='Cash flow'!D25 -> 2639 | C17: ='Cash flow'!H25 -> 2703 | D17: ='Cash flow'!I25 -> 2425.62 | E17: 2270 | F17: =IF(E17="","",E17/B17-1) -> -0.13982569 | G17: =IF(E17="","",E17/D17-1) -> -0.064156793
A18: Adj. Free Cash Flow | B18: ='Cash flow'!D54 -> 4818 | C18: ='Cash flow'!H54 -> 4797 | D18: ='Cash flow'!I54 -> 4859.12 | E18: 5071 | F18: =IF(E18="","",E18/B18-1) -> 0.052511416 | G18: =IF(E18="","",E18/D18-1) -> 0.043604603
A19: Diluted EPS | B19: ='Income statement'!D47 -> 2.41 | C19: ='Income statement'!H47 -> 2.99 | D19: ='Income statement'!I47 -> 2.92 | E19: 3.22 | F19: =IF(E19="","",E19/B19-1) -> 0.33609959 | G19: =IF(E19="","",E19/D19-1) -> 0.10273973
A21: Operational metrics
A22: Postpaid Account Net Adds (in 000') | B22: =Retail!D69 -> 396 | C22: =Retail!H69 -> 277 | D22: =Retail!I69 -> 251.92 | E22: 274 | F22: =IF(E22="","",E22/B22-1) -> -0.30808081 | G22: =IF(E22="","",E22/D22-1) -> 0.087646872
A23: Postpaid ARPA (in $) | B23: =Retail!D63 -> 149.44 | C23: =Retail!H63 -> 152.91 | D23: =Retail!I63 -> 153.96 | E23: 155.73 | F23: =IF(E23="","",E23/B23-1) -> 0.042090471 | G23: =IF(E23="","",E23/D23-1) -> 0.011496493
A24: Postpaid Account Churn | B24: =Retail!D67 -> 0.97% | C24: =Retail!H67 -> 0.99% | D24: =Retail!I67 -> 1.05% | E24: 0.0109 | F24: =IF(E24="","",E24-B24) -> 0.0012 | G24: =IF(E24="","",E24-D24) -> 0.0004
A26: Note: Q3'25, Q2'26 and Consensus link to the Visible Alpha consensus tabs (as of 10/28/26). Enter 3Q26 actuals in the shaded 'Actual 3Q26' column; margins, YoY and Beat/Miss calculate automatically. Margins are on service revenue; margin and churn YoY / Beat-Miss shown as percentage-point differences.
Q32: Key takeaways — TMUS 3Q26
Q33: • Clean beat on all headline lines: Total revenue $23,584M (+7.4% YoY) beat consensus by 1.7%, service revenue $19,375M (+6.2% YoY) beat by 0.3%, Adj. EBITDA $9,620M (+10.8% YoY) beat by 2.2%, and diluted EPS of $3.22 (+33.6% YoY) beat the $2.92 consensus by 10.3%.
Q34: • EPS growth is flattered by an easy comp: 3Q25 included a $208M after-tax ($0.18/sh) capitalized-software impairment. 3Q26 still absorbed $0.09/sh of UScellular merger costs (vs. $0.05 in 3Q25), and diluted shares fell to 1,071.6M from 1,126.6M on ongoing buybacks.
Q35: • Adj. EBITDA margin of 49.7% of service revenue was ~90bp above consensus (48.7%) and +204bp YoY. Management credits higher service and equipment revenues, partly offset by higher equipment and service costs. Cost of services ($3,007M, +4.7% YoY) was 4.0% below consensus despite higher wholesale network access costs, Metronet/Lumos installation-fee amortization, and repair & maintenance.
Q36: • Postpaid service revenue of $16,269M grew 9.3% YoY and beat consensus by 1.1%, driven by more average accounts (including the 3Q25 UScellular and Metronet acquisitions) and higher ARPA. Weak spots: prepaid revenue $2,427M (-7.5% YoY, 2.2% below consensus) and wholesale & other $679M (-7.5% YoY, 7.4% below consensus); the materials give no driver for either.
Q37: • Postpaid ARPA of $155.73 (+4.2% YoY, +1.8% QoQ) beat consensus ($153.96) by 1.1%. Drivers: higher fee revenue (tax- and fee-exclusive plans), rate plan modernization, and more customers per account (5G broadband, T-Mobile for Business), partly offset by heavier promotions and bundled offers.
Q38: • Postpaid net account adds of 274K beat consensus (252K) by 8.8% but fell 31% YoY (396K) and were roughly flat QoQ (277K). Churn of 1.09% was 4bp worse than consensus (1.05%), +12bp YoY and +10bp QoQ. Management blames broadband-only accounts (higher churn), the temporary impact of rate plan modernization, and seasonally higher switching.
Q39: • Equipment revenue of $3,929M (+13.4% YoY) beat consensus by 8.9%, while cost of equipment sales of $5,444M (+12.2% YoY) came in 7.9% above consensus. Both reflect a richer high-end phone mix, higher manufacturer pricing and more device liquidations, partly offset by fewer prepaid devices sold. Net impact on EBITDA was largely neutral.
Q40: • Adj. FCF of $5,071M (+5.3% YoY) beat consensus by 4.4%, helped by CapEx of $2,270M (-14.0% YoY, 6.4% below consensus) on the 'planned timing of capital purchases'. With the FY26 ~$10.0B CapEx guide unchanged, Q4 CapEx should step up to ~$2.4B. Operating cash flow of $7,341M fell 1.6% YoY on working-capital outflows; merger-related payments were $198M (vs. $96M).
Q41: • FY26 guidance raised at the midpoint: Core Adj. EBITDA to $37.35–37.45B (from $37.1–37.5B, +$100M at midpoint); operating cash flow to $28.7–28.8B (from $28.4–28.8B, +$150M); Adj. FCF to $18.7–18.8B (from $18.4–18.8B, +$150M). Effective tax rate cut to 24–25% (from 25–26%). Net adds narrowed to ~1.0M (was 950K–1.05M); CapEx ~$10.0B unchanged.
Q42: • Capital returns: $3.5B returned in 3Q26 ($2.4B buybacks of 13.6M shares and $1.1B dividends), and another $791M repurchased through 10/23. The quarterly dividend was raised 15% to $1.17/sh. Net debt / LTM Core Adj. EBITDA eased to 2.2x (from 2.3x in 2Q26).

Sheet 3Q26 Fill-in Prompt
A1: 3Q26 Earnings Fill-in Prompt — for a Claude / Copilot agent in Excel
A2: How to use: select A5:A54, copy (Ctrl+C), and paste into the agent's chat along with the attached earnings files.
A3: Copy the prompt below ↓
A5: ROLE & GOAL
A6: You are a sell-side equity research analyst covering T-Mobile US (TMUS). T-Mobile has just released its 3Q26 earnings. I have attached the earnings materials (these may include the press release, financial statements, investor factbook / trending schedules, and non-GAAP reconciliations). Your job is to (1) fill in the 3Q26 actuals on the '3Q26 First look' sheet of this workbook, (2) verify the automatic YoY Growth and Beat/Miss calculations, and (3) write a short list of key takeaways. Work quickly, but accuracy comes first — every number must be traceable to the attached documents.
A8: STEP 1 — READ THE MATERIALS
A9: • Read all attached files before writing anything. Find the Q3 2026 column (quarter ended September 30, 2026) in each table. Use the quarterly figures only — not year-to-date, nine-month, or full-year totals.
A10: • If two documents show different values for the same metric, use the financial statements / reconciliation tables over the narrative text, and tell me about the conflict at the end.
A12: STEP 2 — FILL IN COLUMN E ('Actual 3Q26') ON THE '3Q26 First look' SHEET
A13: Enter hardcoded values (not formulas) in these cells only. Units: $ in millions unless noted. Enter costs and CapEx as positive numbers.
A14: • E5 Total Revenue — 'Total revenues' from the income statement
A15: • E6 Service Revenue — 'Total service revenues'
... A54: When you finish, reply with: (a) a confirmation of which cells in column E you filled in; (b) a list of any KPIs you could not find; (c) any data conflicts between documents or anything unusual (e.g., restated prior periods or definition changes); and (d) confirmation that you checked columns F and G.

Sheet Consensus 10-28-26 ->

Sheet Retail
A2: T-Mobile US, Inc. | Retail
A3: NASDAQGS:TMUS (MI KEY: 4091145; SPCIQ KEY: 93339)
A5: Visible Alpha
A7: Period Type : Fiscal Quarter, Fiscal Halves, Fiscal Year
A8: Period Start : 2025
A9: Period End : 2030
A10: Currency : Reported
A11: Consensus View : Mean
A12: As Of: 10/28/2026
A14: All numbers in $M unless otherwise indicated | B14: FQ1 2025A | C14: FQ2 2025A | D14: FQ3 2025A | E14: FQ4 2025A | F14: FY2025A | G14: FQ1 2026A | H14: FQ2 2026A | I14: FQ3 2026E | J14: FQ4 2026E | K14: FY2026E | L14: FQ1 2027E | M14: FQ2 2027E | N14: FQ3 2027E | O14: FQ4 2027E | P14: FY2027E | Q14: FQ1 2028E | R14: FQ2 2028E | S14: FQ3 2028E | T14: FQ4 2028E | U14: FY2028E | V14: FQ1 2029E | W14: FQ2 2029E | X14: FQ3 2029E | Y14: FQ4 2029E | Z14: FY2029E | AA14: FQ1 2030E | AB14: FQ2 2030E | AC14: FQ3 2030E | AD14: FQ4 2030E | AE14: FY2030E
A15: Number of Contributors Available | B15: 20 | C15: 20 | D15: 20 | E15: 20 | F15: 22 | G15: 21 | H15: 21 | I15: 21 of 22 | J15: 21 of 22 | K15: 22 of 22 | L15: 13 of 22 | M15: 13 of 22 | N15: 12 of 22 | O15: 12 of 22 | P15: 22 of 22 | Q15: 6 of 22 | R15: 6 of 22 | S15: 6 of 22 | T15: 6 of 22 | U15: 19 of 22 | V15: 5 of 22 | W15: 5 of 22 | X15: 5 of 22 | Y15: 5 of 22 | Z15: 15 of 22 | AA15: 4 of 22 | AB15: 4 of 22 | AC15: 4 of 22 | AD15: 4 of 22 | AE15: 14 of 22
A16: Phone postpaid
A17: Beginning phone - postpaid subscribers(K#) | B17: 79013 | C17: 79508 | D17: 80338 | E17: 84632 | F17: 79013 | G17: 85594 | H17: 85882.28 | I17: 86535.63 | J17: 87252.4 | K17: 85485.82 | L17: 88143.33 | M17: 88512.62 | N17: 89135.84 | O17: 89811.76 | P17: 88053.8 | Q17: 90439.98 | R17: 90737.08 | S17: 91258.98 | T17: 91894.31 | U17: 90384.87 | V17: 92459.84 | W17: 92693.93 | X17: 93165.3 | Y17: 93739.28 | Z17: 92457.91 | AA17: 94316.88 | AB17: 94536.12 | AC17: 94965.13 | AD17: 95459.31 | AE17: 94397.64
A18: Phone - postpaid gross adds(K#) | B18: 2658.81 | C18: 2987.92 | D18: 3209.35 | E18: 3566.46 | F18: 12422.54 | G18: 2794.57 | H18: 2897.53 | I18: 3083.33 | J18: 3381.73 | K18: 12168.93 | L18: 2802.36 | M18: 2903.16 | N18: 3109.06 | O18: 3390.43 | P18: 12193.18 | Q18: 2830.47 | R18: 2858.25 | S18: 3135.66 | T18: 3400.81 | U18: 12256.73 | V18: 2847.79 | W18: 2874.29 | X18: 3139.84 | Y18: 3428.81 | Z18: 12358.37 | AA18: 2870.67 | AB18: 2869.02 | AC18: 3145.6 | AD18: 3409.1 | AE18: 12415.56
A19: Churn rate - phone postpaid(%) | B19: 0.91% | C19: 0.90% | D19: 0.89% | E19: 1.02% | F19: 0.93% | G19: 0.94% | H19: 0.85% | I19: 0.91% | J19: 0.99% | K19: 0.93% | L19: 0.93% | M19: 0.87% | N19: 0.92% | O19: 0.99% | P19: 0.92% | Q19: 0.93% | R19: 0.87% | S19: 0.92% | T19: 1.00% | U19: 0.92% | V19: 0.94% | W19: 0.88% | X19: 0.93% | Y19: 1.02% | Z19: 0.93% | AA19: 0.94% | AB19: 0.86% | AC19: 0.93% | AD19: 1.01% | AE19: 0.92%
A20: Phone - postpaid disconnects(K#) | B20: 2163.81 | C20: 2157.92 | D20: 2202.35 | E20: 2604.46 | F20: 9128.54 | G20: 2394.47 | H20: 2257.01 | I20: 2376.52 | J20: 2603.04 | K20: 9627.26 | L20: 2460.69 | M20: 2304.26 | N20: 2464.24 | O20: 2675.1 | P20: 9826.75 | Q20: 2533.41 | R20: 2371.61 | S20: 2537.7 | T20: 2776.86 | U20: 10097.61 | V20: 2612.7 | W20: 2443.91 | X20: 2608.86 | Y20: 2873.63 | Z20: 10357.84 | AA20: 2651.43 | AB20: 2440.01 | AC20: 2651.42 | AD20: 2888.62 | AE20: 10501.53
A21: Phone - postpaid internal/ organic net adds(K#) | B21: 495 | C21: 830 | D21: 1007 | E21: 962 | F21: 3294 | G21: 406.03 | H21: 653.35 | I21: 712.79 | J21: 780.14 | K21: 2554.04 | L21: 369.29 | M21: 623.23 | N21: 675.91 | O21: 734.29 | P21: 2341.78 | Q21: 297.1 | R21: 521.91 | S21: 635.32 | T21: 656.46 | U21: 2120.46 | V21: 234.08 | W21: 471.38 | X21: 573.98 | Y21: 592.18 | Z21: 1939.13 | AA21: 219.23 | AB21: 429.01 | AC21: 494.18 | AD21: 520.48 | AE21: 1799.95
A22: Phone - postpaid - Base Adjustments(K#) | B22: - | C22: - | D22: 3287 | E22: - | F22: 3287 | G22: -45.1 | H22: - | I22: 63.59 | J22: - | K22: -4.54 | L22: - | M22: - | N22: - | O22: - | P22: 3.85 | Q22: - | R22: - | S22: - | T22: - | U22: - | V22: - | W22: - | X22: - | Y22: - | Z22: - | AA22: - | AB22: - | AC22: - | AD22: - | AE22: -
A23: Phone - postpaid - Total Change in Subscribers(K#) | B23: 495 | C23: 830 | D23: 4294 | E23: 962 | F23: 6581 | G23: 403.21 | H23: 653.35 | I23: 716.77 | J23: 780.14 | K23: 2567.97 | L23: 369.29 | M23: 623.23 | N23: 675.91 | O23: 734.29 | P23: 2351.31 | Q23: 297.1 | R23: 521.91 | S23: 635.32 | T23: 656.46 | U23: 2144.18 | V23: 234.08 | W23: 471.38 | X23: 573.98 | Y23: 592.18 | Z23: 1939.13 | AA23: 219.23 | AB23: 429.01 | AC23: 494.18 | AD23: 520.48 | AE23: 1799.95
A24: Phone - postpaid subscribers(K#) | B24: 79508 | C24: 80338 | D24: 84632 | E24: 85594 | F24: 85594 | G24: 85882.28 | H24: 86535.63 | I24: 87252.4 | J24: 88032.54 | K24: 88053.8 | L24: 88512.62 | M24: 89135.84 | N24: 89811.76 | O24: 90546.04 | P24: 90405.11 | Q24: 90737.08 | R24: 91258.98 | S24: 91894.31 | T24: 92550.77 | U24: 92529.05 | V24: 92693.93 | W24: 93165.3 | X24: 93739.28 | Y24: 94331.47 | Z24: 94397.04 | AA24: 94536.12 | AB24: 94965.13 | AC24: 95459.31 | AD24: 95979.79 | AE24: 96197.59
A25: Phone - postpaid average subscribers(K#) | B25: 79260.5 | C25: 79923 | D25: 82485 | E25: 85113 | F25: 82303.5 | G25: 85680.67 | H25: 86208.95 | I25: 86894.01 | J25: 87642.47 | K25: 86718.28 | L25: 88327.98 | M25: 88824.23 | N25: 89473.8 | O25: 90178.9 | P25: 89208.32 | Q25: 90588.53 | R25: 90998.03 | S25: 91576.65 | T25: 92222.54 | U25: 91442.67 | V25: 92576.88 | W25: 92929.62 | X25: 93452.29 | Y25: 94035.37 | Z25: 93409.87 | AA25: 94426.5 | AB25: 94750.62 | AC25: 95212.22 | AD25: 95719.55 | AE25: 95278.45
A26: Phone - postpaid ARPU($) | B26: 49.38 | C26: 50.62 | D26: 50.71 | E26: 50.71 | F26: 50.35 | G26: 50.4 | H26: 51.17 | I26: 51.21 | J26: 51.53 | K26: 51.11 | L26: 51.04 | M26: 51.8 | N26: 51.8 | O26: 52.11 | P26: 51.8 | Q26: 51.36 | R26: 52.25 | S26: 52.18 | T26: 52.47 | U26: 52.42 | V26: 51.96 | W26: 52.85 | X26: 52.74 | Y26: 53.1 | Z26: 52.73 | AA26: 51.99 | AB26: 52.78 | AC26: 52.62 | AD26: 53.06 | AE26: 53.03
A27: Phone - postpaid revenue | B27: 11741.65 | C27: 12137.11 | D27: 12548.44 | E27: 12948.24 | F27: 49375.44 | G27: 12965.46 | H27: 13210.99 | I27: 13348.32 | J27: 13544.35 | K27: 53153.76 | L27: 13526.59 | M27: 13802.02 | N27: 13903.09 | O27: 14091.55 | P27: 55423.6 | Q27: 13964.73 | R27: 14270.18 | S27: 14342.04 | T27: 14519.31 | U27: 57484.97 | V27: 14442.14 | W27: 14742.81 | X27: 14797.68 | Y27: 14983.23 | Z27: 59022.21 | AA27: 14746.02 | AB27: 15016.36 | AC27: 15046.88 | AD27: 15245.42 | AE27: 60502.33
A29: Postpaid other
A30: Beginning postpaid other - subscribers(K#) | B30: 25105 | C30: 25947 | D30: 26946 | E30: 29431 | F30: 25105 | G30: 30851 | H30: 31634.01 | I30: 32437.83 | J30: 33400.64 | K30: 30808.19 | L30: 34691.01 | M30: 35479.99 | N30: 36282.04 | O30: 37248.13 | P30: 34412.09 | Q30: 38422.18 | R30: 39147.07 | S30: 39879.31 | T30: 40765.04 | U30: 37741.4 | V30: 42089.45 | W30: 42722.35 | X30: 43366.25 | Y30: 44187.17 | Z30: 41157.03 | AA30: 44958.67 | AB30: 45592.65 | AC30: 46253.18 | AD30: 46982.51 | AE30: 43899.09
A31: Postpaid other - gross adds(K#) | B31: 2014.55 | C31: 2109.52 | D31: 2586.89 | E31: 2804.62 | F31: 9515.57 | G31: 2382.84 | H31: 2358.49 | I31: 2445.83 | J31: 2743.26 | K31: 9930.41 | L31: 2130.86 | M31: 2123.83 | N31: 2234.58 | O31: 2555.1 | P31: 10143.06 | Q31: 2379.92 | R31: 2429.38 | S31: 2523.53 | T31: 2788.53 | U31: 10857.63 | V31: 2407.46 | W31: 2450.11 | X31: 2536.66 | Y31: 2798.91 | Z31: 11187.77 | AA31: 2433.53 | AB31: 2473.76 | AC31: 2556.35 | AD31: 2819.35 | AE31: 11546.16
A32: Churn rate - postpaid other(%) | B32: 1.62% | C32: 1.62% | D32: 1.56% | E32: 1.61% | F32: 1.60% | G32: 1.34% | H32: 1.28% | I32: 1.25% | J32: 1.35% | K32: 1.30% | L32: 1.16% | M32: 1.10% | N32: 1.11% | O32: 1.20% | P32: 1.54% | Q32: 1.26% | R32: 1.32% | S32: 1.32% | T32: 1.32% | U32: 1.62% | V32: 1.23% | W32: 1.29% | X32: 1.28% | Y32: 1.28% | Z32: 1.60% | AA32: 1.20% | AB32: 1.25% | AC32: 1.25% | AD32: 1.25% | AE32: 1.58%
A33: Postpaid other - disconnects(K#) | B33: 1239.79 | C33: 1277.14 | D33: 1291.79 | E33: 1461.94 | F33: 5270.66 | G33: 1252.22 | H33: 1225.13 | I33: 1235.28 | J33: 1377.9 | K33: 5090.53 | L33: 1218.04 | M33: 1186.48 | N33: 1231.76 | O33: 1365.22 | P33: 6720.74 | Q33: 1506.93 | R33: 1609.71 | S33: 1644.8 | T33: 1690.46 | U33: 7742.67 | V33: 1611.9 | W33: 1711.98 | X33: 1742.96 | Y33: 1784.58 | Z33: 8264.5 | AA33: 1698.41 | AB33: 1794.53 | AC33: 1821.55 | AD33: 1859.43 | AE33: 8743.33
A34: Postpaid other internal/ organic net adds(K#) | B34: 842 | C34: 902 | D34: 1340 | E34: 1420 | F34: 4504 | G34: 843.56 | H34: 817.48 | I34: 971.1 | J34: 1082.43 | K34: 3714.58 | L34: 817.1 | M34: 832.18 | N34: 992.22 | O34: 1148.33 | P34: 3446.96 | Q34: 776.39 | R34: 783.45 | S34: 929.4 | T34: 1143.35 | U34: 3159.32 | V34: 703.68 | W34: 711.19 | X34: 885.89 | Y34: 1027.13 | Z34: 2947.12 | AA34: 762.05 | AB34: 782.25 | AC34: 815.24 | AD34: 948.9 | AE34: 2851.18
A35: Postpaid other Base Adjustments(K#) | B35: - | C35: 97 | D35: 1145 | E35: - | F35: 1242 | G35: -16.05 | H35: - | I35: - | J35: - | K35: -16.05 | L35: - | M35: - | N35: - | O35: - | P35: - | Q35: - | R35: - | S35: - | T35: - | U35: - | V35: - | W35: - | X35: - | Y35: - | Z35: - | AA35: - | AB35: - | AC35: - | AD35: - | AE35: -
A36: Postpaid other - Total Change in Subscribers(K#) | B36: 842 | C36: 999 | D36: 2485 | E36: 1420 | F36: 5746 | G36: 828.47 | H36: 805.36 | I36: 964.64 | J36: 1065.69 | K36: 3603.9 | L36: 794.8 | M36: 808.13 | N36: 973.52 | O36: 1107.2 | P36: 3349.47 | Q36: 740.84 | R36: 749.31 | S36: 903.92 | T36: 1074.93 | U36: 3081.49 | V36: 657.33 | W36: 669.6 | X36: 846.87 | Y36: 951.55 | Z36: 2894.46 | AA36: 668.26 | AB36: 695.07 | AC36: 764.13 | AD36: 854.51 | AE36: 2774.03
A37: Postpaid other - subscribers(K#) | B37: 25947 | C37: 26946 | D37: 29431 | E37: 30851 | F37: 30851 | G37: 31634.01 | H37: 32437.83 | I37: 33400.64 | J37: 34463.66 | K37: 34412.09 | L37: 35479.99 | M37: 36282.04 | N37: 37248.13 | O37: 38346.58 | P37: 37761.56 | Q37: 39147.07 | R37: 39879.31 | S37: 40765.04 | T37: 41820.7 | U37: 40822.88 | V37: 42722.35 | W37: 43366.25 | X37: 44187.17 | Y37: 45112.53 | Z37: 44051.49 | AA37: 45592.65 | AB37: 46253.18 | AC37: 46982.51 | AD37: 47801.98 | AE37: 46673.12
A38: Postpaid other - average subscribers(K#) | B38: 25526 | C38: 26446.5 | D38: 28188.5 | E38: 30141 | F38: 27978 | G38: 31220.47 | H38: 32035.92 | I38: 32919.23 | J38: 33932.15 | K38: 32573.12 | L38: 35085.5 | M38: 35881.01 | N38: 36765.08 | O38: 37797.35 | P38: 36054.14 | Q38: 38784.62 | R38: 39513.19 | S38: 40322.17 | T38: 41292.87 | U38: 39256.61 | V38: 42405.9 | W38: 43044.3 | X38: 43776.71 | Y38: 44649.85 | Z38: 42573.02 | AA38: 45275.66 | AB38: 45922.92 | AC38: 46617.84 | AD38: 47392.24 | AE38: 45252.09
A39: Postpaid other - ARPU($) | B39: 24.19 | C39: 24.46 | D39: 27.59 | E39: 26.87 | F39: 25.28 | G39: 27.9 | H39: 27.34 | I39: 28.14 | J39: 27.96 | K39: 27.31 | L39: 28.5 | M39: 28.19 | N39: 29.33 | O39: 29.08 | P39: 28.21 | Q39: 29.61 | R39: 29.18 | S39: 30.72 | T39: 30.07 | U39: 29.12 | V39: 30.71 | W39: 30.48 | X39: 32.36 | Y39: 31.23 | Z39: 30.96 | AA39: 31.8 | AB39: 31.58 | AC39: 33.12 | AD39: 32.05 | AE39: 32.24
A40: Postpaid other - revenue | B40: 1852.35 | C40: 1940.89 | D40: 2333.56 | E40: 2429.76 | F40: 8556.56 | G40: 2626.24 | H40: 2621.72 | I40: 2749.18 | J40: 2825.44 | K40: 10675.47 | L40: 3000.84 | M40: 3011.94 | N40: 3175.7 | O40: 3258.5 | P40: 12226.99 | Q40: 3440.68 | R40: 3418.05 | S40: 3612.08 | T40: 3652.95 | U40: 13760.16 | V40: 3889.42 | W40: 3875.68 | X40: 4105.61 | Y40: 4085.1 | Z40: 15902.68 | AA40: 4320.35 | AB40: 4353.97 | AC40: 4633.18 | AD40: 4557.94 | AE40: 17615.69
A42: Postpaid 5G broadband net adds(K#) | B42: 387 | C42: 427 | D42: 607 | E42: 439 | F42: 1860 | G42: 392.29 | H42: 371.96 | I42: 380.55 | J42: 374.24 | K42: 1519.05 | L42: 333.3 | M42: 325.6 | N42: 334.39 | O42: 331.06 | P42: 1310.33 | Q42: 274.49 | R42: 259.32 | S42: 264.74 | T42: 257.14 | U42: 1095.62 | V42: 219.46 | W42: 201.59 | X42: 208.75 | Y42: 199.58 | Z42: 932.98 | AA42: 177.69 | AB42: 161.06 | AC42: 168.83 | AD42: 160.23 | AE42: 804.75
A43: Postpaid other internal/ organic net adds excl 5G broadband(K#) | B43: 453 | C43: 464.33 | D43: 838 | E43: 939 | F43: 2694.33 | G43: 443.11 | H43: 412.42 | I43: 492.39 | J43: 526.51 | K43: 1874.42 | L43: 345.44 | M43: 362.33 | N43: 448.3 | O43: 459.23 | P43: 1554.75 | Q43: 337.45 | R43: 356.7 | S43: 448.4 | T43: 461.21 | U43: 1503.77 | V43: 334.6 | W43: 356 | X43: 453.39 | Y43: 467.89 | Z43: 1478.2 | AA43: 335.94 | AB43: 359.33 | AC43: 462.46 | AD43: 478.5 | AE43: 1472.61
A44: Postpaid other internal/ organic net adds(K#) | B44: 842 | C44: 902 | D44: 1340 | E44: 1420 | F44: 4504 | G44: 843.56 | H44: 817.48 | I44: 971.1 | J44: 1082.43 | K44: 3714.58 | L44: 817.1 | M44: 832.18 | N44: 992.22 | O44: 1148.33 | P44: 3446.96 | Q44: 776.39 | R44: 783.45 | S44: 929.4 | T44: 1143.35 | U44: 3159.32 | V44: 703.68 | W44: 711.19 | X44: 885.89 | Y44: 1027.13 | Z44: 2947.12 | AA44: 762.05 | AB44: 782.25 | AC44: 815.24 | AD44: 948.9 | AE44: 2851.18
A46: 5G broadband customers(K#) | B46: 6854 | C46: 7308 | D46: 7955 | E46: 8450 | F46: 8450 | G46: 8881.54 | H46: 9294.06 | I46: 9709.79 | J46: 10124.35 | K46: 10112.73 | L46: 10458.22 | M46: 10810.55 | N46: 11170.64 | O46: 11529.6 | P46: 11557.8 | Q46: 11679.62 | R46: 11952.89 | S46: 12232.36 | T46: 12507.65 | U46: 12720.55 | V46: 12757.54 | W46: 12939.63 | X46: 13129.41 | Y46: 13314.35 | Z46: 13600.45 | AA46: 13846.93 | AB46: 14031.98 | AC46: 14227.19 | AD46: 14416.83 | AE46: 14641.42
A47: Postpaid other subscribers excl 5G broadband(K#) | B47: 19093 | C47: 19638 | D47: 21476 | E47: 22401 | F47: 22401 | G47: 22756.62 | H47: 23151.76 | I47: 23710.47 | J47: 24376.99 | K47: 24331.09 | L47: 25021.76 | M47: 25471.48 | N47: 26077.49 | O47: 26816.98 | P47: 26232.56 | Q47: 27467.45 | R47: 27926.42 | S47: 28532.68 | T47: 29313.05 | U47: 28138.54 | V47: 29964.81 | W47: 30426.63 | X47: 31057.76 | Y47: 31798.17 | Z47: 30533.15 | AA47: 31745.72 | AB47: 32221.2 | AC47: 32755.32 | AD47: 33385.14 | AE47: 32116.83
A48: Postpaid other - subscribers(K#) | B48: 25947 | C48: 26946 | D48: 29431 | E48: 30851 | F48: 30851 | G48: 31634.01 | H48: 32437.83 | I48: 33400.64 | J48: 34463.66 | K48: 34412.09 | L48: 35479.99 | M48: 36282.04 | N48: 37248.13 | O48: 38346.58 | P48: 37761.56 | Q48: 39147.07 | R48: 39879.31 | S48: 40765.04 | T48: 41820.7 | U48: 40822.88 | V48: 42722.35 | W48: 43366.25 | X48: 44187.17 | Y48: 45112.53 | Z48: 44051.49 | AA48: 45592.65 | AB48: 46253.18 | AC48: 46982.51 | AD48: 47801.98 | AE48: 46673.12
A50: Total postpaid
A51: Postpaid beginning subscribers(K#) | B51: 104118 | C51: 105455 | D51: 107284 | E51: 114063 | F51: 104118 | G51: 116445 | H51: 117631.12 | I51: 119099.56 | J51: 120571.46 | K51: 116288.27 | L51: 122824.7 | M51: 124175 | N51: 125648.23 | O51: 126927.11 | P51: 122424.38 | Q51: 128845.55 | R51: 130161.77 | S51: 131493.88 | T51: 132435 | U51: 128009.92 | V51: 134483.97 | W51: 135772.44 | X51: 137028.55 | Y51: 137720.49 | Z51: 133361.51 | AA51: 139419.44 | AB51: 140585.83 | AC51: 141712.01 | AD51: 142265.22 | AE51: 138130.01
A52: Postpaid gross adds(K#) | B52: 4360.46 | C52: 4772.58 | D52: 5441.86 | E52: 5982.47 | F52: 20557.38 | G52: 4808.98 | H52: 4882.74 | I52: 5172.68 | J52: 5774.53 | K52: 20638.93 | L52: 4972.16 | M52: 5053.96 | N52: 5326.78 | O52: 5993.36 | P52: 21159.95 | Q52: 5307.46 | R52: 5317.08 | S52: 5694.43 | T52: 6319.89 | U52: 21563.74 | V52: 5360.72 | W52: 5354.48 | X52: 5723.26 | Y52: 6350.49 | Z52: 21830.28 | AA52: 5418.85 | AB52: 5400.58 | AC52: 5765.52 | AD52: 6399.3 | AE52: 22124.35
A53: Churn rate - Postpaid(%) | B53: 1.05% | C53: 1.04% | D53: 1.02% | E53: 1.14% | F53: 1.06% | G53: 1.07% | H53: 1.01% | I53: 1.04% | J53: 1.12% | K53: 1.06% | L53: 1.03% | M53: 0.97% | N53: 1.01% | O53: 1.08% | P53: 1.05% | Q53: 1.11% | R53: 1.06% | S53: 1.10% | T53: 1.16% | U53: 1.07% | V53: 1.11% | W53: 1.06% | X53: 1.10% | Y53: 1.16% | Z53: 1.07% | AA53: 1.11% | AB53: 1.05% | AC53: 1.10% | AD53: 1.15% | AE53: 1.07%
A54: Postpaid disconnects(K#) | B54: 3290.64 | C54: 3316.56 | D54: 3375.61 | E54: 3942.04 | F54: 13933 | G54: 3749.85 | H54: 3594.49 | I54: 3728.27 | J54: 4071.28 | K54: 15147.29 | L54: 3818.99 | M54: 3636.3 | N54: 3838.04 | O54: 4135.47 | P54: 15825.71 | Q54: 4304.92 | R54: 4138.53 | S54: 4368.38 | T54: 4650.8 | U54: 16767.26 | V54: 4480.84 | W54: 4305.13 | X54: 4534.99 | Y54: 4818.33 | Z54: 17442.61 | AA54: 4638.63 | AB54: 4453.71 | AC54: 4683.63 | AD54: 4968.15 | AE54: 18062.69
A55: Postpaid - internal/ organic net adds(K#) | B55: 1337 | C55: 1732 | D55: 2347 | E55: 2382 | F55: 7798 | G55: 1251.64 | H55: 1473.96 | I55: 1649.36 | J55: 1844.4 | K55: 6219.36 | L55: 1199.67 | M55: 1487.23 | N55: 1602.7 | O55: 1855.47 | P55: 5723.03 | Q55: 1156.89 | R55: 1351.14 | S55: 1465.6 | T55: 1741.93 | U55: 5206.69 | V55: 1115.33 | W55: 1310.18 | X55: 1374.88 | Y55: 1556.02 | Z55: 4878.09 | AA55: 1017.7 | AB55: 1205.94 | AC55: 1266.82 | AD55: 1450.54 | AE55: 4627.29
A56: Postpaid - Base Adjustments(K#) | B56: - | C56: 97 | D56: 4432 | E56: 35 | F56: 4529 | G56: -61.15 | H56: -16 | I56: - | J56: - | K56: -77.15 | L56: - | M56: - | N56: - | O56: - | P56: - | Q56: - | R56: - | S56: - | T56: - | U56: - | V56: - | W56: - | X56: - | Y56: - | Z56: - | AA56: - | AB56: - | AC56: - | AD56: - | AE56: -
A57: Postpaid - Total Change in Subscribers(K#) | B57: 1337 | C57: 1829 | D57: 6779 | E57: 2382 | F57: 12327 | G57: 1354.04 | H57: 1468.44 | I57: 1471.9 | J57: 1887.16 | K57: 6136.1 | L57: 1350.3 | M57: 1473.23 | N57: 1278.88 | O57: 1920.38 | P57: 5637.75 | Q57: 1316.22 | R57: 1332.1 | S57: 941.12 | T57: 1848.66 | U57: 5129.19 | V57: 1288.47 | W57: 1256.11 | X57: 691.94 | Y57: 1698.95 | Z57: 4768.5 | AA57: 1166.39 | AB57: 1126.18 | AC57: 553.21 | AD57: 1569.89 | AE57: 4464.79
A58: Postpaid subscribers(K#) | B58: 105455 | C58: 107284 | D58: 114063 | E58: 116445 | F58: 116445 | G58: 117631.12 | H58: 119099.56 | I58: 120571.46 | J58: 122458.62 | K58: 122424.38 | L58: 124175 | M58: 125648.23 | N58: 126927.11 | O58: 128847.49 | P58: 128062.12 | Q58: 130161.77 | R58: 131493.88 | S58: 132435 | T58: 134283.66 | U58: 133139.11 | V58: 135772.44 | W58: 137028.55 | X58: 137720.49 | Y58: 139419.44 | Z58: 138130.01 | AA58: 140585.83 | AB58: 141712.01 | AC58: 142265.22 | AD58: 143835.11 | AE58: 142594.8
A59: Postpaid average subscribers(K#) | B59: 104786.5 | C59: 106369.5 | D59: 110673.5 | E59: 115254 | F59: 110281.5 | G59: 116954.1 | H59: 118365.34 | I59: 119835.51 | J59: 121515.04 | K59: 119346.07 | L59: 123499.85 | M59: 124911.62 | N59: 126287.67 | O59: 127887.3 | P59: 125258.83 | Q59: 129503.66 | R59: 130827.82 | S59: 131964.44 | T59: 133359.33 | U59: 130560.44 | V59: 135128.21 | W59: 136400.49 | X59: 137374.52 | Y59: 138569.96 | Z59: 135728.46 | AA59: 140002.63 | AB59: 141148.92 | AC59: 141988.61 | AD59: 143050.16 | AE59: 140345.09
A60: Postpaid ARPU($) | B60: 43.24 | C60: 44.12 | D60: 44.82 | E60: 44.48 | F60: 43.78 | G60: 44.53 | H60: 44.65 | I60: 44.79 | J60: 45 | K60: 44.65 | L60: 44.75 | M60: 44.75 | N60: 45.02 | O60: 45.2 | P60: 45.05 | Q60: 44.9 | R60: 44.86 | S60: 45.2 | T60: 45.31 | U60: 45.5 | V60: 45.28 | W60: 45.19 | X60: 45.65 | Y60: 45.69 | Z60: 46 | AA60: 45.63 | AB60: 45.54 | AC60: 46.02 | AD60: 46.05 | AE60: 46.45
A61: Postpaid customers per account(#) | B61: 3.39 | C61: 3.41 | D61: 3.36 | E61: 3.4 | F61: 3.4 | G61: 3.42 | H61: 3.43 | I61: 3.44 | J61: 3.47 | K61: 3.46 | L61: 3.5 | M61: 3.52 | N61: 3.53 | O61: 3.56 | P61: 3.53 | Q61: 3.57 | R61: 3.59 | S61: 3.59 | T61: 3.62 | U61: 3.6 | V61: 3.63 | W61: 3.65 | X61: 3.64 | Y61: 3.68 | Z61: 3.66 | AA61: 3.69 | AB61: 3.72 | AC61: 3.69 | AD61: 3.74 | AE61: 3.72
A62: Postpaid average accounts(K#) | B62: 30996.5 | C62: 31300.5 | D62: 32740.5 | E62: 34109.5 | F62: 32567 | G62: 34339.5 | H62: 34569.5 | I62: 34821.4 | J62: 35086.14 | K62: 34706.75 | L62: 35320.1 | M62: 35548.19 | N62: 35812.16 | O62: 36076.31 | P62: 35683.79 | Q62: 36290.04 | R62: 36495.72 | S62: 36750.71 | T62: 36984.38 | U62: 36591.79 | V62: 37203.53 | W62: 37381.68 | X62: 37610.73 | Y62: 37807.63 | Z62: 37392.73 | AA62: 37806.6 | AB62: 37937.74 | AC62: 38114.46 | AD62: 38254.85 | AE62: 38059.15
A63: Postpaid ARPA($) | B63: 146.22 | C63: 149.87 | D63: 149.44 | E63: 150.17 | F63: 148.93 | G63: 151.93 | H63: 152.91 | I63: 153.96 | J63: 155.51 | K63: 153.51 | L63: 156.42 | M63: 157.46 | N63: 158.74 | O63: 160.11 | P63: 158.17 | Q63: 160.63 | R63: 161.28 | S63: 162.63 | T63: 163.76 | U63: 162.64 | V63: 165.02 | W63: 165.55 | X63: 167.14 | Y63: 167.97 | Z63: 167.07 | AA63: 168.94 | AB63: 169.41 | AC63: 171.42 | AD63: 172.16 | AE63: 171.35
A64: Postpaid revenues | B64: 13594 | C64: 14078 | D64: 14882 | E64: 15378 | F64: 57932 | G64: 15629 | H64: 15853 | I64: 16096.01 | J64: 16403.48 | K64: 63930.52 | L64: 16596.92 | M64: 16812.97 | N64: 17069.83 | O64: 17340.86 | P64: 67767.9 | Q64: 17487.63 | R64: 17658.59 | S64: 17930.42 | T64: 18169.87 | U64: 71428.58 | V64: 18418.68 | W64: 18566.42 | X64: 18859.26 | Y64: 19051.47 | Z64: 75190.17 | AA64: 19160.79 | AB64: 19282.62 | AC64: 19600.88 | AD64: 19757.8 | AE64: 78549.24
A66: Postpaid accounts gross adds(K#) | B66: 1076.21 | C66: 1176.33 | D66: 1312.71 | E66: 1321.14 | F66: 4886.4 | G66: 1288.39 | H66: 1299.84 | I66: 1347.18 | J66: 1415.62 | K66: 5348.68 | L66: 1295.44 | M66: 1307.49 | N66: 1396.02 | O66: 1434.4 | P66: 5457.3 | Q66: 1306.95 | R66: 1266.48 | S66: 1460.38 | T66: 1366.62 | U66: 5431.05 | V66: 1435.92 | W66: 1148.57 | X66: 1609.62 | Y66: 1290.79 | Z66: 5498.12 | AA66: 1600.39 | AB66: 784.05 | AC66: 1763.67 | AD66: 954.8 | AE66: 5368.26
A67: Postpaid accounts - Churn(%) | B67: 0.94% | C67: 0.92% | D67: 0.97% | E67: 1.04% | F67: 0.96% | G67: 1.04% | H67: 0.99% | I67: 1.05% | J67: 1.08% | K67: 1.04% | L67: 1.04% | M67: 0.98% | N67: 1.03% | O67: 1.08% | P67: 1.04% | Q67: 1.04% | R67: 0.96% | S67: 1.03% | T67: 1.09% | U67: 1.05% | V67: 1.08% | W67: 0.95% | X67: 1.07% | Y67: 1.16% | Z67: 1.07% | AA67: 1.08% | AB67: 0.90% | AC67: 1.06% | AD67: 1.17% | AE67: 1.07%
A68: Postpaid accounts - disconnects(K#) | B68: 874.1 | C68: 863.89 | D68: 952.75 | E68: 1064.22 | F68: 3754.96 | G68: 1071.39 | H68: 1026.71 | I68: 1095.99 | J68: 1138.26 | K68: 4326.56 | L68: 1095.18 | M68: 1045.86 | N68: 1106.07 | O68: 1167.08 | P68: 4444.14 | Q68: 1132.95 | R68: 1057 | S68: 1141.89 | T68: 1215.76 | U68: 4600.63 | V68: 1202.28 | W68: 1069.99 | X68: 1207.94 | Y68: 1311.92 | Z68: 4798.52 | AA68: 1224.01 | AB68: 1018.53 | AC68: 1203.95 | AD68: 1325.65 | AE68: 4859.34
A69: Postpaid account internal/ organic net adds(K#) | B69: 205 | C69: 318 | D69: 396 | E69: 261 | F69: 1180 | G69: 217 | H69: 277 | I69: 251.92 | J69: 277.12 | K69: 1018.14 | L69: 200.07 | M69: 256.12 | N69: 271.83 | O69: 256.46 | P69: 940.76 | Q69: 185.2 | R69: 226.18 | S69: 283.8 | T69: 183.54 | U69: 873.66 | V69: 214.59 | W69: 141.71 | X69: 316.4 | Y69: 77.38 | Z69: 762.04 | AA69: 271.96 | AB69: -9.68 | AC69: 363.12 | AD69: -82.33 | AE69: 661.24
A70: Postpaid account - Base Adjustments(K#) | B70: - | C70: 85 | D70: 2081 | E70: 2166 | F70: 2166 | G70: -18 | H70: -16 | I70: - | J70: - | K70: -32.8 | L70: - | M70: - | N70: - | O70: - | P70: - | Q70: - | R70: - | S70: - | T70: - | U70: - | V70: - | W70: - | X70: - | Y70: - | Z70: - | AA70: - | AB70: - | AC70: - | AD70: - | AE70: -
A71: Postpaid account - Total Change in Subscribers(K#) | B71: 205 | C71: 318 | D71: 396 | E71: 261 | F71: 3346 | G71: 199 | H71: 261 | I71: 251.92 | J71: 277.12 | K71: 994.77 | L71: 200.07 | M71: 256.12 | N71: 271.83 | O71: 256.46 | P71: 940.76 | Q71: 185.2 | R71: 226.18 | S71: 283.8 | T71: 183.54 | U71: 873.66 | V71: 214.59 | W71: 141.71 | X71: 316.4 | Y71: 77.38 | Z71: 762.04 | AA71: 271.96 | AB71: -9.68 | AC71: 363.12 | AD71: -82.33 | AE71: 661.24
A72: Postpaid accounts(K#) | B72: 31099 | C72: 31502 | D72: 33979 | E72: 34240 | F72: 34240 | G72: 34439 | H72: 34700 | I72: 34946.82 | J72: 35223.94 | K72: 35225.94 | L72: 35420.13 | M72: 35676.25 | N72: 35948.08 | O72: 36204.54 | P72: 36166.69 | Q72: 36382.64 | R72: 36608.81 | S72: 36892.61 | T72: 37076.15 | U72: 37021.3 | V72: 37310.82 | W72: 37452.53 | X72: 37768.93 | Y72: 37846.32 | Z72: 37794.81 | AA72: 37942.58 | AB72: 37932.9 | AC72: 38296.02 | AD72: 38213.69 | AE72: 38393.18
A73: Postpaid average accounts(K#) | B73: 30996.5 | C73: 31300.5 | D73: 32740.5 | E73: 34109.5 | F73: 32567 | G73: 34339.5 | H73: 34569.5 | I73: 34821.4 | J73: 35086.14 | K73: 34706.75 | L73: 35320.1 | M73: 35548.19 | N73: 35812.16 | O73: 36076.31 | P73: 35683.79 | Q73: 36290.04 | R73: 36495.72 | S73: 36750.71 | T73: 36984.38 | U73: 36591.79 | V73: 37203.53 | W73: 37381.68 | X73: 37610.73 | Y73: 37807.63 | Z73: 37392.73 | AA73: 37806.6 | AB73: 37937.74 | AC73: 38114.46 | AD73: 38254.85 | AE73: 38059.15
A74: Postpaid ABPU($) | B74: 54.54 | C74: 55.27 | D74: 56.18 | E74: 56.24 | F74: 55.07 | G74: 54.37 | H74: 53.98 | I74: 52.56 | J74: 52.75 | K74: 53.46 | L74: 50.9 | M74: 51.3 | N74: 51.66 | O74: 52.12 | P74: 52.36 | Q74: - | R74: - | S74: - | T74: - | U74: 53.07 | V74: - | W74: - | X74: - | Y74: - | Z74: 54.51 | AA74: - | AB74: - | AC74: - | AD74: - | AE74: 55.23
A75: Postpaid ABPA($) | B75: 184.39 | C75: 187.82 | D75: 189.9 | E75: 190.04 | F75: 186.49 | G75: 192.17 | H75: 192.7 | I75: 181.24 | J75: 183.26 | K75: 184.63 | L75: 177.87 | M75: 180.17 | N75: 182.43 | O75: 185.28 | P75: 184.72 | Q75: - | R75: - | S75: - | T75: - | U75: 190.67 | V75: - | W75: - | X75: - | Y75: - | Z75: 200.3 | AA75: - | AB75: - | AC75: - | AD75: - | AE75: 206.51
A76: Total Billing | B76: 17146 | C76: 17637 | D76: 18652 | E76: 19446 | F76: 72881 | G76: 19797 | H76: 19985 | I76: 18936.05 | J76: 19291.84 | K76: 76703.5 | L76: 18839.02 | M76: 19184.66 | N76: 19553.52 | O76: 19989.32 | P76: 78912.89 | Q76: - | R76: - | S76: - | T76: - | U76: 83420.8 | V76: - | W76: - | X76: - | Y76: - | Z76: 89612.91 | AA76: - | AB76: - | AC76: - | AD76: - | AE76: 94128.97
A78: Prepaid
A79: Prepaid beginning subscribers(K#) | B79: 25410 | C79: 25455 | D79: 25494 | E79: 25886 | F79: 25410 | G79: 25943 | H79: 25949.86 | I79: 25982.16 | J79: 26013.17 | K79: 25921.19 | L79: 26068.07 | M79: 26098.61 | N79: 26129.74 | O79: 26155.53 | P79: 26061.72 | Q79: 26181.91 | R79: 26203.84 | S79: 26234.01 | T79: 26258.12 | U79: 26194.51 | V79: 26287.48 | W79: 26305.33 | X79: 26329.96 | Y79: 26348.5 | Z79: 26265.25 | AA79: 26215.74 | AB79: 26190.3 | AC79: 26188.5 | AD79: 26174.78 | AE79: 26303.46
A80: Prepaid gross adds(K#) | B80: 2089.77 | C80: 2064.22 | D80: 2177.84 | E80: 2202.72 | F80: 8534.56 | G80: 2111.9 | H80: 2091.12 | I80: 2167.6 | J80: 2190.35 | K80: 8551.74 | L80: 2118.27 | M80: 2090.16 | N80: 2170.68 | O80: 2187.53 | P80: 7903.69 | Q80: 2126.57 | R80: 2121.74 | S80: 2183.02 | T80: 2199.18 | U80: 7797.04 | V80: 2135.6 | W80: 2131.94 | X80: 2185.3 | Y80: 2195.07 | Z80: 7692.01 | AA80: 2116.47 | AB80: 2136.8 | AC80: 2167.6 | AD80: 2172.31 | AE80: 7546.78
A81: Churn rate - Prepaid(%) | B81: 2.68% | C81: 2.65% | D81: 2.77% | E81: 2.76% | F81: 2.72% | G81: 2.68% | H81: 2.65% | I81: 2.75% | J81: 2.76% | K81: 2.71% | L81: 2.67% | M81: 2.63% | N81: 2.74% | O81: 2.74% | P81: 2.69% | Q81: 2.68% | R81: 2.66% | S81: 2.74% | T81: 2.73% | U81: 2.66% | V81: 2.67% | W81: 2.65% | X81: 2.72% | Y81: 2.72% | Z81: 2.64% | AA81: 2.70% | AB81: 2.68% | AC81: 2.74% | AD81: 2.73% | AE81: 2.63%
A82: Prepaid disconnects(K#) | B82: 2044.77 | C82: 2025.22 | D82: 2134.84 | E82: 2145.72 | F82: 8350.56 | G82: 2085.85 | H82: 2063.2 | I82: 2140.23 | J82: 2150.41 | K82: 8436.25 | L82: 2089.21 | M82: 2061.47 | N82: 2146.5 | O82: 2149.57 | P82: 8422.13 | Q82: 2102.69 | R82: 2089.63 | S82: 2155.8 | T82: 2153.25 | U82: 8374.1 | V82: 2107 | W82: 2095.87 | X82: 2154.61 | Y82: 2152.92 | Z82: 8333.61 | AA82: 2124.63 | AB82: 2114.77 | AC82: 2158.45 | AD82: 2156.25 | AE82: 8297.71
A83: Prepaid internal/ organic net adds(K#) | B83: 45 | C83: 39 | D83: 43 | E83: 57 | F83: 184 | G83: 29.56 | H83: 31.61 | I83: 33.24 | J83: 45.83 | K83: 141.88 | L83: 34.97 | M83: 30.78 | N83: 25.89 | O83: 34.11 | P83: 139.8 | Q83: 25.86 | R83: 34.94 | S83: 29.48 | T83: 39.27 | U83: 132.55 | V83: 28.6 | W83: 36.07 | X83: 30.7 | Y83: 42.15 | Z83: 116.32 | AA83: -8.15 | AB83: 22.03 | AC83: 9.14 | AD83: 16.06 | AE83: 79.14
A84: Prepaid - Base Adjustments(K#) | B84: 3504 | C84: -211 | D84: 349 | E84: - | F84: 349 | G84: - | H84: - | I84: - | J84: - | K84: - | L84: - | M84: - | N84: - | O84: - | P84: - | Q84: - | R84: - | S84: - | T84: - | U84: - | V84: - | W84: - | X84: - | Y84: - | Z84: - | AA84: - | AB84: - | AC84: - | AD84: - | AE84: -
A85: Prepaid - Total Change in Subscribers(K#) | B85: 45 | C85: 39 | D85: 392 | E85: 57 | F85: 533 | G85: 30.12 | H85: 32.3 | I85: 33.22 | J85: 44.69 | K85: 149.9 | L85: 34.35 | M85: 31.14 | N85: 25.79 | O85: 32.88 | P85: 145.58 | Q85: 21.93 | R85: 30.17 | S85: 24.12 | T85: 31.94 | U85: 132.29 | V85: 17.86 | W85: 24.63 | X85: 18.53 | Y85: 27.3 | Z85: 97.59 | AA85: -25.44 | AB85: -1.8 | AC85: -13.72 | AD85: -9.04 | AE85: 43.1
A86: Prepaid subscribers(K#) | B86: 25455 | C86: 25494 | D86: 25886 | E86: 25943 | F86: 25943 | G86: 25949.86 | H86: 25982.16 | I86: 26013.17 | J86: 26052.3 | K86: 26061.72 | L86: 26098.61 | M86: 26129.74 | N86: 26155.53 | O86: 26188.41 | P86: 26207.29 | Q86: 26203.84 | R86: 26234.01 | S86: 26258.12 | T86: 26290.06 | U86: 26326.8 | V86: 26305.33 | W86: 26329.96 | X86: 26348.5 | Y86: 26375.79 | Z86: 26362.84 | AA86: 26190.3 | AB86: 26188.5 | AC86: 26174.78 | AD86: 26165.74 | AE86: 26346.57
A87: Prepaid average subscribers(K#) | B87: 25432.5 | C87: 25474.5 | D87: 25690 | E87: 25914.5 | F87: 25676.5 | G87: 25934.79 | H87: 25966.01 | I87: 25997.66 | J87: 26032.73 | K87: 25993.1 | L87: 26083.34 | M87: 26114.18 | N87: 26142.64 | O87: 26171.97 | P87: 26136.42 | Q87: 26192.87 | R87: 26218.92 | S87: 26246.07 | T87: 26274.09 | U87: 26260.54 | V87: 26296.41 | W87: 26317.65 | X87: 26339.23 | Y87: 26362.14 | Z87: 26313.98 | AA87: 26203.02 | AB87: 26189.4 | AC87: 26181.64 | AD87: 26170.26 | AE87: 26324.72
A88: Prepaid ARPU($) | B88: 34.64 | C88: 34.58 | D88: 33.93 | E88: 33.33 | F88: 34.14 | G88: 32.31 | H88: 32.05 | I88: 32.32 | J88: 32.24 | K88: 32.09 | L88: 32.55 | M88: 32.25 | N88: 32.26 | O88: 32.2 | P88: 32.03 | Q88: 32.67 | R88: 32.17 | S88: 32.29 | T88: 32.03 | U88: 31.74 | V88: 32.68 | W88: 32.2 | X88: 32.02 | Y88: 31.48 | Z88: 31.51 | AA88: 32.31 | AB88: 32.17 | AC88: 31.66 | AD88: 31.07 | AE88: 31.21
A89: Prepaid revenues | B89: 2643 | C89: 2643 | D89: 2625 | E89: 2586 | F89: 10497 | G89: 2517 | H89: 2473 | I89: 2481.39 | J89: 2482.49 | K89: 9967.21 | L89: 2469.5 | M89: 2443.48 | N89: 2447.14 | O89: 2441.2 | P89: 9886.9 | Q89: 2519.36 | R89: 2476.79 | S89: 2490.96 | T89: 2479.85 | U89: 9914.01 | V89: 2503.4 | W89: 2461.09 | X89: 2452.49 | Y89: 2420.45 | Z89: 9835.13 | AA89: 2427.69 | AB89: 2408.96 | AC89: 2373.86 | AD89: 2338.09 | AE89: 9735.64
A91: Total Retail
A92: Total retail beginning subscriber(K#) | B92: 129528 | C92: 130910 | D92: 132778 | E92: 139949 | F92: 129528 | G92: 142388 | H92: 143578.15 | I92: 145081.15 | J92: 146584.92 | K92: 142208.01 | L92: 148894.09 | M92: 150268.67 | N92: 151772.95 | O92: 153074.84 | P92: 148486.37 | Q92: 155005.09 | R92: 156326.44 | S92: 157683.73 | T92: 158639.87 | U92: 154197.34 | V92: 160688.2 | W92: 161967.65 | X92: 163236.36 | Y92: 163929.99 | Z92: 159594.47 | AA92: 165635.18 | AB92: 166776.13 | AC92: 167900.51 | AD92: 168439.99 | AE92: 164433.47
A93: Total retail gross adds(K#) | B93: 6504.1 | C93: 6896.71 | D93: 7716.88 | E93: 8270.15 | F93: 29387.84 | G93: 7003 | H93: 7083.93 | I93: 7394.7 | J93: 8032.23 | K93: 29513.86 | L93: 7074.35 | M93: 7138.73 | N93: 7475 | O93: 8156.03 | P93: 29877.79 | Q93: 7421.61 | R93: 7477.26 | S93: 7853.45 | T93: 8490.53 | U93: 30102.42 | V93: 7470.67 | W93: 7502.84 | X93: 7873.33 | Y93: 8510.82 | Z93: 30266.01 | AA93: 7518.18 | AB93: 7541.63 | AC93: 7905.68 | AD93: 8549.98 | AE93: 30429.42
A94: Total retail churn rate(%) | B94: 1.36% | C94: 1.35% | D94: 1.35% | E94: 1.43% | F94: 1.36% | G94: 1.36% | H94: 1.31% | I94: 1.34% | J94: 1.41% | K94: 1.35% | L94: 1.32% | M94: 1.26% | N94: 1.31% | O94: 1.36% | P94: 1.33% | Q94: 1.38% | R94: 1.34% | S94: 1.38% | T94: 1.43% | U94: 1.33% | V94: 1.37% | W94: 1.33% | X94: 1.37% | Y94: 1.42% | Z94: 1.33% | AA94: 1.36% | AB94: 1.32% | AC94: 1.36% | AD94: 1.41% | AE94: 1.32%
A95: Total retail disconnects(K#) | B95: 5313.45 | C95: 5322.21 | D95: 5506.19 | E95: 6049.11 | F95: 22191.52 | G95: 5833.75 | H95: 5646.99 | I95: 5864.05 | J95: 6223.56 | K95: 23573.63 | L95: 5915.39 | M95: 5692.65 | N95: 5982.49 | O95: 6289.51 | P95: 24236.81 | Q95: 6461.86 | R95: 6283.04 | S95: 6561.19 | T95: 6844.76 | U95: 25104.04 | V95: 6647.33 | W95: 6458.51 | X95: 6735.97 | Y95: 7020.29 | Z95: 25737.48 | AA95: 6812.94 | AB95: 6614.17 | AC95: 6891.22 | AD95: 7176.73 | AE95: 26315.62
A96: Total retail internal/ organic net adds(K#) | B96: 1382 | C96: 1771 | D96: 2390 | E96: 2439 | F96: 7982 | G96: 1254.45 | H96: 1510.59 | I96: 1715.44 | J96: 1970.97 | K96: 6451.45 | L96: 1092.9 | M96: 1447.87 | N96: 1662.15 | O96: 1953.26 | P96: 5812.44 | Q96: 1038.14 | R96: 1285.07 | S96: 1612 | T96: 1919.27 | U96: 5446.16 | V96: 1032.05 | W96: 1321.02 | X96: 1732.61 | Y96: 1785.29 | Z96: 5252.76 | AA96: 914.57 | AB96: 1200.08 | AC96: 1602.28 | AD96: 1657.6 | AE96: 5093.13
A97: Total retail - Base Adjustments(K#) | B97: 3504 | C97: 97 | D97: 4781 | E97: 35 | F97: 4878 | G97: - | H97: - | I97: - | J97: - | K97: - | L97: - | M97: - | N97: - | O97: - | P97: - | Q97: - | R97: - | S97: - | T97: - | U97: - | V97: - | W97: - | X97: - | Y97: - | Z97: - | AA97: - | AB97: - | AC97: - | AD97: - | AE97: -
A98: Total retail - Total Change in Subscribers(K#) | B98: 1382 | C98: 1868 | D98: 7171 | E98: 2439 | F98: 12860 | G98: 1383 | H98: 1503 | I98: 1503.77 | J98: 1925.62 | K98: 6278.36 | L98: 1374.59 | M98: 1504.27 | N98: 1301.89 | O98: 1947.89 | P98: 5777.29 | Q98: 1321.35 | R98: 1357.3 | S98: 956.13 | T98: 1867.77 | U98: 5247.59 | V98: 1279.45 | W98: 1268.71 | X98: 693.63 | Y98: 1705.19 | Z98: 4839 | AA98: 1140.95 | AB98: 1124.38 | AC98: 539.49 | AD98: 1560.86 | AE98: 4507.89
A99: Total retail subscribers(K#) | B99: 130910 | C99: 132778 | D99: 139949 | E99: 142388 | F99: 142388 | G99: 143578.15 | H99: 145081.15 | I99: 146584.92 | J99: 148510.54 | K99: 148486.37 | L99: 150268.67 | M99: 151772.95 | N99: 153074.84 | O99: 155022.73 | P99: 154263.65 | Q99: 156326.44 | R99: 157683.73 | S99: 158639.87 | T99: 160507.64 | U99: 159444.93 | V99: 161967.65 | W99: 163236.36 | X99: 163929.99 | Y99: 165635.18 | Z99: 164433.47 | AA99: 166776.13 | AB99: 167900.51 | AC99: 168439.99 | AD99: 170000.85 | AE99: 168941.36
A100: Total retail average subscribers(K#) | B100: 130219 | C100: 131844 | D100: 136363.5 | E100: 141168.5 | F100: 135958 | G100: 142886.65 | H100: 144272.99 | I100: 145833.03 | J100: 147547.73 | K100: 145377.79 | L100: 149581.38 | M100: 151020.81 | N100: 152423.89 | O100: 154048.78 | P100: 151415.06 | Q100: 155665.76 | R100: 157005.08 | S100: 158161.8 | T100: 159573.75 | U100: 156829.11 | V100: 161327.93 | W100: 162602.01 | X100: 163583.18 | Y100: 164782.59 | Z100: 162020.15 | AA100: 166205.66 | AB100: 167338.32 | AC100: 168170.25 | AD100: 169220.42 | AE100: 166688.44
A101: Total retail ARPU($) | B101: 41.56 | C101: 42.27 | D101: 42.79 | E101: 42.42 | F101: 41.94 | G101: 42.34 | H101: 42.35 | I101: 42.45 | J101: 42.69 | K101: 42.36 | L101: 42.49 | M101: 42.52 | N101: 42.7 | O101: 42.87 | P101: 42.74 | Q101: 42.68 | R101: 42.61 | S101: 42.89 | T101: 42.98 | U101: 43.17 | V101: 42.97 | W101: 42.87 | X101: 43.2 | Y101: 43.18 | Z101: 43.64 | AA101: 43.3 | AB101: 43.2 | AC101: 43.56 | AD101: 43.53 | AE101: 44.1
A102: Retail service revenue | B102: 16237 | C102: 16721 | D102: 17507 | E102: 17964 | F102: 68429 | G102: 18146 | H102: 18326 | I102: 18577.4 | J102: 18885.98 | K102: 73897.73 | L102: 19066.42 | M102: 19256.45 | N102: 19516.97 | O102: 19782.06 | P102: 77654.8 | Q102: 20006.99 | R102: 20135.38 | S102: 20421.38 | T102: 20649.72 | U102: 81342.59 | V102: 20922.09 | W102: 21027.51 | X102: 21311.75 | Y102: 21471.92 | Z102: 85025.3 | AA102: 21588.47 | AB102: 21691.58 | AC102: 21974.74 | AD102: 22095.89 | AE102: 88284.88
A104: Supplemental informations
A105: Wireless capex | B105: 2451 | C105: 2396 | D105: 2639 | E105: 2469 | F105: 9955 | G105: 2623 | H105: 2703 | I105: 2421.25 | J105: 2342.15 | K105: 10082.31 | L105: 2455.9 | M105: 2512.93 | N105: 2428.23 | O105: 2399.77 | P105: 9877.93 | Q105: 2529.8 | R105: 2587.52 | S105: 2422.58 | T105: 2357.25 | U105: 10091.19 | V105: 2598.15 | W105: 2627.42 | X105: 2439.72 | Y105: 2436.36 | Z105: 10424.93 | AA105: 2644.12 | AB105: 2663.14 | AC105: 2496.64 | AD105: 2555.87 | AE105: 10913.15
A107: Upgrades
A108: Beginning phone - postpaid subscribers(K#) | B108: 79013 | C108: 79508 | D108: 80338 | E108: 84632 | F108: 79013 | G108: 85594 | H108: 85882.28 | I108: 86535.63 | J108: 87252.4 | K108: 85485.82 | L108: 88143.33 | M108: 88512.62 | N108: 89135.84 | O108: 89811.76 | P108: 88053.8 | Q108: 90439.98 | R108: 90737.08 | S108: 91258.98 | T108: 91894.31 | U108: 90384.87 | V108: 92459.84 | W108: 92693.93 | X108: 93165.3 | Y108: 93739.28 | Z108: 92457.91 | AA108: 94316.88 | AB108: 94536.12 | AC108: 94965.13 | AD108: 95459.31 | AE108: 94397.64
A109: Postpaid upgrade rate(%) | B109: 2.80% | C109: 2.50% | D109: 2.70% | E109: 3.80% | F109: 11.80% | G109: 2.80% | H109: 2.60% | I109: 2.77% | J109: 3.88% | K109: 12.37% | L109: 2.79% | M109: 2.61% | N109: 2.78% | O109: 3.86% | P109: 12.48% | Q109: 2.86% | R109: 2.66% | S109: 2.82% | T109: 3.92% | U109: 12.65% | V109: 2.89% | W109: 2.69% | X109: 2.84% | Y109: 3.94% | Z109: 17.47% | AA109: 2.93% | AB109: 2.73% | AC109: 2.90% | AD109: 4.00% | AE109: 18.41%
A110: Postpaid upgrades(K#) | B110: 2212.36 | C110: 1987.7 | D110: 2169.13 | E110: 3216.02 | F110: 9323.53 | G110: 2396.63 | H110: 2232.56 | I110: 2391.72 | J110: 3382.28 | K110: 10592.18 | L110: 2461.9 | M110: 2310.51 | N110: 2475.31 | O110: 3468.49 | P110: 10955.77 | Q110: 2589.23 | R110: 2417.37 | S110: 2578.61 | T110: 3609.99 | U110: 11368.15 | V110: 2673.82 | W110: 2496.35 | X110: 2650.48 | Y110: 3701.48 | Z110: 11409.12 | AA110: 2773.23 | AB110: 2590.73 | AC110: 2761.94 | AD110: 3830.58 | AE110: 11699.59

Sheet Wholesale
A2: T-Mobile US, Inc. | Wholesale
A3: NASDAQGS:TMUS (MI KEY: 4091145; SPCIQ KEY: 93339)
A5: Visible Alpha
A7: Period Type : Fiscal Quarter, Fiscal Halves, Fiscal Year
A8: Period Start : 2025
A9: Period End : 2030
A10: Currency : Reported
A11: Consensus View : Mean
A12: As Of: 10/28/2026
A14: All numbers in $M unless otherwise indicated | B14: FQ1 2025A | C14: FQ2 2025A | D14: FQ3 2025A | E14: FQ4 2025A | F14: FY2025A | G14: FQ1 2026A | H14: FQ2 2026A | I14: FQ3 2026E | J14: FQ4 2026E | K14: FY2026E | L14: FQ1 2027E | M14: FQ2 2027E | N14: FQ3 2027E | O14: FQ4 2027E | P14: FY2027E | Q14: FQ1 2028E | R14: FQ2 2028E | S14: FQ3 2028E | T14: FQ4 2028E | U14: FY2028E | V14: FQ1 2029E | W14: FQ2 2029E | X14: FQ3 2029E | Y14: FQ4 2029E | Z14: FY2029E | AA14: FQ1 2030E | AB14: FQ2 2030E | AC14: FQ3 2030E | AD14: FQ4 2030E | AE14: FY2030E
A15: Number of Contributors Available | B15: 20 | C15: 20 | D15: 20 | E15: 20 | F15: 22 | G15: 21 | H15: 21 | I15: 21 of 22 | J15: 21 of 22 | K15: 22 of 22 | L15: 13 of 22 | M15: 13 of 22 | N15: 12 of 22 | O15: 12 of 22 | P15: 22 of 22 | Q15: 6 of 22 | R15: 6 of 22 | S15: 6 of 22 | T15: 6 of 22 | U15: 19 of 22 | V15: 5 of 22 | W15: 5 of 22 | X15: 5 of 22 | Y15: 5 of 22 | Z15: 15 of 22 | AA15: 4 of 22 | AB15: 4 of 22 | AC15: 4 of 22 | AD15: 4 of 22 | AE15: 14 of 22
A16: Total wholesale beginning subscribers - Boost(K#) | B16: 19222 | C16: 18472 | D16: 17722 | E16: 16972 | F16: 19222 | G16: 16222 | H16: 15972 | I16: 15722 | J16: 15472 | K16: 16222 | L16: - | M16: - | N16: - | O16: - | P16: 15222 | Q16: - | R16: - | S16: - | T16: - | U16: 14222 | V16: - | W16: - | X16: - | Y16: - | Z16: 14222 | AA16: - | AB16: - | AC16: - | AD16: - | AE16: 14222
A17: Total wholesale gross addition - Boost(K#) | B17: 2359.76 | C17: 2236.01 | D17: 2112.26 | E17: 1988.51 | F17: 8696.52 | G17: 2406.01 | H17: 2364.76 | I17: 2323.51 | J17: 2282.26 | K17: 9376.52 | L17: - | M17: - | N17: - | O17: - | P17: 8716.52 | Q17: - | R17: - | S17: - | T17: - | U17: 9386.52 | V17: - | W17: - | X17: - | Y17: - | Z17: 9386.52 | AA17: - | AB17: - | AC17: - | AD17: - | AE17: 9386.52
A18: Total wholesale net adds - Boost(K#) | B18: -750 | C18: -750 | D18: -750 | E18: -750 | F18: -3000 | G18: -250 | H18: -250 | I18: -250 | J18: -250 | K18: -1000 | L18: - | M18: - | N18: - | O18: - | P18: -1000 | Q18: - | R18: - | S18: - | T18: - | U18: - | V18: - | W18: - | X18: - | Y18: - | Z18: - | AA18: - | AB18: - | AC18: - | AD18: - | AE18: -
A19: Total wholesale subscribers - Boost(K#) | B19: 18472 | C19: 17722 | D19: 16972 | E19: 16222 | F19: 16222 | G19: 15972 | H19: 15722 | I19: 15472 | J19: 15222 | K19: 15222 | L19: - | M19: - | N19: - | O19: - | P19: 14222 | Q19: - | R19: - | S19: - | T19: - | U19: 14222 | V19: - | W19: - | X19: - | Y19: - | Z19: 14222 | AA19: - | AB19: - | AC19: - | AD19: - | AE19: 14222
A20: Total wholesale average subscribers - Boost(K#) | B20: 18847 | C20: 18097 | D20: 17347 | E20: 16597 | F20: 17722 | G20: 16097 | H20: 15847 | I20: 15597 | J20: 15347 | K20: 15722 | L20: - | M20: - | N20: - | O20: - | P20: 14722 | Q20: - | R20: - | S20: - | T20: - | U20: 14222 | V20: - | W20: - | X20: - | Y20: - | Z20: 14222 | AA20: - | AB20: - | AC20: - | AD20: - | AE20: 14222
A21: Total wholesale ARPU - Boost($) | B21: 4.15 | C21: 3.78 | D21: 4.01 | E21: 5.28 | F21: 4.95 | G21: 4.35 | H21: 3.83 | I21: 5.08 | J21: 5.49 | K21: 4.68 | L21: - | M21: - | N21: - | O21: - | P21: 4.91 | Q21: - | R21: - | S21: - | T21: - | U21: 5.16 | V21: - | W21: - | X21: - | Y21: - | Z21: 5.41 | AA21: - | AB21: - | AC21: - | AD21: - | AE21: 5.69
A23: Total wholesale beginning subscribers(K#) | B23: - | C23: - | D23: - | E23: - | F23: - | G23: - | H23: - | I23: - | J23: - | K23: - | L23: - | M23: - | N23: - | O23: - | P23: - | Q23: - | R23: - | S23: - | T23: - | U23: - | V23: - | W23: - | X23: - | Y23: - | Z23: - | AA23: - | AB23: - | AC23: - | AD23: - | AE23: -
A24: Total wholesale gross addition(K#) | B24: - | C24: - | D24: - | E24: - | F24: - | G24: - | H24: - | I24: - | J24: - | K24: - | L24: - | M24: - | N24: - | O24: - | P24: - | Q24: - | R24: - | S24: - | T24: - | U24: - | V24: - | W24: - | X24: - | Y24: - | Z24: - | AA24: - | AB24: - | AC24: - | AD24: - | AE24: -
A25: Total wholesale net adds(K#) | B25: 202.22 | C25: 180.24 | D25: 21.59 | E25: 204.26 | F25: 608.32 | G25: 182 | H25: 162.22 | I25: 19.43 | J25: 183.83 | K25: 547.48 | L25: 182 | M25: 162.22 | N25: 19.43 | O25: 183.83 | P25: 547.48 | Q25: 182 | R25: 162.22 | S25: 19.43 | T25: 183.83 | U25: 547.48 | V25: 182 | W25: 162.22 | X25: 19.43 | Y25: 183.83 | Z25: 547.48 | AA25: 182 | AB25: 162.22 | AC25: 19.43 | AD25: 183.83 | AE25: 547.48
A26: Total wholesale subscribers(K#) | B26: 35051.32 | C26: 35231.57 | D26: 35253.16 | E26: 35457.42 | F26: 35457.42 | G26: 35639.42 | H26: 35801.64 | I26: 35821.07 | J26: 36004.9 | K26: 36004.9 | L26: 36186.9 | M26: 36349.12 | N26: 36368.55 | O26: 36552.39 | P26: 36552.39 | Q26: 36734.39 | R26: 36896.61 | S26: 36916.04 | T26: 37099.87 | U26: 37099.87 | V26: 37281.87 | W26: 37444.09 | X26: 37463.52 | Y26: 37647.35 | Z26: 37647.35 | AA26: 37829.36 | AB26: 37991.57 | AC26: 38011.01 | AD26: 38194.84 | AE26: 38194.84
A27: Total wholesale average subscribers(K#) | B27: 34950.21 | C27: 35141.44 | D27: 35242.36 | E27: 35355.29 | F27: 35248.37 | G27: 35548.42 | H27: 35720.53 | I27: 35811.35 | J27: 35912.98 | K27: 35816.76 | L27: 36095.9 | M27: 36268.01 | N27: 36358.84 | O27: 36460.47 | P27: 36364.24 | Q27: 36643.39 | R27: 36815.5 | S27: 36906.32 | T27: 37007.95 | U27: 36911.73 | V27: 37190.87 | W27: 37362.98 | X27: 37453.81 | Y27: 37555.44 | Z27: 37459.21 | AA27: 37738.35 | AB27: 37910.47 | AC27: 38001.29 | AD27: 38102.92 | AE27: 38006.69
A28: Total wholesale ARPU($) | B28: 2.89 | C28: 2.71 | D28: 2.54 | E28: 2.36 | F28: 2.62 | G28: 2.35 | H28: 2.34 | I28: 2.53 | J28: 2.44 | K28: 2.41 | L28: 2.43 | M28: 2.42 | N28: 2.81 | O28: 3.63 | P28: 2.82 | Q28: 2.59 | R28: 2.57 | S28: 2.99 | T28: 3.87 | U28: 3 | V28: 2.7 | W28: 2.69 | X28: 3.13 | Y28: 4.04 | Z28: 3.13 | AA28: 2.77 | AB28: 2.76 | AC28: 3.2 | AD28: 4.14 | AE28: 3.21
A29: Wholesale revenues | B29: 354.99 | C29: 355.35 | D29: 371.11 | E29: 365.54 | F29: 1446.99 | G29: 337.17 | H29: 311.19 | I29: 363.99 | J29: 388.77 | K29: 1401.13 | L29: 351.05 | M29: 348.73 | N29: 374.01 | O29: 420.77 | P29: 1392.14 | Q29: 365.97 | R29: 363.6 | S29: 390.69 | T29: 441.11 | U29: 1377.43 | V29: 374.5 | W29: 372.13 | X29: 400.63 | Y29: 453.99 | Z29: 1293.51 | AA29: 380.53 | AB29: 378.16 | AC29: 407.65 | AD29: 463.09 | AE29: 1307.89

Sheet Revenue
A2: T-Mobile US, Inc. | Revenue
A3: NASDAQGS:TMUS (MI KEY: 4091145; SPCIQ KEY: 93339)
A5: Visible Alpha
A7: Period Type : Fiscal Quarter, Fiscal Halves, Fiscal Year
A8: Period Start : 2025
A9: Period End : 2030
A10: Currency : Reported
A11: Consensus View : Mean
A12: As Of: 10/28/2026
A14: All numbers in $M unless otherwise indicated | B14: FQ1 2025A | C14: FQ2 2025A | D14: FQ3 2025A | E14: FQ4 2025A | F14: FY2025A | G14: FQ1 2026A | H14: FQ2 2026A | I14: FQ3 2026E | J14: FQ4 2026E | K14: FY2026E | L14: FQ1 2027E | M14: FQ2 2027E | N14: FQ3 2027E | O14: FQ4 2027E | P14: FY2027E | Q14: FQ1 2028E | R14: FQ2 2028E | S14: FQ3 2028E | T14: FQ4 2028E | U14: FY2028E | V14: FQ1 2029E | W14: FQ2 2029E | X14: FQ3 2029E | Y14: FQ4 2029E | Z14: FY2029E | AA14: FQ1 2030E | AB14: FQ2 2030E | AC14: FQ3 2030E | AD14: FQ4 2030E | AE14: FY2030E
A15: Number of Contributors Available | B15: 20 | C15: 20 | D15: 20 | E15: 20 | F15: 22 | G15: 21 | H15: 21 | I15: 21 of 22 | J15: 21 of 22 | K15: 22 of 22 | L15: 13 of 22 | M15: 13 of 22 | N15: 12 of 22 | O15: 12 of 22 | P15: 22 of 22 | Q15: 6 of 22 | R15: 6 of 22 | S15: 6 of 22 | T15: 6 of 22 | U15: 19 of 22 | V15: 5 of 22 | W15: 5 of 22 | X15: 5 of 22 | Y15: 5 of 22 | Z15: 15 of 22 | AA15: 4 of 22 | AB15: 4 of 22 | AC15: 4 of 22 | AD15: 4 of 22 | AE15: 14 of 22
A16: Segments
A17: Phone - postpaid revenue | B17: 11741.65 | C17: 12137.11 | D17: 12548.44 | E17: 12948.24 | F17: 49375.44 | G17: 12965.46 | H17: 13210.99 | I17: 13348.32 | J17: 13544.35 | K17: 53153.76 | L17: 13526.59 | M17: 13802.02 | N17: 13903.09 | O17: 14091.55 | P17: 55423.6 | Q17: 13964.73 | R17: 14270.18 | S17: 14342.04 | T17: 14519.31 | U17: 57484.97 | V17: 14442.14 | W17: 14742.81 | X17: 14797.68 | Y17: 14983.23 | Z17: 59022.21 | AA17: 14746.02 | AB17: 15016.36 | AC17: 15046.88 | AD17: 15245.42 | AE17: 60502.33
A18: Postpaid 5G broadband revenue | B18: 871.7 | C18: 933.26 | D18: 1019.66 | E18: 1091.77 | F18: 3916.39 | G18: 1172.48 | H18: 1224.29 | I18: 1294.77 | J18: 1350.15 | K18: 5041.69 | L18: 1476.98 | M18: 1512.02 | N18: 1578.2 | O18: 1616.54 | P18: 5984.87 | Q18: 1472.45 | R18: 1510.21 | S18: 1582.4 | T18: 1592.43 | U18: 6783.17 | V18: 1635.88 | W18: 1666.5 | X18: 1735.52 | Y18: 1736.86 | Z18: 7516.8 | AA18: 1775.29 | AB18: 1800.25 | AC18: 1866.96 | AD18: 1861.26 | AE18: 8209.64
A19: Prepaid 5G broadband revenue | B19: 102.09 | C19: 106.71 | D19: 111.55 | E19: 118.49 | F19: 438.85 | G19: 126.01 | H19: 131.07 | I19: 135.77 | J19: 140.38 | K19: 533.23 | L19: 146.03 | M19: 149.35 | N19: 152.53 | O19: 155.49 | P19: 599.4 | Q19: 157.73 | R19: 161.56 | S19: 165.17 | T19: 168.57 | U19: 653.12 | V19: 171.76 | W19: 174.75 | X19: 177.57 | Y19: 180.22 | Z19: 702.04 | AA19: 182.71 | AB19: 185.05 | AC19: 187.25 | AD19: 189.32 | AE19: 747.21
A20: 5G broadband revenue | B20: 976.56 | C20: 1045.66 | D20: 1131.45 | E20: 1213.26 | F20: 4388.58 | G20: 1299.35 | H20: 1361.46 | I20: 1424.25 | J20: 1484.65 | K20: 5586.15 | L20: 1601.41 | M20: 1652.45 | N20: 1711.91 | O20: 1760.32 | P20: 6622.18 | Q20: 1736.63 | R20: 1775.09 | S20: 1824.81 | T20: 1854.03 | U20: 7434.29 | V20: 1846.32 | W20: 1878.66 | X20: 1929.87 | Y20: 1947.62 | Z20: 8116.54 | AA20: 1981.24 | AB20: 2004.79 | AC20: 2048.92 | AD20: 2057.23 | AE20: 8762.67
A21: Fiber revenue | B21: 2.05 | C21: 14.2 | D21: 102.89 | E21: 188.27 | F21: 296.2 | G21: 200.78 | H21: 213.26 | I21: 228.43 | J21: 246 | K21: 888.48 | L21: 280.43 | M21: 311.46 | N21: 335.55 | O21: 360.79 | P21: 1282.9 | Q21: 435.09 | R21: 464.71 | S21: 496.34 | T21: 528.94 | U21: 1762.59 | V21: 615.21 | W21: 656.82 | X21: 699.53 | Y21: 743.36 | Z21: 2321.53 | AA21: 803.15 | AB21: 848.26 | AC21: 894.43 | AD21: 941.68 | AE21: 2978.35
A22: Other revenue - Non FWA | B22: 872.29 | C22: 899.55 | D22: 1117.98 | E22: 1118.3 | F22: 4008.13 | G22: 1326.82 | H22: 1173.95 | I22: 1229.03 | J22: 1241.14 | K22: 4970.94 | L22: - | M22: - | N22: - | O22: - | P22: 5359.85 | Q22: - | R22: - | S22: - | T22: - | U22: 5701.97 | V22: - | W22: - | X22: - | Y22: - | Z22: 6017.11 | AA22: - | AB22: - | AC22: - | AD22: - | AE22: 6306.97
A23: Other excl. 5G broadband revenue | B23: 907.3 | C23: 929.52 | D23: 1165.25 | E23: 1205.4 | F23: 4188.53 | G23: 1326.36 | H23: 1267.92 | I23: 1296.9 | J23: 1303.79 | K23: 5180.58 | L23: 1387.81 | M23: 1341.08 | N23: 1440.15 | O23: 1437.29 | P23: 5761.62 | Q23: 1597.63 | R23: 1548.36 | S23: 1675.31 | T23: 1655.88 | U23: 6537.09 | V23: 1847.03 | W23: 1837.62 | X23: 2025.47 | Y23: 1912.44 | Z23: 7491.1 | AA23: 2070.81 | AB23: 2059.37 | AC23: 2260.64 | AD23: 2135.38 | AE23: 8361.48
A24: Postpaid other - revenue | B24: 1852.35 | C24: 1940.89 | D24: 2333.56 | E24: 2429.76 | F24: 8556.56 | G24: 2626.24 | H24: 2621.72 | I24: 2749.18 | J24: 2825.44 | K24: 10675.47 | L24: 3000.84 | M24: 3011.94 | N24: 3175.7 | O24: 3258.5 | P24: 12226.99 | Q24: 3440.68 | R24: 3418.05 | S24: 3612.08 | T24: 3652.95 | U24: 13760.16 | V24: 3889.42 | W24: 3875.68 | X24: 4105.61 | Y24: 4085.1 | Z24: 15902.68 | AA24: 4320.35 | AB24: 4353.97 | AC24: 4633.18 | AD24: 4557.94 | AE24: 17615.69
A25: Postpaid revenues | B25: 13594 | C25: 14078 | D25: 14882 | E25: 15378 | F25: 57932 | G25: 15629 | H25: 15853 | I25: 16096.01 | J25: 16403.48 | K25: 63930.52 | L25: 16596.92 | M25: 16812.97 | N25: 17069.83 | O25: 17340.86 | P25: 67767.9 | Q25: 17487.63 | R25: 17658.59 | S25: 17930.42 | T25: 18169.87 | U25: 71428.58 | V25: 18418.68 | W25: 18566.42 | X25: 18859.26 | Y25: 19051.47 | Z25: 75190.17 | AA25: 19160.79 | AB25: 19282.62 | AC25: 19600.88 | AD25: 19757.8 | AE25: 78549.24
A26: Prepaid revenues | B26: 2643 | C26: 2643 | D26: 2625 | E26: 2586 | F26: 10497 | G26: 2517 | H26: 2473 | I26: 2481.39 | J26: 2482.49 | K26: 9967.21 | L26: 2469.5 | M26: 2443.48 | N26: 2447.14 | O26: 2441.2 | P26: 9886.9 | Q26: 2519.36 | R26: 2476.79 | S26: 2490.96 | T26: 2479.85 | U26: 9914.01 | V26: 2503.4 | W26: 2461.09 | X26: 2452.49 | Y26: 2420.45 | Z26: 9835.13 | AA26: 2427.69 | AB26: 2408.96 | AC26: 2373.86 | AD26: 2338.09 | AE26: 9735.64
A27: Retail service revenue | B27: 16237 | C27: 16721 | D27: 17507 | E27: 17964 | F27: 68429 | G27: 18146 | H27: 18326 | I27: 18577.4 | J27: 18885.98 | K27: 73897.73 | L27: 19066.42 | M27: 19256.45 | N27: 19516.97 | O27: 19782.06 | P27: 77654.8 | Q27: 20006.99 | R27: 20135.38 | S27: 20421.38 | T27: 20649.72 | U27: 81342.59 | V27: 20922.09 | W27: 21027.51 | X27: 21311.75 | Y27: 21471.92 | Z27: 85025.3 | AA27: 21588.47 | AB27: 21691.58 | AC27: 21974.74 | AD27: 22095.89 | AE27: 88284.88
A28: Wholesale revenues | B28: 354.99 | C28: 355.35 | D28: 371.11 | E28: 365.54 | F28: 1446.99 | G28: 337.17 | H28: 311.19 | I28: 363.99 | J28: 388.77 | K28: 1401.13 | L28: 351.05 | M28: 348.73 | N28: 374.01 | O28: 420.77 | P28: 1392.14 | Q28: 365.97 | R28: 363.6 | S28: 390.69 | T28: 441.11 | U28: 1377.43 | V28: 374.5 | W28: 372.13 | X28: 400.63 | Y28: 453.99 | Z28: 1293.51 | AA28: 380.53 | AB28: 378.16 | AC28: 407.65 | AD28: 463.09 | AE28: 1307.89
A29: Roaming and other service revenues | B29: 333.01 | C29: 361.65 | D29: 362.89 | E29: 372.46 | F29: 1430.01 | G29: 347.83 | H29: 345.81 | I29: 385.85 | J29: 414.18 | K29: 1493.67 | L29: 395.68 | M29: 382.02 | N29: 426.89 | O29: 438.6 | P29: 1527.89 | Q29: 403.6 | R29: 389.66 | S29: 435.43 | T29: 447.37 | U29: 1558.02 | V29: 411.67 | W29: 397.45 | X29: 444.14 | Y29: 456.32 | Z29: 1660.91 | AA29: 419.9 | AB29: 405.4 | AC29: 453.02 | AD29: 465.45 | AE29: 1688.48
A30: Wholesale, roaming and other service revenues | B30: 688 | C30: 717 | D30: 734 | E30: 738 | F30: 2877 | G30: 685 | H30: 657 | I30: 733.62 | J30: 781.67 | K30: 2883.41 | L30: 709.84 | M30: 695.14 | N30: 759 | O30: 792.71 | P30: 2960.38 | Q30: 836.44 | R30: 688.15 | S30: 750.06 | T30: 791.61 | U30: 3084.55 | V30: 859.66 | W30: 686.45 | X30: 753.05 | Y30: 782.31 | Z30: 3083.01 | AA30: 953.58 | AB30: 745.61 | AC30: 827.69 | AD30: 864.78 | AE30: 3227.02
A31: Total service revenues | B31: 16925 | C31: 17438 | D31: 18241 | E31: 18702 | F31: 71306 | G31: 18831 | H31: 18983 | I31: 19311.99 | J31: 19665.06 | K31: 76774.73 | L31: 19777.07 | M31: 19950.65 | N31: 20275.97 | O31: 20574.78 | P31: 80614.1 | Q31: 20843.43 | R31: 20823.53 | S31: 21171.44 | T31: 21441.33 | U31: 84422.97 | V31: 21781.74 | W31: 21713.96 | X31: 22064.79 | Y31: 22254.23 | Z31: 88108.33 | AA31: 22542.06 | AB31: 22437.19 | AC31: 22802.42 | AD31: 22960.68 | AE31: 91511.92
A32: Equipment sales | B32: 3703 | C32: 3433 | D32: 3461 | E32: 5362 | F32: 15959 | G32: 3995 | H32: 3524 | I32: 3613.03 | J32: 5415.77 | K32: 16448.98 | L32: 4041 | M32: 3588.16 | N32: 3690.74 | O32: 5569.75 | P32: 16841.98 | Q32: 4227.77 | R32: 3712.17 | S32: 3821.18 | T32: 5757.47 | U32: 17202.1 | V32: 4328.04 | W32: 3789.86 | X32: 3888.98 | Y32: 5891.73 | Z32: 17731.85 | AA32: 4423.45 | AB32: 3862.73 | AC32: 3974.78 | AD32: 6006.9 | AE32: 18094.43
A33: Lease revenues | B33: 1 | C33: 6 | D33: 4 | E33: 2 | F33: 13 | G33: 1 | H33: 11 | I33: 5.58 | J33: 4.94 | K33: 2.3 | L33: 1.9 | M33: 1.88 | N33: 1.86 | O33: 1.85 | P33: 7.52 | Q33: - | R33: - | S33: - | T33: - | U33: 6.73 | V33: - | W33: - | X33: - | Y33: - | Z33: 6.25 | AA33: - | AB33: - | AC33: - | AD33: - | AE33: 5.56
A34: Equipment revenues | B34: 3704 | C34: 3439 | D34: 3465 | E34: 5364 | F34: 15972 | G34: 3996 | H34: 3524 | I34: 3607.84 | J34: 5412.2 | K34: 16497.78 | L34: 4059.07 | M34: 3600.41 | N34: 3699.42 | O34: 5570.28 | P34: 16923.6 | Q34: 4227.77 | R34: 3712.17 | S34: 3821.18 | T34: 5757.47 | U34: 17346.38 | V34: 4328.04 | W34: 3789.86 | X34: 3888.98 | Y34: 5891.73 | Z34: 17732.74 | AA34: 4423.45 | AB34: 3862.73 | AC34: 3974.78 | AD34: 6006.9 | AE34: 18095.29
A35: Other revenues | B35: 257 | C35: 255 | D35: 251 | E35: 268 | F35: 1031 | G35: 280 | H35: 284 | I35: 268.41 | J35: 276.42 | K35: 1105.62 | L35: 289.73 | M35: 294.26 | N35: 277.09 | O35: 290.62 | P35: 1132.6 | Q35: 300.97 | R35: 303.52 | S35: 286.66 | T35: 302.35 | U35: 1166.93 | V35: 306.01 | W35: 310.01 | X35: 287 | Y35: 302.58 | Z35: 1194.11 | AA35: 294.8 | AB35: 299.01 | AC35: 273.3 | AD35: 287.34 | AE35: 1198.86
A36: Equipment sales and other revenue | B36: 3961 | C36: 3694 | D36: 3716 | E36: 5632 | F36: 17003 | G36: 4276 | H36: 3808 | I36: 3876.26 | J36: 5688.61 | K36: 17603.4 | L36: 4348.81 | M36: 3894.67 | N36: 3976.51 | O36: 5860.9 | P36: 18056.2 | Q36: 4528.74 | R36: 4015.69 | S36: 4107.84 | T36: 6059.82 | U36: 18513.31 | V36: 4572.86 | W36: 4037.87 | X36: 4118.58 | Y36: 6133.79 | Z36: 18841.56 | AA36: 4644.55 | AB36: 4086.99 | AC36: 4179.75 | AD36: 6222.41 | AE36: 19201.93
A37: Total wireless revenue | B37: 20886 | C37: 21132 | D37: 21957 | E37: 24334 | F37: 88309 | G37: 23107 | H37: 22791 | I37: 23188.25 | J37: 25353.67 | K37: 94378.13 | L37: 24125.87 | M37: 23845.32 | N37: 24252.48 | O37: 26435.68 | P37: 98670.3 | Q37: 25372.17 | R37: 24839.22 | S37: 25279.28 | T37: 27501.15 | U37: 102936.28 | V37: 26354.6 | W37: 25751.82 | X37: 26183.37 | Y37: 28388.02 | Z37: 106949.89 | AA37: 27186.61 | AB37: 26524.18 | AC37: 26982.17 | AD37: 29183.09 | AE37: 110713.85
A38: Total revenues | B38: 20886 | C38: 21132 | D38: 21957 | E38: 24334 | F38: 88309 | G38: 23107 | H38: 22791 | I38: 23184.12 | J38: 25344.2 | K38: 94367.96 | L38: 24125.87 | M38: 23845.32 | N38: 24252.48 | O38: 26435.68 | P38: 98611.83 | Q38: 25372.17 | R38: 24839.22 | S38: 25279.28 | T38: 27501.15 | U38: 102811.96 | V38: 26354.6 | W38: 25751.82 | X38: 26183.37 | Y38: 28388.02 | Z38: 106733.85 | AA38: 27186.61 | AB38: 26524.18 | AC38: 26982.17 | AD38: 29183.09 | AE38: 110416.98
A40: Equipment revenue
A41: Postpaid revenues | B41: 13594 | C41: 14078 | D41: 14882 | E41: 15378 | F41: 57932 | G41: 15629 | H41: 15853 | I41: 16096.01 | J41: 16403.48 | K41: 63930.52 | L41: 16596.92 | M41: 16812.97 | N41: 17069.83 | O41: 17340.86 | P41: 67767.9 | Q41: 17487.63 | R41: 17658.59 | S41: 17930.42 | T41: 18169.87 | U41: 71428.58 | V41: 18418.68 | W41: 18566.42 | X41: 18859.26 | Y41: 19051.47 | Z41: 75190.17 | AA41: 19160.79 | AB41: 19282.62 | AC41: 19600.88 | AD41: 19757.8 | AE41: 78549.24
A42: EIP Billing | B42: 3551 | C42: 3553 | D42: 3766 | E42: 4066 | F42: 14936 | G42: 4167 | H42: 4132 | I42: 4179.08 | J42: 4214.71 | K42: 16789.62 | L42: 4461.65 | M42: 4611.17 | N42: 4765.71 | O42: 4925.42 | P42: 18116.77 | Q42: - | R42: - | S42: - | T42: - | U42: 19460.43 | V42: - | W42: - | X42: - | Y42: - | Z42: 20940.76 | AA42: - | AB42: - | AC42: - | AD42: - | AE42: 22526.98
A43: Lease revenues | B43: 1 | C43: 6 | D43: 4 | E43: 2 | F43: 13 | G43: 1 | H43: 11 | I43: 5.58 | J43: 4.94 | K43: 2.3 | L43: 1.9 | M43: 1.88 | N43: 1.86 | O43: 1.85 | P43: 7.52 | Q43: - | R43: - | S43: - | T43: - | U43: 6.73 | V43: - | W43: - | X43: - | Y43: - | Z43: 6.25 | AA43: - | AB43: - | AC43: - | AD43: - | AE43: 5.56
A44: EIP Billings & Lease revenue | B44: 3552 | C44: 3559 | D44: 3770 | E44: 4068 | F44: 14949 | G44: 4168 | H44: 4132 | I44: 4180.05 | J44: 4215.67 | K44: 16791.24 | L44: 4463.55 | M44: 4613.06 | N44: 4767.57 | O44: 4927.27 | P44: 13589.45 | Q44: - | R44: - | S44: - | T44: - | U44: 14597.12 | V44: - | W44: - | X44: - | Y44: - | Z44: 20944.22 | AA44: - | AB44: - | AC44: - | AD44: - | AE44: 22530.3
A45: Total Billing | B45: 17146 | C45: 17637 | D45: 18652 | E45: 19446 | F45: 72881 | G45: 19797 | H45: 19985 | I45: 18936.05 | J45: 19291.84 | K45: 76703.5 | L45: 18839.02 | M45: 19184.66 | N45: 19553.52 | O45: 19989.32 | P45: 78912.89 | Q45: - | R45: - | S45: - | T45: - | U45: 83420.8 | V45: - | W45: - | X45: - | Y45: - | Z45: 89612.91 | AA45: - | AB45: - | AC45: - | AD45: - | AE45: 94128.97
A47: Phones devices(K#) | B47: 7655.5 | C47: 7778.03 | D47: 8219.11 | E47: 9324.99 | F47: 32488.6 | G47: 8013.58 | H47: 7886.87 | I47: 8153.34 | J47: 9463.91 | K47: 34222.46 | L47: 8083.07 | M47: 7924.21 | N47: 8168.26 | O47: 9307.27 | P47: 34704.73 | Q47: 8215.34 | R47: 8052.95 | S47: 8291.39 | T47: 9458.19 | U47: 35631.21 | V47: 8304.34 | W47: 8121.65 | X47: 8362.51 | Y47: 9551.08 | Z47: 35993.39 | AA47: 8388.05 | AB47: 8194.04 | AC47: 8434.18 | AD47: 9645.8 | AE47: 36719.15
A48: Mobile broadband and IoT devices(K#) | B48: 2113.21 | C48: 2157.95 | D48: 2491.96 | E48: 2715.82 | F48: 9478.94 | G48: 2145.07 | H48: 2154.77 | I48: 2278.22 | J48: 2245.5 | K48: 9042.9 | L48: 2000 | M48: 2000 | N48: 2000 | O48: 2000 | P48: 9299 | Q48: 2000 | R48: 2000 | S48: 2000 | T48: 2000 | U48: 8933.72 | V48: 2000 | W48: 2000 | X48: 2000 | Y48: 2000 | Z48: 8149.31 | AA48: 2000 | AB48: 2000 | AC48: 2000 | AD48: 2000 | AE48: 7865.56
A49: Total Devices Sold(K#) | B49: 10057.48 | C49: 10254.25 | D49: 11075.81 | E49: 12729.26 | F49: 44116.79 | G49: 10799.44 | H49: 10532.13 | I49: 11058.45 | J49: 12666.94 | K49: 45209.23 | L49: 10313.36 | M49: 10097.24 | N49: 10717.85 | O49: 12018.68 | P49: 46265.84 | Q49: 10487.44 | R49: 10211.11 | S49: 10839 | T49: 12210.99 | U49: 47123.16 | V49: 10323.73 | W49: 10137.71 | X49: 10554.97 | Y49: 11956.85 | Z49: 48895.74 | AA49: 10385.7 | AB49: 10192.66 | AC49: 10614.44 | AD49: 12033.61 | AE49: 49846.36
A50: Equipment revenue per device($) | B50: 362.11 | C50: 336.85 | D50: 312.93 | E50: 402.92 | F50: 355.66 | G50: 371.97 | H50: 336.11 | I50: 325.29 | J50: 439.97 | K50: 364.23 | L50: 413.41 | M50: 373.36 | N50: 361.87 | O50: 497.32 | P50: 373.49 | Q50: 413.41 | R50: 373.36 | S50: 361.87 | T50: 497.32 | U50: 374.2 | V50: 442.98 | W50: 396.13 | X50: 385 | Y50: 550 | Z50: 383.59 | AA50: 442.98 | AB50: 396.13 | AC50: 385 | AD50: 550 | AE50: 384.21
A51: Equipment sales | B51: 3703 | C51: 3433 | D51: 3461 | E51: 5362 | F51: 15959 | G51: 3995 | H51: 3524 | I51: 3613.03 | J51: 5415.77 | K51: 16448.98 | L51: 4041 | M51: 3588.16 | N51: 3690.74 | O51: 5569.75 | P51: 16841.98 | Q51: 4227.77 | R51: 3712.17 | S51: 3821.18 | T51: 5757.47 | U51: 17202.1 | V51: 4328.04 | W51: 3789.86 | X51: 3888.98 | Y51: 5891.73 | Z51: 17731.85 | AA51: 4423.45 | AB51: 3862.73 | AC51: 3974.78 | AD51: 6006.9 | AE51: 18094.43
A53: Gross EIP financed | B53: 3565 | C53: 3503 | D53: 3871 | E53: 5774 | F53: 16713 | G53: 4322 | H53: 3958 | I53: 4298.64 | J53: 5783.4 | K53: 18335.71 | L53: 4057.37 | M53: 3568.88 | N53: 3574.28 | O53: 5669.22 | P53: 15207.43 | Q53: - | R53: - | S53: - | T53: - | U53: 16231.69 | V53: - | W53: - | X53: - | Y53: - | Z53: 21768.67 | AA53: - | AB53: - | AC53: - | AD53: - | AE53: 23021.64
A55: Equipment revenues | B55: 3704 | C55: 3439 | D55: 3465 | E55: 5364 | F55: 15972 | G55: 3996 | H55: 3524 | I55: 3607.84 | J55: 5412.2 | K55: 16497.78 | L55: 4059.07 | M55: 3600.41 | N55: 3699.42 | O55: 5570.28 | P55: 16923.6 | Q55: 4227.77 | R55: 3712.17 | S55: 3821.18 | T55: 5757.47 | U55: 17346.38 | V55: 4328.04 | W55: 3789.86 | X55: 3888.98 | Y55: 5891.73 | Z55: 17732.74 | AA55: 4423.45 | AB55: 3862.73 | AC55: 3974.78 | AD55: 6006.9 | AE55: 18095.29
A56: Cost of equipment | B56: 4798 | C56: 4659 | D56: 4853 | E56: 6967 | F56: 21277 | G56: 5488 | H56: 5055 | I56: 5045.7 | J56: 7070.42 | K56: 22601.78 | L56: 5501.48 | M56: 5041.32 | N56: 5156.51 | O56: 7233.86 | P56: 22987.02 | Q56: 5707.99 | R56: 5157.68 | S56: 5312.18 | T56: 7407.3 | U56: 23536.37 | V56: 5860.55 | W56: 5280.35 | X56: 5391.7 | Y56: 7553.87 | Z56: 23849.09 | AA56: 5962.29 | AB56: 5423.43 | AC56: 5497.85 | AD56: 7675.6 | AE56: 24297.3
A57: Equipment subsidies | B57: -1094 | C57: -1220 | D57: -1388 | E57: -1603 | F57: -5305 | G57: -1492 | H57: -1531 | I57: -1438.37 | J57: -1649.03 | K57: -6097.86 | L57: -1442.41 | M57: -1440.92 | N57: -1457.09 | O57: -1663.58 | P57: -6058.47 | Q57: -1480.22 | R57: -1445.51 | S57: -1491.01 | T57: -1649.83 | U57: -6189.99 | V57: -1532.51 | W57: -1490.49 | X57: -1502.71 | Y57: -1662.13 | Z57: -6116.34 | AA57: -1538.84 | AB57: -1560.7 | AC57: -1523.07 | AD57: -1668.7 | AE57: -6202.02
A59: Device Financing - Leased Devices
A60: Lease revenues | B60: 1 | C60: 6 | D60: 4 | E60: 2 | F60: 13 | G60: 1 | H60: 11 | I60: 5.58 | J60: 4.94 | K60: 2.3 | L60: 1.9 | M60: 1.88 | N60: 1.86 | O60: 1.85 | P60: 7.52 | Q60: - | R60: - | S60: - | T60: - | U60: 6.73 | V60: - | W60: - | X60: - | Y60: - | Z60: 6.25 | AA60: - | AB60: - | AC60: - | AD60: - | AE60: 5.56
A61: Depreciation and amortization associated with leased devices | B61: 4 | C61: 1 | D61: 0.27 | E61: 0.14 | F61: 5 | G61: - | H61: - | I61: - | J61: - | K61: 0.44 | L61: - | M61: - | N61: - | O61: - | P61: 0.44 | Q61: - | R61: - | S61: - | T61: - | U61: 0.44 | V61: - | W61: - | X61: - | Y61: - | Z61: - | AA61: - | AB61: - | AC61: - | AD61: - | AE61: -
A62: Leased devices transferred from inventory to property and equipment | B62: - | C62: - | D62: - | E62: - | F62: - | G62: - | H62: - | I62: - | J62: - | K62: - | L62: - | M62: - | N62: - | O62: - | P62: - | Q62: - | R62: - | S62: - | T62: - | U62: - | V62: - | W62: - | X62: - | Y62: - | Z62: - | AA62: - | AB62: - | AC62: - | AD62: - | AE62: -
A64: Total subscribers
A65: Total retail subscribers(K#) | B65: 130910 | C65: 132778 | D65: 139949 | E65: 142388 | F65: 142388 | G65: 143578.15 | H65: 145081.15 | I65: 146584.92 | J65: 148510.54 | K65: 148486.37 | L65: 150268.67 | M65: 151772.95 | N65: 153074.84 | O65: 155022.73 | P65: 154263.65 | Q65: 156326.44 | R65: 157683.73 | S65: 158639.87 | T65: 160507.64 | U65: 159444.93 | V65: 161967.65 | W65: 163236.36 | X65: 163929.99 | Y65: 165635.18 | Z65: 164433.47 | AA65: 166776.13 | AB65: 167900.51 | AC65: 168439.99 | AD65: 170000.85 | AE65: 168941.36
A66: Total wholesale subscribers(K#) | B66: 35051.32 | C66: 35231.57 | D66: 35253.16 | E66: 35457.42 | F66: 35457.42 | G66: 35639.42 | H66: 35801.64 | I66: 35821.07 | J66: 36004.9 | K66: 36004.9 | L66: 36186.9 | M66: 36349.12 | N66: 36368.55 | O66: 36552.39 | P66: 36552.39 | Q66: 36734.39 | R66: 36896.61 | S66: 36916.04 | T66: 37099.87 | U66: 37099.87 | V66: 37281.87 | W66: 37444.09 | X66: 37463.52 | Y66: 37647.35 | Z66: 37647.35 | AA66: 37829.36 | AB66: 37991.57 | AC66: 38011.01 | AD66: 38194.84 | AE66: 38194.84
A67: Total wholesale subscribers - Boost(K#) | B67: 18472 | C67: 17722 | D67: 16972 | E67: 16222 | F67: 16222 | G67: 15972 | H67: 15722 | I67: 15472 | J67: 15222 | K67: 15222 | L67: - | M67: - | N67: - | O67: - | P67: 14222 | Q67: - | R67: - | S67: - | T67: - | U67: 14222 | V67: - | W67: - | X67: - | Y67: - | Z67: 14222 | AA67: - | AB67: - | AC67: - | AD67: - | AE67: 14222
A68: Total subscribers(K#) | B68: 142313.32 | C68: 143942.93 | D68: 150875.93 | E68: 153077.3 | F68: 158690.14 | G68: 154287.05 | H68: 155735.51 | I68: 157310.37 | J68: 152623.68 | K68: 152623.68 | L68: 150193.13 | M68: 151781.41 | N68: 153346.79 | O68: 155308.56 | P68: 160020.37 | Q68: - | R68: - | S68: - | T68: - | U68: 168333.26 | V68: - | W68: - | X68: - | Y68: - | Z68: 174013.07 | AA68: - | AB68: - | AC68: - | AD68: - | AE68: 179692.32
A70: Total beginning subscribers(K#) | B70: 141170.1 | C70: 142313.32 | D70: 143942.93 | E70: 150875.93 | F70: 146436.17 | G70: 153077.3 | H70: 154287.05 | I70: 155735.51 | J70: 157310.37 | K70: 158690.14 | L70: 148945.28 | M70: 150193.13 | N70: 151781.41 | O70: 153346.79 | P70: 152623.68 | Q70: - | R70: - | S70: - | T70: - | U70: 162434.55 | V70: - | W70: - | X70: - | Y70: - | Z70: 168333.26 | AA70: - | AB70: - | AC70: - | AD70: - | AE70: 174013.07
A71: Total gross adds(K#) | B71: 5575.93 | C71: 5816.31 | D71: 6402.9 | E71: 7439.62 | F71: 25234.77 | G71: 5933.78 | H71: 5942.85 | I71: 6224.4 | J71: 7359.48 | K71: 25460.5 | L71: 5872.39 | M71: 5900.63 | N71: 6281.63 | O71: 7348.3 | P71: 25402.95 | Q71: 5353.69 | R71: 5167.29 | S71: 5699.53 | T71: 6893.52 | U71: 25573.87 | V71: - | W71: - | X71: - | Y71: - | Z71: 28218.05 | AA71: - | AB71: - | AC71: - | AD71: - | AE71: 28415.38
A72: Total net adds(K#) | B72: 999.98 | C72: 1397.09 | D72: 5658.39 | E72: 1872.7 | F72: 9733.97 | G72: 1064.81 | H72: 1255.77 | I72: 1358.88 | J72: 501.14 | K72: 27.11 | L72: 1247.85 | M72: 1588.28 | N72: 1565.38 | O72: 1961.76 | P72: 4899.28 | Q72: - | R72: - | S72: - | T72: - | U72: 4565.81 | V72: - | W72: - | X72: - | Y72: - | Z72: 4403.21 | AA72: - | AB72: - | AC72: - | AD72: - | AE72: 4369.5
A73: Total subscribers(K#) | B73: 142313.32 | C73: 143942.93 | D73: 150875.93 | E73: 153077.3 | F73: 158690.14 | G73: 154287.05 | H73: 155735.51 | I73: 157310.37 | J73: 152623.68 | K73: 152623.68 | L73: 150193.13 | M73: 151781.41 | N73: 153346.79 | O73: 155308.56 | P73: 160020.37 | Q73: - | R73: - | S73: - | T73: - | U73: 168333.26 | V73: - | W73: - | X73: - | Y73: - | Z73: 174013.07 | AA73: - | AB73: - | AC73: - | AD73: - | AE73: 179692.32
A74: Total average subscribers(K#) | B74: 141741.71 | C74: 143140.25 | D74: 148007.05 | E74: 151976.61 | F74: 152473.26 | G74: 153682.18 | H74: 155011.28 | I74: 156522.94 | J74: 154967.03 | K74: 152790.06 | L74: 149569.21 | M74: 150987.27 | N74: 152564.1 | O74: 154327.67 | P74: 157066.68 | Q74: - | R74: - | S74: - | T74: - | U74: 165383.9 | V74: - | W74: - | X74: - | Y74: - | Z74: 171173.17 | AA74: - | AB74: - | AC74: - | AD74: - | AE74: 176852.7
A75: Total Service ARPU($) | B75: 40.08 | C75: 40.88 | D75: 41.35 | E75: 41.25 | F75: 39.09 | G75: 41.06 | H75: 41.03 | I75: 41.34 | J75: 42.47 | K75: 42 | L75: 44.16 | M75: 44.08 | N75: 44.32 | O75: 44.65 | P75: 42.9 | Q75: - | R75: - | S75: - | T75: - | U75: 42.61 | V75: - | W75: - | X75: - | Y75: - | Z75: 42.91 | AA75: - | AB75: - | AC75: - | AD75: - | AE75: 43.22
A76: Total service revenues | B76: 16925 | C76: 17438 | D76: 18241 | E76: 18702 | F76: 71306 | G76: 18831 | H76: 18983 | I76: 19311.99 | J76: 19665.06 | K76: 76774.73 | L76: 19777.07 | M76: 19950.65 | N76: 20275.97 | O76: 20574.78 | P76: 80614.1 | Q76: 20843.43 | R76: 20823.53 | S76: 21171.44 | T76: 21441.33 | U76: 84422.97 | V76: 21781.74 | W76: 21713.96 | X76: 22064.79 | Y76: 22254.23 | Z76: 88108.33 | AA76: 22542.06 | AB76: 22437.19 | AC76: 22802.42 | AD76: 22960.68 | AE76: 91511.92

Sheet Income statement
A2: T-Mobile US, Inc. | Income statement
A3: NASDAQGS:TMUS (MI KEY: 4091145; SPCIQ KEY: 93339)
A5: Visible Alpha
A7: Period Type : Fiscal Quarter, Fiscal Halves, Fiscal Year
A8: Period Start : 2025
A9: Period End : 2030
A10: Currency : Reported
A11: Consensus View : Mean
A12: As Of: 10/28/2026
A14: All numbers in $M unless otherwise indicated | B14: FQ1 2025A | C14: FQ2 2025A | D14: FQ3 2025A | E14: FQ4 2025A | F14: FY2025A | G14: FQ1 2026A | H14: FQ2 2026A | I14: FQ3 2026E | J14: FQ4 2026E | K14: FY2026E | L14: FQ1 2027E | M14: FQ2 2027E | N14: FQ3 2027E | O14: FQ4 2027E | P14: FY2027E | Q14: FQ1 2028E | R14: FQ2 2028E | S14: FQ3 2028E | T14: FQ4 2028E | U14: FY2028E | V14: FQ1 2029E | W14: FQ2 2029E | X14: FQ3 2029E | Y14: FQ4 2029E | Z14: FY2029E | AA14: FQ1 2030E | AB14: FQ2 2030E | AC14: FQ3 2030E | AD14: FQ4 2030E | AE14: FY2030E
A15: Number of Contributors Available | B15: 20 | C15: 20 | D15: 20 | E15: 20 | F15: 22 | G15: 21 | H15: 21 | I15: 21 of 22 | J15: 21 of 22 | K15: 22 of 22 | L15: 13 of 22 | M15: 13 of 22 | N15: 12 of 22 | O15: 12 of 22 | P15: 22 of 22 | Q15: 6 of 22 | R15: 6 of 22 | S15: 6 of 22 | T15: 6 of 22 | U15: 19 of 22 | V15: 5 of 22 | W15: 5 of 22 | X15: 5 of 22 | Y15: 5 of 22 | Z15: 15 of 22 | AA15: 4 of 22 | AB15: 4 of 22 | AC15: 4 of 22 | AD15: 4 of 22 | AE15: 14 of 22
A16: Total revenues | B16: 20886 | C16: 21132 | D16: 21957 | E16: 24334 | F16: 88309 | G16: 23107 | H16: 22791 | I16: 23184.12 | J16: 25344.2 | K16: 94367.96 | L16: 24125.87 | M16: 23845.32 | N16: 24252.48 | O16: 26435.68 | P16: 98611.83 | Q16: 25372.17 | R16: 24839.22 | S16: 25279.28 | T16: 27501.15 | U16: 102811.96 | V16: 26354.6 | W16: 25751.82 | X16: 26183.37 | Y16: 28388.02 | Z16: 106733.85 | AA16: 27186.61 | AB16: 26524.18 | AC16: 26982.17 | AD16: 29183.09 | AE16: 110416.98
A17: Cost of services - excl synergies & CTA | B17: 2582 | C17: 2689 | D17: 2811 | E17: 3031 | F17: 11113 | G17: 2894 | H17: 2865 | I17: 4258.82 | J17: 4463.67 | K17: 16938.99 | L17: 4365.85 | M17: 4253.27 | N17: 4485.24 | O17: 4701.79 | P17: 17806.15 | Q17: 4554.12 | R17: 4577.4 | S17: 4654.29 | T17: 4694.2 | U17: 18544.71 | V17: 4792.06 | W17: 4813.14 | X17: 4896.15 | Y17: 4925.93 | Z17: 19250.96 | AA17: 5043.81 | AB17: 5062.02 | AC17: 5150.06 | AD17: 5170.57 | AE17: 19845.92
A18: Cost of services - Synergies | B18: 20 | C18: 28 | D18: 55 | E18: 250 | F18: 353 | G18: 101 | H18: 69 | I18: -1337.5 | J18: -1375 | K18: -5345 | L18: -1397.5 | M18: -1422.5 | N18: -1450 | O18: -1450 | P18: -5720 | Q18: -1300 | R18: -1300 | S18: -1300 | T18: -1300 | U18: -5720 | V18: -1300 | W18: -1300 | X18: -1300 | Y18: -1300 | Z18: -5695 | AA18: -1300 | AB18: -1300 | AC18: -1300 | AD18: -1300 | AE18: -5670
A19: Cost of services excl. CTA | B19: 2602 | C19: 2717 | D19: 2873 | E19: 3305 | F19: 11497 | G19: 3339 | H19: 2978 | I19: 3068.14 | J19: 3214.48 | K19: 12304.89 | L19: 3088.38 | M19: 3022.66 | N19: 3086.54 | O19: 3175.06 | P19: 12360.35 | Q19: 3161.93 | R19: 3065.91 | S19: 3155.16 | T19: 3279.06 | U19: 12570.37 | V19: 3289.64 | W19: 3156.37 | X19: 3256.75 | Y19: 3388.5 | Z19: 13157.96 | AA19: 3449.75 | AB19: 3271.8 | AC19: 3402.84 | AD19: 3574.9 | AE19: 13634.67
A20: Merger related costs - cost of services | B20: 15.43 | C20: 25.8 | D20: 7 | E20: 24 | F20: 31 | G20: 344 | H20: 44 | I20: 148.91 | J20: 139.1 | K20: 719.42 | L20: 134.49 | M20: 151.09 | N20: 175.03 | O20: 164.82 | P20: 522.14 | Q20: 319.99 | R20: 343.8 | S20: 373.21 | T20: 399.22 | U20: 1436.23 | V20: 431.36 | W20: 459.59 | X20: 494.49 | Y20: 523.56 | Z20: 1909 | AA20: 559.86 | AB20: 590.28 | AC20: 628.54 | AD20: 659.34 | AE20: 2438.03
A21: Cost of services | B21: 2602 | C21: 2717 | D21: 2873 | E21: 3305 | F21: 11497 | G21: 3339 | H21: 2978 | I21: 3131.93 | J21: 3238.72 | K21: 12637.86 | L21: 3127.01 | M21: 3069.24 | N21: 3117.15 | O21: 3195.14 | P21: 12495.32 | Q21: 3163.65 | R21: 3090.57 | S21: 3174.35 | T21: 3284.28 | U21: 12592.4 | V21: 3294.19 | W21: 3196.18 | X21: 3288.41 | Y21: 3401.88 | Z21: 13185.12 | AA21: 3451.77 | AB21: 3328.93 | AC21: 3442.49 | AD21: 3581.49 | AE21: 13672.07
A22: Cost of equipment, excl. merger related costs | B22: 4798 | C22: 4659 | D22: 4851 | E22: 6959 | F22: 21267 | G22: 5466 | H22: 5032 | I22: 5002.26 | J22: 7223.96 | K22: 22737.6 | L22: 5535.22 | M22: 5101.4 | N22: 5195.21 | O22: 7363.88 | P22: 23201.57 | Q22: 5680.75 | R22: 5167.61 | S22: 5293.22 | T22: 7568.63 | U22: 23711.24 | V22: 5874.22 | W22: 5336.68 | X22: 5338.68 | Y22: 7809.82 | Z22: 24146.59 | AA22: 5935.9 | AB22: 5387.9 | AC22: 5387.48 | AD22: 7889.98 | AE22: 24539.25
A23: Merger related costs - cost of equipment sales | B23: - | C23: - | D23: 2 | E23: 8 | F23: 10 | G23: 22 | H23: 23 | I23: 23 | J23: 22.67 | K23: 75.25 | L23: 50 | M23: 50 | N23: - | O23: - | P23: 100 | Q23: - | R23: - | S23: - | T23: - | U23: - | V23: - | W23: - | X23: - | Y23: - | Z23: - | AA23: - | AB23: - | AC23: - | AD23: - | AE23: -
A24: Cost of equipment | B24: 4798 | C24: 4659 | D24: 4853 | E24: 6967 | F24: 21277 | G24: 5488 | H24: 5055 | I24: 5045.7 | J24: 7070.42 | K24: 22601.78 | L24: 5501.48 | M24: 5041.32 | N24: 5156.51 | O24: 7233.86 | P24: 22987.02 | Q24: 5707.99 | R24: 5157.68 | S24: 5312.18 | T24: 7407.3 | U24: 23536.37 | V24: 5860.55 | W24: 5280.35 | X24: 5391.7 | Y24: 7553.87 | Z24: 23849.09 | AA24: 5962.29 | AB24: 5423.43 | AC24: 5497.85 | AD24: 7675.6 | AE24: 24297.3
A25: Total cost of revenue | B25: 7400 | C25: 7376 | D25: 7726 | E25: 10272 | F25: 32774 | G25: 8827 | H25: 8033 | I25: 8172.32 | J25: 10311.61 | K25: 35277.95 | L25: 8628.49 | M25: 8110.57 | N25: 8273.67 | O25: 10429 | P25: 35491.89 | Q25: 8871.64 | R25: 8248.25 | S25: 8486.53 | T25: 10691.58 | U25: 36128.76 | V25: 9154.74 | W25: 8476.53 | X25: 8680.1 | Y25: 10955.75 | Z25: 37034.21 | AA25: 9414.06 | AB25: 8752.36 | AC25: 8940.34 | AD25: 11257.09 | AE25: 37969.37
A26: SG&A - excl synergies & CTA | B26: 5415 | C26: 5415 | D26: 5828 | E26: 6106 | F26: 22764 | G26: 5709 | H26: 5569 | I26: 5989.04 | J26: 6151.73 | K26: 23418.77 | L26: 5947.77 | M26: 5646.75 | N26: 6055.36 | O26: 6092.85 | P26: 23742.73 | Q26: 6109.04 | R26: 5789.11 | S26: 6205.07 | T26: 6235.36 | U26: 24338.56 | V26: 6242.3 | W26: 5905.02 | X26: 6327.87 | Y26: 6352.3 | Z26: 24827.49 | AA26: 6354 | AB26: 6001.16 | AC26: 6430.7 | AD26: 6450.38 | AE26: 25236.24
A27: SG&A - Wireline and other | B27: - | C27: - | D27: - | E27: - | F27: - | G27: - | H27: - | I27: - | J27: - | K27: - | L27: - | M27: - | N27: - | O27: - | P27: - | Q27: - | R27: - | S27: - | T27: - | U27: - | V27: - | W27: - | X27: - | Y27: - | Z27: - | AA27: - | AB27: - | AC27: - | AD27: - | AE27: -
A28: SG&A - Synergies | B28: 59 | C28: -51 | D28: 123 | E28: 353 | F28: 484 | G28: 209 | H28: 150 | I28: -350 | J28: -402.5 | K28: -1328 | L28: -447.5 | M28: -482.5 | N28: -1090 | O28: -1090 | P28: -4140 | Q28: - | R28: - | S28: - | T28: - | U28: -4140 | V28: - | W28: - | X28: - | Y28: - | Z28: -4140 | AA28: - | AB28: - | AC28: - | AD28: - | AE28: -4140
A29: SG&A - excl. merger related cost | B29: 5474 | C29: 5364 | D29: 5951 | E29: 6459 | F29: 23248 | G29: 5918 | H29: 5719 | I29: 5977.54 | J29: 6264.65 | K29: 23771.29 | L29: 5786.74 | M29: 5697.92 | N29: 5940.78 | O29: 6206.12 | P29: 23791.06 | Q29: 5989.08 | R29: 5884.78 | S29: 6086.99 | T29: 6463.9 | U29: 24381.79 | V29: 6222.07 | W29: 6036.14 | X29: 6347.92 | Y29: 6545.28 | Z29: 25005.19 | AA29: 6387.82 | AB29: 6192.65 | AC29: 6512.02 | AD29: 6706.74 | AE29: 25598.76
A30: Merger related costs/(gains) - SG&A | B30: 14 | C30: 33 | D30: 64 | E30: 111 | F30: 222 | G30: 48 | H30: 115 | I30: 142 | J30: 130.62 | K30: 539.67 | L30: 162.5 | M30: 181.25 | N30: 83.33 | O30: 33.33 | P30: 396.4 | Q30: - | R30: - | S30: - | T30: - | U30: - | V30: - | W30: - | X30: - | Y30: - | Z30: - | AA30: - | AB30: - | AC30: - | AD30: - | AE30: -
A31: Selling, general & administrative | B31: 5488 | C31: 5397 | D31: 6015 | E31: 6570 | F31: 23470 | G31: 5966 | H31: 5834 | I31: 6069.95 | J31: 6328.7 | K31: 24222.85 | L31: 5944.65 | M31: 5878 | N31: 6041.81 | O31: 6274.39 | P31: 24326.64 | Q31: 6048.52 | R31: 5910.29 | S31: 6165.94 | T31: 6377.79 | U31: 24817.49 | V31: 6258.78 | W31: 6096.89 | X31: 6382.21 | Y31: 6511.4 | Z31: 25286.91 | AA31: 6296.11 | AB31: 6074.8 | AC31: 6420.52 | AD31: 6565.23 | AE31: 25774.28
A32: Total other adjustments | B32: 79 | C32: -23 | D32: 278 | E32: 121 | F32: 278 | G32: 282 | H32: 156.33 | I32: 250 | J32: 250 | K32: 605 | L32: 250 | M32: 250 | N32: 250 | O32: 250 | P32: 1000 | Q32: - | R32: - | S32: - | T32: - | U32: - | V32: - | W32: - | X32: - | Y32: - | Z32: - | AA32: - | AB32: - | AC32: - | AD32: - | AE32: -
A33: Depreciation and amortization | B33: 3198 | C33: 3146 | D33: 3408 | E33: 3756 | F33: 13508 | G33: 3817 | H33: 3434 | I33: 3577.37 | J33: 3610.24 | K33: 14416.73 | L33: 3567.64 | M33: 3486.46 | N33: 3522.23 | O33: 3535.48 | P33: 14308.28 | Q33: 3528.41 | R33: 3462.92 | S33: 3504.13 | T33: 3512.84 | U33: 14279.96 | V33: 3524.11 | W33: 3443.97 | X33: 3499.6 | Y33: 3512.66 | Z33: 14257.62 | AA33: 3610.93 | AB33: 3479.38 | AC33: 3544.58 | AD33: 3566.1 | AE33: 14453.64
A34: Total cost and expenses | B34: 16086 | C34: 15919 | D34: 17427 | E34: 20598 | F34: 70030 | G34: 18610 | H34: 17301 | I34: 17828.07 | J34: 20250.16 | K34: 73987.98 | L34: 18160.02 | M34: 17494.25 | N34: 17858.54 | O34: 20259.7 | P34: 74148.79 | Q34: 18448.57 | R34: 17621.46 | S34: 18156.6 | T34: 20582.22 | U34: 75166.54 | V34: 18937.63 | W34: 18017.39 | X34: 18561.91 | Y34: 20979.81 | Z34: 76464.99 | AA34: 19321.1 | AB34: 18306.53 | AC34: 18905.44 | AD34: 21388.42 | AE34: 78033.85
A35: Operating income/(loss) | B35: 4800 | C35: 5213 | D35: 4530 | E35: 3736 | F35: 18279 | G35: 4497 | H35: 5490 | I35: 5321.15 | J35: 5062.42 | K35: 20369.03 | L35: 5950.2 | M35: 6302.68 | N35: 6341.46 | O35: 6170.89 | P35: 24319.91 | Q35: 6923.6 | R35: 7217.76 | S35: 7122.68 | T35: 6918.94 | U35: 27659.84 | V35: 7416.97 | W35: 7734.43 | X35: 7621.46 | Y35: 7408.22 | Z35: 30212.48 | AA35: 7865.5 | AB35: 8217.65 | AC35: 8076.74 | AD35: 7794.66 | AE35: 32273.95
A36: Total interest expense | B36: 916 | C36: 922 | D36: 924 | E36: 1012 | F36: 3774 | G36: 1031 | H36: 1055 | I36: 1039.14 | J36: 1037.73 | K36: 4162.87 | L36: 1176.61 | M36: 1184.12 | N36: 1183.57 | O36: 1225.84 | P36: 4604.88 | Q36: 1224.32 | R36: 1231.25 | S36: 1240.89 | T36: 1280.97 | U36: 4874.1 | V36: 1247.17 | W36: 1243.88 | X36: 1229.99 | Y36: 1287.69 | Z36: 5045.5 | AA36: 1272.9 | AB36: 1266.92 | AC36: 1249.64 | AD36: 1229.27 | AE36: 5147.9
A37: Interest income | B37: - | C37: - | D37: - | E37: - | F37: - | G37: - | H37: - | I37: 10.83 | J37: 12.78 | K37: 23.61 | L37: 3 | M37: 4 | N37: 4 | O37: 6 | P37: 42.88 | Q37: - | R37: - | S37: - | T37: - | U37: 43.26 | V37: - | W37: - | X37: - | Y37: - | Z37: 40.26 | AA37: - | AB37: - | AC37: - | AD37: - | AE37: 40.26
A38: Net interest income/(expense) | B38: -916 | C38: -922 | D38: -924 | E38: -1012 | F38: -3774 | G38: -1031 | H38: -1055 | I38: -1047.72 | J38: -1049.89 | K38: -4190.17 | L38: -1167.64 | M38: -1196.97 | N38: -1200.33 | O38: -1227.9 | P38: -4692.74 | Q38: -1258.12 | R38: -1280.18 | S38: -1275.88 | T38: -1296.32 | U38: -4978.46 | V38: -1302.66 | W38: -1315.67 | X38: -1298.96 | Y38: -1327.58 | Z38: -5210.87 | AA38: -1277.3 | AB38: -1287.68 | AC38: -1261.04 | AD38: -1249.63 | AE38: -5263.24
A39: Other expense, net | B39: -46 | C39: -11 | D39: -78 | E39: -89 | F39: -224 | G39: -132 | H39: -107 | I39: -97.29 | J39: -92.78 | K39: -358.43 | L39: -95.2 | M39: -93.75 | N39: -91.44 | O39: -92.58 | P39: -310.44 | Q39: -92.11 | R39: -86.14 | S39: -83.83 | T39: -82.99 | U39: -265.46 | V39: -87.01 | W39: -79.85 | X39: -77.25 | Y39: -76.46 | Z39: -235.31 | AA39: -65.31 | AB39: -56.07 | AC39: -52.89 | AD39: -52.1 | AE39: -167.71
A40: Total Non-operating expense, net | B40: -962 | C40: -933 | D40: -1002 | E40: -1101 | F40: -3998 | G40: -1163 | H40: -1162 | I40: -1129.25 | J40: -1124.47 | K40: -4547.13 | L40: -1245.58 | M40: -1280.15 | N40: -1277.13 | O40: -1308.23 | P40: -4952.83 | Q40: -1334.88 | R40: -1351.96 | S40: -1345.74 | T40: -1365.48 | U40: -5216.48 | V40: -1372.26 | W40: -1379.55 | X40: -1360.77 | Y40: -1388.75 | Z40: -5336.18 | AA40: -1326.29 | AB40: -1329.73 | AC40: -1300.71 | AD40: -1288.71 | AE40: -5289.83
A41: Income/(loss) before income taxes | B41: 3838 | C41: 4280 | D41: 3528 | E41: 2635 | F41: 14281 | G41: 3334 | H41: 4328 | I41: 4194.71 | J41: 3939.92 | K41: 15822.22 | L41: 4684.83 | M41: 5048.49 | N41: 5094.81 | O41: 4844.94 | P41: 19405.83 | Q41: 5588.72 | R41: 5865.8 | S41: 5776.94 | T41: 5553.45 | U41: 22484.84 | V41: 6044.71 | W41: 6354.88 | X41: 6260.7 | Y41: 6019.47 | Z41: 24859.9 | AA41: 6539.22 | AB41: 6887.92 | AC41: 6776.03 | AD41: 6505.95 | AE41: 26950.3
A42: Provision/(benefit) for income taxes | B42: 885 | C42: 1058 | D42: 814 | E42: 532 | F42: 3289 | G42: 830 | H42: 1089 | I42: 1068.02 | J42: 1009.19 | K42: 4024.25 | L42: 1181.5 | M42: 1275.35 | N42: 1288.18 | O42: 1226.72 | P42: 4914.74 | Q42: 1414.51 | R42: 1489.8 | S42: 1467.58 | T42: 1411.09 | U42: 5693.41 | V42: 1514.71 | W42: 1599.9 | X42: 1576.58 | Y42: 1516.23 | Z42: 6266.32 | AA42: 1641.19 | AB42: 1728.64 | AC42: 1701.02 | AD42: 1633.41 | AE42: 6787.9
A43: Income/(loss) from continuing operations | B43: 2953 | C43: 3222 | D43: 2714 | E43: 2103 | F43: 10992 | G43: 2504 | H43: 3239 | I43: 3135.84 | J43: 2945.41 | K43: 11821.78 | L43: 3503.34 | M43: 3773.14 | N43: 3806.63 | O43: 3618.22 | P43: 14554.97 | Q43: 4174.21 | R43: 4376 | S43: 4309.36 | T43: 4142.36 | U43: 16852.21 | V43: 4530 | W43: 4754.99 | X43: 4684.12 | Y43: 4503.24 | Z43: 18688.21 | AA43: 4898.02 | AB43: 5159.29 | AC43: 5075.01 | AD43: 4872.54 | AE43: 20282.1
A44: Income/(loss) from discontinued operations, net of tax | B44: - | C44: - | D44: - | E44: - | F44: - | G44: - | H44: - | I44: - | J44: - | K44: - | L44: - | M44: - | N44: - | O44: - | P44: - | Q44: - | R44: - | S44: - | T44: - | U44: - | V44: - | W44: - | X44: - | Y44: - | Z44: - | AA44: - | AB44: - | AC44: - | AD44: - | AE44: -
A45: Net income/(loss) | B45: 2953 | C45: 3222 | D45: 2714 | E45: 2103 | F45: 10992 | G45: 2504 | H45: 3239 | I45: 3134.01 | J45: 2948.95 | K45: 11815.28 | L45: 3503.34 | M45: 3773.14 | N45: 3806.63 | O45: 3618.22 | P45: 14548.17 | Q45: 4174.21 | R45: 4376 | S45: 4309.36 | T45: 4142.36 | U45: 16852.21 | V45: 4530 | W45: 4754.99 | X45: 4684.12 | Y45: 4503.24 | Z45: 18688.21 | AA45: 4898.02 | AB45: 5159.29 | AC45: 5075.01 | AD45: 4872.54 | AE45: 20282.1
A46: Basic EPS($) | B46: 2.59 | C46: 2.84 | D46: 2.42 | E46: 1.89 | F46: 9.74 | G46: 2.28 | H46: 2.99 | I46: 2.91 | J46: 2.79 | K46: 10.94 | L46: 3.39 | M46: 3.71 | N46: 3.8 | O46: 3.68 | P46: 14.29 | Q46: 4.27 | R46: 4.55 | S46: 4.56 | T46: 4.47 | U46: 17.51 | V46: 5.01 | W46: 5.36 | X46: 5.38 | Y46: 5.29 | Z46: 21.07 | AA46: 5.73 | AB46: 6.12 | AC46: 6.14 | AD46: 6 | AE46: 24.38
A47: Diluted EPS($) | B47: 2.58 | C47: 2.84 | D47: 2.41 | E47: 1.88 | F47: 9.72 | G47: 2.27 | H47: 2.99 | I47: 2.92 | J47: 2.78 | K47: 10.94 | L47: 3.34 | M47: 3.65 | N47: 3.73 | O47: 3.6 | P47: 14.06 | Q47: 4.26 | R47: 4.55 | S47: 4.56 | T47: 4.46 | U47: 17.17 | V47: 5.01 | W47: 5.35 | X47: 5.38 | Y47: 5.28 | Z47: 20.38 | AA47: 5.72 | AB47: 6.12 | AC47: 6.13 | AD47: 6 | AE47: 23.38
A48: Weighted average shares outstanding - basic(M#) | B48: 1140.54 | C48: 1132.76 | D48: 1123.75 | E48: 1115.21 | F48: 1128.07 | G48: 1100.17 | H48: 1081.77 | I48: 1069.65 | J48: 1055.36 | K48: 1077.87 | L48: 1041.98 | M48: 1028.19 | N48: 1014.05 | O48: 1000.13 | P48: 1029.04 | Q48: 978 | R48: 961.48 | S48: 945.26 | T48: 929.34 | U48: 975.06 | V48: 906.35 | W48: 889.58 | X48: 873.04 | Y48: 856.72 | Z48: 906.42 | AA48: 860.24 | AB48: 845.64 | AC48: 831.32 | AD48: 817.25 | AE48: 859.71
A49: Weighted average shares outstanding - diluted(M#) | B49: 1144.66 | C49: 1134.85 | D49: 1126.63 | E49: 1117.39 | F49: 1130.88 | G49: 1102.05 | H49: 1082.41 | I49: 1071.15 | J49: 1058.52 | K49: 1078.36 | L49: 1046.47 | M49: 1033.51 | N49: 1020.72 | O49: 1007.97 | P49: 1033.07 | Q49: 978.83 | R49: 962.1 | S49: 946.25 | T49: 930.22 | U49: 980.52 | V49: 907.22 | W49: 890.2 | X49: 874.09 | Y49: 857.64 | Z49: 918.98 | AA49: 861.15 | AB49: 846.24 | AC49: 832.46 | AD49: 818.23 | AE49: 874.56
A50: Dividend per share($) | B50: 0.88 | C50: 0.88 | D50: 0.88 | E50: 1.02 | F50: 3.66 | G50: 1.02 | H50: 1.02 | I50: 1.01 | J50: 1.11 | K50: 4.16 | L50: 1.14 | M50: 1.14 | N50: 1.13 | O50: 1.22 | P50: 4.69 | Q50: 1.28 | R50: 1.28 | S50: 1.27 | T50: 1.41 | U50: 5.32 | V50: 1.45 | W50: 1.45 | X50: 1.44 | Y50: 1.6 | Z50: 6.05 | AA50: 1.59 | AB50: 1.59 | AC50: 1.57 | AD50: 1.72 | AE50: 6.82
A52: Supplemental
A53: End of period shares outstanding - Basic(M#) | B53: 1137.34 | C53: 1127.45 | D53: 1118.51 | E53: 1106.93 | F53: 1109.2 | G53: 1085.87 | H53: 1074.82 | I53: 1062.03 | J53: 1048.8 | K53: 1049.16 | L53: 1031.11 | M53: 1014.94 | N53: 998.96 | O53: 984.27 | P53: 993.01 | Q53: 973.34 | R53: 954.26 | S53: 935.58 | T53: 917.31 | U53: 928.28 | V53: 898.79 | W53: 880.59 | X53: 862.67 | Y53: 845.05 | Z53: 864.49 | AA53: 827.73 | AB53: 810.71 | AC53: 793.96 | AD53: 777.49 | AE53: 802.61

Sheet Balance sheet
A2: T-Mobile US, Inc. | Balance sheet
A3: NASDAQGS:TMUS (MI KEY: 4091145; SPCIQ KEY: 93339)
A5: Visible Alpha
A7: Period Type : Fiscal Quarter, Fiscal Halves, Fiscal Year
A8: Period Start : 2025
A9: Period End : 2030
A10: Currency : Reported
A11: Consensus View : Mean
A12: As Of: 10/28/2026
A14: All numbers in $M unless otherwise indicated | B14: FQ1 2025A | C14: FQ2 2025A | D14: FQ3 2025A | E14: FQ4 2025A | F14: FY2025A | G14: FQ1 2026A | H14: FQ2 2026A | I14: FQ3 2026E | J14: FQ4 2026E | K14: FY2026E | L14: FQ1 2027E | M14: FQ2 2027E | N14: FQ3 2027E | O14: FQ4 2027E | P14: FY2027E | Q14: FQ1 2028E | R14: FQ2 2028E | S14: FQ3 2028E | T14: FQ4 2028E | U14: FY2028E | V14: FQ1 2029E | W14: FQ2 2029E | X14: FQ3 2029E | Y14: FQ4 2029E | Z14: FY2029E | AA14: FQ1 2030E | AB14: FQ2 2030E | AC14: FQ3 2030E | AD14: FQ4 2030E | AE14: FY2030E
A15: Number of Contributors Available | B15: 20 | C15: 20 | D15: 20 | E15: 20 | F15: 22 | G15: 21 | H15: 21 | I15: 21 of 22 | J15: 21 of 22 | K15: 22 of 22 | L15: 13 of 22 | M15: 13 of 22 | N15: 12 of 22 | O15: 12 of 22 | P15: 22 of 22 | Q15: 6 of 22 | R15: 6 of 22 | S15: 6 of 22 | T15: 6 of 22 | U15: 19 of 22 | V15: 5 of 22 | W15: 5 of 22 | X15: 5 of 22 | Y15: 5 of 22 | Z15: 15 of 22 | AA15: 4 of 22 | AB15: 4 of 22 | AC15: 4 of 22 | AD15: 4 of 22 | AE15: 14 of 22
A16: Cash, Cash equivalents and short term investments | B16: 12003 | C16: 10259 | D16: 3310 | E16: 5598 | F16: 5598 | G16: 3520 | H16: 2825 | I16: 4728.73 | J16: 5216.03 | K16: 5351.87 | L16: 8699.42 | M16: 9430.65 | N16: 9096.62 | O16: 9315.24 | P16: 8315.52 | Q16: 8244.19 | R16: 7937.68 | S16: 7596.73 | T16: 5899.04 | U16: 9036.03 | V16: 7446.47 | W16: 7679.96 | X16: 7829.76 | Y16: 7608.76 | Z16: 10285.84 | AA16: 5920.99 | AB16: 6358.89 | AC16: 9296.73 | AD16: 7736.44 | AE16: 11296.67
A17: Receivables from Affiliates | B17: - | C17: - | D17: - | E17: - | F17: - | G17: - | H17: - | I17: - | J17: - | K17: - | L17: - | M17: - | N17: - | O17: - | P17: - | Q17: - | R17: - | S17: - | T17: - | U17: - | V17: - | W17: - | X17: - | Y17: - | Z17: - | AA17: - | AB17: - | AC17: - | AD17: - | AE17: -
A18: Accounts receivable, net of allowance | B18: 4392 | C18: 4598 | D18: 5084 | E18: 4874 | F18: 4874 | G18: 4866 | H18: 5247 | I18: 5392.12 | J18: 5536.13 | K18: 5536.98 | L18: 5642.41 | M18: 5772.66 | N18: 5837.42 | O18: 5913.47 | P18: 5954.34 | Q18: 5741.28 | R18: 5849.9 | S18: 5982.23 | T18: 5973.62 | U18: 6114.66 | V18: 6519.53 | W18: 6639.53 | X18: 6793.94 | Y18: 6772.92 | Z18: 6727.32 | AA18: 6979.98 | AB18: 7094.89 | AC18: 7248.91 | AD18: 7228.46 | AE18: 7152.9
A19: Equipment installment plan receivables, net - current | B19: 4294 | C19: 4226 | D19: 4599 | E19: 4997 | F19: 4997 | G19: 4935 | H19: 4715 | I19: 4661.09 | J19: 5072.17 | K19: 5113.72 | L19: 5041.01 | M19: 4904.79 | N19: 4880.47 | O19: 5243.62 | P19: 5297.49 | Q19: 5177.88 | R19: 5076.03 | S19: 5067.3 | T19: 5319.7 | U19: 5512.95 | V19: 5489.42 | W19: 5349.25 | X19: 5329.55 | Y19: 5633.64 | Z19: 5805.08 | AA19: 5663.69 | AB19: 5512.49 | AC19: 5485.81 | AD19: 5784.64 | AE19: 6046.16
A20: Total receiveables | B20: 8686 | C20: 8824 | D20: 9683 | E20: 9871 | F20: 9871 | G20: 9801 | H20: 9962 | I20: 9961.58 | J20: 10500.54 | K20: 10557.3 | L20: 10683.42 | M20: 10677.45 | N20: 10717.88 | O20: 11157.09 | P20: 11094.28 | Q20: 10919.16 | R20: 10925.93 | S20: 11049.53 | T20: 11293.32 | U20: 11371.8 | V20: 12008.95 | W20: 11988.78 | X20: 12123.49 | Y20: 12406.56 | Z20: 12081.41 | AA20: 12643.67 | AB20: 12607.38 | AC20: 12734.72 | AD20: 13013.1 | AE20: 12594.03
A21: Inventories | B21: 1937 | C21: 1690 | D21: 2370 | E21: 2405 | F21: 2405 | G21: 2327 | H21: 2191 | I21: 2281.03 | J21: 2555.6 | K21: 2511.41 | L21: 2373.09 | M21: 2245.89 | N21: 2381.86 | O21: 2687.11 | P21: 2645.54 | Q21: 2382.92 | R21: 2319.71 | S21: 2477.26 | T21: 2444.71 | U21: 2848.42 | V21: 2482.4 | W21: 2395.9 | X21: 2589.64 | Y21: 2543.83 | Z21: 3095.85 | AA21: 2557.84 | AB21: 2468.51 | AC21: 2663.39 | AD21: 2617.56 | AE21: 3279.41
A22: Prepaid expenses | B22: 980 | C22: 1125 | D22: 1128 | E22: 1215 | F22: 1215 | G22: 1067 | H22: 1027 | I22: 1024.92 | J22: 1066.39 | K22: 1084.5 | L22: 1035.79 | M22: 1029.16 | N22: 1042.73 | O22: 1044.51 | P22: 1097.98 | Q22: 1081.64 | R22: 1062.47 | S22: 1086.12 | T22: 1108.89 | U22: 1163.16 | V22: 1176.2 | W22: 1140.57 | X22: 1173.06 | Y22: 1205.2 | Z22: 1145.72 | AA22: 1227.91 | AB22: 1189.34 | AC22: 1222.67 | AD22: 1257.08 | AE22: 1181.56
A23: Deferred tax asset - current | B23: - | C23: - | D23: - | E23: - | F23: - | G23: - | H23: - | I23: - | J23: - | K23: - | L23: - | M23: - | N23: - | O23: - | P23: - | Q23: - | R23: - | S23: - | T23: - | U23: - | V23: - | W23: - | X23: - | Y23: - | Z23: - | AA23: - | AB23: - | AC23: - | AD23: - | AE23: -
A24: Other current assets | B24: 3835 | C24: 4874 | D24: 5212 | E24: 5372 | F24: 5372 | G24: 5403 | H24: 5764 | I24: 5695.37 | J24: 5826.17 | K24: 5588.49 | L24: 5641.57 | M24: 5892.88 | N24: 5765.38 | O24: 5702.04 | P24: 5898.58 | Q24: 4894.61 | R24: 4994.91 | S24: 4886.19 | T24: 4903.36 | U24: 5783.29 | V24: 5974.61 | W24: 6112.52 | X24: 5929.54 | Y24: 5940.26 | Z24: 6084.03 | AA24: 6093.94 | AB24: 6230.3 | AC24: 6039.63 | AD24: 6048.34 | AE24: 6164.59
A25: Deferred tax and other current assets | B25: 4815 | C25: 5999 | D25: 6340 | E25: 6587 | F25: 6587 | G25: 6470 | H25: 6791 | I25: 6625.53 | J25: 6837.32 | K25: 6681.26 | L25: 6911.24 | M25: 7090.63 | N25: 7082.7 | O25: 7201.42 | P25: 7006.15 | Q25: 6302.15 | R25: 6350.83 | S25: 6299.78 | T25: 6323.75 | U25: 7157.11 | V25: 6970.9 | W25: 7022.04 | X25: 6946.8 | Y25: 6968.23 | Z25: 7663.75 | AA25: 7056.43 | AB25: 7105.32 | AC25: 7026.65 | AD25: 7048.21 | AE25: 8013.61
A26: Total current assets | B26: 27441 | C26: 26772 | D26: 21703 | E26: 24461 | F26: 24461 | G26: 22118 | H26: 21769 | I26: 23775.38 | J26: 25242.25 | K26: 25243.78 | L26: 28450.77 | M26: 29166.99 | N26: 28966.5 | O26: 29907.08 | P26: 29196.5 | Q26: 27176.2 | R26: 26827 | S26: 26607.93 | T26: 24999.15 | U26: 30863.36 | V26: 27420.64 | W26: 27613.76 | X26: 27925.59 | Y26: 27823.48 | Z26: 33949.05 | AA26: 28178.92 | AB26: 28540.11 | AC26: 31721.5 | AD26: 30415.31 | AE26: 37497.6
A27: Gross PP&E | B27: 117900.17 | C27: 118700.28 | D27: 122379.49 | E27: 123511.61 | F27: 116389.41 | G27: 123535.88 | H27: 124105.88 | I27: 126474.03 | J27: 126899.38 | K27: 117862.4 | L27: 169329 | M27: 171982 | N27: 174332 | O27: 176682 | P27: 119217.14 | Q27: - | R27: - | S27: - | T27: - | U27: 120964.38 | V27: - | W27: - | X27: - | Y27: - | Z27: 123104.73 | AA27: - | AB27: - | AC27: - | AD27: - | AE27: 126305.98
A28: Accumulated Depreciation | B28: 80003.17 | C28: 81219.28 | D28: 83661.49 | E28: 85178.61 | F28: 78056.41 | G28: 86273.88 | H28: 87482.88 | I28: 90787.03 | J28: 92280.54 | K28: 82738.44 | L28: 134946.9 | M28: 137982.13 | N28: 140971.99 | O28: 143907.47 | P28: 87216.72 | Q28: - | R28: - | S28: - | T28: - | U28: 91788.3 | V28: - | W28: - | X28: - | Y28: - | Z28: 96499.42 | AA28: - | AB28: - | AC28: - | AD28: - | AE28: 101429.31
A29: Property and equipment, net | B29: 37897 | C29: 37481 | D29: 38718 | E29: 38333 | F29: 38333 | G29: 37262 | H29: 36623 | I29: 35291.42 | J29: 34108.54 | K29: 34221.18 | L29: 32832.48 | M29: 31863.03 | N29: 30772.68 | O29: 29697.83 | P29: 30285.97 | Q29: 30486.41 | R29: 29804.9 | S29: 28947.45 | T29: 28116.98 | U29: 28712.56 | V29: 25630.54 | W29: 24829.39 | X29: 23798.41 | Y29: 22799.08 | Z29: 26815.65 | AA29: 21910.58 | AB29: 21166.86 | AC29: 20186.2 | AD29: 19238.47 | AE29: 25401.53
A30: Goodwill | B30: 13467 | C30: 13460 | D30: 13690 | E30: 13678 | F30: 13678 | G30: 13664 | H30: 13667 | I30: 13887 | J30: 14107.73 | K30: 14057.18 | L30: 13667 | M30: 13667 | N30: 13667 | O30: 13667 | P30: 14586.59 | Q30: 13667 | R30: 13667 | S30: 13667 | T30: 13667 | U30: 15342.53 | V30: 13667 | W30: 13667 | X30: 13667 | Y30: 13667 | Z30: 16427.17 | AA30: 13667 | AB30: 13667 | AC30: 13667 | AD30: 13667 | AE30: 16927.17
A31: Spectrum licenses | B31: 98733 | C31: 95928 | D31: 97749 | E31: 98032 | F31: 98032 | G31: 97564 | H31: 98178 | I31: 97970.64 | J31: 98025.98 | K31: 98609.98 | L31: 97656.64 | M31: 97372.55 | N31: 99479.5 | O31: 99517 | P31: 102053.04 | Q31: 101621 | R31: 102296 | S31: 104311 | T31: 105956 | U31: 105906.81 | V31: 107819.25 | W31: 107838 | X31: 110356.75 | Y31: 110375.5 | Z31: 110562.88 | AA31: 110394.25 | AB31: 110413 | AC31: 110431.75 | AD31: 111425.5 | AE31: 111480.31
A32: Other intangible assets, net | B32: 2618 | C32: 2438 | D32: 4117 | E32: 3843 | F32: 3843 | G32: 3573 | H32: 3295 | I32: 3226.23 | J32: 3160.17 | K32: 3186.4 | L32: 3104.55 | M32: 3049.97 | N32: 2997.92 | O32: 2948.25 | P32: 2982.69 | Q32: 2655.48 | R32: 2576.72 | S32: 2502.87 | T32: 2800.95 | U32: 2894.56 | V32: 2593.21 | W32: 2552.74 | X32: 2514.71 | Y32: 1885.57 | Z32: 2340.8 | AA32: 2447.84 | AB32: 2420.78 | AC32: 2397.23 | AD32: 2376.75 | AE32: 2474.08
A33: Intangibles - net | B33: 114818 | C33: 111826 | D33: 115556 | E33: 115553 | F33: 115553 | G33: 114801 | H33: 115140 | I33: 114602.08 | J33: 114682.32 | K33: 115489.13 | L33: 114376.05 | M33: 114008.97 | N33: 116144.42 | O33: 116132.25 | P33: 117928.04 | Q33: 117943.48 | R33: 118539.72 | S33: 120480.87 | T33: 124368.45 | U33: 123260.62 | V33: 127293.21 | W33: 127277.74 | X33: 130598.04 | Y33: 130587.28 | Z33: 129631.48 | AA33: 130581.17 | AB33: 130579.11 | AC33: 130580.56 | AD33: 131885.08 | AE33: 129126.6
A34: Operating lease right of used assets - Noncurrent | B34: 25025 | C34: 24735 | D34: 26070 | E34: 25692 | F34: 25692 | G34: 25021 | H34: 24596 | I34: 24585.88 | J34: 24525.41 | K34: 24782.87 | L34: 24336.02 | M34: 24359.36 | N34: 24384.16 | O34: 24407.84 | P34: 24539.79 | Q34: 24060.51 | R34: 24096.77 | S34: 24132.89 | T34: 24172.12 | U34: 24354.74 | V34: 24596 | W34: 24596 | X34: 24596 | Y34: 24596 | Z34: 25159.74 | AA34: 24596 | AB34: 24596 | AC34: 24596 | AD34: 24596 | AE34: 25161.4
A35: Financing lease right of used assets - Noncurrent | B35: 2977 | C35: 3105 | D35: 2955 | E35: 2760 | F35: 2760 | G35: 2766 | H35: 2994 | I35: 2993.68 | J35: 2981.11 | K35: 2929.81 | L35: 2981.51 | M35: 2984.55 | N35: 2987.79 | O35: 2990.87 | P35: 2920.88 | Q35: 2992.98 | R35: 2997.92 | S35: 3002.85 | T35: 3008.2 | U35: 2898.59 | V35: 2994 | W35: 2994 | X35: 2994 | Y35: 2994 | Z35: 2968 | AA35: 2994 | AB35: 2994 | AC35: 2994 | AD35: 2994 | AE35: 2968
A36: Other long term assets | B36: 6475 | C36: 8724 | D36: 12178 | E36: 12438 | F36: 12438 | G36: 12699 | H36: 12431 | I36: 12558.82 | J36: 12936.68 | K36: 12923.2 | L36: 12327.92 | M36: 12284.54 | N36: 12289.02 | O36: 12379.66 | P36: 14085.17 | Q36: 12042.31 | R36: 12118.19 | S36: 12152.31 | T36: 12189.6 | U36: 15535.68 | V36: 12459.75 | W36: 12412 | X36: 12437 | Y36: 12462 | Z36: 12796.29 | AA36: 12411.75 | AB36: 12364 | AC36: 12389 | AD36: 12414 | AE36: 12841.38
A37: Total other noncurrent assets | B37: 9452 | C37: 11829 | D37: 15133 | E37: 15198 | F37: 15198 | G37: 15465 | H37: 15425 | I37: 15570.65 | J37: 15974.93 | K37: 15901.02 | L37: 15309.42 | M37: 15269.09 | N37: 15276.81 | O37: 15370.54 | P37: 17149.92 | Q37: 15035.29 | R37: 15116.11 | S37: 15155.16 | T37: 15197.8 | U37: 18730.49 | V37: 15453.75 | W37: 15406 | X37: 15431 | Y37: 15456 | Z37: 15854.88 | AA37: 15405.75 | AB37: 15358 | AC37: 15383 | AD37: 15408 | AE37: 15904.98
A38: Total noncurrent assets | B38: 187192 | C38: 185871 | D38: 195477 | E38: 194776 | F38: 194776 | G38: 192549 | H38: 191784 | I38: 190325.87 | J38: 189771.91 | K38: 190595.16 | L38: 187820.07 | M38: 186495.92 | N38: 187359.59 | O38: 186346.25 | P38: 192102.09 | Q38: 188439.62 | R38: 188340.95 | S38: 189134.56 | T38: 191398.22 | U38: 197328.17 | V38: 191766.94 | W38: 190993.18 | X38: 192481.79 | Y38: 191446.42 | Z38: 199437.5 | AA38: 191964.48 | AB38: 191205.04 | AC38: 190225.01 | AD38: 190590.48 | AE38: 198946.64
A39: Total assets | B39: 214633 | C39: 212643 | D39: 217180 | E39: 219237 | F39: 219237 | G39: 214667 | H39: 213553 | I39: 214122.71 | J39: 214989.62 | K39: 215734.53 | L39: 216355.03 | M39: 215764.07 | N39: 216326.09 | O39: 216253.33 | P39: 221629.83 | Q39: 215615.82 | R39: 215167.95 | S39: 215742.49 | T39: 214617.17 | U39: 226661 | V39: 216753.59 | W39: 216106.95 | X39: 217393.91 | Y39: 216250.49 | Z39: 231642.64 | AA39: 215959.76 | AB39: 215475.7 | AC39: 217652.9 | AD39: 216355.23 | AE39: 235935.48
A40: Short-term debt | B40: 8214 | C40: 6408 | D40: 6333 | E40: 5135 | F40: 5135 | G40: 2238 | H40: 6117 | I40: 6117 | J40: 6117 | K40: 5992.91 | L40: 6117 | M40: 6117 | N40: 6117 | O40: 6117 | P40: 5999.9 | Q40: 6117 | R40: 6117 | S40: 6117 | T40: 6117 | U40: 5990.1 | V40: 6117 | W40: 6117 | X40: 6117 | Y40: 6117 | Z40: 6018.8 | AA40: 6117 | AB40: 6117 | AC40: 6117 | AD40: 6117 | AE40: 6007.89
... A49: Long-term debt | B49: 76033 | C49: 75018 | D49: 76365 | E49: 79649 | F49: 79649 | G49: 83809 | H49: 78504 | I49: 79701.84 | J49: 81266.25 | K49: 81574.05 | L49: 85566.87 | M49: 86263.19 | N49: 87094.25 | O49: 87563.14 | P49: 88780.74 | Q49: 91755.57 | R49: 92826.78 | S49: 94179.87 | T49: 94155.39 | U49: 94791.61 | V49: 93972.02 | W49: 94005.64 | X49: 95646.78 | Y49: 96250.41 | Z49: 98745.57 | AA49: 91774.57 | AB49: 91477.77 | AC49: 93312.91 | AD49: 93156.92 | AE49: 99488.64
A50: Long-term debt to affiliates | B50: 1497 | C50: 1497 | D50: 1498 | E50: 1498 | F50: 1498 | G50: - | H50: - | I50: - | J50: - | K50: 1498 | L50: - | M50: - | N50: - | O50: - | P50: 1498 | Q50: - | R50: - | S50: - | T50: - | U50: 1498 | V50: - | W50: - | X50: - | Y50: - | Z50: 1498 | AA50: - | AB50: - | AC50: - | AD50: - | AE50: 1498
A51: Total LT debt - net | B51: 77530 | C51: 76515 | D51: 77863 | E51: 81147 | F51: 81147 | G51: 83809 | H51: 78504 | I51: 79691.59 | J51: 81240.78 | K51: 81691.6 | L51: 85663.06 | M51: 86568.81 | N51: 87597.04 | O51: 88296.04 | P51: 89295.75 | Q51: 91755.57 | R51: 92826.78 | S51: 94179.87 | T51: 94155.39 | U51: 94504.75 | V51: 93972.02 | W51: 94005.64 | X51: 95646.78 | Y51: 96250.41 | Z51: 97515.33 | AA51: 91774.57 | AB51: 91477.77 | AC51: 93312.91 | AD51: 93156.92 | AE51: 97796.21
A52: Financing lease liabilities - Noncurrent | B52: 1117 | C52: 1188 | D52: 1186 | E52: 1107 | F52: 1107 | G52: 1024 | H52: 1121 | I52: 1121.93 | J52: 1121.93 | K52: 1115.85 | L52: 1122.12 | M52: 1122.12 | N52: 1123.25 | O52: 1123.25 | P52: 1112.9 | Q52: 1121 | R52: 1121 | S52: 1121 | T52: 1121 | U52: 1105.51 | V52: 1121 | W52: 1121 | X52: 1121 | Y52: 1121 | Z52: 1119.44 | AA52: 1121 | AB52: 1121 | AC52: 1121 | AD52: 1121 | AE52: 1119.44
A53: Operating lease liabilities - Noncurrent | B53: 25974 | C53: 25646 | D53: 26780 | E53: 26371 | F53: 26371 | G53: 25856 | H53: 25438 | I53: 25392.99 | J53: 25346.62 | K53: 25594.01 | L53: 25333.64 | M53: 25282.54 | N53: 25257.53 | O53: 25230.63 | P53: 25418.02 | Q53: 24816.6 | R53: 24714.4 | S53: 24613 | T53: 24559.2 | U53: 25222.73 | V53: 25584 | W53: 25581.25 | X53: 25579.5 | Y53: 25637.25 | Z53: 25743.67 | AA53: 25631.75 | AB53: 25629 | AC53: 25627.25 | AD53: 25685 | AE53: 25772.46
A54: Deferred rents and other long-term liabilities | B54: 4139 | C54: 4014 | D54: 3783 | E54: 3794 | F54: 3794 | G54: 3993 | H54: 3985 | I54: 3908.06 | J54: 3868.74 | K54: 3871.61 | L54: 3890.66 | M54: 3944.28 | N54: 3973.72 | O54: 4018.12 | P54: 4024.68 | Q54: 4147.59 | R54: 4255.34 | S54: 4286.63 | T54: 4371.67 | U54: 4199.64 | V54: 4502.16 | W54: 4613.6 | X54: 4665.65 | Y54: 4784.1 | Z54: 4318.94 | AA54: 4890.42 | AB54: 5023.62 | AC54: 5097.43 | AD54: 5237.6 | AE54: 4520.49
A55: Tower obligation | B55: 3634 | C55: 3603 | D55: 3568 | E55: 3532 | F55: 3532 | G55: 3496 | H55: 3461 | I55: 3463.47 | J55: 3463.47 | K55: 3452.92 | L55: 3464.46 | M55: 3464.46 | N55: 3467.96 | O55: 3467.96 | P55: 3436.18 | Q55: 3461 | R55: 3461 | S55: 3461 | T55: 3461 | U55: 3406.25 | V55: 3461 | W55: 3461 | X55: 3461 | Y55: 3461 | Z55: 3394.73 | AA55: 3461 | AB55: 3461 | AC55: 3461 | AD55: 3461 | AE55: 3376.55
A56: Deferred tax liabilities | B56: 17505 | C56: 18468 | D56: 19222 | E56: 19583 | F56: 19583 | G56: 20266 | H56: 21225 | I56: 21790.64 | J56: 22251.25 | K56: 22095.58 | L56: 22438.31 | M56: 22645.13 | N56: 22854.32 | O56: 23059.68 | P56: 23057.44 | Q56: 24018.77 | R56: 24294.82 | S56: 24570.03 | T56: 24859.81 | U56: 24133.12 | V56: 24699.77 | W56: 24965.71 | X56: 25230.9 | Y56: 25514.89 | Z56: 25077.33 | AA56: 25596 | AB56: 25675.98 | AC56: 25755.25 | AD56: 25844.61 | AE56: 25480.67
A57: Total long-term liabilities | B57: 129899 | C57: 129434 | D57: 132402 | E57: 135534 | F57: 135534 | G57: 138444 | H57: 133734 | I57: 135538.15 | J57: 137322.07 | K57: 137778.11 | L57: 141819.6 | M57: 142915.66 | N57: 144142.3 | O57: 145043.9 | P57: 147001.86 | Q57: 148931.37 | R57: 150237.25 | S57: 151761.25 | T57: 152004.3 | U57: 152984.48 | V57: 152512.36 | W57: 152845.68 | X57: 154739.22 | Y57: 155711.01 | Z57: 157258.41 | AA57: 152474.74 | AB57: 152388.38 | AC57: 154374.84 | AD57: 154506.13 | AE57: 158826.45
A58: Total liabilities | B58: 153528 | C58: 151536 | D58: 156703 | E58: 160034 | F58: 160034 | G58: 158788 | H58: 157288 | I58: 159146.74 | J58: 161790.25 | K58: 162257.58 | L58: 166266.1 | M58: 167085.79 | N58: 168503.5 | O58: 170396.79 | P58: 171915.91 | Q58: 173125.76 | R58: 174210.76 | S58: 175823.95 | T58: 176373.17 | U58: 178050.96 | V58: 176194.4 | W58: 176264.24 | X58: 178330.9 | Y58: 179680.63 | Z58: 182236.16 | AA58: 176183.55 | AB58: 175761.3 | AC58: 178048.69 | AD58: 178781.51 | AE58: 184458.37
A59: Treasury stock | B59: 23085 | C59: 25569 | D59: 28064 | E59: 30545 | F59: 30545 | G59: 35497 | H59: 37667 | I59: 39239.5 | J59: 40835.73 | K59: 40915.33 | L59: 43227.79 | M59: 45136.72 | N59: 47064 | O59: 49010.08 | P59: 48246.23 | Q59: 51427.13 | R59: 53999.27 | S59: 56595.72 | T59: 59217.08 | U59: 56673.34 | V59: 67913.21 | W59: 71254.55 | X59: 74629.41 | Y59: 78038.64 | Z59: 68657.2 | AA59: 71339.67 | AB59: 74006.33 | AC59: 76673 | AD59: 79339.67 | AE59: 72160.29
A60: Accumulated other comprehensive income | B60: -989 | C60: -908 | D60: -881 | E60: -848 | F60: -848 | G60: -835 | H60: -635 | I60: -610.89 | J60: -587.67 | K60: -635 | L60: -635 | M60: -635 | N60: -635 | O60: -635 | P60: -558.55 | Q60: -635 | R60: -635 | S60: -635 | T60: -635 | U60: -466.8 | V60: -635 | W60: -635 | X60: -635 | Y60: -635 | Z60: -293 | AA60: -635 | AB60: -635 | AC60: -635 | AD60: -635 | AE60: -124
A61: Accumulated deficit | B61: 16342 | C61: 18576 | D61: 20155 | E61: 21136 | F61: 21136 | G61: 22541 | H61: 24688 | I61: 24845.19 | J61: 23892.14 | K61: 24719.27 | L61: 22183.13 | M61: 23389.09 | N61: 25028.34 | O61: 24500.77 | P61: 30431.5 | Q61: 22652.58 | R61: 23907.14 | S61: 25349.49 | T61: 26100.34 | U61: 37393.83 | V61: 37320.3 | W61: 39837.97 | X61: 42331.34 | Y61: 42778.32 | Z61: 52435.66 | AA61: 39592.05 | AB61: 42156.64 | AC61: 44685.53 | AD61: 44738.28 | AE61: 62487.56
A62: Additional paid-in capital | B62: 68837 | C62: 69008 | D62: 69267 | E62: 69460 | F62: 69460 | G62: 69670 | H62: 69879 | I62: 69476.09 | J62: 69188.67 | K62: 69316.01 | L62: 69974 | M62: 70011.17 | N62: 70048.83 | O62: 70087 | P62: 67922.03 | Q62: 69879 | R62: 69879 | S62: 69879 | T62: 69879 | U62: 65982.96 | V62: 69879 | W62: 69879 | X62: 69879 | Y62: 69879 | Z62: 61793.29 | AA62: 69879 | AB62: 69879 | AC62: 69879 | AD62: 69879 | AE62: 56623.04
... A67: Net debt | B67: 75994 | C67: 75009 | D67: 83229 | E67: 82954 | F67: 82954 | G67: 84706 | H67: 84095 | I67: 82469.48 | J67: 83366.16 | K67: 83868.37 | L67: 84582.83 | M67: 84406.8 | N67: 86201.93 | O67: 86785.64 | P67: 89207.88 | Q67: 93877.87 | R67: 95245.78 | S67: 97315.03 | T67: 99362.36 | U67: 94112.14 | V67: 97882.28 | W67: 97832.05 | X67: 99769.92 | Y67: 100871.31 | Z67: 94882.46 | AA67: 98932.84 | AB67: 98349.14 | AC67: 97098.86 | AD67: 99179.41 | AE67: 93867.98

Sheet Cash flow
A2: T-Mobile US, Inc. | Cash flow
A3: NASDAQGS:TMUS (MI KEY: 4091145; SPCIQ KEY: 93339)
A5: Visible Alpha
A7: Period Type : Fiscal Quarter, Fiscal Halves, Fiscal Year
A8: Period Start : 2025
A9: Period End : 2030
A10: Currency : Reported
A11: Consensus View : Mean
A12: As Of: 10/28/2026
A14: All numbers in $M unless otherwise indicated | B14: FQ1 2025A | C14: FQ2 2025A | D14: FQ3 2025A | E14: FQ4 2025A | F14: FY2025A | G14: FQ1 2026A | H14: FQ2 2026A | I14: FQ3 2026E | J14: FQ4 2026E | K14: FY2026E | L14: FQ1 2027E | M14: FQ2 2027E | N14: FQ3 2027E | O14: FQ4 2027E | P14: FY2027E | Q14: FQ1 2028E | R14: FQ2 2028E | S14: FQ3 2028E | T14: FQ4 2028E | U14: FY2028E | V14: FQ1 2029E | W14: FQ2 2029E | X14: FQ3 2029E | Y14: FQ4 2029E | Z14: FY2029E | AA14: FQ1 2030E | AB14: FQ2 2030E | AC14: FQ3 2030E | AD14: FQ4 2030E | AE14: FY2030E
A15: Number of Contributors Available | B15: 20 | C15: 20 | D15: 20 | E15: 20 | F15: 22 | G15: 21 | H15: 21 | I15: 21 of 22 | J15: 21 of 22 | K15: 22 of 22 | L15: 13 of 22 | M15: 13 of 22 | N15: 12 of 22 | O15: 12 of 22 | P15: 22 of 22 | Q15: 6 of 22 | R15: 6 of 22 | S15: 6 of 22 | T15: 6 of 22 | U15: 19 of 22 | V15: 5 of 22 | W15: 5 of 22 | X15: 5 of 22 | Y15: 5 of 22 | Z15: 15 of 22 | AA15: 4 of 22 | AB15: 4 of 22 | AC15: 4 of 22 | AD15: 4 of 22 | AE15: 14 of 22
A16: Net income/(loss) - CF | B16: 2953 | C16: 3222 | D16: 2714 | E16: 2103 | F16: 10992 | G16: 2504 | H16: 3239 | I16: 3111.44 | J16: 2942.99 | K16: 11787.12 | L16: 3552.08 | M16: 3770.03 | N16: 3782.45 | O16: 3630.11 | P16: 14606.32 | Q16: 4174.21 | R16: 4376 | S16: 4309.36 | T16: 4142.36 | U16: 16969.87 | V16: 4530 | W16: 4754.99 | X16: 4684.12 | Y16: 4503.24 | Z16: 18845.19 | AA16: 4898.02 | AB16: 5159.29 | AC16: 5075.01 | AD16: 4872.54 | AE16: 20474.16
A17: Depreciation and amortization - CF | B17: 3198 | C17: 3146 | D17: 3408 | E17: 3756 | F17: 13508 | G17: 3817 | H17: 3434 | I17: 3561.8 | J17: 3568.61 | K17: 14368.1 | L17: 3559.12 | M17: 3486.42 | N17: 3518.33 | O17: 3532.78 | P17: 14144.3 | Q17: 3528.41 | R17: 3462.92 | S17: 3504.13 | T17: 3512.84 | U17: 13953.72 | V17: 3524.11 | W17: 3443.97 | X17: 3499.6 | Y17: 3512.66 | Z17: 13929.13 | AA17: 3610.93 | AB17: 3479.38 | AC17: 3544.58 | AD17: 3566.1 | AE17: 14071.57
A18: Stock-Based Compensation - CF | B18: 186 | C18: 200 | D18: 227 | E18: 216 | F18: 829 | G18: 209 | H18: 214 | I18: 206.82 | J18: 218.31 | K18: 847.75 | L18: 205.62 | M18: 209.8 | N18: 214.8 | O18: 220.1 | P18: 865.37 | Q18: 203.6 | R18: 206.22 | S18: 207.26 | T18: 211.83 | U18: 891.55 | V18: 215.99 | W18: 220.93 | X18: 220.68 | Y18: 219.01 | Z18: 930.28 | AA18: 222.35 | AB18: 227.37 | AC18: 222.66 | AD18: 224.18 | AE18: 968.12
A19: Accounts receivable change | B19: -93 | C19: -338 | D19: -366 | E19: 42 | F19: -755 | G19: -162 | H19: -498 | I19: -416.57 | J19: -459.68 | K19: -1197.75 | L19: -304.11 | M19: -249.02 | N19: -234.28 | O19: -433.53 | P19: -885.69 | Q19: -332.44 | R19: -534.22 | S19: -534.07 | T19: -534.27 | U19: -969.03 | V19: -400 | W19: -400 | X19: -400 | Y19: -400 | Z19: -1044.15 | AA19: -400 | AB19: -400 | AC19: -400 | AD19: -400 | AE19: -1169.51
A20: Inventory change | B20: -318 | C20: 264 | D20: -537 | E20: -24 | F20: -615 | G20: 86 | H20: 142 | I20: -184.81 | J20: -209.09 | K20: -15.55 | L20: 223.14 | M20: 193.49 | N20: -202.83 | O20: -355.41 | P20: -113.53 | Q20: 57.66 | R20: 61.52 | S20: -277.94 | T20: 64.75 | U20: -85.71 | V20: 86 | W20: 142 | X20: -537 | Y20: 150 | Z20: -58.79 | AA20: 86 | AB20: 142 | AC20: -537 | AD20: 150 | AE20: -68.32
A21: Other (Increase)/Decrease in Working Capital , Net | B21: -195 | C21: -723 | D21: 366 | E21: -243 | F21: -1024 | G21: -360 | H21: -339 | I21: -60.06 | J21: -55.12 | K21: -612.36 | L21: -321.31 | M21: -475.37 | N21: -78.14 | O21: 148.29 | P21: -429.21 | Q21: -196.71 | R21: -527.95 | S21: -184.56 | T21: -28.28 | U21: -764.77 | V21: -596.85 | W21: -407.62 | X21: 264.97 | Y21: 762.94 | Z21: -1043.52 | AA21: -577.42 | AB21: -403.28 | AC21: 447.71 | AD21: 651.54 | AE21: -916.25
A22: Total changes in working capital | B22: -776 | C22: -658 | D22: -537 | E22: -423 | F22: -2394 | G22: -436 | H22: -886 | I22: -450.15 | J22: -503.76 | K22: -1817.71 | L22: -495.63 | M22: -497.88 | N22: -381.1 | O22: -317.24 | P22: -1317.46 | Q22: -562.8 | R22: -604.56 | S22: -544.42 | T22: -227.96 | U22: -1534.01 | V22: -759.12 | W22: -442.63 | X22: -310.84 | Y22: 27.53 | Z22: -1611.9 | AA22: -769.02 | AB22: -297.43 | AC22: -111.62 | AD22: 305.18 | AE22: -1453.27
A23: Total other OCF adjustment | B23: 1286 | C23: 1082 | D23: 1645 | E23: 1002 | F23: 5015 | G23: 1128 | H23: 1308 | I23: 819.93 | J23: 706.51 | K23: 3765.17 | L23: 625.68 | M23: 504.4 | N23: 513.14 | O23: 756.27 | P23: 1987.26 | Q23: 744.5 | R23: 615.8 | S23: 580.68 | T23: 617.94 | U23: 2148.63 | V23: 564.4 | W23: 553.43 | X23: 547.32 | Y23: 593.48 | Z23: 2129.41 | AA23: 321.78 | AB23: 316.2 | AC23: 317.23 | AD23: 335.11 | AE23: 1656.4
A24: Net cash flows provided by/(used in) operating activities | B24: 6847 | C24: 6992 | D24: 7457 | E24: 6654 | F24: 27950 | G24: 7222 | H24: 7500 | I24: 7326.45 | J24: 6846.41 | K24: 28834.58 | L24: 7527.63 | M24: 7430.78 | N24: 7535.92 | O24: 7734.28 | P24: 30085.44 | Q24: 7979.06 | R24: 7972.36 | S24: 7980.28 | T24: 8172.11 | U24: 32164.83 | V24: 7948.74 | W24: 8407.24 | X24: 8519.58 | Y24: 8719.54 | Z24: 33981.54 | AA24: 8155.88 | AB24: 8757.27 | AC24: 8921.48 | AD24: 9171.71 | AE24: 35439.44
A25: Purchases of property and equipment | B25: 2451 | C25: 2396 | D25: 2639 | E25: 2469 | F25: 9955 | G25: 2623 | H25: 2703 | I25: 2425.62 | J25: 2334.25 | K25: 10079.49 | L25: 2455.9 | M25: 2512.93 | N25: 2428.23 | O25: 2399.77 | P25: 9859.03 | Q25: 2529.8 | R25: 2587.52 | S25: 2422.58 | T25: 2357.25 | U25: 10063.63 | V25: 2598.15 | W25: 2627.42 | X25: 2439.72 | Y25: 2436.36 | Z25: 10372.5 | AA25: 2644.12 | AB25: 2663.14 | AC25: 2496.64 | AD25: 2555.87 | AE25: 10826.58
A26: Proceeds from the sale of property, equipment and intangible assets | B26: 7 | C26: 2066 | D26: 18 | E26: 77 | F26: 2168 | G26: 95 | H26: 16 | I26: - | J26: - | K26: 111 | L26: - | M26: - | N26: - | O26: - | P26: - | Q26: - | R26: - | S26: - | T26: - | U26: - | V26: - | W26: - | X26: - | Y26: - | Z26: - | AA26: - | AB26: - | AC26: - | AD26: - | AE26: -
A27: Purchases of spectrum licenses and other intangible assets | B27: 73 | C27: 842 | D27: 1590 | E27: 63 | F27: 2568 | G27: 26 | H27: 484 | I27: -878.78 | J27: 995.67 | K27: 983.12 | L27: 168.75 | M27: 168.75 | N27: 3695.83 | O27: 168.75 | P27: 6754.55 | Q27: 125 | R27: 1968.75 | S27: 2593.75 | T27: 2131.25 | U27: 5604.17 | V27: 62.5 | W27: 62.5 | X27: 3375 | Y27: 62.5 | Z27: 6700 | AA27: 62.5 | AB27: 62.5 | AC27: 62.5 | AD27: 1341.67 | AE27: 2980.32
A28: Proceeds/Payments of investments | B28: 586 | C28: 2160.5 | D28: -1642.5 | E28: 1309 | F28: 1804 | G28: 1158.5 | H28: 1304 | I28: -135 | J28: 200 | K28: 4990 | L28: - | M28: - | N28: - | O28: - | P28: - | Q28: - | R28: - | S28: - | T28: - | U28: - | V28: - | W28: - | X28: - | Y28: - | Z28: - | AA28: - | AB28: - | AC28: - | AD28: - | AE28: -
A29: (Acquisition)/divestiture of business activities, net | B29: -727 | C29: 1 | D29: -2797 | E29: 51 | F29: -3523 | G29: -1 | H29: -672.5 | I29: 675 | J29: -172.1 | K29: 67.09 | L29: -125 | M29: -1062.5 | N29: -125 | O29: -312.5 | P29: -5350 | Q29: -500 | R29: -500 | S29: - | T29: - | U29: -1008.33 | V29: - | W29: - | X29: - | Y29: - | Z29: -1000 | AA29: - | AB29: - | AC29: - | AD29: - | AE29: -3000
A30: Net (acquisitions)/disposals | B30: -727 | C30: 1 | D30: -2797 | E30: 693 | F30: -3523 | G30: -1 | H30: -13.67 | I30: 405 | J30: 13.95 | K30: 435.3 | L30: -5062.5 | M30: -1062.5 | N30: -125 | O30: -312.5 | P30: -6125 | Q30: -500 | R30: -500 | S30: - | T30: - | U30: -1008.33 | V30: - | W30: - | X30: - | Y30: - | Z30: -1000 | AA30: - | AB30: - | AC30: - | AD30: - | AE30: -3000
A31: Investing activities Other, net | B31: -165 | C31: 1678 | D31: -3113 | E31: 32 | F31: -1561 | G31: -199 | H31: 135 | I31: -887.5 | J31: -4825 | K31: -1647.95 | L31: -5000 | M31: - | N31: - | O31: -5750 | P31: -8117.18 | Q31: -3000 | R31: -1000 | S31: -2000 | T31: -4500 | U31: -6367.03 | V31: - | W31: - | X31: - | Y31: -7000 | Z31: -7000 | AA31: - | AB31: - | AC31: - | AD31: -6500 | AE31: -6500
A32: Net cash provided by/(used in) investing activities | B32: -3409 | C32: -1559 | D32: -10139 | E32: -2500 | F32: -17607 | G32: -2849 | H32: -3052 | I32: -2185.4 | J32: -3751.54 | K32: -11918.01 | L32: -3772.56 | M32: -2746.26 | N32: -4455.5 | O32: -3563.41 | P32: -18059.97 | Q32: -3175.64 | R32: -4150.02 | S32: -4485.08 | T32: -4528.09 | U32: -16078.52 | V32: -2623.15 | W32: -2652.42 | X32: -4464.72 | Y32: -3861.36 | Z32: -13908.22 | AA32: -2675.37 | AB32: -2694.39 | AC32: -2527.89 | AD32: -5187.12 | AE32: -13165.17
A33: Net change in debt | B33: 6980 | C33: -3594 | D33: -648 | E33: 1821 | F33: 4559 | G33: -341 | H33: -1701 | I33: 1389.45 | J33: 1530.06 | K33: 222.37 | L33: 6851.08 | M33: 1570.08 | N33: 1494.64 | O33: 1748.12 | P33: 9561.52 | Q33: 1315.83 | R33: 2320.25 | S33: 1985.12 | T33: -103.17 | U33: 3647.13 | V33: 500.25 | W33: 483.25 | X33: 2833.5 | Y33: 1650.25 | Z33: 3114.58 | AA33: 0.5 | AB33: 0.5 | AC33: 4000.25 | AD33: 0.5 | AE33: 2035.42
A34: Proceeds from issuance of equity | B34: 0 | C34: 0 | D34: 0 | E34: 0 | F34: 0 | G34: 0 | H34: 0 | I34: 0 | J34: 0 | K34: 0 | L34: 0 | M34: 0 | N34: 0 | O34: 0 | P34: 0 | Q34: 0 | R34: 0 | S34: 0 | T34: 0 | U34: 0 | V34: 0 | W34: 0 | X34: 0 | Y34: 0 | Z34: 0 | AA34: 0 | AB34: 0 | AC34: 0 | AD34: 0 | AE34: 0
A35: Share repurchase | B35: 2494 | C35: 2555 | D35: 2479 | E35: 2446 | F35: 9974 | G35: 4826 | H35: 2320 | I35: 2549.9 | J35: 2497 | K35: 11993.55 | L35: 2875.14 | M35: 2874.29 | N35: 3039.86 | O35: 3035.14 | P35: 11342.82 | Q35: 3833.33 | R35: 3833.33 | S35: 3833.33 | T35: 3833.33 | U35: 13596.38 | V35: 4375 | W35: 4375 | X35: 4375 | Y35: 4375 | Z35: 15582.81 | AA35: 4375 | AB35: 4375 | AC35: 4375 | AD35: 4375 | AE35: 16228.52
A36: Purchase of treasury stock | B36: - | C36: - | D36: - | E36: - | F36: - | G36: - | H36: - | I36: - | J36: - | K36: - | L36: - | M36: - | N36: - | O36: - | P36: - | Q36: - | R36: - | S36: - | T36: - | U36: - | V36: - | W36: - | X36: - | Y36: - | Z36: - | AA36: - | AB36: - | AC36: - | AD36: - | AE36: -
A37: Net change in equity | B37: -2494 | C37: -2555 | D37: -2479 | E37: -2446 | F37: -9974 | G37: -4826 | H37: -2320 | I37: -2510.48 | J37: -2419.28 | K37: -11920.31 | L37: -2901.44 | M37: -3338.76 | N37: -3049.85 | O37: -3079.35 | P37: -11401.48 | Q37: -3832.03 | R37: -3851.79 | S37: -3872.04 | T37: -3892.8 | U37: -13301.83 | V37: -4196.89 | W37: -4223.06 | X37: -4249.89 | Y37: -4277.39 | Z37: -15292.65 | AA37: -3937.5 | AB37: -3937.5 | AC37: -3937.5 | AD37: -3937.5 | AE37: -15643.67
A38: Dividends on common stock - CF | B38: 1003 | C38: 996 | D38: 987 | E38: 1135 | F38: 4121 | G38: 1120 | H38: 1101 | I38: 1089 | J38: 1172.05 | K38: 4472.32 | L38: 1195.22 | M38: 1180.24 | N38: 1159.42 | O38: 1231.67 | P38: 4819.88 | Q38: 1253.14 | R38: 1231.61 | S38: 1201.43 | T38: 1307.78 | U38: 5164.08 | V38: 1314.75 | W38: 1289.89 | X38: 1254.3 | Y38: 1363.44 | Z38: 5483.59 | AA38: 1361.77 | AB38: 1338.19 | AC38: 1300.89 | AD38: 1398.89 | AE38: 5835.06
A39: Financing activities Other, net | B39: -290 | C39: -60 | D39: -124 | E39: -71 | F39: -545 | G39: -153 | H39: -60 | I39: -125.5 | J39: -39.75 | K39: -307.21 | L39: -170 | M39: -170 | N39: -170 | O39: -170 | P39: -680 | Q39: -170 | R39: -170 | S39: -170 | T39: -170 | U39: -680 | V39: -210 | W39: -210 | X39: -210 | Y39: -210 | Z39: -840 | AA39: -210 | AB39: -210 | AC39: -210 | AD39: -210 | AE39: -840
A40: Net cash provided by/(used in) financing activities | B40: 3193 | C40: -7205 | D40: -4238 | E40: -1831 | F40: -10081 | G40: -6440 | H40: -5182 | I40: -3086.04 | J40: -2400.12 | K40: -16485.88 | L40: -90.73 | M40: -3859.87 | N40: -3303.2 | O40: -3733.47 | P40: -8869.8 | Q40: -3632.33 | R40: -4128.85 | S40: -3837.05 | T40: -5341.71 | U40: -14763.14 | V40: -4402.3 | W40: -5521.34 | X40: -3905.05 | Y40: -5079.19 | Z40: -17707.07 | AA40: -4514.72 | AB40: -5624.98 | AC40: -3455.75 | AD40: -5544.88 | AE40: -19429.66
A41: Effect of exchange rate changes on cash and cash equivalents, including restricted cash | B41: - | C41: 13 | D41: - | E41: -12 | F41: 1 | G41: - | H41: - | I41: - | J41: - | K41: - | L41: - | M41: - | N41: - | O41: - | P41: - | Q41: - | R41: - | S41: - | T41: - | U41: - | V41: - | W41: - | X41: - | Y41: - | Z41: - | AA41: - | AB41: - | AC41: - | AD41: - | AE41: -
A42: Change in cash and cash equivalents | B42: 6631 | C42: -1772 | D42: -6920 | E42: 2323 | F42: 262 | G42: -2067 | H42: -734 | I42: 2032.75 | J42: 776.27 | K42: 332.2 | L42: 3870.86 | M42: 886.43 | N42: -209.25 | O42: 440.48 | P42: 3907.22 | Q42: 1405.31 | R42: -367.81 | S42: -410.23 | T42: -2037.23 | U42: 1037.49 | V42: 1154.11 | W42: 291.85 | X42: 187.26 | Y42: -276.26 | Z42: 3048.04 | AA42: 1287.73 | AB42: 583.87 | AC42: 3917.12 | AD42: -2080.39 | AE42: 3953.05
A43: Cash - beginning of period | B43: 5713 | C43: 12344 | D43: 10585 | E43: 3665 | F43: 5713 | G43: 5976 | H43: 3909 | I43: 3128.07 | J43: 5255.11 | K43: 7180.31 | L43: 6313.93 | M43: 10521.72 | N43: 11487.78 | O43: 11278.53 | P43: 7256.78 | Q43: 8088.97 | R43: 9494.27 | S43: 9126.47 | T43: 8716.24 | U43: 10307.19 | V43: 7578.98 | W43: 8733.09 | X43: 9024.95 | Y43: 9212.2 | Z43: 12514.31 | AA43: 5723.6 | AB43: 7011.32 | AC43: 7595.19 | AD43: 11512.31 | AE43: 12526.37
A44: Cash - end of period | B44: 12344 | C44: 10585 | D44: 3665 | E44: 5976 | F44: 5976 | G44: 3909 | H44: 3175 | I44: 5255.11 | J44: 6312.52 | K44: 7256.78 | L44: 10521.72 | M44: 11487.78 | N44: 11278.53 | O44: 11719.01 | P44: 11488.8 | Q44: 9494.27 | R44: 9126.47 | S44: 8716.24 | T44: 6679.01 | U44: 12670.28 | V44: 8733.09 | W44: 9024.95 | X44: 9212.2 | Y44: 8935.94 | Z44: 16113.27 | AA44: 7011.32 | AB44: 7595.19 | AC44: 11512.31 | AD44: 9431.92 | AE44: 16905.65
A46: Adjusted Free Cash Flow
A47: Net cash flows provided by/(used in) operating activities | B47: 6847 | C47: 6992 | D47: 7457 | E47: 6654 | F47: 27950 | G47: 7222 | H47: 7500 | I47: 7326.45 | J47: 6846.41 | K47: 28834.58 | L47: 7527.63 | M47: 7430.78 | N47: 7535.92 | O47: 7734.28 | P47: 30085.44 | Q47: 7979.06 | R47: 7972.36 | S47: 7980.28 | T47: 8172.11 | U47: 32164.83 | V47: 7948.74 | W47: 8407.24 | X47: 8519.58 | Y47: 8719.54 | Z47: 33981.54 | AA47: 8155.88 | AB47: 8757.27 | AC47: 8921.48 | AD47: 9171.71 | AE47: 35439.44
A48: Purchases of property and equipment | B48: 2451 | C48: 2396 | D48: 2639 | E48: 2469 | F48: 9955 | G48: 2623 | H48: 2703 | I48: 2425.62 | J48: 2334.25 | K48: 10079.49 | L48: 2455.9 | M48: 2512.93 | N48: 2428.23 | O48: 2399.77 | P48: 9859.03 | Q48: 2529.8 | R48: 2587.52 | S48: 2422.58 | T48: 2357.25 | U48: 10063.63 | V48: 2598.15 | W48: 2627.42 | X48: 2439.72 | Y48: 2436.36 | Z48: 10372.5 | AA48: 2644.12 | AB48: 2663.14 | AC48: 2496.64 | AD48: 2555.87 | AE48: 10826.58
A49: Free cash flow | B49: 4396 | C49: 4596 | D49: 4818 | E49: 4185 | F49: 17995 | G49: 4599 | H49: 4797 | I49: 4900.79 | J49: 4513.08 | K49: 18756.22 | L49: 5071.19 | M49: 4925.76 | N49: 5134.87 | O49: 5364.54 | P49: 20257.51 | Q49: 5449.26 | R49: 5384.85 | S49: 5557.69 | T49: 5814.86 | U49: 22101.2 | V49: 5350.59 | W49: 5779.82 | X49: 6079.86 | Y49: 6283.18 | Z49: 23609.04 | AA49: 5511.76 | AB49: 6094.13 | AC49: 6424.84 | AD49: 6615.84 | AE49: 24612.86
A50: Proceeds related to securitization transactions - FCF | B50: 2643 | C50: 2643 | D50: 2625 | E50: 2586 | F50: 10497 | G50: 2517 | H50: 2473 | I50: - | J50: - | K50: 4990 | L50: - | M50: - | N50: - | O50: - | P50: - | Q50: - | R50: - | S50: - | T50: - | U50: - | V50: - | W50: - | X50: - | Y50: - | Z50: - | AA50: - | AB50: - | AC50: - | AD50: - | AE50: -
A51: Cash paid for the settlement of interest rate swaps - FCF | B51: -2643 | C51: -2643 | D51: -2625 | E51: -2586 | F51: -10497 | G51: -2517 | H51: -2473 | I51: - | J51: - | K51: -4990 | L51: - | M51: - | N51: - | O51: - | P51: - | Q51: - | R51: - | S51: - | T51: - | U51: - | V51: - | W51: - | X51: - | Y51: - | Z51: - | AA51: - | AB51: - | AC51: - | AD51: - | AE51: -
A52: Cash payments for debt prepayment or debt extinguishment costs - FCF | B52: - | C52: - | D52: - | E52: - | F52: - | G52: - | H52: - | I52: - | J52: - | K52: - | L52: - | M52: - | N52: - | O52: - | P52: - | Q52: - | R52: - | S52: - | T52: - | U52: - | V52: - | W52: - | X52: - | Y52: - | Z52: - | AA52: - | AB52: - | AC52: - | AD52: - | AE52: -
A53: Proceeds related to sales of tower sites - FCF | B53: - | C53: - | D53: - | E53: - | F53: - | G53: - | H53: - | I53: - | J53: - | K53: - | L53: - | M53: - | N53: - | O53: - | P53: - | Q53: - | R53: - | S53: - | T53: - | U53: - | V53: - | W53: - | X53: - | Y53: - | Z53: - | AA53: - | AB53: - | AC53: - | AD53: - | AE53: -
A54: Adjusted Free Cash Flow | B54: 4396 | C54: 4596 | D54: 4818 | E54: 4185 | F54: 17995 | G54: 4599 | H54: 4797 | I54: 4859.12 | J54: 4563.45 | K54: 18813.26 | L54: 5126.5 | M54: 4852.46 | N54: 5077.74 | O54: 5423.22 | P54: 20267.81 | Q54: 5449.26 | R54: 5384.85 | S54: 5557.69 | T54: 5814.86 | U54: 22081.03 | V54: 5350.59 | W54: 5779.82 | X54: 6079.86 | Y54: 6283.18 | Z54: 23580.58 | AA54: 5511.76 | AB54: 6094.13 | AC54: 6424.84 | AD54: 6615.84 | AE54: 24639.07
A55: Net cash payments for Merger-related costs - FCF | B55: -70 | C55: -92 | D55: -96 | E55: -100 | F55: -358 | G55: -153 | H55: -181 | I55: -378.11 | J55: -415.19 | K55: -1159.59 | L55: -235.5 | M55: -288 | N55: -235.5 | O55: -176.67 | P55: -967.83 | Q55: - | R55: - | S55: - | T55: - | U55: -500 | V55: - | W55: - | X55: - | Y55: - | Z55: - | AA55: - | AB55: - | AC55: - | AD55: - | AE55: -
A56: Adjusted Free cash flow - excluding merger costs | B56: 4466 | C56: 4688 | D56: 4914 | E56: 4285 | F56: 18353 | G56: 4752 | H56: 4978 | I56: 5164.19 | J56: 4972.69 | K56: 19862.22 | L56: 5815.63 | M56: 4750.42 | N56: 4946.98 | O56: 5606.22 | P56: 21065.65 | Q56: 5922.15 | R56: 4899.44 | S56: 5155.85 | T56: 5273.56 | U56: 22187.3 | V56: 4985.53 | W56: 5265.94 | X56: 6041.7 | Y56: 5772.53 | Z56: 23457.14 | AA56: 5001.02 | AB56: 5272.44 | AC56: 6394.68 | AD56: 6299.11 | AE56: 24486.74
A58: Adjusted FCF per share($) | B58: 3.84 | C58: 4.05 | D58: 4.28 | E58: 3.75 | F58: 15.91 | G58: 4.17 | H58: 4.43 | I58: 4.48 | J58: 4.32 | K58: 17.38 | L58: 4.79 | M58: 4.73 | N58: 5.04 | O58: 5.35 | P58: 19.74 | Q58: 5.57 | R58: 5.6 | S58: 5.88 | T58: 6.26 | U58: 22.65 | V58: 5.91 | W58: 6.49 | X58: 6.96 | Y58: 7.34 | Z58: 25.79 | AA58: 6.43 | AB58: 7.22 | AC58: 7.73 | AD58: 8.11 | AE58: 28.36
A59: Adjusted FCF per share - excluding merger costs($) | B59: 3.9 | C59: 4.13 | D59: 4.36 | E59: 3.83 | F59: 16.23 | G59: 4.31 | H59: 4.6 | I59: 4.83 | J59: 4.71 | K59: 18.44 | L59: 5.58 | M59: 4.61 | N59: 4.87 | O59: 5.63 | P59: 20.57 | Q59: 6.04 | R59: 5.08 | S59: 5.43 | T59: 5.63 | U59: 22.95 | V59: 5.53 | W59: 5.94 | X59: 6.93 | Y59: 6.73 | Z59: 26.5 | AA59: 5.93 | AB59: 6.35 | AC59: 7.83 | AD59: 7.84 | AE59: 30.06

Sheet EBITDA
A2: T-Mobile US, Inc. | EBITDA
A3: NASDAQGS:TMUS (MI KEY: 4091145; SPCIQ KEY: 93339)
A5: Visible Alpha
A7: Period Type : Fiscal Quarter, Fiscal Halves, Fiscal Year
A8: Period Start : 2025
A9: Period End : 2030
A10: Currency : Reported
A11: Consensus View : Mean
A12: As Of: 10/28/2026
A14: All numbers in $M unless otherwise indicated | B14: FQ1 2025A | C14: FQ2 2025A | D14: FQ3 2025A | E14: FQ4 2025A | F14: FY2025A | G14: FQ1 2026A | H14: FQ2 2026A | I14: FQ3 2026E | J14: FQ4 2026E | K14: FY2026E | L14: FQ1 2027E | M14: FQ2 2027E | N14: FQ3 2027E | O14: FQ4 2027E | P14: FY2027E | Q14: FQ1 2028E | R14: FQ2 2028E | S14: FQ3 2028E | T14: FQ4 2028E | U14: FY2028E | V14: FQ1 2029E | W14: FQ2 2029E | X14: FQ3 2029E | Y14: FQ4 2029E | Z14: FY2029E | AA14: FQ1 2030E | AB14: FQ2 2030E | AC14: FQ3 2030E | AD14: FQ4 2030E | AE14: FY2030E
A15: Number of Contributors Available | B15: 20 | C15: 20 | D15: 20 | E15: 20 | F15: 22 | G15: 21 | H15: 21 | I15: 21 of 22 | J15: 21 of 22 | K15: 22 of 22 | L15: 13 of 22 | M15: 13 of 22 | N15: 12 of 22 | O15: 12 of 22 | P15: 22 of 22 | Q15: 6 of 22 | R15: 6 of 22 | S15: 6 of 22 | T15: 6 of 22 | U15: 19 of 22 | V15: 5 of 22 | W15: 5 of 22 | X15: 5 of 22 | Y15: 5 of 22 | Z15: 15 of 22 | AA15: 4 of 22 | AB15: 4 of 22 | AC15: 4 of 22 | AD15: 4 of 22 | AE15: 14 of 22
A16: Operating income/(loss) | B16: 4800 | C16: 5213 | D16: 4530 | E16: 3736 | F16: 18279 | G16: 4497 | H16: 5490 | I16: 5321.15 | J16: 5062.42 | K16: 20369.03 | L16: 5950.2 | M16: 6302.68 | N16: 6341.46 | O16: 6170.89 | P16: 24319.91 | Q16: 6923.6 | R16: 7217.76 | S16: 7122.68 | T16: 6918.94 | U16: 27659.84 | V16: 7416.97 | W16: 7734.43 | X16: 7621.46 | Y16: 7408.22 | Z16: 30212.48 | AA16: 7865.5 | AB16: 8217.65 | AC16: 8076.74 | AD16: 7794.66 | AE16: 32273.95
A17: Depreciation and amortization | B17: 3198 | C17: 3146 | D17: 3408 | E17: 3756 | F17: 13508 | G17: 3817 | H17: 3434 | I17: 3577.37 | J17: 3610.24 | K17: 14416.73 | L17: 3567.64 | M17: 3486.46 | N17: 3522.23 | O17: 3535.48 | P17: 14308.28 | Q17: 3528.41 | R17: 3462.92 | S17: 3504.13 | T17: 3512.84 | U17: 14279.96 | V17: 3524.11 | W17: 3443.97 | X17: 3499.6 | Y17: 3512.66 | Z17: 14257.62 | AA17: 3610.93 | AB17: 3479.38 | AC17: 3544.58 | AD17: 3566.1 | AE17: 14453.64
A18: Stock-Based Compensation | B18: 168 | C18: 178 | D18: 217 | E18: 209 | F18: 772 | G18: 203 | H18: 212 | I18: 207.35 | J18: 216.25 | K18: 857.86 | L18: 206.66 | M18: 211.41 | N18: 217.02 | O18: 220.87 | P18: 892.08 | Q18: 206.99 | R18: 210.03 | S18: 211.62 | T18: 215.71 | U18: 935.96 | V18: 219.83 | W18: 224.87 | X18: 225.73 | Y18: 224.66 | Z18: 921.89 | AA18: 228.45 | AB18: 234.95 | AC18: 236.23 | AD18: 234.82 | AE18: 958.33
A19: Merger related costs - EBITDA | B19: 14 | C19: 33 | D19: 73 | E19: 143 | F19: 263 | G19: 406 | H19: 182 | I19: 255.06 | J19: 248.25 | K19: 1091.72 | L19: 242.38 | M19: 252.38 | N19: 182 | O19: 140.71 | P19: 731.02 | Q19: - | R19: - | S19: - | T19: - | U19: 179.77 | V19: - | W19: - | X19: - | Y19: - | Z19: - | AA19: - | AB19: - | AC19: - | AD19: - | AE19: -
A20: Total other adjustments in EBITDA | B20: 79 | C20: -23 | D20: 456 | E20: 603 | F20: 1115 | G20: 318 | H20: 219 | I20: 172.06 | J20: 140.68 | K20: 770.45 | L20: 172.41 | M20: 167.89 | N20: 208.24 | O20: 205.17 | P20: 719.16 | Q20: 292.36 | R20: 295.54 | S20: 298.53 | T20: 297.24 | U20: 848.16 | V20: 295.92 | W20: 296.81 | X20: 297.12 | Y20: 296.77 | Z20: 693.31 | AA20: - | AB20: - | AC20: - | AD20: - | AE20: 200
A21: Total adjustment excl SBC in EBITDA | B21: 93 | C21: 10 | D21: 529 | E21: 746 | F21: 1378 | G21: 724 | H21: 401 | I21: 331.15 | J21: 308.12 | K21: 1725.36 | L21: 262.87 | M21: 269.06 | N21: 210.97 | O21: 177.84 | P21: 940.44 | Q21: 292.36 | R21: 295.54 | S21: 298.53 | T21: 297.24 | U21: 561.7 | V21: 295.92 | W21: 296.81 | X21: 297.12 | Y21: 296.77 | Z21: 462.2 | AA21: - | AB21: - | AC21: - | AD21: - | AE21: 99.98
A22: Adjusted EBITDA | B22: 8259 | C22: 8547 | D22: 8684 | E22: 8447 | F22: 33937 | G22: 9241 | H22: 9537 | I22: 9413.94 | J22: 9173.53 | K22: 37357.38 | L22: 9948.96 | M22: 10261.12 | N22: 10271.42 | O22: 10042.79 | P22: 40443.08 | Q22: 10707.73 | R22: 10939.97 | S22: 10888.19 | T22: 10697.03 | U22: 43081.84 | V22: 11220.09 | W22: 11462.64 | X22: 11406.22 | Y22: 11204.89 | Z22: 45546.14 | AA22: 11704.88 | AB22: 11931.98 | AC22: 11857.55 | AD22: 11595.59 | AE22: 47816.07
A23: Lease revenue adjustment | B23: 1 | C23: 6 | D23: 4 | E23: 2 | F23: 13 | G23: 1 | H23: 0 | I23: 0.98 | J23: -0.49 | K23: 1.81 | L23: 0.17 | M23: 0.17 | N23: 0.17 | O23: 0.17 | P23: 1.19 | Q23: 0 | R23: 0 | S23: 0 | T23: 0 | U23: 1.19 | V23: 0 | W23: 0 | X23: 0 | Y23: 0 | Z23: 0.89 | AA23: 0 | AB23: 0 | AC23: 0 | AD23: 0 | AE23: 0.86
A24: US Cellular in EBITDA | B24: 182 | C24: 174 | D24: 165.18 | E24: 114.5 | F24: 635.67 | G24: 152.79 | H24: 162.4 | I24: 177.26 | J24: 225.09 | K24: 875.15 | L24: 136.38 | M24: 126.14 | N24: 138.71 | O24: 82.42 | P24: 491.83 | Q24: 131.26 | R24: 119.45 | S24: 132.81 | T24: 72.33 | U24: 252.92 | V24: 126.4 | W24: 112.9 | X24: 127 | Y24: 61.47 | Z24: 427.77 | AA24: 120.9 | AB24: 105.28 | AC24: 120.19 | AD24: 48.69 | AE24: 395.07
A25: Synergies in EBITDA | B25: - | C25: - | D25: 15.3 | E25: 71.25 | F25: 86.55 | G25: 83.12 | H25: 73.5 | I25: 265.31 | J25: 166.25 | K25: 537.5 | L25: 201.88 | M25: 237.5 | N25: 237.5 | O25: 237.5 | P25: 707.19 | Q25: 237.5 | R25: 237.5 | S25: 237.5 | T25: 237.5 | U25: 950 | V25: 237.5 | W25: 237.5 | X25: 237.5 | Y25: 237.5 | Z25: 950 | AA25: 237.5 | AB25: 237.5 | AC25: 237.5 | AD25: 237.5 | AE25: 950
A26: Core Adjusted EBITDA | B26: 8258 | C26: 8541 | D26: 8680 | E26: 8445 | F26: 33924 | G26: 9240 | H26: 9537 | I26: 9409.55 | J26: 9176.36 | K26: 37360.89 | L26: 9979.38 | M26: 10288.98 | N26: 10271.27 | O26: 10042.63 | P26: 40446.98 | Q26: 10707.73 | R26: 10939.97 | S26: 10888.19 | T26: 10697.03 | U26: 43110.13 | V26: 11220.09 | W26: 11462.64 | X26: 11406.22 | Y26: 11204.89 | Z26: 45545.31 | AA26: 11704.88 | AB26: 11931.98 | AC26: 11857.55 | AD26: 11595.59 | AE26: 47815.28
