Workbook

Sheet Guidance Summary
A1: EXHIBIT 2: TMUS Financial guidance summary (updated for 3Q26)
A3: FY2026 Full-Year Guidance
A4: Metric | B4: Previous Guidance (2Q26) | C4: Current Guidance (3Q26) | D4: Change | E4: Source / Notes
A5: Postpaid net account additions | B5: 950K – 1.05M | C5: ~1.0M | D5: Narrowed to midpoint | E5: Range narrowed to the midpoint. Implies ~232K in Q4 vs 274K in Q3 and 261K in 4Q25 — below Q4 seasonality.
A6: Service revenues | B6: ~$77.0B (+8% YoY) | C6: ="~$"&TEXT('Guidance Detail'!D6/1000,"0.0")&"B (+"&TEXT('Guidance Detail'!L6,"0%")&" YoY)" -> ~$76.8B (+8% YoY) | D6: =IF('Guidance Detail'!H6=0,"No change",IF('Guidance Detail'!H6>0,"+","–")&"$"&TEXT(ABS('Guidance Detail'!H6),"#,##0")&"M") -> –$200M | E6: Disclosed on call. Lower wholesale & other (TracFone/Boost MVNO rolling off faster than expected) and continued prepaid declines, partly offset by postpaid outperformance. New: Q4 organic postpaid service revenue growth ~7% YoY.
A7: Postpaid ARPA growth | B7: 2.5% – 3.0% | C7: ~3.5% | D7: ="Raised (+"&TEXT('Guidance Detail'!H12*10000,"0")&"bps at midpoint)" -> Raised (+75bps at midpoint) | E7: Disclosed on call. Driven by premium rate plan adoption (60% of new-account lines on premium plans), deeper account relationships and rate plan modernization. 9M26 YoY +3.4%; implies Q4 ARPA roughly flat QoQ (~$156).
A8: Core Adjusted EBITDA | B8: $37.1B – $37.5B | C8: ="$"&TEXT('Guidance Detail'!D7/1000,"0.0#")&"B – $"&TEXT('Guidance Detail'!E7/1000,"0.0#")&"B"&" (+"&TEXT('Guidance Detail'!L7,"0%")&" YoY at midpoint)" -> $37.35B – $37.45B (+10% YoY at midpoint) | D8: =IF('Guidance Detail'!H7=0,"No change",IF('Guidance Detail'!H7>0,"+","–")&"$"&TEXT(ABS('Guidance Detail'!H7),"#,##0")&"M at midpoint") -> +$100M at midpoint | E8: Low end raised $250M; high end unchanged. Implies Q4 of ~$8.95–9.05B (+6–7% YoY) vs +11.5% YoY through 9M; Q3 inventory constraints shifted some device cost into Q4.
A9: Capital expenditures (capex) | B9: ~$10.0B | C9: ~$10.0B | D9: No change | E9: Implies ~$2.4B in Q4 after $2.27B in Q3 (down 14% YoY on planned timing).
A10: Net cash provided by operating activities | B10: $28.4B – $28.8B | C10: ="$"&TEXT('Guidance Detail'!D8/1000,"0.0#")&"B – $"&TEXT('Guidance Detail'!E8/1000,"0.0#")&"B" -> $28.7B – $28.8B | D10: =IF('Guidance Detail'!H8=0,"No change",IF('Guidance Detail'!H8>0,"+","–")&"$"&TEXT(ABS('Guidance Detail'!H8),"#,##0")&"M at midpoint") -> +$150M at midpoint | E10: Low end raised $300M; high end unchanged. Includes net payments for UScellular merger-related costs ($532M YTD).
A11: Adjusted Free Cash Flow | B11: $18.4B – $18.8B | C11: ="$"&TEXT('Guidance Detail'!D10/1000,"0.0#")&"B – $"&TEXT('Guidance Detail'!E10/1000,"0.0#")&"B" -> $18.7B – $18.8B | D11: =IF('Guidance Detail'!H10=0,"No change",IF('Guidance Detail'!H10>0,"+","–")&"$"&TEXT(ABS('Guidance Detail'!H10),"#,##0")&"M at midpoint") -> +$150M at midpoint | E11: Low end raised $300M; high end unchanged. Includes UScellular merger-related payments; assumes no material net cash inflows from securitization.
A12: Effective tax rate | B12: 25% – 26% | C12: 24% – 25% | D12: ="("&TEXT(ABS('Guidance Detail'!H11)*10000,"0")&") bps" -> (100) bps | E12: Lowered 100bps. Q3 ETR 23.9%; 9M26 24.6%.
A14: Q4 2026 Implied Guidance (FY guide less 9M26 actuals)
A15: Metric | B15: Q4'26 Implied | C15: 4Q25 Actual | D15: Implied YoY
A16: Postpaid net account additions | B16: ="~"&TEXT('Guidance Detail'!P5,"0")&"K" -> ~232K | C16: ='Guidance Detail'!J5 -> 261 | D16: =TEXT('Guidance Detail'!Q5,"0%;(0%)") -> (11%)
A17: Service revenues | B17: ="~$"&TEXT('Guidance Detail'!P6/1000,"0.0")&"B" -> ~$19.6B | C17: ='Guidance Detail'!J6/1000 -> 18.702 | D17: ="+"&TEXT('Guidance Detail'!Q6,"0%") -> +5%
A18: Postpaid service revenue growth (organic) | B18: ~+7% YoY | C18: n/a | D18: Guided on call
A19: Postpaid ARPA (approx.) | B19: ="~$"&TEXT('Guidance Detail'!E18,"0") -> ~$156 | C19: ='Guidance Detail'!E17 -> 150.17 | D19: ="+"&TEXT('Guidance Detail'!E19,"0%")&" (QoQ "&TEXT('Guidance Detail'!E20,"0.0%;(0.0%)")&")" -> +4% (QoQ 0.2%)
A20: Core Adjusted EBITDA | B20: ="$"&TEXT('Guidance Detail'!N7/1000,"0.00")&"B – $"&TEXT('Guidance Detail'!O7/1000,"0.00")&"B" -> $8.95B – $9.05B | C20: ='Guidance Detail'!J7/1000 -> 8.445 | D20: ="+"&TEXT('Guidance Detail'!N7/'Guidance Detail'!J7-1,"0.0%")&" to +"&TEXT('Guidance Detail'!O7/'Guidance Detail'!J7-1,"0.0%") -> +6.0% to +7.2%
A21: Capital expenditures | B21: ="~$"&TEXT('Guidance Detail'!P9/1000,"0.0")&"B" -> ~$2.4B | C21: ='Guidance Detail'!J9/1000 -> 2.469 | D21: =TEXT('Guidance Detail'!Q9,"0%;(0%)") -> (3%)
A22: Adjusted Free Cash Flow | B22: ="$"&TEXT('Guidance Detail'!N10/1000,"0.00")&"B – $"&TEXT('Guidance Detail'!O10/1000,"0.00")&"B" -> $4.23B – $4.33B | C22: ='Guidance Detail'!J10/1000 -> 4.185 | D22: ="+"&TEXT('Guidance Detail'!N10/'Guidance Detail'!J10-1,"0.0%")&" to +"&TEXT('Guidance Detail'!O10/'Guidance Detail'!J10-1,"0.0%") -> +1.1% to +3.5%
A24: Q3 2026 Guide vs. Actual
A25: Metric | B25: Q3 2026 Guide | C25: Q3 2026 Actual | D25: Variance vs. Guide
A26: Postpaid net additions | B26: ~250K | C26: =TEXT('Guidance Detail'!C26,"0")&"K" -> 274K | D26: ="+"&TEXT('Guidance Detail'!D26,"0")&"K" -> +24K
A27: Service revenues | B27: ~$19.3B (+6% YoY) | C27: ="$"&TEXT('Guidance Detail'!C27/1000,"0.00")&"B (+"&TEXT('Guidance Detail'!G27,"0.0%")&" YoY)" -> $19.38B (+6.2% YoY) | D27: ="+$"&TEXT('Guidance Detail'!D27,"0")&"M" -> +$75M
A28: Core Adjusted EBITDA | B28: ~$9.4B (+8% YoY) | C28: ="$"&TEXT('Guidance Detail'!C28/1000,"0.00")&"B (+"&TEXT('Guidance Detail'!G28,"0.0%")&" YoY)" -> $9.62B (+10.8% YoY) | D28: ="+$"&TEXT('Guidance Detail'!D28,"0")&"M" -> +$220M
A30: Source: Company reports (3Q26 earnings release, investor factbook and earnings call), Bernstein analysis. Previous FY guidance, prior ~$77.0B service revenue figure and Q3 guide per prior Bernstein exhibit. Implied Q4 figures calculated on 'Guidance Detail' tab.

Sheet Guidance Detail
A1: TMUS 2026 guidance detail ($ in millions unless noted)
A2: Blue = hardcoded input (company reports / prior Bernstein exhibit); black = formula. Implied Q4 = FY guide less 9M26 actual.
A4: Metric | B4: Prev Low | C4: Prev High | D4: Cur Low | E4: Cur High | F4: Prev Mid | G4: Cur Mid | H4: Δ Mid | I4: 9M25A | J4: Q4'25A | K4: FY25A | L4: YoY @ Cur Mid | M4: 9M26A | N4: Implied Q4 Low | O4: Implied Q4 High | P4: Implied Q4 Mid | Q4: Implied Q4 YoY (mid) | R4: Source
A5: Postpaid net account additions (K) | B5: 950 | C5: 1050 | D5: 1000 | E5: 1000 | F5: =AVERAGE(B5:C5) -> 1000 | G5: =AVERAGE(D5:E5) -> 1000 | H5: =G5-F5 -> 0 | I5: 919 | J5: 261 | K5: =I5+J5 -> 1180 | L5: =IF(K5=0,"",G5/K5-1) -> -0.15254237 | M5: 768 | N5: =D5-M5 -> 232 | O5: =E5-M5 -> 232 | P5: =AVERAGE(N5:O5) -> 232 | Q5: =IF(J5=0,"",P5/J5-1) -> -0.11111111 | R5: Release p.3; factbook p.20
A6: Service revenues | B6: 77000 | C6: 77000 | D6: 76800 | E6: 76800 | F6: =AVERAGE(B6:C6) -> 77000 | G6: =AVERAGE(D6:E6) -> 76800 | H6: =G6-F6 -> -200 | I6: 52604 | J6: 18702 | K6: =I6+J6 -> 71306 | L6: =IF(K6=0,"",G6/K6-1) -> 0.077048215 | M6: 57189 | N6: =D6-M6 -> 19611 | O6: =E6-M6 -> 19611 | P6: =AVERAGE(N6:O6) -> 19611 | Q6: =IF(J6=0,"",P6/J6-1) -> 0.048604427 | R6: Prior guide ~$77.0B per prior exhibit; ~$76.8B per 3Q26 call (Osvaldik)
A7: Core Adjusted EBITDA | B7: 37100 | C7: 37500 | D7: 37350 | E7: 37450 | F7: =AVERAGE(B7:C7) -> 37300 | G7: =AVERAGE(D7:E7) -> 37400 | H7: =G7-F7 -> 100 | I7: 25479 | J7: 8445 | K7: =I7+J7 -> 33924 | L7: =IF(K7=0,"",G7/K7-1) -> 0.10246433 | M7: 28397 | N7: =D7-M7 -> 8953 | O7: =E7-M7 -> 9053 | P7: =AVERAGE(N7:O7) -> 9003 | Q7: =IF(J7=0,"",P7/J7-1) -> 0.0660746 | R7: Release p.3; factbook p.21
A8: Net cash provided by operating activities | B8: 28400 | C8: 28800 | D8: 28700 | E8: 28800 | F8: =AVERAGE(B8:C8) -> 28600 | G8: =AVERAGE(D8:E8) -> 28750 | H8: =G8-F8 -> 150 | I8: 21296 | J8: 6654 | K8: =I8+J8 -> 27950 | L8: =IF(K8=0,"",G8/K8-1) -> 0.02862254 | M8: 22063 | N8: =D8-M8 -> 6637 | O8: =E8-M8 -> 6737 | P8: =AVERAGE(N8:O8) -> 6687 | Q8: =IF(J8=0,"",P8/J8-1) -> 0.0049594229 | R8: Release p.3; factbook p.21
A9: Capital expenditures | B9: 10000 | C9: 10000 | D9: 10000 | E9: 10000 | F9: =AVERAGE(B9:C9) -> 10000 | G9: =AVERAGE(D9:E9) -> 10000 | H9: =G9-F9 -> 0 | I9: 7486 | J9: 2469 | K9: =I9+J9 -> 9955 | L9: =IF(K9=0,"",G9/K9-1) -> 0.0045203415 | M9: 7596 | N9: =D9-M9 -> 2404 | O9: =E9-M9 -> 2404 | P9: =AVERAGE(N9:O9) -> 2404 | Q9: =IF(J9=0,"",P9/J9-1) -> -0.026326448 | R9: Release p.3; cash purchases of PP&E incl. capitalized interest
A10: Adjusted Free Cash Flow | B10: 18400 | C10: 18800 | D10: 18700 | E10: 18800 | F10: =AVERAGE(B10:C10) -> 18600 | G10: =AVERAGE(D10:E10) -> 18750 | H10: =G10-F10 -> 150 | I10: 13810 | J10: 4185 | K10: =I10+J10 -> 17995 | L10: =IF(K10=0,"",G10/K10-1) -> 0.041956099 | M10: 14467 | N10: =D10-M10 -> 4233 | O10: =E10-M10 -> 4333 | P10: =AVERAGE(N10:O10) -> 4283 | Q10: =IF(J10=0,"",P10/J10-1) -> 0.023416965 | R10: Release p.3; factbook p.21
A11: Effective tax rate | B11: 0.25 | C11: 0.26 | D11: 0.24 | E11: 0.25 | F11: =AVERAGE(B11:C11) -> 0.255 | G11: =AVERAGE(D11:E11) -> 0.245 | H11: =G11-F11 -> -0.01 | M11: =3004/12202 -> 0.24618915 | R11: 9M26 ETR = income tax expense $3,004M / pre-tax income $12,202M (factbook p.17)
A12: Postpaid ARPA growth (YoY) | B12: 0.025 | C12: 0.03 | D12: 0.035 | E12: 0.035 | F12: =AVERAGE(B12:C12) -> 0.0275 | G12: =AVERAGE(D12:E12) -> 0.035 | H12: =G12-F12 -> 0.0075 | M12: =C21/B21-1 -> 0.033593645 | R12: ~3.5% per 3Q26 call (Osvaldik), up from 2.5–3.0%; 9M26 YoY from ARPA block below
A15: Implied Q4'26 postpaid ARPA (approximation: simple average of quarterly ARPA, not account-weighted)
B16: Q1 | C16: Q2 | D16: Q3 | E16: Q4
A17: 2025 ARPA ($) | B17: 146.22 | C17: 149.87 | D17: 149.44 | E17: 150.17
A18: 2026 ARPA ($) | B18: 151.93 | C18: 152.91 | D18: 155.73 | E18: =AVERAGE(B17:E17)*(1+G12)*4-SUM(B18:D18) -> 155.9795
A19: YoY | B19: =B18/B17-1 -> 0.039050745 | C19: =C18/C17-1 -> 0.020284246 | D19: =D18/D17-1 -> 0.042090471 | E19: =E18/E17-1 -> 0.038686156
A20: QoQ (Q4 vs Q3) | E20: =E18/D18-1 -> 0.0016021319
A21: 9M average ARPA ($): 2025 | 2026 | B21: 148.54 | C21: 153.53 | D21: Factbook p.20 (nine-month ARPA)
A24: Q3'26 guide vs actual
A25: Metric | B25: Q3 Guide | C25: Q3 Actual | D25: Variance | E25: Q3'25A | F25: Guide YoY | G25: Actual YoY | H25: Source
A26: Postpaid net additions (K) | B26: 250 | C26: 274 | D26: =C26-B26 -> 24 | E26: 396 | F26: =B26/E26-1 -> -0.36868687 | G26: =C26/E26-1 -> -0.30808081 | H26: Guide per prior Bernstein exhibit; actuals per 3Q26 release
A27: Service revenues | B27: 19300 | C27: 19375 | D27: =C27-B27 -> 75 | E27: 18241 | F27: =B27/E27-1 -> 0.058056028 | G27: =C27/E27-1 -> 0.062167644 | H27: Guide per prior Bernstein exhibit; actuals per 3Q26 release
A28: Core Adjusted EBITDA | B28: 9400 | C28: 9620 | D28: =C28-B28 -> 220 | E28: 8680 | F28: =B28/E28-1 -> 0.082949309 | G28: =C28/E28-1 -> 0.10829493 | H28: Guide per prior Bernstein exhibit; actuals per 3Q26 release
