Workbook
Name IQ_CH: 110000
Name IQ_CQ: 5000
Name IQ_CY: 10000
Name IQ_DAILY: 500000
Name IQ_FH: 100000
Name IQ_FQ: 500
Name IQ_FY: 1000
Name IQ_LTM: 2000
Name IQ_MONTH: 15000
Name IQ_NTM: 6000
Name IQ_WEEK: 50000
Name IQ_YTD: 3000

Sheet First look
A1: Verizon — Q3 2026 Earnings First Look
A2: $B (except as noted) | B2: Q3'25 | C2: Q2'26 | D2: Consensus 3Q'26 | E2: Actual 3Q'26 | F2: YoY Growth | G2: Beat/Miss
A3: Total Revenue | B3: ='Income statement'!D18/1000 -> 33.821 | C3: ='Income statement'!H18/1000 -> 34.253 | D3: ='Income statement'!I18/1000 -> 34.76799 | E3: 34.313 | F3: =IF(E3="","",E3/B3-1) -> 0.014547175 | G3: =IF(E3="","",E3/D3-1) -> -0.013086463
A4: Consumer Segment | B4: =Segment!D20/1000 -> 26.105 | C4: =Segment!H20/1000 -> 26.242 | D4: =Segment!I20/1000 -> 26.90166 | E4: 26.432 | F4: =IF(E4="","",E4/B4-1) -> 0.012526336 | G4: =IF(E4="","",E4/D4-1) -> -0.017458402
A5: Business Segment | B5: =Segment!D24/1000 -> 6.843 | C5: =Segment!H24/1000 -> 7.155 | D5: =Segment!I24/1000 -> 7.25908 | E5: 7.023 | F5: =IF(E5="","",E5/B5-1) -> 0.026304253 | G5: =IF(E5="","",E5/D5-1) -> -0.032522028
A6: Wireless Equipment | B6: ='Income statement'!D17/1000 -> 5.619 | C6: ='Income statement'!H17/1000 -> 5.024 | D6: ='Income statement'!I17/1000 -> 5.44478 | E6: 5.116 | F6: =IF(E6="","",E6/B6-1) -> -0.089517708 | G6: =IF(E6="","",E6/D6-1) -> -0.060384442
A8: Total Mobility and Broadband Service Rev | B8: =Segment!D29/1000 -> 22.839 | C8: =Segment!H29/1000 -> 23.365 | D8: =Segment!I29/1000 -> 23.53792 | E8: =E9+E10 -> 23.49 | F8: =IF(E8="","",E8/B8-1) -> 0.028503875 | G8: =IF(E8="","",E8/D8-1) -> -0.0020358638
A9: Cons. Mobility and broadband service | B9: =Segment!D17/1000 -> 19.096 | C9: =Segment!H17/1000 -> 19.637 | D9: =Segment!I17/1000 -> 19.77217 | E9: 19.777 | F9: =IF(E9="","",E9/B9-1) -> 0.035661919 | G9: =IF(E9="","",E9/D9-1) -> 0.00024428275
A10: Bus. Mobility and broadband service | B10: =Segment!D21/1000 -> 3.743 | C10: =Segment!H21/1000 -> 3.728 | D10: =Segment!I21/1000 -> 3.77446 | E10: 3.713 | F10: =IF(E10="","",E10/B10-1) -> -0.0080149613 | G10: =IF(E10="","",E10/D10-1) -> -0.016283124
A12: Total Adj. EBITDA | B12: ='Income statement'!D29/1000 -> 12.775 | C12: ='Income statement'!H29/1000 -> 13.723 | D12: ='Income statement'!I29/1000 -> 13.69151 | E12: 13.8 | F12: =IF(E12="","",E12/B12-1) -> 0.080234834 | G12: =IF(E12="","",E12/D12-1) -> 0.0079238886
A13: Consumer Segment | B13: =Segment!D82/1000 -> 11.232 | C13: =Segment!H82/1000 -> 11.819 | D13: =Segment!I82/1000 -> 11.90974 | E13: 11.965 | F13: =IF(E13="","",E13/B13-1) -> 0.065259972 | G13: =IF(E13="","",E13/D13-1) -> 0.0046398998
A14: Business Segment | B14: =Segment!D83/1000 -> 1.718 | C14: =Segment!H83/1000 -> 2.082 | D14: =Segment!I83/1000 -> 1.92104 | E14: 1.941 | F14: =IF(E14="","",E14/B14-1) -> 0.1298021 | G14: =IF(E14="","",E14/D14-1) -> 0.010390205
A15: Total EBITDA Margin | B15: =IF(B12="","",B12/B3) -> 0.3777239 | C15: =IF(C12="","",C12/C3) -> 0.40063644 | D15: =IF(D12="","",D12/D3) -> 0.39379642 | E15: =IF(E12="","",E12/E3) -> 0.40217993 | F15: =IF(E15="","",E15-B15) -> 0.024456032 | G15: =IF(E15="","",E15-D15) -> 0.0083835116
A16: Consumer EBITDA Margin | B16: =IF(B13="","",B13/B4) -> 0.4302624 | C16: =IF(C13="","",C13/C4) -> 0.45038488 | D16: =IF(D13="","",D13/D4) -> 0.44271394 | E16: =IF(E13="","",E13/E4) -> 0.452671 | F16: =IF(E16="","",E16-B16) -> 0.022408603 | G16: =IF(E16="","",E16-D16) -> 0.0099570608
A17: Business EBITDA Margin | B17: =IF(B14="","",B14/B5) -> 0.25105948 | C17: =IF(C14="","",C14/C5) -> 0.29098532 | D17: =IF(D14="","",D14/D5) -> 0.2646396 | E17: =IF(E14="","",E14/E5) -> 0.27637762 | F17: =IF(E17="","",E17-B17) -> 0.02531814 | G17: =IF(E17="","",E17-D17) -> 0.01173802
A18: Adjusted EPS | B18: ='Income statement'!D52 -> 1.21 | C18: ='Income statement'!H52 -> 1.3 | D18: ='Income statement'!I52 -> 1.27 | E18: 1.31 | F18: =IF(E18="","",E18/B18-1) -> 0.082644628 | G18: =IF(E18="","",E18/D18-1) -> 0.031496063
A20: Operational metrics
A21: Total Postpaid Net Adds (in 000') | B21: =Wireless!D21 -> 36 | C21: =Wireless!H21 -> 188 | D21: =Wireless!I21 -> 203.14 | E21: 231 | F21: =IF(E21="","",IF(B21<=0,"n.m",E21/B21-1)) -> 5.4166667 | G21: =IF(E21="","",IF(D21<=0,"n.m",E21/D21-1)) -> 0.1371468
A22: Total Postpaid Phone Net Adds (in 000') | B22: =Consumer!D164+Business!D89 -> 44 | C22: =Consumer!H164+Business!H89 -> 165.36 | D22: =Consumer!I164+Business!I89 -> 186.48 | E22: 406 | F22: =IF(E22="","",IF(B22<=0,"n.m",E22/B22-1)) -> 8.2272727 | G22: =IF(E22="","",IF(D22<=0,"n.m",E22/D22-1)) -> 1.1771772
A23: Total FWA Net Adds (in 000') | B23: =Wireless!D89 -> 261 | C23: =Wireless!H89 -> 193 | D23: =Wireless!I89 -> 194.3 | E23: 159 | F23: =IF(E23="","",IF(B23<=0,"n.m",E23/B23-1)) -> -0.3908046 | G23: =IF(E23="","",IF(D23<=0,"n.m",E23/D23-1)) -> -0.18167782
A24: Fios Internet Net Adds (in 000') | B24: =Wireline!D40 -> 61 | C24: =Wireline!H40 -> 155 | D24: =Wireline!I40 -> 167.68 | E24: 155 | F24: =IF(E24="","",IF(B24<=0,"n.m",E24/B24-1)) -> 1.5409836 | G24: =IF(E24="","",IF(D24<=0,"n.m",E24/D24-1)) -> -0.075620229
A25: Postpaid Phone Churn Rate | B25: =(Consumer!D163+Business!D88)/(Consumer!D168+Business!D93)/3 -> 0.0097880252 | C25: =(Consumer!H163+Business!H88)/(Consumer!H168+Business!H93)/3 -> 0.0091991412 | D25: =(Consumer!I163+Business!I88)/(Consumer!I168+Business!I93)/3 -> 0.0093659504 | E25: 0.0094 | F25: =IF(E25="","",E25/B25-1) -> -0.039642851 | G25: =IF(E25="","",E25/D25-1) -> 0.0036354709
A26: Prepaid Churn Rate | B26: =Wireless!D37 -> 3.73% | C26: =Wireless!H37 -> 3.59% | D26: =Wireless!I37 -> 3.77% | E26: 0.038 | F26: =IF(E26="","",E26/B26-1) -> 0.018766756 | G26: =IF(E26="","",E26/D26-1) -> 0.0079575597
A28: Note: Q3'25, Q2'26 and consensus linked to Visible Alpha consensus tabs (as of 10/25/2026). Enter actuals in column E (yellow); YoY & Beat/Miss populate automatically. Margin YoY/Beat shown as pct-pt change.
K37: 3Q26 Key Takeaways
K38: • Headline: Revenue $34.31B missed consensus by 1.3% (+1.5% YoY). Adj. EBITDA of $13.8B beat by about 0.8% (+8.0% YoY, a company record per mgmt), and adj. EPS of $1.31 beat the $1.27 consensus by 3.1% (+8.3% YoY). GAAP EPS was $1.25 (+6.8%). Adj. EBITDA is disclosed only to $0.1B, so the beat could be anywhere from +0.4% to +1.2%. [VZ 3Q26 PR excerpt; VZ 3Q26 FS p.1]
K39: • Segment EBITDA beat: Consumer $11.97B (+0.5% vs cons, +6.5% YoY) and Business $1.94B (+1.0% vs cons, +13.0% YoY), with combined segment EBITDA of $13.91B vs $13.83B consensus. Segment revenue missed: Consumer -1.7% and Business -3.3% vs cons. [VZ 3Q26 FS p.5-6]
K40: • Postpaid phone net adds of 406K were the biggest surprise: +118% vs 186K consensus and up from 44K in 3Q25. Total postpaid was only 231K (+14% vs cons), which implies about -175K non-phone. Core prepaid was -12K (prepaid phone -52K). The FS gives no explanation, and 3Q26 commentary was not provided. [VZ 3Q26 FS p.7]
K41: • Churn/ARPA: postpaid phone churn was 0.94%, in line with consensus and down 4 bps YoY. Core prepaid churn was 3.80% vs 3.73% YoY. The upgrade rate fell to 2.6% from 3.3%, ARPA fell 1.9% YoY to $168.08 and postpaid accounts were flat at 34.47M. No explanation given. [VZ 3Q26 FS p.7]
K42: • Broadband: FWA net adds of 159K missed by 18% vs 194K consensus and were down 39% YoY. Fiber net adds of 155K were 7.6% below consensus but up 154% YoY. Total broadband net adds were 314K. Fiber connections reached 11.07M (+44% YoY), which includes acquired fiber subs. No explanation given. [VZ 3Q26 FS p.7]
K43: • Equipment revenue was $5.12B: -9.0% YoY and -6.0% vs cons, consistent with the lower upgrade rate. In 2Q, management attributed the equipment decline to lower upgrade volumes and reduced device subsidies [2Q26 PR p.3]; there is no 3Q-specific explanation. Business 'Other' revenue grew 10.0% YoY. [VZ 3Q26 FS p.1, p.6]
K44: • Mobility and broadband service revenue was $23.49B: +2.9% YoY and in line with consensus (-0.2%). Consumer grew 3.6% and Business fell 0.8%. That is roughly in line with 2Q guidance for growth to 'approach 3.0 percent' in 3Q26. [VZ 3Q26 FS p.5-6; 2Q26 PR p.4]
K45: • Margins: Consumer EBITDA margin was 45.3% (+2.2pp YoY, +1.0pp vs cons) and Business was 27.6% (+2.5pp YoY, +1.2pp vs cons). Both match the reported segment margins. In the P&L, cost of equipment fell (Consumer -11.5%) and SG&A fell (-2.9% / -4.8%), partly offset by higher cost of services (+7.4% / +5.3%). No management explanation in the materials. [VZ 3Q26 FS p.5-6]
K46: • Guidance: no 3Q26 guidance update was in the uploaded materials. The last guidance (2Q26) was FY26 M&BB service revenue growth of 2.5-3.0%, adj. EPS of $4.99-5.04, FCF growth of 9-10%, capex of $16.0-16.5B, and postpaid phone net adds in the upper half of 750K-1.0M. Year to date: 645K phone net adds, 9M capex of $11.9B and 9M CFO of $29.9B (+6.8% YoY). [2Q26 PR p.4; VZ 3Q26 FS p.4, p.7]
K47: • Capital allocation/M&A: 9M buybacks were $4.0B (target up to $4.5B) and shares fell to 4,145M from 4,217M. Dividend was $0.7075/qtr. 9M cash paid for acquisitions was $9.48B (acquiree not named in the FS) and goodwill rose $7.9B. Cash fell to $4.5B from $19.0B. Net unsecured debt/adj. EBITDA was 2.3x (2.2x at YE25). [VZ 3Q26 FS p.2-4]
K48: • Recasts/definitions: 1Q26 segment revenue disaggregation was recast. In 2Q26, international wireline/managed network services moved from Business to Corporate & other. The 3Q25 figures in the FS match column B, so B and E are on the same basis. E22 uses reported phone net adds, while B-D use the sum of segment organic figures (2Q26: 165K vs 184K reported). 'Fios Internet' is now reported as 'Fiber broadband'. [VZ 3Q26 FS p.5-7]
K49: • Comparability/one-time items: the FS does not split organic vs. acquired net adds, and operating stats include M&A-related adjustments. Adj. EPS ($1.31) vs GAAP EPS ($1.25) implies about $0.06/share of special items, which are not itemized in the materials provided. D&A rose 10.3% YoY and interest expense rose 17.2% YoY. Implied Corporate & other: revenue about $0.86B and adj. EBITDA about -$0.1B. Still pending: segment phone net adds. [VZ 3Q26 FS p.1, p.7; PR excerpt]

Sheet first look fill instructions
A1: VZ 3Q26 First Look – Prompt for Claude Excel agent (copy cell A3)
A3: ROLE & GOAL You are filling in Verizon's (VZ) 3Q26 earnings "First look" table in this workbook as soon as results are out. I have uploaded the 3Q26 earnings materials (likely the press release, the financial and operating results / supplemental, and the trending schedules). Work fast but put accuracy first. Do not guess any number. STEP 1 – READ THE MATERIALS - Open every uploaded file and figure out which document holds which data. Use the financial and operating results and the trending schedules as the main sources for segment numbers and KPIs. Use the press release for headline numbers and management commentary. - Read the 'First look' sheet before writing anything. Columns B, C and D (Q3'25, Q2'26, Consensus 3Q'26) are formulas linked to the consensus tabs. Do NOT change them. Column E (Actual 3Q'26) is the only input column. Columns F (YoY Growth) and G (Beat/Miss) already contain formulas that fill in automatically once E has values. STEP 2 – FILL COLUMN E (Actual 3Q'26) ON 'First look' Enter reported 3Q26 values as hardcoded numbers in the units shown. Dollar rows are in $ billions (for example, $34,253M becomes 34.253; keep full precision and do not round). Net adds are in thousands. Churn is a decimal (0.92% is entered as 0.0092). - E3 Total Revenue = total operating revenues (consolidated) - E4 Consumer Segment revenue | E5 Business Segment revenue - E6 Wireless Equipment revenue (consolidated) - E8 Total Mobility & broadband service revenue (consolidated) - E9 Consumer mobility & broadband service revenue | E10 Business mobility & broadband service revenue - E12 Total Adjusted EBITDA (consolidated) - E13 Consumer segment EBITDA | E14 Business segment EBITDA - E15:E17 EBITDA margins: these are ALREADY FORMULAS (EBITDA / revenue). Do not overwrite them. Instead, check them against the company's reported segment EBITDA margins and flag any difference. - E18 Adjusted EPS (diluted, adjusted / non-GAAP) - E21 Total postpaid net adds: use the same definition as the source tab (Wireless tab row 21, organic, excluding acquired subscribers) - E22 Total postpaid phone net adds: use Verizon's REPORTED consolidated total (Consumer + Business). Note that C22 is built as Consumer organic + Business organic from the consensus tabs (165K for Q2'26 vs 184K reported). Flag that definitional gap in your summary. - E23 Total FWA net adds (organic) | E24 Fios Internet net adds (organic) - E25 Postpaid phone churn (total retail postpaid phone churn as reported) | E26 Prepaid churn (as reported) Match each line to the same definition the B–D columns use (organic vs. reported, segment vs. consolidated). If Verizon's reported line uses a different definition, use the one closest to ours and flag it. For every value you enter, add a cell note citing the document and the page or table it came from (e.g. "Source: VZ 3Q26 Financial & Operating Info, p.X, Consumer table"). STEP 3 – FORMATTING After filling column E, make it match columns B–D: - Remove the light-yellow input fill (#FFF2CC) from E3:E26. - Keep the grey band fill (#D9D9D9) on rows 3, 12 and 18 so E matches B–D on those rows. - Use blue font (#0000FF) for hardcoded actuals and keep black for the formula cells E15:E17. Keep bold on E3, E12 and E18. - Keep the existing number formats (0.0 for $B, 0.0% for margins, $0.00 for EPS, #,##0 for net adds, 0.00% for churn). - Do not touch the F:G formulas. Check that F3:G26 calculated with no #DIV/0!, #VALUE! or other errors, and that "n.m" shows where the base is zero or negative. STEP 4 – DOUBLE-CHECK (required before you report back) - Re-read E3:G26 and compare each number against the source document a second time. - Check that Consumer + Business + Corporate/other ties to total revenue and total EBITDA within rounding. - Sanity-check against Q2'26 (column C) and consensus (column D). Re-check any metric that is more than ±10% off consensus or more than ±15% off YoY before you accept it. - In chat, tell me which cells you verified. STEP 5 – REPORTING CHANGES / RECASTS (report in chat AND in column K) Tell me clearly if any of the following happened: - A KPI in this table is no longer disclosed, or has been renamed or redefined this quarter (leave that E cell blank, add a note explaining why, and tell me). - Prior-period numbers (e.g. 3Q25 or 2Q26) were RECAST or restated. Say which lines changed, the old vs. new values, and the reason given (segment realignment, acquisition such as Frontier, accounting change, subscriber base adjustment, etc.). If Q3'25 was recast, say whether our column B (consensus-tab actuals) is now on a different basis than column E. - Any new segment, KPI or disclosure appeared. - Any one-time items or adjustments that affect comparability (acquired subscribers, base adjustments, non-GAAP reconciling items). STEP 6 – KEY TAKEAWAYS IN COLUMN K ON 'First look' Read the press release, the CEO/CFO quotes and any commentary in the materials. Write in column K starting at K2: - K2: header "3Q26 Key Takeaways" (same style as the table header: dark blue #1F4E79 fill, white bold font). - K3 onward: one concise bullet per cell (about 8–12 bullets), with wrap text on and column K about 600px wide. Cover: 1. Headline: overall beat/miss on revenue, adj. EBITDA and adj. EPS vs. consensus, with the % from column G. 2. Biggest surprises: any line with a beat or miss of more than about 3% (more than about 10% for net adds and other KPIs) or a large YoY change (from column F). Say what happened and quote or paraphrase management's explanation, citing the document. 3. Subscriber trends: postpaid phone net adds, churn, FWA and Fios. Name the drivers management cited (pricing, promotions, competition, convergence, etc.). 4. Margin and cost story: EBITDA margin expansion or compression and its drivers. 5. Guidance: any change to 2026 guidance (raised, reaffirmed or lowered) and to FCF and capex outlook. 6. Anything else notable: capital allocation, M&A or integration updates, the reporting changes and recasts from Step 5, and one-time items. - If management gave no explanation for a big variance, say "no explanation given". Do not make one up. - Keep each bullet to 1–2 sentences, lead with the number, and cite the source document in brackets. FINAL CHAT REPLY Keep it short: (1) confirm column E was filled and which cells were verified, (2) list any KPIs that were missing, redefined or recast and why, (3) give the top 3 takeaways. Do not paste the whole table into chat.

Sheet Consunesus 10-25-26 ->

Sheet Cash flow
A2: Verizon Communications Inc. | Cash flow
A3: NYSE:VZ (MI KEY: 4057229; SPCIQ KEY: 415798)
A5: Visible Alpha
A7: Period Type : Fiscal Quarter, Fiscal Halves, Fiscal Year
A8: Period Start : 2025
A9: Period End : 2030
A10: Currency : Reported
A11: Consensus View : Mean
A12: As Of: 10/25/2026
A14: All numbers in $M unless otherwise indicated | B14: FQ1 2025A | C14: FQ2 2025A | D14: FQ3 2025A | E14: FQ4 2025A | F14: FY2025A | G14: FQ1 2026A | H14: FQ2 2026A | I14: FQ3 2026E | J14: FQ4 2026E | K14: FY2026E | L14: FQ1 2027E | M14: FQ2 2027E | N14: FQ3 2027E | O14: FQ4 2027E | P14: FY2027E | Q14: FQ1 2028E | R14: FQ2 2028E | S14: FQ3 2028E | T14: FQ4 2028E | U14: FY2028E | V14: FQ1 2029E | W14: FQ2 2029E | X14: FQ3 2029E | Y14: FQ4 2029E | Z14: FY2029E | AA14: FQ1 2030E | AB14: FQ2 2030E | AC14: FQ3 2030E | AD14: FQ4 2030E | AE14: FY2030E
A15: Number of Contributors Available | B15: 19 | C15: 19 | D15: 19 | E15: 19 | F15: 20 | G15: 20 | H15: 20 | I15: 20 of 20 | J15: 20 of 20 | K15: 20 of 20 | L15: 13 of 20 | M15: 13 of 20 | N15: 12 of 20 | O15: 12 of 20 | P15: 20 of 20 | Q15: 7 of 20 | R15: 7 of 20 | S15: 7 of 20 | T15: 7 of 20 | U15: 18 of 20 | V15: 5 of 20 | W15: 5 of 20 | X15: 5 of 20 | Y15: 5 of 20 | Z15: 14 of 20 | AA15: 5 of 20 | AB15: 5 of 20 | AC15: 5 of 20 | AD15: 5 of 20 | AE15: 14 of 20
A16: Net income (CF) | B16: 4983 | C16: 5121 | D16: 5056 | E16: 2448 | F16: 17608 | G16: 5146 | H16: 3949 | I16: 5303.09 | J16: 4752.37 | K16: 19133.86 | L16: 5444.26 | M16: 5415.87 | N16: 5602.89 | O16: 5041.72 | P16: 21494.47 | Q16: 5598.85 | R16: 5676.23 | S16: 5839.72 | T16: 5352.45 | U16: 22534.14 | V16: 5833.63 | W16: 5888.31 | X16: 6030.81 | Y16: 5564.66 | Z16: 23385.22 | AA16: 5984.87 | AB16: 6037.95 | AC16: 6177.96 | AD16: 5716.5 | AE16: 23890.43
A17: Depreciation and amortization | B17: 4577 | C17: 4635 | D17: 4618 | E17: 4519 | F17: 18349 | G17: 4892 | H17: 5008 | I17: 4908.03 | J17: 4917.89 | K17: 19650.53 | L17: 4884.88 | M17: 4903.96 | N17: 4909.15 | O17: 4908.2 | P17: 19719.89 | Q17: 4958.67 | R17: 4989.73 | S17: 4989.71 | T17: 4951.88 | U17: 19926.25 | V17: 5048.85 | W17: 5075.42 | X17: 5078.01 | Y17: 5049.66 | Z17: 20159.83 | AA17: 5079.13 | AB17: 5104.86 | AC17: 5106.84 | AD17: 5076.39 | AE17: 20293.9
A18: Employee retirement benefits | B18: 143 | C18: 188 | D18: 113 | E18: 581 | F18: 1025 | G18: -117 | H18: 152 | I18: -24.16 | J18: -6 | K18: -5.43 | L18: -36.38 | M18: 32.65 | N18: 27.66 | O18: -19.92 | P18: -67.54 | Q18: -51.83 | R18: 54.19 | S18: 23.41 | T18: -49.63 | U18: -79.9 | V18: -12.66 | W18: -12.66 | X18: -12.66 | Y18: -12.66 | Z18: -107.1 | AA18: -9.79 | AB18: -9.79 | AC18: -9.79 | AD18: -9.79 | AE18: -99.45
A19: Deferred income taxes | B19: 132 | C19: -37 | D19: 1714 | E19: 531 | F19: 2340 | G19: 703 | H19: 730 | I19: 555.76 | J19: 299.32 | K19: 2050.32 | L19: 345.17 | M19: 391.07 | N19: 413.37 | O19: 379.04 | P19: 1430.99 | Q19: 229.15 | R19: 370.54 | S19: 354.32 | T19: 324.63 | U19: 1078.24 | V19: 363.45 | W19: 363.8 | X19: 354.02 | Y19: 323.36 | Z19: 969.07 | AA19: 195.41 | AB19: 181.63 | AC19: 193.92 | AD19: 168.03 | AE19: 604.59
A20: Provision for uncollectible accounts | B20: 587 | C20: 548 | D20: 478 | E20: 736 | F20: 2349 | G20: 581 | H20: 462 | I20: 508.27 | J20: 525.25 | K20: 2004.21 | L20: 480.43 | M20: 453.58 | N20: 452.12 | O20: 476.71 | P20: 1969.84 | Q20: 466.44 | R20: 449.79 | S20: 448.3 | T20: 493.96 | U20: 1991.24 | V20: 465.64 | W20: 441.04 | X20: 443.55 | Y20: 499.93 | Z20: 2011.85 | AA20: 465.87 | AB20: 441.24 | AC20: 443.76 | AD20: 500.26 | AE20: 2012.14
A21: Equity in earnings of unconsolidated businesses, net of dividends received | B21: 20 | C21: 9 | D21: 12 | E21: 1 | F21: 42 | G21: 3 | H21: -38 | I21: 8.07 | J21: 3.61 | K21: -29.16 | L21: 3.92 | M21: -13.39 | N21: 8.06 | O21: 3.58 | P21: 2.17 | Q21: 3.87 | R21: -12.16 | S21: 7.87 | T21: 3.78 | U21: 6.13 | V21: 2.67 | W21: -24 | X21: 9.33 | Y21: 2.67 | Z21: -2 | AA21: 2.67 | AB21: -24 | AC21: 9.33 | AD21: 2.67 | AE21: -2
A22: Changes in current assets and liabilities, net of effects from acquisition/disposition of businesses | B22: -2618 | C22: -700 | D22: -736 | E22: 1734 | F22: -2320 | G22: -3082 | H22: -336 | I22: -776.04 | J22: 433.06 | K22: -3638.96 | L22: -1681.47 | M22: -1052.33 | N22: -201.78 | O22: 406.3 | P22: -2866.3 | Q22: -1548.28 | R22: -1373.8 | S22: 198.88 | T22: 648.29 | U22: -2427.72 | V22: -1443.31 | W22: -1589.2 | X22: 240.34 | Y22: 194.93 | Z22: -2517.18 | AA22: -1467.55 | AB22: -1598.96 | AC22: 242.38 | AD22: 148.62 | AE22: -2343.15
A23: Total other operating cash flow | B23: -42 | C23: -789 | D23: 11 | E23: -1436 | F23: -2256 | G23: -142 | H23: 508 | I23: -284.89 | J23: -987.04 | K23: -516.15 | L23: -236.39 | M23: -237.82 | N23: -341.36 | O23: -914.4 | P23: -1029.26 | Q23: -215.43 | R23: -554.2 | S23: -491.68 | T23: -1198.29 | U23: -1264.38 | V23: -427.13 | W23: -555.98 | X23: -560.25 | Y23: -783.38 | Z23: -775.63 | AA23: -317.78 | AB23: -430.89 | AC23: -454.53 | AD23: -706.94 | AE23: -661.63
A24: Net cash provided by/(used in) operating activities | B24: 7782 | C24: 8975 | D24: 11266 | E24: 9114 | F24: 37137 | G24: 7984 | H24: 10435 | I24: 10195.14 | J24: 9843.96 | K24: 38344.56 | L24: 9271.15 | M24: 9801.61 | N24: 10843.04 | O24: 10373.83 | P24: 40128.93 | Q24: 9453.19 | R24: 9614.53 | S24: 11381.22 | T24: 10664.98 | U24: 41155.82 | V24: 9918.03 | W24: 9710.06 | X24: 11694.01 | Y24: 10997.31 | Z24: 42390.26 | AA24: 9997.28 | AB24: 9799.76 | AC24: 11798.99 | AD24: 11038.02 | AE24: 42950.9
A25: Capital expenditures (including capitalized software) | B25: 4145 | C25: 3808 | D25: 4310 | E25: 4748 | F25: 17011 | G25: 4201 | H25: 4009 | I25: 4008.73 | J25: 4142.97 | K25: 16344.13 | L25: 4160.61 | M25: 4114.25 | N25: 4086.13 | O25: 4258.26 | P25: 16665.32 | Q25: 4287.07 | R25: 4168.59 | S25: 4166.07 | T25: 4256.04 | U25: 16949.72 | V25: 4309.76 | W25: 4177.1 | X25: 4153.67 | Y25: 4233.86 | Z25: 17063.41 | AA25: 4316.82 | AB25: 4186.32 | AC25: 4159.72 | AD25: 4239.67 | AE25: 17179.16
A26: Net (acquisitions)/disposals | B26: -122 | C26: -112 | D26: -106 | E26: -110 | F26: -450 | G26: -9563 | H26: -1072 | I26: -2306.69 | J26: -103.6 | K26: -13796.1 | L26: -229.25 | M26: -94 | N26: -6318 | O26: -87.33 | P26: -4508.5 | Q26: -84 | R26: -125 | S26: -5083.33 | T26: -1116.67 | U26: -5268.53 | V26: -150 | W26: -150 | X26: -2575 | Y26: -150 | Z26: -2766.8 | AA26: -150 | AB26: -150 | AC26: -150 | AD26: -2675 | AE26: -2825.36
A27: Other investing cash flow | B27: 515 | C27: 482 | D27: -74 | E27: -122 | F27: 801 | G27: 191 | H27: 154 | I27: -103.18 | J27: -100.09 | K27: 266.82 | L27: -106.22 | M27: -53.84 | N27: -105.36 | O27: -103.87 | P27: -321.84 | Q27: -112.63 | R27: -112.12 | S27: -111.68 | T27: -110.28 | U27: -417.37 | V27: -125.49 | W27: -124.48 | X27: -123.62 | Y27: -120.92 | Z27: -396.34 | AA27: -125.78 | AB27: -124.73 | AC27: -123.88 | AD27: -121.33 | AE27: -363.81
... A39: Free cash flow per share($) | B39: 0.86 | C39: 1.22 | D39: 1.64 | E39: 1.03 | F39: 4.76 | G39: 0.9 | H39: 1.54 | I39: 1.45 | J39: 1.4 | K39: 5.25 | L39: 1.21 | M39: 1.41 | N39: 1.67 | O39: 1.53 | P39: 5.75 | Q39: 1.31 | R39: 1.4 | S39: 1.88 | T39: 1.69 | U39: 6.29 | V39: 1.48 | W39: 1.49 | X39: 2.05 | Y39: 1.87 | Z39: 6.82 | AA39: 1.58 | AB39: 1.58 | AC39: 2.17 | AD39: 1.97 | AE39: 7.28

Sheet Balance sheet
A2: Verizon Communications Inc. | Balance sheet
A3: NYSE:VZ (MI KEY: 4057229; SPCIQ KEY: 415798)
A5: Visible Alpha
A7: Period Type : Fiscal Quarter, Fiscal Halves, Fiscal Year
A8: Period Start : 2025
A9: Period End : 2030
A10: Currency : Reported
A11: Consensus View : Mean
A12: As Of: 10/25/2026
A14: All numbers in $M unless otherwise indicated | B14: FQ1 2025A | C14: FQ2 2025A | D14: FQ3 2025A | E14: FQ4 2025A | F14: FY2025A | G14: FQ1 2026A | H14: FQ2 2026A | I14: FQ3 2026E | J14: FQ4 2026E | K14: FY2026E | L14: FQ1 2027E | M14: FQ2 2027E | N14: FQ3 2027E | O14: FQ4 2027E | P14: FY2027E | Q14: FQ1 2028E | R14: FQ2 2028E | S14: FQ3 2028E | T14: FQ4 2028E | U14: FY2028E | V14: FQ1 2029E | W14: FQ2 2029E | X14: FQ3 2029E | Y14: FQ4 2029E | Z14: FY2029E | AA14: FQ1 2030E | AB14: FQ2 2030E | AC14: FQ3 2030E | AD14: FQ4 2030E | AE14: FY2030E
A15: Number of Contributors Available | B15: 19 | C15: 19 | D15: 19 | E15: 19 | F15: 20 | G15: 20 | H15: 20 | I15: 20 of 20 | J15: 20 of 20 | K15: 20 of 20 | L15: 13 of 20 | M15: 13 of 20 | N15: 12 of 20 | O15: 12 of 20 | P15: 20 of 20 | Q15: 7 of 20 | R15: 7 of 20 | S15: 7 of 20 | T15: 7 of 20 | U15: 18 of 20 | V15: 5 of 20 | W15: 5 of 20 | X15: 5 of 20 | Y15: 5 of 20 | Z15: 14 of 20 | AA15: 5 of 20 | AB15: 5 of 20 | AC15: 5 of 20 | AD15: 5 of 20 | AE15: 14 of 20
A16: Cash and short-term investments | B16: 2257 | C16: 3435 | D16: 7706 | E16: 19048 | F16: 19048 | G16: 8366 | H16: 1752 | I16: 3509.75 | J16: 4829.82 | K16: 5010.65 | L16: 4019.84 | M16: 4027.01 | N16: 3382.77 | O16: 4141.25 | P16: 5279.76 | Q16: 2564.68 | R16: 2861.5 | S16: 2466.91 | T16: 2293.35 | U16: 6842.32 | V16: 2605.05 | W16: 2944.21 | X16: 5147.27 | Y16: 5075.03 | Z16: 12574.3 | AA16: 4439.21 | AB16: 5089.11 | AC16: 7434.46 | AD16: 7375.6 | AE16: 17359.43
A17: Accounts receivable, net of allowances | B17: 25889 | C17: 26275 | D17: 25920 | E17: 27097 | F17: 27097 | G17: 26655 | H17: 26486 | I17: 26976.88 | J17: 28099.76 | K17: 28041.15 | L17: 27288.15 | M17: 27146.94 | N17: 27229.65 | O17: 28664.42 | P17: 28731.44 | Q17: 28068.74 | R17: 28278.55 | S17: 27844.82 | T17: 29234.44 | U17: 29228.04 | V17: 28771.04 | W17: 28749.16 | X17: 28378.19 | Y17: 29838.6 | Z17: 29861.9 | AA17: 29033.1 | AB17: 28932.01 | AC17: 28549.54 | AD17: 30235.33 | AE17: 30247.71
A18: Inventories | B18: 2197 | C18: 2137 | D18: 2700 | E18: 2441 | F18: 2441 | G18: 2320 | H18: 2036 | I18: 2187.13 | J18: 2378.04 | K18: 2385.59 | L18: 2172.48 | M18: 2118.89 | N18: 2269.75 | O18: 2326.08 | P18: 2347.74 | Q18: 2038.31 | R18: 2059.24 | S18: 2083.67 | T18: 2224.92 | U18: 2348.75 | V18: 2036.23 | W18: 2003.99 | X18: 2012.72 | Y18: 2141.97 | Z18: 2359.38 | AA18: 2128.5 | AB18: 2094.09 | AC18: 2095.27 | AD18: 2241.28 | AE18: 2392.72
A19: Prepaid expenses and other current assets | B19: 7010 | C19: 6999 | D19: 7684 | E19: 8336 | F19: 8336 | G19: 7382 | H19: 7297 | I19: 7655.39 | J19: 8016.61 | K19: 8051.03 | L19: 8230.66 | M19: 8396.94 | N19: 8687.86 | O19: 9041.24 | P19: 8892.43 | Q19: 9128.67 | R19: 9316.49 | S19: 9475.03 | T19: 9869.24 | U19: 9363.19 | V19: 10584.86 | W19: 10829.66 | X19: 11040.57 | Y19: 11479.53 | Z19: 10304.15 | AA19: 10937.53 | AB19: 11106.71 | AC19: 11255.14 | AD19: 11764.67 | AE19: 10833.38
A20: Total current assets | B20: 37353 | C20: 38846 | D20: 44010 | E20: 56922 | F20: 56922 | G20: 44723 | H20: 37571 | I20: 40778.74 | J20: 43742.94 | K20: 43879.85 | L20: 41293.94 | M20: 40550.04 | N20: 40941.99 | O20: 43312.23 | P20: 45440.64 | Q20: 40965.78 | R20: 40969.58 | S20: 40695 | T20: 41801.81 | U20: 48247.41 | V20: 41108.06 | W20: 40893.78 | X20: 42937.98 | Y20: 43956.09 | Z20: 55007.19 | AA20: 42794.83 | AB20: 42850.29 | AC20: 44793.32 | AD20: 46211.93 | AE20: 59129.12
A21: Plant, property and equipment, gross | B21: 331888 | C21: 332529 | D21: 334765 | E21: 337991 | F21: 337991 | G21: 357650 | H21: 357086 | I21: 360802.25 | J21: 364017.27 | K21: 363758.22 | L21: 367574.51 | M21: 370539.54 | N21: 374169.93 | O21: 377343.86 | P21: 378519.22 | Q21: 382168.14 | R21: 385733 | S21: 389283.65 | T21: 392895.77 | U21: 394884.55 | V21: 393589.56 | W21: 396914.3 | X21: 400163.54 | Y21: 403403.99 | Z21: 409726.21 | AA21: 406990.09 | AB21: 410336.52 | AC21: 413605.65 | AD21: 416862.69 | AE21: 425470.25
A22: Accumulated depreciation | B22: 223965 | C22: 224460 | D22: 226298 | E22: 228524 | F22: 228524 | G22: 231678 | H22: 231589 | I22: 232545.54 | J22: 235738.67 | K22: 236658.09 | L22: 235945.26 | M22: 238652.59 | N22: 241338.09 | O22: 244119.83 | P22: 250503.71 | Q22: 252186.08 | R22: 255235.45 | S22: 258217.25 | T22: 261182.88 | U22: 269732.89 | V22: 274985.98 | W22: 279111.69 | X22: 283131.46 | Y22: 287137.81 | Z22: 291737.81 | AA22: 291300.38 | AB22: 295496.63 | AC22: 299583.97 | AD22: 303655.15 | AE22: 309288.59
A23: Plant, property and equipment, net | B23: 107923 | C23: 108069 | D23: 108467 | E23: 109467 | F23: 109467 | G23: 125972 | H23: 125497 | I23: 125354.72 | J23: 124953.21 | K23: 124498.16 | L23: 127187.82 | M23: 126912.38 | N23: 126973.46 | O23: 126798.17 | P23: 123740.31 | Q23: 124995.8 | R23: 124915.49 | S23: 124870.83 | T23: 124945.68 | U23: 120673.66 | V23: 117760.41 | W23: 116996.62 | X23: 116258.33 | Y23: 115632.04 | Z23: 115981.85 | AA23: 115653.75 | AB23: 114930.25 | AC23: 114231.88 | AD23: 113628.47 | AE23: 114448.48
A24: Investments in unconsolidated businesses | B24: 820 | C24: 807 | D24: 799 | E24: 785 | F24: 785 | G24: 730 | H24: 783 | I24: 779.67 | J24: 780.79 | K24: 781.05 | L24: 777.2 | M24: 781.59 | N24: 781.33 | O24: 781.79 | P24: 825.25 | Q24: 781.99 | R24: 789.85 | S24: 789.24 | T24: 790.05 | U24: 837.19 | V24: 793.25 | W24: 804.25 | X24: 802.75 | Y24: 803.5 | Z24: 851.81 | AA24: 800.4 | AB24: 809.2 | AC24: 808 | AD24: 808.6 | AE24: 852.1
A25: Operating lease assets | B25: 24175 | C25: 23949 | D25: 23760 | E25: 23498 | F25: 23498 | G25: 23401 | H25: 23158 | I25: 23133.01 | J25: 23226.83 | K25: 23302.38 | L25: 23104.87 | M25: 23104.42 | N25: 23148.93 | O25: 23257.27 | P25: 23405.19 | Q25: 23073.01 | R25: 23096.19 | S25: 23166.91 | T25: 23360.03 | U25: 23631.6 | V25: 23158 | W25: 23158 | X25: 23158 | Y25: 23158 | Z25: 23741.33 | AA25: 23158 | AB25: 23158 | AC25: 23158 | AD25: 23158 | AE25: 23756.72
A26: Other noncurrent assets | B26: 19678 | C26: 21318 | D26: 21012 | E26: 23248 | F26: 23248 | G26: 22547 | H26: 22037 | I26: 22402.22 | J26: 23555.11 | K26: 23594.14 | L26: 24556.73 | M26: 25387.62 | N26: 26098.37 | O26: 27073.47 | P26: 25825.21 | Q26: 21064.66 | R26: 21264.71 | S26: 21090.18 | T26: 21058.18 | U26: 21976.05 | V26: 19308.33 | W26: 19067.67 | X26: 18810.33 | Y26: 18556.67 | Z26: 21247.98 | AA26: 18160.22 | AB26: 17755.33 | AC26: 17357.72 | AD26: 17022.91 | AE26: 20770.94
A27: Total other noncurrent & operating lease assets | B27: 43853 | C27: 45267 | D27: 44772 | E27: 46746 | F27: 46746 | G27: 45948 | H27: 45195 | I27: 45597.43 | J27: 46642.98 | K27: 46728.63 | L27: 47269.47 | M27: 47910.67 | N27: 48601.29 | O27: 49830.44 | P27: 48400.85 | Q27: 44349.14 | R27: 44527.72 | S27: 44444.67 | T27: 44573.57 | U27: 45615.22 | V27: 43148.5 | W27: 42968 | X27: 42775 | Y27: 42584.75 | Z27: 45164.79 | AA27: 43341.82 | AB27: 42960.89 | AC27: 42610.44 | AD27: 43218.41 | AE27: 45224.82
... A57: Total liabilities and equity | B57: 380364 | C57: 383285 | D57: 388331 | E57: 404258 | F57: 404258 | G57: 417882 | H57: 410186 | I57: 414605.86 | J57: 417934.21 | K57: 417797.9 | L57: 417215.14 | M57: 416725.5 | N57: 420467.09 | O57: 423703.46 | P57: 421899.14 | Q57: 416118.06 | R57: 416095.77 | S57: 418104.25 | T57: 419808.35 | U57: 423040.43 | V57: 413223.35 | W57: 411909.59 | X57: 414104.81 | Y57: 414140.94 | Z57: 426208.25 | AA57: 412013 | AB57: 410887.47 | AC57: 411695.12 | AD57: 414073.54 | AE57: 429077.1
A59: Debt
A60: Supp - Total debt | B60: 143649 | C60: 145996 | D60: 146775 | E60: 158150 | F60: 158150 | G60: 172460 | H60: 165231 | I60: 164750.26 | J60: 163782.45 | K60: 163177.75 | L60: 163217.51 | M60: 162244.63 | N60: 162533.51 | O60: 162101.68 | P60: 161831.54 | Q60: 162273.96 | R60: 162542 | S60: 163434.4 | T60: 163369.22 | U60: 163045.41 | V60: 165683.02 | W60: 166045.41 | X60: 167153.84 | Y60: 166472.04 | Z60: 162928.97 | AA60: 166871.24 | AB60: 167457.44 | AC60: 167821.14 | AD60: 167895.54 | AE60: 161675.7
A61: Cash and short-term investments | B61: 2257 | C61: 3435 | D61: 7706 | E61: 19048 | F61: 19048 | G61: 8366 | H61: 1752 | I61: 3509.75 | J61: 4829.82 | K61: 5010.65 | L61: 4019.84 | M61: 4027.01 | N61: 3382.77 | O61: 4141.25 | P61: 5279.76 | Q61: 2564.68 | R61: 2861.5 | S61: 2466.91 | T61: 2293.35 | U61: 6842.32 | V61: 2605.05 | W61: 2944.21 | X61: 5147.27 | Y61: 5075.03 | Z61: 12574.3 | AA61: 4439.21 | AB61: 5089.11 | AC61: 7434.46 | AD61: 7375.6 | AE61: 17359.43
A62: Net Debt | B62: 141392 | C62: 142561 | D62: 139069 | E62: 139102 | F62: 139102 | G62: 164094 | H62: 163479 | I62: 160826.46 | J62: 158683.04 | K62: 157729.36 | L62: 159439.78 | M62: 159138.49 | N62: 160171.95 | O62: 159218.84 | P62: 156658.72 | Q62: 161219.84 | R62: 161906.06 | S62: 163036.9 | T62: 163740.84 | U62: 157222.01 | V62: 167716.75 | W62: 168650.19 | X62: 168078.66 | Y62: 168236.93 | Z62: 153278.47 | AA62: 166175.54 | AB62: 166739.95 | AC62: 164927.78 | AD62: 165924.89 | AE62: 148622.61
A63: Secured Debt | B63: 26336 | C63: 26600 | D63: 27061 | E63: 27067 | F63: 27067 | G63: 29962 | H63: 28760 | I63: 28950.25 | J63: 28950.25 | K63: 28627.73 | L63: 30932 | M63: 30932 | N63: 30932 | O63: 30932 | P63: 28682.41 | Q63: 34797 | R63: 34797 | S63: 34797 | T63: 34797 | U63: 29155.29 | V63: 34797 | W63: 34797 | X63: 34797 | Y63: 34797 | Z63: 29225.01 | AA63: 34797 | AB63: 34797 | AC63: 34797 | AD63: 34797 | AE63: 29295.42
A64: Net unsecured debt | B64: 115056 | C64: 115961 | D64: 112008 | E64: 110053 | F64: 110053 | G64: 130053 | H64: 128682 | I64: 133760.41 | J64: 131681.55 | K64: 129082.37 | L64: 129995.91 | M64: 131436.48 | N64: 129333.31 | O64: 128451.61 | P64: 128754.19 | Q64: 127057.54 | R64: 129572.88 | S64: 127806.04 | T64: 129523.17 | U64: 129754.71 | V64: 133312.47 | W64: 136716.76 | X64: 134543.82 | Y64: 138369.14 | Z64: 128751.22 | AA64: 139406.35 | AB64: 143710.01 | AC64: 142212.05 | AD64: 146590.16 | AE64: 127232.17

Sheet Income statement
A2: Verizon Communications Inc. | Income statement
A3: NYSE:VZ (MI KEY: 4057229; SPCIQ KEY: 415798)
A5: Visible Alpha
A7: Period Type : Fiscal Quarter, Fiscal Halves, Fiscal Year
A8: Period Start : 2025
A9: Period End : 2030
A10: Currency : Reported
A11: Consensus View : Mean
A12: As Of: 10/25/2026
A14: All numbers in $M unless otherwise indicated | B14: FQ1 2025A | C14: FQ2 2025A | D14: FQ3 2025A | E14: FQ4 2025A | F14: FY2025A | G14: FQ1 2026A | H14: FQ2 2026A | I14: FQ3 2026E | J14: FQ4 2026E | K14: FY2026E | L14: FQ1 2027E | M14: FQ2 2027E | N14: FQ3 2027E | O14: FQ4 2027E | P14: FY2027E | Q14: FQ1 2028E | R14: FQ2 2028E | S14: FQ3 2028E | T14: FQ4 2028E | U14: FY2028E | V14: FQ1 2029E | W14: FQ2 2029E | X14: FQ3 2029E | Y14: FQ4 2029E | Z14: FY2029E | AA14: FQ1 2030E | AB14: FQ2 2030E | AC14: FQ3 2030E | AD14: FQ4 2030E | AE14: FY2030E
A15: Number of Contributors Available | B15: 19 | C15: 19 | D15: 19 | E15: 19 | F15: 20 | G15: 20 | H15: 20 | I15: 20 of 20 | J15: 20 of 20 | K15: 20 of 20 | L15: 13 of 20 | M15: 13 of 20 | N15: 12 of 20 | O15: 12 of 20 | P15: 20 of 20 | Q15: 7 of 20 | R15: 7 of 20 | S15: 7 of 20 | T15: 7 of 20 | U15: 18 of 20 | V15: 5 of 20 | W15: 5 of 20 | X15: 5 of 20 | Y15: 5 of 20 | Z15: 14 of 20 | AA15: 5 of 20 | AB15: 5 of 20 | AC15: 5 of 20 | AD15: 5 of 20 | AE15: 14 of 20
A16: Service revenues and other | B16: 28087 | C16: 28249 | D16: 28202 | E16: 28183 | F16: 112721 | G16: 28759 | H16: 29229 | I16: 29275.35 | J16: 29485.76 | K16: 116755.23 | L16: 29425.41 | M16: 29620.34 | N16: 29606.36 | O16: 29869.15 | P16: 118456.24 | Q16: 29655.14 | R16: 29850.03 | S16: 29784 | T16: 30023.76 | U16: 119410.82 | V16: 29901.34 | W16: 30092.34 | X16: 29917.36 | Y16: 30158.97 | Z16: 120899.01 | AA16: 30090.4 | AB16: 30284.4 | AC16: 30083.58 | AD16: 30318.98 | AE16: 121698.25
A17: Wireless equipment revenues | B17: 5398 | C17: 6255 | D17: 5619 | E17: 8198 | F17: 25470 | G17: 5681 | H17: 5024 | I17: 5444.78 | J17: 7798.8 | K17: 23942.47 | L17: 5909.46 | M17: 5441.35 | N17: 5551.61 | O17: 7926.31 | P17: 24821.18 | Q17: 6063.63 | R17: 5735.04 | S17: 5643.93 | T17: 8158.98 | U17: 25342.68 | V17: 6123.01 | W17: 5460.13 | X17: 5526.68 | Y17: 7893.21 | Z17: 25100.87 | AA17: 6212.16 | AB17: 5537.56 | AC17: 5603.24 | AD17: 8006.64 | AE17: 25426.3
A18: Operating revenues | B18: 33485 | C18: 34504 | D18: 33821 | E18: 36381 | F18: 138191 | G18: 34440 | H18: 34253 | I18: 34767.99 | J18: 37338.71 | K18: 140869.69 | L18: 35282.92 | M18: 35119.78 | N18: 35157.97 | O18: 37795.46 | P18: 143512.71 | Q18: 35718.77 | R18: 35585.08 | S18: 35427.93 | T18: 38182.74 | U18: 145247.85 | V18: 36024.35 | W18: 35552.48 | X18: 35444.04 | Y18: 38052.19 | Z18: 146846.84 | AA18: 36302.56 | AB18: 35821.97 | AC18: 35686.82 | AD18: 38325.61 | AE18: 148307.92
A19: Cost of services | B19: 6950 | C19: 6878 | D19: 6863 | E19: 7098 | F19: 27789 | G19: 7167 | H19: 7225 | I19: 7159.92 | J19: 7235.2 | K19: 28770.42 | L19: 7272.3 | M19: 7222.54 | N19: 7148.92 | O19: 7273.7 | P19: 28909 | Q19: 7282.86 | R19: 7231.33 | S19: 7114.56 | T19: 7247.3 | U19: 29032.54 | V19: 7350.49 | W19: 7303.06 | X19: 7124.68 | Y19: 7258.22 | Z19: 29295.24 | AA19: 7369.69 | AB19: 7326.85 | AC19: 7136.53 | AD19: 7268.69 | AE19: 29400.68
A20: Cost of wireless equipment | B20: 6106 | C20: 7007 | D20: 6483 | E20: 9380 | F20: 28976 | G20: 6506 | H20: 5859 | I20: 6300.47 | J20: 8928.79 | K20: 27592.79 | L20: 6758.1 | M20: 6263.52 | N20: 6438.11 | O20: 9168.88 | P20: 28649.58 | Q20: 6920.3 | R20: 6568.38 | S20: 6443.63 | T20: 9295.96 | U20: 29028.6 | V20: 6961.02 | W20: 6266.3 | X20: 6298.82 | Y20: 8927.48 | Z20: 28912.26 | AA20: 7051.53 | AB20: 6345.12 | AC20: 6376.91 | AD20: 9044.97 | AE20: 29319.41
A21: Cost of services and sales -Operating | B21: 13056 | C21: 13885 | D21: 13346 | E21: 16478 | F21: 56765 | G21: 13673 | H21: 13084 | I21: 13451.92 | J21: 16149.04 | K21: 56340.79 | L21: 14030.4 | M21: 13486.06 | N21: 13587.03 | O21: 16442.58 | P21: 57482.57 | Q21: 14203.15 | R21: 13799.71 | S21: 13558.19 | T21: 16543.26 | U21: 57977.78 | V21: 14311.51 | W21: 13569.37 | X21: 13423.5 | Y21: 16185.7 | Z21: 58145.06 | AA21: 14421.22 | AB21: 13671.97 | AC21: 13513.44 | AD21: 16313.66 | AE21: 58663.3
A22: Selling, general and admin. exp. - Operating | B22: 7874 | C22: 7812 | D22: 7700 | E22: 8043 | F22: 31429 | G22: 7372 | H22: 7446 | I22: 7586.89 | J22: 8042.84 | K22: 31112.36 | L22: 7429.02 | M22: 7745.23 | N22: 7467.75 | O22: 8422.53 | P22: 30851.31 | Q22: 7377.62 | R22: 7529.5 | S22: 7404.82 | T22: 7822.66 | U22: 30071.08 | V22: 7204.9 | W22: 7400.9 | X22: 7236.81 | Y22: 7720.71 | Z22: 29963.66 | AA22: 7169.04 | AB22: 7364.24 | AC22: 7190.75 | AD22: 7676.01 | AE22: 29947.07
A23: Total adjustment to Selling, general and administrative exp. | B23: 352.54 | C23: 326.53 | D23: 52 | E23: 2337 | F23: 2389 | G23: 261 | H23: 1536 | I23: 261 | J23: 261 | K23: 1579.38 | L23: 261 | M23: 261 | N23: 130.5 | O23: -2969.33 | P23: -2577.83 | Q23: - | R23: - | S23: - | T23: - | U23: - | V23: - | W23: - | X23: - | Y23: - | Z23: - | AA23: - | AB23: - | AC23: - | AD23: - | AE23: -
A24: Selling, general and administrative expense | B24: 7874 | C24: 7812 | D24: 7752 | E24: 10380 | F24: 33818 | G24: 7633 | H24: 8982 | I24: 7611.47 | J24: 8110.16 | K24: 32464.99 | L24: 7433.15 | M24: 7748.86 | N24: 7468.65 | O24: 7911.33 | P24: 30648.2 | Q24: 7386.98 | R24: 7536.38 | S24: 7400.6 | T24: 7839.14 | U24: 30034.78 | V24: 7204.9 | W24: 7400.9 | X24: 7236.81 | Y24: 7720.71 | Z24: 29892.15 | AA24: 7169.04 | AB24: 7364.24 | AC24: 7190.75 | AD24: 7676.01 | AE24: 29888.16
A25: Total operations and support - Operating | B25: 20930 | C25: 21697 | D25: 21046 | E25: 24521 | F25: 88194 | G25: 21045 | H25: 20530 | I25: 21064.64 | J25: 24270.53 | K25: 87629.44 | L25: 21459.42 | M25: 21231.29 | N25: 21054.78 | O25: 24865.11 | P25: 88538.84 | Q25: 21580.78 | R25: 21329.21 | S25: 20963.01 | T25: 24365.92 | U25: 88392.43 | V25: 21516.41 | W25: 20970.26 | X25: 20660.3 | Y25: 23906.41 | Z25: 88614.61 | AA25: 21590.26 | AB25: 21036.21 | AC25: 20704.18 | AD25: 23989.66 | AE25: 89176.95
A26: Depreciation and amortization expense | B26: 4577 | C26: 4635 | D26: 4618 | E26: 4519 | F26: 18349 | G26: 4892 | H26: 5008 | I26: 4975.75 | J26: 5015.47 | K26: 19886.06 | L26: 5020.06 | M26: 5049.13 | N26: 5064.56 | O26: 5070.69 | P26: 19972.73 | Q26: 5075.42 | R26: 5123.95 | S26: 5128.67 | T26: 5079.46 | U26: 20017.81 | V26: 5132.81 | W26: 5167.99 | X26: 5173.01 | Y26: 5139.19 | Z26: 20229.77 | AA26: 5200.65 | AB26: 5235.13 | AC26: 5239.79 | AD26: 5203.89 | AE26: 20394.95
A27: Total operating expenses | B27: 25507 | C27: 26332 | D27: 25716 | E27: 31377 | F27: 108932 | G27: 26198 | H27: 27074 | I27: 25977.67 | J27: 29232.07 | K27: 108555.39 | L27: 26417.49 | M27: 26087.11 | N27: 26047.53 | O27: 29197.18 | P27: 108002.97 | Q27: 26417.22 | R27: 25936.01 | S27: 25841.31 | T27: 28809.23 | U27: 107896.57 | V27: 26565.26 | W27: 26045.69 | X27: 25738.31 | Y27: 28956.07 | Z27: 108065.24 | AA27: 26669.4 | AB27: 26141.07 | AC27: 25811.02 | AD27: 29066.05 | AE27: 108679.72
A28: Total operating expenses -Operating | B28: 25507 | C28: 26332 | D28: 25664 | E28: 29040 | F28: 106543 | G28: 25937 | H28: 25538 | I28: 26004.84 | J28: 29265.43 | K28: 107527.58 | L28: 26393.76 | M28: 26063.38 | N28: 26023.81 | O28: 29737.06 | P28: 108464.66 | Q28: 26417.22 | R28: 25936.01 | S28: 25841.31 | T28: 28809.23 | U28: 108149.87 | V28: 26565.26 | W28: 26045.69 | X28: 25738.31 | Y28: 28956.07 | Z28: 108454.61 | AA28: 26669.4 | AB28: 26141.07 | AC28: 25811.02 | AD28: 29066.05 | AE28: 109101.17
A29: Adjusted EBITDA | B29: 12555 | C29: 12807 | D29: 12775 | E29: 11860 | F29: 49997 | G29: 13395 | H29: 13723 | I29: 13691.51 | J29: 13088.18 | K29: 53752.39 | L29: 13911.4 | M29: 13958.05 | N29: 14127.43 | O29: 13449.57 | P29: 55419.85 | Q29: 14128.63 | R29: 14248.99 | S29: 14469.15 | T29: 13800.33 | U29: 56817.42 | V29: 14507.94 | W29: 14582.21 | X29: 14783.74 | Y29: 14145.78 | Z29: 58232.23 | AA29: 14712.29 | AB29: 14785.76 | AC29: 14982.64 | AD29: 14335.95 | AE29: 59130.97
A30: Operating income/(loss) -Operating | B30: 7978 | C30: 8172 | D30: 8157 | E30: 7341 | F30: 31648 | G30: 8503 | H30: 8715 | I30: 8728.72 | J30: 8080.7 | K30: 34040.45 | L30: 8930.57 | M30: 8931.91 | N30: 9087.29 | O30: 8454.13 | P30: 35508.19 | Q30: 9169.92 | R30: 9219.83 | S30: 9412.6 | T30: 8938.4 | U30: 36934.38 | V30: 9459.09 | W30: 9506.79 | X30: 9705.73 | Y30: 9096.12 | Z30: 38154.03 | AA30: 9633.16 | AB30: 9680.9 | AC30: 9875.8 | AD30: 9259.56 | AE30: 38934.35
A31: Total adjustments in Operating income/(loss) | B31: 63 | C31: 116 | D31: 52 | E31: 2337 | F31: 2389 | G31: 261 | H31: 1536 | I31: 109.86 | J31: 1092.41 | K31: 1808.91 | L31: 39.15 | M31: 768 | N31: 17.89 | O31: 602.95 | P31: 340.92 | Q31: - | R31: - | S31: - | T31: - | U31: -208.78 | V31: - | W31: - | X31: - | Y31: - | Z31: 700 | AA31: - | AB31: - | AC31: - | AD31: - | AE31: 700
A32: Operating income/(loss) | B32: 7978 | C32: 8172 | D32: 8105 | E32: 5004 | F32: 29259 | G32: 8242 | H32: 7179 | I32: 8742.86 | J32: 7984.1 | K32: 32281.17 | L32: 8953.39 | M32: 8843.97 | N32: 9085.66 | O32: 8399.32 | P32: 35454.59 | Q32: 9169.92 | R32: 9219.83 | S32: 9412.6 | T32: 8938.4 | U32: 36860.72 | V32: 9459.09 | W32: 9506.79 | X32: 9705.73 | Y32: 9096.12 | Z32: 37940.08 | AA32: 9633.16 | AB32: 9680.9 | AC32: 9875.8 | AD32: 9259.56 | AE32: 38590.13
A33: Equity in earnings of unconsolidated businesses | B33: 6 | C33: -3 | D33: -6 | E33: 3 | F33: - | G33: 5 | H33: 44 | I33: 11.9 | J33: 14.4 | K33: 60.21 | L33: 3.93 | M33: 18.62 | N33: 1.93 | O33: 3.32 | P33: 47.41 | Q33: 9.66 | R33: 29.2 | S33: 4.16 | T33: 8.77 | U33: 43.63 | V33: 5 | W33: 44 | X33: -6 | Y33: 3 | Z33: 37.88 | AA33: 5 | AB33: 44 | AC33: -6 | AD33: 3 | AE33: 37.71
A34: Other income, net | B34: 121 | C34: 79 | D34: 92 | E34: -185 | F34: 107 | G34: 477 | H34: 36 | I34: 87.55 | J34: 76.83 | K34: 636.77 | L34: 118.1 | M34: 115.14 | N34: 113.48 | O34: 117.73 | P34: 396 | Q34: 55.88 | R34: 53.72 | S34: 53.05 | T34: 55.98 | U34: 230.81 | V34: 27.87 | W34: 27.93 | X34: 29.61 | Y34: 28.98 | Z34: 221.71 | AA34: 31.29 | AB34: 34.41 | AC34: 36.98 | AD34: 41.45 | AE34: 242.19
A35: Other income, net - Operating | B35: -5.45 | C35: -12.34 | D35: -25.51 | E35: 224.64 | F35: 81.77 | G35: 185 | H35: -92.05 | I35: 45.92 | J35: 117.78 | K35: 210.18 | L35: 26.89 | M35: 3.45 | N35: 3.45 | O35: -71.55 | P35: -37.75 | Q35: -81.53 | R35: -95.59 | S35: -95.59 | T35: -95.59 | U35: -368.3 | V35: -106.29 | W35: -101.6 | X35: -101.6 | Y35: -101.6 | Z35: -411.08 | AA35: -107.57 | AB35: -108.44 | AC35: -99.16 | AD35: -77.37 | AE35: -392.55
A36: Interest expense | B36: 1632 | C36: 1639 | D36: 1664 | E36: 1759 | F36: 6694 | G36: 1940 | H36: 1985 | I36: 1939.74 | J36: 1922.08 | K36: 7781.91 | L36: 1940.05 | M36: 1932.61 | N36: 1927.83 | O36: 1941.54 | P36: 7712.69 | Q36: 1949.8 | R36: 1943.92 | S36: 1940.34 | T36: 1952.01 | U36: 7771.81 | V36: 1964.68 | W36: 1953.01 | X36: 1955.46 | Y36: 1952.81 | Z36: 7776.55 | AA36: 1945.7 | AB36: 1938.62 | AC36: 1941.06 | AD36: 1929.86 | AE36: 7722.77
A37: Total non-operating expenses | B37: -1505 | C37: -1563 | D37: -1578 | E37: -1941 | F37: -6587 | G37: -1458 | H37: -1905 | I37: -1852.27 | J37: -1840.68 | K37: -7090.35 | L37: -1846.85 | M37: -1834.82 | N37: -1840.64 | O37: -1851.27 | P37: -7348.7 | Q37: -1922.5 | R37: -1904.68 | S37: -1918.32 | T37: -1927.23 | U37: -7593.91 | V37: -1940.39 | W37: -1913.07 | X37: -1934.17 | Y37: -1928.42 | Z37: -7611.42 | AA37: -1918.67 | AB37: -1893.49 | AC37: -1913.88 | AD37: -1895.5 | AE37: -7588.07
A38: Income before provision for income taxes | B38: 6473 | C38: 6609 | D38: 6527 | E38: 3063 | F38: 22672 | G38: 6784 | H38: 5274 | I38: 6891.42 | J38: 6192.62 | K38: 25208.79 | L38: 7088.49 | M38: 7065.11 | N38: 7283.13 | O38: 6543.72 | P38: 28049.19 | Q38: 7273.58 | R38: 7378.07 | S38: 7586.95 | T38: 6949.44 | U38: 29332.41 | V38: 7518.7 | W38: 7593.72 | X38: 7771.56 | Y38: 7167.7 | Z38: 30374.39 | AA38: 7714.49 | AB38: 7787.41 | AC38: 7961.93 | AD38: 7364.07 | AE38: 31046.61
A39: Income before provision for income taxes - Operating | B39: 6576.02 | C39: 6731.06 | D39: 6692.5 | E39: 6287.33 | F39: 26286.91 | G39: 6933.25 | H39: 6995.99 | I39: 7020.2 | J39: 6335.93 | K39: 27138.05 | L39: 6969.84 | M39: 7761.35 | N39: 7230.87 | O39: 6471.9 | P39: 28569.61 | Q39: 7242.58 | R39: 8056.67 | S39: 7524.89 | T39: 6832.27 | U39: 30402.47 | V39: 7371.47 | W39: 8232.61 | X39: 7693.23 | Y39: 6974.57 | Z39: 31913.75 | AA39: 7674.21 | AB39: 8526.54 | AC39: 8001.25 | AD39: 7296.82 | AE39: 33519.27
A40: Provision for income taxes | B40: 1490 | C40: 1488 | D40: 1471 | E40: 615 | F40: 5064 | G40: 1638 | H40: 1325 | I40: 1567.3 | J40: 1396.84 | K40: 5934.82 | L40: 1645.65 | M40: 1638.91 | N40: 1694.22 | O40: 1522.3 | P40: 6445.71 | Q40: 1687.58 | R40: 1714.69 | S40: 1760.08 | T40: 1609.84 | U40: 6694.68 | V40: 1710.55 | W40: 1730.88 | X40: 1766.22 | Y40: 1628.51 | Z40: 6863.26 | AA40: 1755.1 | AB40: 1774.94 | AC40: 1809.45 | AD40: 1673.04 | AE40: 7020.9
A41: Provision for income taxes - Operating | B41: 1448.61 | C41: 1543.06 | D41: 1457.88 | E41: 1230.44 | F41: 5679.98 | G41: 1470.35 | H41: 1486.34 | I41: 1607.58 | J41: 1416.18 | K41: 5927.68 | L41: 1646.06 | M41: 1833.45 | N41: 1707.7 | O41: 1527.24 | P41: 6597.26 | Q41: 1710.31 | R41: 1903.17 | S41: 1777.01 | T41: 1612.54 | U41: 6993.92 | V41: 1740.02 | W41: 1944.02 | X41: 1816.2 | Y41: 1645.56 | Z41: 7367.59 | AA41: 1811.56 | AB41: 2013.41 | AC41: 1888.89 | AD41: 1721.59 | AE41: 7774.35
A42: Net income attri. to Verizon | B42: 4879 | C42: 5003 | D42: 4950 | E42: 2342 | F42: 17174 | G42: 5045 | H42: 3835 | I42: 5186.64 | J42: 4664.27 | K42: 18784.99 | L42: 5334.85 | M42: 5311.09 | N42: 5477.76 | O42: 4912.63 | P42: 21182.71 | Q42: 5474.03 | R42: 5544.51 | S42: 5712.66 | T42: 5228.03 | U42: 22262.93 | V42: 5690.55 | W42: 5738.16 | X42: 5885.52 | Y42: 5424.31 | Z42: 23235.55 | AA42: 5840.05 | AB42: 5885.81 | AC42: 6030.83 | AD42: 5574.49 | AE42: 23891.15
A43: Total post tax adjustments | B43: 142 | C43: 143 | D43: 193 | E43: 2262 | F43: 2740 | G43: 331 | H43: 1591 | I43: 181.14 | J43: 315.45 | K43: 2139.82 | L43: 121.48 | M43: 228.58 | N43: 113.09 | O43: 187.32 | P43: 483.75 | Q43: 123.31 | R43: 133.43 | S43: 114.37 | T43: 108.02 | U43: 372.73 | V43: 126.73 | W43: 135.52 | X43: 118.87 | Y43: 115.35 | Z43: 384.52 | AA43: 119.24 | AB43: 128.81 | AC43: 110.6 | AD43: 110.42 | AE43: 353.74
A44: Net income attri. to Verizon - Operating | B44: 5021 | C44: 5146 | D44: 5143 | E44: 4604 | F44: 19914 | G44: 5376 | H44: 5426 | I44: 5316.48 | J44: 4851.76 | K44: 20971.14 | L44: 5414.05 | M44: 5452.76 | N44: 5552.06 | O44: 5030.23 | P44: 21553.11 | Q44: 5544.5 | R44: 5620.75 | S44: 5778.02 | T44: 5289.75 | U44: 22521.06 | V44: 5791.93 | W44: 5846.58 | X44: 5980.61 | Y44: 5516.59 | Z44: 23562.73 | AA44: 5935.44 | AB44: 5988.86 | AC44: 6119.31 | AD44: 5662.83 | AE44: 24193.28
A46: Net income attri. to Verizon | B46: 4879 | C46: 5003 | D46: 4950 | E46: 2342 | F46: 17174 | G46: 5045 | H46: 3835 | I46: 5186.64 | J46: 4664.27 | K46: 18784.99 | L46: 5334.85 | M46: 5311.09 | N46: 5477.76 | O46: 4912.63 | P46: 21182.71 | Q46: 5474.03 | R46: 5544.51 | S46: 5712.66 | T46: 5228.03 | U46: 22262.93 | V46: 5690.55 | W46: 5738.16 | X46: 5885.52 | Y46: 5424.31 | Z46: 23235.55 | AA46: 5840.05 | AB46: 5885.81 | AC46: 6030.83 | AD46: 5574.49 | AE46: 23891.15
... A55: Dividends declared per common share($) | B55: 0.68 | C55: 0.68 | D55: 0.69 | E55: 0.69 | F55: 2.73 | G55: 0.71 | H55: 0.71 | I55: 0.71 | J55: 0.71 | K55: 2.82 | L55: 0.72 | M55: 0.72 | N55: 0.72 | O55: 0.72 | P55: 2.88 | Q55: 0.73 | R55: 0.74 | S55: 0.74 | T55: 0.74 | U55: 2.93 | V55: 0.75 | W55: 0.75 | X55: 0.76 | Y55: 0.76 | Z55: 2.98 | AA55: 0.77 | AB55: 0.77 | AC55: 0.77 | AD55: 0.77 | AE55: 3.04

Sheet Segment
A2: Verizon Communications Inc. | Segment
A3: NYSE:VZ (MI KEY: 4057229; SPCIQ KEY: 415798)
A5: Visible Alpha
A7: Period Type : Fiscal Quarter, Fiscal Halves, Fiscal Year
A8: Period Start : 2025
A9: Period End : 2030
A10: Currency : Reported
A11: Consensus View : Mean
A12: As Of: 10/25/2026
A14: All numbers in $M unless otherwise indicated | B14: FQ1 2025A | C14: FQ2 2025A | D14: FQ3 2025A | E14: FQ4 2025A | F14: FY2025A | G14: FQ1 2026A | H14: FQ2 2026A | I14: FQ3 2026E | J14: FQ4 2026E | K14: FY2026E | L14: FQ1 2027E | M14: FQ2 2027E | N14: FQ3 2027E | O14: FQ4 2027E | P14: FY2027E | Q14: FQ1 2028E | R14: FQ2 2028E | S14: FQ3 2028E | T14: FQ4 2028E | U14: FY2028E | V14: FQ1 2029E | W14: FQ2 2029E | X14: FQ3 2029E | Y14: FQ4 2029E | Z14: FY2029E | AA14: FQ1 2030E | AB14: FQ2 2030E | AC14: FQ3 2030E | AD14: FQ4 2030E | AE14: FY2030E
A15: Number of Contributors Available | B15: 19 | C15: 19 | D15: 19 | E15: 19 | F15: 20 | G15: 20 | H15: 20 | I15: 20 of 20 | J15: 20 of 20 | K15: 20 of 20 | L15: 13 of 20 | M15: 13 of 20 | N15: 12 of 20 | O15: 12 of 20 | P15: 20 of 20 | Q15: 7 of 20 | R15: 7 of 20 | S15: 7 of 20 | T15: 7 of 20 | U15: 18 of 20 | V15: 5 of 20 | W15: 5 of 20 | X15: 5 of 20 | Y15: 5 of 20 | Z15: 14 of 20 | AA15: 5 of 20 | AB15: 5 of 20 | AC15: 5 of 20 | AD15: 5 of 20 | AE15: 14 of 20
A16: Total Revenue
A17: Mobility and broadband service - Consumer revenue | B17: 18801 | C17: 19002 | D17: 19096 | E17: 19024 | F17: 75923 | G17: 19180 | H17: 19637 | I17: 19772.17 | J17: 19892.47 | K17: 78481.64 | L17: 19811.36 | M17: 20060.92 | N17: 20205.41 | O17: 20384.12 | P17: 80428.37 | Q17: 20314.57 | R17: 20384.6 | S17: 20600.29 | T17: 20782.71 | U17: 82264.66 | V17: 20736.49 | W17: 20805.2 | X17: 21021.81 | Y17: 21198.39 | Z17: 84629.72 | AA17: 21128.11 | AB17: 21193.1 | AC17: 21410.57 | AD17: 21582.48 | AE17: 86156.61
A18: Wireless equipment - Consumer revenue | B18: 4532 | C18: 5369 | D18: 4766 | E18: 7112 | F18: 21779 | G18: 4824 | H18: 4178 | I18: 4702.67 | J18: 6850.42 | K18: 20555.08 | L18: 5022.61 | M18: 4478.76 | N18: 4764.71 | O18: 6950.22 | P18: 21192.17 | Q18: 5200.2 | R18: 4637.88 | S18: 4750.49 | T18: 6943.42 | U18: 21558.91 | V18: 5275.6 | W18: 4711.31 | X18: 4826.76 | Y18: 7051.47 | Z18: 21905.92 | AA18: 5365.12 | AB18: 4791.66 | AC18: 4907.12 | AD18: 7169.39 | AE18: 22317.36
A19: Other - Consumer revenue | B19: 2285 | C19: 2277 | D19: 2243 | E19: 2300 | F19: 9105 | G19: 2449 | H19: 2427 | I19: 2367.38 | J19: 2423.71 | K19: 9667.09 | L19: 2396.45 | M19: 2509.83 | N19: 2350.69 | O19: 2428.81 | P19: 9626.98 | Q19: 2356.92 | R19: 2327.01 | S19: 2276.2 | T19: 2311.13 | U19: 9531.25 | V19: 2300.54 | W19: 2277.57 | X19: 2226.4 | Y19: 2263.09 | Z19: 9472.41 | AA19: 2245.59 | AB19: 2227.58 | AC19: 2177.78 | AD19: 2217.77 | AE19: 9435.79
A20: Consumer revenue | B20: 25618 | C20: 26648 | D20: 26105 | E20: 28436 | F20: 106807 | G20: 26453 | H20: 26242 | I20: 26901.66 | J20: 29297.33 | K20: 109199.99 | L20: 27260.45 | M20: 27452.45 | N20: 27365.61 | O20: 29899.88 | P20: 111777.76 | Q20: 27859.95 | R20: 28078.08 | S20: 27814.54 | T20: 30452.56 | U20: 113914.48 | V20: 28134.02 | W20: 27892.22 | X20: 27893.33 | Y20: 30291.06 | Z20: 115768.21 | AA20: 28473.62 | AB20: 28254.1 | AC20: 28220.46 | AD20: 30652.32 | AE20: 117513.61
A21: Mobility and broadband service - Business revenue | B21: 3717 | C21: 3733 | D21: 3743 | E21: 3747 | F21: 14940 | G21: 3688 | H21: 3728 | I21: 3774.46 | J21: 3770.83 | K21: 14961.29 | L21: 3733.38 | M21: 3724.54 | N21: 3786.06 | O21: 3825.12 | P21: 15118.9 | Q21: 3774.25 | R21: 3695.16 | S21: 3744.27 | T21: 3801.58 | U21: 15271.95 | V21: 3817.21 | W21: 3716.71 | X21: 3763.66 | Y21: 3826.73 | Z21: 15478.85 | AA21: 3855.36 | AB21: 3735.67 | AC21: 3781.37 | AD21: 3850.15 | AE21: 15658.96
A22: Wireless equipment - Business revenue | B22: 866 | C22: 886 | D22: 853 | E22: 1087 | F22: 3692 | G22: 857 | H22: 846 | I22: 857.09 | J22: 1129.68 | K22: 3689.77 | L22: 906.08 | M22: 862.47 | N22: 864.69 | O22: 1141.51 | P22: 3806.25 | Q22: 947.72 | R22: 903.37 | S22: 886.29 | T22: 1174.39 | U22: 3976.44 | V22: 963.62 | W22: 918.62 | X22: 902.29 | Y22: 1194.92 | Z22: 3983.11 | AA22: 982.32 | AB22: 935.47 | AC22: 919.26 | AD22: 1217.35 | AE22: 4049.76
A23: Other - Business revenue | B23: 2419 | C23: 2354 | D23: 2247 | E23: 2243 | F23: 9263 | G23: 2585 | H23: 2581 | I23: 2616.77 | J23: 2595.61 | K23: 10475.49 | L23: 2662.78 | M23: 2633.98 | N23: 2521.53 | O23: 2536.6 | P23: 10369.27 | Q23: 2505.48 | R23: 2487.61 | S23: 2396.96 | T23: 2412.27 | U23: 9974.55 | V23: 2387.32 | W23: 2357.29 | X23: 2272.11 | Y23: 2285.25 | Z23: 9543.19 | AA23: 2283.26 | AB23: 2241.95 | AC23: 2161.63 | AD23: 2172.83 | AE23: 9234.42
A24: Business revenue | B24: 7002 | C24: 6973 | D24: 6843 | E24: 7077 | F24: 29069 | G24: 7130 | H24: 7155 | I24: 7259.08 | J24: 7509.81 | K24: 29256.56 | L24: 7337.87 | M24: 7238.86 | N24: 7168.08 | O24: 7482.67 | P24: 29322.39 | Q24: 7289.21 | R24: 7154.03 | S24: 7057.54 | T24: 7393.92 | U24: 29344.89 | V24: 7152.35 | W24: 6909.13 | X24: 6849.87 | Y24: 7184.08 | Z24: 29078.38 | AA24: 7042.65 | AB24: 6776.71 | AC24: 6723.68 | AD24: 7065.25 | AE24: 28938.32
A25: Total telecom revenue | B25: 32620 | C25: 33621 | D25: 32948 | E25: 35513 | F25: 135876 | G25: 33583 | H25: 33397 | I25: 34160.75 | J25: 36807.14 | K25: 138474.32 | L25: 34598.31 | M25: 34691.3 | N25: 34533.69 | O25: 37382.55 | P25: 141100.15 | Q25: 35149.16 | R25: 35232.1 | S25: 34872.08 | T25: 37846.47 | U25: 143259.36 | V25: 35286.37 | W25: 34801.35 | X25: 34743.2 | Y25: 37475.14 | Z25: 144846.59 | AA25: 35516.27 | AB25: 35030.8 | AC25: 34944.14 | AD25: 37717.56 | AE25: 146451.93
A26: Corporate and other revenue | B26: 865 | C26: 883 | D26: 873 | E26: 868 | F26: 3489 | G26: 857 | H26: 856 | I26: 773.72 | J26: 769.62 | K26: 3136.01 | L26: 774.32 | M26: 793.99 | N26: 777.42 | O26: 774.93 | P26: 3124.38 | Q26: 707.2 | R26: 743.8 | S26: 711.59 | T26: 708.1 | U26: 2885.55 | V26: 685.06 | W26: 735.67 | X26: 690.95 | Y26: 686 | Z26: 2818.49 | AA26: 686.05 | AB26: 735.92 | AC26: 691.71 | AD26: 686.52 | AE26: 2746.51
A27: Operating revenues | B27: 33485 | C27: 34504 | D27: 33821 | E27: 36381 | F27: 138191 | G27: 34440 | H27: 34253 | I27: 34767.99 | J27: 37338.71 | K27: 140869.69 | L27: 35282.92 | M27: 35119.78 | N27: 35157.97 | O27: 37795.46 | P27: 143512.71 | Q27: 35718.77 | R27: 35585.08 | S27: 35427.93 | T27: 38182.74 | U27: 145247.85 | V27: 36024.35 | W27: 35552.48 | X27: 35444.04 | Y27: 38052.19 | Z27: 146846.84 | AA27: 36302.56 | AB27: 35821.97 | AC27: 35686.82 | AD27: 38325.61 | AE27: 148307.92
A29: Mobility and broadband service revenue | B29: 22518 | C29: 22735 | D29: 22839 | E29: 22771 | F29: 90863 | G29: 22868 | H29: 23365 | I29: 23537.92 | J29: 23668.13 | K29: 93439.05 | L29: 23567.31 | M29: 23887.5 | N29: 24002.34 | O29: 24198.56 | P29: 95636.76 | Q29: 24096.84 | R29: 24393.11 | S29: 24426.98 | T29: 24625.65 | U29: 97628.4 | V29: 24546.27 | W29: 24873.83 | X29: 24787.53 | Y29: 24989.43 | Z29: 99953.23 | AA29: 24940.61 | AB29: 25266.74 | AC29: 25153.4 | AD29: 25350.98 | AE29: 101594.52
... A33: Operating revenues | B33: 33485 | C33: 34504 | D33: 33821 | E33: 36381 | F33: 138191 | G33: 34440 | H33: 34253 | I33: 34767.99 | J33: 37338.71 | K33: 140869.69 | L33: 35282.92 | M33: 35119.78 | N33: 35157.97 | O33: 37795.46 | P33: 143512.71 | Q33: 35718.77 | R33: 35585.08 | S33: 35427.93 | T33: 38182.74 | U33: 145247.85 | V33: 36024.35 | W33: 35552.48 | X33: 35444.04 | Y33: 38052.19 | Z33: 146846.84 | AA33: 36302.56 | AB33: 35821.97 | AC33: 35686.82 | AD33: 38325.61 | AE33: 148307.92
A35: FiOS Revenue
A36: FiOS Total digital revenue - Consumer | B36: 2896 | C36: 2924 | D36: 2937 | E36: 2921 | F36: 11678 | G36: 3249.42 | H36: 3540.64 | I36: 3610.55 | J36: 3646.33 | K36: 13648.6 | L36: 3630.55 | M36: 3741.5 | N36: 3690.29 | O36: 3710.84 | P36: 14764.48 | Q36: 3816.56 | R36: 4003.03 | S36: 3883.42 | T36: 3879 | U36: 15560.79 | V36: 4071.38 | W36: 4358.72 | X36: 4100.96 | Y36: 4137.91 | Z36: 16200.47 | AA36: 4163.93 | AB36: 4497.1 | AC36: 4191.72 | AD36: 4222.82 | AE36: 16573.59
A37: FiOS Total digital revenue - Business | B37: 310 | C37: 310 | D37: 310 | E37: 314 | F37: 1244 | G37: 342.24 | H37: 370.89 | I37: 359.23 | J37: 360.84 | K37: 1390.75 | L37: 375.72 | M37: 367.84 | N37: 364.95 | O37: 371.93 | P37: 1430.94 | Q37: 397.21 | R37: 384.01 | S37: 379.05 | T37: 389.13 | U37: 1436.75 | V37: 413.51 | W37: 391.32 | X37: 381.52 | Y37: 387.53 | Z37: 1426.62 | AA37: 410.82 | AB37: 388.09 | AC37: 378.23 | AD37: 383.86 | AE37: 1431.84
A38: FiOS Total digital revenue | B38: 3206 | C38: 3234 | D38: 3247 | E38: 3235 | F38: 12922 | G38: 3631.51 | H38: 3977.32 | I38: 4047.14 | J38: 4095.48 | K38: 15347.92 | L38: 4140.16 | M38: 4251.45 | N38: 4189.81 | O38: 4212.64 | P38: 16526.26 | Q38: 4213.78 | R38: 4387.04 | S38: 4262.47 | T38: 4268.13 | U38: 16949.28 | V38: 4484.89 | W38: 4750.04 | X38: 4482.48 | Y38: 4525.43 | Z38: 17529.11 | AA38: 4574.75 | AB38: 4885.19 | AC38: 4569.95 | AD38: 4606.68 | AE38: 17832.41
A40: Cost of services - Consumer | B40: 4574 | C40: 4581 | D40: 4635 | E40: 4643 | F40: 18433 | G40: 4820 | H40: 4928 | I40: 4813.24 | J40: 4832.84 | K40: 19328.05 | L40: 4824.56 | M40: 4806.68 | N40: 4806.46 | O40: 4868.49 | P40: 19362.53 | Q40: 4733.83 | R40: 4813.52 | S40: 4739.33 | T40: 4799.49 | U40: 19608.64 | V40: 4876.32 | W40: 4983.68 | X40: 4854.68 | Y40: 4933.69 | Z40: 20073.1 | AA40: 4892.88 | AB40: 5016.92 | AC40: 4873.24 | AD40: 4951.8 | AE40: 20214.79
A41: Cost of services - Business | B41: 2154 | C41: 2060 | D41: 1985 | E41: 2083 | F41: 8282 | G41: 2117 | H41: 2023 | I41: 2165.54 | J41: 2209.86 | K41: 8695.74 | L41: 2277.22 | M41: 2154.27 | N41: 2164.01 | O41: 2195.33 | P41: 8861.88 | Q41: 2189.71 | R41: 2044.08 | S41: 2021.06 | T41: 2043.69 | U41: 8707.2 | V41: 2057.42 | W41: 1873.92 | X41: 1866.29 | Y41: 1866.19 | Z41: 8546.92 | AA41: 1987.86 | AB41: 1798.11 | AC41: 1790.9 | AD41: 1790.92 | AE41: 8461.44
A42: Cost of revenue - Total telecom | B42: 6728 | C42: 6641 | D42: 6620 | E42: 6726 | F42: 26715 | G42: 6937 | H42: 6951 | I42: 6978.78 | J42: 7042.69 | K42: 28013.54 | L42: 7101.78 | M42: 6960.94 | N42: 6970.47 | O42: 7063.82 | P42: 28226.17 | Q42: 6923.54 | R42: 6857.6 | S42: 6760.39 | T42: 6843.18 | U42: 28329.31 | V42: 6933.74 | W42: 6857.6 | X42: 6720.97 | Y42: 6799.88 | Z42: 28620.02 | AA42: 6880.73 | AB42: 6815.03 | AC42: 6664.14 | AD42: 6742.72 | AE42: 28676.23
A43: Cost of services - Corporate and other | B43: 222 | C43: 237 | D43: 243 | E43: 372 | F43: 1074 | G43: 230 | H43: 274 | I43: 228.74 | J43: 234.7 | K43: 768.88 | L43: 180.5 | M43: 278.2 | N43: 177.97 | O43: 242.17 | P43: 882.86 | Q43: 209.08 | R43: 213.83 | S43: 183.89 | T43: 258.94 | U43: 719.15 | V43: 172.04 | W43: 183.74 | X43: 168.6 | Y43: 229.64 | Z43: 625.98 | AA43: 172.08 | AB43: 184.03 | AC43: 168.57 | AD43: 230.02 | AE43: 622.93
A44: Cost of services | B44: 6950 | C44: 6878 | D44: 6863 | E44: 7098 | F44: 27789 | G44: 7167 | H44: 7225 | I44: 7159.92 | J44: 7235.2 | K44: 28770.42 | L44: 7272.3 | M44: 7222.54 | N44: 7148.92 | O44: 7273.7 | P44: 28909 | Q44: 7282.86 | R44: 7231.33 | S44: 7114.56 | T44: 7247.3 | U44: 29032.54 | V44: 7350.49 | W44: 7303.06 | X44: 7124.68 | Y44: 7258.22 | Z44: 29295.24 | AA44: 7369.69 | AB44: 7326.85 | AC44: 7136.53 | AD44: 7268.69 | AE44: 29400.68
A46: Cost of wireless equipment - Consumer | B46: 4912 | C46: 5806 | D46: 5270 | E46: 7942 | F46: 23930 | G46: 5303 | H46: 4658 | I46: 5207.09 | J46: 7662.28 | K46: 23075.18 | L46: 5538.32 | M46: 5267.01 | N46: 5296.22 | O46: 7928.1 | P46: 23934.5 | Q46: 5827.62 | R46: 5677.83 | S46: 5342.65 | T46: 8182.3 | U46: 24449.83 | V46: 5852.98 | W46: 5212.21 | X46: 5250.34 | Y46: 7792.66 | Z46: 24390.93 | AA46: 5968.77 | AB46: 5313.58 | AC46: 5350.27 | AD46: 7947.81 | AE46: 24839.83
A47: Cost of wireless equipment - Business | B47: 1194 | C47: 1201 | D47: 1213 | E47: 1438 | F47: 5046 | G47: 1202 | H47: 1203 | I47: 1203.68 | J47: 1468.9 | K47: 5093.48 | L47: 1219.57 | M47: 1194.12 | N47: 1205.19 | O47: 1468.73 | P47: 5166.55 | Q47: 1265.51 | R47: 1288.5 | S47: 1231.88 | T47: 1495.92 | U47: 5353.29 | V47: 1274.91 | W47: 1244.15 | X47: 1192.91 | Y47: 1407.6 | Z47: 5395.91 | AA47: 1295.01 | AB47: 1261.87 | AC47: 1210.57 | AD47: 1430.7 | AE47: 5484.63
A48: Cost of wireless equipment - Total telecom | B48: 6106 | C48: 7007 | D48: 6483 | E48: 9380 | F48: 28976 | G48: 6505 | H48: 5861 | I48: 6410.77 | J48: 9131.17 | K48: 28128.2 | L48: 6757.89 | M48: 6461.13 | N48: 6501.42 | O48: 9396.83 | P48: 28977.59 | Q48: 7093.13 | R48: 6966.33 | S48: 6574.53 | T48: 9678.22 | U48: 29642.68 | V48: 7127.89 | W48: 6456.36 | X48: 6443.25 | Y48: 9200.26 | Z48: 29786.84 | AA48: 7263.78 | AB48: 6575.45 | AC48: 6560.83 | AD48: 9378.51 | AE48: 30324.46
A49: Cost of wireless equipment - Corporate and other | B49: -335.27 | C49: -376.45 | D49: -354.33 | E49: -439.78 | F49: -1505.83 | G49: 1 | H49: -2 | I49: -52.53 | J49: -338.74 | K49: -399.34 | L49: 296.48 | M49: -127.99 | N49: 336.76 | O49: 674.76 | P49: 1180.01 | Q49: 211.98 | R49: 115.25 | S49: -46.22 | T49: 591.55 | U49: 872.56 | V49: - | W49: - | X49: - | Y49: - | Z49: - | AA49: - | AB49: - | AC49: - | AD49: - | AE49: -
A50: Cost of wireless equipment | B50: 6106 | C50: 7007 | D50: 6483 | E50: 9380 | F50: 28976 | G50: 6506 | H50: 5859 | I50: 6300.47 | J50: 8928.79 | K50: 27592.79 | L50: 6758.1 | M50: 6263.52 | N50: 6438.11 | O50: 9168.88 | P50: 28649.58 | Q50: 6920.3 | R50: 6568.38 | S50: 6443.63 | T50: 9295.96 | U50: 29028.6 | V50: 6961.02 | W50: 6266.3 | X50: 6298.82 | Y50: 8927.48 | Z50: 28912.26 | AA50: 7051.53 | AB50: 6345.12 | AC50: 6376.91 | AD50: 9044.97 | AE50: 29319.41
A52: Cost of sales - Consumer | B52: 9486 | C52: 10387 | D52: 9905 | E52: 12585 | F52: 42363 | G52: 10123 | H52: 9586 | I52: 10020.33 | J52: 12495.12 | K52: 42403.23 | L52: 10362.88 | M52: 10073.68 | N52: 10102.68 | O52: 12796.59 | P52: 43297.03 | Q52: 10561.45 | R52: 10491.34 | S52: 10081.98 | T52: 12981.78 | U52: 44058.47 | V52: 10729.31 | W52: 10195.89 | X52: 10105.01 | Y52: 12726.35 | Z52: 44464.04 | AA52: 10861.65 | AB52: 10330.5 | AC52: 10223.51 | AD52: 12899.61 | AE52: 45054.62
A53: Cost of sales - Business | B53: 3348 | C53: 3261 | D53: 3198 | E53: 3521 | F53: 13328 | G53: 3319 | H53: 3226 | I53: 3369.22 | J53: 3678.75 | K53: 13789.21 | L53: 3496.79 | M53: 3348.39 | N53: 3369.21 | O53: 3664.05 | P53: 14028.43 | Q53: 3455.22 | R53: 3332.58 | S53: 3252.94 | T53: 3539.61 | U53: 14060.49 | V53: 3332.33 | W53: 3118.07 | X53: 3059.2 | Y53: 3273.79 | Z53: 13942.83 | AA53: 3282.86 | AB53: 3059.98 | AC53: 3001.47 | AD53: 3221.62 | AE53: 13946.07
A54: Cost of sales - Total telecom | B54: 12834 | C54: 13648 | D54: 13103 | E54: 16106 | F54: 55691 | G54: 13442 | H54: 12812 | I54: 13389.55 | J54: 16173.87 | K54: 56141.74 | L54: 13859.68 | M54: 13422.07 | N54: 13471.89 | O54: 16460.65 | P54: 57203.75 | Q54: 14016.67 | R54: 13823.92 | S54: 13334.92 | T54: 16521.4 | U54: 57972 | V54: 14061.64 | W54: 13313.95 | X54: 13164.22 | Y54: 16000.14 | Z54: 58406.86 | AA54: 14144.51 | AB54: 13390.47 | AC54: 13224.98 | AD54: 16121.23 | AE54: 59000.69
A55: Cost of sales - Corporate and other | B55: 222 | C55: 237 | D55: 243 | E55: 372 | F55: 1074 | G55: 231 | H55: 272 | I55: 271.34 | J55: 347.42 | K55: 912.24 | L55: 281.04 | M55: 268.41 | N55: 327.78 | O55: 403.56 | P55: 1164.22 | Q55: 202.22 | R55: 209.14 | S55: 200.23 | T55: 236.61 | U55: 709.41 | V55: 172.04 | W55: 183.74 | X55: 168.6 | Y55: 229.64 | Z55: 625.98 | AA55: 172.08 | AB55: 184.03 | AC55: 168.57 | AD55: 230.02 | AE55: 622.93
A56: Cost of services and sales -Operating | B56: 13056 | C56: 13885 | D56: 13346 | E56: 16478 | F56: 56765 | G56: 13673 | H56: 13084 | I56: 13451.92 | J56: 16149.04 | K56: 56340.79 | L56: 14030.4 | M56: 13486.06 | N56: 13587.03 | O56: 16442.58 | P56: 57482.57 | Q56: 14203.15 | R56: 13799.71 | S56: 13558.19 | T56: 16543.26 | U56: 57977.78 | V56: 14311.51 | W56: 13569.37 | X56: 13423.5 | Y56: 16185.7 | Z56: 58145.06 | AA56: 14421.22 | AB56: 13671.97 | AC56: 13513.44 | AD56: 16313.66 | AE56: 58663.3
A58: SG&A - Consumer | B58: 5165 | C58: 5036 | D58: 4968 | E58: 5474 | F58: 20643 | G58: 4886 | H58: 4837 | I58: 4968.39 | J58: 5480.98 | K58: 20193.51 | L58: 5002.6 | M58: 4934.42 | N58: 5037.13 | O58: 5603.44 | P58: 20418.33 | Q58: 4972.74 | R58: 4901.15 | S58: 4942.37 | T58: 5448.48 | U58: 20316.63 | V58: 4874.05 | W58: 4816.63 | X58: 4892.5 | Y58: 5403.84 | Z58: 20510.28 | AA58: 4850.85 | AB58: 4795.17 | AC58: 4864.41 | AD58: 5384.08 | AE58: 20623.58
A59: SG&A - Business | B59: 1919 | C59: 1990 | D59: 1927 | E59: 1885 | F59: 7721 | G59: 1806 | H59: 1847 | I59: 1966.9 | J59: 1968.44 | K59: 7716.32 | L59: 1854.83 | M59: 1800.69 | N59: 1923.74 | O59: 1952.96 | P59: 7572.46 | Q59: 1805.35 | R59: 1671.63 | S59: 1887.3 | T59: 1923.4 | U59: 7358.37 | V59: 1656.29 | W59: 1432.27 | X59: 1749.45 | Y59: 1785.49 | Z59: 7120.94 | AA59: 1580.75 | AB59: 1349.07 | AC59: 1666.2 | AD59: 1697.16 | AE59: 6968.64
A60: SG&A - Total telecom | B60: 7084 | C60: 7026 | D60: 6895 | E60: 7359 | F60: 28364 | G60: 6692 | H60: 6684 | I60: 6935.3 | J60: 7449.41 | K60: 27873.19 | L60: 6857.43 | M60: 6735.11 | N60: 6960.88 | O60: 7556.4 | P60: 27940.16 | Q60: 6778.09 | R60: 6572.78 | S60: 6829.67 | T60: 7371.89 | U60: 27636.02 | V60: 6530.35 | W60: 6248.9 | X60: 6641.96 | Y60: 7189.33 | Z60: 27631.22 | AA60: 6431.6 | AB60: 6144.25 | AC60: 6530.61 | AD60: 7081.24 | AE60: 27592.23
A61: SG&A - Corporate and other | B61: 790 | C61: 786 | D61: 805 | E61: 684 | F61: 3065 | G61: 680 | H61: 2298 | I61: 719.88 | J61: 671.66 | K61: 3727.8 | L61: 612.66 | M61: 1036.25 | N61: 579.84 | O61: 1275.2 | P61: 3302.39 | Q61: 609.57 | R61: 730.7 | S61: 628.95 | T61: 613.88 | U61: 2779.15 | V61: 584.1 | W61: 738.7 | X61: 608.61 | Y61: 589.58 | Z61: 2759.22 | AA61: 579.62 | AB61: 735.44 | AC61: 604.93 | AD61: 584.72 | AE61: 2754.75
A62: Selling, general and admin. exp. - Operating | B62: 7874 | C62: 7812 | D62: 7700 | E62: 8043 | F62: 31429 | G62: 7372 | H62: 7446 | I62: 7586.89 | J62: 8042.84 | K62: 31112.36 | L62: 7429.02 | M62: 7745.23 | N62: 7467.75 | O62: 8422.53 | P62: 30851.31 | Q62: 7377.62 | R62: 7529.5 | S62: 7404.82 | T62: 7822.66 | U62: 30071.08 | V62: 7204.9 | W62: 7400.9 | X62: 7236.81 | Y62: 7720.71 | Z62: 29963.66 | AA62: 7169.04 | AB62: 7364.24 | AC62: 7190.75 | AD62: 7676.01 | AE62: 29947.07
A64: Depreciation and amortization - Consumer | B64: 3543 | C64: 3582 | D64: 3568 | E64: 3480 | F64: 14173 | G64: 3730 | H64: 3787 | I64: 3803.21 | J64: 3851.47 | K64: 15134.07 | L64: 3834.37 | M64: 3850.11 | N64: 3888.79 | O64: 3895.28 | P64: 15331.01 | Q64: 3858.03 | R64: 3893.17 | S64: 3945.76 | T64: 3877.83 | U64: 15513.17 | V64: 3855.64 | W64: 3878.8 | X64: 3971.52 | Y64: 3917.13 | Z64: 15686.79 | AA64: 3883.14 | AB64: 3906.75 | AC64: 4001.46 | AD64: 3945.82 | AE64: 15885.24
... A91: Capital expenditures (including capitalized software) | B91: 4145 | C91: 3808 | D91: 4310 | E91: 4748 | F91: 17011 | G91: 4201 | H91: 4009 | I91: 4008.73 | J91: 4142.97 | K91: 16344.13 | L91: 4160.61 | M91: 4114.25 | N91: 4086.13 | O91: 4258.26 | P91: 16665.32 | Q91: 4287.07 | R91: 4168.59 | S91: 4166.07 | T91: 4256.04 | U91: 16949.72 | V91: 4309.76 | W91: 4177.1 | X91: 4153.67 | Y91: 4233.86 | Z91: 17063.41 | AA91: 4316.82 | AB91: 4186.32 | AC91: 4159.72 | AD91: 4239.67 | AE91: 17179.16

Sheet Wireline
A2: Verizon Communications Inc. | Wireline
A3: NYSE:VZ (MI KEY: 4057229; SPCIQ KEY: 415798)
A5: Visible Alpha
A7: Period Type : Fiscal Quarter, Fiscal Halves, Fiscal Year
A8: Period Start : 2025
A9: Period End : 2030
A10: Currency : Reported
A11: Consensus View : Mean
A12: As Of: 10/25/2026
A14: All numbers in $M unless otherwise indicated | B14: FQ1 2025A | C14: FQ2 2025A | D14: FQ3 2025A | E14: FQ4 2025A | F14: FY2025A | G14: FQ1 2026A | H14: FQ2 2026A | I14: FQ3 2026E | J14: FQ4 2026E | K14: FY2026E | L14: FQ1 2027E | M14: FQ2 2027E | N14: FQ3 2027E | O14: FQ4 2027E | P14: FY2027E | Q14: FQ1 2028E | R14: FQ2 2028E | S14: FQ3 2028E | T14: FQ4 2028E | U14: FY2028E | V14: FQ1 2029E | W14: FQ2 2029E | X14: FQ3 2029E | Y14: FQ4 2029E | Z14: FY2029E | AA14: FQ1 2030E | AB14: FQ2 2030E | AC14: FQ3 2030E | AD14: FQ4 2030E | AE14: FY2030E
A15: Number of Contributors Available | B15: 19 | C15: 19 | D15: 19 | E15: 19 | F15: 20 | G15: 20 | H15: 20 | I15: 20 of 20 | J15: 20 of 20 | K15: 20 of 20 | L15: 13 of 20 | M15: 13 of 20 | N15: 12 of 20 | O15: 12 of 20 | P15: 20 of 20 | Q15: 7 of 20 | R15: 7 of 20 | S15: 7 of 20 | T15: 7 of 20 | U15: 18 of 20 | V15: 5 of 20 | W15: 5 of 20 | X15: 5 of 20 | Y15: 5 of 20 | Z15: 14 of 20 | AA15: 5 of 20 | AB15: 5 of 20 | AC15: 5 of 20 | AD15: 5 of 20 | AE15: 14 of 20
A16: Revenue
A17: Consumer markets revenue | B17: 2785.35 | C17: 2811.1 | D17: 2821.1 | E17: 2804.6 | F17: 11222.13 | G17: 3225.9 | H17: 3472 | I17: 3697.78 | J17: 3753.82 | K17: 14149.5 | L17: 4302.18 | M17: 4667.53 | N17: 4346.58 | O17: 4395.55 | P17: 15334.02 | Q17: 4364.84 | R17: 4790.57 | S17: 4409.87 | T17: 4453.07 | U17: 15761.24 | V17: 4413 | W17: 4901.26 | X17: 4453.27 | Y17: 4488.62 | Z17: 16230.29 | AA17: 4434.12 | AB17: 4988.09 | AC17: 4471.73 | AD17: 4503.88 | AE17: 16649.77
A18: Business markets revenue | B18: 2622.67 | C18: 2566.33 | D18: 2463 | E18: 2447 | F18: 10099 | G18: 2758.5 | H18: 2651.17 | I18: 2623.71 | J18: 2606.18 | K18: 10639.56 | L18: 2729.6 | M18: 2608.73 | N18: 2426 | O18: 2410.18 | P18: 10003.35 | Q18: 2500.93 | R18: 2390.27 | S18: 2222.64 | T18: 2208.45 | U18: 9244.26 | V18: 2292.83 | W18: 2191.74 | X18: 2038.07 | Y18: 2025.49 | Z18: 8549.11 | AA18: 2104.07 | AB18: 2011.74 | AC18: 1870.88 | AD18: 1859.83 | AE18: 7913.41
A19: Wireline revenue | B19: 5512.4 | C19: 5485.56 | D19: 5389.23 | E19: 5354.73 | F19: 21741.92 | G19: 6165.52 | H19: 6320.66 | I19: 6413.8 | J19: 6420.69 | K19: 25320.67 | L19: 6778.04 | M19: 6854.72 | N19: 6583.99 | O19: 6588.3 | P19: 25491.92 | Q19: 6791.9 | R19: 6939.35 | S19: 6568.62 | T19: 6578.7 | U19: 25105.08 | V19: 6696.07 | W19: 6878.06 | X19: 6474.29 | Y19: 6478.14 | Z19: 24805.83 | AA19: 6603.84 | AB19: 6822.51 | AC19: 6383.93 | AD19: 6384.68 | AE19: 24552.17
A21: Cost of sales - Wireline | B21: 3662.97 | C21: 3704.72 | D21: 3621.88 | E21: 3677.73 | F21: 13418.67 | G21: 4090.4 | H21: 4115.52 | I21: 4185 | J21: 4169.46 | K21: 14272.67 | L21: 4048.44 | M21: 4013.62 | N21: 3964.82 | O21: 3952.85 | P21: 13973.33 | Q21: 3868.65 | R21: 3837.1 | S21: 3791.92 | T21: 3777.29 | U21: 13639.11 | V21: 3741.85 | W21: 3711 | X21: 3666.73 | Y21: 3648.49 | Z21: 13491.7 | AA21: 3606.68 | AB21: 3574.73 | AC21: 3534.62 | AD21: 3517.02 | AE21: 13352.42
A22: SG&A - Wireline | B22: 1264.69 | C22: 1198.1 | D22: 1162.49 | E22: 1087.36 | F22: 4712.65 | G22: 1050.45 | H22: 1495.86 | I22: 1046.25 | J22: 1042.37 | K22: 4514.02 | L22: 1012.11 | M22: 1003.4 | N22: 991.2 | O22: 988.21 | P22: 4169.13 | Q22: 967.16 | R22: 959.27 | S22: 947.98 | T22: 944.32 | U22: 4065.89 | V22: 935.46 | W22: 927.75 | X22: 916.68 | Y22: 912.12 | Z22: 4018.45 | AA22: 901.67 | AB22: 893.68 | AC22: 883.65 | AD22: 879.25 | AE22: 3974.45
A23: Operations and support - Wireline | B23: 4626.32 | C23: 4569.31 | D23: 4484.39 | E23: 4451.29 | F23: 18131.32 | G23: 4558.72 | H23: 4880.8 | I23: 4663.43 | J23: 4683.73 | K23: 18786.69 | L23: 5060.55 | M23: 5017.02 | N23: 4956.02 | O23: 4941.06 | P23: 18142.46 | Q23: 4835.81 | R23: 4796.37 | S23: 4739.9 | T23: 4721.61 | U23: 17705 | V23: 4677.32 | W23: 4638.75 | X23: 4583.41 | Y23: 4560.61 | Z23: 17510.14 | AA23: 4508.35 | AB23: 4468.41 | AC23: 4418.27 | AD23: 4396.27 | AE23: 17326.87
A24: Depreciation and amortization - Wireline | B24: 1543.52 | C24: 1544.15 | D24: 1521.41 | E24: 1507.89 | F24: 6116.97 | G24: 1555.78 | H24: 1674.58 | I24: 1503.32 | J24: 1513.26 | K24: 5936.1 | L24: - | M24: - | N24: - | O24: - | P24: 5982.17 | Q24: - | R24: - | S24: - | T24: - | U24: 5225.36 | V24: - | W24: - | X24: - | Y24: - | Z24: 4970.01 | AA24: - | AB24: - | AC24: - | AD24: - | AE24: 4657
A25: Total operating expenses - Wireline | B25: 6652.55 | C25: 6723.93 | D25: 6484.34 | E25: 6660.14 | F25: 22614.76 | G25: 6956 | H25: 6906.64 | I25: 5402.95 | J25: 5458.53 | K25: 21621.99 | L25: - | M25: - | N25: - | O25: - | P25: 21565.31 | Q25: - | R25: - | S25: - | T25: - | U25: 21648.36 | V25: - | W25: - | X25: - | Y25: - | Z25: 22028.56 | AA25: - | AB25: - | AC25: - | AD25: - | AE25: 22520.49
A26: Operating income/(loss) - Wireline | B26: -1259.09 | C26: -1351.8 | D26: -1207.54 | E26: -1414.02 | F26: -1975.5 | G26: -444.66 | H26: -336.49 | I26: -280.23 | J26: -324.94 | K26: -1386.32 | L26: - | M26: 6369.91 | N26: - | O26: - | P26: -1325.89 | Q26: - | R26: - | S26: - | T26: - | U26: -1313.13 | V26: - | W26: - | X26: - | Y26: - | Z26: -1298.94 | AA26: - | AB26: - | AC26: - | AD26: - | AE26: -1319.64
A27: Adjusted EBITDA - Wireline | B27: 344.79 | C27: 290.68 | D27: 372.39 | E27: 219.67 | F27: 3157.19 | G27: 1150.51 | H27: 923.07 | I27: 1287.67 | J27: 1262.5 | K27: 4623.75 | L27: 1558.11 | M27: 3965 | N27: 1535.21 | O27: 1538.04 | P27: 5060.29 | Q27: 1584.04 | R27: 1592.41 | S27: 1573.81 | T27: 1576.82 | U27: 5173.01 | V27: 1557.71 | W27: 1569.08 | X27: 1554.11 | Y27: 1555.75 | Z27: 5203.04 | AA27: 1531.52 | AB27: 1542.14 | AC27: 1534.57 | AD27: 1540.12 | AE27: 5243.38
A28: Capital expenditures - Wireline | B28: 1327.84 | C28: 1226.85 | D28: 1368.6 | E28: 1537.19 | F28: 5460.48 | G28: 1433.34 | H28: 1440.24 | I28: 1456.37 | J28: 1480.1 | K28: 5810.06 | L28: 1354.84 | M28: 1350.53 | N28: 1335.95 | O28: 1347.4 | P28: 6023.74 | Q28: 1294.37 | R28: 1289.38 | S28: 1267.98 | T28: 1284.44 | U28: 6246.05 | V28: 1113.69 | W28: 1102.66 | X28: 1095.34 | Y28: 1091.14 | Z28: 6387.97 | AA28: 1032.54 | AB28: 1028.86 | AC28: 1024.88 | AD28: 1022.96 | AE28: 6251.54
A29: FiOS connections
A30: Beginning Subs. - Total Video(K#) | B30: 2738 | C30: 2678 | D30: 2615 | E30: 2543 | F30: 2738 | G30: 2488 | H30: 2491.82 | I30: 2463.71 | J30: 2400.75 | K30: 2495.15 | L30: 2325.4 | M30: 2260 | N30: 2189.65 | O30: 2119.66 | P30: 2345.96 | Q30: 2093.24 | R30: 2027.13 | S30: 1957.02 | T30: 1886.58 | U30: 2094.16 | V30: 1922.18 | W30: 1862.79 | X30: 1798.72 | Y30: 1737.66 | Z30: 1887.8 | AA30: 1686.83 | AB30: 1630.84 | AC30: 1570.76 | AD30: 1512.94 | AE30: 1664.77
A31: Net adds - FiOS Video open for sale(K#) | B31: 84.18 | C31: 146.86 | D31: 147.03 | E31: 134.42 | F31: 512.49 | G31: 8858.38 | H31: 439.03 | I31: 495.71 | J31: 480 | K31: 10273.12 | L31: 473.84 | M31: 474.84 | N31: 475.84 | O31: 476.84 | P31: 1964.31 | Q31: 477.84 | R31: 478.84 | S31: 479.84 | T31: 480.84 | U31: 2104.12 | V31: 392.67 | W31: 393.47 | X31: 394.27 | Y31: 395.07 | Z31: 1990.17 | AA31: 351.09 | AB31: 351.79 | AC31: 352.49 | AD31: 353.19 | AE31: 1934.52
A32: FiOS Video open for sale(K#) | B32: 17034.8 | C32: 17181.65 | D32: 17328.69 | E32: 17404.65 | F32: 17404.65 | G32: 26868.1 | H32: 27307.13 | I32: 27802.84 | J32: 28282.85 | K32: 28282.85 | L32: 28719.83 | M32: 29194.68 | N32: 29670.52 | O32: 30147.37 | P32: 30247.16 | Q32: 30625.21 | R32: 31104.05 | S32: 31583.9 | T32: 32064.74 | U32: 32351.28 | V32: 32457.41 | W32: 32850.89 | X32: 33245.16 | Y32: 33640.24 | Z32: 34341.45 | AA32: 33991.33 | AB32: 34343.12 | AC32: 34695.61 | AD32: 35048.8 | AE32: 36275.97
A33: Penetration - FiOS Video(%) | B33: 15.77% | C33: 15.27% | D33: 14.73% | E33: 14.31% | F33: 14.31% | G33: 9.31% | H33: 8.91% | I33: 8.49% | J33: 8.11% | K33: 8.11% | L33: 7.86% | M33: 7.42% | N33: 7.10% | O33: 6.79% | P33: 6.75% | Q33: 6.44% | R33: 6.07% | S33: 5.79% | T33: 5.52% | U33: 5.50% | V33: 5.23% | W33: 4.93% | X33: 4.70% | Y33: 4.48% | Z33: 4.40% | AA33: 4.24% | AB33: 3.99% | AC33: 3.79% | AD33: 3.61% | AE33: 3.40%
A34: Net adds - FiOS Video subscribers(K#) | B34: -60 | C34: -63 | D34: -72 | E34: -55 | F34: -250 | G34: -40.83 | H34: -68.35 | I34: -70.76 | J34: -61.71 | K34: -232.13 | L34: -65.4 | M34: -70.36 | N34: -69.99 | O34: -59.94 | P34: -254.95 | Q34: -66.11 | R34: -70.11 | S34: -70.44 | T34: -58.57 | U34: -249.74 | V34: -59.39 | W34: -64.07 | X34: -61.06 | Y34: -50.83 | Z34: -233.57 | AA34: -55.99 | AB34: -60.08 | AC34: -57.82 | AD34: -48.1 | AE34: -229.16
A35: FiOS Video subscribers(K#) | B35: 2678 | C35: 2615 | D35: 2543 | E35: 2488 | F35: 2488 | G35: 2486.76 | H35: 2429.29 | I35: 2401.91 | J35: 2347.77 | K35: 2347.77 | L35: 2260 | M35: 2189.65 | N35: 2119.66 | O35: 2059.72 | P35: 2096.03 | Q35: 2027.13 | R35: 1957.02 | S35: 1886.58 | T35: 1828.01 | U35: 1850.43 | V35: 1862.79 | W35: 1798.72 | X35: 1737.66 | Y35: 1686.83 | Z35: 1664.58 | AA35: 1630.84 | AB35: 1570.76 | AC35: 1512.94 | AD35: 1464.84 | AE35: 1444.15
A37: Net adds - FiOS Internet open for sale(K#) | B37: 155.83 | C37: 169.14 | D37: 164 | E37: 157.57 | F37: 624.29 | G37: 7999.26 | H37: 402.08 | I37: 455.26 | J37: 455.57 | K37: 9274.74 | L37: 375 | M37: 437.5 | N37: 425 | O37: 412.5 | P37: 1770.26 | Q37: 383.33 | R37: 383.33 | S37: 383.33 | T37: 383.33 | U37: 1837.5 | V37: 345.83 | W37: 345.83 | X37: 345.83 | Y37: 345.83 | Z37: 1762.5 | AA37: 325 | AB37: 325 | AC37: 325 | AD37: 325 | AE37: 1720.83
A38: FiOS Internet open for sale(K#) | B38: 18637.25 | C38: 18806.39 | D38: 18970.39 | E38: 19127.96 | F38: 19127.96 | G38: 27486.17 | H38: 27888.25 | I38: 28343.51 | J38: 28799.07 | K38: 28799.07 | L38: 29278.62 | M38: 29716.12 | N38: 30141.12 | O38: 30553.62 | P38: 30569.33 | Q38: 29771.5 | R38: 30154.83 | S38: 30538.17 | T38: 30921.5 | U38: 32406.83 | V38: 31267.33 | W38: 31613.17 | X38: 31959 | Y38: 32304.83 | Z38: 34169.33 | AA38: 32629.83 | AB38: 32954.83 | AC38: 33279.83 | AD38: 33604.83 | AE38: 35890.17
A39: Penetration - FiOS Internet(%) | B39: 40.74% | C39: 40.54% | D39: 40.51% | E39: 40.53% | F39: 40.53% | G39: 40.28% | H39: 40.31% | I39: 40.32% | J39: 40.33% | K39: 40.33% | L39: 40.92% | M39: 40.95% | N39: 41.06% | O39: 41.17% | P39: 40.53% | Q39: 43.54% | R39: 43.67% | S39: 43.88% | T39: 44.05% | U39: 40.80% | V39: 44.27% | W39: 44.43% | X39: 44.65% | Y39: 44.84% | Z39: 41.09% | AA39: 45.04% | AB39: 45.20% | AC39: 45.42% | AD39: 45.61% | AE39: 41.33%
A40: Internal/organic Net adds - Fiber broadband(K#) | B40: 45 | C40: 32 | D40: 61 | E40: 67 | F40: 205 | G40: 127 | H40: 155 | I40: 167.68 | J40: 154.39 | K40: 606.67 | L40: 163.15 | M40: 163.73 | N40: 175.39 | O40: 165.96 | P40: 660.19 | Q40: 173.1 | R40: 173.89 | S40: 183.67 | T40: 170.22 | U40: 696.64 | V40: 182.88 | W40: 176.84 | X40: 183.46 | Y40: 176.44 | Z40: 689.11 | AA40: 175.98 | AB40: 172.69 | AC40: 179.83 | AD40: 172.92 | AE40: 666.48
A41: Acquired Net adds - Fiber broadband(K#) | B41: - | C41: - | D41: - | E41: - | F41: - | G41: 2889 | H41: 1 | I41: -0.05 | J41: - | K41: 2886.9 | L41: - | M41: - | N41: - | O41: - | P41: - | Q41: - | R41: - | S41: - | T41: - | U41: - | V41: - | W41: - | X41: - | Y41: - | Z41: - | AA41: - | AB41: - | AC41: - | AD41: - | AE41: -
A42: Net adds - Fiber broadband(K#) | B42: 45 | C42: 32 | D42: 61 | E42: 67 | F42: 205 | G42: 3016 | H42: 156 | I42: 159.51 | J42: 155.39 | K42: 3287 | L42: 166.11 | M42: 162.8 | N42: 178.19 | O42: 173.43 | P42: 676.81 | Q42: 181.11 | R42: 180.37 | S42: 191.79 | T42: 181.92 | U42: 700.4 | V42: 182.88 | W42: 176.84 | X42: 183.46 | Y42: 176.44 | Z42: 669.59 | AA42: 175.98 | AB42: 172.69 | AC42: 179.83 | AD42: 172.92 | AE42: 636.01
A43: Fiber broadband subscribers(K#) | B43: 7581 | C43: 7613 | D43: 7674 | E43: 7741 | F43: 7741 | G43: 10757 | H43: 10913 | I43: 11097.75 | J43: 11249.68 | K43: 11254.79 | L43: 11483.97 | M43: 11643.78 | N43: 11818.05 | O43: 11984.81 | P43: 11901.79 | Q43: 12065.25 | R43: 12239.14 | S43: 12422.81 | T43: 12593.03 | U43: 12557.42 | V43: 12827.93 | W43: 13004.76 | X43: 13188.23 | Y43: 13364.67 | Z43: 13168.89 | AA43: 13540.65 | AB43: 13713.34 | AC43: 13893.16 | AD43: 14066.09 | AE43: 13761.66
A45: Net adds - FiOS Digital Voice residence connections(K#) | B45: -73.89 | C45: -68.17 | D45: -69.76 | E45: -62.84 | F45: -274.66 | G45: 73.72 | H45: -72.6 | I45: -72.2 | J45: -74.36 | K45: -145.46 | L45: -63.35 | M45: -67.01 | N45: -65.07 | O45: -66.96 | P45: -277.05 | Q45: -79.22 | R45: -81.7 | S45: -83.42 | T45: -85.29 | U45: -289.37 | V45: -83.72 | W45: -85.98 | X45: -87.69 | Y45: -89.35 | Z45: -305.61 | AA45: -88.09 | AB45: -89.55 | AC45: -91.05 | AD45: -22.94 | AE45: -241.52
A46: FiOS Digital Voice residence connections(K#) | B46: 2299.85 | C46: 2253.98 | D46: 2184.22 | E46: 2186.99 | F46: 2186.99 | G46: 2176.49 | H46: 2103.88 | I46: 2031.68 | J46: 1957.32 | K46: 1957.32 | L46: 1915.32 | M46: 1848.31 | N46: 1783.24 | O46: 1716.29 | P46: 1680.27 | Q46: 1512.4 | R46: 1430.71 | S46: 1347.29 | T46: 1262 | U46: 1390.9 | V46: 1178.28 | W46: 1092.31 | X46: 1004.62 | Y46: 915.26 | Z46: 1085.29 | AA46: 827.17 | AB46: 737.62 | AC46: 646.57 | AD46: 1228 | AE46: 987.39
A48: Net adds - FiOS(K#) | B48: -34.46 | C48: -62.65 | D48: -57.19 | E48: 17.58 | F48: -136.73 | G48: 2492.42 | H48: 15.37 | I48: 10.78 | J48: 16.04 | K48: 2529.41 | L48: 20.82 | M48: 10.25 | N48: 24.08 | O48: 28.91 | P48: 75.32 | Q48: -1.21 | R48: -1.83 | S48: -4.32 | T48: 1.72 | U48: 57.35 | V48: -10.22 | W48: -11.95 | X48: -18.28 | Y48: -14.2 | Z48: -2.06 | AA48: -25.46 | AB48: -17.88 | AC48: -23.77 | AD48: -18.35 | AE48: -70.78
A49: FiOS Digital connections(K#) | B49: 13335.3 | C49: 13268.12 | D49: 13204.33 | E49: 13222.7 | F49: 13222.7 | G49: 15869.56 | H49: 15885.35 | I49: 15896.13 | J49: 15912.17 | K49: 15912.17 | L49: 16056.66 | M49: 16066.91 | N49: 16090.99 | O49: 16119.9 | P49: 15987.5 | Q49: 15469.23 | R49: 15467.4 | S49: 15463.08 | T49: 15464.8 | U49: 15687.95 | V49: 15454.58 | W49: 15442.63 | X49: 15424.35 | Y49: 15410.15 | Z49: 15685.88 | AA49: 15384.68 | AB49: 15366.8 | AC49: 15343.03 | AD49: 15324.68 | AE49: 15615.1
A50: Average Fios connections(K#) | B50: 13353.92 | C50: 13301.71 | D50: 13236.23 | E50: 13213.52 | F50: 13295.82 | G50: 14574.52 | H50: 15877.46 | I50: 15890.74 | J50: 15904.15 | K50: 14787.48 | L50: 16046.25 | M50: 16061.78 | N50: 16078.95 | O50: 16105.44 | P50: 15950.2 | Q50: 15469.83 | R50: 15468.32 | S50: 15465.24 | T50: 15463.94 | U50: 15659.72 | V50: 15459.69 | W50: 15448.6 | X50: 15433.49 | Y50: 15417.25 | Z50: 15687.37 | AA50: 15397.41 | AB50: 15375.74 | AC50: 15354.92 | AD50: 15333.86 | AE50: 15650.96
A51: FiOS ARPU($) | B51: 84.45 | C51: 84.72 | D51: 86.85 | E51: 86.35 | F51: 84.97 | G51: 88.51 | H51: 88.64 | I51: 89.53 | J51: 89.99 | K51: 92.65 | L51: 91.94 | M51: 90.38 | N51: 91.24 | O51: 91.68 | P51: 91.3 | Q51: 91.04 | R51: 87.32 | S51: 88.29 | T51: 88.44 | U51: 93.17 | V51: 92.75 | W51: 88.96 | X51: 89.94 | Y51: 90.08 | Z51: 95.06 | AA51: 94.44 | AB51: 90.59 | AC51: 91.58 | AD51: 91.72 | AE51: 96.88
A52: FiOS consumer revenue | B52: 3206 | C52: 3234 | D52: 3247 | E52: 3235 | F52: 12922 | G52: 3713.57 | H52: 4121.62 | I52: 4168.06 | J52: 4193.98 | K52: 16197.23 | L52: 4289.41 | M52: 4223.2 | N52: 4268.44 | O52: 4295.11 | P52: 17076.16 | Q52: 4216.64 | R52: 4057.4 | S52: 4114.28 | T52: 4130.82 | U52: 17519.6 | V52: 4344.15 | W52: 4181.57 | X52: 4241.53 | Y52: 4259.78 | Z52: 17979.66 | AA52: 4480.23 | AB52: 4313.98 | AC52: 4376.84 | AD52: 4396.44 | AE52: 18443.41
A54: FiOS Total digital subscribers - Consumer(K#) | B54: 12582.46 | C54: 12495.68 | D54: 12432.24 | E54: 12392 | F54: 12392 | G54: 15042.95 | H54: 15068.56 | I54: 15095.97 | J54: 15127.45 | K54: 15127.45 | L54: 15295.29 | M54: 15306.1 | N54: 15333.21 | O54: 15364.13 | P54: 15239.22 | Q54: 14940.18 | R54: 14954.21 | S54: 14975.05 | T54: 14999.55 | U54: 15109.79 | V54: 15030.99 | W54: 15032.9 | X54: 15032.36 | Y54: 15041.65 | Z54: 15223.73 | AA54: 15036.15 | AB54: 15035.56 | AC54: 15032.29 | AD54: 15039.35 | AE54: 15264.51
A55: FiOS Total digital subscribers - SMB(K#) | B55: 457 | C55: 460 | D55: 460 | E55: 460 | F55: 460 | G55: 547.41 | H55: 506.59 | I55: 542.43 | J55: 546.03 | K55: 546.03 | L55: 565.55 | M55: 572.42 | N55: 577.85 | O55: 583.25 | P55: 566.87 | Q55: 561.71 | R55: 564.76 | S55: 568.55 | T55: 571.84 | U55: 608.3 | V55: 573.87 | W55: 576.38 | X55: 579.74 | Y55: 582.58 | Z55: 630.06 | AA55: 584.15 | AB55: 586.27 | AC55: 589.29 | AD55: 591.79 | AE55: 648.62
A56: FiOS Digital connections(K#) | B56: 13335.3 | C56: 13268.12 | D56: 13204.33 | E56: 13222.7 | F56: 13222.7 | G56: 15869.56 | H56: 15885.35 | I56: 15896.13 | J56: 15912.17 | K56: 15912.17 | L56: 16056.66 | M56: 16066.91 | N56: 16090.99 | O56: 16119.9 | P56: 15987.5 | Q56: 15469.23 | R56: 15467.4 | S56: 15463.08 | T56: 15464.8 | U56: 15687.95 | V56: 15454.58 | W56: 15442.63 | X56: 15424.35 | Y56: 15410.15 | Z56: 15685.88 | AA56: 15384.68 | AB56: 15366.8 | AC56: 15343.03 | AD56: 15324.68 | AE56: 15615.1
A58: Supplemental
A59: Broadband
A60: Wireline broadband subscribers - Consumer(K#) | B60: 7330 | C60: 7348 | D60: 7395 | E60: 7451 | F60: 7451 | G60: 10267.63 | H60: 10376.99 | I60: 10502.21 | J60: 10614.58 | K60: 10614.58 | L60: 11156.47 | M60: 11269.32 | N60: 11402.8 | O60: 11533.58 | P60: 11056.51 | Q60: 11576.59 | R60: 11693.63 | S60: 11817.89 | T60: 11948.67 | U60: 11525.25 | V60: 11973.13 | W60: 12080.56 | X60: 12185.8 | Y60: 12291.21 | Z60: 11888.49 | AA60: 12386.87 | AB60: 12491.59 | AC60: 12594.25 | AD60: 12698.22 | AE60: 12296.4
A61: FiOS Broadband subscribers - SMB(K#) | B61: 459 | C61: 458 | D61: 456 | E61: 452 | F61: 452 | G61: 580.36 | H61: 582.05 | I61: 570.62 | J61: 571.41 | K61: 571.41 | L61: 588.97 | M61: 592.62 | N61: 595.32 | O61: 598.27 | P61: 581.18 | Q61: 686.66 | R61: 688.35 | S61: 692.32 | T61: 695.84 | U61: 614.83 | V61: 682.94 | W61: 683.25 | X61: 684.59 | Y61: 686.49 | Z61: 620.98 | AA61: 687.1 | AB61: 687.92 | AC61: 689.76 | AD61: 691.64 | AE61: 640.05
A62: Total wireline broadband connections(K#) | B62: 7789 | C62: 7806 | D62: 7851 | E62: 7903 | F62: 7903 | G62: 11298.97 | H62: 10973.6 | I62: 11084.79 | J62: 11198.03 | K62: 11552.45 | L62: 11768.6 | M62: 11885.71 | N62: 12022.34 | O62: 12156.56 | P62: 11650.8 | Q62: 12263.25 | R62: 12381.98 | S62: 12510.2 | T62: 12644.51 | U62: 12140.08 | V62: 12656.07 | W62: 12763.81 | X62: 12870.39 | Y62: 12977.71 | Z62: 12509.47 | AA62: 13073.97 | AB62: 13179.51 | AC62: 13284.01 | AD62: 13389.85 | AE62: 12936.45
A63: Ending subscribers - Fixed wireless access (FWA) broadband(K#) | B63: 4845 | C63: 5112 | D63: 5391 | E63: 5727 | F63: 5727 | G63: 6006 | H63: 6208 | I63: 6400.19 | J63: 6635.66 | K63: 6635.66 | L63: 6811.75 | M63: 6996.51 | N63: 7185.67 | O63: 7398.22 | P63: 7441.25 | Q63: 7495.17 | R63: 7655.84 | S63: 7819.74 | T63: 7993.47 | U63: 8172.4 | V63: 7963.46 | W63: 8089.96 | X63: 8217.04 | Y63: 8341.21 | Z63: 8700.33 | AA63: 8445.73 | AB63: 8550.27 | AC63: 8655.17 | AD63: 8757.3 | AE63: 9189.53
A64: Broadband connections(K#) | B64: 12426 | C64: 12725 | D64: 13065 | E64: 13630 | F64: 13630 | G64: 16763 | H64: 17121 | I64: 17399.06 | J64: 17765.43 | K64: 18040.56 | L64: 18419.07 | M64: 18736.33 | N64: 19073.99 | O64: 19427.96 | P64: 19120.38 | Q64: 19574.44 | R64: 19866.15 | S64: 20165.41 | T64: 20456.13 | U64: 20364.84 | V64: 20595 | W64: 20838.81 | X64: 21082.47 | Y64: 21323.04 | Z64: 21388.08 | AA64: 21533.02 | AB64: 21749.98 | AC64: 21966.61 | AD64: 22180.79 | AE64: 22352.57
A65: Total Voice connections
A66: Net adds - Total voice connections(K#) | B66: -216.25 | C66: -211.3 | D66: -211.79 | E66: -215.19 | F66: -854.52 | G66: 297.79 | H66: 143.85 | I66: -171.46 | J66: -176.06 | K66: 94.12 | L66: -181.2 | M66: -177.46 | N66: -179 | O66: -183.24 | P66: -681.73 | Q66: -175.97 | R66: -172.58 | S66: -174.29 | T66: -178.2 | U66: -672.17 | V66: -172.47 | W66: -169.33 | X66: -171 | Y66: -174.32 | Z66: -670.96 | AA66: -169.73 | AB66: -166.41 | AC66: -167.91 | AD66: -170.73 | AE66: -669.45
A67: Total voice connections(K#) | B67: 5985.06 | C67: 5773.76 | D67: 5561.97 | E67: 5346.79 | F67: 5346.79 | G67: 5663.32 | H67: 5817.18 | I67: 5645.72 | J67: 5469.65 | K67: 5469.65 | L67: 5824.15 | M67: 5646.68 | N67: 5467.69 | O67: 5284.45 | P67: 4787.92 | Q67: 5108.48 | R67: 4935.9 | S67: 4761.61 | T67: 4583.41 | U67: 4115.75 | V67: 4410.94 | W67: 4241.61 | X67: 4070.61 | Y67: 3896.29 | Z67: 3444.79 | AA67: 3726.56 | AB67: 3560.15 | AC67: 3392.24 | AD67: 3221.51 | AE67: 2775.34

Sheet Wireless
A2: Verizon Communications Inc. | Wireless
A3: NYSE:VZ (MI KEY: 4057229; SPCIQ KEY: 415798)
A5: Visible Alpha
A7: Period Type : Fiscal Quarter, Fiscal Halves, Fiscal Year
A8: Period Start : 2025
A9: Period End : 2030
A10: Currency : Reported
A11: Consensus View : Mean
A12: As Of: 10/25/2026
A14: All numbers in $M unless otherwise indicated | B14: FQ1 2025A | C14: FQ2 2025A | D14: FQ3 2025A | E14: FQ4 2025A | F14: FY2025A | G14: FQ1 2026A | H14: FQ2 2026A | I14: FQ3 2026E | J14: FQ4 2026E | K14: FY2026E | L14: FQ1 2027E | M14: FQ2 2027E | N14: FQ3 2027E | O14: FQ4 2027E | P14: FY2027E | Q14: FQ1 2028E | R14: FQ2 2028E | S14: FQ3 2028E | T14: FQ4 2028E | U14: FY2028E | V14: FQ1 2029E | W14: FQ2 2029E | X14: FQ3 2029E | Y14: FQ4 2029E | Z14: FY2029E | AA14: FQ1 2030E | AB14: FQ2 2030E | AC14: FQ3 2030E | AD14: FQ4 2030E | AE14: FY2030E
A15: Number of Contributors Available | B15: 19 | C15: 19 | D15: 19 | E15: 19 | F15: 20 | G15: 20 | H15: 20 | I15: 20 of 20 | J15: 20 of 20 | K15: 20 of 20 | L15: 13 of 20 | M15: 13 of 20 | N15: 12 of 20 | O15: 12 of 20 | P15: 20 of 20 | Q15: 7 of 20 | R15: 7 of 20 | S15: 7 of 20 | T15: 7 of 20 | U15: 18 of 20 | V15: 5 of 20 | W15: 5 of 20 | X15: 5 of 20 | Y15: 5 of 20 | Z15: 14 of 20 | AA15: 5 of 20 | AB15: 5 of 20 | AC15: 5 of 20 | AD15: 5 of 20 | AE15: 14 of 20
A16: Retail Postpaid
A17: Beginning subs - Wireless retail postpaid(K#) | B17: 125937 | C17: 125744 | D17: 125895 | E17: 125913 | F17: 125937 | G17: 126705 | H17: 126499 | I17: 126642.48 | J17: 126862.01 | K17: 126705 | L17: 127620.66 | M17: 127566.47 | N17: 127744.51 | O17: 127901.62 | P17: 127664.17 | Q17: 128612.39 | R17: 128461.25 | S17: 128618.55 | T17: 128719.58 | U17: 128915.63 | V17: 129652.11 | W17: 129474.49 | X17: 129569.1 | Y17: 129704.4 | Z17: 130150.35 | AA17: 130417.85 | AB17: 130207.43 | AC17: 130265.07 | AD17: 130364.62 | AE17: 131162.53
A18: Gross adds - Wireless retail postpaid(K#) | B18: 4474 | C18: 4834 | D18: 4663 | E18: 5813 | F18: 19784 | G18: 4669.62 | H18: 4722.79 | I18: 4832.11 | J18: 5556.91 | K18: 19781.42 | L18: 4553.54 | M18: 4668.47 | N18: 4623.03 | O18: 5383.42 | P18: 19955.98 | Q18: 4478.19 | R18: 4613.39 | S18: 4506.65 | T18: 5292.52 | U18: 20016.72 | V18: 4382.14 | W18: 4417.62 | X18: 4521.31 | Y18: 5133.27 | Z18: 20126.11 | AA18: 4369.27 | AB18: 4395.94 | AC18: 4501.45 | AD18: 5107.33 | AE18: 20275.73
A19: Churn rate - Wireless retail postpaid(%) | B19: 1.23% | C19: 1.24% | D19: 1.23% | E19: 1.32% | F19: 1.25% | G19: 1.26% | H19: 1.19% | I19: 1.20% | J19: 1.24% | K19: 1.22% | L19: 1.22% | M19: 1.17% | N19: 1.18% | O19: 1.21% | P19: 1.21% | Q19: 1.22% | R19: 1.16% | S19: 1.18% | T19: 1.20% | U19: 1.21% | V19: 1.21% | W19: 1.14% | X19: 1.17% | Y19: 1.17% | Z19: 1.22% | AA19: 1.21% | AB19: 1.14% | AC19: 1.17% | AD19: 1.17% | AE19: 1.22%
A20: Disconnects - Wireless retail postpaid(K#) | B20: 4643.51 | C20: 4680.49 | D20: 4645.86 | E20: 5001.84 | F20: 18948.15 | G20: 4789.35 | H20: 4505.36 | I20: 4579.11 | J20: 4726.31 | K20: 18600.1 | L20: 4656.94 | M20: 4472.36 | N20: 4545.7 | O20: 4642.9 | P20: 18667.98 | Q20: 4705.73 | R20: 4450.73 | S20: 4528.99 | T20: 4610.88 | U20: 18899.13 | V20: 4661.15 | W20: 4384.37 | X20: 4511.42 | Y20: 4521.04 | Z20: 19128.05 | AA20: 4677.12 | AB20: 4398.84 | AC20: 4525.96 | AD20: 4535.74 | AE20: 19372.18
A21: Internal/Organic net adds - Wireless retail postpaid(K#) | B21: -159 | C21: 155 | D21: 36 | E21: 829 | F21: 861 | G21: -196 | H21: 188 | I21: 203.14 | J21: 803.58 | K21: 1019.82 | L21: -38.11 | M21: 184.45 | N21: 113.62 | O21: 777.66 | P21: 1240.55 | Q21: -136.33 | R21: 168.69 | S21: 23.37 | T21: 663.37 | U21: 1103.85 | V21: -149.53 | W21: 108.52 | X21: 39.88 | Y21: 654.56 | Z21: 1068.77 | AA21: -178.02 | AB21: 74.79 | AC21: 7.69 | AD21: 618.8 | AE21: 979.75
A22: Acquired net adds - Wireless retail postpaid(K#) | B22: -34 | C22: -4 | D22: -18 | E22: -37 | F22: -93 | G22: -10 | H22: -68 | I22: -102 | J22: - | K22: -80.75 | L22: - | M22: - | N22: - | O22: - | P22: - | Q22: - | R22: - | S22: - | T22: - | U22: - | V22: - | W22: - | X22: - | Y22: - | Z22: - | AA22: - | AB22: - | AC22: - | AD22: - | AE22: -
A23: Net adds - Wireless retail postpaid(K#) | B23: -193 | C23: 151 | D23: 18 | E23: 792 | F23: 768 | G23: -206 | H23: 120 | I23: 219.53 | J23: 802.17 | K23: 963.77 | L23: -54.19 | M23: 178.05 | N23: 157.11 | O23: 800.05 | P23: 1202.81 | Q23: -151.14 | R23: 157.3 | S23: 101.03 | T23: 711.32 | U23: 1065.95 | V23: -177.63 | W23: 94.61 | X23: 135.3 | Y23: 713.45 | Z23: 1012.18 | AA23: -210.42 | AB23: 57.63 | AC23: 99.56 | AD23: 674.84 | AE23: 921.16
A24: Wireless retail postpaid subscribers(K#) | B24: 125744 | C24: 125895 | D24: 125913 | E24: 126705 | F24: 126705 | G24: 126499 | H24: 126619 | I24: 126862.01 | J24: 127664.17 | K24: 127664.17 | L24: 127566.47 | M24: 127744.51 | N24: 127901.62 | O24: 128701.67 | P24: 128866.99 | Q24: 128461.25 | R24: 128618.55 | S24: 128719.58 | T24: 129430.9 | U24: 129954.59 | V24: 129474.49 | W24: 129569.1 | X24: 129704.4 | Y24: 130417.85 | Z24: 131162.53 | AA24: 130207.43 | AB24: 130265.07 | AC24: 130364.62 | AD24: 131039.46 | AE24: 132083.69
A25: Wireless retail postpaid average subscribers(K#) | B25: 125840.5 | C25: 125819.5 | D25: 125904 | E25: 126309 | F25: 126321 | G25: 126602 | H25: 126559 | I25: 126752.24 | J25: 127263.09 | K25: 127046.53 | L25: 127593.56 | M25: 127655.49 | N25: 127823.07 | O25: 128301.65 | P25: 128213.84 | Q25: 128536.82 | R25: 128539.9 | S25: 128669.07 | T25: 129075.24 | U25: 129387.28 | V25: 129563.3 | W25: 129521.8 | X25: 129636.75 | Y25: 130061.13 | Z25: 130618.27 | AA25: 130312.64 | AB25: 130236.25 | AC25: 130314.84 | AD25: 130702.04 | AE25: 131585.96
A26: ARPU - Wireless retail postpaid($) | B26: 46.92 | C26: 47.03 | D26: 46.89 | E26: 46.58 | F26: 46.89 | G26: 45.33 | H26: 45.63 | I26: 46.53 | J26: 46.59 | K26: 46 | L26: 46.28 | M26: 46.3 | N26: 46.67 | O26: 46.71 | P26: 45.96 | Q26: 45.83 | R26: 45.83 | S26: 46.27 | T26: 46.29 | U26: 46.25 | V26: 45.63 | W26: 45.48 | X26: 46.04 | Y26: 46.11 | Z26: 46.19 | AA26: 45.61 | AB26: 45.46 | AC26: 46.02 | AD26: 46.09 | AE26: 46.16
A27: Postpaid service revenue | B27: 17714.15 | C27: 17764.38 | D27: 17756.25 | E27: 17649.43 | F27: 70884.21 | G27: 17215.56 | H27: 17324.73 | I27: 17565.08 | J27: 17660.22 | K27: 69902.11 | L27: 17542.62 | M27: 17564.78 | N27: 17740.05 | O27: 17827.87 | P27: 70624.41 | Q27: 17677.95 | R27: 17683.18 | S27: 17867.16 | T27: 17933.42 | U27: 71351.39 | V27: 17757.46 | W27: 17697.43 | X27: 17929.02 | Y27: 18017.78 | Z27: 71995.82 | AA27: 17859.38 | AB27: 17795.81 | AC27: 18024.33 | AD27: 18107.71 | AE27: 72664.6
A28: Postpaid upgrade rate
A29: Retail postpaid upgrade rate(%) | B29: 2.80% | C29: 3.60% | D29: 3.30% | E29: 4.40% | F29: 14.49% | G29: 3.00% | H29: 2.60% | I29: 2.93% | J29: 4.04% | K29: 12.92% | L29: 3.02% | M29: 2.84% | N29: 2.93% | O29: 4.00% | P29: 11.81% | Q29: 3.06% | R29: 2.92% | S29: 2.87% | T29: 3.94% | U29: 13.03% | V29: 3.05% | W29: 2.70% | X29: 2.72% | Y29: 3.75% | Z29: 12.64% | AA29: 3.05% | AB29: 2.69% | AC29: 2.71% | AD29: 3.74% | AE29: 12.65%
A30: Postpaid handset upgrades(K#) | B30: 3417.08 | C30: 4441.39 | D30: 4058.83 | E30: 5494.95 | F30: 17412.25 | G30: 3684.98 | H30: 3371.08 | I30: 3537.73 | J30: 5024.08 | K30: 15617.87 | L30: 3738.76 | M30: 3653.07 | N30: 3600.34 | O30: 4983.7 | P30: 15974.76 | Q30: 3791.41 | R30: 3761.95 | S30: 3550.84 | T30: 4958.67 | U30: 16212.3 | V30: 4096.58 | W30: 3765.11 | X30: 3596.61 | Y30: 5058.59 | Z30: 16550.43 | AA30: 4115.28 | AB30: 3778.26 | AC30: 3613.43 | AD30: 5078.35 | AE30: 16687.86
A31: Gross adds - Wireless retail postpaid(K#) | B31: 4474 | C31: 4834 | D31: 4663 | E31: 5813 | F31: 19784 | G31: 4669.62 | H31: 4722.79 | I31: 4832.11 | J31: 5556.91 | K31: 19781.42 | L31: 4553.54 | M31: 4668.47 | N31: 4623.03 | O31: 5383.42 | P31: 19955.98 | Q31: 4478.19 | R31: 4613.39 | S31: 4506.65 | T31: 5292.52 | U31: 20016.72 | V31: 4382.14 | W31: 4417.62 | X31: 4521.31 | Y31: 5133.27 | Z31: 20126.11 | AA31: 4369.27 | AB31: 4395.94 | AC31: 4501.45 | AD31: 5107.33 | AE31: 20275.73
A32: Total Postpaid Device Sales(K#) | B32: 7875.97 | C32: 9265.23 | D32: 8719.83 | E32: 11298.37 | F32: 37159.41 | G32: 8340.55 | H32: 8134.79 | I32: 8361.67 | J32: 10582.33 | K32: 35419.34 | L32: 8325.42 | M32: 8432.44 | N32: 8185.08 | O32: 10295.1 | P32: 35952.44 | Q32: 8207.92 | R32: 8426.66 | S32: 7851.96 | T32: 10034.5 | U32: 36266.31 | V32: 8461.87 | W32: 8156.09 | X32: 7827.73 | Y32: 9826.32 | Z32: 36794.51 | AA32: 8451.04 | AB32: 8141.52 | AC32: 7817.16 | AD32: 9811.03 | AE32: 37103.17
A34: Retail Prepaid
A35: Beginning subs - Retail prepaid(K#) | B35: 20138 | C35: 20230 | D35: 20241 | E35: 20206 | F35: 20138 | G35: 20225 | H35: 20299 | I35: 19983.02 | J35: 19987.48 | K35: 19841 | L35: 19967.25 | M35: 20057.68 | N35: 20103.24 | O35: 20106.99 | P35: 20020.82 | Q35: 20311.04 | R35: 20369.01 | S35: 20387.94 | T35: 20362.6 | U35: 20225.77 | V35: 20131.3 | W35: 20161.66 | X35: 20166.03 | Y35: 20141.34 | Z35: 20214.56 | AA35: 20137.32 | AB35: 20116.87 | AC35: 20101.69 | AD35: 20103.48 | AE35: 20277.48
A36: Gross adds - Retail prepaid(K#) | B36: 2284.43 | C36: 2308.34 | D36: 2334.26 | E36: 2361.04 | F36: 9460.13 | G36: 2207.34 | H36: 2271.17 | I36: 2258.65 | J36: 2316.18 | K36: 9061.23 | L36: 2237.28 | M36: 2286.49 | N36: 2272.32 | O36: 2325.05 | P36: 8996.19 | Q36: 2305.84 | R36: 2353.32 | S36: 2323.3 | T36: 2396.45 | U36: 8999.97 | V36: 2247.55 | W36: 2309.09 | X36: 2258.89 | Y36: 2340.57 | Z36: 8816.87 | AA36: 2185.41 | AB36: 2271.85 | AC36: 2271.98 | AD36: 2352.46 | AE36: 8754.75
A37: Churn rate - Retail prepaid(%) | B37: 3.58% | C37: 3.98% | D37: 3.73% | E37: 3.93% | F37: 4.00% | G37: 3.45% | H37: 3.59% | I37: 3.77% | J37: 3.82% | K37: 3.72% | L37: 3.59% | M37: 3.74% | N37: 3.77% | O37: 3.83% | P37: 3.67% | Q37: 3.67% | R37: 3.81% | S37: 3.82% | T37: 3.83% | U37: 3.65% | V37: 3.67% | W37: 3.81% | X37: 3.77% | Y37: 3.88% | Z37: 3.62% | AA37: 3.65% | AB37: 3.79% | AC37: 3.76% | AD37: 3.87% | AE37: 3.59%
A38: Disconnects - Retail prepaid(K#) | B38: 2021.43 | C38: 2268.34 | D38: 2289.26 | E38: 2254.04 | F38: 9134.13 | G38: 2118.74 | H38: 2223.09 | I38: 2255.74 | J38: 2285.96 | K38: 8883.52 | L38: 2140.57 | M38: 2236.29 | N38: 2259.27 | O38: 2292.77 | P38: 8838.18 | Q38: 2242.09 | R38: 2329.87 | S38: 2338 | T38: 2341.48 | U38: 8896.22 | V38: 2217.19 | W38: 2304.73 | X38: 2283.58 | Y38: 2344.59 | Z38: 8784.24 | AA38: 2205.86 | AB38: 2287.03 | AC38: 2270.19 | AD38: 2334.01 | AE38: 8737.68
A39: Internal/Organic net adds - Retail prepaid(K#) | B39: 94 | C39: 22 | D39: -34 | E39: 22 | F39: 104 | G39: 80 | H39: 35 | I39: 4.47 | J39: 33.34 | K39: 183.09 | L39: 105.5 | M39: 53.16 | N39: 4.37 | O39: 32.68 | P39: 174.29 | Q39: 57.97 | R39: 18.93 | S39: -25.34 | T39: 41.65 | U39: 108.61 | V39: 30.37 | W39: 4.36 | X39: -24.69 | Y39: -4.02 | Z39: 62.92 | AA39: -20.44 | AB39: -15.18 | AC39: 1.79 | AD39: 18.45 | AE39: 46.18
A40: Acquired net adds - Retail prepaid(K#) | B40: -2.25 | C40: -7.17 | D40: -0.83 | E40: -1.83 | F40: -17 | G40: -1.33 | H40: -1 | I40: - | J40: - | K40: -3.6 | L40: - | M40: - | N40: - | O40: - | P40: - | Q40: - | R40: - | S40: - | T40: - | U40: - | V40: - | W40: - | X40: - | Y40: - | Z40: - | AA40: - | AB40: - | AC40: - | AD40: - | AE40: -
A41: Net adds - Retail prepaid(K#) | B41: 92 | C41: 11 | D41: -35 | E41: 19 | F41: 87 | G41: 94.86 | H41: 35 | I41: 4.47 | J41: 33.34 | K41: 181.46 | L41: 105.5 | M41: 53.16 | N41: 4.37 | O41: 32.68 | P41: 174.29 | Q41: 57.97 | R41: 18.93 | S41: -25.34 | T41: 41.65 | U41: 108.61 | V41: 30.37 | W41: 4.36 | X41: -24.69 | Y41: -4.02 | Z41: 62.92 | AA41: -20.44 | AB41: -15.18 | AC41: 1.79 | AD41: 18.45 | AE41: 46.18
A42: Retail prepaid subscribers(K#) | B42: 20230 | C42: 20241 | D42: 20206 | E42: 20225 | F42: 20225 | G42: 20299 | H42: 20334 | I42: 19987.48 | J42: 20020.82 | K42: 20020.82 | L42: 20057.68 | M42: 20103.24 | N42: 20106.99 | O42: 20135 | P42: 20179.27 | Q42: 20369.01 | R42: 20387.94 | S42: 20362.6 | T42: 20404.25 | U42: 20334.38 | V42: 20161.66 | W42: 20166.03 | X42: 20141.34 | Y42: 20137.32 | Z42: 20277.48 | AA42: 20116.87 | AB42: 20101.69 | AC42: 20103.48 | AD42: 20121.93 | AE42: 20323.66
A43: Retail prepaid average subscribers(K#) | B43: 20184 | C43: 20235.5 | D43: 20223.5 | E43: 20215.5 | F43: 20181.5 | G43: 20262 | H43: 20316.5 | I43: 19985.25 | J43: 20004.15 | K43: 19943.54 | L43: 20012.46 | M43: 20080.46 | N43: 20105.11 | O43: 20120.99 | P43: 20105.75 | Q43: 20340.02 | R43: 20378.47 | S43: 20375.27 | T43: 20383.42 | U43: 20284.49 | V43: 20146.48 | W43: 20163.85 | X43: 20153.68 | Y43: 20139.33 | Z43: 20251.36 | AA43: 20127.09 | AB43: 20109.28 | AC43: 20102.59 | AD43: 20112.71 | AE43: 20293.49
A44: ARPU - Retail prepaid($) | B44: 31.92 | C44: 32.56 | D44: 32.7 | E44: 32.9 | F44: 32.52 | G44: 33.31 | H44: 33.37 | I44: 32.88 | J44: 33.21 | K44: 32.88 | L44: 33.79 | M44: 33.88 | N44: 33.94 | O44: 34.26 | P44: 33.47 | Q44: 33.17 | R44: 33.23 | S44: 33.09 | T44: 33.3 | U44: 33.4 | V44: 33.22 | W44: 33.29 | X44: 33.15 | Y44: 33.35 | Z44: 33.69 | AA44: 33.28 | AB44: 33.35 | AC44: 33.2 | AD44: 33.41 | AE44: 33.97
A45: Prepaid service revenue | B45: 1810.82 | C45: 1855.63 | D45: 1867.77 | E45: 1886.7 | F45: 7420.92 | G45: 1921.05 | H45: 1933.62 | I45: 1960.84 | J45: 1981.71 | K45: 7822.89 | L45: 2011.7 | M45: 2023.48 | N45: 2031.79 | O45: 2051.04 | P45: 8031.76 | Q45: 2031.02 | R45: 2037.98 | S45: 2034.23 | T45: 2046.21 | U45: 8113.05 | V45: 2056.85 | W45: 2062.23 | X45: 2056.96 | Y45: 2067.48 | Z45: 8230.6 | AA45: 2075.1 | AB45: 2076.41 | AC45: 2070.09 | AD45: 2081.11 | AE45: 8326.33
A46: Wireless Retail (Postpaid+Prepaid)
A47: Beginning subs - Retail(K#) | B47: 146075 | C47: 145974 | D47: 146136 | E47: 146119 | F47: 146075 | G47: 146930 | H47: 146798 | I47: 146988.28 | J47: 147106.68 | K47: 146842 | L47: 147825.06 | M47: 147802.84 | N47: 148014.12 | O47: 148107.94 | P47: 147935.35 | Q47: 148758.72 | R47: 148601.63 | S47: 148747.97 | T47: 148716.16 | U47: 149246.43 | V47: 149191.77 | W47: 148942.19 | X47: 148980.5 | Y47: 148965.32 | Z47: 150609.84 | AA47: 149576.94 | AB47: 149247.57 | AC47: 149229.86 | AD47: 149206.45 | AE47: 151659.85
A48: Gross adds - Retail(K#) | B48: 6768.95 | C48: 7143.82 | D48: 7016.12 | E48: 8191.88 | F48: 29269.28 | G48: 6882.35 | H48: 7030.94 | I48: 7121.23 | J48: 7900.79 | K48: 28945.44 | L48: 6796.15 | M48: 7009.86 | N48: 6898.48 | O48: 7724.33 | P48: 29065.68 | Q48: 6784.03 | R48: 6966.71 | S48: 6829.95 | T48: 7688.97 | U48: 29138 | V48: 6629.7 | W48: 6726.71 | X48: 6780.2 | Y48: 7473.84 | Z48: 29156.97 | AA48: 6554.68 | AB48: 6667.8 | AC48: 6773.43 | AD48: 7459.79 | AE48: 29291.09
A49: Churn rate - Retail(%) | B49: 1.56% | C49: 1.59% | D49: 1.60% | E49: 1.67% | F49: 1.60% | G49: 1.58% | H49: 1.54% | I49: 1.56% | J49: 1.59% | K49: 1.57% | L49: 1.56% | M49: 1.53% | N49: 1.55% | O49: 1.56% | P49: 1.55% | Q49: 1.56% | R49: 1.52% | S49: 1.54% | T49: 1.55% | U49: 1.55% | V49: 1.54% | W49: 1.50% | X49: 1.52% | Y49: 1.53% | Z49: 1.54% | AA49: 1.54% | AB49: 1.49% | AC49: 1.52% | AD49: 1.53% | AE49: 1.55%
A50: Disconnects - Retail(K#) | B50: 6833.95 | C50: 6966.82 | D50: 7014.12 | E50: 7340.88 | F50: 28304.28 | G50: 6980.83 | H50: 6788.83 | I50: 6889.35 | J50: 7038.36 | K50: 27697.37 | L50: 6910.81 | M50: 6791.34 | N50: 6864.86 | O50: 6940.14 | P50: 27679.06 | Q50: 6948.46 | R50: 6779.87 | S50: 6867.08 | T50: 6949.52 | U50: 27900.08 | V50: 6879.27 | W50: 6688.41 | X50: 6795.38 | Y50: 6862.23 | Z50: 28032.12 | AA50: 6884.05 | AB50: 6685.5 | AC50: 6796.83 | AD50: 6866.72 | AE50: 28264.17
A51: Internal/Organic net adds - Retail(K#) | B51: -65 | C51: 177 | D51: 2 | E51: 851 | F51: 965 | G51: -116 | H51: 223 | I51: 217.56 | J51: 809.17 | K51: 1162.95 | L51: -52.34 | M51: 199.49 | N51: 87.56 | O51: 730.9 | P51: 1249.51 | Q51: -157.1 | R51: 146.34 | S51: -31.81 | T51: 675.52 | U51: 1109.2 | V51: -249.57 | W51: 38.31 | X51: -15.18 | Y51: 611.62 | Z51: 1039.73 | AA51: -329.37 | AB51: -17.71 | AC51: -23.41 | AD51: 593.07 | AE51: 953.97
A52: Acquired net adds - Retail(K#) | B52: -36 | C52: -15 | D52: -19 | E52: -40 | F52: -110 | G52: -16 | H52: -68 | I52: -542.5 | J52: - | K52: -85.1 | L52: - | M52: - | N52: - | O52: - | P52: - | Q52: - | R52: - | S52: - | T52: - | U52: - | V52: - | W52: - | X52: - | Y52: - | Z52: - | AA52: - | AB52: - | AC52: - | AD52: - | AE52: -
A53: Net adds - Retail(K#) | B53: -101 | C53: 162 | D53: -17 | E53: 811 | F53: 855 | G53: -132 | H53: 155 | I53: 118.4 | J53: 828.67 | K53: 1093.35 | L53: -22.22 | M53: 211.29 | N53: 93.82 | O53: 766.55 | P53: 1288.71 | Q53: -157.1 | R53: 146.34 | S53: -31.81 | T53: 675.52 | U53: 1136.41 | V53: -249.57 | W53: 38.31 | X53: -15.18 | Y53: 611.62 | Z53: 1050.01 | AA53: -329.37 | AB53: -17.71 | AC53: -23.41 | AD53: 593.07 | AE53: 946.79
A54: Retail connections(K#) | B54: 145974 | C54: 146136 | D54: 146119 | E54: 146930 | F54: 146930 | G54: 146798 | H54: 146953 | I54: 147106.68 | J54: 147935.35 | K54: 147935.35 | L54: 147802.84 | M54: 148014.12 | N54: 148107.94 | O54: 148874.48 | P54: 149224.06 | Q54: 148601.63 | R54: 148747.97 | S54: 148716.16 | T54: 149391.68 | U54: 150426.18 | V54: 148942.19 | W54: 148980.5 | X54: 148965.32 | Y54: 149576.94 | Z54: 151659.85 | AA54: 149247.57 | AB54: 149229.86 | AC54: 149206.45 | AD54: 149799.52 | AE54: 152606.64
A55: Retail average subscribers(K#) | B55: 146024.5 | C55: 146055 | D55: 146127.5 | E55: 146524.5 | F55: 146502.5 | G55: 146864 | H55: 146875.5 | I55: 147047.48 | J55: 147521.01 | K55: 147293.61 | L55: 147813.95 | M55: 147908.48 | N55: 148061.03 | O55: 148491.21 | P55: 148532.82 | Q55: 148680.18 | R55: 148674.8 | S55: 148732.07 | T55: 149053.92 | U55: 149833.12 | V55: 149066.98 | W55: 148961.34 | X55: 148972.91 | Y55: 149271.13 | Z55: 151105.97 | AA55: 149412.25 | AB55: 149238.71 | AC55: 149218.15 | AD55: 149502.99 | AE55: 152093.87
A56: ARPU - Retail service($) | B56: 44.57 | C56: 44.78 | D56: 44.76 | E56: 45.29 | F56: 45.49 | G56: 44.39 | H56: 44.74 | I56: 45.01 | J56: 45.14 | K56: 44.76 | L56: 45.22 | M56: 45.3 | N56: 45.62 | O56: 45.82 | P56: 44.81 | Q56: 46.22 | R56: 46.29 | S56: 46.63 | T56: 46.92 | U56: 44.89 | V56: 46.29 | W56: 46.03 | X56: 46.46 | Y56: 47.03 | Z56: 44.59 | AA56: 46.61 | AB56: 46.3 | AC56: 46.73 | AD56: 47.32 | AE56: 44.68
A57: Retail service revenue | B57: 19524.98 | C57: 19620.01 | D57: 19624.02 | E57: 19536.13 | F57: 79555.32 | G57: 19511.5 | H57: 19666.32 | I57: 19812.38 | J57: 19945.53 | K57: 78977.37 | L57: 19985.21 | M57: 20051.62 | N57: 20207.87 | O57: 20362.25 | P57: 79895.3 | Q57: 20442.13 | R57: 20512.19 | S57: 20665.72 | T57: 20835.87 | U57: 80876.07 | V57: 20510.26 | W57: 20474.98 | X57: 20643.16 | Y57: 20889.76 | Z57: 81161.13 | AA57: 20726.37 | AB57: 20667.2 | AC57: 20829.21 | AD57: 21076.43 | AE57: 81977.41
A58: Wireless financials
A59: Wireless service revenue - Consumer | B59: 17199 | C59: 17369 | D59: 17441 | E59: 17373 | F59: 69382 | G59: 17151.76 | H59: 17296.89 | I59: 17390.38 | J59: 17493.12 | K59: 69336.43 | L59: 17398.87 | M59: 17504.36 | N59: 17602.83 | O59: 17699.97 | P59: 70276.33 | Q59: 17480.09 | R59: 17625.02 | S59: 17725.56 | T59: 17816.32 | U59: 71311.93 | V59: 17606.75 | W59: 17728.14 | X59: 17807.1 | Y59: 17937.62 | Z59: 72361.27 | AA59: 17729.32 | AB59: 17844.54 | AC59: 17920.51 | AD59: 18049.14 | AE59: 73182.59
A60: Wireless service revenue - Business | B60: 3565 | C60: 3579 | D60: 3588 | E60: 3589 | F60: 14321 | G60: 3541.58 | H60: 3544.35 | I60: 3569.7 | J60: 3581.78 | K60: 14255.95 | L60: 3583.86 | M60: 3578.18 | N60: 3605.67 | O60: 3636.55 | P60: 14408.88 | Q60: 3605.43 | R60: 3564.62 | S60: 3587.2 | T60: 3616.2 | U60: 14499.75 | V60: 3589.07 | W60: 3480.94 | X60: 3515.2 | Y60: 3566.91 | Z60: 14579.67 | AA60: 3604.72 | AB60: 3477.18 | AC60: 3509.98 | AD60: 3567.54 | AE60: 14715.58
A61: Service revenue - Wireless | B61: 20764 | C61: 20948 | D61: 21029 | E61: 20962 | F61: 83703 | G61: 20677.98 | H61: 20823.16 | I61: 20957.96 | J61: 21067.45 | K61: 83532.34 | L61: 20966.39 | M61: 21081.17 | N61: 21223.11 | O61: 21339.22 | P61: 84669.94 | Q61: 21151.73 | R61: 21261.83 | S61: 21390.83 | T61: 21497.96 | U61: 85906.9 | V61: 21356.11 | W61: 21402.14 | X61: 21525.46 | Y61: 21671.77 | Z61: 87090.93 | AA61: 21541.5 | AB61: 21569.35 | AC61: 21688.79 | AD61: 21837.41 | AE61: 88117.71
A62: Wireless equipment revenue - Consumer | B62: 4532 | C62: 5369 | D62: 4766 | E62: 7112 | F62: 21779 | G62: 4824 | H62: 4178 | I62: 4778.46 | J62: 6978.87 | K62: 21481.4 | L62: 5045.64 | M62: 5066.07 | N62: 4824.4 | O62: 7190.74 | P62: 22419.81 | Q62: 5277.6 | R62: 5284.66 | S62: 4929.9 | T62: 7508.37 | U62: 23249.09 | V62: 5309 | W62: 4707.65 | X62: 4782.18 | Y62: 7030.12 | Z62: 23109.25 | AA62: 5398.91 | AB62: 4786.25 | AC62: 4859.58 | AD62: 7150.06 | AE62: 23550.12
A63: Wireless equipment revenue - Business | B63: 866 | C63: 886 | D63: 853 | E63: 1086 | F63: 3691 | G63: 857 | H63: 846 | I63: 849.03 | J63: 1070.37 | K63: 3547.68 | L63: 960.61 | M63: 883.45 | N63: 866.54 | O63: 1074.15 | P63: 3700.47 | Q63: 935.27 | R63: 943.22 | S63: 891.82 | T63: 1139.6 | U63: 3936.23 | V63: 940.35 | W63: 914.03 | X63: 876.71 | Y63: 1058.21 | Z63: 3947.48 | AA63: 956.46 | AB63: 928.28 | AC63: 890.93 | AD63: 1076.6 | AE63: 4018.7
A64: Wireless equipment revenues | B64: 5398 | C64: 6255 | D64: 5619 | E64: 8198 | F64: 25470 | G64: 5681 | H64: 5024 | I64: 5444.78 | J64: 7798.8 | K64: 23942.47 | L64: 5909.46 | M64: 5441.35 | N64: 5551.61 | O64: 7926.31 | P64: 24821.18 | Q64: 6063.63 | R64: 5735.04 | S64: 5643.93 | T64: 8158.98 | U64: 25342.68 | V64: 6123.01 | W64: 5460.13 | X64: 5526.68 | Y64: 7893.21 | Z64: 25100.87 | AA64: 6212.16 | AB64: 5537.56 | AC64: 5603.24 | AD64: 8006.64 | AE64: 25426.3
A65: Other revenue - Wireless | B65: 1014 | C65: 1021 | D65: 996 | E65: 1085 | F65: 4116 | G65: 1038.97 | H65: 1119.58 | I65: 922.33 | J65: 1100.83 | K65: 4015.76 | L65: 821.88 | M65: 800.08 | N65: 808.37 | O65: 863.19 | P65: 3727.36 | Q65: 707.06 | R65: 682.5 | S65: 673.18 | T65: 727.59 | U65: 3818.82 | V65: 1065.05 | W65: 1044.63 | X65: 1018.72 | Y65: 1102.53 | Z65: 4479.07 | AA65: 1070.33 | AB65: 1050.25 | AC65: 1023.9 | AD65: 1108.17 | AE65: 4584.2
A66: Wireless revenue | B66: 26162 | C66: 27203 | D66: 27644 | E66: 30245 | F66: 113289 | G66: 26795.17 | H66: 26373.57 | I66: 26957.3 | J66: 29477.29 | K66: 107243.87 | L66: 27265.71 | M66: 26761.88 | N66: 27171.66 | O66: 29625.26 | P66: 111518.32 | Q66: 27595.64 | R66: 27092.99 | S66: 27407.11 | T66: 29877.86 | U66: 113619.36 | V66: 28051.05 | W66: 27457.98 | X66: 27668.44 | Y66: 30308.34 | Z66: 115274.02 | AA66: 28334.42 | AB66: 27711.45 | AC66: 27917.54 | AD66: 30601.41 | AE66: 116617.9
A67: Cost of services - Wireless | B67: 3210.93 | C67: 3160.09 | D67: 3212.48 | E67: 3244.45 | F67: 12827.95 | G67: 3089.19 | H67: 3000.26 | I67: 3073.35 | J67: 3086.94 | K67: 12249.74 | L67: 2888.09 | M67: 2749.41 | N67: 2843.48 | O67: 2836.24 | P67: 12394.17 | Q67: 3183.77 | R67: 2893.76 | S67: 3072.83 | T67: 3046.89 | U67: 12611.84 | V67: 3239.98 | W67: 2947.8 | X67: 3128.14 | Y67: 3101.29 | Z67: 12829.89 | AA67: 3297.46 | AB67: 3003.21 | AC67: 3184.97 | AD67: 3157.44 | AE67: 13048.86
A68: Cost of equipment - Wireless | B68: 6106 | C68: 7007 | D68: 6483 | E68: 9380 | F68: 28976 | G68: 6506 | H68: 5859 | I68: 6275.72 | J68: 9075.89 | K68: 27919.36 | L68: 6758.31 | M68: 6405.62 | N68: 6371.7 | O68: 9168.09 | P68: 28679.86 | Q68: 7110.58 | R68: 7116.03 | S68: 6466.26 | T68: 9626.8 | U68: 29310.17 | V68: 7009.84 | W68: 6298.56 | X68: 6067.17 | Y68: 8693.53 | Z68: 28932.91 | AA68: 7087.52 | AB68: 6368.52 | AC68: 6129.95 | AD68: 8790.53 | AE68: 29344.02
A69: Cost of sales - Wireless | B69: 9316.93 | C69: 10167.09 | D69: 9695.48 | E69: 12624.45 | F69: 41803.95 | G69: 9594.53 | H69: 8860.59 | I69: 9147.74 | J69: 12017.31 | K69: 39620.17 | L69: 9699.67 | M69: 9086.5 | N69: 8918.26 | O69: 11329.35 | P69: 40442.44 | Q69: 10474.43 | R69: 9527.31 | S69: 9381.87 | T69: 12402.47 | U69: 41315.01 | V69: 10663.39 | W69: 9727.26 | X69: 9582.25 | Y69: 12662.25 | Z69: 42066.58 | AA69: 10904.53 | AB69: 9950.24 | AC69: 9794.44 | AD69: 12954.88 | AE69: 42813.22
A70: SG&A - Wireless | B70: 5909.67 | C70: 5927.56 | D70: 5942.31 | E70: 6570.73 | F70: 24350.28 | G70: 6004.12 | H70: 5760.29 | I70: 6304.06 | J70: 7002.2 | K70: 25070.67 | L70: 5901.96 | M70: 5194.46 | N70: 5916.08 | O70: 6596.14 | P70: 25424.62 | Q70: 5924.78 | R70: 5211.24 | S70: 5937.43 | T70: 6620.11 | U70: 25998.73 | V70: 5942.65 | W70: 5224.14 | X70: 5955.36 | Y70: 6641.65 | Z70: 26548.08 | AA70: 5959.31 | AB70: 5236.05 | AC70: 5972.55 | AD70: 6662.96 | AE70: 27092.22
A71: Operations and support - Wireless | B71: 15417.51 | C71: 16284.16 | D71: 15827.32 | E71: 19386.18 | F71: 66915.17 | G71: 15783.76 | H71: 14812.15 | I71: 15716.18 | J71: 19285.02 | K71: 65597.11 | L71: 16138.25 | M71: 14598.04 | N71: 15185.62 | O71: 18767.31 | P71: 67594.78 | Q71: 16399.21 | R71: 14738.55 | S71: 15319.29 | T71: 19022.58 | U71: 69227.53 | V71: 16606.04 | W71: 14951.4 | X71: 15537.61 | Y71: 19303.9 | Z71: 70940.51 | AA71: 16863.84 | AB71: 15186.29 | AC71: 15766.99 | AD71: 19617.84 | AE71: 72661.83
A72: Depreciation and amortization - Wireless | B72: 2776.65 | C72: 2797.68 | D72: 2808.54 | E72: 2758.9 | F72: 11141.77 | G72: 2911.68 | H72: 2858.66 | I72: 2867.16 | J72: 2865.03 | K72: 11565.36 | L72: - | M72: - | N72: - | O72: - | P72: 11589.92 | Q72: - | R72: - | S72: - | T72: - | U72: 11608.72 | V72: - | W72: - | X72: - | Y72: - | Z72: 11621.11 | AA72: - | AB72: - | AC72: - | AD72: - | AE72: 11626.23
A73: Total operating expenses -Wireless | B73: 17747.73 | C73: 18502.71 | D73: 18188.66 | E73: 21517.57 | F73: 75956.67 | G73: 17779.18 | H73: 17196.82 | I73: 19157.2 | J73: 22565.89 | K73: 78970.81 | L73: - | M73: - | N73: - | O73: - | P73: 80952.16 | Q73: - | R73: - | S73: - | T73: - | U73: 83365.49 | V73: - | W73: - | X73: - | Y73: - | Z73: 85797.32 | AA73: - | AB73: - | AC73: - | AD73: - | AE73: 88114.48
A74: Operating income/(loss) - Wireless | B74: 9428.27 | C74: 9721.29 | D74: 9455.34 | E74: 8727.43 | F74: 37332.33 | G74: 9539.06 | H74: 9626.88 | I74: 8244.8 | J74: 7400.77 | K74: 32683.98 | L74: - | M74: - | N74: - | O74: - | P74: 32200.18 | Q74: - | R74: - | S74: - | T74: - | U74: 31390.74 | V74: - | W74: - | X74: - | Y74: - | Z74: 30533.45 | AA74: - | AB74: - | AC74: - | AD74: - | AE74: 29631.81
A75: Adjusted EBITDA - Wireless | B75: 12107.02 | C75: 12396.08 | D75: 12263.33 | E75: 11412.14 | F75: 48178.58 | G75: 12241.34 | H75: 12603.74 | I75: 12027.49 | J75: 11387.19 | K75: 44676.15 | L75: 6238.3 | M75: 12999.2 | N75: 12591.92 | O75: 11985.79 | P75: 45251.76 | Q75: 12413.66 | R75: 13305.57 | S75: 12645.05 | T75: 11899.1 | U75: 48933.04 | V75: 12509.99 | W75: 13407.82 | X75: 12740.92 | Y75: 11981.44 | Z75: 49183.36 | AA75: 12595.67 | AB75: 13502.95 | AC75: 12832.36 | AD75: 12058.37 | AE75: 49329.15
A76: Capital expenditures - Wireless | B76: 2578.73 | C76: 2444.27 | D76: 2680.13 | E76: 3044.95 | F76: 10748.08 | G76: 2403.54 | H76: 2315.73 | I76: 2216.56 | J76: 2264.18 | K76: 9200.01 | L76: 2383.39 | M76: 2320.8 | N76: 2268.93 | O76: 2272.66 | P76: 9304.13 | Q76: 2698.15 | R76: 2704.83 | S76: 2727.25 | T76: 2732.63 | U76: 9486.86 | V76: 2584.22 | W76: 2555.76 | X76: 2588.45 | Y76: 2606.22 | Z76: 9354.2 | AA76: 2604.79 | AB76: 2576.41 | AC76: 2609.32 | AD76: 2626.73 | AE76: 9425.78
A77: Other Wireless metrics
A78: Net adds - Retail postpaid accounts(K#) | B78: -174 | C78: -50 | D78: -176 | E78: 26 | F78: -353 | G78: -127 | H78: -132 | I78: 50.97 | J78: 94.02 | K78: -84.29 | L78: -65.78 | M78: -56.57 | N78: 30.05 | O78: 118.07 | P78: 44.79 | Q78: -41.3 | R78: -73.76 | S78: 37.1 | T78: 109.49 | U78: 110.97 | V78: -41.6 | W78: -106.42 | X78: 34.95 | Y78: 92.51 | Z78: 105.86 | AA78: -49.55 | AB78: -115.2 | AC78: 27.11 | AD78: 82.72 | AE78: 93.3
A79: Retail postpaid accounts(K#) | B79: 34696 | C79: 34646 | D79: 34470 | E79: 34496 | F79: 34496 | G79: 34369 | H79: 34237 | I79: 34285.16 | J79: 34372.16 | K79: 34372.16 | L79: 34305.57 | M79: 34249 | N79: 34279.05 | O79: 34397.13 | P79: 34391.27 | Q79: 34375.88 | R79: 34302.13 | S79: 34339.23 | T79: 34448.72 | U79: 34519.68 | V79: 34391.01 | W79: 34284.59 | X79: 34319.54 | Y79: 34412.05 | Z79: 34581.66 | AA79: 34362.5 | AB79: 34247.3 | AC79: 34274.41 | AD79: 34357.12 | AE79: 34629.96
A80: Average retail postpaid accounts(K#) | B80: 34772.5 | C80: 34671 | D80: 34558 | E80: 34483 | F80: 34672.5 | G80: 34432.5 | H80: 34303 | I80: 34261.08 | J80: 34328.66 | K80: 34401.34 | L80: 34338.46 | M80: 34277.28 | N80: 34264.03 | O80: 34338.09 | P80: 34370.9 | Q80: 34396.53 | R80: 34339.01 | S80: 34320.68 | T80: 34393.98 | U80: 34470.12 | V80: 34411.81 | W80: 34337.8 | X80: 34302.07 | Y80: 34365.8 | Z80: 34536.69 | AA80: 34387.28 | AB80: 34304.9 | AC80: 34260.85 | AD80: 34315.77 | AE80: 34592.21
A81: Retail postpaid connections per account(#) | B81: 3.62 | C81: 3.63 | D81: 3.65 | E81: 3.67 | F81: 3.67 | G81: 3.68 | H81: 3.7 | I81: 3.7 | J81: 3.72 | K81: 3.71 | L81: 3.72 | M81: 3.73 | N81: 3.74 | O81: 3.75 | P81: 3.75 | Q81: 3.74 | R81: 3.75 | S81: 3.75 | T81: 3.76 | U81: 3.77 | V81: 3.77 | W81: 3.78 | X81: 3.78 | Y81: 3.79 | Z81: 3.8 | AA81: 3.79 | AB81: 3.8 | AC81: 3.8 | AD81: 3.82 | AE81: 3.82
A82: Retail postpaid ARPA($) | B82: 169.81 | C82: 170.79 | D82: 171.27 | E82: 170.61 | F82: 170.62 | G82: 166.66 | H82: 168.35 | I82: 170.73 | J82: 171.64 | K82: 169.31 | L82: 170.03 | M82: 170.49 | N82: 172.25 | O82: 173.18 | P82: 171.18 | Q82: 170.93 | R82: 171.02 | S82: 172.96 | T82: 173.98 | U82: 172.35 | V82: 172.32 | W82: 172.2 | X82: 174.19 | Y82: 175.37 | Z82: 173.79 | AA82: 173.56 | AB82: 173.34 | AC82: 175.33 | AD82: 176.56 | AE82: 175.09
A84: Supplemental
A85: Fixed wireless access (FWA) broadband
A86: Fixed wireless Homes passed - net addition(K#) | B86: 2250 | C86: 2250 | D86: 2250 | E86: 2250 | F86: 8625 | G86: 4500 | H86: 1750 | I86: 1750 | J86: 1750 | K86: 7000 | L86: 1625 | M86: 1625 | N86: 1625 | O86: 1625 | P86: 7500 | Q86: 1500 | R86: 1500 | S86: 1500 | T86: 1500 | U86: 6351.25 | V86: 1500 | W86: 1500 | X86: 1500 | Y86: 1500 | Z86: 5987.38 | AA86: 1500 | AB86: 1500 | AC86: 1500 | AD86: 1500 | AE86: 6007
A87: Fixed wireless Homes passed(K#) | B87: 56500 | C87: 57850 | D87: 59200 | E87: 60550 | F87: 61708.33 | G87: 59312.5 | H87: 60187.5 | I87: 61500 | J87: 62812.5 | K87: 65250 | L87: 60500 | M87: 62125 | N87: 63750 | O87: 65375 | P87: 72750 | Q87: 75500 | R87: 77000 | S87: 78500 | T87: 80000 | U87: 83101.25 | V87: 81500 | W87: 83000 | X87: 84500 | Y87: 86000 | Z87: 87591.79 | AA87: 87500 | AB87: 89000 | AC87: 90500 | AD87: 92000 | AE87: 92097.04
A89: Internal/Organic net adds - Fixed wireless access (FWA) broadband(K#) | B89: 308 | C89: 278 | D89: 261 | E89: 319 | F89: 1166 | G89: 214 | H89: 193 | I89: 194.3 | J89: 215.11 | K89: 815.15 | L89: 185.92 | M89: 180.82 | N89: 182.93 | O89: 196.69 | P89: 785.74 | Q89: 160.09 | R89: 154.05 | S89: 155.6 | T89: 166.96 | U89: 719.27 | V89: 122.68 | W89: 120.39 | X89: 118.72 | Y89: 117.94 | Z89: 588.43 | AA89: 102.77 | AB89: 101.56 | AC89: 99.77 | AD89: 99.13 | AE89: 520.43
A90: Acquired net adds - Fixed wireless access (FWA) broadband(K#) | B90: -31 | C90: -11 | D90: 18 | E90: 17 | F90: -7 | G90: 65 | H90: 9 | I90: 43.1 | J90: 37.65 | K90: 78.82 | L90: 20.25 | M90: 23.55 | N90: 29.79 | O90: 24.39 | P90: 97.97 | Q90: 19.93 | R90: 23.14 | S90: 29.06 | T90: 23.7 | U90: 95.83 | V90: 12.13 | W90: 15.28 | X90: 20.9 | Y90: 15.58 | Z90: 63.89 | AA90: 4.37 | AB90: 7.45 | AC90: 12.81 | AD90: 7.52 | AE90: 32.16
A91: Net adds- Fixed wireless access (FWA) broadband(K#) | B91: 277 | C91: 267 | D91: 279 | E91: 336 | F91: 1159 | G91: 279 | H91: 202 | I91: 201.06 | J91: 235.46 | K91: 903.06 | L91: 190.54 | M91: 184.76 | N91: 189.16 | O91: 212.56 | P91: 805.59 | Q91: 165.79 | R91: 160.66 | S91: 163.9 | T91: 173.73 | U91: 741.89 | V91: 127.53 | W91: 126.51 | X91: 127.08 | Y91: 124.17 | Z91: 567.01 | AA91: 104.52 | AB91: 104.54 | AC91: 104.9 | AD91: 102.14 | AE91: 489.19
A92: Ending subscribers - Fixed wireless access (FWA) broadband(K#) | B92: 4845 | C92: 5112 | D92: 5391 | E92: 5727 | F92: 5727 | G92: 6006 | H92: 6208 | I92: 6400.19 | J92: 6635.66 | K92: 6635.66 | L92: 6811.75 | M92: 6996.51 | N92: 7185.67 | O92: 7398.22 | P92: 7441.25 | Q92: 7495.17 | R92: 7655.84 | S92: 7819.74 | T92: 7993.47 | U92: 8172.4 | V92: 7963.46 | W92: 8089.96 | X92: 8217.04 | Y92: 8341.21 | Z92: 8700.33 | AA92: 8445.73 | AB92: 8550.27 | AC92: 8655.17 | AD92: 8757.3 | AE92: 9189.53
A93: Average subs - Fixed wireless access (FWA) broadband(K#) | B93: 4706.5 | C93: 4978.5 | D93: 5251.5 | E93: 5559 | F93: 5147.5 | G93: 5866.5 | H93: 6107 | I93: 6299.66 | J93: 6517.92 | K93: 6188.57 | L93: 6716.48 | M93: 6904.13 | N93: 7091.09 | O93: 7291.94 | P93: 7038.77 | Q93: 7412.28 | R93: 7575.5 | S93: 7737.79 | T93: 7906.6 | U93: 7801.79 | V93: 7899.69 | W93: 8026.71 | X93: 8153.5 | Y93: 8279.13 | Z93: 8417.2 | AA93: 8393.47 | AB93: 8498 | AC93: 8602.72 | AD93: 8706.23 | AE93: 8945.28
A94: ARPU - Fixed wireless access (FWA) broadband($) | B94: 47.31 | C94: 48.74 | D94: 48.11 | E94: 47.13 | F94: 47.82 | G94: 47.22 | H94: 47.86 | I94: 47.54 | J94: 47.06 | K94: 47.46 | L94: 48.06 | M94: 48.66 | N94: 48.43 | O94: 48.09 | P94: 47.7 | Q94: 48.39 | R94: 49.28 | S94: 48.94 | T94: 48.41 | U94: 47.94 | V94: 48.7 | W94: 49.59 | X94: 49.23 | Y94: 48.7 | Z94: 48.17 | AA94: 48.98 | AB94: 49.89 | AC94: 49.53 | AD94: 48.99 | AE94: 48.4
A95: Wireless fixed 5G revenues | B95: 668 | C95: 728 | D95: 758 | E95: 786 | F95: 2940 | G95: 831.36 | H95: 874.46 | I95: 896.21 | J95: 916.04 | K95: 3516.58 | L95: 953.92 | M95: 990.63 | N95: 1010.7 | O95: 1027.84 | P95: 4001.71 | Q95: 1041.84 | R95: 1081.75 | S95: 1094.25 | T95: 1102.07 | U95: 4461.45 | V95: 1126.54 | W95: 1163.99 | X95: 1171.69 | Y95: 1174.37 | Z95: 4873.71 | AA95: 1195.88 | AB95: 1231.94 | AC95: 1236.25 | AD95: 1235.32 | AE95: 5232.24
A97: Wireless equipment revenues | B97: 5398 | C97: 6255 | D97: 5619 | E97: 8198 | F97: 25470 | G97: 5681 | H97: 5024 | I97: 5444.78 | J97: 7798.8 | K97: 23942.47 | L97: 5909.46 | M97: 5441.35 | N97: 5551.61 | O97: 7926.31 | P97: 24821.18 | Q97: 6063.63 | R97: 5735.04 | S97: 5643.93 | T97: 8158.98 | U97: 25342.68 | V97: 6123.01 | W97: 5460.13 | X97: 5526.68 | Y97: 7893.21 | Z97: 25100.87 | AA97: 6212.16 | AB97: 5537.56 | AC97: 5603.24 | AD97: 8006.64 | AE97: 25426.3
A98: Total Postpaid Device Sales(K#) | B98: 7875.97 | C98: 9265.23 | D98: 8719.83 | E98: 11298.37 | F98: 37159.41 | G98: 8340.55 | H98: 8134.79 | I98: 8361.67 | J98: 10582.33 | K98: 35419.34 | L98: 8325.42 | M98: 8432.44 | N98: 8185.08 | O98: 10295.1 | P98: 35952.44 | Q98: 8207.92 | R98: 8426.66 | S98: 7851.96 | T98: 10034.5 | U98: 36266.31 | V98: 8461.87 | W98: 8156.09 | X98: 7827.73 | Y98: 9826.32 | Z98: 36794.51 | AA98: 8451.04 | AB98: 8141.52 | AC98: 7817.16 | AD98: 9811.03 | AE98: 37103.17
A99: Gross adds - Wireless retail postpaid(K#) | B99: 4474 | C99: 4834 | D99: 4663 | E99: 5813 | F99: 19784 | G99: 4669.62 | H99: 4722.79 | I99: 4832.11 | J99: 5556.91 | K99: 19781.42 | L99: 4553.54 | M99: 4668.47 | N99: 4623.03 | O99: 5383.42 | P99: 19955.98 | Q99: 4478.19 | R99: 4613.39 | S99: 4506.65 | T99: 5292.52 | U99: 20016.72 | V99: 4382.14 | W99: 4417.62 | X99: 4521.31 | Y99: 5133.27 | Z99: 20126.11 | AA99: 4369.27 | AB99: 4395.94 | AC99: 4501.45 | AD99: 5107.33 | AE99: 20275.73
... A101: Revenue per handset($) | B101: 546.03 | C101: 554.96 | D101: 521.91 | E101: 612.24 | F101: 561.99 | G101: 559.6 | H101: 527.57 | I101: 539.63 | J101: 635.79 | K101: 569.43 | L101: 590.05 | M101: 574.41 | N101: 566.56 | O101: 689.84 | P101: 590.77 | Q101: 607.89 | R101: 594.36 | S101: 581.83 | T101: 717.75 | U101: 605.66 | V101: 598.55 | W101: 556.94 | X101: 578.62 | Y101: 685.87 | Z101: 591.56 | AA101: 611.94 | AB101: 569.44 | AC101: 591.61 | AD101: 701.28 | AE101: 601.64

Sheet Business
A2: Verizon Communications Inc. | Business
A3: NYSE:VZ (MI KEY: 4057229; SPCIQ KEY: 415798)
A5: Visible Alpha
A7: Period Type : Fiscal Quarter, Fiscal Halves, Fiscal Year
A8: Period Start : 2025
A9: Period End : 2030
A10: Currency : Reported
A11: Consensus View : Mean
A12: As Of: 10/25/2026
A14: All numbers in $M unless otherwise indicated | B14: FQ1 2025A | C14: FQ2 2025A | D14: FQ3 2025A | E14: FQ4 2025A | F14: FY2025A | G14: FQ1 2026A | H14: FQ2 2026A | I14: FQ3 2026E | J14: FQ4 2026E | K14: FY2026E | L14: FQ1 2027E | M14: FQ2 2027E | N14: FQ3 2027E | O14: FQ4 2027E | P14: FY2027E | Q14: FQ1 2028E | R14: FQ2 2028E | S14: FQ3 2028E | T14: FQ4 2028E | U14: FY2028E | V14: FQ1 2029E | W14: FQ2 2029E | X14: FQ3 2029E | Y14: FQ4 2029E | Z14: FY2029E | AA14: FQ1 2030E | AB14: FQ2 2030E | AC14: FQ3 2030E | AD14: FQ4 2030E | AE14: FY2030E
A15: Number of Contributors Available | B15: 19 | C15: 19 | D15: 19 | E15: 19 | F15: 20 | G15: 20 | H15: 20 | I15: 20 of 20 | J15: 20 of 20 | K15: 20 of 20 | L15: 13 of 20 | M15: 13 of 20 | N15: 12 of 20 | O15: 12 of 20 | P15: 20 of 20 | Q15: 7 of 20 | R15: 7 of 20 | S15: 7 of 20 | T15: 7 of 20 | U15: 18 of 20 | V15: 5 of 20 | W15: 5 of 20 | X15: 5 of 20 | Y15: 5 of 20 | Z15: 14 of 20 | AA15: 5 of 20 | AB15: 5 of 20 | AC15: 5 of 20 | AD15: 5 of 20 | AE15: 14 of 20
A16: Wireless service
A17: Beginning subscriber - Wireless Retail postpaid - Business(K#) | B17: 30819 | C17: 30890 | D17: 30947 | E17: 31043 | F17: 30819 | G17: 31027 | H17: 31052.36 | I17: 31127.78 | J17: 31261.76 | K17: 31027 | L17: 31469.33 | M17: 31553.03 | N17: 31650.15 | O17: 31768.76 | P17: 31409.28 | Q17: 31858.7 | R17: 31936.4 | S17: 32049.04 | T17: 32166.38 | U17: 31804.28 | V17: 32323.84 | W17: 32406.59 | X17: 32518.2 | Y17: 32627.28 | Z17: 32237.28 | AA17: 32706.48 | AB17: 32788.44 | AC17: 32897.18 | AD17: 33000.35 | AE17: 32677.95
A18: Gross adds - Wireless Retail postpaid - Business(K#) | B18: 1504 | C18: 1557 | D18: 1559 | E18: 1534 | F18: 6154 | G18: 1483.88 | H18: 1521.96 | I18: 1549.79 | J18: 1571.8 | K18: 6135.27 | L18: 1505.8 | M18: 1503.46 | N18: 1532.41 | O18: 1535.37 | P18: 6135.26 | Q18: 1506.22 | R18: 1516.14 | S18: 1540.79 | T18: 1504.89 | U18: 6208.91 | V18: 1517.4 | W18: 1477.57 | X18: 1521.03 | Y18: 1528.07 | Z18: 6297.36 | AA18: 1526.41 | AB18: 1482.82 | AC18: 1524.54 | AD18: 1533.64 | AE18: 6356.79
A19: Disconnects - Wireless Retail postpaid - Business(K#) | B19: 1406.97 | C19: 1493.36 | D19: 1450.57 | E19: 1526.92 | F19: 5874 | G19: 1442.21 | H19: 1412.16 | I19: 1416.45 | J19: 1424.79 | K19: 5699.76 | L19: 1422.38 | M19: 1407.07 | N19: 1414.37 | O19: 1422.14 | P19: 5710.07 | Q19: 1428.99 | R19: 1404.62 | S19: 1424.29 | T19: 1447.37 | U19: 5812.05 | V19: 1434.58 | W19: 1366.5 | X19: 1412.25 | Y19: 1448.94 | Z19: 5863.86 | AA19: 1444.43 | AB19: 1374.61 | AC19: 1421.59 | AD19: 1458.44 | AE19: 5920.77
A20: Churn - Wireless Retail postpaid - Business(%) | B20: 1.52% | C20: 1.61% | D20: 1.56% | E20: 1.64% | F20: 1.58% | G20: 1.53% | H20: 1.52% | I20: 1.52% | J20: 1.52% | K20: 1.52% | L20: 1.51% | M20: 1.49% | N20: 1.49% | O20: 1.49% | P20: 1.51% | Q20: 1.49% | R20: 1.47% | S20: 1.48% | T20: 1.50% | U20: 1.52% | V20: 1.48% | W20: 1.41% | X20: 1.45% | Y20: 1.48% | Z20: 1.51% | AA20: 1.47% | AB20: 1.40% | AC20: 1.44% | AD20: 1.48% | AE20: 1.50%
A21: Internal/Organic net adds - Wireless Retail postpaid - Business(K#) | B21: 94 | C21: 65 | D21: 110 | E21: 11 | F21: 280 | G21: 74.76 | H21: 102.84 | I21: 133.98 | J21: 147.52 | K21: 433.53 | L21: 83.7 | M21: 97.13 | N21: 118.61 | O21: 113.75 | P21: 430.95 | Q21: 77.7 | R21: 112.64 | S21: 117.34 | T21: 58.32 | U21: 403.68 | V21: 82.75 | W21: 111.61 | X21: 109.08 | Y21: 79.2 | Z21: 440.67 | AA21: 81.96 | AB21: 108.74 | AC21: 103.17 | AD21: 75.25 | AE21: 443.6
A22: Acquired net adds - Wireless Retail postpaid - Business(K#) | B22: -23 | C22: -8 | D22: -14 | E22: -27 | F22: -72 | G22: -5 | H22: -217 | I22: - | J22: - | K22: -222 | L22: - | M22: - | N22: - | O22: - | P22: - | Q22: - | R22: - | S22: - | T22: - | U22: - | V22: - | W22: - | X22: - | Y22: - | Z22: - | AA22: - | AB22: - | AC22: - | AD22: - | AE22: -
A23: Net adds - Wireless Retail postpaid - Business(K#) | B23: 71 | C23: 57 | D23: 96 | E23: -16 | F23: 208 | G23: 73.76 | H23: 63.39 | I23: 133.98 | J23: 147.52 | K23: 396.53 | L23: 83.7 | M23: 97.13 | N23: 118.61 | O23: 113.75 | P23: 430.95 | Q23: 77.7 | R23: 112.64 | S23: 117.34 | T23: 58.32 | U23: 403.68 | V23: 82.75 | W23: 111.61 | X23: 109.08 | Y23: 79.2 | Z23: 440.67 | AA23: 81.96 | AB23: 108.74 | AC23: 103.17 | AD23: 75.25 | AE23: 443.6
A24: Ending subscriber - Wireless Retail postpaid - Business(K#) | B24: 30890 | C24: 30947 | D24: 31043 | E24: 31027 | F24: 31027 | G24: 31067.91 | H24: 31115.75 | I24: 31261.76 | J24: 31409.28 | K24: 31409.28 | L24: 31553.03 | M24: 31650.15 | N24: 31768.76 | O24: 31882.51 | P24: 31840.23 | Q24: 31936.4 | R24: 32049.04 | S24: 32166.38 | T24: 32224.7 | U24: 32207.96 | V24: 32406.59 | W24: 32518.2 | X24: 32627.28 | Y24: 32706.48 | Z24: 32677.95 | AA24: 32788.44 | AB24: 32897.18 | AC24: 33000.35 | AD24: 33075.6 | AE24: 33121.55
A25: Average subscriber - Wireless Retail postpaid - Business(K#) | B25: 30854.5 | C25: 30918.5 | D25: 30995 | E25: 31035 | F25: 30923 | G25: 31047.45 | H25: 31131.46 | I25: 31231.49 | J25: 31365 | K25: 31224.9 | L25: 31511.18 | M25: 31601.59 | N25: 31709.46 | O25: 31825.63 | P25: 31653.56 | Q25: 31897.55 | R25: 31992.72 | S25: 32107.71 | T25: 32195.54 | U25: 32038.2 | V25: 32365.22 | W25: 32462.4 | X25: 32572.74 | Y25: 32666.88 | Z25: 32497.47 | AA25: 32747.46 | AB25: 32842.81 | AC25: 32948.76 | AD25: 33037.97 | AE25: 32940.13
A26: ARPU - Wireless Retail postpaid - Business($) | B26: 38.51 | C26: 38.59 | D26: 38.59 | E26: 38.55 | F26: 38.56 | G26: 38.09 | H26: 37.95 | I26: 38.1 | J26: 38.06 | K26: 38.07 | L26: 37.91 | M26: 37.75 | N26: 37.91 | O26: 38.09 | P26: 37.92 | Q26: 37.69 | R26: 37.16 | S26: 37.26 | T26: 37.46 | U26: 37.43 | V26: 37 | W26: 35.81 | X26: 36.04 | Y26: 36.46 | Z26: 37.03 | AA26: 36.75 | AB26: 35.39 | AC26: 35.62 | AD26: 36.09 | AE26: 36.8
A27: Wireless service revenue - Business | B27: 3565 | C27: 3579 | D27: 3588 | E27: 3589 | F27: 14321 | G27: 3541.58 | H27: 3544.35 | I27: 3569.7 | J27: 3581.78 | K27: 14255.95 | L27: 3583.86 | M27: 3578.18 | N27: 3605.67 | O27: 3636.55 | P27: 14408.88 | Q27: 3605.43 | R27: 3564.62 | S27: 3587.2 | T27: 3616.2 | U27: 14499.75 | V27: 3589.07 | W27: 3480.94 | X27: 3515.2 | Y27: 3566.91 | Z27: 14579.67 | AA27: 3604.72 | AB27: 3477.18 | AC27: 3509.98 | AD27: 3567.54 | AE27: 14715.58
A28: Equipment revenue
A29: Wireless retail postpaid upgrade rate - Business(%) | B29: 2.20% | C29: 2.30% | D29: 2.30% | E29: 2.60% | F29: 9.40% | G29: 2.20% | H29: 2.30% | I29: 2.12% | J29: 2.55% | K29: 9.20% | L29: 2.34% | M29: 2.14% | N29: 2.16% | O29: 2.49% | P29: 9.46% | Q29: 2.36% | R29: 2.06% | S29: 2.11% | T29: 2.44% | U29: 9.66% | V29: 2.34% | W29: 1.64% | X29: 1.74% | Y29: 2.09% | Z29: 9.65% | AA29: 2.34% | AB29: 1.64% | AC29: 1.74% | AD29: 2.09% | AE29: 9.67%
A30: Total upgrade - Wireless Retail postpaid - Business(K#) | B30: 678.8 | C30: 711.13 | D30: 712.88 | E30: 806.91 | F30: 2909.72 | G30: 706.25 | H30: 640.05 | I30: 632.66 | J30: 785.36 | K30: 2764.32 | L30: 732.07 | M30: 623.3 | N30: 633.22 | O30: 747.17 | P30: 2864.85 | Q30: 755.4 | R30: 531.56 | S30: 566.73 | T30: 683.91 | U30: 2972.1 | V30: 768.54 | W30: 540.14 | X30: 576.69 | Y30: 695.47 | Z30: 3044.01 | AA30: 780.69 | AB30: 548.15 | AC30: 586.14 | AD30: 706.54 | AE30: 3091.34
A31: Gross adds - Wireless Retail postpaid - Business(K#) | B31: 1504 | C31: 1557 | D31: 1559 | E31: 1534 | F31: 6154 | G31: 1483.88 | H31: 1521.96 | I31: 1549.79 | J31: 1571.8 | K31: 6135.27 | L31: 1505.8 | M31: 1503.46 | N31: 1532.41 | O31: 1535.37 | P31: 6135.26 | Q31: 1506.22 | R31: 1516.14 | S31: 1540.79 | T31: 1504.89 | U31: 6208.91 | V31: 1517.4 | W31: 1477.57 | X31: 1521.03 | Y31: 1528.07 | Z31: 6297.36 | AA31: 1526.41 | AB31: 1482.82 | AC31: 1524.54 | AD31: 1533.64 | AE31: 6356.79
A32: Total devices - Wireless Retail postpaid - Business(K#) | B32: 2161.42 | C32: 2245.98 | D32: 2249.77 | E32: 2318.97 | F32: 8976.14 | G32: 2182.27 | H32: 2146.02 | I32: 2180.99 | J32: 2365.85 | K32: 8875.14 | L32: 2253.67 | M32: 2046.38 | N32: 2106.88 | O32: 2233.44 | P32: 8952.47 | Q32: 2240.8 | R32: 1913.32 | S32: 2040.43 | T32: 2125.52 | U32: 9111.74 | V32: 2255.6 | W32: 1921.06 | X32: 2050.92 | Y32: 2136.94 | Z32: 9282.49 | AA32: 2275.72 | AB32: 1934.81 | AC32: 2067.88 | AD32: 2155.17 | AE32: 9396.8
A33: Equipment revenue per device sold - Wireless Retail postpaid - Business($) | B33: 407.25 | C33: 394.73 | D33: 379.38 | E33: 468.7 | F33: 411.48 | G33: 400.42 | H33: 389.8 | I33: 386.17 | J33: 475.9 | K33: 413.07 | L33: 410.39 | M33: 436.1 | N33: 397.62 | O33: 494.21 | P33: 426.88 | Q33: 415.09 | R33: 490.84 | S33: 424.93 | T33: 520.04 | U33: 431.29 | V33: 420.91 | W33: 498.82 | X33: 432.47 | Y33: 528.91 | Z33: 432.97 | AA33: 427.16 | AB33: 506.26 | AC33: 438.88 | AD33: 536.87 | AE33: 436.53
A34: Wireless equipment revenue - Business | B34: 866 | C34: 886 | D34: 853 | E34: 1086 | F34: 3691 | G34: 857 | H34: 846 | I34: 849.03 | J34: 1070.37 | K34: 3547.68 | L34: 960.61 | M34: 883.45 | N34: 866.54 | O34: 1074.15 | P34: 3700.47 | Q34: 935.27 | R34: 943.22 | S34: 891.82 | T34: 1139.6 | U34: 3936.23 | V34: 940.35 | W34: 914.03 | X34: 876.71 | Y34: 1058.21 | Z34: 3947.48 | AA34: 956.46 | AB34: 928.28 | AC34: 890.93 | AD34: 1076.6 | AE34: 4018.7
A36: Wireline
A37: FiOS
A38: Net adds - FiOS Video - SMB(K#) | B38: -2 | C38: -1 | D38: -2 | E38: -2 | F38: -7 | G38: -2 | H38: -2 | I38: -1.8 | J38: -1.99 | K38: -7.14 | L38: -1.94 | M38: -1.7 | N38: -1.84 | O38: -2.1 | P38: -7.17 | Q38: -2.17 | R38: -2.19 | S38: -2.2 | T38: -2.22 | U38: -7.27 | V38: -2.47 | W38: -2.49 | X38: -2.5 | Y38: -2.52 | Z38: -7.18 | AA38: -2.54 | AB38: -2.55 | AC38: -2.57 | AD38: -2.58 | AE38: -7.15
A39: Net adds - FiOS Internet - SMB(K#) | B39: 4 | C39: 4 | D39: 2 | E39: 2 | F39: 12 | G39: 5.51 | H39: 7.08 | I39: 5.58 | J39: 5.78 | K39: 22.54 | L39: 8.3 | M39: 8.82 | N39: 7.58 | O39: 7.85 | P39: 28.56 | Q39: 6.34 | R39: 6.66 | S39: 6.97 | T39: 6.59 | U39: 31.6 | V39: 3.53 | W39: 4.02 | X39: 4.52 | Y39: 4.01 | Z39: 26.77 | AA39: 3.07 | AB39: 3.61 | AC39: 4.19 | AD39: 3.67 | AE39: 24.64
A40: Net adds - FiOS Total digital - SMB(K#) | B40: 2 | C40: 3 | D40: - | E40: - | F40: 5 | G40: 4.15 | H40: 5.25 | I40: 4.3 | J40: 4.32 | K40: 15.39 | L40: 6.34 | M40: 7.13 | N40: 6.7 | O40: 6.66 | P40: 20.75 | Q40: 4.08 | R40: 4.38 | S40: 6.23 | T40: 5.69 | U40: 23.95 | V40: 1.06 | W40: 1.53 | X40: 3.02 | Y40: 2.23 | Z40: 18.55 | AA40: 0.53 | AB40: 1.06 | AC40: 2.43 | AD40: 1.63 | AE40: 16.19
A42: FiOS Video subscribers - SMB(K#) | B42: 52 | C42: 51 | D42: 49 | E42: 47 | F42: 47 | G42: 45 | H42: 44.49 | I42: 42.78 | J42: 40.91 | K42: 40.91 | L42: 38.67 | M42: 36.97 | N42: 35.13 | O42: 33.04 | P42: 34.17 | Q42: 29.69 | R42: 27.51 | S42: 25.3 | T42: 23.09 | U42: 27.31 | V42: 19.84 | W42: 17.36 | X42: 14.85 | Y42: 19.5 | Z42: 24.31 | AA42: 17.75 | AB42: 16 | AC42: 14.25 | AD42: 12.5 | AE42: 19
A43: FiOS Internet subscribers - SMB(K#) | B43: 405 | C43: 409 | D43: 411 | E43: 413 | F43: 413 | G43: 539.3 | H43: 525.68 | I43: 541.67 | J43: 548 | K43: 548 | L43: 574.54 | M43: 584.22 | N43: 592.66 | O43: 601.36 | P43: 578.75 | Q43: 630.91 | R43: 639.07 | S43: 647.54 | T43: 655.63 | U43: 626.93 | V43: 634.7 | W43: 640.72 | X43: 647.24 | Y43: 653.25 | Z43: 644.35 | AA43: 658.32 | AB43: 663.93 | AC43: 670.12 | AD43: 675.79 | AE43: 671.66
A44: FiOS Total digital subscribers - SMB(K#) | B44: 457 | C44: 460 | D44: 460 | E44: 460 | F44: 460 | G44: 547.41 | H44: 506.59 | I44: 542.43 | J44: 546.03 | K44: 546.03 | L44: 565.55 | M44: 572.42 | N44: 577.85 | O44: 583.25 | P44: 566.87 | Q44: 561.71 | R44: 564.76 | S44: 568.55 | T44: 571.84 | U44: 608.3 | V44: 573.87 | W44: 576.38 | X44: 579.74 | Y44: 582.58 | Z44: 630.06 | AA44: 584.15 | AB44: 586.27 | AC44: 589.29 | AD44: 591.79 | AE44: 648.62
A45: FiOS Average Total digital - SMB(K#) | B45: 456 | C45: 458.5 | D45: 460 | E45: 460 | F45: 457.5 | G45: 500.29 | H45: 497.69 | I45: 495.45 | J45: 534.32 | K45: 499.48 | L45: 562.59 | M45: 568.99 | N45: 575.14 | O45: 580.55 | P45: 545.48 | Q45: 560.4 | R45: 563.23 | S45: 566.66 | T45: 570.2 | U45: 578.48 | V45: 572.85 | W45: 575.13 | X45: 578.06 | Y45: 581.16 | Z45: 600.1 | AA45: 583.37 | AB45: 585.21 | AC45: 587.78 | AD45: 590.54 | AE45: 618.86
A46: FiOS Total digital ARPU - SMB($) | B46: 226.61 | C46: 225.37 | D46: 224.64 | E46: 227.54 | F46: 226.59 | G46: 217.38 | H46: 226.27 | I46: 233.44 | J46: 222.42 | K46: 228.65 | L46: 209.53 | M46: 202.49 | N46: 201.33 | O46: 202.22 | P46: 220.48 | Q46: 220.96 | R46: 209.96 | S46: 208.97 | T46: 211.3 | U46: 217.6 | V46: 223.99 | W46: 208.11 | X46: 206.99 | Y46: 209.13 | Z46: 217.82 | AA46: 219.59 | AB46: 203.75 | AC46: 202.66 | AD46: 204.77 | AE46: 216.98
A47: FiOS Total digital revenue - Business | B47: 310 | C47: 310 | D47: 310 | E47: 314 | F47: 1244 | G47: 342.24 | H47: 370.89 | I47: 359.23 | J47: 360.84 | K47: 1390.75 | L47: 375.72 | M47: 367.84 | N47: 364.95 | O47: 371.93 | P47: 1430.94 | Q47: 397.21 | R47: 384.01 | S47: 379.05 | T47: 389.13 | U47: 1436.75 | V47: 413.51 | W47: 391.32 | X47: 381.52 | Y47: 387.53 | Z47: 1426.62 | AA47: 410.82 | AB47: 388.09 | AC47: 378.23 | AD47: 383.86 | AE47: 1431.84
A48: Broadband
A49: Internal/Organic net adds - DSL - SMB(K#) | B49: -4 | C49: -5.5 | D49: -4 | E49: -5.5 | F49: -19 | G49: -3.8 | H49: -8 | I49: -8 | J49: -8 | K49: -27.8 | L49: -5.56 | M49: -5.56 | N49: -5.56 | O49: -5.56 | P49: -22.24 | Q49: -4.45 | R49: -4.45 | S49: -4.45 | T49: -4.45 | U49: -17.79 | V49: -3.56 | W49: -3.56 | X49: -3.56 | Y49: - | Z49: -10.68 | AA49: -2.14 | AB49: -2.14 | AC49: -2.14 | AD49: - | AE49: -6.41
A50: Acquired net adds - DSL - SMB(K#) | B50: - | C50: 1 | D50: - | E50: -20 | F50: -39 | G50: 55 | H50: - | I50: - | J50: - | K50: 55 | L50: - | M50: - | N50: - | O50: - | P50: - | Q50: - | R50: - | S50: - | T50: - | U50: - | V50: - | W50: - | X50: - | Y50: - | Z50: - | AA50: - | AB50: - | AC50: - | AD50: - | AE50: -
A51: Net adds - DSL - SMB(K#) | B51: -4 | C51: -5 | D51: -4 | E51: -6 | F51: -19 | G51: 12.15 | H51: -6.92 | I51: -6.51 | J51: -6.38 | K51: 20.91 | L51: -6.15 | M51: -6.19 | N51: -5.86 | O51: -5.88 | P51: -24.3 | Q51: -6.36 | R51: -5.22 | S51: -4.76 | T51: -4.82 | U51: -16.8 | V51: -4.04 | W51: -4.37 | X51: -3.84 | Y51: -4.17 | Z51: -10.99 | AA51: -3.13 | AB51: -3.46 | AC51: -3.02 | AD51: -3.68 | AE51: -8.16
A52: DSL subscribers - SMB(K#) | B52: 54 | C52: 49 | D52: 45 | E52: 39 | F52: 39 | G52: 78.73 | H52: 71.81 | I52: 65.3 | J52: 58.92 | K52: 58.92 | L52: 57.12 | M52: 50.93 | N52: 44.18 | O52: 47.97 | P52: 39.67 | Q52: 48.5 | R52: 86.46 | S52: 80.9 | T52: 75.59 | U52: 37.24 | V52: 70.84 | W52: 66.25 | X52: 61.8 | Y52: 59.27 | Z52: 28.74 | AA52: 55.76 | AB52: 52.34 | AC52: 48.99 | AD52: 46.79 | AE52: 22.82
A54: Internal/Organic net adds - Broadband - SMB(K#) | B54: - | C54: -2 | D54: -2 | E54: -3 | F54: -7 | G54: 5.58 | H54: 5.72 | I54: 1.52 | J54: 1.9 | K54: 11.44 | L54: 7.44 | M54: 8.02 | N54: 5.21 | O54: 6.06 | P54: 20.9 | Q54: 0.78 | R54: 3.78 | S54: 6.78 | T54: 6.78 | U54: 33.39 | V54: 0.44 | W54: 0.44 | X54: 0.44 | Y54: 4 | Z54: 29.95 | AA54: 0.86 | AB54: 0.86 | AC54: 0.86 | AD54: 3 | AE54: 26.56
A55: Acquired net adds - Broadband - SMB(K#) | B55: - | C55: 1 | D55: - | E55: -1 | F55: -51 | G55: 184.67 | H55: 1 | I55: - | J55: - | K55: 185 | L55: - | M55: - | N55: - | O55: - | P55: - | Q55: - | R55: - | S55: - | T55: - | U55: - | V55: - | W55: - | X55: - | Y55: - | Z55: - | AA55: - | AB55: - | AC55: - | AD55: - | AE55: -
A56: Net adds - Broadband - SMB(K#) | B56: - | C56: -1 | D56: -2 | E56: -4 | F56: -7 | G56: 110.76 | H56: 2.12 | I56: 0.68 | J56: 0.97 | K56: 103.41 | L56: 3.02 | M56: 4.26 | N56: 3.15 | O56: 3.44 | P56: 9.76 | Q56: 0.13 | R56: 1.69 | S56: 3.97 | T56: 3.52 | U56: 20.54 | V56: 0.15 | W56: 0.31 | X56: 1.34 | Y56: 1.9 | Z56: 19.5 | AA56: 0.61 | AB56: 0.82 | AC56: 1.84 | AD56: 1.88 | AE56: 19.08
A57: Beginning subs - Business FWA(K#) | B57: 1854 | C57: 1931 | D57: 2035 | E57: 2193 | F57: 1854 | G57: 2320 | H57: 2427.91 | I57: 2520.06 | J57: 2625.48 | K57: 2327.18 | L57: 2730.14 | M57: 2817.23 | N57: 2903.03 | O57: 2997.74 | P57: 2734.92 | Q57: 2960.54 | R57: 3028.36 | S57: 3097.96 | T57: 3169.19 | U57: 3057.91 | V57: 3103.47 | W57: 3144.86 | X57: 3188.52 | Y57: 3234.33 | Z57: 3330.89 | AA57: 3276.46 | AB57: 3310.84 | AC57: 3347.4 | AD57: 3386.09 | AE57: 3545.04
A58: Internal/Organic net adds - Business FWA broadband(K#) | B58: 109 | C58: 114 | D58: 140 | E58: 110 | F58: 473 | G58: 94.44 | H58: 98.63 | I58: 107.75 | J58: 111.35 | K58: 412.16 | L58: 91.82 | M58: 91.44 | N58: 96.8 | O58: 101.1 | P58: 383.68 | Q58: 89.67 | R58: 91.33 | S58: 93.33 | T58: 90 | U58: 355.82 | V58: 19 | W58: 24 | X58: 30 | Y58: 20 | Z58: 217.44 | AA58: 4 | AB58: 9 | AC58: 15 | AD58: 5 | AE58: 199.13
A59: Acquired net adds - Business FWA broadband(K#) | B59: -32 | C59: -10 | D59: 18 | E59: 17 | F59: -7 | G59: 39.23 | H59: -25 | I59: - | J59: - | K59: -5.39 | L59: - | M59: - | N59: - | O59: - | P59: - | Q59: - | R59: - | S59: - | T59: - | U59: - | V59: - | W59: - | X59: - | Y59: - | Z59: - | AA59: - | AB59: - | AC59: - | AD59: - | AE59: -
A60: Net adds - Business FWA broadband(K#) | B60: 77 | C60: 104 | D60: 158 | E60: 127 | F60: 466 | G60: 100.01 | H60: 92.15 | I60: 105.42 | J60: 109.44 | K60: 407.02 | L60: 87.1 | M60: 85.79 | N60: 94.71 | O60: 98.27 | P60: 358.2 | Q60: 67.81 | R60: 69.6 | S60: 71.23 | T60: 68.42 | U60: 307.33 | V60: 41.39 | W60: 43.66 | X60: 45.81 | Y60: 42.12 | Z60: 214.14 | AA60: 34.38 | AB60: 36.56 | AC60: 38.69 | AD60: 35.06 | AE60: 197.09
A62: FiOS Broadband subscribers - SMB(K#) | B62: 459 | C62: 458 | D62: 456 | E62: 452 | F62: 452 | G62: 580.36 | H62: 582.05 | I62: 570.62 | J62: 571.41 | K62: 571.41 | L62: 588.97 | M62: 592.62 | N62: 595.32 | O62: 598.27 | P62: 581.18 | Q62: 686.66 | R62: 688.35 | S62: 692.32 | T62: 695.84 | U62: 614.83 | V62: 682.94 | W62: 683.25 | X62: 684.59 | Y62: 686.49 | Z62: 620.98 | AA62: 687.1 | AB62: 687.92 | AC62: 689.76 | AD62: 691.64 | AE62: 640.05
A63: Ending subscribers - Business FWA broadband(K#) | B63: 1931 | C63: 2035 | D63: 2193 | E63: 2320 | F63: 2320 | G63: 2427.91 | H63: 2520.06 | I63: 2625.48 | J63: 2734.92 | K63: 2734.92 | L63: 2817.23 | M63: 2903.03 | N63: 2997.74 | O63: 3096.01 | P63: 3093.12 | Q63: 3028.36 | R63: 3097.96 | S63: 3169.19 | T63: 3237.6 | U63: 3365.24 | V63: 3144.86 | W63: 3188.52 | X63: 3234.33 | Y63: 3276.46 | Z63: 3545.04 | AA63: 3310.84 | AB63: 3347.4 | AC63: 3386.09 | AD63: 3421.14 | AE63: 3742.13
A64: Total Broadband connections - Business(K#) | B64: 2390 | C64: 2493 | D64: 2649 | E64: 2772 | F64: 2772 | G64: 2978.86 | H64: 3073.71 | I64: 3180.92 | J64: 3292.51 | K64: 3292.51 | L64: 3369.77 | M64: 3460.5 | N64: 3559.2 | O64: 3661.71 | P64: 3665.61 | Q64: 3660.27 | R64: 3732.31 | S64: 3806.75 | T64: 3877.95 | U64: 3975.39 | V64: 3939.1 | W64: 4002.08 | X64: 4067.44 | Y64: 4130.46 | Z64: 4239.08 | AA64: 4186.7 | AB64: 4244.74 | AC64: 4305.13 | AD64: 4362.83 | AE64: 4487.14
A66: Net adds - Voice - SMB(K#) | B66: -77.35 | C66: -77.48 | D66: -75.95 | E66: -73.21 | F66: -303.99 | G66: -65.98 | H66: -66.13 | I66: -65.23 | J66: -65.19 | K66: -263.59 | L66: -58.31 | M66: -58.48 | N66: -56.51 | O66: -56.46 | P66: -241.42 | Q66: -55.9 | R66: -56.43 | S66: -54.32 | T66: -54.56 | U66: -221.98 | V66: -52.85 | W66: -53.34 | X66: -51.4 | Y66: -51.62 | Z66: -204.89 | AA66: -50.25 | AB66: -50.7 | AC66: -48.91 | AD66: -49.11 | AE66: -189.83
A67: FiOS Voice subscribers - SMB(K#) | B67: 3112.49 | C67: 3035.01 | D67: 2959.06 | E67: 2885.85 | F67: 2885.85 | G67: 2859.4 | H67: 2801.28 | I67: 2694.12 | J67: 2628.93 | K67: 2628.93 | L67: 2698.62 | M67: 2640.14 | N67: 2583.63 | O67: 2527.17 | P67: 2387.51 | Q67: 2419.04 | R67: 2362.61 | S67: 2308.29 | T67: 2253.73 | U67: 2165.52 | V67: 2200.87 | W67: 2147.53 | X67: 2096.14 | Y67: 2044.52 | Z67: 1960.63 | AA67: 1994.26 | AB67: 1943.56 | AC67: 1894.65 | AD67: 1845.54 | AE67: 1770.8
A69: Business
A70: Enterprise and public sector - Business | B70: 3457 | C70: 3435 | D70: 3311 | E70: 3331 | F70: 13534 | G70: 3297.25 | H70: 3267.36 | I70: 3243.4 | J70: 3292.67 | K70: 13115.75 | L70: 3254.92 | M70: 3223.08 | N70: 3147.47 | O70: 3184.96 | P70: 12850.02 | Q70: 3170.57 | R70: 3134.4 | S70: 3048.55 | T70: 3129.96 | U70: 12560.67 | V70: 3156.42 | W70: 3109.33 | X70: 3053.31 | Y70: 3200.41 | Z70: 12342.24 | AA70: 3100.13 | AB70: 3057.48 | AC70: 3005.12 | AD70: 3156.57 | AE70: 12101.18
A71: Business market and SaaS - Business | B71: 3314 | C71: 3346 | D71: 3352 | E71: 3569 | F71: 13581 | G71: 3436.49 | H71: 3437.08 | I71: 3526 | J71: 3728.84 | K71: 14249.07 | L71: 3509.55 | M71: 3522.79 | N71: 3518.81 | O71: 3692.72 | P71: 14392.8 | Q71: 3487.12 | R71: 3484.36 | S71: 3459.77 | T71: 3674.14 | U71: 14553 | V71: 3347.48 | W71: 3314.62 | X71: 3263.66 | Y71: 3464.58 | Z71: 14616.95 | AA71: 3266.34 | AB71: 3239.19 | AC71: 3192.63 | AD71: 3399.8 | AE71: 14661.06
A72: Wholesale revenue - Business | B72: 515 | C72: 494 | D72: 479 | E72: 466 | F72: 1954 | G72: 506.75 | H72: 480.8 | I72: 464.95 | J72: 417.74 | K72: 1876.7 | L72: 480.52 | M72: 457.72 | N72: 490.98 | O72: 457.84 | P72: 1894.93 | Q72: 496.51 | R72: 477.03 | S72: 463.31 | T72: 451.49 | U72: 1816.45 | V72: 591.02 | W72: 569.05 | X72: 553.9 | Y72: 540.95 | Z72: 1836.34 | AA72: 617.62 | AB72: 595.23 | AC72: 579.94 | AD72: 566.92 | AE72: 1827.34
A73: Business revenue | B73: 7002 | C73: 6973 | D73: 6843 | E73: 7077 | F73: 29069 | G73: 7130 | H73: 7155 | I73: 7259.08 | J73: 7509.81 | K73: 29256.56 | L73: 7337.87 | M73: 7238.86 | N73: 7168.08 | O73: 7482.67 | P73: 29322.39 | Q73: 7289.21 | R73: 7154.03 | S73: 7057.54 | T73: 7393.92 | U73: 29344.89 | V73: 7152.35 | W73: 6909.13 | X73: 6849.87 | Y73: 7184.08 | Z73: 29078.38 | AA73: 7042.65 | AB73: 6776.71 | AC73: 6723.68 | AD73: 7065.25 | AE73: 28938.32
A74: Cost of services - Business | B74: 2154 | C74: 2060 | D74: 1985 | E74: 2083 | F74: 8282 | G74: 2117 | H74: 2023 | I74: 2165.54 | J74: 2209.86 | K74: 8695.74 | L74: 2277.22 | M74: 2154.27 | N74: 2164.01 | O74: 2195.33 | P74: 8861.88 | Q74: 2189.71 | R74: 2044.08 | S74: 2021.06 | T74: 2043.69 | U74: 8707.2 | V74: 2057.42 | W74: 1873.92 | X74: 1866.29 | Y74: 1866.19 | Z74: 8546.92 | AA74: 1987.86 | AB74: 1798.11 | AC74: 1790.9 | AD74: 1790.92 | AE74: 8461.44
A75: Cost of wireless equipment - Business | B75: 1194 | C75: 1201 | D75: 1213 | E75: 1438 | F75: 5046 | G75: 1202 | H75: 1203 | I75: 1203.68 | J75: 1468.9 | K75: 5093.48 | L75: 1219.57 | M75: 1194.12 | N75: 1205.19 | O75: 1468.73 | P75: 5166.55 | Q75: 1265.51 | R75: 1288.5 | S75: 1231.88 | T75: 1495.92 | U75: 5353.29 | V75: 1274.91 | W75: 1244.15 | X75: 1192.91 | Y75: 1407.6 | Z75: 5395.91 | AA75: 1295.01 | AB75: 1261.87 | AC75: 1210.57 | AD75: 1430.7 | AE75: 5484.63
A76: Cost of sales - Business | B76: 3348 | C76: 3261 | D76: 3198 | E76: 3521 | F76: 13328 | G76: 3319 | H76: 3226 | I76: 3369.22 | J76: 3678.75 | K76: 13789.21 | L76: 3496.79 | M76: 3348.39 | N76: 3369.21 | O76: 3664.05 | P76: 14028.43 | Q76: 3455.22 | R76: 3332.58 | S76: 3252.94 | T76: 3539.61 | U76: 14060.49 | V76: 3332.33 | W76: 3118.07 | X76: 3059.2 | Y76: 3273.79 | Z76: 13942.83 | AA76: 3282.86 | AB76: 3059.98 | AC76: 3001.47 | AD76: 3221.62 | AE76: 13946.07
A77: Gross profit/(loss) - Business | B77: 3654 | C77: 3712 | D77: 3645 | E77: 3556 | F77: 14567 | G77: 3811 | H77: 3929 | I77: 3874.1 | J77: 3829.02 | K77: 15959.11 | L77: 3846.26 | M77: 3859.01 | N77: 3784.71 | O77: 3796.67 | P77: 16305.05 | Q77: 3821.63 | R77: 3754.42 | S77: 3717.22 | T77: 3760.01 | U77: 16285.93 | V77: 3666.93 | W77: 3572.82 | X77: 3549.34 | Y77: 3625.84 | Z77: 14964.71 | AA77: 3550.72 | AB77: 3434.89 | AC77: 3418.25 | AD77: 3498.29 | AE77: 14783.18
A78: SG&A - Business | B78: 1919 | C78: 1990 | D78: 1927 | E78: 1885 | F78: 7721 | G78: 1806 | H78: 1847 | I78: 1966.9 | J78: 1968.44 | K78: 7716.32 | L78: 1854.83 | M78: 1800.69 | N78: 1923.74 | O78: 1952.96 | P78: 7572.46 | Q78: 1805.35 | R78: 1671.63 | S78: 1887.3 | T78: 1923.4 | U78: 7358.37 | V78: 1656.29 | W78: 1432.27 | X78: 1749.45 | Y78: 1785.49 | Z78: 7120.94 | AA78: 1580.75 | AB78: 1349.07 | AC78: 1666.2 | AD78: 1697.16 | AE78: 6968.64
A79: Operating expenses - Business | B79: 5267 | C79: 5251 | D79: 5125 | E79: 5406 | F79: 21049 | G79: 5125 | H79: 5073 | I79: 5314.2 | J79: 5625.68 | K79: 20666 | L79: 5351.63 | M79: 5149.08 | N79: 5292.95 | O79: 5617.01 | P79: 21474.26 | Q79: 5260.57 | R79: 5004.21 | S79: 5140.24 | T79: 5463.02 | U79: 21269.69 | V79: 4988.62 | W79: 4550.34 | X79: 4808.65 | Y79: 5059.28 | Z79: 20899.76 | AA79: 4863.62 | AB79: 4409.05 | AC79: 4667.66 | AD79: 4918.78 | AE79: 20750.78
A80: Depreciation and amortization - Business | B80: 989 | C80: 998 | D80: 1002 | E80: 987 | F80: 3976 | G80: 1049 | H80: 1091 | I80: 1096.95 | J80: 1099.08 | K80: 4349.86 | L80: 1094.39 | M80: 1102.6 | N80: 1116.17 | O80: 1119.85 | P80: 4426.12 | Q80: 1103.27 | R80: 1120.1 | S80: 1138.09 | T80: 1127.98 | U80: 4395.13 | V80: 1110.82 | W80: 1114.03 | X80: 1130.15 | Y80: 1123.57 | Z80: 4377.74 | AA80: 1117.6 | AB80: 1120.85 | AC80: 1137.28 | AD80: 1130.55 | AE80: 4374.96
A81: Total operating expenses - Business | B81: 6256 | C81: 6249 | D81: 6127 | E81: 6393 | F81: 25025 | G81: 6174 | H81: 6164 | I81: 6374.11 | J81: 6680.2 | K81: 25457.96 | L81: 6373.03 | M81: 6181.97 | N81: 6318.19 | O81: 6622.92 | P81: 25682.31 | Q81: 6140.65 | R81: 5830.17 | S81: 5932.32 | T81: 6121.44 | U81: 25419.37 | V81: 5996.5 | W81: 5655.35 | X81: 5759.09 | Y81: 5955.71 | Z81: 25510.31 | AA81: 5861.64 | AB81: 5492.45 | AC81: 5597.34 | AD81: 5800.5 | AE81: 25381.75
... A83: Operating income/(loss) - Business | B83: 746 | C83: 724 | D83: 716 | E83: 684 | F83: 2870 | G83: 956 | H83: 991 | I83: 825.05 | J83: 774.55 | K83: 3475.33 | L83: 911.29 | M83: 933.14 | N83: 777.56 | O83: 767.24 | P83: 3415.66 | Q83: 1016.3 | R83: 969.65 | S83: 797.12 | T83: 867.2 | U83: 3549.83 | V83: 954.93 | W83: 884.48 | X83: 718.28 | Y83: 790.76 | Z83: 3479.76 | AA83: 896.69 | AB83: 803.9 | AC83: 643.39 | AD83: 717.72 | AE83: 3628.98
A85: Retail postpaid phones
A86: Gross adds - Wireless Retail postpaid phones - Business(K#) | B86: 715 | C86: 756 | D86: 756 | E86: 783 | F86: 3010 | G86: 773.87 | H86: 767.36 | I86: 769.71 | J86: 770.53 | K86: 3081.47 | L86: 769.61 | M86: 755.43 | N86: 771.05 | O86: 775.84 | P86: 3038.37 | Q86: 779.88 | R86: 753.3 | S86: 772.33 | T86: 775.36 | U86: 3036.89 | V86: 810.8 | W86: 741.01 | X86: 770.56 | Y86: 764.29 | Z86: 3034.05 | AA86: 818.97 | AB86: 747.39 | AC86: 777.98 | AD86: 771.36 | AE86: 3053.3
A87: Churn rate - Wireless Retail postpaid phones - Business(%) | B87: 1.15% | C87: 1.26% | D87: 1.25% | E87: 1.27% | F87: 1.23% | G87: 1.25% | H87: 1.16% | I87: 1.21% | J87: 1.19% | K87: 1.19% | L87: 1.20% | M87: 1.14% | N87: 1.20% | O87: 1.18% | P87: 1.17% | Q87: 1.20% | R87: 1.12% | S87: 1.18% | T87: 1.16% | U87: 1.17% | V87: 1.22% | W87: 1.08% | X87: 1.15% | Y87: 1.16% | Z87: 1.16% | AA87: 1.22% | AB87: 1.07% | AC87: 1.15% | AD87: 1.16% | AE87: 1.16%
A88: Disconnects - Wireless Retail postpaid phones - Business(K#) | B88: 647.79 | C88: 711.7 | D88: 707.44 | E88: 720.59 | F88: 2787.51 | G88: 702.21 | H88: 669.05 | I88: 693.3 | J88: 686.59 | K88: 2745.39 | L88: 702.43 | M88: 669.34 | N88: 698.65 | O88: 696.85 | P88: 2747.15 | Q88: 716.7 | R88: 664.91 | S88: 700.01 | T88: 695.48 | U88: 2763.1 | V88: 732.88 | W88: 647.31 | X88: 696.23 | Y88: 704.82 | Z88: 2776.79 | AA88: 742.15 | AB88: 654.61 | AC88: 704.64 | AD88: 713.25 | AE88: 2803.93
A89: Net adds internal/organic - Wireless Retail postpaid phones - Business(K#) | B89: 67 | C89: 42 | D89: 51 | E89: 65 | F89: 225 | G89: 90 | H89: 108.32 | I89: 74.62 | J89: 80.91 | K89: 330.03 | L89: 72.49 | M89: 84.88 | N89: 68.99 | O89: 97.72 | P89: 301.35 | Q89: 72.29 | R89: 91.52 | S89: 72.27 | T89: 83.24 | U89: 284.11 | V89: 77.92 | W89: 93.69 | X89: 74.33 | Y89: 59.47 | Z89: 265.84 | AA89: 76.83 | AB89: 92.78 | AC89: 73.33 | AD89: 58.11 | AE89: 259.19
A90: Net adds adjustment - Wireless Retail postpaid phones - Business(K#) | B90: -4 | C90: -2 | D90: -17 | E90: -3 | F90: -26 | G90: -41.25 | H90: -6 | I90: - | J90: - | K90: -71.73 | L90: - | M90: - | N90: - | O90: - | P90: - | Q90: - | R90: - | S90: - | T90: - | U90: - | V90: - | W90: - | X90: - | Y90: - | Z90: - | AA90: - | AB90: - | AC90: - | AD90: - | AE90: -
A91: Net Adds - Wireless Retail postpaid phones - Business(K#) | B91: 63 | C91: 40 | D91: 34 | E91: 62 | F91: 199 | G91: 70.01 | H91: 106.9 | I91: 77.71 | J91: 84.76 | K91: 323.47 | L91: 71.41 | M91: 79.29 | N91: 71.7 | O91: 103.82 | P91: 305.66 | Q91: 72.87 | R91: 85.9 | S91: 80.34 | T91: 92.8 | U91: 285.86 | V91: 86.88 | W91: 88.54 | X91: 96.49 | Y91: 71.7 | Z91: 264.79 | AA91: 90.24 | AB91: 92.16 | AC91: 100 | AD91: 74.66 | AE91: 258.85
A92: Total Wireless Retail postpaid phone subscribers - Business(K#) | B92: 18808 | C92: 18848 | D92: 18882 | E92: 18944 | F92: 18944 | G92: 19014.01 | H92: 19114.45 | I92: 19182.71 | J92: 19267.47 | K92: 19267.47 | L92: 19340.68 | M92: 19419.97 | N92: 19491.68 | O92: 19595.5 | P92: 19573.13 | Q92: 19720.02 | R92: 19805.93 | S92: 19886.27 | T92: 19979.07 | U92: 19862.23 | V92: 20077.96 | W92: 20166.5 | X92: 20262.99 | Y92: 20334.69 | Z92: 20097.06 | AA92: 20424.93 | AB92: 20517.09 | AC92: 20617.09 | AD92: 20691.75 | AE92: 20355.91
A93: Average Wireless Retail postpaid phone subscribers - Business(K#) | B93: 18776.5 | C93: 18828 | D93: 18865 | E93: 18913 | F93: 18844.5 | G93: 18979 | H93: 19064.23 | I93: 19143.85 | J93: 19225.09 | K93: 19105.05 | L93: 19304.97 | M93: 19380.33 | N93: 19455.82 | O93: 19543.59 | P93: 19421.17 | Q93: 19683.59 | R93: 19762.98 | S93: 19846.1 | T93: 19932.67 | U93: 19720.3 | V93: 20034.52 | W93: 20122.23 | X93: 20214.74 | Y93: 20298.84 | Z93: 19966.01 | AA93: 20379.81 | AB93: 20471.01 | AC93: 20567.09 | AD93: 20654.42 | AE93: 20227.87
A95: Net adds - Internet device subscribers - Business(K#) | B95: 27 | C95: 23 | D95: 59 | E95: -54 | F95: 55 | G95: -47.22 | H95: -54.57 | I95: 49.26 | J95: 41.12 | K95: -11.41 | L95: 15.3 | M95: 17.01 | N95: 31.24 | O95: -41.31 | P95: 89.28 | Q95: 2.63 | R95: 12.92 | S95: 32.29 | T95: -66.44 | U95: 82.16 | V95: 32.5 | W95: 32.5 | X95: 32.5 | Y95: 32.5 | Z95: 188.15 | AA95: 32.5 | AB95: 32.5 | AC95: 32.5 | AD95: 32.5 | AE95: 204.15
A96: Internet device subscribers - Business(K#) | B96: 12082 | C96: 12099 | D96: 12161 | E96: 12083 | F96: 12083 | G96: 11764.4 | H96: 11711.65 | I96: 11760.38 | J96: 11807.11 | K96: 11807.11 | L96: 11715.12 | M96: 11739.73 | N96: 11778.53 | O96: 11768.48 | P96: 11918.85 | Q96: 11418.17 | R96: 11431.09 | S96: 11463.38 | T96: 11396.94 | U96: 11922.13 | V96: 11488 | W96: 11520.5 | X96: 11553 | Y96: 11585.5 | Z96: 12217.33 | AA96: 11618 | AB96: 11650.5 | AC96: 11683 | AD96: 11715.5 | AE96: 12421.48

Sheet Consumer
A2: Verizon Communications Inc. | Consumer
A3: NYSE:VZ (MI KEY: 4057229; SPCIQ KEY: 415798)
A5: Visible Alpha
A7: Period Type : Fiscal Quarter, Fiscal Halves, Fiscal Year
A8: Period Start : 2025
A9: Period End : 2030
A10: Currency : Reported
A11: Consensus View : Mean
A12: As Of: 10/25/2026
A14: All numbers in $M unless otherwise indicated | B14: FQ1 2025A | C14: FQ2 2025A | D14: FQ3 2025A | E14: FQ4 2025A | F14: FY2025A | G14: FQ1 2026A | H14: FQ2 2026A | I14: FQ3 2026E | J14: FQ4 2026E | K14: FY2026E | L14: FQ1 2027E | M14: FQ2 2027E | N14: FQ3 2027E | O14: FQ4 2027E | P14: FY2027E | Q14: FQ1 2028E | R14: FQ2 2028E | S14: FQ3 2028E | T14: FQ4 2028E | U14: FY2028E | V14: FQ1 2029E | W14: FQ2 2029E | X14: FQ3 2029E | Y14: FQ4 2029E | Z14: FY2029E | AA14: FQ1 2030E | AB14: FQ2 2030E | AC14: FQ3 2030E | AD14: FQ4 2030E | AE14: FY2030E
A15: Number of Contributors Available | B15: 19 | C15: 19 | D15: 19 | E15: 19 | F15: 20 | G15: 20 | H15: 20 | I15: 20 of 20 | J15: 20 of 20 | K15: 20 of 20 | L15: 13 of 20 | M15: 13 of 20 | N15: 12 of 20 | O15: 12 of 20 | P15: 20 of 20 | Q15: 7 of 20 | R15: 7 of 20 | S15: 7 of 20 | T15: 7 of 20 | U15: 18 of 20 | V15: 5 of 20 | W15: 5 of 20 | X15: 5 of 20 | Y15: 5 of 20 | Z15: 14 of 20 | AA15: 5 of 20 | AB15: 5 of 20 | AC15: 5 of 20 | AD15: 5 of 20 | AE15: 14 of 20
A16: Wireless retail postpaid
A17: Gross adds - Wireless Retail postpaid - Consumer(K#) | B17: 2970 | C17: 3277 | D17: 3104 | E17: 4279 | F17: 13630 | G17: 3158.67 | H17: 3258.14 | I17: 3239.2 | J17: 3994.1 | K17: 13692.51 | L17: 3057.48 | M17: 3191.13 | N17: 3107.42 | O17: 4018.78 | P17: 13735.21 | Q17: 3012.58 | R17: 3150.28 | S17: 3032.12 | T17: 3955.39 | U17: 13893.94 | V17: 2864.74 | W17: 2940.05 | X17: 3000.28 | Y17: 3605.2 | Z17: 13845.22 | AA17: 2842.86 | AB17: 2913.12 | AC17: 2976.9 | AD17: 3573.7 | AE17: 13899.98
A18: Churn - Wireless Retail postpaid - Consumer(%) | B18: 1.13% | C18: 1.12% | D18: 1.12% | E18: 1.21% | F18: 1.14% | G18: 1.16% | H18: 1.10% | I18: 1.10% | J18: 1.13% | K18: 1.12% | L18: 1.12% | M18: 1.04% | N18: 1.07% | O18: 1.09% | P18: 1.10% | Q18: 1.12% | R18: 1.05% | S18: 1.08% | T18: 1.10% | U18: 1.11% | V18: 1.12% | W18: 1.05% | X18: 1.08% | Y18: 1.06% | Z18: 1.12% | AA18: 1.12% | AB18: 1.05% | AC18: 1.08% | AD18: 1.07% | AE18: 1.12%
A19: Disconnects - Wireless Retail postpaid - Consumer(K#) | B19: 3220.03 | C19: 3188.67 | D19: 3188.94 | E19: 3458.45 | F19: 13049 | G19: 3333.34 | H19: 3143.94 | I19: 3150.85 | J19: 3247.31 | K19: 12942.91 | L19: 3229.39 | M19: 3001.67 | N19: 3110.78 | O19: 3182.48 | P19: 12831.13 | Q19: 3261.44 | R19: 3055.38 | S19: 3142.25 | T19: 3214.87 | U19: 13101.1 | V19: 3227.43 | W19: 3017.71 | X19: 3099.85 | Y19: 3068.76 | Z19: 13265.78 | AA19: 3233.74 | AB19: 3024.39 | AC19: 3105.27 | AD19: 3074.33 | AE19: 13422.48
A20: Internal/Organic net adds - Wireless Retail postpaid - Consumer(K#) | B20: -253 | C20: 90 | D20: -74 | E20: 818 | F20: 581 | G20: -158.59 | H20: 140.93 | I20: 120.61 | J20: 772.96 | K20: 914.62 | L20: -168.07 | M20: 193.31 | N20: 0.17 | O20: 844.01 | P20: 1049.58 | Q20: -249.08 | R20: 95.54 | S20: -110.17 | T20: 744.35 | U20: 951.12 | V20: -362.69 | W20: -77.66 | X20: -99.57 | Y20: 536.44 | Z20: 796.91 | AA20: -390.88 | AB20: -111.27 | AC20: -128.37 | AD20: 499.37 | AE20: 721.95
A21: Acquired net adds - Wireless Retail postpaid - Consumer(K#) | B21: -11 | C21: 4 | D21: -4 | E21: -10 | F21: -21 | G21: -8.25 | H21: -52.5 | I21: - | J21: - | K21: -60.75 | L21: - | M21: - | N21: - | O21: - | P21: - | Q21: - | R21: - | S21: - | T21: - | U21: - | V21: - | W21: - | X21: - | Y21: - | Z21: - | AA21: - | AB21: - | AC21: - | AD21: - | AE21: -
A22: Net adds - Wireless Retail postpaid - Consumer(K#) | B22: -264 | C22: 94 | D22: -78 | E22: 808 | F22: 560 | G22: -161.59 | H22: 121.84 | I22: 120.61 | J22: 772.96 | K22: 894.37 | L22: -168.07 | M22: 193.31 | N22: 0.17 | O22: 844.01 | P22: 1049.58 | Q22: -249.08 | R22: 95.54 | S22: -110.17 | T22: 744.35 | U22: 951.12 | V22: -362.69 | W22: -77.66 | X22: -99.57 | Y22: 536.44 | Z22: 796.91 | AA22: -390.88 | AB22: -111.27 | AC22: -128.37 | AD22: 499.37 | AE22: 721.95
A23: Ending subscribers - Wireless Retail postpaid - Consumer(K#) | B23: 94854 | C23: 94948 | D23: 94870 | E23: 95678 | F23: 95678 | G23: 95516.41 | H23: 95638.25 | I23: 95799.42 | J23: 96572.37 | K23: 96572.37 | L23: 96333.88 | M23: 96527.19 | N23: 96527.36 | O23: 97371.37 | P23: 97621.95 | Q23: 96664.81 | R23: 96760.34 | S23: 96650.18 | T23: 97394.53 | U23: 98602.98 | V23: 96046.27 | W23: 95968.6 | X23: 95869.03 | Y23: 96405.47 | Z23: 99339.91 | AA23: 96014.59 | AB23: 95903.32 | AC23: 95774.96 | AD23: 96274.33 | AE23: 100061.86
A24: Average subscribers - Wireless Retail postpaid - Consumer(K#) | B24: 94986 | C24: 94901 | D24: 94909 | E24: 95274 | F24: 95398 | G24: 95597.21 | H24: 95577.33 | I24: 95739.12 | J24: 96185.9 | K24: 96037.59 | L24: 96417.92 | M24: 96430.54 | N24: 96527.27 | O24: 96949.36 | P24: 97074.64 | Q24: 96789.35 | R24: 96712.58 | S24: 96705.26 | T24: 97022.35 | U24: 98104.21 | V24: 96227.61 | W24: 96007.43 | X24: 95918.82 | Y24: 96137.25 | Z24: 98914.44 | AA24: 96210.03 | AB24: 95958.96 | AC24: 95839.14 | AD24: 96024.64 | AE24: 99674.94
A25: ARPU - Wireless Retail service postpaid - Consumer($) | B25: 50.43 | C25: 50.65 | D25: 50.57 | E25: 50.06 | F25: 50.23 | G25: 50.09 | H25: 49.7 | I25: 49.79 | J25: 49.81 | K25: 49.72 | L25: 49.48 | M25: 49.66 | N25: 49.81 | O25: 49.87 | P25: 49.47 | Q25: 49.17 | R25: 49.49 | S25: 49.65 | T25: 49.71 | U25: 64.34 | V25: 49.62 | W25: 50.05 | X25: 50.27 | Y25: 50.57 | Z25: 66.29 | AA25: 49.95 | AB25: 50.38 | AC25: 50.6 | AD25: 50.91 | AE25: 66.46
A26: Ending accounts - Wireless Retail postpaid - Consumer(K#) | B26: 32620 | C26: 32550 | D26: 32353 | E26: 32384 | F26: 32384 | G26: 32297.69 | H26: 32278.07 | I26: 32237.05 | J26: 32354.86 | K26: 32354.86 | L26: 32225.02 | M26: 32185.5 | N26: 32106.08 | O26: 32268.94 | P26: 32347.46 | Q26: 31995.66 | R26: 31969.91 | S26: 31832.88 | T26: 31941.22 | U26: 32347.69 | V26: 31526.3 | W26: 31428.26 | X26: 31290.52 | Y26: 31312.44 | Z26: 32313.14 | AA26: 31224 | AB26: 31116.34 | AC26: 30971.08 | AD26: 30981.74 | AE26: 32287.58
A27: Average accounts - Wireless Retail postpaid - Consumer(K#) | B27: 32707 | C27: 32585 | D27: 32451.5 | E27: 32368.5 | F27: 32589 | G27: 32343.08 | H27: 32287.88 | I27: 32268.41 | J27: 32295.95 | K27: 32359.46 | L27: 32279.29 | M27: 32205.26 | N27: 32145.79 | O27: 32187.52 | P27: 32345.22 | Q27: 32043.09 | R27: 31982.79 | S27: 31901.4 | T27: 31887.05 | U27: 32332.41 | V27: 31566.43 | W27: 31477.29 | X27: 31359.39 | Y27: 31301.47 | Z27: 32311.96 | AA27: 31268.23 | AB27: 31170.18 | AC27: 31043.71 | AD27: 30976.41 | AE27: 32292.54
A28: ARPA - Wireless Retail postpaid - Consumer($) | B28: 146.46 | C28: 147.5 | D28: 147.91 | E28: 147.36 | F28: 147.31 | G28: 148.35 | H28: 147.04 | I28: 147.68 | J28: 147.96 | K28: 147.63 | L28: 147.93 | M28: 148.52 | N28: 149.42 | O28: 149.65 | P28: 148.2 | Q28: 148.08 | R28: 148.64 | S28: 149.6 | T28: 149.55 | U28: 149.21 | V28: 149.62 | W28: 149.93 | X28: 151.39 | Y28: 151.71 | Z28: 150.54 | AA28: 151.05 | AB28: 151.37 | AC28: 152.86 | AD28: 153.18 | AE28: 151.44
A29: Consumer postpaid connections per account - Consumer($) | B29: 2.91 | C29: 2.92 | D29: 2.93 | E29: 2.95 | F29: 2.95 | G29: 2.96 | H29: 2.97 | I29: 2.97 | J29: 2.98 | K29: 2.98 | L29: 2.99 | M29: 3 | N29: 3.01 | O29: 3.02 | P29: 3.02 | Q29: 3.02 | R29: 3.03 | S29: 3.04 | T29: 3.05 | U29: 3.05 | V29: 3.05 | W29: 3.05 | X29: 3.06 | Y29: 3.08 | Z29: 3.08 | AA29: 3.08 | AB29: 3.08 | AC29: 3.09 | AD29: 3.11 | AE29: 3.1
A30: Postpaid service revenue - Consumer | B30: 14370.8 | C30: 14418.86 | D30: 14399.7 | E30: 14309.47 | F30: 57498.83 | G30: 14326.79 | H30: 14232.52 | I30: 14297.68 | J30: 14367.46 | K30: 57271.73 | L30: 14311.59 | M30: 14366.19 | N30: 14422.48 | O30: 14504.06 | P30: 57616.49 | Q30: 14275.36 | R30: 14356.52 | S30: 14400.32 | T30: 14464.79 | U30: 58143.39 | V30: 14321.41 | W30: 14410.47 | X30: 14460.21 | Y30: 14579.82 | Z30: 58834.16 | AA30: 14409.14 | AB30: 14495.51 | AC30: 14541.31 | AD30: 14657.3 | AE30: 59340.85
A32: Equipment revenue
A33: Wireless retail postpaid upgrade rate - Consumer(%) | B33: 3.00% | C33: 4.00% | D33: 3.60% | E33: 5.00% | F33: 15.57% | G33: 3.22% | H33: 3.04% | I33: 3.20% | J33: 4.58% | K33: 13.99% | L33: 3.32% | M33: 3.24% | N33: 3.18% | O33: 4.51% | P33: 14.07% | Q33: 3.30% | R33: 3.42% | S33: 3.17% | T33: 4.44% | U33: 14.02% | V33: 3.40% | W33: 3.30% | X33: 2.90% | Y33: 4.23% | Z33: 13.59% | AA33: 3.40% | AB33: 3.30% | AC33: 2.90% | AD33: 4.23% | AE33: 13.54%
A34: Total upgrade - Wireless Retail postpaid - Consumer(K#) | B34: 2849.58 | C34: 3796.04 | D34: 3416.72 | E34: 4763.7 | F34: 14826.04 | G34: 3081.64 | H34: 2906.49 | I34: 3059.97 | J34: 4391.15 | K34: 13420.9 | L34: 3198.33 | M34: 3121.41 | N34: 3072.68 | O34: 4360.07 | P34: 13629.71 | Q34: 3196.2 | R34: 3301.7 | S34: 3072.65 | T34: 4297.31 | U34: 13775.33 | V34: 3275.91 | W34: 3161.55 | X34: 2783.97 | Y34: 4066.47 | Z34: 13540.52 | AA34: 3275.14 | AB34: 3159.51 | AC34: 2782.09 | AD34: 4062.1 | AE34: 13578.89
A35: Gross adds - Wireless Retail postpaid - Consumer(K#) | B35: 2970 | C35: 3277 | D35: 3104 | E35: 4279 | F35: 13630 | G35: 3158.67 | H35: 3258.14 | I35: 3239.2 | J35: 3994.1 | K35: 13692.51 | L35: 3057.48 | M35: 3191.13 | N35: 3107.42 | O35: 4018.78 | P35: 13735.21 | Q35: 3012.58 | R35: 3150.28 | S35: 3032.12 | T35: 3955.39 | U35: 13893.94 | V35: 2864.74 | W35: 2940.05 | X35: 3000.28 | Y35: 3605.2 | Z35: 13845.22 | AA35: 2842.86 | AB35: 2913.12 | AC35: 2976.9 | AD35: 3573.7 | AE35: 13899.98
A36: Total devices - Wireless Retail postpaid - Consumer(K#) | B36: 5819.58 | C36: 7073.04 | D36: 6520.72 | E36: 9042.7 | F36: 28456.04 | G36: 6247.6 | H36: 6202.57 | I36: 6318.36 | J36: 8488.46 | K36: 27238.65 | L36: 6268.1 | M36: 6366.02 | N36: 6218.06 | O36: 8417.47 | P36: 27496.93 | Q36: 6208.78 | R36: 6451.98 | S36: 6104.77 | T36: 8252.71 | U36: 27652.71 | V36: 6140.64 | W36: 6101.6 | X36: 5784.25 | Y36: 7671.67 | Z36: 27337.43 | AA36: 6117.99 | AB36: 6072.63 | AC36: 5759 | AD36: 7635.8 | AE36: 27418.11
A37: Equipment revenue per device sold - Wireless Retail postpaid - Consumer($) | B37: 778.75 | C37: 759.08 | D37: 730.9 | E37: 786.49 | F37: 765.36 | G37: 781.08 | H37: 731.64 | I37: 747.71 | J37: 815.63 | K37: 772.88 | L37: 815.56 | M37: 788.24 | N37: 775.22 | O37: 855.22 | P37: 814.27 | Q37: 850.71 | R37: 817.41 | S37: 810.01 | T37: 909.33 | U37: 828.29 | V37: 866.94 | W37: 772.47 | X37: 831.3 | Y37: 918.52 | Z37: 822.23 | AA37: 885.41 | AB37: 789.35 | AC37: 849.21 | AD37: 938.92 | AE37: 834.28
A38: Wireless equipment revenue - Consumer | B38: 4532 | C38: 5369 | D38: 4766 | E38: 7112 | F38: 21779 | G38: 4824 | H38: 4178 | I38: 4778.46 | J38: 6978.87 | K38: 21481.4 | L38: 5045.64 | M38: 5066.07 | N38: 4824.4 | O38: 7190.74 | P38: 22419.81 | Q38: 5277.6 | R38: 5284.66 | S38: 4929.9 | T38: 7508.37 | U38: 23249.09 | V38: 5309 | W38: 4707.65 | X38: 4782.18 | Y38: 7030.12 | Z38: 23109.25 | AA38: 5398.91 | AB38: 4786.25 | AC38: 4859.58 | AD38: 7150.06 | AE38: 23550.12
A40: Wireless retail prepaid
A41: Gross adds - Wireless Retail prepaid - Consumer - Core (Ex. Safelink)(K#) | B41: 2105.53 | C41: 2101.68 | D41: 2177.52 | E41: 2248.02 | F41: 8632.75 | G41: 2104.68 | H41: 2153.23 | I41: 2210.87 | J41: 2280.12 | K41: 8743.07 | L41: 2115.87 | M41: 2164.65 | N41: 2228.63 | O41: 2297.46 | P41: 8751.96 | Q41: 2126.76 | R41: 2174.85 | S41: 2246.34 | T41: 2316.31 | U41: 8780.95 | V41: 2121.65 | W41: 2167.76 | X41: 2243.85 | Y41: 2315.31 | Z41: 8773.85 | AA41: 2068.12 | AB41: 2133.26 | AC41: 2242.11 | AD41: 2311.29 | AE41: 8728.59
A42: Churn Rate - Wireless Retail prepaid - Consumer - Core (Ex. Safelink)(%) | B42: 3.47% | C42: 3.60% | D42: 3.73% | E42: 3.73% | F42: 3.63% | G42: 3.45% | H42: 3.59% | I42: 3.72% | J42: 3.74% | K42: 3.61% | L42: 3.45% | M42: 3.58% | N42: 3.72% | O42: 3.75% | P42: 3.61% | Q42: 3.45% | R42: 3.58% | S42: 3.74% | T42: 3.76% | U42: 3.61% | V42: 3.43% | W42: 3.57% | X42: 3.73% | Y42: 3.76% | Z42: 3.60% | AA42: 3.42% | AB42: 3.55% | AC42: 3.71% | AD42: 3.74% | AE42: 3.59%
A43: Disconnects - Wireless Retail prepaid - Consumer - Core (Ex. Safelink)(K#) | B43: 1968.53 | C43: 2051.68 | D43: 2130.52 | E43: 2139.02 | F43: 8289.75 | G43: 1989.68 | H43: 2080.23 | I43: 2158.18 | J43: 2176.11 | K43: 8383.56 | L43: 2012.53 | M43: 2090.08 | N43: 2182.67 | O43: 2201.38 | P43: 8443.7 | Q43: 2041.78 | R43: 2129.19 | S43: 2223.54 | T43: 2243.26 | U43: 8573.4 | V43: 2053.65 | W43: 2140.22 | X43: 2236.16 | Y43: 2257.78 | Z43: 8619.06 | AA43: 2053.59 | AB43: 2135.64 | AC43: 2229.67 | AD43: 2251.72 | AE43: 8634.03
A44: Internal/Organic net adds - Wireless Retail prepaid - Consumer - Core (Ex. Safelink)(K#) | B44: 137 | C44: 50 | D44: 47 | E44: 109 | F44: 343 | G44: 115 | H44: 73 | I44: 42.05 | J44: 91.53 | K44: 321.58 | L44: 86.43 | M44: 59.88 | N44: 30.63 | O44: 77.15 | P44: 259.83 | Q44: 85.7 | R44: 46.05 | S44: 22.82 | T44: 73.69 | U44: 206.12 | V44: 67.99 | W44: 27.54 | X44: 7.68 | Y44: 57.54 | Z44: 153.66 | AA44: 14.54 | AB44: -2.38 | AC44: 12.44 | AD44: 47.76 | AE44: 120.59
A45: Acquired net adds - Wireless Retail prepaid - Consumer - Core (Ex. Safelink)(K#) | B45: -3 | C45: -10 | D45: -2 | E45: -2 | F45: -17 | G45: -5 | H45: -1 | I45: - | J45: - | K45: -6 | L45: - | M45: - | N45: - | O45: - | P45: - | Q45: - | R45: - | S45: - | T45: - | U45: - | V45: - | W45: - | X45: - | Y45: - | Z45: - | AA45: - | AB45: - | AC45: - | AD45: - | AE45: -
A46: Net adds - Wireless Retail prepaid - Consumer - Core (Ex. Safelink)(K#) | B46: 134 | C46: 40 | D46: 45 | E46: 107 | F46: 326 | G46: 110 | H46: 72 | I46: 43.41 | J46: 79.9 | K46: 269.26 | L46: 66.1 | M46: 45.94 | N46: 38.82 | O46: 73.08 | P46: 234.27 | Q46: 85.7 | R46: 46.05 | S46: 22.82 | T46: 73.69 | U46: 207.83 | V46: 67.99 | W46: 27.54 | X46: 7.68 | Y46: 57.54 | Z46: 167.81 | AA46: 14.54 | AB46: -2.38 | AC46: 12.44 | AD46: 47.76 | AE46: 144.58
A47: Ending subscribers - Wireless Retail prepaid - Consumer - Core (Ex. Safelink)(K#) | B47: 18977 | C47: 19017 | D47: 19062 | E47: 19169 | F47: 19169 | G47: 19279 | H47: 19351 | I47: 19358.36 | J47: 19438.26 | K47: 19438.26 | L47: 19494.78 | M47: 19540.72 | N47: 19579.54 | O47: 19652.61 | P47: 19672.52 | Q47: 19866.54 | R47: 19912.59 | S47: 19935.42 | T47: 20009.1 | U47: 19944.7 | V47: 20107.96 | W47: 20135.49 | X47: 20143.18 | Y47: 20200.71 | Z47: 20119.89 | AA47: 20215.25 | AB47: 20212.87 | AC47: 20225.31 | AD47: 20284.88 | AE47: 20246.39
A48: Average subscribers - Wireless Retail prepaid - Consumer - Core (Ex. Safelink)(K#) | B48: 18910 | C48: 18997 | D48: 19039.5 | E48: 19115.5 | F48: 19006 | G48: 19224 | H48: 19315 | I48: 19326.67 | J48: 19390.92 | K48: 19298.48 | L48: 19434.27 | M48: 19487.95 | N48: 19530.48 | O48: 19589.66 | P48: 19534.98 | Q48: 19743.84 | R48: 19805.48 | S48: 19840.21 | T48: 19894.37 | U48: 19798.68 | V48: 19935.78 | W48: 19978.31 | X48: 19996.39 | Y48: 20036.55 | Z48: 19969.14 | AA48: 20035.35 | AB48: 20036.25 | AC48: 20041.83 | AD48: 20085.53 | AE48: 20098.81
A49: ARPU - Wireless Retail prepaid - Consumer - Core (Ex. Safelink)($) | B49: 31.92 | C49: 32.56 | D49: 32.7 | E49: 32.9 | F49: 32.52 | G49: 33.31 | H49: 33.37 | I49: 33.19 | J49: 33.31 | K49: 33.26 | L49: 33.44 | M49: 33.56 | N49: 33.47 | O49: 33.58 | P49: 33.63 | Q49: 34.02 | R49: 34.08 | S49: 34.01 | T49: 34.13 | U49: 34.14 | V49: 34.46 | W49: 34.52 | X49: 34.44 | Y49: 34.63 | Z49: 34.58 | AA49: 34.86 | AB49: 34.92 | AC49: 34.84 | AD49: 35.03 | AE49: 34.98
A50: Revenue - Wireless Retail prepaid - Consumer - Core (Ex. Safelink) | B50: 1810.82 | C50: 1855.63 | D50: 1867.77 | E50: 1886.7 | F50: 7420.92 | G50: 1921.05 | H50: 1933.62 | I50: 1924.63 | J50: 1938.04 | K50: 7700.16 | L50: 1949.93 | M50: 1962.55 | N50: 1961.36 | O50: 1973.87 | P50: 7872.05 | Q50: 2015.06 | R50: 2024.98 | S50: 2024.52 | T50: 2037.26 | U50: 8118.75 | V50: 2061.4 | W50: 2069.43 | X50: 2066.46 | Y50: 2081.65 | Z50: 8291.41 | AA50: 2095.74 | AB50: 2099.46 | AC50: 2095.14 | AD50: 2110.7 | AE50: 8427.92
A52: Net adds - Wireless Retail prepaid - Consumer - Safelink(K#) | B52: -42.5 | C52: -28.5 | D52: -80.5 | E52: -87.5 | F52: -239 | G52: -35.38 | H52: -37.73 | I52: -64.75 | J52: -67.6 | K52: -205.45 | L52: -42.5 | M52: -42.5 | N52: -60 | O52: -60 | P52: -194.06 | Q52: -30 | R52: -30 | S52: -47.5 | T52: -47.5 | U52: -160.75 | V52: -12.5 | W52: -12.5 | X52: -12.5 | Y52: -12.5 | Z52: -118.8 | AA52: -10 | AB52: -10 | AC52: -10 | AD52: -10 | AE52: -88.87
A53: Ending subscribers - Wireless Retail prepaid - Consumer - Safelink(K#) | B53: 1253 | C53: 1224 | D53: 1144 | E53: 1056 | F53: 1056 | G53: 1020.12 | H53: 982.9 | I53: 918.15 | J53: 850.55 | K53: 850.55 | L53: 793 | M53: 750.5 | N53: 690.5 | O53: 630.5 | P53: 656.49 | Q53: 600.5 | R53: 570.5 | S53: 523 | T53: 475.5 | U53: 495.74 | V53: 520.5 | W53: 508 | X53: 495.5 | Y53: 483 | Z53: 402.86 | AA53: 473 | AB53: 463 | AC53: 453 | AD53: 443 | AE53: 313.99
A54: ARPU - Wireless Retail prepaid - Consumer - Safelink($) | B54: 10.84 | C54: 10.84 | D54: 10.84 | E54: 10.84 | F54: 11.06 | G54: 10.84 | H54: 10.84 | I54: 10.84 | J54: 10.84 | K54: 11.15 | L54: 10.84 | M54: 10.84 | N54: 10.84 | O54: 10.84 | P54: 11.2 | Q54: 10.84 | R54: 10.84 | S54: 10.84 | T54: 10.84 | U54: 11.23 | V54: - | W54: - | X54: - | Y54: - | Z54: - | AA54: - | AB54: - | AC54: - | AD54: - | AE54: -
A55: Revenue - Wireless Retail prepaid - Consumer - Safelink | B55: 41.43 | C55: 40.28 | D55: 38.51 | E55: 35.78 | F55: 156 | G55: 33 | H55: 57.08 | I55: 50 | J55: 50 | K55: 190.08 | L55: 50 | M55: 50 | N55: 50 | O55: 50 | P55: 200 | Q55: 50 | R55: 50 | S55: 50 | T55: 50 | U55: 200 | V55: - | W55: - | X55: - | Y55: - | Z55: - | AA55: - | AB55: - | AC55: - | AD55: - | AE55: -
A57: Gross adds - Wireless Retail prepaid - Consumer(K#) | B57: 2377.14 | C57: 2412.86 | D57: 2465.14 | E57: 2448.81 | F57: 9703.95 | G57: 2413.02 | H57: 2457.38 | I57: 2427.63 | J57: 2455.37 | K57: 9753.4 | L57: 2440.2 | M57: 2474.88 | N57: 2474.88 | O57: 2494.55 | P57: 9678.28 | Q57: 2334.89 | R57: 2378.94 | S57: 2383.4 | T57: 2418.55 | U57: 9710.5 | V57: 2236.75 | W57: 2372.78 | X57: 2291.15 | Y57: 2334.86 | Z57: 9784.12 | AA57: 2067.55 | AB57: 2276.68 | AC57: 2342.17 | AD57: 2383.74 | AE57: 9808.5
A58: Churn rate - Wireless Retail prepaid - Consumer(%) | B58: 3.74% | C58: 3.92% | D58: 3.99% | E58: 3.95% | F58: 3.80% | G58: 3.83% | H58: 3.97% | I58: 3.99% | J58: 3.98% | K58: 3.94% | L58: 3.87% | M58: 3.98% | N58: 4.00% | O58: 3.94% | P58: 3.88% | Q58: 3.67% | R58: 3.80% | S58: 3.83% | T58: 3.73% | U58: 3.87% | V58: 3.58% | W58: 3.87% | X58: 3.82% | Y58: 3.79% | Z58: 3.92% | AA58: 3.57% | AB58: 3.84% | AC58: 3.80% | AD58: 3.77% | AE58: 3.91%
A59: Disconnects - Wireless Retail prepaid - Consumer(K#) | B59: 2226.34 | C59: 2332.76 | D59: 2392.89 | E59: 2363.96 | F59: 9313.36 | G59: 2330.9 | H59: 2419.54 | I59: 2436.38 | J59: 2427.73 | K59: 9612.73 | L59: 2371.14 | M59: 2444.91 | N59: 2459.91 | O59: 2426.51 | P59: 9530.23 | Q59: 2267.4 | R59: 2356.4 | S59: 2377.87 | T59: 2315.73 | U59: 9555.85 | V59: 2191.97 | W59: 2372.25 | X59: 2339.26 | Y59: 2317.42 | Z59: 9687.07 | AA59: 2178.18 | AB59: 2334.85 | AC59: 2305.17 | AD59: 2293.94 | AE59: 9707.22
A60: Internal/Organic net adds - Wireless Retail prepaid - Consumer(K#) | B60: 94 | C60: 22 | D60: -34 | E60: 22 | F60: 104 | G60: 80.96 | H60: 35 | I60: -5.5 | J60: 27.77 | K60: 132.05 | L60: 68.67 | M60: 29.99 | N60: 16.55 | O60: 68.82 | P60: 148.1 | Q60: 66.56 | R60: 22.18 | S60: 7.25 | T60: 103.54 | U60: 149.11 | V60: 42.5 | W60: 0.5 | X60: -45.5 | Y60: 16.5 | Z60: 101.81 | AA60: -105 | AB60: -55 | AC60: 35 | AD60: 85 | AE60: 101.76
A61: Acquired net adds - Wireless Retail prepaid - Consumer(K#) | B61: -2 | C61: -11 | D61: -1 | E61: -3 | F61: -17 | G61: -1.33 | H61: -1 | I61: - | J61: - | K61: -2 | L61: - | M61: - | N61: - | O61: - | P61: - | Q61: - | R61: - | S61: - | T61: - | U61: - | V61: - | W61: - | X61: - | Y61: - | Z61: - | AA61: - | AB61: - | AC61: - | AD61: - | AE61: -
A62: Net adds - Wireless Retail prepaid - Consumer(K#) | B62: 92 | C62: 11 | D62: -35 | E62: 19 | F62: 87 | G62: 81.1 | H62: 37.22 | I62: -5.5 | J62: 27.77 | K62: 132.05 | L62: 68.67 | M62: 29.99 | N62: 16.55 | O62: 68.82 | P62: 148.1 | Q62: 66.56 | R62: 22.18 | S62: 7.25 | T62: 103.54 | U62: 149.11 | V62: 42.5 | W62: 0.5 | X62: -45.5 | Y62: 16.5 | Z62: 101.81 | AA62: -105 | AB62: -55 | AC62: 35 | AD62: 85 | AE62: 101.76
A63: Ending subscribers - Wireless Retail prepaid - Consumer(K#) | B63: 20230 | C63: 20241 | D63: 20206 | E63: 20225 | F63: 20225 | G63: 20305.96 | H63: 20343.32 | I63: 20329.28 | J63: 20357.05 | K63: 20357.05 | L63: 20454.44 | M63: 20484.43 | N63: 20500.98 | O63: 20569.8 | P63: 20505.15 | Q63: 20646.31 | R63: 20668.48 | S63: 20675.73 | T63: 20779.28 | U63: 20654.26 | V63: 20410.5 | W63: 20411 | X63: 20365.5 | Y63: 20382 | Z63: 20645.85 | AA63: 20277 | AB63: 20222 | AC63: 20257 | AD63: 20342 | AE63: 20747.61
A64: Average subscribers - Wireless Retail prepaid - Consumer(K#) | B64: 20184 | C64: 20235.5 | D64: 20223.5 | E64: 20215.5 | F64: 20181.5 | G64: 20265.48 | H64: 20324.64 | I64: 20332.03 | J64: 20343.16 | K64: 20297.96 | L64: 20420.1 | M64: 20469.43 | N64: 20492.71 | O64: 20535.39 | P64: 20433.03 | Q64: 20613.03 | R64: 20657.39 | S64: 20672.11 | T64: 20727.51 | U64: 20581.64 | V64: 20389.25 | W64: 20410.75 | X64: 20388.25 | Y64: 20373.75 | Z64: 20597.53 | AA64: 20329.5 | AB64: 20249.5 | AC64: 20239.5 | AD64: 20299.5 | AE64: 20682.98
A65: ARPU - Wireless Retail prepaid - Consumer($) | B65: 30.91 | C65: 31.55 | D65: 31.57 | E65: 31.82 | F65: 31.5 | G65: 31.8 | H65: 31.84 | I65: 31.77 | J65: 31.98 | K65: 31.72 | L65: 31.91 | M65: 32.09 | N65: 31.97 | O65: 32.2 | P65: 31.9 | Q65: 32.47 | R65: 32.67 | S65: 32.48 | T65: 32.76 | U65: 32.22 | V65: 33.25 | W65: 33.33 | X65: 33.05 | Y65: 33.36 | Z65: 32.66 | AA65: 33.5 | AB65: 33.59 | AC65: 33.3 | AD65: 33.62 | AE65: 32.97
A66: Wireless Retail prepaid revenue - Consumer | B66: 1871.62 | C66: 1915.05 | D66: 1915.63 | E66: 1929.75 | F66: 7632.05 | G66: 1932.63 | H66: 1940.42 | I66: 1937.56 | J66: 1951.31 | K66: 7761.93 | L66: 1950.57 | M66: 1963.42 | N66: 1957.51 | O66: 1973.5 | P66: 7835.63 | Q66: 1988.41 | R66: 2000.22 | S66: 1987.16 | T66: 2004.21 | U66: 7926.51 | V66: 2022.43 | W66: 2026.27 | X66: 2005.7 | Y66: 2021.22 | Z66: 8020.79 | AA66: 2024.98 | AB66: 2023.62 | AC66: 2003.63 | AD66: 2023.07 | AE66: 8089.73
A68: Wholesale/other revenue - Consumer | B68: 976.84 | C68: 1053.18 | D68: 1136.76 | E68: 1148.89 | F68: 4193.49 | G68: 1115.48 | H68: 1167.26 | I68: 1191.76 | J68: 1212.71 | K68: 4615.54 | L68: 1184.01 | M68: 1217.71 | N68: 1264.11 | O68: 1276.97 | P68: 5003.09 | Q68: 1270.81 | R68: 1305.07 | S68: 1357.22 | T68: 1363.87 | U68: 5384.25 | V68: 1274.47 | W68: 1300.37 | X68: 1338.94 | Y68: 1334.69 | Z68: 5603.92 | AA68: 1300.91 | AB68: 1326.9 | AC68: 1366.09 | AD68: 1360.94 | AE68: 5837.36
A70: Average subscribers - Wireless Retail prepaid - Consumer(K#) | B70: 20184 | C70: 20235.5 | D70: 20223.5 | E70: 20215.5 | F70: 20181.5 | G70: 20265.48 | H70: 20324.64 | I70: 20332.03 | J70: 20343.16 | K70: 20297.96 | L70: 20420.1 | M70: 20469.43 | N70: 20492.71 | O70: 20535.39 | P70: 20433.03 | Q70: 20613.03 | R70: 20657.39 | S70: 20672.11 | T70: 20727.51 | U70: 20581.64 | V70: 20389.25 | W70: 20410.75 | X70: 20388.25 | Y70: 20373.75 | Z70: 20597.53 | AA70: 20329.5 | AB70: 20249.5 | AC70: 20239.5 | AD70: 20299.5 | AE70: 20682.98
A71: ARPU - Wireless Retail prepaid & Wholesale - Consumer($) | B71: 46.71 | C71: 48.6 | D71: 50.13 | E71: 50.51 | F71: 49.07 | G71: 48.75 | H71: 50.27 | I71: 51.01 | J71: 51.62 | K71: 50.04 | L71: 49.75 | M71: 51.02 | N71: 52.11 | O71: 52.55 | P71: 51.79 | Q71: 51.12 | R71: 52.64 | S71: 53.92 | T71: 54.27 | U71: 53.4 | V71: 52.59 | W71: 53.85 | X71: 54.68 | Y71: 54.62 | Z71: 55 | AA71: 53.33 | AB71: 54.7 | AC71: 55.53 | AD71: 55.35 | AE71: 56.18
A72: Prepaid service revenue & Wholesale - Consumer | B72: 2828.2 | C72: 2950.14 | D72: 3041.3 | E72: 3063.53 | F72: 11883.17 | G72: 2997.53 | H72: 3064.3 | I72: 3092.53 | J72: 3125.68 | K72: 12180.81 | L72: 3088.25 | M72: 3140.26 | N72: 3183.48 | O72: 3200.28 | P72: 12666.89 | Q72: 3204.72 | R72: 3268.5 | S72: 3325.25 | T72: 3351.53 | U72: 13189.41 | V72: 3285.33 | W72: 3317.67 | X72: 3346.89 | Y72: 3357.8 | Z72: 13567.43 | AA72: 3320.19 | AB72: 3349.03 | AC72: 3379.21 | AD72: 3391.85 | AE72: 13895.35
A74: Total wireless retail
A75: Beginning subscribers - Consumer(K#) | B75: 115256 | C75: 115084 | D75: 115189 | E75: 115076 | F75: 115256 | G75: 115903 | H75: 115789.65 | I75: 115976.8 | J75: 116103.33 | K75: 115811.63 | L75: 116696.92 | M75: 116540.49 | N75: 116743.4 | O75: 116744.2 | P75: 116822.23 | Q75: 117475.16 | R75: 117276.77 | S75: 117388.79 | T75: 117277.48 | U75: 118033.68 | V75: 116892.26 | W75: 116559.93 | X75: 116486.63 | Y75: 116362.37 | Z75: 118883.79 | AA75: 116894.79 | AB75: 116483.46 | AC75: 116357.01 | AD75: 116230.44 | AE75: 119768.04
A76: Gross adds - Wireless Retail - Consumer(K#) | B76: 5265.51 | C76: 5569.47 | D76: 5452.9 | E76: 6660.67 | F76: 23014.96 | G76: 5288.54 | H76: 5459.07 | I76: 5401.77 | J76: 6245.2 | K76: 22402.48 | L76: 5430.71 | M76: 5646.4 | N76: 5510.53 | O76: 6459.08 | P76: 22466 | Q76: 5317.89 | R76: 5490.63 | S76: 5362.28 | T76: 6343.85 | U76: 22529.26 | V76: 5113.15 | W76: 5248.23 | X76: 5260.02 | Y76: 5941.25 | Z76: 22263.05 | AA76: 5030.43 | AB76: 5184.91 | AC76: 5249.5 | AD76: 5921.6 | AE76: 22366.43
A77: Churn - Wireless Retail - Consumer(%) | B77: 1.57% | C77: 1.58% | D77: 1.61% | E77: 1.68% | F77: 1.61% | G77: 1.55% | H77: 1.51% | I77: 1.50% | J77: 1.53% | K77: 1.52% | L77: 1.50% | M77: 1.45% | N77: 1.46% | O77: 1.47% | P77: 1.50% | Q77: 1.57% | R77: 1.54% | S77: 1.55% | T77: 1.56% | U77: 1.59% | V77: 1.56% | W77: 1.52% | X77: 1.54% | Y77: 1.54% | Z77: 1.59% | AA77: 1.56% | AB77: 1.52% | AC77: 1.54% | AD77: 1.55% | AE77: 1.59%
A78: Disconnects - Wireless Retail - Consumer(K#) | B78: 5424.51 | C78: 5457.47 | D78: 5560.9 | E78: 5820.67 | F78: 22263.55 | G78: 5400.66 | H78: 5257.27 | I78: 5233.62 | J78: 5332.55 | K78: 21227.01 | L78: 5241.85 | M78: 5061.39 | N78: 5113.81 | O78: 5161.16 | P78: 21116.77 | Q78: 5524.26 | R78: 5388.2 | S78: 5455.11 | T78: 5499.3 | U78: 22503.87 | V78: 5446.27 | W78: 5321.16 | X78: 5385.44 | Y78: 5404.45 | Z78: 22622.11 | AA78: 5443.9 | AB78: 5311.82 | AC78: 5376.92 | AD78: 5399.35 | AE78: 22773.93
A79: Internal/Organic net adds - Wireless Retail - Consumer(K#) | B79: -159 | C79: 112 | D79: -108 | E79: 840 | F79: 685 | G79: -100.44 | H79: 177.35 | I79: 121 | J79: 761.51 | K79: 1001.43 | L79: -146.4 | M79: 231.95 | N79: -30.77 | O79: 843.08 | P79: 1147.55 | Q79: -198.39 | R79: 112.02 | S79: -111.3 | T79: 800.99 | U79: 1044.91 | V79: -332.33 | W79: -73.3 | X79: -124.26 | Y79: 532.42 | Z79: 884.26 | AA79: -411.33 | AB79: -126.45 | AC79: -126.58 | AD79: 517.82 | AE79: 819.29
A80: Acquired net adds - Wireless Retail - Consumer(K#) | B80: -13 | C80: -7 | D80: -5 | E80: -13 | F80: -38 | G80: -8 | H80: -43 | I80: - | J80: - | K80: -51 | L80: - | M80: - | N80: - | O80: - | P80: - | Q80: - | R80: - | S80: - | T80: - | U80: - | V80: - | W80: - | X80: - | Y80: - | Z80: - | AA80: - | AB80: - | AC80: - | AD80: - | AE80: -
A81: Net adds - Wireless Retail - Consumer(K#) | B81: -172 | C81: 105 | D81: -113 | E81: 827 | F81: 647 | G81: -114.31 | H81: 155.43 | I81: 127.99 | J81: 718.9 | K81: 929.46 | L81: -156.43 | M81: 202.91 | N81: 0.8 | O81: 763.41 | P81: 1069.38 | Q81: -198.39 | R81: 112.02 | S81: -111.3 | T81: 800.99 | U81: 1044.91 | V81: -332.33 | W81: -73.3 | X81: -124.26 | Y81: 532.42 | Z81: 884.26 | AA81: -411.33 | AB81: -126.45 | AC81: -126.58 | AD81: 517.82 | AE81: 819.29
A82: Ending subscribers - Consumer(K#) | B82: 115084 | C82: 115189 | D82: 115076 | E82: 115903 | F82: 115903 | G82: 115784.15 | H82: 115932.88 | I82: 116103.33 | J82: 116822.23 | K82: 116822.24 | L82: 116540.49 | M82: 116743.4 | N82: 116744.2 | O82: 117507.61 | P82: 117891.61 | Q82: 117276.77 | R82: 117388.79 | S82: 117277.48 | T82: 118078.47 | U82: 119078.59 | V82: 116559.93 | W82: 116486.63 | X82: 116362.37 | Y82: 116894.79 | Z82: 119768.04 | AA82: 116483.46 | AB82: 116357.01 | AC82: 116230.44 | AD82: 116748.26 | AE82: 120587.33
A83: Average subscribers - Consumer(K#) | B83: 115170 | C83: 115136.5 | D83: 115132.5 | E83: 115489.5 | F83: 115579.5 | G83: 115841.55 | H83: 115858.51 | I83: 116039.34 | J83: 116462.78 | K83: 116242.85 | L83: 116618.71 | M83: 116641.95 | N83: 116743.8 | O83: 117125.91 | P83: 117302.44 | Q83: 117375.96 | R83: 117332.78 | S83: 117333.14 | T83: 117677.98 | U83: 118497.42 | V83: 116726.09 | W83: 116523.28 | X83: 116424.5 | Y83: 116628.58 | Z83: 119253.7 | AA83: 116689.13 | AB83: 116420.24 | AC83: 116293.73 | AD83: 116489.35 | AE83: 120094.12
A84: ARPA - Wireless Retail - Consumer($) | B84: 49.78 | C84: 50.29 | D84: 50.5 | E84: 50.14 | F84: 50.02 | G84: 49.35 | H84: 49.77 | I84: 49.98 | J84: 50.09 | K84: 49.72 | L84: 49.66 | M84: 49.97 | N84: 50.21 | O84: 50.3 | P84: 49.9 | Q84: 49.65 | R84: 50.08 | S84: 50.36 | T84: 50.47 | U84: 50.07 | V84: 50.29 | W84: 50.72 | X84: 50.99 | Y84: 51.28 | Z84: 50.44 | AA84: 50.66 | AB84: 51.1 | AC84: 51.38 | AD84: 51.66 | AE84: 50.62
A85: Wireless service revenue - Consumer | B85: 17199 | C85: 17369 | D85: 17441 | E85: 17373 | F85: 69382 | G85: 17151.76 | H85: 17296.89 | I85: 17390.38 | J85: 17493.12 | K85: 69336.43 | L85: 17398.87 | M85: 17504.36 | N85: 17602.83 | O85: 17699.97 | P85: 70276.33 | Q85: 17480.09 | R85: 17625.02 | S85: 17725.56 | T85: 17816.32 | U85: 71311.93 | V85: 17606.75 | W85: 17728.14 | X85: 17807.1 | Y85: 17937.62 | Z85: 72361.27 | AA85: 17729.32 | AB85: 17844.54 | AC85: 17920.51 | AD85: 18049.14 | AE85: 73182.59
A87: Wireline
A88: FiOS
A89: Acquired Net adds - FiOS Video - Consumer(K#) | B89: - | C89: - | D89: - | E89: - | F89: - | G89: 110 | H89: - | I89: - | J89: - | K89: 110 | L89: - | M89: - | N89: - | O89: - | P89: - | Q89: - | R89: - | S89: - | T89: - | U89: - | V89: - | W89: - | X89: - | Y89: - | Z89: - | AA89: - | AB89: - | AC89: - | AD89: - | AE89: -
A90: Internal/organic Net adds - FiOS Video - Consumer(K#) | B90: -58 | C90: -62 | D90: -70 | E90: -53 | F90: -243 | G90: -65.05 | H90: -66.95 | I90: -73.25 | J90: -60.17 | K90: -265.43 | L90: -63.67 | M90: -65.48 | N90: -71.59 | O90: -58.92 | P90: -259.65 | Q90: -62.36 | R90: -64.08 | S90: -70.01 | T90: -57.72 | U90: -254.17 | V90: -47.24 | W90: -50.5 | X90: -57.02 | Y90: -43.17 | Z90: -197.93 | AA90: -44.88 | AB90: -47.97 | AC90: -54.16 | AD90: -41.01 | AE90: -188.03
A91: Net adds - FiOS Video - Consumer(K#) | B91: -58 | C91: -62 | D91: -70 | E91: -53 | F91: -243 | G91: -29.19 | H91: -66.78 | I91: -69 | J91: -59.85 | K91: -215.31 | L91: -63.47 | M91: -68.56 | N91: -68.03 | O91: -57.83 | P91: -248.03 | Q91: -63.94 | R91: -67.92 | S91: -68.24 | T91: -56.36 | U91: -242.78 | V91: -56.92 | W91: -61.58 | X91: -58.56 | Y91: -48.3 | Z91: -226.71 | AA91: -53.45 | AB91: -57.53 | AC91: -55.25 | AD91: -45.52 | AE91: -222.27
A92: Internal/organic Net adds - FiOS Internet - Consumer(K#) | B92: 41 | C92: 28 | D92: 59 | E92: 65 | F92: 193 | G92: 127.17 | H92: 151.48 | I92: 155.86 | J92: 153.14 | K92: 587.65 | L92: 146.72 | M92: 145.77 | N92: 160.81 | O92: 155.57 | P92: 633.94 | Q92: 147.89 | R92: 156.22 | S92: 158.88 | T92: 148.75 | U92: 643.12 | V92: 129.88 | W92: 135.07 | X92: 121.43 | Y92: 119.5 | Z92: 588.56 | AA92: 116 | AB92: 128.82 | AC92: 116.57 | AD92: 116.25 | AE92: 539.84
A93: Acquired Net adds - FiOS Internet - Consumer(K#) | B93: 401 | C93: - | D93: - | E93: - | F93: 401 | G93: 2752.68 | H93: 0.98 | I93: - | J93: - | K93: 2753.1 | L93: - | M93: - | N93: - | O93: - | P93: - | Q93: - | R93: - | S93: - | T93: - | U93: - | V93: - | W93: - | X93: - | Y93: - | Z93: - | AA93: - | AB93: - | AC93: - | AD93: - | AE93: -
A94: Net adds - FiOS Internet - Consumer(K#) | B94: 41 | C94: 28 | D94: 59 | E94: 65 | F94: 193 | G94: 2255.55 | H94: 138.97 | I94: 136.84 | J94: 137 | K94: 2685.76 | L94: 147.35 | M94: 145.09 | N94: 161.81 | O94: 158.25 | P94: 585.69 | Q94: 147.75 | R94: 152.02 | S94: 159.66 | T94: 153.16 | U94: 590.79 | V94: 134.76 | W94: 135.84 | X94: 133.52 | Y94: 133.55 | Z94: 541.17 | AA94: 124.65 | AB94: 131.06 | AC94: 128.99 | AD94: 129.96 | AE94: 502.61
A95: Internal/organic Net adds - FiOS Digital voice - Consumer(K#) | B95: -70 | C95: -70 | D95: -70 | E95: -70 | F95: -280 | G95: -56 | H95: -56 | I95: -56 | J95: -56 | K95: -224 | L95: -44.8 | M95: -44.8 | N95: -44.8 | O95: -44.8 | P95: -179.2 | Q95: -35.84 | R95: -35.84 | S95: -35.84 | T95: -35.84 | U95: -143.36 | V95: -28.67 | W95: -28.67 | X95: -28.67 | Y95: -28.67 | Z95: -114.69 | AA95: -22.94 | AB95: -22.94 | AC95: -22.94 | AD95: -22.94 | AE95: -91.75
A96: Acquired Net adds - FiOS Digital voice - Consumer(K#) | B96: - | C96: - | D96: - | E96: - | F96: - | G96: 75 | H96: - | I96: - | J96: - | K96: 75 | L96: - | M96: - | N96: - | O96: - | P96: - | Q96: - | R96: - | S96: - | T96: - | U96: - | V96: - | W96: - | X96: - | Y96: - | Z96: - | AA96: - | AB96: - | AC96: - | AD96: - | AE96: -
A97: Net adds - FiOS Digital voice - Consumer(K#) | B97: -64.14 | C97: -61.08 | D97: -70 | E97: -61.15 | F97: -280 | G97: 32.12 | H97: -67.92 | I97: -68.65 | J97: -69.81 | K97: -174.26 | L97: -64.11 | M97: -64.49 | N97: -64.31 | O97: -65.21 | P97: -261.26 | Q97: -71.79 | R97: -70.08 | S97: -72.53 | T97: -72.96 | U97: -264.21 | V97: -74.58 | W97: -72.35 | X97: -75.5 | Y97: -75.96 | Z97: -268.82 | AA97: -76.7 | AB97: -74.11 | AC97: -77.02 | AD97: -32.9 | AE97: -212.27
A98: Internal/organic Net adds - FiOS Total digital - Consumer(K#) | B98: -72.47 | C98: -89.13 | D98: -65.8 | E98: -42.47 | F98: -269.88 | G98: 16.43 | H98: 38.65 | I98: 29.33 | J98: 50.37 | K98: 67.65 | L98: 39.73 | M98: 34.89 | N98: 40.67 | O98: 55.15 | P98: 170.44 | Q98: 35.43 | R98: 56 | S98: 25.14 | T98: 39.72 | U98: 169.26 | V98: 43.09 | W98: 63.83 | X98: 33.31 | Y98: 47.16 | Z98: 175.41 | AA98: 49.18 | AB98: 70.09 | AC98: 39.9 | AD98: 53.05 | AE98: 129.62
A99: Acquired Internal/organic Net adds - FiOS Total digital - Consumer(K#) | B99: - | C99: - | D99: - | E99: - | F99: - | G99: 2830.59 | H99: - | I99: - | J99: - | K99: 2830.59 | L99: - | M99: - | N99: - | O99: - | P99: - | Q99: - | R99: - | S99: - | T99: - | U99: - | V99: - | W99: - | X99: - | Y99: - | Z99: - | AA99: - | AB99: - | AC99: - | AD99: - | AE99: -
A100: Net adds - FiOS Total digital - Consumer(K#) | B100: -29.94 | C100: -81.98 | D100: -58.68 | E100: -32.76 | F100: -330 | G100: 2591.16 | H100: 25.61 | I100: 27.41 | J100: 31.48 | K100: 2675.67 | L100: 17.73 | M100: 10.81 | N100: 27.11 | O100: 30.92 | P100: 111.76 | Q100: 12.04 | R100: 14.04 | S100: 20.84 | T100: 24.5 | U100: 146.47 | V100: 3.26 | W100: 1.91 | X100: -0.53 | Y100: 9.28 | Z100: 100.48 | AA100: -5.49 | AB100: -0.59 | AC100: -3.27 | AD100: 7.05 | AE100: 47.57
A102: FiOS Video subscribers - Consumer(K#) | B102: 2626 | C102: 2564 | D102: 2494 | E102: 2441 | F102: 2441 | G102: 2445.86 | H102: 2388.61 | I102: 2357.99 | J102: 2305.05 | K102: 2305.05 | L102: 2221.38 | M102: 2152.82 | N102: 2084.79 | O102: 2026.96 | P102: 2060.06 | Q102: 1997.44 | R102: 1929.51 | S102: 1861.28 | T102: 1804.92 | U102: 1823.93 | V102: 1842.95 | W102: 1781.37 | X102: 1722.81 | Y102: 1674.51 | Z102: 1643.39 | AA102: 1621.06 | AB102: 1563.53 | AC102: 1508.28 | AD102: 1462.76 | AE102: 1434.01
A103: FiOS Internet subscribers - Consumer(K#) | B103: 7176 | C103: 7204 | D103: 7263 | E103: 7328 | F103: 7328 | G103: 10290.96 | H103: 10441.7 | I103: 10559.14 | J103: 10707.98 | K103: 10707.98 | L103: 10964.14 | M103: 11109.23 | N103: 11271.04 | O103: 11429.29 | P103: 11311.81 | Q103: 11438.29 | R103: 11590.31 | S103: 11749.97 | T103: 11903.13 | U103: 11916.1 | V103: 11942.93 | W103: 12078.77 | X103: 12212.29 | Y103: 12345.84 | Z103: 12444.28 | AA103: 12470.49 | AB103: 12601.55 | AC103: 12730.54 | AD103: 12860.5 | AE103: 12957.84
A104: FiOS Digital voice subscribers - Consumer(K#) | B104: 2230.06 | C104: 2168.98 | D104: 2105.26 | E104: 2044.12 | F104: 2044.12 | G104: 2067.37 | H104: 1999.45 | I104: 1930.8 | J104: 1860.99 | K104: 1860.99 | L104: 1836.75 | M104: 1772.26 | N104: 1707.95 | O104: 1642.74 | P104: 1599.73 | Q104: 1471.85 | R104: 1401.77 | S104: 1329.24 | T104: 1256.27 | U104: 1335.51 | V104: 1245.11 | W104: 1172.77 | X104: 1097.27 | Y104: 1021.3 | Z104: 1105.19 | AA104: 944.61 | AB104: 870.49 | AC104: 793.48 | AD104: 1143.46 | AE104: 992.33
A105: FiOS Total digital subscribers - Consumer(K#) | B105: 12582.46 | C105: 12495.68 | D105: 12432.24 | E105: 12392 | F105: 12392 | G105: 15042.95 | H105: 15068.56 | I105: 15095.97 | J105: 15127.45 | K105: 15127.45 | L105: 15295.29 | M105: 15306.1 | N105: 15333.21 | O105: 15364.13 | P105: 15239.22 | Q105: 14940.18 | R105: 14954.21 | S105: 14975.05 | T105: 14999.55 | U105: 15109.79 | V105: 15030.99 | W105: 15032.9 | X105: 15032.36 | Y105: 15041.65 | Z105: 15223.73 | AA105: 15036.15 | AB105: 15035.56 | AC105: 15032.29 | AD105: 15039.35 | AE105: 15264.51
A106: FiOS Average Total digital - Consumer(K#) | B106: 12598.07 | C106: 12539.07 | D106: 12463.96 | E106: 12412.12 | F106: 12500.09 | G106: 13747.36 | H106: 15055.75 | I106: 15082.27 | J106: 15111.71 | K106: 14028.87 | L106: 15286.42 | M106: 15300.7 | N106: 15319.66 | O106: 15348.67 | P106: 15183.58 | Q106: 14934.16 | R106: 14947.2 | S106: 14964.63 | T106: 14987.3 | U106: 15045.98 | V106: 15029.36 | W106: 15031.94 | X106: 15032.63 | Y106: 15037 | Z106: 15181 | AA106: 15038.9 | AB106: 15035.86 | AC106: 15033.93 | AD106: 15035.82 | AE106: 15244.45
A107: FiOS ARPU Total digital - Consumer($) | B107: 77.82 | C107: 78.97 | D107: 79.74 | E107: 79.59 | F107: 78.36 | G107: 80.57 | H107: 79.95 | I107: 81.92 | J107: 82.13 | K107: 81.92 | L107: 82.17 | M107: 84.53 | N107: 83.06 | O107: 83.49 | P107: 83.48 | Q107: 90.01 | R107: 94.42 | S107: 91.19 | T107: 91.77 | U107: 89.74 | V107: 90.2 | W107: 96.39 | X107: 90.85 | Y107: 91.62 | Z107: 90.82 | AA107: 92.19 | AB107: 99.34 | AC107: 92.89 | AD107: 93.57 | AE107: 92.98
A108: FiOS Total digital revenue - Consumer | B108: 2896 | C108: 2924 | D108: 2937 | E108: 2921 | F108: 11678 | G108: 3249.42 | H108: 3540.64 | I108: 3610.55 | J108: 3646.33 | K108: 13648.6 | L108: 3630.55 | M108: 3741.5 | N108: 3690.29 | O108: 3710.84 | P108: 14764.48 | Q108: 3816.56 | R108: 4003.03 | S108: 3883.42 | T108: 3879 | U108: 15560.79 | V108: 4071.38 | W108: 4358.72 | X108: 4100.96 | Y108: 4137.91 | Z108: 16200.47 | AA108: 4163.93 | AB108: 4497.1 | AC108: 4191.72 | AD108: 4222.82 | AE108: 16573.59
A110: Broadband
A111: Internal/Organic net adds - DSL - Consumer(K#) | B111: -10 | C111: -11 | D111: -12 | E111: -9 | F111: -42 | G111: -13 | H111: -35 | I111: -35 | J111: -35 | K111: -118 | L111: -33 | M111: -32.5 | N111: -32.5 | O111: -32.5 | P111: -130.5 | Q111: -33 | R111: -30 | S111: -30 | T111: -30 | U111: -123 | V111: -33 | W111: -27.5 | X111: -27.5 | Y111: -27.5 | Z111: -115.5 | AA111: -33 | AB111: -25 | AC111: -25 | AD111: -25 | AE111: -108
A112: Acquired net adds - DSL - Consumer(K#) | B112: -1 | C112: 1 | D112: - | E112: - | F112: - | G112: 400 | H112: - | I112: - | J112: - | K112: 400 | L112: - | M112: - | N112: - | O112: - | P112: - | Q112: - | R112: - | S112: - | T112: - | U112: - | V112: - | W112: - | X112: - | Y112: - | Z112: - | AA112: - | AB112: - | AC112: - | AD112: - | AE112: -
A113: Net adds - DSL - Consumer(K#) | B113: -11 | C113: -10 | D113: -12 | E113: -9 | F113: -42 | G113: 85.2 | H113: -25.32 | I113: -26.96 | J113: -25.27 | K113: 86.91 | L113: -22.84 | M113: -22.1 | N113: -18.89 | O113: -18.02 | P113: -91.57 | Q113: -21.71 | R113: -21.04 | S113: -13.48 | T113: -13.7 | U113: -52.74 | V113: -15.52 | W113: -13.4 | X113: -13.29 | Y113: -13.13 | Z113: -40.78 | AA113: -14 | AB113: -4.5 | AC113: -4.5 | AD113: -3 | AE113: -18.15
A114: DSL subscribers - Consumer(K#) | B114: 154 | C114: 144 | D114: 132 | E114: 123 | F114: 123 | G114: 277.59 | H114: 254.33 | I114: 229.41 | J114: 205.93 | K114: 205.93 | L114: 178.89 | M114: 158.59 | N114: 138.66 | O114: 119.45 | P114: 114.01 | Q114: 110.44 | R114: 89.4 | S114: 85.02 | T114: 95.38 | U114: 68.4 | V114: 79.87 | W114: 66.46 | X114: 53.17 | Y114: 40.05 | Z114: 30.42 | AA114: 26.05 | AB114: 33.07 | AC114: 28.57 | AD114: 49.14 | AE114: 18.85
...
